{
  "type": "Feature",
  "properties": {
    "gn:admin1_code":"7.0",
    "gn:asciiname":"Moroto",
    "gn:country_code":"BO",
    "gn:dem":3202,
    "gn:feature_class":"P",
    "gn:feature_code":"PPL",
    "gn:name":"Moroto",
    "gn:population":0,
    "gn:timezone":"America/La_Paz",
    "iso:country":"BO",
    "name:und_x_variant":[
        "Morota",
        "Moroto"
    ],
    "wof:name":"Moroto",
    "wof:placetype":"locality"
},
  "geometry": {"coordinates":[-65.5177,-18.72296],"type":"Point"}
}