{
  "type": "Feature",
  "properties": {
    "gn:admin1_code":"7.0",
    "gn:asciiname":"Muyu Tinco",
    "gn:country_code":"BO",
    "gn:dem":3755,
    "gn:feature_class":"P",
    "gn:feature_code":"PPL",
    "gn:name":"Muyu Tinco",
    "gn:population":0,
    "gn:timezone":"America/La_Paz",
    "iso:country":"BO",
    "wof:name":"Muyu Tinco",
    "wof:placetype":"locality"
},
  "geometry": {"coordinates":[-67.22225999999999,-21.33941],"type":"Point"}
}