{
  "type": "Feature",
  "properties": {
    "gn:admin1_code":"8.0",
    "gn:asciiname":"Motacucito",
    "gn:country_code":"BO",
    "gn:dem":375,
    "gn:feature_class":"P",
    "gn:feature_code":"PPL",
    "gn:name":"Motacucito",
    "gn:population":0,
    "gn:timezone":"America/La_Paz",
    "iso:country":"BO",
    "wof:name":"Motacucito",
    "wof:placetype":"locality"
},
  "geometry": {"coordinates":[-60.03333000000001,-18.16667],"type":"Point"}
}