{
  "type": "Feature",
  "properties": {
    "gn:admin1_code":"8.0",
    "gn:asciiname":"La Suerte",
    "gn:country_code":"BO",
    "gn:dem":233,
    "gn:feature_class":"P",
    "gn:feature_code":"PPL",
    "gn:name":"La Suerte",
    "gn:population":0,
    "gn:timezone":"America/La_Paz",
    "iso:country":"BO",
    "wof:name":"La Suerte",
    "wof:placetype":"locality"
},
  "geometry": {"coordinates":[-61.71666999999999,-14.76667],"type":"Point"}
}