{
  "type": "Feature",
  "properties": {
    "gn:admin1_code":"5.0",
    "gn:asciiname":"Rumeroma",
    "gn:country_code":"BO",
    "gn:dem":3926,
    "gn:feature_class":"P",
    "gn:feature_code":"PPL",
    "gn:name":"Rumeroma",
    "gn:population":0,
    "gn:timezone":"America/La_Paz",
    "iso:country":"BO",
    "name:und_x_variant":[
        "Estancia Romeruma",
        "Rumeroma"
    ],
    "wof:name":"Rumeroma",
    "wof:placetype":"locality"
},
  "geometry": {"coordinates":[-68.03128000000001,-18.11607],"type":"Point"}
}