{
  "type": "Feature",
  "properties": {
    "gn:admin1_code":"5.0",
    "gn:asciiname":"Yarcoma",
    "gn:country_code":"BO",
    "gn:dem":3709,
    "gn:feature_class":"P",
    "gn:feature_code":"PPL",
    "gn:name":"Yarcoma",
    "gn:population":0,
    "gn:timezone":"America/La_Paz",
    "iso:country":"BO",
    "wof:name":"Yarcoma",
    "wof:placetype":"locality"
},
  "geometry": {"coordinates":[-67.45,-18.28333],"type":"Point"}
}