{
  "type": "Feature",
  "properties": {
    "gn:admin1_code":"1.0",
    "gn:asciiname":"Molleni",
    "gn:country_code":"BO",
    "gn:dem":2024,
    "gn:feature_class":"P",
    "gn:feature_code":"PPL",
    "gn:name":"Molleni",
    "gn:population":0,
    "gn:timezone":"America/La_Paz",
    "iso:country":"BO",
    "wof:name":"Molleni",
    "wof:placetype":"locality"
},
  "geometry": {"coordinates":[-64.46247,-19.78049],"type":"Point"}
}