{
  "type": "Feature",
  "properties": {
    "gn:admin1_code":"7.0",
    "gn:asciiname":"Sagrario",
    "gn:country_code":"BO",
    "gn:dem":4185,
    "gn:feature_class":"P",
    "gn:feature_code":"PPL",
    "gn:name":"Sagrario",
    "gn:population":0,
    "gn:timezone":"America/La_Paz",
    "iso:country":"BO",
    "wof:name":"Sagrario",
    "wof:placetype":"locality"
},
  "geometry": {"coordinates":[-65.98333000000001,-20.93333],"type":"Point"}
}