{
  "type": "Feature",
  "properties": {
    "gn:admin1_code":"07",
    "gn:asciiname":"Calaota",
    "gn:country_code":"BO",
    "gn:dem":2010,
    "gn:feature_class":"P",
    "gn:feature_code":"PPL",
    "gn:name":"Calaota",
    "gn:population":0,
    "gn:timezone":"America/La_Paz",
    "iso:country":"BO",
    "name:und_x_variant":[
        "Calauta",
        "Calaota"
    ],
    "wof:name":"Calaota",
    "wof:placetype":"locality"
},
  "geometry": {"coordinates":[-65.76144000000001,-18.06646],"type":"Point"}
}