{
  "type": "Feature",
  "properties": {
    "gn:admin1_code":"7.0",
    "gn:asciiname":"Tolapacheta",
    "gn:country_code":"BO",
    "gn:dem":4129,
    "gn:feature_class":"P",
    "gn:feature_code":"PPL",
    "gn:name":"Tolapacheta",
    "gn:population":0,
    "gn:timezone":"America/La_Paz",
    "iso:country":"BO",
    "wof:name":"Tolapacheta",
    "wof:placetype":"locality"
},
  "geometry": {"coordinates":[-68.58333,-19.68333],"type":"Point"}
}