{
  "type": "Feature",
  "properties": {
    "gn:admin1_code":"04",
    "gn:asciiname":"Chuluyapu",
    "gn:country_code":"BO",
    "gn:dem":3119,
    "gn:feature_class":"P",
    "gn:feature_code":"PPL",
    "gn:name":"Chuluyapu",
    "gn:population":0,
    "gn:timezone":"America/La_Paz",
    "iso:country":"BO",
    "name:spa_x_preferred":[
        "Chuluyapu"
    ],
    "wof:name":"Chuluyapu",
    "wof:placetype":"locality"
},
  "geometry": {"coordinates":[-68.71898,-15.59267],"type":"Point"}
}