{
  "type": "Feature",
  "properties": {
    "gn:admin1_code":"4.0",
    "gn:asciiname":"Estancia Viluyo",
    "gn:country_code":"BO",
    "gn:dem":4282,
    "gn:feature_class":"P",
    "gn:feature_code":"PPL",
    "gn:name":"Estancia Viluyo",
    "gn:population":0,
    "gn:timezone":"America/La_Paz",
    "iso:country":"BO",
    "wof:name":"Estancia Viluyo",
    "wof:placetype":"locality"
},
  "geometry": {"coordinates":[-67.26666999999999,-17.26667],"type":"Point"}
}