{
  "type": "Feature",
  "properties": {
    "gn:admin1_code":"04",
    "gn:asciiname":"Cantapaya",
    "gn:country_code":"BO",
    "gn:dem":3848,
    "gn:feature_class":"P",
    "gn:feature_code":"PPL",
    "gn:name":"Cantapaya",
    "gn:population":0,
    "gn:timezone":"America/La_Paz",
    "iso:country":"BO",
    "wof:name":"Cantapaya",
    "wof:placetype":"locality"
},
  "geometry": {"coordinates":[-68.51666999999999,-16.36667000000001],"type":"Point"}
}