{
  "type": "Feature",
  "properties": {
    "gn:admin1_code":"6.0",
    "gn:asciiname":"Nationada",
    "gn:country_code":"BO",
    "gn:dem":192,
    "gn:feature_class":"P",
    "gn:feature_code":"PPL",
    "gn:name":"Nationada",
    "gn:population":0,
    "gn:timezone":"America/La_Paz",
    "iso:country":"BO",
    "name:und_x_variant":[
        "Junin",
        "National",
        "Nationada"
    ],
    "wof:name":"Nationada",
    "wof:placetype":"locality"
},
  "geometry": {"coordinates":[-67.07184000000001,-11.20729],"type":"Point"}
}