{
  "type": "Feature",
  "properties": {
    "gn:admin1_code":"1.0",
    "gn:asciiname":"Mosca Pampa",
    "gn:cc2":"BO",
    "gn:country_code":"BO",
    "gn:dem":2174,
    "gn:feature_class":"P",
    "gn:feature_code":"PPL",
    "gn:name":"Mosca Pampa",
    "gn:population":0,
    "gn:timezone":"America/La_Paz",
    "iso:country":"BO",
    "name:und_x_variant":[
        "Moska Pampa",
        "Mosca Pampa"
    ],
    "wof:name":"Mosca Pampa",
    "wof:placetype":"locality"
},
  "geometry": {"coordinates":[-64.40000000000001,-19.36667000000001],"type":"Point"}
}