{
  "type": "Feature",
  "properties": {
    "gn:admin1_code":"4.0",
    "gn:asciiname":"Kachu",
    "gn:country_code":"BO",
    "gn:dem":3803,
    "gn:feature_class":"P",
    "gn:feature_code":"PPL",
    "gn:name":"Kachu",
    "gn:population":0,
    "gn:timezone":"America/La_Paz",
    "iso:country":"BO",
    "wof:name":"Kachu",
    "wof:placetype":"locality"
},
  "geometry": {"coordinates":[-68.34999999999999,-17.46667],"type":"Point"}
}