{
  "type": "Feature",
  "properties": {
    "gn:admin1_code":"3.0",
    "gn:asciiname":"Monte Saltado",
    "gn:cc2":"BO",
    "gn:country_code":"BO",
    "gn:dem":147,
    "gn:feature_class":"P",
    "gn:feature_code":"PPL",
    "gn:name":"Monte Saltado",
    "gn:population":0,
    "gn:timezone":"America/La_Paz",
    "iso:country":"BO",
    "name:und_x_variant":[
        "Monte Salado",
        "Monte Saltado"
    ],
    "wof:name":"Monte Saltado",
    "wof:placetype":"locality"
},
  "geometry": {"coordinates":[-66.23333000000001,-11.26667],"type":"Point"}
}