{
  "type": "Feature",
  "properties": {
    "gn:admin1_code":"7.0",
    "gn:asciiname":"Huailla",
    "gn:country_code":"BO",
    "gn:dem":3739,
    "gn:feature_class":"P",
    "gn:feature_code":"PPL",
    "gn:name":"Huailla",
    "gn:population":0,
    "gn:timezone":"America/La_Paz",
    "iso:country":"BO",
    "wof:name":"Huailla",
    "wof:placetype":"locality"
},
  "geometry": {"coordinates":[-65.65000000000001,-21.25],"type":"Point"}
}