{
  "type": "Feature",
  "properties": {
    "gn:admin1_code":"06",
    "gn:asciiname":"Cacharia",
    "gn:country_code":"BO",
    "gn:dem":223,
    "gn:feature_class":"P",
    "gn:feature_code":"PPL",
    "gn:name":"Cacharia",
    "gn:population":0,
    "gn:timezone":"America/La_Paz",
    "iso:country":"BO",
    "name:spa_x_preferred":[
        "Cacharia"
    ],
    "wof:name":"Cacharia",
    "wof:placetype":"locality"
},
  "geometry": {"coordinates":[-67.94555,-11.04156],"type":"Point"}
}