{
  "type": "Feature",
  "properties": {
    "gn:admin1_code":"7.0",
    "gn:asciiname":"Tajopunta",
    "gn:country_code":"BO",
    "gn:dem":4052,
    "gn:feature_class":"P",
    "gn:feature_code":"PPL",
    "gn:name":"Tajopunta",
    "gn:population":0,
    "gn:timezone":"America/La_Paz",
    "iso:country":"BO",
    "wof:name":"Tajopunta",
    "wof:placetype":"locality"
},
  "geometry": {"coordinates":[-66.06667,-21.25],"type":"Point"}
}