{
  "type": "Feature",
  "properties": {
    "gn:admin1_code":"02",
    "gn:asciiname":"Estancia El Potrero",
    "gn:country_code":"BO",
    "gn:dem":490,
    "gn:feature_class":"P",
    "gn:feature_code":"PPL",
    "gn:name":"Estancia El Potrero",
    "gn:population":0,
    "gn:timezone":"America/La_Paz",
    "iso:country":"BO",
    "wof:name":"Estancia El Potrero",
    "wof:placetype":"locality"
},
  "geometry": {"coordinates":[-60.73333,-16.56667],"type":"Point"}
}