{
  "type": "Feature",
  "properties": {
    "gn:admin1_code":"07",
    "gn:asciiname":"Estancia Buena Vista",
    "gn:country_code":"BO",
    "gn:dem":4089,
    "gn:feature_class":"P",
    "gn:feature_code":"PPL",
    "gn:name":"Estancia Buena Vista",
    "gn:population":0,
    "gn:timezone":"America/La_Paz",
    "iso:country":"BO",
    "wof:name":"Estancia Buena Vista",
    "wof:placetype":"locality"
},
  "geometry": {"coordinates":[-68.07644999999999,-20.61484],"type":"Point"}
}