{
  "type": "Feature",
  "properties": {
    "gn:admin1_code":"8.0",
    "gn:asciiname":"Tunilla",
    "gn:country_code":"BO",
    "gn:dem":1049,
    "gn:feature_class":"P",
    "gn:feature_code":"PPL",
    "gn:name":"Tunilla",
    "gn:population":0,
    "gn:timezone":"America/La_Paz",
    "iso:country":"BO",
    "wof:name":"Tunilla",
    "wof:placetype":"locality"
},
  "geometry": {"coordinates":[-64.30199,-18.51027],"type":"Point"}
}