{
  "type": "Feature",
  "properties": {
    "gn:admin1_code":"8.0",
    "gn:asciiname":"Tunilla",
    "gn:country_code":"BO",
    "gn:dem":1049,
    "gn:feature_class":"P",
    "gn:feature_code":"PPL",
    "gn:name":"Tunilla",
    "gn:population":0,
    "gn:timezone":"America/La_Paz",
    "iso:country":"BO",
    "name:ceb_x_preferred":[
        "Tunilla"
    ],
    "name:deu_x_preferred":[
        "Tunilla"
    ],
    "name:fin_x_preferred":[
        "Tunilla"
    ],
    "name:ita_x_preferred":[
        "Tunilla"
    ],
    "name:nld_x_preferred":[
        "Tunilla"
    ],
    "name:ron_x_preferred":[
        "Tunilla"
    ],
    "name:spa_x_preferred":[
        "Tunilla"
    ],
    "name:swe_x_preferred":[
        "Tunilla"
    ],
    "name:war_x_preferred":[
        "Tunilla"
    ],
    "wof:name":"Tunilla",
    "wof:placetype":"locality"
},
  "geometry": {"coordinates":[-64.30199,-18.51027],"type":"Point"}
}