{
  "type": "Feature",
  "properties": {
    "gn:admin1_code":"5.0",
    "gn:asciiname":"Querarani",
    "gn:cc2":"BO",
    "gn:country_code":"BO",
    "gn:dem":3856,
    "gn:feature_class":"P",
    "gn:feature_code":"PPL",
    "gn:name":"Querarani",
    "gn:population":0,
    "gn:timezone":"America/La_Paz",
    "iso:country":"BO",
    "name:und_x_variant":[
        "Quererani",
        "Querarani"
    ],
    "wof:name":"Querarani",
    "wof:placetype":"locality"
},
  "geometry": {"coordinates":[-67.05,-17.66667],"type":"Point"}
}