{
  "type": "Feature",
  "properties": {
    "gn:admin1_code":"4.0",
    "gn:asciiname":"Limari",
    "gn:cc2":"BO",
    "gn:country_code":"BO",
    "gn:dem":3853,
    "gn:feature_class":"P",
    "gn:feature_code":"PPL",
    "gn:name":"Limari",
    "gn:population":0,
    "gn:timezone":"America/La_Paz",
    "iso:country":"BO",
    "name:und_x_variant":[
        "Limara",
        "Limari"
    ],
    "wof:name":"Limari",
    "wof:placetype":"locality"
},
  "geometry": {"coordinates":[-68.61667,-17.36667000000001],"type":"Point"}
}