{
  "type": "Feature",
  "properties": {
    "gn:admin1_code":"06",
    "gn:asciiname":"Dieciseis de Julio",
    "gn:country_code":"BO",
    "gn:dem":193,
    "gn:feature_class":"P",
    "gn:feature_code":"PPL",
    "gn:name":"Dieciseis de Julio",
    "gn:population":0,
    "gn:timezone":"America/La_Paz",
    "iso:country":"BO",
    "name:spa_x_preferred":[
        "Dieciseis de Julio"
    ],
    "wof:name":"Dieciseis de Julio",
    "wof:placetype":"locality"
},
  "geometry": {"coordinates":[-67.31479,-10.89099],"type":"Point"}
}