{
  "type": "Feature",
  "properties": {
    "gn:admin1_code":"07",
    "gn:asciiname":"Cueva",
    "gn:country_code":"BO",
    "gn:dem":3306,
    "gn:feature_class":"P",
    "gn:feature_code":"PPL",
    "gn:name":"Cueva",
    "gn:population":0,
    "gn:timezone":"America/La_Paz",
    "iso:country":"BO",
    "name:und_x_variant":[
        "Estancia Cueva",
        "Cueva"
    ],
    "wof:name":"Cueva",
    "wof:placetype":"locality"
},
  "geometry": {"coordinates":[-66.10528000000001,-20.50801],"type":"Point"}
}