{
  "type": "Feature",
  "properties": {
    "gn:admin1_code":"04",
    "gn:asciiname":"Coriquina",
    "gn:country_code":"BO",
    "gn:dem":4219,
    "gn:feature_class":"P",
    "gn:feature_code":"PPL",
    "gn:name":"Coriquina",
    "gn:population":0,
    "gn:timezone":"America/La_Paz",
    "iso:country":"BO",
    "wof:name":"Coriquina",
    "wof:placetype":"locality"
},
  "geometry": {"coordinates":[-69.08333,-15.43333],"type":"Point"}
}