{
  "type": "Feature",
  "properties": {
    "gn:admin1_code":"04",
    "gn:asciiname":"Estancia Jiskha Khara Kkota",
    "gn:country_code":"BO",
    "gn:dem":4560,
    "gn:feature_class":"P",
    "gn:feature_code":"PPL",
    "gn:name":"Estancia Jiskha Khara Kkota",
    "gn:population":0,
    "gn:timezone":"America/La_Paz",
    "iso:country":"BO",
    "wof:name":"Estancia Jiskha Khara Kkota",
    "wof:placetype":"locality"
},
  "geometry": {"coordinates":[-69.06667,-15.28333],"type":"Point"}
}