{
  "type": "Feature",
  "properties": {
    "gn:admin1_code":"4.0",
    "gn:asciiname":"Pogije",
    "gn:cc2":"BO",
    "gn:country_code":"BO",
    "gn:dem":1173,
    "gn:feature_class":"P",
    "gn:feature_code":"PPL",
    "gn:name":"Pogije",
    "gn:population":0,
    "gn:timezone":"America/La_Paz",
    "iso:country":"BO",
    "name:und_x_variant":[
        "Rogige",
        "Poquije",
        "Pogije"
    ],
    "wof:name":"Pogije",
    "wof:placetype":"locality"
},
  "geometry": {"coordinates":[-68.51666999999999,-14.98333],"type":"Point"}
}