{
  "type": "Feature",
  "properties": {
    "gn:admin1_code":"2.0",
    "gn:asciiname":"Estancia Torrini",
    "gn:country_code":"BO",
    "gn:dem":2856,
    "gn:feature_class":"P",
    "gn:feature_code":"PPL",
    "gn:name":"Estancia Torrini",
    "gn:population":0,
    "gn:timezone":"America/La_Paz",
    "iso:country":"BO",
    "wof:name":"Estancia Torrini",
    "wof:placetype":"locality"
},
  "geometry": {"coordinates":[-66.23333000000001,-17.76667],"type":"Point"}
}