{
  "type": "Feature",
  "properties": {
    "gn:admin1_code":"2.0",
    "gn:asciiname":"La Vina",
    "gn:cc2":"BO",
    "gn:country_code":"BO",
    "gn:dem":2761,
    "gn:feature_class":"P",
    "gn:feature_code":"PPL",
    "gn:name":"La Vi\u00f1a",
    "gn:population":0,
    "gn:timezone":"America/La_Paz",
    "iso:country":"BO",
    "name:und_x_variant":[
        "Vi\u00f1a",
        "La Vi\u00f1a"
    ],
    "wof:name":"La Vina",
    "wof:placetype":"locality"
},
  "geometry": {"coordinates":[-64.83333,-17.85],"type":"Point"}
}