{
  "type": "Feature",
  "properties": {
    "gn:admin1_code":"1.0",
    "gn:asciiname":"Parapeti",
    "gn:country_code":"BO",
    "gn:dem":940,
    "gn:feature_class":"P",
    "gn:feature_code":"PPL",
    "gn:name":"Parapet\u00ed",
    "gn:population":0,
    "gn:timezone":"America/La_Paz",
    "iso:country":"BO",
    "wof:name":"Parapeti",
    "wof:placetype":"locality"
},
  "geometry": {"coordinates":[-63.87036,-20.18643],"type":"Point"}
}