{
  "type": "Feature",
  "properties": {
    "gn:admin1_code":"4.0",
    "gn:asciiname":"Mariapu",
    "gn:country_code":"BO",
    "gn:dem":807,
    "gn:feature_class":"P",
    "gn:feature_code":"PPL",
    "gn:name":"Mariapu",
    "gn:population":0,
    "gn:timezone":"America/La_Paz",
    "iso:country":"BO",
    "wof:name":"Mariapu",
    "wof:placetype":"locality"
},
  "geometry": {"coordinates":[-68.03333000000001,-15.43333],"type":"Point"}
}