{
  "type": "Feature",
  "properties": {
    "gn:admin1_code":"8.0",
    "gn:asciiname":"San Lorencito",
    "gn:cc2":"BO",
    "gn:country_code":"BO",
    "gn:dem":382,
    "gn:feature_class":"P",
    "gn:feature_code":"PPL",
    "gn:name":"San Lorencito",
    "gn:population":0,
    "gn:timezone":"America/La_Paz",
    "iso:country":"BO",
    "name:und_x_variant":[
        "Estancia San Lorencito",
        "San Lorencito"
    ],
    "wof:name":"San Lorencito",
    "wof:placetype":"locality"
},
  "geometry": {"coordinates":[-61.01667,-16.31667],"type":"Point"}
}