{
  "type": "Feature",
  "properties": {
    "gn:admin1_code":"04",
    "gn:asciiname":"Cohapujio",
    "gn:cc2":"BO",
    "gn:country_code":"BO",
    "gn:dem":3863,
    "gn:feature_class":"P",
    "gn:feature_code":"PPL",
    "gn:name":"Cohapujio",
    "gn:population":0,
    "gn:timezone":"America/La_Paz",
    "iso:country":"BO",
    "name:und_x_variant":[
        "Estancia Challa Japujo",
        "Cokapujio",
        "Cohapujio"
    ],
    "wof:name":"Cohapujio",
    "wof:placetype":"locality"
},
  "geometry": {"coordinates":[-68.81667,-17.16667],"type":"Point"}
}