{
  "type": "Feature",
  "properties": {
    "gn:admin1_code":"05",
    "gn:asciiname":"Estancia Kollpa Jahuira",
    "gn:country_code":"BO",
    "gn:dem":3813,
    "gn:feature_class":"P",
    "gn:feature_code":"PPL",
    "gn:name":"Estancia Kollpa Jahuira",
    "gn:population":0,
    "gn:timezone":"America/La_Paz",
    "iso:country":"BO",
    "wof:name":"Estancia Kollpa Jahuira",
    "wof:placetype":"locality"
},
  "geometry": {"coordinates":[-68.56641999999999,-18.38898],"type":"Point"}
}