{
  "type": "Feature",
  "properties": {
    "gn:admin1_code":"06",
    "gn:asciiname":"Ballivian",
    "gn:country_code":"BO",
    "gn:dem":154,
    "gn:feature_class":"P",
    "gn:feature_code":"PPL",
    "gn:name":"Ballivi\u00e1n",
    "gn:population":0,
    "gn:timezone":"America/La_Paz",
    "iso:country":"BO",
    "wof:name":"Ballivian",
    "wof:placetype":"locality"
},
  "geometry": {"coordinates":[-67.66880999999999,-11.58153],"type":"Point"}
}