{
  "type": "Feature",
  "properties": {
    "gn:admin1_code":"04",
    "gn:asciiname":"Copani",
    "gn:country_code":"BO",
    "gn:dem":3850,
    "gn:feature_class":"P",
    "gn:feature_code":"PPL",
    "gn:name":"Copani",
    "gn:population":0,
    "gn:timezone":"America/La_Paz",
    "iso:country":"BO",
    "wof:name":"Copani",
    "wof:placetype":"locality"
},
  "geometry": {"coordinates":[-68.73333000000001,-17.43333],"type":"Point"}
}