{
  "type": "Feature",
  "properties": {
    "gn:admin1_code":"05",
    "gn:asciiname":"Estancia Kkotana",
    "gn:country_code":"BO",
    "gn:dem":4086,
    "gn:feature_class":"P",
    "gn:feature_code":"PPL",
    "gn:name":"Estancia Kkota\u00f1a",
    "gn:population":0,
    "gn:timezone":"America/La_Paz",
    "iso:country":"BO",
    "wof:name":"Estancia Kkotana",
    "wof:placetype":"locality"
},
  "geometry": {"coordinates":[-68.68911999999999,-18.90752],"type":"Point"}
}