{
  "type": "Feature",
  "properties": {
    "gn:admin1_code":"4.0",
    "gn:asciiname":"Huacuyo",
    "gn:cc2":"BO",
    "gn:country_code":"BO",
    "gn:dem":4166,
    "gn:feature_class":"P",
    "gn:feature_code":"PPL",
    "gn:name":"Huacuyo",
    "gn:population":0,
    "gn:timezone":"America/La_Paz",
    "iso:country":"BO",
    "name:und_x_variant":[
        "Comunidad Huacuya",
        "Huacuyo"
    ],
    "wof:name":"Huacuyo",
    "wof:placetype":"locality"
},
  "geometry": {"coordinates":[-69.03333000000001,-16.15],"type":"Point"}
}