{
  "type": "Feature",
  "properties": {
    "gn:admin1_code":"05",
    "gn:asciiname":"Estancia Chaka Pata",
    "gn:country_code":"BO",
    "gn:dem":3773,
    "gn:feature_class":"P",
    "gn:feature_code":"PPL",
    "gn:name":"Estancia Chaka Pata",
    "gn:population":0,
    "gn:timezone":"America/La_Paz",
    "iso:country":"BO",
    "wof:name":"Estancia Chaka Pata",
    "wof:placetype":"locality"
},
  "geometry": {"coordinates":[-68.00528,-18.4979],"type":"Point"}
}