{
  "type": "Feature",
  "properties": {
    "gn:admin1_code":"4.0",
    "gn:asciiname":"Llimphi",
    "gn:cc2":"BO",
    "gn:country_code":"BO",
    "gn:dem":4314,
    "gn:feature_class":"P",
    "gn:feature_code":"PPL",
    "gn:name":"Llimphi",
    "gn:population":0,
    "gn:timezone":"America/La_Paz",
    "iso:country":"BO",
    "name:und_x_variant":[
        "Estancia Llimphi",
        "Llimphi"
    ],
    "wof:name":"Llimphi",
    "wof:placetype":"locality"
},
  "geometry": {"coordinates":[-69.06667,-17.81667000000001],"type":"Point"}
}