{
  "type": "Feature",
  "properties": {
    "gn:admin1_code":"4.0",
    "gn:asciiname":"Estancia Ramarani",
    "gn:country_code":"BO",
    "gn:dem":4516,
    "gn:feature_class":"P",
    "gn:feature_code":"PPL",
    "gn:name":"Estancia Ramarani",
    "gn:population":0,
    "gn:timezone":"America/La_Paz",
    "iso:country":"BO",
    "wof:name":"Estancia Ramarani",
    "wof:placetype":"locality"
},
  "geometry": {"coordinates":[-69.09999999999999,-15.33333],"type":"Point"}
}