{
  "type": "Feature",
  "properties": {
    "gn:admin1_code":"08",
    "gn:asciiname":"El Plato",
    "gn:country_code":"BO",
    "gn:dem":246,
    "gn:feature_class":"P",
    "gn:feature_code":"PPL",
    "gn:name":"El Plato",
    "gn:population":0,
    "gn:timezone":"America/La_Paz",
    "iso:country":"BO",
    "name:und_x_variant":[
        "Comunidad El Plato"
    ],
    "wof:name":"El Plato",
    "wof:placetype":"locality"
},
  "geometry": {"coordinates":[-62.87096,-16.96521],"type":"Point"}
}