{
  "type": "Feature",
  "properties": {
    "gn:admin1_code":"04",
    "gn:asciiname":"Chonchocoro",
    "gn:cc2":"BO",
    "gn:country_code":"BO",
    "gn:dem":3879,
    "gn:feature_class":"P",
    "gn:feature_code":"PPL",
    "gn:name":"Chonchocoro",
    "gn:population":0,
    "gn:timezone":"America/La_Paz",
    "iso:country":"BO",
    "name:und_x_variant":[
        "Chonchucoro",
        "Chonchocoro"
    ],
    "wof:name":"Chonchocoro",
    "wof:placetype":"locality"
},
  "geometry": {"coordinates":[-68.28333000000001,-16.58333],"type":"Point"}
}