{
  "type": "Feature",
  "properties": {
    "gn:admin1_code":"4.0",
    "gn:asciiname":"Tajma",
    "gn:country_code":"BO",
    "gn:dem":2075,
    "gn:feature_class":"P",
    "gn:feature_code":"PPL",
    "gn:name":"Tajma",
    "gn:population":0,
    "gn:timezone":"America/La_Paz",
    "iso:country":"BO",
    "wof:name":"Tajma",
    "wof:placetype":"locality"
},
  "geometry": {"coordinates":[-67.53333000000001,-16.23333],"type":"Point"}
}