{
  "type": "Feature",
  "properties": {
    "gn:admin1_code":"4.0",
    "gn:asciiname":"Juanillo",
    "gn:cc2":"BO",
    "gn:country_code":"BO",
    "gn:dem":3867,
    "gn:feature_class":"P",
    "gn:feature_code":"PPL",
    "gn:name":"Juanillo",
    "gn:population":0,
    "gn:timezone":"America/La_Paz",
    "iso:country":"BO",
    "name:und_x_variant":[
        "Juanilla",
        "Juanillo"
    ],
    "wof:name":"Juanillo",
    "wof:placetype":"locality"
},
  "geometry": {"coordinates":[-68.28333000000001,-17.56667],"type":"Point"}
}