{
  "type": "Feature",
  "properties": {
    "gn:admin1_code":"2.0",
    "gn:asciiname":"Villa Mercedes",
    "gn:country_code":"BO",
    "gn:dem":2702,
    "gn:feature_class":"P",
    "gn:feature_code":"PPL",
    "gn:name":"Villa Mercedes",
    "gn:population":0,
    "gn:timezone":"America/La_Paz",
    "iso:country":"BO",
    "wof:name":"Villa Mercedes",
    "wof:placetype":"locality"
},
  "geometry": {"coordinates":[-66.05,-17.56667],"type":"Point"}
}