{
  "type": "Feature",
  "properties": {
    "gn:admin1_code":"2.0",
    "gn:asciiname":"Quebrada",
    "gn:country_code":"BO",
    "gn:dem":2035,
    "gn:feature_class":"P",
    "gn:feature_code":"PPL",
    "gn:name":"Quebrada",
    "gn:population":0,
    "gn:timezone":"America/La_Paz",
    "iso:country":"BO",
    "name:ceb_x_preferred":[
        "Quebrada"
    ],
    "name:deu_x_preferred":[
        "Quebrada"
    ],
    "name:fra_x_preferred":[
        "Quebrada"
    ],
    "name:nld_x_preferred":[
        "Quebrada"
    ],
    "name:spa_x_preferred":[
        "Quebrada"
    ],
    "name:swe_x_preferred":[
        "Quebrada"
    ],
    "wof:name":"Quebrada",
    "wof:placetype":"locality"
},
  "geometry": {"coordinates":[-65.23333000000001,-18.36667000000001],"type":"Point"}
}