{
  "type": "Feature",
  "properties": {
    "gn:admin1_code":"04",
    "gn:asciiname":"Bartolo",
    "gn:country_code":"BO",
    "gn:dem":1415,
    "gn:feature_class":"P",
    "gn:feature_code":"PPL",
    "gn:name":"Bartolo",
    "gn:population":0,
    "gn:timezone":"America/La_Paz",
    "iso:country":"BO",
    "name:ceb_x_preferred":[
        "Bartolo"
    ],
    "name:deu_x_preferred":[
        "Bartolo"
    ],
    "name:fra_x_preferred":[
        "Bartolo"
    ],
    "name:pol_x_preferred":[
        "Bartolo"
    ],
    "name:rus_x_preferred":[
        "\u0411\u0430\u0440\u0442\u043e\u043b\u043e"
    ],
    "name:spa_x_preferred":[
        "Bartolo"
    ],
    "name:swe_x_preferred":[
        "Bartolo"
    ],
    "name:ukr_x_preferred":[
        "\u0411\u0430\u0440\u0442\u043e\u043b\u043e"
    ],
    "wof:name":"Bartolo",
    "wof:placetype":"locality"
},
  "geometry": {"coordinates":[-68.11667,-15.56667],"type":"Point"}
}