{
  "type": "Feature",
  "properties": {
    "gn:admin1_code":"6.0",
    "gn:asciiname":"Isidro",
    "gn:country_code":"BO",
    "gn:dem":158,
    "gn:feature_class":"P",
    "gn:feature_code":"PPL",
    "gn:name":"Isidro",
    "gn:population":0,
    "gn:timezone":"America/La_Paz",
    "iso:country":"BO",
    "wof:name":"Isidro",
    "wof:placetype":"locality"
},
  "geometry": {"coordinates":[-67.26666999999999,-11.45],"type":"Point"}
}