{
  "type": "Feature",
  "properties": {
    "gn:admin1_code":"04",
    "gn:asciiname":"Chullina",
    "gn:country_code":"BO",
    "gn:dem":3339,
    "gn:feature_class":"P",
    "gn:feature_code":"PPL",
    "gn:name":"Chullina",
    "gn:population":0,
    "gn:timezone":"America/La_Paz",
    "iso:country":"BO",
    "name:und_x_variant":[
        "Chulina",
        "Cholina",
        "Chullina"
    ],
    "wof:name":"Chullina",
    "wof:placetype":"locality"
},
  "geometry": {"coordinates":[-68.93719,-15.16884],"type":"Point"}
}