{
  "type": "Feature",
  "properties": {
    "gn:admin1_code":"06",
    "gn:asciiname":"Guarape",
    "gn:country_code":"BO",
    "gn:dem":222,
    "gn:feature_class":"P",
    "gn:feature_code":"PPL",
    "gn:name":"Guarape",
    "gn:population":0,
    "gn:timezone":"America/La_Paz",
    "iso:country":"BO",
    "name:spa_x_preferred":[
        "Guarape"
    ],
    "wof:name":"Guarape",
    "wof:placetype":"locality"
},
  "geometry": {"coordinates":[-68.31408,-11.15379],"type":"Point"}
}