{
  "type": "Feature",
  "properties": {
    "gn:admin1_code":"09",
    "gn:asciiname":"Antigua Colonia Crevaux",
    "gn:cc2":"BO",
    "gn:country_code":"BO",
    "gn:dem":294,
    "gn:feature_class":"P",
    "gn:feature_code":"PPL",
    "gn:name":"Antigua Colonia Crevaux",
    "gn:population":0,
    "gn:timezone":"America/La_Paz",
    "iso:country":"BO",
    "name:und_x_variant":[
        "Colonia Crevaux",
        "Antigua Colonia Crevaux"
    ],
    "wof:name":"Antigua Colonia Crevaux",
    "wof:placetype":"locality"
},
  "geometry": {"coordinates":[-62.91667,-21.91667],"type":"Point"}
}