{
  "type": "Feature",
  "properties": {
    "gn:admin1_code":"3.0",
    "gn:asciiname":"Independencia",
    "gn:cc2":"BO",
    "gn:country_code":"BO",
    "gn:dem":195,
    "gn:feature_class":"P",
    "gn:feature_code":"PPL",
    "gn:name":"Independencia",
    "gn:population":0,
    "gn:timezone":"America/La_Paz",
    "iso:country":"BO",
    "name:und_x_variant":[
        "Independiente",
        "Independencia"
    ],
    "wof:name":"Independencia",
    "wof:placetype":"locality"
},
  "geometry": {"coordinates":[-62.45,-13.45],"type":"Point"}
}