{
  "type": "Feature",
  "properties": {
    "gn:admin1_code":"04",
    "gn:asciiname":"Alto Achacana",
    "gn:country_code":"BO",
    "gn:dem":3846,
    "gn:feature_class":"P",
    "gn:feature_code":"PPL",
    "gn:name":"Alto Achacana",
    "gn:population":0,
    "gn:timezone":"America/La_Paz",
    "iso:country":"BO",
    "wof:name":"Alto Achacana",
    "wof:placetype":"locality"
},
  "geometry": {"coordinates":[-69.08333,-16.81667],"type":"Point"}
}