{
  "type": "Feature",
  "properties": {
    "gn:admin1_code":"02",
    "gn:asciiname":"Flairisco",
    "gn:country_code":"BO",
    "gn:dem":2180,
    "gn:feature_class":"P",
    "gn:feature_code":"PPL",
    "gn:name":"Flairisco",
    "gn:population":0,
    "gn:timezone":"America/La_Paz",
    "iso:country":"BO",
    "wof:name":"Flairisco",
    "wof:placetype":"locality"
},
  "geometry": {"coordinates":[-65.17794000000001,-17.90554],"type":"Point"}
}