{
  "type": "Feature",
  "properties": {
    "gn:admin1_code":"04",
    "gn:asciiname":"Cachuro",
    "gn:cc2":"BO",
    "gn:country_code":"BO",
    "gn:dem":4119,
    "gn:feature_class":"P",
    "gn:feature_code":"PPL",
    "gn:name":"Cachuro",
    "gn:population":0,
    "gn:timezone":"America/La_Paz",
    "iso:country":"BO",
    "name:und_x_variant":[
        "Kachura",
        "Cachuro"
    ],
    "wof:name":"Cachuro",
    "wof:placetype":"locality"
},
  "geometry": {"coordinates":[-68.59999999999999,-17.71667],"type":"Point"}
}