{
  "type": "Feature",
  "properties": {
    "gn:admin1_code":"8.0",
    "gn:asciiname":"Los Monos",
    "gn:country_code":"BO",
    "gn:dem":1066,
    "gn:feature_class":"P",
    "gn:feature_code":"PPL",
    "gn:name":"Los Monos",
    "gn:population":0,
    "gn:timezone":"America/La_Paz",
    "iso:country":"BO",
    "wof:name":"Los Monos",
    "wof:placetype":"locality"
},
  "geometry": {"coordinates":[-63.69161,-18.1469],"type":"Point"}
}