{
  "type": "Feature",
  "properties": {
    "gn:admin1_code":"8.0",
    "gn:asciiname":"Mariqui",
    "gn:country_code":"BO",
    "gn:dem":550,
    "gn:feature_class":"P",
    "gn:feature_code":"PPL",
    "gn:name":"Mariqui",
    "gn:population":0,
    "gn:timezone":"America/La_Paz",
    "iso:country":"BO",
    "name:und_x_variant":[
        "Maviqui",
        "Mariqui"
    ],
    "wof:name":"Mariqui",
    "wof:placetype":"locality"
},
  "geometry": {"coordinates":[-62.89653000000001,-19.91713],"type":"Point"}
}