{
  "type": "Feature",
  "properties": {
    "gn:admin1_code":"07",
    "gn:asciiname":"Estancia Casla",
    "gn:country_code":"BO",
    "gn:dem":3768,
    "gn:feature_class":"P",
    "gn:feature_code":"PPL",
    "gn:name":"Estancia Casla",
    "gn:population":0,
    "gn:timezone":"America/La_Paz",
    "iso:country":"BO",
    "wof:name":"Estancia Casla",
    "wof:placetype":"locality"
},
  "geometry": {"coordinates":[-65.77779,-19.95952],"type":"Point"}
}