{
  "type": "Feature",
  "properties": {
    "gn:admin1_code":"4.0",
    "gn:asciiname":"Kanapa",
    "gn:cc2":"BO",
    "gn:country_code":"BO",
    "gn:dem":3841,
    "gn:feature_class":"P",
    "gn:feature_code":"PPL",
    "gn:name":"Kanapa",
    "gn:population":0,
    "gn:timezone":"America/La_Paz",
    "iso:country":"BO",
    "name:und_x_variant":[
        "Estancia Kanapa",
        "Kanapa"
    ],
    "wof:name":"Kanapa",
    "wof:placetype":"locality"
},
  "geometry": {"coordinates":[-68.88333,-16.88332999999999],"type":"Point"}
}