{
  "type": "Feature",
  "properties": {
    "gn:admin1_code":"02",
    "gn:asciiname":"Antakawa",
    "gn:country_code":"BO",
    "gn:dem":2837,
    "gn:feature_class":"P",
    "gn:feature_code":"PPL",
    "gn:name":"Antakawa",
    "gn:population":0,
    "gn:timezone":"America/La_Paz",
    "iso:country":"BO",
    "wof:name":"Antakawa",
    "wof:placetype":"locality"
},
  "geometry": {"coordinates":[-65.14372,-17.86497],"type":"Point"}
}