{
  "type": "Feature",
  "properties": {
    "gn:admin1_code":"03",
    "gn:asciiname":"Chevejecure",
    "gn:cc2":"BO",
    "gn:country_code":"BO",
    "gn:dem":178,
    "gn:feature_class":"P",
    "gn:feature_code":"PPL",
    "gn:name":"Chevej\u00e9cure",
    "gn:population":0,
    "gn:timezone":"America/La_Paz",
    "iso:country":"BO",
    "name:und_x_variant":[
        "Chevejure",
        "Chevej\u00e9cure"
    ],
    "wof:name":"Chevejecure",
    "wof:placetype":"locality"
},
  "geometry": {"coordinates":[-66.05,-14.81667],"type":"Point"}
}