{
  "type": "Feature",
  "properties": {
    "gn:admin1_code":"4.0",
    "gn:asciiname":"Humanata",
    "gn:country_code":"BO",
    "gn:dem":3995,
    "gn:feature_class":"P",
    "gn:feature_code":"PPL",
    "gn:name":"Humanata",
    "gn:population":0,
    "gn:timezone":"America/La_Paz",
    "iso:country":"BO",
    "name:deu_x_preferred":[
        "Municipio Humanata"
    ],
    "name:kat_x_preferred":[
        "\u10e3\u10d0\u10db\u10d0\u10dc\u10e2\u10d8\u10e1 \u10db\u10e3\u10dc\u10d8\u10ea\u10d8\u10de\u10d0\u10da\u10d8\u10e2\u10d4\u10e2\u10d8"
    ],
    "name:que_x_preferred":[
        "Umanata munisipyu"
    ],
    "name:und_x_variant":[
        "Umanata",
        "Humanata"
    ],
    "name:xmf_x_preferred":[
        "\u10e3\u10d0\u10db\u10d0\u10dc\u10e2\u10d0\u10e8 \u10db\u10e3\u10dc\u10d8\u10ea\u10d8\u10de\u10d0\u10da\u10d8\u10e2\u10d4\u10e2\u10d8"
    ],
    "wof:name":"Humanata",
    "wof:placetype":"locality"
},
  "geometry": {"coordinates":[-69.13013000000001,-15.46876],"type":"Point"}
}