{
  "type": "Feature",
  "properties": {
    "gn:admin1_code":"4.0",
    "gn:asciiname":"Pariguaya",
    "gn:cc2":"BO",
    "gn:country_code":"BO",
    "gn:dem":2956,
    "gn:feature_class":"P",
    "gn:feature_code":"PPL",
    "gn:name":"Pariguaya",
    "gn:population":0,
    "gn:timezone":"America/La_Paz",
    "iso:country":"BO",
    "name:und_x_variant":[
        "Parihuaya",
        "Pariguaya"
    ],
    "wof:name":"Pariguaya",
    "wof:placetype":"locality"
},
  "geometry": {"coordinates":[-67.53333000000001,-16.58333],"type":"Point"}
}