{
  "type": "Feature",
  "properties": {
    "gn:admin1_code":"04",
    "gn:asciiname":"Chichilaya",
    "gn:cc2":"BO",
    "gn:country_code":"BO",
    "gn:dem":3832,
    "gn:feature_class":"P",
    "gn:feature_code":"PPL",
    "gn:name":"Chichilaya",
    "gn:population":0,
    "gn:timezone":"America/La_Paz",
    "iso:country":"BO",
    "name:und_x_variant":[
        "Cachilaya",
        "Comunidad Cachilaya",
        "Chichilaya"
    ],
    "wof:name":"Chichilaya",
    "wof:placetype":"locality"
},
  "geometry": {"coordinates":[-68.58333,-16.31667],"type":"Point"}
}