{
  "type": "Feature",
  "properties": {
    "gn:admin1_code":"04",
    "gn:asciiname":"Ekerana",
    "gn:cc2":"BO",
    "gn:country_code":"BO",
    "gn:dem":3903,
    "gn:feature_class":"P",
    "gn:feature_code":"PPL",
    "gn:name":"Ekerana",
    "gn:population":0,
    "gn:timezone":"America/La_Paz",
    "iso:country":"BO",
    "name:und_x_variant":[
        "Ekerani",
        "Ekerane",
        "Ekerana"
    ],
    "wof:name":"Ekerana",
    "wof:placetype":"locality"
},
  "geometry": {"coordinates":[-68.59999999999999,-16.11667000000001],"type":"Point"}
}