{
  "type": "Feature",
  "properties": {
    "gn:admin1_code":"7.0",
    "gn:asciiname":"Japo",
    "gn:country_code":"BO",
    "gn:dem":4092,
    "gn:feature_class":"P",
    "gn:feature_code":"PPL",
    "gn:name":"Japo",
    "gn:population":0,
    "gn:timezone":"America/La_Paz",
    "iso:country":"BO",
    "wof:name":"Japo",
    "wof:placetype":"locality"
},
  "geometry": {"coordinates":[-66.14348000000001,-18.22218],"type":"Point"}
}