{
  "type": "Feature",
  "properties": {
    "gn:admin1_code":"1.0",
    "gn:asciiname":"La Mendoza",
    "gn:country_code":"BO",
    "gn:dem":2356,
    "gn:feature_class":"P",
    "gn:feature_code":"PPL",
    "gn:name":"La Mendoza",
    "gn:population":0,
    "gn:timezone":"America/La_Paz",
    "iso:country":"BO",
    "wof:name":"La Mendoza",
    "wof:placetype":"locality"
},
  "geometry": {"coordinates":[-65.01666999999999,-19.33333],"type":"Point"}
}