{
  "type": "Feature",
  "properties": {
    "gn:admin1_code":"09",
    "gn:asciiname":"El Morro",
    "gn:country_code":"BO",
    "gn:dem":2612,
    "gn:feature_class":"P",
    "gn:feature_code":"PPL",
    "gn:name":"El Morro",
    "gn:population":0,
    "gn:timezone":"America/La_Paz",
    "iso:country":"BO",
    "name:ceb_x_preferred":[
        "El Morro"
    ],
    "name:deu_x_preferred":[
        "El Morro"
    ],
    "name:fra_x_preferred":[
        "El Morro"
    ],
    "name:spa_x_preferred":[
        "El Morro"
    ],
    "name:swe_x_preferred":[
        "El Morro"
    ],
    "wof:name":"El Morro",
    "wof:placetype":"locality"
},
  "geometry": {"coordinates":[-65.26666999999999,-21.55],"type":"Point"}
}