{
  "type": "Feature",
  "properties": {
    "gn:admin1_code":"4.0",
    "gn:asciiname":"Viluyo",
    "gn:cc2":"BO",
    "gn:country_code":"BO",
    "gn:dem":3935,
    "gn:feature_class":"P",
    "gn:feature_code":"PPL",
    "gn:name":"Viluyo",
    "gn:population":0,
    "gn:timezone":"America/La_Paz",
    "iso:country":"BO",
    "name:und_x_variant":[
        "Comunidad Viluyo",
        "Viluyo"
    ],
    "wof:name":"Viluyo",
    "wof:placetype":"locality"
},
  "geometry": {"coordinates":[-68.45,-16.63332999999999],"type":"Point"}
}