{
  "type": "Feature",
  "properties": {
    "gn:admin1_code":"7.0",
    "gn:asciiname":"Huaillani",
    "gn:cc2":"BO",
    "gn:country_code":"BO",
    "gn:dem":4453,
    "gn:feature_class":"P",
    "gn:feature_code":"PPL",
    "gn:name":"Huaillani",
    "gn:population":0,
    "gn:timezone":"America/La_Paz",
    "iso:country":"BO",
    "name:und_x_variant":[
        "Huallani",
        "Huaillani"
    ],
    "wof:name":"Huaillani",
    "wof:placetype":"locality"
},
  "geometry": {"coordinates":[-66.63333,-18.51667],"type":"Point"}
}