{
  "type": "Feature",
  "properties": {
    "gn:admin1_code":"06",
    "gn:asciiname":"Campoana Castanera",
    "gn:country_code":"BO",
    "gn:dem":228,
    "gn:feature_class":"P",
    "gn:feature_code":"PPL",
    "gn:name":"Campoana Casta\u00f1era",
    "gn:population":0,
    "gn:timezone":"America/La_Paz",
    "iso:country":"BO",
    "name:spa_x_preferred":[
        "Campoana Casta\u00f1era"
    ],
    "wof:name":"Campoana Castanera",
    "wof:placetype":"locality"
},
  "geometry": {"coordinates":[-67.75458,-10.97082],"type":"Point"}
}