{
  "type": "Feature",
  "properties": {
    "gn:admin1_code":"01",
    "gn:asciiname":"Barrero Canada",
    "gn:country_code":"BO",
    "gn:dem":1131,
    "gn:feature_class":"P",
    "gn:feature_code":"PPL",
    "gn:name":"Barrero Ca\u00f1ada",
    "gn:population":0,
    "gn:timezone":"America/La_Paz",
    "iso:country":"BO",
    "name:und_x_variant":[
        "Barrero",
        "Barrero Ca\u00f1ada"
    ],
    "wof:name":"Barrero Canada",
    "wof:placetype":"locality"
},
  "geometry": {"coordinates":[-63.77656999999999,-19.97738],"type":"Point"}
}