{
  "type": "Feature",
  "properties": {
    "gn:admin1_code":"4.0",
    "gn:asciiname":"Quillima",
    "gn:cc2":"BO",
    "gn:country_code":"BO",
    "gn:dem":4084,
    "gn:feature_class":"P",
    "gn:feature_code":"PPL",
    "gn:name":"Quillima",
    "gn:population":0,
    "gn:timezone":"America/La_Paz",
    "iso:country":"BO",
    "name:und_x_variant":[
        "Comunidad Quillima",
        "Quillima"
    ],
    "wof:name":"Quillima",
    "wof:placetype":"locality"
},
  "geometry": {"coordinates":[-68.98333000000001,-15.85],"type":"Point"}
}