{
  "type": "Feature",
  "properties": {
    "gn:admin1_code":"1.0",
    "gn:asciiname":"Hacienda Sacawillki Grande",
    "gn:country_code":"BO",
    "gn:dem":1982,
    "gn:feature_class":"P",
    "gn:feature_code":"PPL",
    "gn:name":"Hacienda Sacawillki Grande",
    "gn:population":0,
    "gn:timezone":"America/La_Paz",
    "iso:country":"BO",
    "wof:name":"Hacienda Sacawillki Grande",
    "wof:placetype":"locality"
},
  "geometry": {"coordinates":[-64.62979,-20.36716],"type":"Point"}
}