{
  "type": "Feature",
  "properties": {
    "gn:admin1_code":"1.0",
    "gn:asciiname":"Tiacia",
    "gn:country_code":"BO",
    "gn:dem":697,
    "gn:feature_class":"P",
    "gn:feature_code":"PPL",
    "gn:name":"Tiacia",
    "gn:population":0,
    "gn:timezone":"America/La_Paz",
    "iso:country":"BO",
    "name:und_x_variant":[
        "Itacia",
        "Tiacia"
    ],
    "wof:name":"Tiacia",
    "wof:placetype":"locality"
},
  "geometry": {"coordinates":[-63.6828,-20.93416],"type":"Point"}
}