{
  "type": "Feature",
  "properties": {
    "gn:admin1_code":"06",
    "gn:asciiname":"Fasen Dina",
    "gn:country_code":"BO",
    "gn:dem":197,
    "gn:feature_class":"P",
    "gn:feature_code":"PPL",
    "gn:name":"Fasen Dina",
    "gn:population":0,
    "gn:timezone":"America/La_Paz",
    "iso:country":"BO",
    "name:spa_x_preferred":[
        "Fasen Dina"
    ],
    "wof:name":"Fasen Dina",
    "wof:placetype":"locality"
},
  "geometry": {"coordinates":[-68.0741,-11.01663],"type":"Point"}
}