{
  "type": "Feature",
  "properties": {
    "gn:admin1_code":"6.0",
    "gn:asciiname":"Illimani",
    "gn:country_code":"BO",
    "gn:dem":125,
    "gn:feature_class":"P",
    "gn:feature_code":"PPL",
    "gn:name":"Illimani",
    "gn:population":0,
    "gn:timezone":"America/La_Paz",
    "iso:country":"BO",
    "wof:name":"Illimani",
    "wof:placetype":"locality"
},
  "geometry": {"coordinates":[-66.40000000000001,-9.86667],"type":"Point"}
}