{
  "type": "Feature",
  "properties": {
    "gn:admin1_code":"6.0",
    "gn:asciiname":"Illimani",
    "gn:country_code":"BO",
    "gn:dem":125,
    "gn:feature_class":"P",
    "gn:feature_code":"PPL",
    "gn:name":"Illimani",
    "gn:population":0,
    "gn:timezone":"America/La_Paz",
    "iso:country":"BO",
    "name:aym_x_preferred":[
        "Jillimani"
    ],
    "name:bel_x_preferred":[
        "\u0406\u043b\u044c\u0456\u043c\u0430\u043d\u0456"
    ],
    "name:ceb_x_preferred":[
        "Nevado Illimani"
    ],
    "name:ces_x_preferred":[
        "Illimani"
    ],
    "name:dan_x_preferred":[
        "Illimani"
    ],
    "name:deu_x_preferred":[
        "Illimani"
    ],
    "name:dsb_x_preferred":[
        "Illimani"
    ],
    "name:epo_x_preferred":[
        "Illimani"
    ],
    "name:eus_x_preferred":[
        "Illimani"
    ],
    "name:fin_x_preferred":[
        "Illimani"
    ],
    "name:fra_x_preferred":[
        "Nevado Illimani"
    ],
    "name:glg_x_preferred":[
        "Illimani"
    ],
    "name:hun_x_preferred":[
        "Illimani"
    ],
    "name:ind_x_preferred":[
        "Illimani"
    ],
    "name:ita_x_preferred":[
        "Illimani"
    ],
    "name:jpn_x_preferred":[
        "\u30a4\u30ea\u30de\u30cb"
    ],
    "name:kat_x_preferred":[
        "\u10d8\u10da\u10d8\u10db\u10d0\u10dc\u10d8"
    ],
    "name:lit_x_preferred":[
        "Iljimanis"
    ],
    "name:nld_x_preferred":[
        "Illimani"
    ],
    "name:oss_x_preferred":[
        "\u0418\u043b\u044c\u0438\u043c\u0430\u043d\u0438"
    ],
    "name:pol_x_preferred":[
        "Illimani"
    ],
    "name:por_x_preferred":[
        "Illimani"
    ],
    "name:que_x_preferred":[
        "Illimani"
    ],
    "name:ron_x_preferred":[
        "Illimani"
    ],
    "name:rus_x_preferred":[
        "\u0418\u043b\u044c\u0438\u043c\u0430\u043d\u0438"
    ],
    "name:spa_x_preferred":[
        "Illimani"
    ],
    "name:swa_x_preferred":[
        "Illimani"
    ],
    "name:swe_x_preferred":[
        "Illimani"
    ],
    "name:tur_x_preferred":[
        "Illimani"
    ],
    "name:ukr_x_preferred":[
        "\u0406\u0457\u043c\u0430\u043d\u0456"
    ],
    "name:zho_x_preferred":[
        "\u4f0a\u5b9c\u99ac\u5c3c\u5cf0"
    ],
    "wof:name":"Illimani",
    "wof:placetype":"locality"
},
  "geometry": {"coordinates":[-66.40000000000001,-9.86667],"type":"Point"}
}