{
  "type": "Feature",
  "properties": {
    "gn:admin1_code":"05",
    "gn:asciiname":"El Tambillo",
    "gn:country_code":"BO",
    "gn:dem":3743,
    "gn:feature_class":"P",
    "gn:feature_code":"PPL",
    "gn:name":"El Tambillo",
    "gn:population":0,
    "gn:timezone":"America/La_Paz",
    "iso:country":"BO",
    "name:und_x_variant":[
        "Tambillo",
        "El Tambillo"
    ],
    "wof:name":"El Tambillo",
    "wof:placetype":"locality"
},
  "geometry": {"coordinates":[-67.35218,-19.43044],"type":"Point"}
}