{
  "type": "Feature",
  "properties": {
    "gn:admin1_code":"4.0",
    "gn:asciiname":"Llanga Belen",
    "gn:country_code":"BO",
    "gn:dem":3752,
    "gn:feature_class":"P",
    "gn:feature_code":"PPL",
    "gn:name":"Llanga Bel\u00e9n",
    "gn:population":0,
    "gn:timezone":"America/La_Paz",
    "iso:country":"BO",
    "name:und_x_variant":[
        "Llanga Bel\u00e9n",
        "Llango Bel\u00e9n"
    ],
    "wof:name":"Llanga Belen",
    "wof:placetype":"locality"
},
  "geometry": {"coordinates":[-67.90526,-17.34568],"type":"Point"}
}