{
  "type": "Feature",
  "properties": {
    "gn:admin1_code":"7.0",
    "gn:asciiname":"Nicolaspata",
    "gn:country_code":"BO",
    "gn:dem":4044,
    "gn:feature_class":"P",
    "gn:feature_code":"PPL",
    "gn:name":"Nicolaspata",
    "gn:population":0,
    "gn:timezone":"America/La_Paz",
    "iso:country":"BO",
    "wof:name":"Nicolaspata",
    "wof:placetype":"locality"
},
  "geometry": {"coordinates":[-66.18333,-21.38333],"type":"Point"}
}