{
  "type": "Feature",
  "properties": {
    "gn:admin1_code":"4.0",
    "gn:asciiname":"Poroma",
    "gn:cc2":"BO",
    "gn:country_code":"BO",
    "gn:dem":919,
    "gn:feature_class":"P",
    "gn:feature_code":"PPL",
    "gn:name":"Poroma",
    "gn:population":0,
    "gn:timezone":"America/La_Paz",
    "iso:country":"BO",
    "name:ara_x_preferred":[
        "\u0634\u0632\u0646"
    ],
    "name:und_x_variant":[
        "Porema",
        "Poroma"
    ],
    "wof:name":"Poroma",
    "wof:placetype":"locality"
},
  "geometry": {"coordinates":[-67.84999999999999,-15.61667],"type":"Point"}
}