{
  "type": "Feature",
  "properties": {
    "gn:admin1_code":"07",
    "gn:asciiname":"Cerros del Ojo del Agua",
    "gn:country_code":"BO",
    "gn:dem":3081,
    "gn:feature_class":"P",
    "gn:feature_code":"PPL",
    "gn:name":"Cerros del Ojo del Agua",
    "gn:population":0,
    "gn:timezone":"America/La_Paz",
    "iso:country":"BO",
    "name:und_x_variant":[
        "Cerro del Ojo del Agua",
        "Cerros del Ojo del Agua"
    ],
    "wof:name":"Cerros del Ojo del Agua",
    "wof:placetype":"locality"
},
  "geometry": {"coordinates":[-65.75368,-20.999],"type":"Point"}
}