{
  "type": "Feature",
  "properties": {
    "gn:admin1_code":"4.0",
    "gn:asciiname":"Mazochono",
    "gn:country_code":"BO",
    "gn:dem":1091,
    "gn:feature_class":"P",
    "gn:feature_code":"PPL",
    "gn:name":"Mazochono",
    "gn:population":0,
    "gn:timezone":"America/La_Paz",
    "iso:country":"BO",
    "wof:name":"Mazochono",
    "wof:placetype":"locality"
},
  "geometry": {"coordinates":[-67.71666999999999,-15.58333],"type":"Point"}
}