{
  "type": "Feature",
  "properties": {
    "gn:admin1_code":"03",
    "gn:asciiname":"El Cusi",
    "gn:country_code":"BO",
    "gn:dem":146,
    "gn:feature_class":"P",
    "gn:feature_code":"PPL",
    "gn:name":"El Cusi",
    "gn:population":0,
    "gn:timezone":"America/La_Paz",
    "iso:country":"BO",
    "wof:name":"El Cusi",
    "wof:placetype":"locality"
},
  "geometry": {"coordinates":[-63.61666999999999,-13.73333],"type":"Point"}
}