{
  "type": "Feature",
  "properties": {
    "gn:admin1_code":"08",
    "gn:asciiname":"Carmen Ruiz",
    "gn:cc2":"BO",
    "gn:country_code":"BO",
    "gn:dem":379,
    "gn:feature_class":"P",
    "gn:feature_code":"PPL",
    "gn:name":"C\u00e1rmen Ru\u00edz",
    "gn:population":0,
    "gn:timezone":"America/La_Paz",
    "iso:country":"BO",
    "name:und_x_variant":[
        "El Carmen",
        "Comunidad C\u00e1rmen Ru\u00edz",
        "C\u00e1rmen Ru\u00edz"
    ],
    "wof:name":"Carmen Ruiz",
    "wof:placetype":"locality"
},
  "geometry": {"coordinates":[-61.11666999999999,-16.05],"type":"Point"}
}