{
  "type": "Feature",
  "properties": {
    "gn:admin1_code":"08",
    "gn:asciiname":"El Prado",
    "gn:country_code":"BO",
    "gn:dem":259,
    "gn:feature_class":"P",
    "gn:feature_code":"PPL",
    "gn:name":"El Prado",
    "gn:population":0,
    "gn:timezone":"America/La_Paz",
    "iso:country":"BO",
    "wof:name":"El Prado",
    "wof:placetype":"locality"
},
  "geometry": {"coordinates":[-61.71666999999999,-14.75],"type":"Point"}
}