{
  "type": "Feature",
  "properties": {
    "gn:admin1_code":"4.0",
    "gn:asciiname":"Tiquimaya",
    "gn:cc2":"BO",
    "gn:country_code":"BO",
    "gn:dem":4182,
    "gn:feature_class":"P",
    "gn:feature_code":"PPL",
    "gn:name":"Tiquimaya",
    "gn:population":0,
    "gn:timezone":"America/La_Paz",
    "iso:country":"BO",
    "name:und_x_variant":[
        "Tiguimlaya",
        "Tiguimaya",
        "Tiquimaya"
    ],
    "wof:name":"Tiquimaya",
    "wof:placetype":"locality"
},
  "geometry": {"coordinates":[-68.75,-15.85],"type":"Point"}
}