{
  "type": "Feature",
  "properties": {
    "gn:admin1_code":"06",
    "gn:asciiname":"Puerto San Pedro",
    "gn:country_code":"BO",
    "gn:dem":191,
    "gn:feature_class":"P",
    "gn:feature_code":"PPL",
    "gn:name":"Puerto San Pedro",
    "gn:population":0,
    "gn:timezone":"America/La_Paz",
    "iso:country":"BO",
    "name:spa_x_preferred":[
        "Puerto San Pedro"
    ],
    "wof:name":"Puerto San Pedro",
    "wof:placetype":"locality"
},
  "geometry": {"coordinates":[-68.65694000000001,-12.53693],"type":"Point"}
}