{
  "type": "Feature",
  "properties": {
    "gn:admin1_code":"04",
    "gn:asciiname":"Estancia Khanuma",
    "gn:country_code":"BO",
    "gn:dem":3947,
    "gn:feature_class":"P",
    "gn:feature_code":"PPL",
    "gn:name":"Estancia Kha\u00f1uma",
    "gn:population":0,
    "gn:timezone":"America/La_Paz",
    "iso:country":"BO",
    "wof:name":"Estancia Khanuma",
    "wof:placetype":"locality"
},
  "geometry": {"coordinates":[-68.11667,-17.01667],"type":"Point"}
}