{
  "type": "Feature",
  "properties": {
    "gn:admin1_code":"06",
    "gn:asciiname":"El Kiosko",
    "gn:country_code":"BO",
    "gn:dem":240,
    "gn:feature_class":"P",
    "gn:feature_code":"PPL",
    "gn:name":"El Kiosko",
    "gn:population":0,
    "gn:timezone":"America/La_Paz",
    "iso:country":"BO",
    "wof:name":"El Kiosko",
    "wof:placetype":"locality"
},
  "geometry": {"coordinates":[-69.36672,-10.94785],"type":"Point"}
}