{
  "type": "Feature",
  "properties": {
    "gn:admin1_code":"01",
    "gn:asciiname":"Boicobu",
    "gn:country_code":"BO",
    "gn:dem":940,
    "gn:feature_class":"P",
    "gn:feature_code":"PPL",
    "gn:name":"Boicob\u00fa",
    "gn:population":0,
    "gn:timezone":"America/La_Paz",
    "iso:country":"BO",
    "name:und_x_variant":[
        "Boicovo",
        "Boicobo Mision",
        "Boicob\u00fa"
    ],
    "wof:name":"Boicobu",
    "wof:placetype":"locality"
},
  "geometry": {"coordinates":[-63.65703000000001,-20.69862],"type":"Point"}
}