{
  "type": "Feature",
  "properties": {
    "gn:admin1_code":"01",
    "gn:asciiname":"Cana Cruz",
    "gn:country_code":"BO",
    "gn:dem":2993,
    "gn:feature_class":"P",
    "gn:feature_code":"PPL",
    "gn:name":"Ca\u00f1a Cruz",
    "gn:population":0,
    "gn:timezone":"America/La_Paz",
    "iso:country":"BO",
    "wof:name":"Cana Cruz",
    "wof:placetype":"locality"
},
  "geometry": {"coordinates":[-65.09999999999999,-20.76667],"type":"Point"}
}