{
  "type": "Feature",
  "properties": {
    "gn:admin1_code":"6.0",
    "gn:asciiname":"San Antonio",
    "gn:country_code":"BO",
    "gn:dem":114,
    "gn:feature_class":"P",
    "gn:feature_code":"PPL",
    "gn:name":"San Antonio",
    "gn:population":0,
    "gn:timezone":"America/La_Paz",
    "iso:country":"BO",
    "wof:name":"San Antonio",
    "wof:placetype":"locality"
},
  "geometry": {"coordinates":[-66.52457,-10.13081],"type":"Point"}
}