{
  "type": "Feature",
  "properties": {
    "gn:admin1_code":"02",
    "gn:asciiname":"Kallpas Pampa",
    "gn:country_code":"BO",
    "gn:dem":3100,
    "gn:feature_class":"P",
    "gn:feature_code":"PPL",
    "gn:name":"Kallpas Pampa",
    "gn:population":0,
    "gn:timezone":"America/La_Paz",
    "iso:country":"BO",
    "wof:name":"Kallpas Pampa",
    "wof:placetype":"locality"
},
  "geometry": {"coordinates":[-65.11566999999999,-17.64481],"type":"Point"}
}