{
  "type": "Feature",
  "properties": {
    "gn:admin1_code":"07",
    "gn:asciiname":"Estancia Chojna Cancha",
    "gn:country_code":"BO",
    "gn:dem":3488,
    "gn:feature_class":"P",
    "gn:feature_code":"PPL",
    "gn:name":"Estancia Choj\u00f1a Cancha",
    "gn:population":0,
    "gn:timezone":"America/La_Paz",
    "iso:country":"BO",
    "wof:name":"Estancia Chojna Cancha",
    "wof:placetype":"locality"
},
  "geometry": {"coordinates":[-65.52669,-19.48242],"type":"Point"}
}