{
  "type": "Feature",
  "properties": {
    "gn:admin1_code":"06",
    "gn:asciiname":"Villa Carino",
    "gn:country_code":"BO",
    "gn:dem":165,
    "gn:feature_class":"P",
    "gn:feature_code":"PPL",
    "gn:name":"Villa Carino",
    "gn:population":0,
    "gn:timezone":"America/La_Paz",
    "iso:country":"BO",
    "name:spa_x_preferred":[
        "Villa Carino"
    ],
    "wof:name":"Villa Carino",
    "wof:placetype":"locality"
},
  "geometry": {"coordinates":[-67.90619000000001,-10.87571],"type":"Point"}
}