{
  "type": "Feature",
  "properties": {
    "gn:admin1_code":"8.0",
    "gn:asciiname":"Muchiri",
    "gn:country_code":"BO",
    "gn:dem":971,
    "gn:feature_class":"P",
    "gn:feature_code":"PPL",
    "gn:name":"Muchiri",
    "gn:population":0,
    "gn:timezone":"America/La_Paz",
    "iso:country":"BO",
    "wof:name":"Muchiri",
    "wof:placetype":"locality"
},
  "geometry": {"coordinates":[-63.41667,-19.06667],"type":"Point"}
}