{
  "type": "Feature",
  "properties": {
    "gn:admin1_code":"1.0",
    "gn:asciiname":"Las Ulupicas",
    "gn:country_code":"BO",
    "gn:dem":2262,
    "gn:feature_class":"P",
    "gn:feature_code":"PPL",
    "gn:name":"Las Ulupicas",
    "gn:population":0,
    "gn:timezone":"America/La_Paz",
    "iso:country":"BO",
    "wof:name":"Las Ulupicas",
    "wof:placetype":"locality"
},
  "geometry": {"coordinates":[-65.19696,-21.04667],"type":"Point"}
}