{
  "type": "Feature",
  "properties": {
    "gn:admin1_code":"1.0",
    "gn:asciiname":"Estancia Pata Huasi",
    "gn:country_code":"BO",
    "gn:dem":2875,
    "gn:feature_class":"P",
    "gn:feature_code":"PPL",
    "gn:name":"Estancia Pata Huasi",
    "gn:population":0,
    "gn:timezone":"America/La_Paz",
    "iso:country":"BO",
    "wof:name":"Estancia Pata Huasi",
    "wof:placetype":"locality"
},
  "geometry": {"coordinates":[-65.0331,-20.93879],"type":"Point"}
}