{
  "type": "Feature",
  "properties": {
    "gn:admin1_code":"06",
    "gn:asciiname":"Los Huerfanos",
    "gn:country_code":"BO",
    "gn:dem":292,
    "gn:feature_class":"P",
    "gn:feature_code":"PPL",
    "gn:name":"Los Huerfanos",
    "gn:population":0,
    "gn:timezone":"America/La_Paz",
    "iso:country":"BO",
    "wof:name":"Los Huerfanos",
    "wof:placetype":"locality"
},
  "geometry": {"coordinates":[-69.2401,-11.31629],"type":"Point"}
}