{
  "type": "Feature",
  "properties": {
    "gn:admin1_code":"7.0",
    "gn:asciiname":"Mojon Punta",
    "gn:country_code":"BO",
    "gn:dem":4207,
    "gn:feature_class":"P",
    "gn:feature_code":"PPL",
    "gn:name":"Moj\u00f3n Punta",
    "gn:population":0,
    "gn:timezone":"America/La_Paz",
    "iso:country":"BO",
    "wof:name":"Mojon Punta",
    "wof:placetype":"locality"
},
  "geometry": {"coordinates":[-65.91667,-21.53333],"type":"Point"}
}