{
  "type": "Feature",
  "properties": {
    "gn:admin1_code":"07",
    "gn:asciiname":"Comunidad Thamara",
    "gn:country_code":"BO",
    "gn:dem":3349,
    "gn:feature_class":"P",
    "gn:feature_code":"PPL",
    "gn:name":"Comunidad Thamara",
    "gn:population":0,
    "gn:timezone":"America/La_Paz",
    "iso:country":"BO",
    "wof:name":"Comunidad Thamara",
    "wof:placetype":"locality"
},
  "geometry": {"coordinates":[-65.74369,-19.34828],"type":"Point"}
}