{
  "type": "Feature",
  "properties": {
    "gn:admin1_code":"7.0",
    "gn:asciiname":"Layco",
    "gn:country_code":"BO",
    "gn:dem":3640,
    "gn:feature_class":"P",
    "gn:feature_code":"PPL",
    "gn:name":"Layco",
    "gn:population":0,
    "gn:timezone":"America/La_Paz",
    "iso:country":"BO",
    "name:und_x_variant":[
        "Estancia Laico",
        "Layco"
    ],
    "wof:name":"Layco",
    "wof:placetype":"locality"
},
  "geometry": {"coordinates":[-66.14303000000001,-20.24687],"type":"Point"}
}