{
  "type": "Feature",
  "properties": {
    "gn:admin1_code":"4.0",
    "gn:asciiname":"Jihuacora",
    "gn:cc2":"BO",
    "gn:country_code":"BO",
    "gn:dem":4058,
    "gn:feature_class":"P",
    "gn:feature_code":"PPL",
    "gn:name":"Jihuacora",
    "gn:population":0,
    "gn:timezone":"America/La_Paz",
    "iso:country":"BO",
    "name:und_x_variant":[
        "Ichuacora",
        "Jiguacora",
        "Jihuacora"
    ],
    "wof:name":"Jihuacora",
    "wof:placetype":"locality"
},
  "geometry": {"coordinates":[-69.06667,-17.43333],"type":"Point"}
}