{
  "type": "Feature",
  "properties": {
    "gn:admin1_code":"8.0",
    "gn:asciiname":"Puerto Nuevo de Abapo",
    "gn:cc2":"BO",
    "gn:country_code":"BO",
    "gn:dem":754,
    "gn:feature_class":"P",
    "gn:feature_code":"PPL",
    "gn:name":"Puerto Nuevo de Abap\u00f3",
    "gn:population":0,
    "gn:timezone":"America/La_Paz",
    "iso:country":"BO",
    "name:und_x_variant":[
        "Puerto Nuevo",
        "Puerto Nuevo Abap\u00f3",
        "Puerto Nuevo de Abap\u00f3"
    ],
    "wof:name":"Puerto Nuevo de Abapo",
    "wof:placetype":"locality"
},
  "geometry": {"coordinates":[-63.48333,-18.88333],"type":"Point"}
}