{
  "type": "Feature",
  "properties": {
    "gn:admin1_code":"7.0",
    "gn:asciiname":"Nazarenillo",
    "gn:country_code":"BO",
    "gn:dem":4146,
    "gn:feature_class":"P",
    "gn:feature_code":"PPL",
    "gn:name":"Nazarenillo",
    "gn:population":0,
    "gn:timezone":"America/La_Paz",
    "iso:country":"BO",
    "wof:name":"Nazarenillo",
    "wof:placetype":"locality"
},
  "geometry": {"coordinates":[-65.91667,-21.48333],"type":"Point"}
}