{
  "type": "Feature",
  "properties": {
    "gn:admin1_code":"6.0",
    "gn:asciiname":"Rocha",
    "gn:country_code":"BO",
    "gn:dem":160,
    "gn:feature_class":"P",
    "gn:feature_code":"PPL",
    "gn:name":"Rocha",
    "gn:population":0,
    "gn:timezone":"America/La_Paz",
    "iso:country":"BO",
    "name:ceb_x_preferred":[
        "Rocha"
    ],
    "name:deu_x_preferred":[
        "Rocha"
    ],
    "name:fin_x_preferred":[
        "Rocha"
    ],
    "name:fra_x_preferred":[
        "Rocha"
    ],
    "name:heb_x_preferred":[
        "\u05e8\u05d5\u05e9\u05d4"
    ],
    "name:hsb_x_preferred":[
        "Rocha"
    ],
    "name:ita_x_preferred":[
        "Rocha"
    ],
    "name:nld_x_preferred":[
        "Rocha"
    ],
    "name:pol_x_preferred":[
        "Rocha"
    ],
    "name:por_x_preferred":[
        "Rocha"
    ],
    "name:rus_x_preferred":[
        "\u0420\u043e\u0447\u0430"
    ],
    "name:slk_x_preferred":[
        "Rocha"
    ],
    "name:spa_x_preferred":[
        "Rocha"
    ],
    "name:swe_x_preferred":[
        "Rocha"
    ],
    "wof:name":"Rocha",
    "wof:placetype":"locality"
},
  "geometry": {"coordinates":[-66.18333,-10.36667],"type":"Point"}
}