{
  "type": "Feature",
  "properties": {
    "gn:admin1_code":"07",
    "gn:asciiname":"Chitaca",
    "gn:country_code":"BO",
    "gn:dem":3520,
    "gn:feature_class":"P",
    "gn:feature_code":"PPL",
    "gn:name":"Chitaca",
    "gn:population":0,
    "gn:timezone":"America/La_Paz",
    "iso:country":"BO",
    "wof:name":"Chitaca",
    "wof:placetype":"locality"
},
  "geometry": {"coordinates":[-65.88396999999999,-19.08955],"type":"Point"}
}