{
  "type": "Feature",
  "properties": {
    "gn:admin1_code":"04",
    "gn:asciiname":"Chiacani",
    "gn:country_code":"BO",
    "gn:dem":3519,
    "gn:feature_class":"P",
    "gn:feature_code":"PPL",
    "gn:name":"Chiacani",
    "gn:population":0,
    "gn:timezone":"America/La_Paz",
    "iso:country":"BO",
    "name:spa_x_preferred":[
        "Chiacani"
    ],
    "wof:name":"Chiacani",
    "wof:placetype":"locality"
},
  "geometry": {"coordinates":[-68.74063000000001,-15.76314],"type":"Point"}
}