{
  "type": "Feature",
  "properties": {
    "gn:admin1_code":"1.0",
    "gn:asciiname":"Tacapi",
    "gn:country_code":"BO",
    "gn:dem":2667,
    "gn:feature_class":"P",
    "gn:feature_code":"PPL",
    "gn:name":"Tacapi",
    "gn:population":0,
    "gn:timezone":"America/La_Paz",
    "iso:country":"BO",
    "wof:name":"Tacapi",
    "wof:placetype":"locality"
},
  "geometry": {"coordinates":[-65.30126,-21.32068],"type":"Point"}
}