{
  "type": "Feature",
  "properties": {
    "gn:admin1_code":"04",
    "gn:asciiname":"Cochinitos",
    "gn:cc2":"BO",
    "gn:country_code":"BO",
    "gn:dem":3773,
    "gn:feature_class":"P",
    "gn:feature_code":"PPL",
    "gn:name":"Cochinitos",
    "gn:population":0,
    "gn:timezone":"America/La_Paz",
    "iso:country":"BO",
    "name:und_x_variant":[
        "Cochinito",
        "Cochinitos"
    ],
    "wof:name":"Cochinitos",
    "wof:placetype":"locality"
},
  "geometry": {"coordinates":[-67.91667,-17.28333],"type":"Point"}
}