{
  "type": "Feature",
  "properties": {
    "gn:admin1_code":"1.0",
    "gn:asciiname":"Marcavi",
    "gn:country_code":"BO",
    "gn:dem":2848,
    "gn:feature_class":"P",
    "gn:feature_code":"PPL",
    "gn:name":"Marcavi",
    "gn:population":0,
    "gn:timezone":"America/La_Paz",
    "iso:country":"BO",
    "name:und_x_variant":[
        "San Isidro de Marcavi",
        "Marcavi"
    ],
    "wof:name":"Marcavi",
    "wof:placetype":"locality"
},
  "geometry": {"coordinates":[-64.62047,-19.88252],"type":"Point"}
}