{
  "type": "Feature",
  "properties": {
    "gn:admin1_code":"06",
    "gn:asciiname":"Centro Seco",
    "gn:country_code":"BO",
    "gn:dem":286,
    "gn:feature_class":"P",
    "gn:feature_code":"PPL",
    "gn:name":"Centro Seco",
    "gn:population":0,
    "gn:timezone":"America/La_Paz",
    "iso:country":"BO",
    "wof:name":"Centro Seco",
    "wof:placetype":"locality"
},
  "geometry": {"coordinates":[-69.21311,-11.16085],"type":"Point"}
}