{
  "type": "Feature",
  "properties": {
    "gn:admin1_code":"8.0",
    "gn:asciiname":"Estancia San Bartolo",
    "gn:country_code":"BO",
    "gn:dem":124,
    "gn:feature_class":"P",
    "gn:feature_code":"PPL",
    "gn:name":"Estancia San Bartolo",
    "gn:population":0,
    "gn:timezone":"America/La_Paz",
    "iso:country":"BO",
    "wof:name":"Estancia San Bartolo",
    "wof:placetype":"locality"
},
  "geometry": {"coordinates":[-59.21666999999999,-16.71667],"type":"Point"}
}