{
  "type": "Feature",
  "properties": {
    "gn:admin1_code":"4.0",
    "gn:asciiname":"Estancia Yaropampa",
    "gn:country_code":"BO",
    "gn:dem":1558,
    "gn:feature_class":"P",
    "gn:feature_code":"PPL",
    "gn:name":"Estancia Yaropampa",
    "gn:population":0,
    "gn:timezone":"America/La_Paz",
    "iso:country":"BO",
    "wof:name":"Estancia Yaropampa",
    "wof:placetype":"locality"
},
  "geometry": {"coordinates":[-67.51666999999999,-16.38332999999999],"type":"Point"}
}