{
  "type": "Feature",
  "properties": {
    "gn:admin1_code":"7.0",
    "gn:asciiname":"Haullacuesta",
    "gn:country_code":"BO",
    "gn:dem":3630,
    "gn:feature_class":"P",
    "gn:feature_code":"PPL",
    "gn:name":"Haullacuesta",
    "gn:population":0,
    "gn:timezone":"America/La_Paz",
    "iso:country":"BO",
    "wof:name":"Haullacuesta",
    "wof:placetype":"locality"
},
  "geometry": {"coordinates":[-65.83333,-21.05],"type":"Point"}
}