{
  "type": "Feature",
  "properties": {
    "gn:admin1_code":"04",
    "gn:asciiname":"Estancia Jankho Jakka",
    "gn:country_code":"BO",
    "gn:dem":3856,
    "gn:feature_class":"P",
    "gn:feature_code":"PPL",
    "gn:name":"Estancia Jankho Jakka",
    "gn:population":0,
    "gn:timezone":"America/La_Paz",
    "iso:country":"BO",
    "wof:name":"Estancia Jankho Jakka",
    "wof:placetype":"locality"
},
  "geometry": {"coordinates":[-69.15000000000001,-16.86667000000001],"type":"Point"}
}