{
  "type": "Feature",
  "properties": {
    "gn:admin1_code":"7.0",
    "gn:asciiname":"Ichuchaca",
    "gn:country_code":"BO",
    "gn:dem":4320,
    "gn:feature_class":"P",
    "gn:feature_code":"PPL",
    "gn:name":"Ichuchaca",
    "gn:population":0,
    "gn:timezone":"America/La_Paz",
    "iso:country":"BO",
    "wof:name":"Ichuchaca",
    "wof:placetype":"locality"
},
  "geometry": {"coordinates":[-68.25,-16.05],"type":"Point"}
}