{
  "type": "Feature",
  "properties": {
    "gn:admin1_code":"7.0",
    "gn:asciiname":"Sarcari",
    "gn:country_code":"BO",
    "gn:dem":3789,
    "gn:feature_class":"P",
    "gn:feature_code":"PPL",
    "gn:name":"Sarcari",
    "gn:population":0,
    "gn:timezone":"America/La_Paz",
    "iso:country":"BO",
    "wof:name":"Sarcari",
    "wof:placetype":"locality"
},
  "geometry": {"coordinates":[-66.02171,-21.9111],"type":"Point"}
}