{
  "type": "Feature",
  "properties": {
    "gn:admin1_code":"04",
    "gn:asciiname":"Estancia Catari",
    "gn:country_code":"BO",
    "gn:dem":4192,
    "gn:feature_class":"P",
    "gn:feature_code":"PPL",
    "gn:name":"Estancia Catari",
    "gn:population":0,
    "gn:timezone":"America/La_Paz",
    "iso:country":"BO",
    "wof:name":"Estancia Catari",
    "wof:placetype":"locality"
},
  "geometry": {"coordinates":[-69.45,-17.31667],"type":"Point"}
}