{
  "type": "Feature",
  "properties": {
    "gn:admin1_code":"4.0",
    "gn:asciiname":"Estancia Huaraj Pata",
    "gn:country_code":"BO",
    "gn:dem":4647,
    "gn:feature_class":"P",
    "gn:feature_code":"PPL",
    "gn:name":"Estancia Huaraj Pata",
    "gn:population":0,
    "gn:timezone":"America/La_Paz",
    "iso:country":"BO",
    "name:und_x_variant":[
        "Huaraypata"
    ],
    "wof:name":"Estancia Huaraj Pata",
    "wof:placetype":"locality"
},
  "geometry": {"coordinates":[-69.22711,-15.10356],"type":"Point"}
}