{
  "type": "Feature",
  "properties": {
    "gn:admin1_code":"4.0",
    "gn:asciiname":"Sacacani",
    "gn:cc2":"BO",
    "gn:country_code":"BO",
    "gn:dem":3838,
    "gn:feature_class":"P",
    "gn:feature_code":"PPL",
    "gn:name":"Sacacani",
    "gn:population":0,
    "gn:timezone":"America/La_Paz",
    "iso:country":"BO",
    "name:und_x_variant":[
        "Socacani",
        "Sacacani"
    ],
    "wof:name":"Sacacani",
    "wof:placetype":"locality"
},
  "geometry": {"coordinates":[-68.81667,-17.15],"type":"Point"}
}