{
  "type": "Feature",
  "properties": {
    "gn:admin1_code":"4.0",
    "gn:asciiname":"Mirmapata",
    "gn:country_code":"BO",
    "gn:dem":4149,
    "gn:feature_class":"P",
    "gn:feature_code":"PPL",
    "gn:name":"Mirmapata",
    "gn:population":0,
    "gn:timezone":"America/La_Paz",
    "iso:country":"BO",
    "name:spa_x_preferred":[
        "Mirmapata"
    ],
    "name:spa_x_variant":[
        "Mirma Pata"
    ],
    "wof:name":"Mirmapata",
    "wof:placetype":"locality"
},
  "geometry": {"coordinates":[-69.07182,-15.71118],"type":"Point"}
}