{
  "type": "Feature",
  "properties": {
    "gn:admin1_code":"6.0",
    "gn:asciiname":"Policia",
    "gn:country_code":"BO",
    "gn:dem":283,
    "gn:feature_class":"P",
    "gn:feature_code":"PPL",
    "gn:name":"Polic\u00eda",
    "gn:population":0,
    "gn:timezone":"America/La_Paz",
    "iso:country":"BO",
    "wof:name":"Policia",
    "wof:placetype":"locality"
},
  "geometry": {"coordinates":[-68.86667,-11.76667],"type":"Point"}
}