{
  "type": "Feature",
  "properties": {
    "gn:admin1_code":"06",
    "gn:asciiname":"Las Pampas",
    "gn:country_code":"BO",
    "gn:dem":210,
    "gn:feature_class":"P",
    "gn:feature_code":"PPL",
    "gn:name":"Las Pampas",
    "gn:population":0,
    "gn:timezone":"America/La_Paz",
    "iso:country":"BO",
    "name:spa_x_preferred":[
        "Las Pampas"
    ],
    "wof:name":"Las Pampas",
    "wof:placetype":"locality"
},
  "geometry": {"coordinates":[-68.11494999999999,-11.58753],"type":"Point"}
}