{
  "type": "Feature",
  "properties": {
    "gn:admin1_code":"06",
    "gn:asciiname":"Abuna Chico",
    "gn:country_code":"BO",
    "gn:dem":184,
    "gn:feature_class":"P",
    "gn:feature_code":"PPL",
    "gn:name":"Abuna Chico",
    "gn:population":0,
    "gn:timezone":"America/La_Paz",
    "iso:country":"BO",
    "name:spa_x_preferred":[
        "Abuna Chico"
    ],
    "wof:name":"Abuna Chico",
    "wof:placetype":"locality"
},
  "geometry": {"coordinates":[-67.15598,-10.63429],"type":"Point"}
}