{
  "type": "Feature",
  "properties": {
    "gn:admin1_code":"4.0",
    "gn:asciiname":"Saihuani",
    "gn:cc2":"BO",
    "gn:country_code":"BO",
    "gn:dem":3615,
    "gn:feature_class":"P",
    "gn:feature_code":"PPL",
    "gn:name":"Saihuani",
    "gn:population":0,
    "gn:timezone":"America/La_Paz",
    "iso:country":"BO",
    "name:und_x_variant":[
        "Estancia Saihuani",
        "Saihuani"
    ],
    "wof:name":"Saihuani",
    "wof:placetype":"locality"
},
  "geometry": {"coordinates":[-69.03333000000001,-15.43333],"type":"Point"}
}