{
  "type": "Feature",
  "properties": {
    "gn:admin1_code":"4.0",
    "gn:asciiname":"Estancia Porque",
    "gn:country_code":"BO",
    "gn:dem":4251,
    "gn:feature_class":"P",
    "gn:feature_code":"PPL",
    "gn:name":"Estancia Porque",
    "gn:population":0,
    "gn:timezone":"America/La_Paz",
    "iso:country":"BO",
    "wof:name":"Estancia Porque",
    "wof:placetype":"locality"
},
  "geometry": {"coordinates":[-69.18333,-17.71667],"type":"Point"}
}