{
  "type": "Feature",
  "properties": {
    "gn:admin1_code":"06",
    "gn:asciiname":"Florecitas",
    "gn:country_code":"BO",
    "gn:dem":186,
    "gn:feature_class":"P",
    "gn:feature_code":"PPL",
    "gn:name":"Florecitas",
    "gn:population":0,
    "gn:timezone":"America/La_Paz",
    "iso:country":"BO",
    "name:spa_x_preferred":[
        "Florecitas"
    ],
    "wof:name":"Florecitas",
    "wof:placetype":"locality"
},
  "geometry": {"coordinates":[-68.08457,-11.53714],"type":"Point"}
}