{
  "type": "Feature",
  "properties": {
    "gn:admin1_code":"01",
    "gn:asciiname":"Camblaya",
    "gn:country_code":"BO",
    "gn:dem":3154,
    "gn:feature_class":"P",
    "gn:feature_code":"PPL",
    "gn:name":"Camblaya",
    "gn:population":0,
    "gn:timezone":"America/La_Paz",
    "iso:country":"BO",
    "wof:name":"Camblaya",
    "wof:placetype":"locality"
},
  "geometry": {"coordinates":[-65.34999999999999,-21.08333],"type":"Point"}
}