{
  "type": "Feature",
  "properties": {
    "gn:admin1_code":"06",
    "gn:asciiname":"Tabocau",
    "gn:country_code":"BO",
    "gn:dem":208,
    "gn:feature_class":"P",
    "gn:feature_code":"PPL",
    "gn:name":"Tabocau",
    "gn:population":0,
    "gn:timezone":"America/La_Paz",
    "iso:country":"BO",
    "name:spa_x_preferred":[
        "Tabocau"
    ],
    "wof:name":"Tabocau",
    "wof:placetype":"locality"
},
  "geometry": {"coordinates":[-67.71263,-10.77016],"type":"Point"}
}