{
  "type": "Feature",
  "properties": {
    "gn:admin1_code":"7.0",
    "gn:asciiname":"Mosaj Rocra",
    "gn:country_code":"BO",
    "gn:dem":2273,
    "gn:feature_class":"P",
    "gn:feature_code":"PPL",
    "gn:name":"Mosaj Rocra",
    "gn:population":0,
    "gn:timezone":"America/La_Paz",
    "iso:country":"BO",
    "wof:name":"Mosaj Rocra",
    "wof:placetype":"locality"
},
  "geometry": {"coordinates":[-65.21666999999999,-19.33333],"type":"Point"}
}