{
  "type": "Feature",
  "properties": {
    "gn:admin1_code":"8.0",
    "gn:asciiname":"Pozo Victoriano",
    "gn:country_code":"BO",
    "gn:dem":371,
    "gn:feature_class":"P",
    "gn:feature_code":"PPL",
    "gn:name":"Pozo Victoriano",
    "gn:population":0,
    "gn:timezone":"America/La_Paz",
    "iso:country":"BO",
    "wof:name":"Pozo Victoriano",
    "wof:placetype":"locality"
},
  "geometry": {"coordinates":[-62.81667,-18.63333],"type":"Point"}
}