{
  "type": "Feature",
  "properties": {
    "gn:admin1_code":"04",
    "gn:asciiname":"Ayo Ayo",
    "gn:country_code":"BO",
    "gn:dem":3888,
    "gn:feature_class":"P",
    "gn:feature_code":"PPL",
    "gn:name":"Ayo Ayo",
    "gn:population":0,
    "gn:timezone":"America/La_Paz",
    "iso:country":"BO",
    "name:ceb_x_preferred":[
        "Ayo Ayo"
    ],
    "name:deu_x_preferred":[
        "Ayo Ayo"
    ],
    "name:que_x_preferred":[
        "Ayu Ayu"
    ],
    "name:sco_x_preferred":[
        "Ayo Ayo"
    ],
    "name:swe_x_preferred":[
        "Ayo Ayo"
    ],
    "wof:name":"Ayo Ayo",
    "wof:placetype":"locality"
},
  "geometry": {"coordinates":[-68.00623,-17.0937],"type":"Point"}
}