{
  "type": "Feature",
  "properties": {
    "gn:admin1_code":"4.0",
    "gn:asciiname":"Estancia Sucanavi",
    "gn:country_code":"BO",
    "gn:dem":4153,
    "gn:feature_class":"P",
    "gn:feature_code":"PPL",
    "gn:name":"Estancia Sucanavi",
    "gn:population":0,
    "gn:timezone":"America/La_Paz",
    "iso:country":"BO",
    "wof:name":"Estancia Sucanavi",
    "wof:placetype":"locality"
},
  "geometry": {"coordinates":[-68.06667,-16.91667],"type":"Point"}
}