{
  "type": "Feature",
  "properties": {
    "gn:admin1_code":"1.0",
    "gn:asciiname":"Villca-Villca",
    "gn:country_code":"BO",
    "gn:dem":2108,
    "gn:feature_class":"P",
    "gn:feature_code":"PPL",
    "gn:name":"Villca-Villca",
    "gn:population":0,
    "gn:timezone":"America/La_Paz",
    "iso:country":"BO",
    "wof:name":"Villca-Villca",
    "wof:placetype":"locality"
},
  "geometry": {"coordinates":[-64.31667,-19.45],"type":"Point"}
}