{
  "type": "Feature",
  "properties": {
    "gn:admin1_code":"7.0",
    "gn:asciiname":"Ramadillas",
    "gn:country_code":"BO",
    "gn:dem":4164,
    "gn:feature_class":"P",
    "gn:feature_code":"PPL",
    "gn:name":"Ramadillas",
    "gn:population":0,
    "gn:timezone":"America/La_Paz",
    "iso:country":"BO",
    "wof:name":"Ramadillas",
    "wof:placetype":"locality"
},
  "geometry": {"coordinates":[-66.43333,-21.41667],"type":"Point"}
}