{
  "type": "Feature",
  "properties": {
    "gn:admin1_code":"8.0",
    "gn:asciiname":"Estancia Florida",
    "gn:country_code":"BO",
    "gn:dem":273,
    "gn:feature_class":"P",
    "gn:feature_code":"PPL",
    "gn:name":"Estancia Florida",
    "gn:population":0,
    "gn:timezone":"America/La_Paz",
    "iso:country":"BO",
    "wof:name":"Estancia Florida",
    "wof:placetype":"locality"
},
  "geometry": {"coordinates":[-59.88333000000001,-16.28333],"type":"Point"}
}