{
  "type": "Feature",
  "properties": {
    "gn:admin1_code":"7.0",
    "gn:asciiname":"Lorayoc",
    "gn:cc2":"BO",
    "gn:country_code":"BO",
    "gn:dem":3374,
    "gn:feature_class":"P",
    "gn:feature_code":"PPL",
    "gn:name":"Lorayoc",
    "gn:population":0,
    "gn:timezone":"America/La_Paz",
    "iso:country":"BO",
    "name:und_x_variant":[
        "Loraiyoc",
        "Lorayoc"
    ],
    "wof:name":"Lorayoc",
    "wof:placetype":"locality"
},
  "geometry": {"coordinates":[-65.84999999999999,-21.31667],"type":"Point"}
}