{
  "type": "Feature",
  "properties": {
    "gn:admin1_code":"9.0",
    "gn:asciiname":"Itavere",
    "gn:country_code":"BO",
    "gn:dem":594,
    "gn:feature_class":"P",
    "gn:feature_code":"PPL",
    "gn:name":"Itavere",
    "gn:population":0,
    "gn:timezone":"America/La_Paz",
    "iso:country":"BO",
    "wof:name":"Itavere",
    "wof:placetype":"locality"
},
  "geometry": {"coordinates":[-63.96682,-21.18842],"type":"Point"}
}