{
  "type": "Feature",
  "properties": {
    "gn:admin1_code":"04",
    "gn:asciiname":"Batalla",
    "gn:country_code":"BO",
    "gn:dem":3852,
    "gn:feature_class":"P",
    "gn:feature_code":"PPL",
    "gn:name":"Batalla",
    "gn:population":0,
    "gn:timezone":"America/La_Paz",
    "iso:country":"BO",
    "name:spa_x_preferred":[
        "Batalla"
    ],
    "wof:name":"Batalla",
    "wof:placetype":"locality"
},
  "geometry": {"coordinates":[-68.53143,-16.29982],"type":"Point"}
}