{
  "type": "Feature",
  "properties": {
    "gn:admin1_code":"1.0",
    "gn:asciiname":"Rosa",
    "gn:country_code":"BO",
    "gn:dem":2688,
    "gn:feature_class":"P",
    "gn:feature_code":"PPL",
    "gn:name":"Rosa",
    "gn:population":0,
    "gn:timezone":"America/La_Paz",
    "iso:country":"BO",
    "name:und_x_variant":[
        "Estancia Rosa",
        "Rosa"
    ],
    "wof:name":"Rosa",
    "wof:placetype":"locality"
},
  "geometry": {"coordinates":[-64.64945,-19.1898],"type":"Point"}
}