{
  "type": "Feature",
  "properties": {
    "gn:admin1_code":"01",
    "gn:asciiname":"Cusi Huasi",
    "gn:country_code":"BO",
    "gn:dem":3061,
    "gn:feature_class":"P",
    "gn:feature_code":"PPL",
    "gn:name":"Cusi Huasi",
    "gn:population":0,
    "gn:timezone":"America/La_Paz",
    "iso:country":"BO",
    "wof:name":"Cusi Huasi",
    "wof:placetype":"locality"
},
  "geometry": {"coordinates":[-64.99826,-19.12435],"type":"Point"}
}