{
  "type": "Feature",
  "properties": {
    "gn:admin1_code":"04",
    "gn:asciiname":"Calanganchi Centro",
    "gn:country_code":"BO",
    "gn:dem":3855,
    "gn:feature_class":"P",
    "gn:feature_code":"PPL",
    "gn:name":"Calanganchi Centro",
    "gn:population":0,
    "gn:timezone":"America/La_Paz",
    "iso:country":"BO",
    "name:spa_x_preferred":[
        "Calanganchi Centro"
    ],
    "name:spa_x_variant":[
        "Comunidad Kalancachi",
        "Estancia Kalancachi"
    ],
    "wof:name":"Calanganchi Centro",
    "wof:placetype":"locality"
},
  "geometry": {"coordinates":[-69.25506,-15.63542],"type":"Point"}
}