{
  "type": "Feature",
  "properties": {
    "gn:admin1_code":"7.0",
    "gn:asciiname":"Uyuniviejo",
    "gn:country_code":"BO",
    "gn:dem":3997,
    "gn:feature_class":"P",
    "gn:feature_code":"PPL",
    "gn:name":"Uyuniviejo",
    "gn:population":0,
    "gn:timezone":"America/La_Paz",
    "iso:country":"BO",
    "wof:name":"Uyuniviejo",
    "wof:placetype":"locality"
},
  "geometry": {"coordinates":[-66.66667,-20.43333],"type":"Point"}
}