{
  "type": "Feature",
  "properties": {
    "gn:admin1_code":"01",
    "gn:asciiname":"Comunidad Sanchi Chunchu",
    "gn:country_code":"BO",
    "gn:dem":2210,
    "gn:feature_class":"P",
    "gn:feature_code":"PPL",
    "gn:name":"Comunidad Sanchi Chunchu",
    "gn:population":0,
    "gn:timezone":"America/La_Paz",
    "iso:country":"BO",
    "wof:name":"Comunidad Sanchi Chunchu",
    "wof:placetype":"locality"
},
  "geometry": {"coordinates":[-64.64353,-20.22536],"type":"Point"}
}