{
  "type": "Feature",
  "properties": {
    "gn:admin1_code":"8.0",
    "gn:asciiname":"La Chalera",
    "gn:country_code":"BO",
    "gn:dem":89,
    "gn:feature_class":"P",
    "gn:feature_code":"PPL",
    "gn:name":"La Chalera",
    "gn:population":0,
    "gn:timezone":"America/La_Paz",
    "iso:country":"BO",
    "wof:name":"La Chalera",
    "wof:placetype":"locality"
},
  "geometry": {"coordinates":[-58.03333000000001,-19.23333],"type":"Point"}
}