{
  "type": "Feature",
  "properties": {
    "gn:admin1_code":"2.0",
    "gn:asciiname":"Puerto Mateito",
    "gn:country_code":"BO",
    "gn:dem":1441,
    "gn:feature_class":"P",
    "gn:feature_code":"PPL",
    "gn:name":"Puerto Mateito",
    "gn:population":0,
    "gn:timezone":"America/La_Paz",
    "iso:country":"BO",
    "wof:name":"Puerto Mateito",
    "wof:placetype":"locality"
},
  "geometry": {"coordinates":[-64.66667,-17.73333],"type":"Point"}
}