{
  "type": "Feature",
  "properties": {
    "gn:admin1_code":"04",
    "gn:asciiname":"Comunidad Jajaya",
    "gn:country_code":"BO",
    "gn:dem":3972,
    "gn:feature_class":"P",
    "gn:feature_code":"PPL",
    "gn:name":"Comunidad Jajaya",
    "gn:population":0,
    "gn:timezone":"America/La_Paz",
    "iso:country":"BO",
    "name:spa_x_preferred":[
        "Comunidad Jajaya"
    ],
    "name:spa_x_variant":[
        "Estancia Jajaya",
        "Jajaya"
    ],
    "wof:name":"Comunidad Jajaya",
    "wof:placetype":"locality"
},
  "geometry": {"coordinates":[-69.13065999999999,-15.49039],"type":"Point"}
}