{
  "type": "Feature",
  "properties": {
    "gn:admin1_code":"09",
    "gn:asciiname":"Canasmoro",
    "gn:country_code":"BO",
    "gn:dem":2076,
    "gn:feature_class":"P",
    "gn:feature_code":"PPL",
    "gn:name":"Canasmoro",
    "gn:population":0,
    "gn:timezone":"America/La_Paz",
    "iso:country":"BO",
    "wof:name":"Canasmoro",
    "wof:placetype":"locality"
},
  "geometry": {"coordinates":[-64.75780999999999,-21.34422],"type":"Point"}
}