{
  "type": "Feature",
  "properties": {
    "gn:admin1_code":"1.0",
    "gn:asciiname":"Real Pampa",
    "gn:country_code":"BO",
    "gn:dem":2518,
    "gn:feature_class":"P",
    "gn:feature_code":"PPL",
    "gn:name":"Real Pampa",
    "gn:population":0,
    "gn:timezone":"America/La_Paz",
    "iso:country":"BO",
    "wof:name":"Real Pampa",
    "wof:placetype":"locality"
},
  "geometry": {"coordinates":[-64.19694,-19.43323],"type":"Point"}
}