{
  "type": "Feature",
  "properties": {
    "gn:admin1_code":"08",
    "gn:asciiname":"Cachuelas",
    "gn:cc2":"BO",
    "gn:country_code":"BO",
    "gn:dem":227,
    "gn:feature_class":"P",
    "gn:feature_code":"PPL",
    "gn:name":"Cachuelas",
    "gn:population":0,
    "gn:timezone":"America/La_Paz",
    "iso:country":"BO",
    "name:und_x_variant":[
        "Cachuela",
        "Cachuelas"
    ],
    "wof:name":"Cachuelas",
    "wof:placetype":"locality"
},
  "geometry": {"coordinates":[-62.55,-14.65],"type":"Point"}
}