{
  "type": "Feature",
  "properties": {
    "gn:admin1_code":"06",
    "gn:asciiname":"Las Grotas",
    "gn:country_code":"BO",
    "gn:dem":193,
    "gn:feature_class":"P",
    "gn:feature_code":"PPL",
    "gn:name":"Las Grotas",
    "gn:population":0,
    "gn:timezone":"America/La_Paz",
    "iso:country":"BO",
    "name:spa_x_preferred":[
        "Las Grotas"
    ],
    "wof:name":"Las Grotas",
    "wof:placetype":"locality"
},
  "geometry": {"coordinates":[-67.51955,-10.56966],"type":"Point"}
}