{
  "type": "Feature",
  "properties": {
    "gn:admin1_code":"7.0",
    "gn:asciiname":"Quillconi",
    "gn:country_code":"BO",
    "gn:dem":3769,
    "gn:feature_class":"P",
    "gn:feature_code":"PPL",
    "gn:name":"Quillconi",
    "gn:population":0,
    "gn:timezone":"America/La_Paz",
    "iso:country":"BO",
    "wof:name":"Quillconi",
    "wof:placetype":"locality"
},
  "geometry": {"coordinates":[-66.89312,-21.11886],"type":"Point"}
}