{
  "type": "Feature",
  "properties": {
    "gn:admin1_code":"04",
    "gn:asciiname":"Acalaca",
    "gn:country_code":"BO",
    "gn:dem":1446,
    "gn:feature_class":"P",
    "gn:feature_code":"PPL",
    "gn:name":"Acalaca",
    "gn:population":0,
    "gn:timezone":"America/La_Paz",
    "iso:country":"BO",
    "name:und_x_variant":[
        "Hualaca",
        "Hoalaca",
        "Acalaca"
    ],
    "wof:name":"Acalaca",
    "wof:placetype":"locality"
},
  "geometry": {"coordinates":[-68.36412,-14.80454],"type":"Point"}
}