{
  "type": "Feature",
  "properties": {
    "gn:admin1_code":"8.0",
    "gn:asciiname":"Vallecito",
    "gn:country_code":"BO",
    "gn:dem":1778,
    "gn:feature_class":"P",
    "gn:feature_code":"PPL",
    "gn:name":"Vallecito",
    "gn:population":0,
    "gn:timezone":"America/La_Paz",
    "iso:country":"BO",
    "name:ceb_x_preferred":[
        "Vallecito"
    ],
    "name:deu_x_preferred":[
        "Vallecito"
    ],
    "name:swe_x_preferred":[
        "Vallecito"
    ],
    "wof:name":"Vallecito",
    "wof:placetype":"locality"
},
  "geometry": {"coordinates":[-63.86198,-18.24561],"type":"Point"}
}