{
  "type": "Feature",
  "properties": {
    "iso:country":"BO",
    "name:bul_x_preferred":[
        "\u0421\u0430\u043c\u0430\u0438\u043f\u0430\u0442\u0430"
    ],
    "name:cat_x_preferred":[
        "Samaipata"
    ],
    "name:chi_x_preferred":[
        "\u85a9\u9081\u5e15\u5854"
    ],
    "name:dut_x_preferred":[
        "Samaipata"
    ],
    "name:eng_x_preferred":[
        "Samaipata"
    ],
    "name:fre_x_preferred":[
        "Samaipata"
    ],
    "name:ger_x_preferred":[
        "Samaipata"
    ],
    "name:ita_x_preferred":[
        "Samaipata"
    ],
    "name:jpn_x_preferred":[
        "\u30b5\u30de\u30a4\u30d1\u30bf"
    ],
    "name:lit_x_preferred":[
        "Samaipata"
    ],
    "name:pol_x_preferred":[
        "Samaipata"
    ],
    "name:por_x_preferred":[
        "Samaipata"
    ],
    "name:que_x_preferred":[
        "Samaypata"
    ],
    "name:spa_x_preferred":[
        "Samaipata"
    ],
    "name:swe_x_preferred":[
        "Samaipata"
    ],
    "name:war_x_preferred":[
        "Samaipata"
    ],
    "ne:ADM0CAP":0.0,
    "ne:ADM0NAME":"Bolivia",
    "ne:ADM0_A3":"BOL",
    "ne:ADM1NAME":"Santa Cruz",
    "ne:ADMIN1_COD":0,
    "ne:CAPALT":0,
    "ne:CHANGED":0,
    "ne:CHECKME":0,
    "ne:COMPARE":0,
    "ne:DIFFASCII":0,
    "ne:ELEVATION":0.0,
    "ne:FEATURECLA":"Populated place",
    "ne:GEONAMEID":-1,
    "ne:GEONAMESNO":"No GeoNames match due to small population, not in GeoNames, or poor NEV placement.",
    "ne:GN_POP":0,
    "ne:GTOPO30":0.0,
    "ne:ISO_A2":"BO",
    "ne:LABELRANK":6,
    "ne:LATITUDE":-18.180041,
    "ne:LONGITUDE":-63.77002,
    "ne:LS_MATCH":0,
    "ne:LS_NAME":"Samaipata",
    "ne:MAX_AREAKM":0.0,
    "ne:MAX_AREAMI":0.0,
    "ne:MAX_BBXMAX":0.0,
    "ne:MAX_BBXMIN":0.0,
    "ne:MAX_BBYMAX":0.0,
    "ne:MAX_BBYMIN":0.0,
    "ne:MAX_NATSCA":0.0,
    "ne:MAX_PERKM":0.0,
    "ne:MAX_PERMI":0.0,
    "ne:MAX_POP10":0,
    "ne:MAX_POP20":0,
    "ne:MAX_POP300":0,
    "ne:MAX_POP310":0,
    "ne:MAX_POP50":0,
    "ne:MEAN_BBXC":0.0,
    "ne:MEAN_BBYC":0.0,
    "ne:MEGACITY":0,
    "ne:MIN_AREAKM":0.0,
    "ne:MIN_AREAMI":0.0,
    "ne:MIN_BBXMAX":0.0,
    "ne:MIN_BBXMIN":0.0,
    "ne:MIN_BBYMAX":0.0,
    "ne:MIN_BBYMIN":0.0,
    "ne:MIN_PERKM":0.0,
    "ne:MIN_PERMI":0.0,
    "ne:NAME":"Samaipata",
    "ne:NAMEASCII":"Samaipata",
    "ne:NAMEDIFF":0,
    "ne:NATSCALE":10,
    "ne:POP1950":0,
    "ne:POP1955":0,
    "ne:POP1960":0,
    "ne:POP1965":0,
    "ne:POP1970":0,
    "ne:POP1975":0,
    "ne:POP1980":0,
    "ne:POP1985":0,
    "ne:POP1990":0,
    "ne:POP1995":0,
    "ne:POP2000":0,
    "ne:POP2005":0,
    "ne:POP2010":0,
    "ne:POP2015":0,
    "ne:POP2020":0,
    "ne:POP2025":0,
    "ne:POP2050":0,
    "ne:POP_MAX":2926,
    "ne:POP_MIN":2926,
    "ne:POP_OTHER":0,
    "ne:RANK_MAX":4,
    "ne:RANK_MIN":4,
    "ne:SCALERANK":8,
    "ne:SOV0NAME":"Bolivia",
    "ne:SOV_A3":"BOL",
    "ne:UN_FID":0,
    "ne:UN_LAT":0.0,
    "ne:UN_LONG":0.0,
    "ne:WORLDCITY":0,
    "ne:min_zoom":7.0,
    "wof:name":"Samaipata",
    "wof:placetype":"locality"
},
  "geometry": {"coordinates":[-63.77001998051088,-18.18004148475677],"type":"Point"}
}