{
  "type": "Feature",
  "properties": {
    "gn:admin1_code":"6.0",
    "gn:asciiname":"Linea Para Abajo",
    "gn:country_code":"BO",
    "gn:dem":178,
    "gn:feature_class":"P",
    "gn:feature_code":"PPL",
    "gn:name":"Linea Para Abajo",
    "gn:population":0,
    "gn:timezone":"America/La_Paz",
    "iso:country":"BO",
    "name:spa_x_preferred":[
        "Linea Para Abajo"
    ],
    "name:und_x_variant":[
        "Miapara"
    ],
    "wof:name":"Linea Para Abajo",
    "wof:placetype":"locality"
},
  "geometry": {"coordinates":[-67.81305,-10.69803],"type":"Point"}
}