{
  "type": "Feature",
  "properties": {
    "gn:admin1_code":"06",
    "gn:asciiname":"Suma Uma",
    "gn:country_code":"BO",
    "gn:dem":172,
    "gn:feature_class":"P",
    "gn:feature_code":"PPL",
    "gn:name":"Suma Uma",
    "gn:population":0,
    "gn:timezone":"America/La_Paz",
    "iso:country":"BO",
    "name:spa_x_preferred":[
        "Suma Uma"
    ],
    "wof:name":"Suma Uma",
    "wof:placetype":"locality"
},
  "geometry": {"coordinates":[-67.79089,-10.70762],"type":"Point"}
}