{
  "type": "Feature",
  "properties": {
    "gn:admin1_code":"01",
    "gn:asciiname":"Estancia Apacheta",
    "gn:country_code":"BO",
    "gn:dem":3376,
    "gn:feature_class":"P",
    "gn:feature_code":"PPL",
    "gn:name":"Estancia Apacheta",
    "gn:population":0,
    "gn:timezone":"America/La_Paz",
    "iso:country":"BO",
    "wof:name":"Estancia Apacheta",
    "wof:placetype":"locality"
},
  "geometry": {"coordinates":[-65.10311,-20.13053],"type":"Point"}
}