{
  "type": "Feature",
  "properties": {
    "gn:admin1_code":"5.0",
    "gn:asciiname":"Machacamarca",
    "gn:country_code":"BO",
    "gn:dem":3705,
    "gn:feature_class":"P",
    "gn:feature_code":"PPL",
    "gn:name":"Machacamarca",
    "gn:population":0,
    "gn:timezone":"America/La_Paz",
    "iso:country":"BO",
    "wof:name":"Machacamarca",
    "wof:placetype":"locality"
},
  "geometry": {"coordinates":[-67.32084,-18.38486],"type":"Point"}
}