{
  "type": "Feature",
  "properties": {
    "gn:admin1_code":"5.0",
    "gn:asciiname":"Huayllamarca",
    "gn:country_code":"BO",
    "gn:dem":3872,
    "gn:feature_class":"P",
    "gn:feature_code":"PPL",
    "gn:name":"Huayllamarca",
    "gn:population":0,
    "gn:timezone":"America/La_Paz",
    "iso:country":"BO",
    "name:aym_x_preferred":[
        "Wayllamarka"
    ],
    "name:spa_x_preferred":[
        "Huayllamarca"
    ],
    "name:und_x_variant":[
        "Huaillamarca",
        "Huayllamarca",
        "Huaylla Marca"
    ],
    "wof:name":"Huayllamarca",
    "wof:placetype":"locality"
},
  "geometry": {"coordinates":[-67.94056999999999,-17.83449],"type":"Point"}
}