{
  "type": "Feature",
  "properties": {
    "gn:admin1_code":"07",
    "gn:asciiname":"Chapi",
    "gn:country_code":"BO",
    "gn:dem":3023,
    "gn:feature_class":"P",
    "gn:feature_code":"PPL",
    "gn:name":"Chapi",
    "gn:population":0,
    "gn:timezone":"America/La_Paz",
    "iso:country":"BO",
    "wof:name":"Chapi",
    "wof:placetype":"locality"
},
  "geometry": {"coordinates":[-65.55,-20.68333],"type":"Point"}
}