{
  "type": "Feature",
  "properties": {
    "gn:admin1_code":"8.0",
    "gn:asciiname":"Galpon Suarez",
    "gn:cc2":"BO",
    "gn:country_code":"BO",
    "gn:dem":214,
    "gn:feature_class":"P",
    "gn:feature_code":"PPL",
    "gn:name":"Galp\u00f3n Su\u00e1rez",
    "gn:population":0,
    "gn:timezone":"America/La_Paz",
    "iso:country":"BO",
    "name:und_x_variant":[
        "Galp\u00f3n Su\u00e1ez",
        "Galp\u00f3n Su\u00e1rez"
    ],
    "wof:name":"Galpon Suarez",
    "wof:placetype":"locality"
},
  "geometry": {"coordinates":[-63.61666999999999,-16.66667],"type":"Point"}
}