{
  "type": "Feature",
  "properties": {
    "gn:admin1_code":"06",
    "gn:asciiname":"Buzeta",
    "gn:country_code":"BO",
    "gn:dem":176,
    "gn:feature_class":"P",
    "gn:feature_code":"PPL",
    "gn:name":"Buzeta",
    "gn:population":0,
    "gn:timezone":"America/La_Paz",
    "iso:country":"BO",
    "wof:name":"Buzeta",
    "wof:placetype":"locality"
},
  "geometry": {"coordinates":[-66.46666999999999,-11.21667],"type":"Point"}
}