{
  "type": "Feature",
  "properties": {
    "gn:admin1_code":"06",
    "gn:asciiname":"Buzeta",
    "gn:country_code":"BO",
    "gn:dem":176,
    "gn:feature_class":"P",
    "gn:feature_code":"PPL",
    "gn:name":"Buzeta",
    "gn:population":0,
    "gn:timezone":"America/La_Paz",
    "iso:country":"BO",
    "name:bos_x_preferred":[
        "Buzeta"
    ],
    "name:fra_x_preferred":[
        "Buzeta"
    ],
    "name:hrv_x_preferred":[
        "Buzeta"
    ],
    "name:hun_x_preferred":[
        "Buzeta"
    ],
    "name:nld_x_preferred":[
        "Buzeta"
    ],
    "name:slv_x_preferred":[
        "Buzeta"
    ],
    "name:spa_x_preferred":[
        "Buzeta"
    ],
    "name:srp_x_preferred":[
        "\u0411\u0443\u0437\u0435\u0442\u0430"
    ],
    "name:ukr_x_preferred":[
        "\u0411\u0443\u0437\u0435\u0442\u0430"
    ],
    "wof:name":"Buzeta",
    "wof:placetype":"locality"
},
  "geometry": {"coordinates":[-66.46666999999999,-11.21667],"type":"Point"}
}