{
  "type": "Feature",
  "properties": {
    "gn:admin1_code":"02",
    "gn:asciiname":"Bolson",
    "gn:country_code":"BO",
    "gn:dem":2060,
    "gn:feature_class":"P",
    "gn:feature_code":"PPL",
    "gn:name":"Bols\u00f3n",
    "gn:population":0,
    "gn:timezone":"America/La_Paz",
    "iso:country":"BO",
    "name:nno_x_preferred":[
        "Bolson"
    ],
    "name:pol_x_preferred":[
        "Bolson"
    ],
    "name:slk_x_preferred":[
        "Bolson"
    ],
    "name:spa_x_preferred":[
        "Bols\u00f3n"
    ],
    "name:ukr_x_preferred":[
        "\u0411\u043e\u043b\u044c\u0441\u043e\u043d\u0438"
    ],
    "wof:name":"Bolson",
    "wof:placetype":"locality"
},
  "geometry": {"coordinates":[-64.68333,-18.03333],"type":"Point"}
}