{
  "type": "Feature",
  "properties": {
    "gn:admin1_code":"01",
    "gn:asciiname":"Chunchulli",
    "gn:country_code":"BO",
    "gn:dem":3028,
    "gn:feature_class":"P",
    "gn:feature_code":"PPL",
    "gn:name":"Chunchulli",
    "gn:population":0,
    "gn:timezone":"America/La_Paz",
    "iso:country":"BO",
    "wof:name":"Chunchulli",
    "wof:placetype":"locality"
},
  "geometry": {"coordinates":[-64.85767,-20.66479],"type":"Point"}
}