{
  "type": "Feature",
  "properties": {
    "gn:admin1_code":"4.0",
    "gn:asciiname":"Pusillani",
    "gn:country_code":"BO",
    "gn:dem":3273,
    "gn:feature_class":"P",
    "gn:feature_code":"PPL",
    "gn:name":"Pusillani",
    "gn:population":0,
    "gn:timezone":"America/La_Paz",
    "iso:country":"BO",
    "name:und_x_variant":[
        "Estancia Pusillani",
        "Pusillani"
    ],
    "wof:name":"Pusillani",
    "wof:placetype":"locality"
},
  "geometry": {"coordinates":[-68.72996999999999,-15.45957],"type":"Point"}
}