{
  "type": "Feature",
  "properties": {
    "gn:admin1_code":"4.0",
    "gn:asciiname":"Pahui",
    "gn:cc2":"BO",
    "gn:country_code":"BO",
    "gn:dem":3753,
    "gn:feature_class":"P",
    "gn:feature_code":"PPL",
    "gn:name":"Pahui",
    "gn:population":0,
    "gn:timezone":"America/La_Paz",
    "iso:country":"BO",
    "name:und_x_variant":[
        "Estancia Pahui",
        "Pahui"
    ],
    "wof:name":"Pahui",
    "wof:placetype":"locality"
},
  "geometry": {"coordinates":[-67.84999999999999,-17.53333],"type":"Point"}
}