{
  "type": "Feature",
  "properties": {
    "gn:admin1_code":"7.0",
    "gn:asciiname":"Pornon",
    "gn:country_code":"BO",
    "gn:dem":4249,
    "gn:feature_class":"P",
    "gn:feature_code":"PPL",
    "gn:name":"Porn\u00f3n",
    "gn:population":0,
    "gn:timezone":"America/La_Paz",
    "iso:country":"BO",
    "wof:name":"Pornon",
    "wof:placetype":"locality"
},
  "geometry": {"coordinates":[-66.68333,-20.38333],"type":"Point"}
}