{
  "type": "Feature",
  "properties": {
    "gn:admin1_code":"8.0",
    "gn:asciiname":"La Barrera",
    "gn:cc2":"BO",
    "gn:country_code":"BO",
    "gn:dem":1220,
    "gn:feature_class":"P",
    "gn:feature_code":"PPL",
    "gn:name":"La Barrera",
    "gn:population":0,
    "gn:timezone":"America/La_Paz",
    "iso:country":"BO",
    "name:und_x_variant":[
        "Barrera",
        "La Barrera"
    ],
    "wof:name":"La Barrera",
    "wof:placetype":"locality"
},
  "geometry": {"coordinates":[-63.81667,-18.78333],"type":"Point"}
}