{
  "type": "Feature",
  "properties": {
    "gn:admin1_code":"7.0",
    "gn:asciiname":"Uquilla",
    "gn:country_code":"BO",
    "gn:dem":3937,
    "gn:feature_class":"P",
    "gn:feature_code":"PPL",
    "gn:name":"Uquilla",
    "gn:population":0,
    "gn:timezone":"America/La_Paz",
    "iso:country":"BO",
    "name:und_x_variant":[
        "Estancia Uquilla",
        "Uquilla"
    ],
    "wof:name":"Uquilla",
    "wof:placetype":"locality"
},
  "geometry": {"coordinates":[-68.16897,-20.84135],"type":"Point"}
}