{
  "type": "Feature",
  "properties": {
    "gn:admin1_code":"1.0",
    "gn:asciiname":"Santa Barvara",
    "gn:country_code":"BO",
    "gn:dem":1334,
    "gn:feature_class":"P",
    "gn:feature_code":"PPL",
    "gn:name":"Santa Barvara",
    "gn:population":0,
    "gn:timezone":"America/La_Paz",
    "iso:country":"BO",
    "wof:name":"Santa Barvara",
    "wof:placetype":"locality"
},
  "geometry": {"coordinates":[-64.56667,-20.36667000000001],"type":"Point"}
}