{
  "type": "Feature",
  "properties": {
    "gn:admin1_code":"3.0",
    "gn:asciiname":"Murillo",
    "gn:country_code":"BO",
    "gn:dem":242,
    "gn:feature_class":"P",
    "gn:feature_code":"PPL",
    "gn:name":"Murillo",
    "gn:population":0,
    "gn:timezone":"America/La_Paz",
    "iso:country":"BO",
    "name:bel_x_preferred":[
        "\u041c\u0443\u0440\u044b\u043b\u044c\u044f"
    ],
    "name:bre_x_preferred":[
        "Murillo"
    ],
    "name:cat_x_preferred":[
        "Murillo"
    ],
    "name:ceb_x_preferred":[
        "Murillo"
    ],
    "name:ces_x_preferred":[
        "Murillo"
    ],
    "name:deu_x_preferred":[
        "Murillo"
    ],
    "name:eus_x_preferred":[
        "Murillo"
    ],
    "name:fin_x_preferred":[
        "Murillo"
    ],
    "name:fra_x_preferred":[
        "Murillo"
    ],
    "name:ita_x_preferred":[
        "Murillo"
    ],
    "name:nld_x_preferred":[
        "Murillo"
    ],
    "name:rus_x_preferred":[
        "\u041c\u0443\u0440\u0438\u043b\u044c\u043e"
    ],
    "name:spa_x_preferred":[
        "Murillo"
    ],
    "name:swe_x_preferred":[
        "Murillo"
    ],
    "name:vie_x_preferred":[
        "Murillo"
    ],
    "wof:name":"Murillo",
    "wof:placetype":"locality"
},
  "geometry": {"coordinates":[-62.16667,-13.73333],"type":"Point"}
}