{
  "type": "Feature",
  "properties": {
    "gn:admin1_code":"4.0",
    "gn:asciiname":"Llucturi",
    "gn:country_code":"BO",
    "gn:dem":4000,
    "gn:feature_class":"P",
    "gn:feature_code":"PPL",
    "gn:name":"Llucturi",
    "gn:population":0,
    "gn:timezone":"America/La_Paz",
    "iso:country":"BO",
    "wof:name":"Llucturi",
    "wof:placetype":"locality"
},
  "geometry": {"coordinates":[-68.16667,-16.96667],"type":"Point"}
}