{
  "type": "Feature",
  "properties": {
    "gn:admin1_code":"7.0",
    "gn:asciiname":"Guipampa",
    "gn:country_code":"BO",
    "gn:dem":2999,
    "gn:feature_class":"P",
    "gn:feature_code":"PPL",
    "gn:name":"Guipampa",
    "gn:population":0,
    "gn:timezone":"America/La_Paz",
    "iso:country":"BO",
    "wof:name":"Guipampa",
    "wof:placetype":"locality"
},
  "geometry": {"coordinates":[-65.43333,-19.28333],"type":"Point"}
}