{
  "type": "Feature",
  "properties": {
    "gn:admin1_code":"2.0",
    "gn:admin2_code":"303.0",
    "gn:asciiname":"Independencia",
    "gn:country_code":"BO",
    "gn:dem":2638,
    "gn:feature_class":"P",
    "gn:feature_code":"PPLA2",
    "gn:name":"Independencia",
    "gn:population":0,
    "gn:timezone":"America/La_Paz",
    "iso:country":"BO",
    "name:deu_x_preferred":[
        "Independencia"
    ],
    "name:fas_x_preferred":[
        "\u0622\u06cc\u0648\u067e\u0627\u06cc\u0627"
    ],
    "name:fra_x_preferred":[
        "Independencia"
    ],
    "name:nor_x_preferred":[
        "Ayopaya"
    ],
    "name:pol_x_preferred":[
        "Ayopaya"
    ],
    "name:que_x_preferred":[
        "Jayupaya llaqta"
    ],
    "name:spa_x_preferred":[
        "Independencia"
    ],
    "name:swe_x_preferred":[
        "Ayopaya"
    ],
    "name:und_x_variant":[
        "Ayopaya"
    ],
    "name:war_x_preferred":[
        "Villa Independencia"
    ],
    "name:zho_x_preferred":[
        "\u963f\u7d04\u5e15\u4e9e"
    ],
    "wof:name":"Independencia",
    "wof:placetype":"locality"
},
  "geometry": {"coordinates":[-66.81804,-17.08389],"type":"Point"}
}