{
  "type": "Feature",
  "properties": {
    "gn:admin1_code":"7.0",
    "gn:asciiname":"Lipipuchi",
    "gn:cc2":"BO",
    "gn:country_code":"BO",
    "gn:dem":3668,
    "gn:feature_class":"P",
    "gn:feature_code":"PPL",
    "gn:name":"Lipipuchi",
    "gn:population":0,
    "gn:timezone":"America/La_Paz",
    "iso:country":"BO",
    "name:und_x_variant":[
        "Lipipuchio",
        "Lipipuchi"
    ],
    "wof:name":"Lipipuchi",
    "wof:placetype":"locality"
},
  "geometry": {"coordinates":[-67.23333000000001,-19.66667],"type":"Point"}
}