{
  "type": "Feature",
  "properties": {
    "gn:admin1_code":"7.0",
    "gn:asciiname":"Quebrada Honda",
    "gn:country_code":"BO",
    "gn:dem":3466,
    "gn:feature_class":"P",
    "gn:feature_code":"PPL",
    "gn:name":"Quebrada Honda",
    "gn:population":0,
    "gn:timezone":"America/La_Paz",
    "iso:country":"BO",
    "name:und_x_variant":[
        "Hacienda Quebrada Honda",
        "Quebrada Honda"
    ],
    "wof:name":"Quebrada Honda",
    "wof:placetype":"locality"
},
  "geometry": {"coordinates":[-65.37998,-19.45753],"type":"Point"}
}