{
  "type": "Feature",
  "properties": {
    "gn:admin1_code":"08",
    "gn:asciiname":"Caran",
    "gn:cc2":"BO",
    "gn:country_code":"BO",
    "gn:dem":410,
    "gn:feature_class":"P",
    "gn:feature_code":"PPL",
    "gn:name":"Caran",
    "gn:population":0,
    "gn:timezone":"America/La_Paz",
    "iso:country":"BO",
    "name:und_x_variant":[
        "Carandosena",
        "Caran"
    ],
    "wof:name":"Caran",
    "wof:placetype":"locality"
},
  "geometry": {"coordinates":[-62.98333,-19.03333],"type":"Point"}
}