{
  "type": "Feature",
  "properties": {
    "gn:admin1_code":"09",
    "gn:asciiname":"Abra Ckasa",
    "gn:cc2":"BO",
    "gn:country_code":"BO",
    "gn:dem":2687,
    "gn:feature_class":"P",
    "gn:feature_code":"PPL",
    "gn:name":"Abra Ckasa",
    "gn:population":0,
    "gn:timezone":"America/La_Paz",
    "iso:country":"BO",
    "name:und_x_variant":[
        "Abra Kasa",
        "Abra Ckasa"
    ],
    "wof:name":"Abra Ckasa",
    "wof:placetype":"locality"
},
  "geometry": {"coordinates":[-64.58333,-21.76667],"type":"Point"}
}