{
  "type": "Feature",
  "properties": {
    "gn:admin1_code":"4.0",
    "gn:asciiname":"Jilata",
    "gn:country_code":"BO",
    "gn:dem":3830,
    "gn:feature_class":"P",
    "gn:feature_code":"PPL",
    "gn:name":"Jilata",
    "gn:population":0,
    "gn:timezone":"America/La_Paz",
    "iso:country":"BO",
    "wof:name":"Jilata",
    "wof:placetype":"locality"
},
  "geometry": {"coordinates":[-69.25,-15.56667],"type":"Point"}
}