{
  "type": "Feature",
  "properties": {
    "gn:admin1_code":"04",
    "gn:asciiname":"Aracana",
    "gn:country_code":"BO",
    "gn:dem":3978,
    "gn:feature_class":"P",
    "gn:feature_code":"PPL",
    "gn:name":"Aracana",
    "gn:population":0,
    "gn:timezone":"America/La_Paz",
    "iso:country":"BO",
    "wof:name":"Aracana",
    "wof:placetype":"locality"
},
  "geometry": {"coordinates":[-68.55,-17.15],"type":"Point"}
}