{
  "type": "Feature",
  "properties": {
    "gn:admin1_code":"04",
    "gn:asciiname":"Aracana",
    "gn:country_code":"BO",
    "gn:dem":3978,
    "gn:feature_class":"P",
    "gn:feature_code":"PPL",
    "gn:name":"Aracana",
    "gn:population":0,
    "gn:timezone":"America/La_Paz",
    "iso:country":"BO",
    "name:ceb_x_preferred":[
        "Aracana"
    ],
    "name:fra_x_preferred":[
        "Aracana"
    ],
    "name:lit_x_preferred":[
        "Paprastosios d\u0117\u017eia\u017euv\u0117s"
    ],
    "name:nld_x_preferred":[
        "Aracana"
    ],
    "name:pol_x_preferred":[
        "Aracana"
    ],
    "name:spa_x_preferred":[
        "Aracana"
    ],
    "name:swe_x_preferred":[
        "Aracana"
    ],
    "name:vie_x_preferred":[
        "Aracana"
    ],
    "name:war_x_preferred":[
        "Aracana"
    ],
    "wof:name":"Aracana",
    "wof:placetype":"locality"
},
  "geometry": {"coordinates":[-68.55,-17.15],"type":"Point"}
}