{
  "type": "Feature",
  "properties": {
    "gn:admin1_code":"8.0",
    "gn:asciiname":"Itayo",
    "gn:country_code":"BO",
    "gn:dem":1086,
    "gn:feature_class":"P",
    "gn:feature_code":"PPL",
    "gn:name":"Itayo",
    "gn:population":0,
    "gn:timezone":"America/La_Paz",
    "iso:country":"BO",
    "wof:name":"Itayo",
    "wof:placetype":"locality"
},
  "geometry": {"coordinates":[-63.29382,-19.8399],"type":"Point"}
}