{
  "type": "Feature",
  "properties": {
    "gn:admin1_code":"04",
    "gn:asciiname":"Choro",
    "gn:country_code":"BO",
    "gn:dem":1112,
    "gn:feature_class":"P",
    "gn:feature_code":"PPL",
    "gn:name":"Choro",
    "gn:population":0,
    "gn:timezone":"America/La_Paz",
    "iso:country":"BO",
    "wof:name":"Choro",
    "wof:placetype":"locality"
},
  "geometry": {"coordinates":[-67.63133000000001,-16.02646],"type":"Point"}
}