{
  "type": "Feature",
  "properties": {
    "gn:admin1_code":"04",
    "gn:asciiname":"Choro",
    "gn:country_code":"BO",
    "gn:dem":1112,
    "gn:feature_class":"P",
    "gn:feature_code":"PPL",
    "gn:name":"Choro",
    "gn:population":0,
    "gn:timezone":"America/La_Paz",
    "iso:country":"BO",
    "name:bre_x_preferred":[
        "Choro"
    ],
    "name:bul_x_preferred":[
        "\u0428\u043e\u0440\u0443"
    ],
    "name:cat_x_preferred":[
        "Xoro"
    ],
    "name:deu_x_preferred":[
        "Choro"
    ],
    "name:epo_x_preferred":[
        "\u0108oro"
    ],
    "name:fas_x_preferred":[
        "\u0634\u0648\u0631\u0648"
    ],
    "name:fin_x_preferred":[
        "Choro"
    ],
    "name:fra_x_preferred":[
        "Choro"
    ],
    "name:heb_x_preferred":[
        "\u05e9\u05d5\u05e8\u05d5"
    ],
    "name:ita_x_preferred":[
        "Choro"
    ],
    "name:jpn_x_preferred":[
        "\u30b7\u30e7\u30fc\u30ed"
    ],
    "name:lav_x_preferred":[
        "\u0160oru"
    ],
    "name:pol_x_preferred":[
        "Choro"
    ],
    "name:por_x_preferred":[
        "Choro"
    ],
    "name:rus_x_preferred":[
        "\u0428\u043e\u0440\u043e"
    ],
    "name:spa_x_preferred":[
        "Choro"
    ],
    "wof:name":"Choro",
    "wof:placetype":"locality"
},
  "geometry": {"coordinates":[-67.63133000000001,-16.02646],"type":"Point"}
}