{
  "type": "Feature",
  "properties": {
    "gn:admin1_code":"06",
    "gn:asciiname":"Curiche",
    "gn:country_code":"BO",
    "gn:dem":231,
    "gn:feature_class":"P",
    "gn:feature_code":"PPL",
    "gn:name":"Curiche",
    "gn:population":0,
    "gn:timezone":"America/La_Paz",
    "iso:country":"BO",
    "name:spa_x_preferred":[
        "Curiche"
    ],
    "wof:name":"Curiche",
    "wof:placetype":"locality"
},
  "geometry": {"coordinates":[-68.16074,-11.23533],"type":"Point"}
}