{
  "type": "Feature",
  "properties": {
    "gn:admin1_code":"4.0",
    "gn:asciiname":"Kerani",
    "gn:country_code":"BO",
    "gn:dem":3857,
    "gn:feature_class":"P",
    "gn:feature_code":"PPL",
    "gn:name":"Kerani",
    "gn:population":0,
    "gn:timezone":"America/La_Paz",
    "iso:country":"BO",
    "wof:name":"Kerani",
    "wof:placetype":"locality"
},
  "geometry": {"coordinates":[-68.48333000000001,-16.45],"type":"Point"}
}