{
  "type": "Feature",
  "properties": {
    "gn:admin1_code":"06",
    "gn:asciiname":"Caserinha",
    "gn:country_code":"BO",
    "gn:dem":159,
    "gn:feature_class":"P",
    "gn:feature_code":"PPL",
    "gn:name":"Caserinha",
    "gn:population":0,
    "gn:timezone":"America/La_Paz",
    "iso:country":"BO",
    "name:spa_x_preferred":[
        "Caserinha"
    ],
    "wof:name":"Caserinha",
    "wof:placetype":"locality"
},
  "geometry": {"coordinates":[-67.20635,-10.40854],"type":"Point"}
}