{
  "type": "Feature",
  "properties": {
    "gn:admin1_code":"09",
    "gn:asciiname":"Arrosales",
    "gn:country_code":"BO",
    "gn:dem":381,
    "gn:feature_class":"P",
    "gn:feature_code":"PPL",
    "gn:name":"Arrosales",
    "gn:population":0,
    "gn:timezone":"America/La_Paz",
    "iso:country":"BO",
    "wof:name":"Arrosales",
    "wof:placetype":"locality"
},
  "geometry": {"coordinates":[-64.27229,-22.69655],"type":"Point"}
}