{
  "type": "Feature",
  "properties": {
    "gn:admin1_code":"07",
    "gn:asciiname":"Camacha",
    "gn:cc2":"BO",
    "gn:country_code":"BO",
    "gn:dem":4110,
    "gn:feature_class":"P",
    "gn:feature_code":"PPL",
    "gn:name":"Camacha",
    "gn:population":0,
    "gn:timezone":"America/La_Paz",
    "iso:country":"BO",
    "name:ceb_x_preferred":[
        "Camacha"
    ],
    "name:ces_x_preferred":[
        "Camacha"
    ],
    "name:deu_x_preferred":[
        "Camacha"
    ],
    "name:fra_x_preferred":[
        "Camacha"
    ],
    "name:hun_x_preferred":[
        "Camacha"
    ],
    "name:kaz_x_preferred":[
        "\u041a\u0430\u043c\u0430\u0448\u0430"
    ],
    "name:msa_x_preferred":[
        "Camacha"
    ],
    "name:pol_x_preferred":[
        "Camacha"
    ],
    "name:por_x_preferred":[
        "Camacha"
    ],
    "name:rus_x_preferred":[
        "\u041a\u0430\u043c\u0430\u0448\u0430"
    ],
    "name:spa_x_preferred":[
        "Camacha"
    ],
    "name:tur_x_preferred":[
        "Camacha"
    ],
    "name:ukr_x_preferred":[
        "\u041a\u0430\u043c\u0430\u0448\u0430"
    ],
    "name:und_x_variant":[
        "Camacho",
        "Camacha"
    ],
    "wof:name":"Camacha",
    "wof:placetype":"locality"
},
  "geometry": {"coordinates":[-68.36667,-20.03333],"type":"Point"}
}