{
  "type": "Feature",
  "properties": {
    "gn:admin1_code":"07",
    "gn:asciiname":"Camacha",
    "gn:cc2":"BO",
    "gn:country_code":"BO",
    "gn:dem":4110,
    "gn:feature_class":"P",
    "gn:feature_code":"PPL",
    "gn:name":"Camacha",
    "gn:population":0,
    "gn:timezone":"America/La_Paz",
    "iso:country":"BO",
    "name:und_x_variant":[
        "Camacho",
        "Camacha"
    ],
    "wof:name":"Camacha",
    "wof:placetype":"locality"
},
  "geometry": {"coordinates":[-68.36667,-20.03333],"type":"Point"}
}