{
  "type": "Feature",
  "properties": {
    "gn:admin1_code":"1.0",
    "gn:asciiname":"Tamapampa",
    "gn:country_code":"BO",
    "gn:dem":2589,
    "gn:feature_class":"P",
    "gn:feature_code":"PPL",
    "gn:name":"Tamapampa",
    "gn:population":0,
    "gn:timezone":"America/La_Paz",
    "iso:country":"BO",
    "wof:name":"Tamapampa",
    "wof:placetype":"locality"
},
  "geometry": {"coordinates":[-65.33554000000001,-19.06131],"type":"Point"}
}