{
  "type": "Feature",
  "properties": {
    "gn:admin1_code":"05",
    "gn:asciiname":"Estancia Reca Chata",
    "gn:country_code":"BO",
    "gn:dem":3979,
    "gn:feature_class":"P",
    "gn:feature_code":"PPL",
    "gn:name":"Estancia Reca Chata",
    "gn:population":0,
    "gn:timezone":"America/La_Paz",
    "iso:country":"BO",
    "wof:name":"Estancia Reca Chata",
    "wof:placetype":"locality"
},
  "geometry": {"coordinates":[-68.59721999999999,-18.07952],"type":"Point"}
}