{
  "type": "Feature",
  "properties": {
    "gn:admin1_code":"07",
    "gn:asciiname":"Estancia Beatriz",
    "gn:country_code":"BO",
    "gn:dem":3744,
    "gn:feature_class":"P",
    "gn:feature_code":"PPL",
    "gn:name":"Estancia Beatriz",
    "gn:population":0,
    "gn:timezone":"America/La_Paz",
    "iso:country":"BO",
    "wof:name":"Estancia Beatriz",
    "wof:placetype":"locality"
},
  "geometry": {"coordinates":[-68.53313,-20.52083],"type":"Point"}
}