{
  "type": "Feature",
  "properties": {
    "gn:admin1_code":"3.0",
    "gn:asciiname":"Puerto Rubio",
    "gn:country_code":"BO",
    "gn:dem":156,
    "gn:feature_class":"P",
    "gn:feature_code":"PPL",
    "gn:name":"Puerto Rubio",
    "gn:population":0,
    "gn:timezone":"America/La_Paz",
    "iso:country":"BO",
    "wof:name":"Puerto Rubio",
    "wof:placetype":"locality"
},
  "geometry": {"coordinates":[-62.41667,-13.13333],"type":"Point"}
}