{
  "type": "Feature",
  "properties": {
    "gn:admin1_code":"4.0",
    "gn:asciiname":"Pacaures",
    "gn:country_code":"BO",
    "gn:dem":3861,
    "gn:feature_class":"P",
    "gn:feature_code":"PPL",
    "gn:name":"Pacaures",
    "gn:population":0,
    "gn:timezone":"America/La_Paz",
    "iso:country":"BO",
    "name:und_x_variant":[
        "Pucauris",
        "Estancia Pacaures",
        "Pacaures"
    ],
    "wof:name":"Pacaures",
    "wof:placetype":"locality"
},
  "geometry": {"coordinates":[-69.07279,-15.58672],"type":"Point"}
}