{
  "type": "Feature",
  "properties": {
    "gn:admin1_code":"05",
    "gn:asciiname":"Coopata",
    "gn:country_code":"BO",
    "gn:dem":3711,
    "gn:feature_class":"P",
    "gn:feature_code":"PPL",
    "gn:name":"Coopata",
    "gn:population":0,
    "gn:timezone":"America/La_Paz",
    "iso:country":"BO",
    "wof:name":"Coopata",
    "wof:placetype":"locality"
},
  "geometry": {"coordinates":[-67.35167,-18.2488],"type":"Point"}
}