{
  "type": "Feature",
  "properties": {
    "gn:gn_country":"BO",
    "gn:gn_fcode":"PPL",
    "gn:gn_pop":77,
    "gn:population":77,
    "iso:country":"BO",
    "qs_pg:aaroncc":"BO",
    "qs_pg:gn_country":"BO",
    "qs_pg:gn_fcode":"PPL",
    "qs_pg:gn_pop":77,
    "qs_pg:name":"Jukumari Bajo",
    "qs_pg:photos_9r":0,
    "qs_pg:photos_sr":0,
    "qs_pg:pop_sr":1,
    "qs_pg:qs_pg_placetype":"locality",
    "wof:name":"Jukumari Bajo",
    "wof:placetype":"locality",
    "wof:population":77
},
  "geometry": {"coordinates":[-65.09925,-17.65399],"type":"Point"}
}