{
  "type": "Feature",
  "properties": {
    "gn:admin1_code":"9.0",
    "gn:asciiname":"San Alberto",
    "gn:country_code":"BO",
    "gn:dem":782,
    "gn:feature_class":"P",
    "gn:feature_code":"PPL",
    "gn:name":"San Alberto",
    "gn:population":0,
    "gn:timezone":"America/La_Paz",
    "iso:country":"BO",
    "name:ceb_x_preferred":[
        "San Alberto"
    ],
    "name:deu_x_preferred":[
        "San Alberto"
    ],
    "name:nld_x_preferred":[
        "San Alberto"
    ],
    "name:por_x_preferred":[
        "San Alberto"
    ],
    "name:spa_x_preferred":[
        "San Alberto"
    ],
    "name:srp_x_preferred":[
        "\u0421\u0430\u043d \u0410\u043b\u0431\u0435\u0440\u0442\u043e"
    ],
    "name:swe_x_preferred":[
        "San Alberto"
    ],
    "name:vie_x_preferred":[
        "San Alberto"
    ],
    "wof:name":"San Alberto",
    "wof:placetype":"locality"
},
  "geometry": {"coordinates":[-63.80687,-21.90934],"type":"Point"}
}