{
  "type": "Feature",
  "properties": {
    "gn:admin1_code":"05",
    "gn:asciiname":"Copasalli",
    "gn:country_code":"BO",
    "gn:dem":3698,
    "gn:feature_class":"P",
    "gn:feature_code":"PPL",
    "gn:name":"Copasalli",
    "gn:population":0,
    "gn:timezone":"America/La_Paz",
    "iso:country":"BO",
    "name:und_x_variant":[
        "Estancia Copasalli",
        "Copasalli"
    ],
    "wof:name":"Copasalli",
    "wof:placetype":"locality"
},
  "geometry": {"coordinates":[-67.53198,-19.3317],"type":"Point"}
}