{
  "type": "Feature",
  "properties": {
    "gn:admin1_code":"9.0",
    "gn:asciiname":"Nahurienda",
    "gn:country_code":"BO",
    "gn:dem":780,
    "gn:feature_class":"P",
    "gn:feature_code":"PPL",
    "gn:name":"Nahurienda",
    "gn:population":0,
    "gn:timezone":"America/La_Paz",
    "iso:country":"BO",
    "wof:name":"Nahurienda",
    "wof:placetype":"locality"
},
  "geometry": {"coordinates":[-64.0608,-21.1364],"type":"Point"}
}