{
  "type": "Feature",
  "properties": {
    "gn:admin1_code":"05",
    "gn:asciiname":"Alsuri",
    "gn:cc2":"BO",
    "gn:country_code":"BO",
    "gn:dem":3984,
    "gn:feature_class":"P",
    "gn:feature_code":"PPL",
    "gn:name":"Alsuri",
    "gn:population":0,
    "gn:timezone":"America/La_Paz",
    "iso:country":"BO",
    "name:und_x_variant":[
        "Jalsuri",
        "Alsuri"
    ],
    "wof:name":"Alsuri",
    "wof:placetype":"locality"
},
  "geometry": {"coordinates":[-68.06667,-17.83333],"type":"Point"}
}