{
  "type": "Feature",
  "properties": {
    "gn:admin1_code":"3.0",
    "gn:asciiname":"Hariregua",
    "gn:cc2":"BO",
    "gn:country_code":"BO",
    "gn:dem":196,
    "gn:feature_class":"P",
    "gn:feature_code":"PPL",
    "gn:name":"Hariregua",
    "gn:population":0,
    "gn:timezone":"America/La_Paz",
    "iso:country":"BO",
    "name:und_x_variant":[
        "Arriegua",
        "Hariregua"
    ],
    "wof:name":"Hariregua",
    "wof:placetype":"locality"
},
  "geometry": {"coordinates":[-67.53333000000001,-14.41667],"type":"Point"}
}