{
  "type": "Feature",
  "properties": {
    "gn:admin1_code":"5.0",
    "gn:asciiname":"Estancia Mollebamba",
    "gn:country_code":"BO",
    "gn:dem":3938,
    "gn:feature_class":"P",
    "gn:feature_code":"PPL",
    "gn:name":"Estancia Mollebamba",
    "gn:population":0,
    "gn:timezone":"America/La_Paz",
    "iso:country":"BO",
    "wof:name":"Estancia Mollebamba",
    "wof:placetype":"locality"
},
  "geometry": {"coordinates":[-68.26666999999999,-17.81667000000001],"type":"Point"}
}