{
  "type": "Feature",
  "properties": {
    "gn:admin1_code":"01",
    "gn:asciiname":"Churu",
    "gn:country_code":"BO",
    "gn:dem":1150,
    "gn:feature_class":"P",
    "gn:feature_code":"PPL",
    "gn:name":"Chur\u00fa",
    "gn:population":0,
    "gn:timezone":"America/La_Paz",
    "iso:country":"BO",
    "wof:name":"Churu",
    "wof:placetype":"locality"
},
  "geometry": {"coordinates":[-64.48333000000001,-18.66667],"type":"Point"}
}