{
  "type": "Feature",
  "properties": {
    "gn:admin1_code":"05",
    "gn:asciiname":"Estancia Chana Huano",
    "gn:country_code":"BO",
    "gn:dem":3765,
    "gn:feature_class":"P",
    "gn:feature_code":"PPL",
    "gn:name":"Estancia Cha\u00f1a Huano",
    "gn:population":0,
    "gn:timezone":"America/La_Paz",
    "iso:country":"BO",
    "wof:name":"Estancia Chana Huano",
    "wof:placetype":"locality"
},
  "geometry": {"coordinates":[-68.44598000000001,-18.61969],"type":"Point"}
}