{
  "type": "Feature",
  "properties": {
    "gn:admin1_code":"06",
    "gn:asciiname":"Alto Bahia",
    "gn:country_code":"BO",
    "gn:dem":255,
    "gn:feature_class":"P",
    "gn:feature_code":"PPL",
    "gn:name":"Alto Bahia",
    "gn:population":0,
    "gn:timezone":"America/La_Paz",
    "iso:country":"BO",
    "name:spa_x_preferred":[
        "Alto Bahia"
    ],
    "name:spa_x_variant":[
        "Comunidad Alto Bahia"
    ],
    "wof:name":"Alto Bahia",
    "wof:placetype":"locality"
},
  "geometry": {"coordinates":[-68.77579,-11.12056],"type":"Point"}
}