{
  "type": "Feature",
  "properties": {
    "gn:admin1_code":"09",
    "gn:asciiname":"Canchas Mayu",
    "gn:country_code":"BO",
    "gn:dem":2132,
    "gn:feature_class":"P",
    "gn:feature_code":"PPL",
    "gn:name":"Canchas Mayu",
    "gn:population":0,
    "gn:timezone":"America/La_Paz",
    "iso:country":"BO",
    "wof:name":"Canchas Mayu",
    "wof:placetype":"locality"
},
  "geometry": {"coordinates":[-64.89208000000001,-21.89762],"type":"Point"}
}