{
  "type": "Feature",
  "properties": {
    "gn:admin1_code":"7.0",
    "gn:asciiname":"Pucacasa",
    "gn:country_code":"BO",
    "gn:dem":4441,
    "gn:feature_class":"P",
    "gn:feature_code":"PPL",
    "gn:name":"Pucacasa",
    "gn:population":0,
    "gn:timezone":"America/La_Paz",
    "iso:country":"BO",
    "wof:name":"Pucacasa",
    "wof:placetype":"locality"
},
  "geometry": {"coordinates":[-66.28333000000001,-21.18333],"type":"Point"}
}