{
  "type": "Feature",
  "properties": {
    "gn:admin1_code":"4.0",
    "gn:asciiname":"Puerto Perez",
    "gn:country_code":"BO",
    "gn:dem":3815,
    "gn:feature_class":"P",
    "gn:feature_code":"PPL",
    "gn:name":"Puerto P\u00e9rez",
    "gn:population":0,
    "gn:timezone":"America/La_Paz",
    "iso:country":"BO",
    "name:und_x_variant":[
        "Puerto P\u00e9rez"
    ],
    "wof:name":"Puerto Perez",
    "wof:placetype":"locality"
},
  "geometry": {"coordinates":[-68.63333,-16.26667],"type":"Point"}
}