{
  "type": "Feature",
  "properties": {
    "gn:admin1_code":"08",
    "gn:asciiname":"Colonia Japonesa San Juan",
    "gn:cc2":"BO",
    "gn:country_code":"BO",
    "gn:dem":284,
    "gn:feature_class":"P",
    "gn:feature_code":"PPL",
    "gn:name":"Colonia Japonesa San Juan",
    "gn:population":0,
    "gn:timezone":"America/La_Paz",
    "iso:country":"BO",
    "name:und_x_variant":[
        "Colonia San Juan",
        "Colonia Japonesa San Juan"
    ],
    "wof:name":"Colonia Japonesa San Juan",
    "wof:placetype":"locality"
},
  "geometry": {"coordinates":[-63.85134,-17.2891],"type":"Point"}
}