{
  "type": "Feature",
  "properties": {
    "gn:admin1_code":"2.0",
    "gn:asciiname":"Pucara Chico",
    "gn:country_code":"BO",
    "gn:dem":2558,
    "gn:feature_class":"P",
    "gn:feature_code":"PPL",
    "gn:name":"Pucara Chico",
    "gn:population":0,
    "gn:timezone":"America/La_Paz",
    "iso:country":"BO",
    "wof:name":"Pucara Chico",
    "wof:placetype":"locality"
},
  "geometry": {"coordinates":[-66.18333,-17.43333],"type":"Point"}
}