{
  "type": "Feature",
  "properties": {
    "gn:admin1_code":"4.0",
    "gn:asciiname":"Sirca",
    "gn:country_code":"BO",
    "gn:dem":3844,
    "gn:feature_class":"P",
    "gn:feature_code":"PPL",
    "gn:name":"Sirca",
    "gn:population":0,
    "gn:timezone":"America/La_Paz",
    "iso:country":"BO",
    "wof:name":"Sirca",
    "wof:placetype":"locality"
},
  "geometry": {"coordinates":[-69.03333000000001,-16.81667],"type":"Point"}
}