{
  "type": "Feature",
  "properties": {
    "gn:admin1_code":"04",
    "gn:asciiname":"Achina",
    "gn:country_code":"BO",
    "gn:dem":879,
    "gn:feature_class":"P",
    "gn:feature_code":"PPL",
    "gn:name":"Achina",
    "gn:population":0,
    "gn:timezone":"America/La_Paz",
    "iso:country":"BO",
    "wof:name":"Achina",
    "wof:placetype":"locality"
},
  "geometry": {"coordinates":[-68.06667,-15.73333],"type":"Point"}
}