{
  "type": "Feature",
  "properties": {
    "gn:admin1_code":"7.0",
    "gn:asciiname":"Estancia Pata Caballe",
    "gn:country_code":"BO",
    "gn:dem":3812,
    "gn:feature_class":"P",
    "gn:feature_code":"PPL",
    "gn:name":"Estancia Pata Caballe",
    "gn:population":0,
    "gn:timezone":"America/La_Paz",
    "iso:country":"BO",
    "wof:name":"Estancia Pata Caballe",
    "wof:placetype":"locality"
},
  "geometry": {"coordinates":[-66.40000000000001,-17.96667],"type":"Point"}
}