{
  "type": "Feature",
  "properties": {
    "gn:admin1_code":"1.0",
    "gn:asciiname":"Tejas",
    "gn:country_code":"BO",
    "gn:dem":2360,
    "gn:feature_class":"P",
    "gn:feature_code":"PPL",
    "gn:name":"Tejas",
    "gn:population":0,
    "gn:timezone":"America/La_Paz",
    "iso:country":"BO",
    "name:und_x_variant":[
        "Estancia Tejas",
        "Tejas"
    ],
    "wof:name":"Tejas",
    "wof:placetype":"locality"
},
  "geometry": {"coordinates":[-64.63906999999999,-19.12574],"type":"Point"}
}