{
  "type": "Feature",
  "properties": {
    "gn:admin1_code":"08",
    "gn:asciiname":"Comunidad Naranjillos",
    "gn:country_code":"BO",
    "gn:dem":515,
    "gn:feature_class":"P",
    "gn:feature_code":"PPL",
    "gn:name":"Comunidad Naranjillos",
    "gn:population":0,
    "gn:timezone":"America/La_Paz",
    "iso:country":"BO",
    "wof:name":"Comunidad Naranjillos",
    "wof:placetype":"locality"
},
  "geometry": {"coordinates":[-63.23333,-17.98333],"type":"Point"}
}