{
  "type": "Feature",
  "properties": {
    "gn:admin1_code":"06",
    "gn:asciiname":"Alta Gracia",
    "gn:country_code":"BO",
    "gn:dem":223,
    "gn:feature_class":"P",
    "gn:feature_code":"PPL",
    "gn:name":"Alta Gracia",
    "gn:population":0,
    "gn:timezone":"America/La_Paz",
    "iso:country":"BO",
    "name:ara_x_preferred":[
        "\u0623\u0644\u062a\u0627 \u063a\u0631\u0627\u0633\u064a\u0627"
    ],
    "name:azb_x_preferred":[
        "\u0622\u0644\u062a\u0627 \u0642\u0631\u0627\u0633\u06cc\u0627"
    ],
    "name:ben_x_preferred":[
        "\u0985\u09b2\u09cd\u099f\u09be \u0997\u09cd\u09b0\u09be\u09b8\u09bf\u09df\u09be"
    ],
    "name:bul_x_preferred":[
        "\u0410\u043b\u0442\u0430 \u0413\u0440\u0430\u0441\u0438\u044f"
    ],
    "name:cat_x_preferred":[
        "Alta Gracia"
    ],
    "name:ceb_x_preferred":[
        "Alta Gracia"
    ],
    "name:deu_x_preferred":[
        "Alta Gracia"
    ],
    "name:ell_x_preferred":[
        "\u0386\u03bb\u03c4\u03b1 \u0393\u03ba\u03c1\u03ac\u03c3\u03b9\u03b1"
    ],
    "name:epo_x_preferred":[
        "Alta Gracia"
    ],
    "name:fas_x_preferred":[
        "\u0622\u0644\u062a\u0627 \u06af\u0631\u0627\u0633\u06cc\u0627"
    ],
    "name:fra_x_preferred":[
        "Alta Gracia"
    ],
    "name:hin_x_preferred":[
        "\u0911\u0932\u094d\u091f\u093e \u0917\u094d\u0930\u0947\u0938\u093f\u092f\u093e"
    ],
    "name:hun_x_preferred":[
        "Alta Gracia"
    ],
    "name:ind_x_preferred":[
        "Alta Gracia"
    ],
    "name:ita_x_preferred":[
        "Alta Gracia"
    ],
    "name:kor_x_preferred":[
        "\uc54c\ud0c0 \uadf8\ub77c\uc2dc\uc544"
    ],
    "name:lit_x_preferred":[
        "Alta Grasija"
    ],
    "name:msa_x_preferred":[
        "Alta Gracia"
    ],
    "name:nld_x_preferred":[
        "Alta Gracia"
    ],
    "name:pol_x_preferred":[
        "Alta Gracia"
    ],
    "name:por_x_preferred":[
        "Alta Gracia"
    ],
    "name:rus_x_preferred":[
        "\u0410\u043b\u044c\u0442\u0430-\u0413\u0440\u0430\u0441\u0438\u044f"
    ],
    "name:spa_x_preferred":[
        "Alta Gracia"
    ],
    "name:spa_x_variant":[
        "Barraca Alta Gracia"
    ],
    "name:tur_x_preferred":[
        "Alta Gracia"
    ],
    "name:und_x_variant":[
        "Allagracia",
        "Altagracia"
    ],
    "name:urd_x_preferred":[
        "\u0622\u0644\u0679\u0627 \u06af\u0631\u0627\u0633\u06cc\u0627"
    ],
    "name:vie_x_preferred":[
        "Alta Gracia"
    ],
    "name:zho_x_preferred":[
        "\u4e0a\u683c\u62c9\u897f\u4e9e"
    ],
    "wof:name":"Alta Gracia",
    "wof:placetype":"locality"
},
  "geometry": {"coordinates":[-68.2557,-11.60851],"type":"Point"}
}