{
  "type": "Feature",
  "properties": {
    "gn:admin1_code":"06",
    "gn:asciiname":"Alta Gracia",
    "gn:country_code":"BO",
    "gn:dem":223,
    "gn:feature_class":"P",
    "gn:feature_code":"PPL",
    "gn:name":"Alta Gracia",
    "gn:population":0,
    "gn:timezone":"America/La_Paz",
    "iso:country":"BO",
    "name:spa_x_preferred":[
        "Alta Gracia"
    ],
    "name:spa_x_variant":[
        "Barraca Alta Gracia"
    ],
    "name:und_x_variant":[
        "Allagracia",
        "Altagracia"
    ],
    "wof:name":"Alta Gracia",
    "wof:placetype":"locality"
},
  "geometry": {"coordinates":[-68.2557,-11.60851],"type":"Point"}
}