{
  "type": "Feature",
  "properties": {
    "gn:admin1_code":"08",
    "gn:asciiname":"Equitos",
    "gn:cc2":"BO",
    "gn:country_code":"BO",
    "gn:dem":444,
    "gn:feature_class":"P",
    "gn:feature_code":"PPL",
    "gn:name":"Equitos",
    "gn:population":0,
    "gn:timezone":"America/La_Paz",
    "iso:country":"BO",
    "name:und_x_variant":[
        "Iquito",
        "Equitos"
    ],
    "wof:name":"Equitos",
    "wof:placetype":"locality"
},
  "geometry": {"coordinates":[-61.33333,-17.63332999999999],"type":"Point"}
}