{
  "type": "Feature",
  "properties": {
    "gn:admin1_code":"05",
    "gn:asciiname":"Comunidad Saytuyo",
    "gn:country_code":"BO",
    "gn:dem":3743,
    "gn:feature_class":"P",
    "gn:feature_code":"PPL",
    "gn:name":"Comunidad Saytuyo",
    "gn:population":0,
    "gn:timezone":"America/La_Paz",
    "iso:country":"BO",
    "wof:name":"Comunidad Saytuyo",
    "wof:placetype":"locality"
},
  "geometry": {"coordinates":[-67.21666999999999,-17.75],"type":"Point"}
}