{
  "type": "Feature",
  "properties": {
    "gn:admin1_code":"1.0",
    "gn:asciiname":"Kochi",
    "gn:country_code":"BO",
    "gn:dem":2784,
    "gn:feature_class":"P",
    "gn:feature_code":"PPL",
    "gn:name":"Kochi",
    "gn:population":0,
    "gn:timezone":"America/La_Paz",
    "iso:country":"BO",
    "name:und_x_variant":[
        "Estancia Khochi",
        "Kochi"
    ],
    "wof:name":"Kochi",
    "wof:placetype":"locality"
},
  "geometry": {"coordinates":[-64.86109,-18.9292],"type":"Point"}
}