{
  "type": "Feature",
  "properties": {
    "gn:admin1_code":"1.0",
    "gn:asciiname":"Puerto Quiroga",
    "gn:country_code":"BO",
    "gn:dem":471,
    "gn:feature_class":"P",
    "gn:feature_code":"PPL",
    "gn:name":"Puerto Quiroga",
    "gn:population":0,
    "gn:timezone":"America/La_Paz",
    "iso:country":"BO",
    "wof:name":"Puerto Quiroga",
    "wof:placetype":"locality"
},
  "geometry": {"coordinates":[-62.67503000000001,-20.56114],"type":"Point"}
}