{
  "type": "Feature",
  "properties": {
    "gn:admin1_code":"8.0",
    "gn:asciiname":"Tres Cruces",
    "gn:country_code":"BO",
    "gn:dem":279,
    "gn:feature_class":"P",
    "gn:feature_code":"PPL",
    "gn:name":"Tres Cruces",
    "gn:population":0,
    "gn:timezone":"America/La_Paz",
    "iso:country":"BO",
    "name:cat_x_preferred":[
        "Tres Cruces"
    ],
    "name:deu_x_preferred":[
        "Tres Cruces"
    ],
    "name:spa_x_preferred":[
        "Tres Cruces"
    ],
    "wof:name":"Tres Cruces",
    "wof:placetype":"locality"
},
  "geometry": {"coordinates":[-62.36666999999999,-17.58333],"type":"Point"}
}