{
  "type": "Feature",
  "properties": {
    "gn:admin1_code":"8.0",
    "gn:asciiname":"San Rafaelito",
    "gn:country_code":"BO",
    "gn:dem":348,
    "gn:feature_class":"P",
    "gn:feature_code":"PPL",
    "gn:name":"San Rafaelito",
    "gn:population":0,
    "gn:timezone":"America/La_Paz",
    "iso:country":"BO",
    "wof:name":"San Rafaelito",
    "wof:placetype":"locality"
},
  "geometry": {"coordinates":[-61.65,-17.05],"type":"Point"}
}