{
  "type": "Feature",
  "properties": {
    "gn:admin1_code":"04",
    "gn:asciiname":"Estancia Chacoma",
    "gn:country_code":"BO",
    "gn:dem":4054,
    "gn:feature_class":"P",
    "gn:feature_code":"PPL",
    "gn:name":"Estancia Chacoma",
    "gn:population":0,
    "gn:timezone":"America/La_Paz",
    "iso:country":"BO",
    "wof:name":"Estancia Chacoma",
    "wof:placetype":"locality"
},
  "geometry": {"coordinates":[-69.28333000000001,-17.25],"type":"Point"}
}