{
  "type": "Feature",
  "properties": {
    "gn:admin1_code":"02",
    "gn:asciiname":"Estancia Jatun Pampa",
    "gn:country_code":"BO",
    "gn:dem":3023,
    "gn:feature_class":"P",
    "gn:feature_code":"PPL",
    "gn:name":"Estancia Jatun Pampa",
    "gn:population":0,
    "gn:timezone":"America/La_Paz",
    "iso:country":"BO",
    "wof:name":"Estancia Jatun Pampa",
    "wof:placetype":"locality"
},
  "geometry": {"coordinates":[-66.84999999999999,-17.13332999999999],"type":"Point"}
}