{
  "type": "Feature",
  "properties": {
    "gn:admin1_code":"8.0",
    "gn:asciiname":"Tucumancito",
    "gn:country_code":"BO",
    "gn:dem":792,
    "gn:feature_class":"P",
    "gn:feature_code":"PPL",
    "gn:name":"Tucumancito",
    "gn:population":0,
    "gn:timezone":"America/La_Paz",
    "iso:country":"BO",
    "wof:name":"Tucumancito",
    "wof:placetype":"locality"
},
  "geometry": {"coordinates":[-62.05,-16.41667],"type":"Point"}
}