{
  "type": "Feature",
  "properties": {
    "gn:admin1_code":"9.0",
    "gn:asciiname":"Isque",
    "gn:country_code":"BO",
    "gn:dem":2578,
    "gn:feature_class":"P",
    "gn:feature_code":"PPL",
    "gn:name":"Isque",
    "gn:population":0,
    "gn:timezone":"America/La_Paz",
    "iso:country":"BO",
    "wof:name":"Isque",
    "wof:placetype":"locality"
},
  "geometry": {"coordinates":[-65.32245,-21.75026],"type":"Point"}
}