{
  "type": "Feature",
  "properties": {
    "gn:admin1_code":"7.0",
    "gn:asciiname":"Llavisa",
    "gn:country_code":"BO",
    "gn:dem":4364,
    "gn:feature_class":"P",
    "gn:feature_code":"PPL",
    "gn:name":"Llavisa",
    "gn:population":0,
    "gn:timezone":"America/La_Paz",
    "iso:country":"BO",
    "name:und_x_variant":[
        "Llavis",
        "Llavisa"
    ],
    "wof:name":"Llavisa",
    "wof:placetype":"locality"
},
  "geometry": {"coordinates":[-65.90765999999999,-18.94146],"type":"Point"}
}