{
  "type": "Feature",
  "properties": {
    "gn:admin1_code":"4.0",
    "gn:asciiname":"Villa Futani",
    "gn:country_code":"BO",
    "gn:dem":3821,
    "gn:feature_class":"P",
    "gn:feature_code":"PPL",
    "gn:name":"Villa Futani",
    "gn:population":0,
    "gn:timezone":"America/La_Paz",
    "iso:country":"BO",
    "name:spa_x_preferred":[
        "Villa Futani"
    ],
    "name:spa_x_variant":[
        "Estancia Putani"
    ],
    "wof:name":"Villa Futani",
    "wof:placetype":"locality"
},
  "geometry": {"coordinates":[-69.25888,-15.64866],"type":"Point"}
}