{
  "type": "Feature",
  "properties": {
    "gn:admin1_code":"06",
    "gn:asciiname":"Carnavalito",
    "gn:country_code":"BO",
    "gn:dem":207,
    "gn:feature_class":"P",
    "gn:feature_code":"PPL",
    "gn:name":"Carnavalito",
    "gn:population":0,
    "gn:timezone":"America/La_Paz",
    "iso:country":"BO",
    "name:spa_x_preferred":[
        "Carnavalito"
    ],
    "wof:name":"Carnavalito",
    "wof:placetype":"locality"
},
  "geometry": {"coordinates":[-68.37791,-11.47602],"type":"Point"}
}