{
  "type": "Feature",
  "properties": {
    "gn:admin1_code":"4.0",
    "gn:asciiname":"Kachapaya",
    "gn:country_code":"BO",
    "gn:dem":2885,
    "gn:feature_class":"P",
    "gn:feature_code":"PPL",
    "gn:name":"Kachapaya",
    "gn:population":0,
    "gn:timezone":"America/La_Paz",
    "iso:country":"BO",
    "wof:name":"Kachapaya",
    "wof:placetype":"locality"
},
  "geometry": {"coordinates":[-67.84999999999999,-16.76667],"type":"Point"}
}