{
  "type": "Feature",
  "properties": {
    "gn:admin1_code":"8.0",
    "gn:asciiname":"Las Porongos",
    "gn:cc2":"BO",
    "gn:country_code":"BO",
    "gn:dem":322,
    "gn:feature_class":"P",
    "gn:feature_code":"PPL",
    "gn:name":"Las Porongos",
    "gn:population":0,
    "gn:timezone":"America/La_Paz",
    "iso:country":"BO",
    "name:und_x_variant":[
        "Los Porongos",
        "Las Porongos"
    ],
    "wof:name":"Las Porongos",
    "wof:placetype":"locality"
},
  "geometry": {"coordinates":[-60.88333000000001,-18.11667000000001],"type":"Point"}
}