{
  "type": "Feature",
  "properties": {
    "gn:admin1_code":"06",
    "gn:asciiname":"Azaisal",
    "gn:country_code":"BO",
    "gn:dem":292,
    "gn:feature_class":"P",
    "gn:feature_code":"PPL",
    "gn:name":"Azaisal",
    "gn:population":0,
    "gn:timezone":"America/La_Paz",
    "iso:country":"BO",
    "wof:name":"Azaisal",
    "wof:placetype":"locality"
},
  "geometry": {"coordinates":[-69.01961,-11.39249],"type":"Point"}
}