{
  "type": "Feature",
  "properties": {
    "gn:admin1_code":"07",
    "gn:asciiname":"Estancia Ajia",
    "gn:country_code":"BO",
    "gn:dem":3673,
    "gn:feature_class":"P",
    "gn:feature_code":"PPL",
    "gn:name":"Estancia Ajia",
    "gn:population":0,
    "gn:timezone":"America/La_Paz",
    "iso:country":"BO",
    "wof:name":"Estancia Ajia",
    "wof:placetype":"locality"
},
  "geometry": {"coordinates":[-67.94293,-20.53695],"type":"Point"}
}