{
  "type": "Feature",
  "properties": {
    "gn:admin1_code":"7.0",
    "gn:asciiname":"Malpaso",
    "gn:country_code":"BO",
    "gn:dem":4057,
    "gn:feature_class":"P",
    "gn:feature_code":"PPL",
    "gn:name":"Malpaso",
    "gn:population":0,
    "gn:timezone":"America/La_Paz",
    "iso:country":"BO",
    "name:ceb_x_preferred":[
        "Malpaso"
    ],
    "name:deu_x_preferred":[
        "Malpaso"
    ],
    "name:fra_x_preferred":[
        "Malpaso"
    ],
    "name:nor_x_preferred":[
        "Malpaso"
    ],
    "name:spa_x_preferred":[
        "Malpaso"
    ],
    "name:srp_x_preferred":[
        "\u041c\u0430\u043b\u043f\u0430\u0441\u043e"
    ],
    "name:swe_x_preferred":[
        "Malpaso"
    ],
    "wof:name":"Malpaso",
    "wof:placetype":"locality"
},
  "geometry": {"coordinates":[-66.08333,-21.78333],"type":"Point"}
}