{
  "type": "Feature",
  "properties": {
    "gn:admin1_code":"7.0",
    "gn:asciiname":"Estancia Pasto Waykho",
    "gn:country_code":"BO",
    "gn:dem":3313,
    "gn:feature_class":"P",
    "gn:feature_code":"PPL",
    "gn:name":"Estancia Pasto Waykho",
    "gn:population":0,
    "gn:timezone":"America/La_Paz",
    "iso:country":"BO",
    "wof:name":"Estancia Pasto Waykho",
    "wof:placetype":"locality"
},
  "geometry": {"coordinates":[-65.54066,-20.19044],"type":"Point"}
}