{
  "type": "Feature",
  "properties": {
    "gn:admin1_code":"06",
    "gn:asciiname":"Puerto Mery",
    "gn:country_code":"BO",
    "gn:dem":147,
    "gn:feature_class":"P",
    "gn:feature_code":"PPL",
    "gn:name":"Puerto Mery",
    "gn:population":0,
    "gn:timezone":"America/La_Paz",
    "iso:country":"BO",
    "name:spa_x_preferred":[
        "Puerto Mery"
    ],
    "wof:name":"Puerto Mery",
    "wof:placetype":"locality"
},
  "geometry": {"coordinates":[-67.35758,-10.521],"type":"Point"}
}