{
  "type": "Feature",
  "properties": {
    "gn:admin1_code":"4.0",
    "gn:asciiname":"Susuni",
    "gn:country_code":"BO",
    "gn:dem":1862,
    "gn:feature_class":"P",
    "gn:feature_code":"PPL",
    "gn:name":"Susuni",
    "gn:population":0,
    "gn:timezone":"America/La_Paz",
    "iso:country":"BO",
    "wof:name":"Susuni",
    "wof:placetype":"locality"
},
  "geometry": {"coordinates":[-67.90000000000001,-16.03333],"type":"Point"}
}