{
  "type": "Feature",
  "properties": {
    "gn:admin1_code":"05",
    "gn:asciiname":"Carisuaya",
    "gn:cc2":"BO",
    "gn:country_code":"BO",
    "gn:dem":3863,
    "gn:feature_class":"P",
    "gn:feature_code":"PPL",
    "gn:name":"Carisuaya",
    "gn:population":0,
    "gn:timezone":"America/La_Paz",
    "iso:country":"BO",
    "name:und_x_variant":[
        "Carishuaya",
        "Carisuaya"
    ],
    "wof:name":"Carisuaya",
    "wof:placetype":"locality"
},
  "geometry": {"coordinates":[-67.84999999999999,-18.43333],"type":"Point"}
}