{
  "type": "Feature",
  "properties": {
    "gn:admin1_code":"8.0",
    "gn:asciiname":"Tusabo",
    "gn:country_code":"BO",
    "gn:dem":253,
    "gn:feature_class":"P",
    "gn:feature_code":"PPL",
    "gn:name":"Tusabo",
    "gn:population":0,
    "gn:timezone":"America/La_Paz",
    "iso:country":"BO",
    "wof:name":"Tusabo",
    "wof:placetype":"locality"
},
  "geometry": {"coordinates":[-61.26667,-17.46667],"type":"Point"}
}