{
  "type": "Feature",
  "properties": {
    "gn:country":"BO",
    "gn:fcode":"PPL",
    "gn:population":161,
    "iso:country":"BO",
    "qs:name":"Anta Q\u00b4hawa",
    "qs:photos_9r":0,
    "qs:photos_sr":0,
    "qs:pop_sr":"1",
    "wof:name":"Anta Q\u00b4hawa",
    "wof:placetype":"locality",
    "wof:population":161
},
  "geometry": {"coordinates":[-65.14364999999999,-17.86468],"type":"Point"}
}