{
  "type": "Feature",
  "properties": {
    "gn:admin1_code":"2.0",
    "gn:asciiname":"Pucahuasi",
    "gn:country_code":"BO",
    "gn:dem":3055,
    "gn:feature_class":"P",
    "gn:feature_code":"PPL",
    "gn:name":"Pucahuasi",
    "gn:population":0,
    "gn:timezone":"America/La_Paz",
    "iso:country":"BO",
    "wof:name":"Pucahuasi",
    "wof:placetype":"locality"
},
  "geometry": {"coordinates":[-65.73333000000001,-17.61667000000001],"type":"Point"}
}