{
  "type": "Feature",
  "properties": {
    "gn:admin1_code":"01",
    "gn:asciiname":"Comunidad Puma-Khasa",
    "gn:country_code":"BO",
    "gn:dem":2445,
    "gn:feature_class":"P",
    "gn:feature_code":"PPL",
    "gn:name":"Comunidad Puma-Khasa",
    "gn:population":0,
    "gn:timezone":"America/La_Paz",
    "iso:country":"BO",
    "wof:name":"Comunidad Puma-Khasa",
    "wof:placetype":"locality"
},
  "geometry": {"coordinates":[-64.65682,-20.73481],"type":"Point"}
}