{
  "type": "Feature",
  "properties": {
    "gn:admin1_code":"04",
    "gn:asciiname":"Alaconi",
    "gn:cc2":"BO",
    "gn:country_code":"BO",
    "gn:dem":3957,
    "gn:feature_class":"P",
    "gn:feature_code":"PPL",
    "gn:name":"Alaconi",
    "gn:population":0,
    "gn:timezone":"America/La_Paz",
    "iso:country":"BO",
    "name:und_x_variant":[
        "Estancia Alaconi",
        "Alaconi"
    ],
    "wof:name":"Alaconi",
    "wof:placetype":"locality"
},
  "geometry": {"coordinates":[-69.15000000000001,-17.16667],"type":"Point"}
}