{
  "type": "Feature",
  "properties": {
    "gn:admin1_code":"01",
    "gn:asciiname":"El Banado",
    "gn:country_code":"BO",
    "gn:dem":2068,
    "gn:feature_class":"P",
    "gn:feature_code":"PPL",
    "gn:name":"El Ba\u00f1ado",
    "gn:population":0,
    "gn:timezone":"America/La_Paz",
    "iso:country":"BO",
    "wof:name":"El Banado",
    "wof:placetype":"locality"
},
  "geometry": {"coordinates":[-64.48333000000001,-19.65],"type":"Point"}
}