{
  "type": "Feature",
  "properties": {
    "gn:admin1_code":"8.0",
    "gn:asciiname":"Perico",
    "gn:country_code":"BO",
    "gn:dem":861,
    "gn:feature_class":"P",
    "gn:feature_code":"PPL",
    "gn:name":"Perico",
    "gn:population":0,
    "gn:timezone":"America/La_Paz",
    "iso:country":"BO",
    "name:ceb_x_preferred":[
        "Perico"
    ],
    "name:deu_x_preferred":[
        "Perico"
    ],
    "name:fra_x_preferred":[
        "Perico"
    ],
    "name:pol_x_preferred":[
        "Perico"
    ],
    "name:por_x_preferred":[
        "Perico"
    ],
    "name:sco_x_preferred":[
        "Perico"
    ],
    "name:spa_x_preferred":[
        "Perico"
    ],
    "name:swe_x_preferred":[
        "Perico"
    ],
    "wof:name":"Perico",
    "wof:placetype":"locality"
},
  "geometry": {"coordinates":[-63.69221999999999,-18.65733],"type":"Point"}
}