{
  "type": "Feature",
  "properties": {
    "gn:admin1_code":"2.0",
    "gn:asciiname":"Tipajara",
    "gn:country_code":"BO",
    "gn:dem":2346,
    "gn:feature_class":"P",
    "gn:feature_code":"PPL",
    "gn:name":"Tipajara",
    "gn:population":0,
    "gn:timezone":"America/La_Paz",
    "iso:country":"BO",
    "name:und_x_variant":[
        "Estancia Tipajara",
        "Tipajara"
    ],
    "wof:name":"Tipajara",
    "wof:placetype":"locality"
},
  "geometry": {"coordinates":[-65.27799,-18.13064],"type":"Point"}
}