{
  "type": "Feature",
  "properties": {
    "gn:admin1_code":"04",
    "gn:asciiname":"Cota",
    "gn:country_code":"BO",
    "gn:dem":3197,
    "gn:feature_class":"P",
    "gn:feature_code":"PPL",
    "gn:name":"Cota",
    "gn:population":0,
    "gn:timezone":"America/La_Paz",
    "iso:country":"BO",
    "wof:name":"Cota",
    "wof:placetype":"locality"
},
  "geometry": {"coordinates":[-67.73333000000001,-16.93333],"type":"Point"}
}