{
  "type": "Feature",
  "properties": {
    "gn:admin1_code":"8.0",
    "gn:asciiname":"Campamento Bambarral",
    "gn:cc2":"BO",
    "gn:country_code":"BO",
    "gn:dem":85,
    "gn:feature_class":"P",
    "gn:feature_code":"PPL",
    "gn:name":"Campamento Bambarral",
    "gn:population":0,
    "gn:timezone":"America/La_Paz",
    "iso:country":"BO",
    "name:und_x_variant":[
        "Bambarra",
        "Bambarral",
        "Campamento Bambarral"
    ],
    "wof:name":"Campamento Bambarral",
    "wof:placetype":"locality"
},
  "geometry": {"coordinates":[-57.93333000000001,-19.31667],"type":"Point"}
}