{
  "type": "Feature",
  "properties": {
    "gn:admin1_code":"01",
    "gn:asciiname":"Chamina",
    "gn:country_code":"BO",
    "gn:dem":2936,
    "gn:feature_class":"P",
    "gn:feature_code":"PPL",
    "gn:name":"Chamina",
    "gn:population":0,
    "gn:timezone":"America/La_Paz",
    "iso:country":"BO",
    "name:und_x_variant":[
        "Estancia Chamina",
        "Chamina"
    ],
    "wof:name":"Chamina",
    "wof:placetype":"locality"
},
  "geometry": {"coordinates":[-65.35813,-19.20627],"type":"Point"}
}