{
  "type": "Feature",
  "properties": {
    "gn:admin1_code":"1.0",
    "gn:asciiname":"Represa",
    "gn:country_code":"BO",
    "gn:dem":752,
    "gn:feature_class":"P",
    "gn:feature_code":"PPL",
    "gn:name":"Represa",
    "gn:population":0,
    "gn:timezone":"America/La_Paz",
    "iso:country":"BO",
    "wof:name":"Represa",
    "wof:placetype":"locality"
},
  "geometry": {"coordinates":[-63.13333000000001,-20.63333],"type":"Point"}
}