{
  "type": "Feature",
  "properties": {
    "gn:admin1_code":"04",
    "gn:asciiname":"Culli Culli",
    "gn:country_code":"BO",
    "gn:dem":3880,
    "gn:feature_class":"P",
    "gn:feature_code":"PPL",
    "gn:name":"Culli Culli",
    "gn:population":0,
    "gn:timezone":"America/La_Paz",
    "iso:country":"BO",
    "wof:name":"Culli Culli",
    "wof:placetype":"locality"
},
  "geometry": {"coordinates":[-67.66667,-17.45],"type":"Point"}
}