{
  "type": "Feature",
  "properties": {
    "gn:admin1_code":"04",
    "gn:asciiname":"Chijta",
    "gn:country_code":"BO",
    "gn:dem":3870,
    "gn:feature_class":"P",
    "gn:feature_code":"PPL",
    "gn:name":"Chijta",
    "gn:population":0,
    "gn:timezone":"America/La_Paz",
    "iso:country":"BO",
    "wof:name":"Chijta",
    "wof:placetype":"locality"
},
  "geometry": {"coordinates":[-67.86667,-17.25],"type":"Point"}
}