{
  "type": "Feature",
  "properties": {
    "gn:admin1_code":"6.0",
    "gn:asciiname":"Petropolis",
    "gn:country_code":"BO",
    "gn:dem":148,
    "gn:feature_class":"P",
    "gn:feature_code":"PPL",
    "gn:name":"Petropolis",
    "gn:population":0,
    "gn:timezone":"America/La_Paz",
    "iso:country":"BO",
    "wof:name":"Petropolis",
    "wof:placetype":"locality"
},
  "geometry": {"coordinates":[-67.15000000000001,-10.31667],"type":"Point"}
}