{
  "type": "Feature",
  "properties": {
    "gn:admin1_code":"07",
    "gn:asciiname":"Escala",
    "gn:country_code":"BO",
    "gn:dem":3958,
    "gn:feature_class":"P",
    "gn:feature_code":"PPL",
    "gn:name":"Escala",
    "gn:population":0,
    "gn:timezone":"America/La_Paz",
    "iso:country":"BO",
    "name:und_x_variant":[
        "Escata",
        "Escala"
    ],
    "wof:name":"Escala",
    "wof:placetype":"locality"
},
  "geometry": {"coordinates":[-66.89953,-21.61016],"type":"Point"}
}