{
  "type": "Feature",
  "properties": {
    "gn:admin1_code":"07",
    "gn:asciiname":"Escala",
    "gn:country_code":"BO",
    "gn:dem":3958,
    "gn:feature_class":"P",
    "gn:feature_code":"PPL",
    "gn:name":"Escala",
    "gn:population":0,
    "gn:timezone":"America/La_Paz",
    "iso:country":"BO",
    "name:arg_x_preferred":[
        "Escalar"
    ],
    "name:bug_x_preferred":[
        "Escala"
    ],
    "name:cat_x_preferred":[
        "Escalar"
    ],
    "name:ceb_x_preferred":[
        "Escala"
    ],
    "name:eus_x_preferred":[
        "Escala"
    ],
    "name:fra_x_preferred":[
        "Escala"
    ],
    "name:hun_x_preferred":[
        "Escala"
    ],
    "name:ind_x_preferred":[
        "Escala"
    ],
    "name:ita_x_preferred":[
        "Escala"
    ],
    "name:lat_x_preferred":[
        "Escala"
    ],
    "name:msa_x_preferred":[
        "Escala"
    ],
    "name:nld_x_preferred":[
        "Escala"
    ],
    "name:oci_x_preferred":[
        "Escalar"
    ],
    "name:pol_x_preferred":[
        "Escala"
    ],
    "name:ron_x_preferred":[
        "Escala"
    ],
    "name:rus_x_preferred":[
        "\u042d\u0441\u043a\u0430\u043b\u0430"
    ],
    "name:slk_x_preferred":[
        "Escala"
    ],
    "name:spa_x_preferred":[
        "Escala"
    ],
    "name:swe_x_preferred":[
        "Escala"
    ],
    "name:tgl_x_preferred":[
        "Escala"
    ],
    "name:ukr_x_preferred":[
        "\u0415\u0441\u043a\u0430\u043b\u0430"
    ],
    "name:und_x_variant":[
        "Escata",
        "Escala"
    ],
    "name:vie_x_preferred":[
        "Escala"
    ],
    "name:vol_x_preferred":[
        "Escala"
    ],
    "name:war_x_preferred":[
        "Escala"
    ],
    "name:zho_x_preferred":[
        "\u57c3\u65af\u5361\u62c9"
    ],
    "wof:name":"Escala",
    "wof:placetype":"locality"
},
  "geometry": {"coordinates":[-66.89953,-21.61016],"type":"Point"}
}