{
  "type": "Feature",
  "properties": {
    "gn:admin1_code":"7.0",
    "gn:asciiname":"Estancia Sumatala",
    "gn:country_code":"BO",
    "gn:dem":3729,
    "gn:feature_class":"P",
    "gn:feature_code":"PPL",
    "gn:name":"Estancia Sumatala",
    "gn:population":0,
    "gn:timezone":"America/La_Paz",
    "iso:country":"BO",
    "wof:name":"Estancia Sumatala",
    "wof:placetype":"locality"
},
  "geometry": {"coordinates":[-65.70724,-19.29886],"type":"Point"}
}