{
  "type": "Feature",
  "properties": {
    "gn:admin1_code":"05",
    "gn:asciiname":"Bella Vista de Canaviri",
    "gn:country_code":"BO",
    "gn:dem":3833,
    "gn:feature_class":"P",
    "gn:feature_code":"PPL",
    "gn:name":"Bella Vista de Ca\u00f1aviri",
    "gn:population":0,
    "gn:timezone":"America/La_Paz",
    "iso:country":"BO",
    "wof:name":"Bella Vista de Canaviri",
    "wof:placetype":"locality"
},
  "geometry": {"coordinates":[-66.91667,-18.65],"type":"Point"}
}