{
  "type": "Feature",
  "properties": {
    "gn:admin1_code":"05",
    "gn:asciiname":"Canto Nogachi",
    "gn:cc2":"BO",
    "gn:country_code":"BO",
    "gn:dem":3972,
    "gn:feature_class":"P",
    "gn:feature_code":"PPL",
    "gn:name":"Canto Nogachi",
    "gn:population":0,
    "gn:timezone":"America/La_Paz",
    "iso:country":"BO",
    "name:und_x_variant":[
        "Estancia Canto Nogachi",
        "Canto Nogachi"
    ],
    "wof:name":"Canto Nogachi",
    "wof:placetype":"locality"
},
  "geometry": {"coordinates":[-68.88333,-18.41667],"type":"Point"}
}