{
  "type": "Feature",
  "properties": {
    "gn:admin1_code":"7.0",
    "gn:asciiname":"Oqua Oque",
    "gn:country_code":"BO",
    "gn:dem":3980,
    "gn:feature_class":"P",
    "gn:feature_code":"PPL",
    "gn:name":"Oqua Oque",
    "gn:population":0,
    "gn:timezone":"America/La_Paz",
    "iso:country":"BO",
    "wof:name":"Oqua Oque",
    "wof:placetype":"locality"
},
  "geometry": {"coordinates":[-66.33333,-20.55],"type":"Point"}
}