{
  "type": "Feature",
  "properties": {
    "gn:admin1_code":"03",
    "gn:asciiname":"El Carmen",
    "gn:country_code":"BO",
    "gn:dem":152,
    "gn:feature_class":"P",
    "gn:feature_code":"PPL",
    "gn:name":"El Carmen",
    "gn:population":0,
    "gn:timezone":"America/La_Paz",
    "iso:country":"BO",
    "wof:name":"El Carmen",
    "wof:placetype":"locality"
},
  "geometry": {"coordinates":[-64.68333,-14.53333],"type":"Point"}
}