{
  "type": "Feature",
  "properties": {
    "gn:admin1_code":"6.0",
    "gn:asciiname":"Portachuelo",
    "gn:country_code":"BO",
    "gn:dem":133,
    "gn:feature_class":"P",
    "gn:feature_code":"PPL",
    "gn:name":"Portachuelo",
    "gn:population":0,
    "gn:timezone":"America/La_Paz",
    "iso:country":"BO",
    "name:und_x_variant":[
        "Portachulo",
        "Portachuelo"
    ],
    "wof:name":"Portachuelo",
    "wof:placetype":"locality"
},
  "geometry": {"coordinates":[-66.2925,-11.26128],"type":"Point"}
}