{
  "type": "Feature",
  "properties": {
    "gn:admin1_code":"05",
    "gn:asciiname":"Estancia Huerta",
    "gn:country_code":"BO",
    "gn:dem":4201,
    "gn:feature_class":"P",
    "gn:feature_code":"PPL",
    "gn:name":"Estancia Huerta",
    "gn:population":0,
    "gn:timezone":"America/La_Paz",
    "iso:country":"BO",
    "wof:name":"Estancia Huerta",
    "wof:placetype":"locality"
},
  "geometry": {"coordinates":[-68.96666999999999,-18.16667],"type":"Point"}
}