{
  "type": "Feature",
  "properties": {
    "gn:admin1_code":"7.0",
    "gn:asciiname":"Linque",
    "gn:country_code":"BO",
    "gn:dem":3829,
    "gn:feature_class":"P",
    "gn:feature_code":"PPL",
    "gn:name":"Linque",
    "gn:population":0,
    "gn:timezone":"America/La_Paz",
    "iso:country":"BO",
    "name:und_x_variant":[
        "Liuque",
        "Linque"
    ],
    "wof:name":"Linque",
    "wof:placetype":"locality"
},
  "geometry": {"coordinates":[-65.88169000000001,-21.02073],"type":"Point"}
}