{
  "type": "Feature",
  "properties": {
    "gn:admin1_code":"2.0",
    "gn:asciiname":"Tintin",
    "gn:country_code":"BO",
    "gn:dem":2160,
    "gn:feature_class":"P",
    "gn:feature_code":"PPL",
    "gn:name":"Tintin",
    "gn:population":0,
    "gn:timezone":"America/La_Paz",
    "iso:country":"BO",
    "name:dan_x_preferred":[
        "Tintin"
    ],
    "name:epo_x_preferred":[
        "Tintin"
    ],
    "name:fra_x_preferred":[
        "Tintin"
    ],
    "name:glg_x_preferred":[
        "Tint\u00edn"
    ],
    "name:hun_x_preferred":[
        "Tintin"
    ],
    "name:ita_x_preferred":[
        "Tintin"
    ],
    "name:mal_x_preferred":[
        "\u0d1f\u0d3f\u0d7b\u200c\u0d1f\u0d3f\u0d7b"
    ],
    "name:nld_x_preferred":[
        "Kuifje"
    ],
    "name:pol_x_preferred":[
        "Tintin"
    ],
    "name:sco_x_preferred":[
        "Tintin"
    ],
    "name:spa_x_preferred":[
        "Tint\u00edn"
    ],
    "name:swe_x_preferred":[
        "Tintin"
    ],
    "name:war_x_preferred":[
        "Tintin"
    ],
    "wof:name":"Tintin",
    "wof:placetype":"locality"
},
  "geometry": {"coordinates":[-65.45574999999999,-18.03106],"type":"Point"}
}