{
  "type": "Feature",
  "properties": {
    "gn:admin1_code":"07",
    "gn:asciiname":"Estancia Bella Candelaria",
    "gn:country_code":"BO",
    "gn:dem":3754,
    "gn:feature_class":"P",
    "gn:feature_code":"PPL",
    "gn:name":"Estancia Bella Candelaria",
    "gn:population":0,
    "gn:timezone":"America/La_Paz",
    "iso:country":"BO",
    "wof:name":"Estancia Bella Candelaria",
    "wof:placetype":"locality"
},
  "geometry": {"coordinates":[-67.61667,-20.66667],"type":"Point"}
}