{
  "type": "Feature",
  "properties": {
    "gn:admin1_code":"3.0",
    "gn:asciiname":"Suiza",
    "gn:country_code":"BO",
    "gn:dem":149,
    "gn:feature_class":"P",
    "gn:feature_code":"PPL",
    "gn:name":"Suiza",
    "gn:population":0,
    "gn:timezone":"America/La_Paz",
    "iso:country":"BO",
    "wof:name":"Suiza",
    "wof:placetype":"locality"
},
  "geometry": {"coordinates":[-65.09999999999999,-14.46667],"type":"Point"}
}