{
  "type": "Feature",
  "properties": {
    "gn:admin1_code":"8.0",
    "gn:asciiname":"Puerto Canada",
    "gn:cc2":"BO",
    "gn:country_code":"BO",
    "gn:dem":198,
    "gn:feature_class":"P",
    "gn:feature_code":"PPL",
    "gn:name":"Puerto Ca\u00f1ada",
    "gn:population":0,
    "gn:timezone":"America/La_Paz",
    "iso:country":"BO",
    "name:und_x_variant":[
        "Puerto Granada",
        "Puerto Ca\u00f1ada"
    ],
    "wof:name":"Puerto Canada",
    "wof:placetype":"locality"
},
  "geometry": {"coordinates":[-60.68333000000001,-14.93333],"type":"Point"}
}