{
  "type": "Feature",
  "properties": {
    "gn:admin1_code":"4.0",
    "gn:asciiname":"Huaycho",
    "gn:country_code":"BO",
    "gn:dem":3382,
    "gn:feature_class":"P",
    "gn:feature_code":"PPL",
    "gn:name":"Huaycho",
    "gn:population":0,
    "gn:timezone":"America/La_Paz",
    "iso:country":"BO",
    "name:spa_x_preferred":[
        "Huaycho"
    ],
    "name:spa_x_variant":[
        "Hoaycho"
    ],
    "wof:name":"Huaycho",
    "wof:placetype":"locality"
},
  "geometry": {"coordinates":[-68.73374,-15.81438],"type":"Point"}
}