{
  "type": "Feature",
  "properties": {
    "gn:admin1_code":"05",
    "gn:asciiname":"Concepcion de Belen",
    "gn:country_code":"BO",
    "gn:dem":3673,
    "gn:feature_class":"P",
    "gn:feature_code":"PPL",
    "gn:name":"Concepci\u00f3n de Bel\u00e9n",
    "gn:population":0,
    "gn:timezone":"America/La_Paz",
    "iso:country":"BO",
    "wof:name":"Concepcion de Belen",
    "wof:placetype":"locality"
},
  "geometry": {"coordinates":[-67.88043,-19.19516],"type":"Point"}
}