{
  "type": "Feature",
  "properties": {
    "gn:country":"BO",
    "gn:fcode":"PPL",
    "gn:population":26,
    "iso:country":"BO",
    "qs_pg:aaroncc":"BO",
    "qs_pg:gn_country":"BO",
    "qs_pg:gn_fcode":"PPL",
    "qs_pg:gn_pop":26,
    "qs_pg:name":"Juchuy Vilaque",
    "qs_pg:photos_9r":0,
    "qs_pg:photos_sr":0,
    "qs_pg:pop_sr":1,
    "qs_pg:qs_pg_placetype":"locality",
    "wof:name":"Juchuy Vilaque",
    "wof:placetype":"locality",
    "wof:population":26
},
  "geometry": {"coordinates":[-65.04809,-17.8063],"type":"Point"}
}