{
  "type": "Feature",
  "properties": {
    "gn:admin1_code":"4.0",
    "gn:asciiname":"Kurusani",
    "gn:country_code":"BO",
    "gn:dem":3801,
    "gn:feature_class":"P",
    "gn:feature_code":"PPL",
    "gn:name":"Kurusani",
    "gn:population":0,
    "gn:timezone":"America/La_Paz",
    "iso:country":"BO",
    "wof:name":"Kurusani",
    "wof:placetype":"locality"
},
  "geometry": {"coordinates":[-68.56667,-17.41667],"type":"Point"}
}