{
  "type": "Feature",
  "properties": {
    "gn:admin1_code":"1.0",
    "gn:asciiname":"Rupi Kocha",
    "gn:country_code":"BO",
    "gn:dem":3582,
    "gn:feature_class":"P",
    "gn:feature_code":"PPL",
    "gn:name":"Rupi Kocha",
    "gn:population":0,
    "gn:timezone":"America/La_Paz",
    "iso:country":"BO",
    "name:und_x_variant":[
        "Estancia Chrupi Ckocha",
        "Rupi Kocha"
    ],
    "wof:name":"Rupi Kocha",
    "wof:placetype":"locality"
},
  "geometry": {"coordinates":[-65.23739999999999,-20.08096],"type":"Point"}
}