{
  "type": "Feature",
  "properties": {
    "gn:admin1_code":"4.0",
    "gn:asciiname":"Estancia Kellu Pata",
    "gn:country_code":"BO",
    "gn:dem":5751,
    "gn:feature_class":"P",
    "gn:feature_code":"PPL",
    "gn:name":"Estancia Kellu Pata",
    "gn:population":0,
    "gn:timezone":"America/La_Paz",
    "iso:country":"BO",
    "name:spa_x_preferred":[
        "Estancia Kellu Pata"
    ],
    "name:spa_x_variant":[
        "Khello"
    ],
    "wof:name":"Estancia Kellu Pata",
    "wof:placetype":"locality"
},
  "geometry": {"coordinates":[-69.19147,-14.9136],"type":"Point"}
}