{
  "type": "Feature",
  "properties": {
    "gn:admin1_code":"1.0",
    "gn:asciiname":"La Quemada",
    "gn:country_code":"BO",
    "gn:dem":2366,
    "gn:feature_class":"P",
    "gn:feature_code":"PPL",
    "gn:name":"La Quemada",
    "gn:population":0,
    "gn:timezone":"America/La_Paz",
    "iso:country":"BO",
    "name:deu_x_preferred":[
        "La Quemada"
    ],
    "name:jpn_x_preferred":[
        "\u30e9\u30fb\u30b1\u30de\u30fc\u30c0"
    ],
    "name:nld_x_preferred":[
        "La Quemada"
    ],
    "name:por_x_preferred":[
        "La Quemada"
    ],
    "name:rus_x_preferred":[
        "\u041b\u0430-\u041a\u0435\u043c\u0430\u0434\u0430"
    ],
    "name:spa_x_preferred":[
        "La Quemada"
    ],
    "name:swe_x_preferred":[
        "La Quemada"
    ],
    "wof:name":"La Quemada",
    "wof:placetype":"locality"
},
  "geometry": {"coordinates":[-65.29784000000001,-20.74523],"type":"Point"}
}