{
  "type": "Feature",
  "properties": {
    "gn:admin1_code":"5.0",
    "gn:asciiname":"Estancia Tholachiro",
    "gn:country_code":"BO",
    "gn:dem":3722,
    "gn:feature_class":"P",
    "gn:feature_code":"PPL",
    "gn:name":"Estancia Tholachiro",
    "gn:population":0,
    "gn:timezone":"America/La_Paz",
    "iso:country":"BO",
    "wof:name":"Estancia Tholachiro",
    "wof:placetype":"locality"
},
  "geometry": {"coordinates":[-67.38333,-17.88332999999999],"type":"Point"}
}