{
  "type": "Feature",
  "properties": {
    "gn:admin1_code":"08",
    "gn:asciiname":"Agua Fea",
    "gn:country_code":"BO",
    "gn:dem":401,
    "gn:feature_class":"P",
    "gn:feature_code":"PPL",
    "gn:name":"Agua Fea",
    "gn:population":0,
    "gn:timezone":"America/La_Paz",
    "iso:country":"BO",
    "wof:name":"Agua Fea",
    "wof:placetype":"locality"
},
  "geometry": {"coordinates":[-63.03333000000001,-18.96667],"type":"Point"}
}