{
  "type": "Feature",
  "properties": {
    "gn:admin1_code":"08",
    "gn:asciiname":"Caracara",
    "gn:country_code":"BO",
    "gn:dem":847,
    "gn:feature_class":"P",
    "gn:feature_code":"PPL",
    "gn:name":"Caracara",
    "gn:population":0,
    "gn:timezone":"America/La_Paz",
    "iso:country":"BO",
    "wof:name":"Caracara",
    "wof:placetype":"locality"
},
  "geometry": {"coordinates":[-63.38106,-19.25198],"type":"Point"}
}