{
  "type": "Feature",
  "properties": {
    "gn:admin1_code":"6.0",
    "gn:asciiname":"Manorana",
    "gn:cc2":"BO",
    "gn:country_code":"BO",
    "gn:dem":156,
    "gn:feature_class":"P",
    "gn:feature_code":"PPL",
    "gn:name":"Manorana",
    "gn:population":0,
    "gn:timezone":"America/La_Paz",
    "iso:country":"BO",
    "name:und_x_variant":[
        "Manorena",
        "Manorana"
    ],
    "wof:name":"Manorana",
    "wof:placetype":"locality"
},
  "geometry": {"coordinates":[-66.11667,-10.16667],"type":"Point"}
}