{
  "type": "Feature",
  "properties": {
    "gn:admin1_code":"04",
    "gn:asciiname":"Ancoma Norte",
    "gn:country_code":"BO",
    "gn:dem":3779,
    "gn:feature_class":"P",
    "gn:feature_code":"PPL",
    "gn:name":"Ancoma Norte",
    "gn:population":0,
    "gn:timezone":"America/La_Paz",
    "iso:country":"BO",
    "name:spa_x_preferred":[
        "Ancoma Norte"
    ],
    "name:spa_x_variant":[
        "Ancoma"
    ],
    "wof:name":"Ancoma Norte",
    "wof:placetype":"locality"
},
  "geometry": {"coordinates":[-68.51306,-15.74639],"type":"Point"}
}