{
  "type": "Feature",
  "properties": {
    "gn:admin1_code":"1.0",
    "gn:asciiname":"Kasa",
    "gn:country_code":"BO",
    "gn:dem":3163,
    "gn:feature_class":"P",
    "gn:feature_code":"PPL",
    "gn:name":"Kasa",
    "gn:population":0,
    "gn:timezone":"America/La_Paz",
    "iso:country":"BO",
    "name:aze_x_preferred":[
        "Kasa"
    ],
    "name:ceb_x_preferred":[
        "Kasa"
    ],
    "name:deu_x_preferred":[
        "Kasa"
    ],
    "name:fra_x_preferred":[
        "Kasa"
    ],
    "name:ind_x_preferred":[
        "Kasa"
    ],
    "name:ita_x_preferred":[
        "Kasa"
    ],
    "name:pol_x_preferred":[
        "Kasa"
    ],
    "name:que_x_preferred":[
        "Kasa"
    ],
    "name:spa_x_preferred":[
        "Kasa"
    ],
    "name:swe_x_preferred":[
        "Kasa"
    ],
    "name:und_x_variant":[
        "Estancia Pampa Khasa"
    ],
    "name:vie_x_preferred":[
        "Kasa"
    ],
    "wof:name":"Kasa",
    "wof:placetype":"locality"
},
  "geometry": {"coordinates":[-65.45918,-18.86372],"type":"Point"}
}