{
  "type": "Feature",
  "properties": {
    "gn:admin1_code":"06",
    "gn:asciiname":"Sobrau",
    "gn:country_code":"BO",
    "gn:dem":251,
    "gn:feature_class":"P",
    "gn:feature_code":"PPL",
    "gn:name":"Sobrau",
    "gn:population":0,
    "gn:timezone":"America/La_Paz",
    "iso:country":"BO",
    "wof:name":"Sobrau",
    "wof:placetype":"locality"
},
  "geometry": {"coordinates":[-69.03811999999999,-11.02721],"type":"Point"}
}