{
  "type": "Feature",
  "properties": {
    "gn:admin1_code":"3.0",
    "gn:asciiname":"Guanay",
    "gn:country_code":"BO",
    "gn:dem":158,
    "gn:feature_class":"P",
    "gn:feature_code":"PPL",
    "gn:name":"Guanay",
    "gn:population":0,
    "gn:timezone":"America/La_Paz",
    "iso:country":"BO",
    "name:ceb_x_preferred":[
        "Guanay"
    ],
    "name:deu_x_preferred":[
        "Guanay"
    ],
    "name:fra_x_preferred":[
        "Guanay"
    ],
    "name:ita_x_preferred":[
        "Guanay"
    ],
    "name:que_x_preferred":[
        "Wanay llaqta"
    ],
    "name:swe_x_preferred":[
        "Guanay"
    ],
    "wof:name":"Guanay",
    "wof:placetype":"locality"
},
  "geometry": {"coordinates":[-66.26666999999999,-12.15],"type":"Point"}
}