{
  "type": "Feature",
  "properties": {
    "gn:admin1_code":"4.0",
    "gn:asciiname":"Umala",
    "gn:country_code":"BO",
    "gn:dem":3826,
    "gn:feature_class":"P",
    "gn:feature_code":"PPL",
    "gn:name":"Umala",
    "gn:population":0,
    "gn:timezone":"America/La_Paz",
    "iso:country":"BO",
    "wof:name":"Umala",
    "wof:placetype":"locality"
},
  "geometry": {"coordinates":[-68.02331,-17.37353],"type":"Point"}
}