{
  "type": "Feature",
  "properties": {
    "gn:admin1_code":"5.0",
    "gn:asciiname":"Serkaka",
    "gn:country_code":"BO",
    "gn:dem":3901,
    "gn:feature_class":"P",
    "gn:feature_code":"PPL",
    "gn:name":"Serkaka",
    "gn:population":0,
    "gn:timezone":"America/La_Paz",
    "iso:country":"BO",
    "name:und_x_variant":[
        "Kalajahuira",
        "Serkaka"
    ],
    "wof:name":"Serkaka",
    "wof:placetype":"locality"
},
  "geometry": {"coordinates":[-66.92108,-18.40167000000001],"type":"Point"}
}