{
  "type": "Feature",
  "properties": {
    "gn:admin1_code":"07",
    "gn:asciiname":"Estancia Khellu Mokho",
    "gn:country_code":"BO",
    "gn:dem":3167,
    "gn:feature_class":"P",
    "gn:feature_code":"PPL",
    "gn:name":"Estancia Khellu Mokho",
    "gn:population":0,
    "gn:timezone":"America/La_Paz",
    "iso:country":"BO",
    "wof:name":"Estancia Khellu Mokho",
    "wof:placetype":"locality"
},
  "geometry": {"coordinates":[-65.03036,-19.54585],"type":"Point"}
}