{
  "type": "Feature",
  "properties": {
    "gn:admin1_code":"06",
    "gn:asciiname":"Tokio",
    "gn:country_code":"BO",
    "gn:dem":235,
    "gn:feature_class":"P",
    "gn:feature_code":"PPL",
    "gn:name":"Tokio",
    "gn:population":0,
    "gn:timezone":"America/La_Paz",
    "iso:country":"BO",
    "name:deu_x_preferred":[
        "Tokio"
    ],
    "name:ita_x_preferred":[
        "Tokio"
    ],
    "name:jpn_x_preferred":[
        "\u30c8\u30ad\u30aa"
    ],
    "name:nds_x_preferred":[
        "Tokio"
    ],
    "name:rus_x_preferred":[
        "Tokio"
    ],
    "name:spa_x_preferred":[
        "Tokio"
    ],
    "name:srp_x_preferred":[
        "\u0422\u043e\u043a\u0438\u043e"
    ],
    "wof:name":"Tokio",
    "wof:placetype":"locality"
},
  "geometry": {"coordinates":[-68.44895,-11.44115],"type":"Point"}
}