{
  "type": "Feature",
  "properties": {
    "gn:admin1_code":"06",
    "gn:asciiname":"Tokio",
    "gn:country_code":"BO",
    "gn:dem":235,
    "gn:feature_class":"P",
    "gn:feature_code":"PPL",
    "gn:name":"Tokio",
    "gn:population":0,
    "gn:timezone":"America/La_Paz",
    "iso:country":"BO",
    "name:spa_x_preferred":[
        "Tokio"
    ],
    "wof:name":"Tokio",
    "wof:placetype":"locality"
},
  "geometry": {"coordinates":[-68.44895,-11.44115],"type":"Point"}
}