{
  "type": "Feature",
  "properties": {
    "gn:admin1_code":"5.0",
    "gn:asciiname":"Maulli",
    "gn:cc2":"BO",
    "gn:country_code":"BO",
    "gn:dem":4453,
    "gn:feature_class":"P",
    "gn:feature_code":"PPL",
    "gn:name":"Maulli",
    "gn:population":0,
    "gn:timezone":"America/La_Paz",
    "iso:country":"BO",
    "name:und_x_variant":[
        "Mucli",
        "Mucilli",
        "Muclli",
        "Maulli"
    ],
    "wof:name":"Maulli",
    "wof:placetype":"locality"
},
  "geometry": {"coordinates":[-66.86667,-17.71667],"type":"Point"}
}