{
  "type": "Feature",
  "properties": {
    "gn:admin1_code":"09",
    "gn:asciiname":"Aguaditas",
    "gn:country_code":"BO",
    "gn:dem":936,
    "gn:feature_class":"P",
    "gn:feature_code":"PPL",
    "gn:name":"Aguaditas",
    "gn:population":0,
    "gn:timezone":"America/La_Paz",
    "iso:country":"BO",
    "wof:name":"Aguaditas",
    "wof:placetype":"locality"
},
  "geometry": {"coordinates":[-64.13321999999999,-21.33882],"type":"Point"}
}