{
  "type": "Feature",
  "properties": {
    "gn:admin1_code":"03",
    "gn:asciiname":"Alianza",
    "gn:cc2":"BO",
    "gn:country_code":"BO",
    "gn:dem":120,
    "gn:feature_class":"P",
    "gn:feature_code":"PPL",
    "gn:name":"Alianza",
    "gn:population":0,
    "gn:timezone":"America/La_Paz",
    "iso:country":"BO",
    "name:ceb_x_preferred":[
        "Alianza"
    ],
    "name:por_x_preferred":[
        "Alianza"
    ],
    "name:spa_x_preferred":[
        "Alianza"
    ],
    "name:swe_x_preferred":[
        "Alianza"
    ],
    "name:und_x_variant":[
        "Aliaza"
    ],
    "wof:name":"Alianza",
    "wof:placetype":"locality"
},
  "geometry": {"coordinates":[-66.05,-10.93333],"type":"Point"}
}