{
  "type": "Feature",
  "properties": {
    "gn:admin1_code":"8.0",
    "gn:asciiname":"Rincon de Pailas",
    "gn:country_code":"BO",
    "gn:dem":331,
    "gn:feature_class":"P",
    "gn:feature_code":"PPL",
    "gn:name":"Rinc\u00f3n de Pailas",
    "gn:population":0,
    "gn:timezone":"America/La_Paz",
    "iso:country":"BO",
    "wof:name":"Rincon de Pailas",
    "wof:placetype":"locality"
},
  "geometry": {"coordinates":[-62.95,-17.63332999999999],"type":"Point"}
}