{
  "type": "Feature",
  "properties": {
    "gn:admin1_code":"7.0",
    "gn:asciiname":"Sora Sora",
    "gn:country_code":"BO",
    "gn:dem":4298,
    "gn:feature_class":"P",
    "gn:feature_code":"PPL",
    "gn:name":"Sora Sora",
    "gn:population":0,
    "gn:timezone":"America/La_Paz",
    "iso:country":"BO",
    "wof:name":"Sora Sora",
    "wof:placetype":"locality"
},
  "geometry": {"coordinates":[-66.41121,-19.27529],"type":"Point"}
}