{
  "type": "Feature",
  "properties": {
    "gn:admin1_code":"5.0",
    "gn:asciiname":"Pequereque",
    "gn:country_code":"BO",
    "gn:dem":3781,
    "gn:feature_class":"P",
    "gn:feature_code":"PPL",
    "gn:name":"Pequereque",
    "gn:population":0,
    "gn:timezone":"America/La_Paz",
    "iso:country":"BO",
    "wof:name":"Pequereque",
    "wof:placetype":"locality"
},
  "geometry": {"coordinates":[-66.70896999999999,-18.83126],"type":"Point"}
}