{
  "type": "Feature",
  "properties": {
    "gn:admin1_code":"08",
    "gn:asciiname":"Barraca Vibora",
    "gn:country_code":"BO",
    "gn:dem":223,
    "gn:feature_class":"P",
    "gn:feature_code":"PPL",
    "gn:name":"Barraca V\u00edbora",
    "gn:population":0,
    "gn:timezone":"America/La_Paz",
    "iso:country":"BO",
    "wof:name":"Barraca Vibora",
    "wof:placetype":"locality"
},
  "geometry": {"coordinates":[-64.55,-17.03333],"type":"Point"}
}