{
  "type": "Feature",
  "properties": {
    "gn:admin1_code":"7.0",
    "gn:asciiname":"Taguacomuno",
    "gn:cc2":"BO",
    "gn:country_code":"BO",
    "gn:dem":4104,
    "gn:feature_class":"P",
    "gn:feature_code":"PPL",
    "gn:name":"Taguacomu\u00f1o",
    "gn:population":0,
    "gn:timezone":"America/La_Paz",
    "iso:country":"BO",
    "name:und_x_variant":[
        "Toguacomu\u00f1a",
        "Taguacomu\u00f1o"
    ],
    "wof:name":"Taguacomuno",
    "wof:placetype":"locality"
},
  "geometry": {"coordinates":[-65.75,-19.71667],"type":"Point"}
}