{
  "type": "Feature",
  "properties": {
    "gn:admin1_code":"06",
    "gn:asciiname":"Oro Negro",
    "gn:country_code":"BO",
    "gn:dem":174,
    "gn:feature_class":"P",
    "gn:feature_code":"PPL",
    "gn:name":"Oro Negro",
    "gn:population":0,
    "gn:timezone":"America/La_Paz",
    "iso:country":"BO",
    "name:spa_x_preferred":[
        "Oro Negro"
    ],
    "wof:name":"Oro Negro",
    "wof:placetype":"locality"
},
  "geometry": {"coordinates":[-67.57441999999999,-11.04897],"type":"Point"}
}