{
  "type": "Feature",
  "properties": {
    "gn:admin1_code":"2.0",
    "gn:asciiname":"Cerro Ojrani",
    "gn:country_code":"BO",
    "gn:dem":4484,
    "gn:feature_class":"P",
    "gn:feature_code":"PPL",
    "gn:name":"Cerro Ojrani",
    "gn:population":0,
    "gn:timezone":"America/La_Paz",
    "iso:country":"BO",
    "wof:name":"Cerro Ojrani",
    "wof:placetype":"locality"
},
  "geometry": {"coordinates":[-66.86667,-17.51667],"type":"Point"}
}