{
  "type": "Feature",
  "properties": {
    "gn:admin1_code":"04",
    "gn:asciiname":"Cotana",
    "gn:country_code":"BO",
    "gn:dem":3151,
    "gn:feature_class":"P",
    "gn:feature_code":"PPL",
    "gn:name":"Cota\u00f1a",
    "gn:population":0,
    "gn:timezone":"America/La_Paz",
    "iso:country":"BO",
    "name:ceb_x_preferred":[
        "Cotana"
    ],
    "name:por_x_preferred":[
        "Cotana"
    ],
    "name:swe_x_preferred":[
        "Cotana"
    ],
    "name:und_x_variant":[
        "Cotano",
        "Cota\u00f1a"
    ],
    "name:war_x_preferred":[
        "Cotana"
    ],
    "wof:name":"Cotana",
    "wof:placetype":"locality"
},
  "geometry": {"coordinates":[-68.62501999999999,-15.81325],"type":"Point"}
}