{
  "type": "Feature",
  "properties": {
    "gn:admin1_code":"5.0",
    "gn:asciiname":"Estancia Vila Kkollu",
    "gn:country_code":"BO",
    "gn:dem":3680,
    "gn:feature_class":"P",
    "gn:feature_code":"PPL",
    "gn:name":"Estancia Vila Kkollu",
    "gn:population":0,
    "gn:timezone":"America/La_Paz",
    "iso:country":"BO",
    "wof:name":"Estancia Vila Kkollu",
    "wof:placetype":"locality"
},
  "geometry": {"coordinates":[-68.33629000000001,-19.27606],"type":"Point"}
}