{
  "type": "Feature",
  "properties": {
    "gn:admin1_code":"04",
    "gn:asciiname":"Calvario Chocorosi",
    "gn:cc2":"BO",
    "gn:country_code":"BO",
    "gn:dem":3990,
    "gn:feature_class":"P",
    "gn:feature_code":"PPL",
    "gn:name":"Calvario Chocoros\u00ed",
    "gn:population":0,
    "gn:timezone":"America/La_Paz",
    "iso:country":"BO",
    "name:und_x_variant":[
        "Chocorosi",
        "Calvario Chocoros\u00ed"
    ],
    "wof:name":"Calvario Chocorosi",
    "wof:placetype":"locality"
},
  "geometry": {"coordinates":[-69.31667,-17.01667],"type":"Point"}
}