{
  "type": "Feature",
  "properties": {
    "gn:admin1_code":"8.0",
    "gn:asciiname":"Mosqueras",
    "gn:country_code":"BO",
    "gn:dem":1164,
    "gn:feature_class":"P",
    "gn:feature_code":"PPL",
    "gn:name":"Mosqueras",
    "gn:population":0,
    "gn:timezone":"America/La_Paz",
    "iso:country":"BO",
    "wof:name":"Mosqueras",
    "wof:placetype":"locality"
},
  "geometry": {"coordinates":[-63.72801,-18.36977000000001],"type":"Point"}
}