{
  "type": "Feature",
  "properties": {
    "gn:admin1_code":"07",
    "gn:asciiname":"Chaquilla",
    "gn:country_code":"BO",
    "gn:dem":3951,
    "gn:feature_class":"P",
    "gn:feature_code":"PPL",
    "gn:name":"Chaquilla",
    "gn:population":0,
    "gn:timezone":"America/La_Paz",
    "iso:country":"BO",
    "wof:name":"Chaquilla",
    "wof:placetype":"locality"
},
  "geometry": {"coordinates":[-66.09045,-19.81118],"type":"Point"}
}