{
  "type": "Feature",
  "properties": {
    "gn:admin1_code":"4.0",
    "gn:asciiname":"Estancia Sipesipe",
    "gn:country_code":"BO",
    "gn:dem":3882,
    "gn:feature_class":"P",
    "gn:feature_code":"PPL",
    "gn:name":"Estancia Sipesipe",
    "gn:population":0,
    "gn:timezone":"America/La_Paz",
    "iso:country":"BO",
    "wof:name":"Estancia Sipesipe",
    "wof:placetype":"locality"
},
  "geometry": {"coordinates":[-67.78333000000001,-17.36667000000001],"type":"Point"}
}