{
  "type": "Feature",
  "properties": {
    "gn:admin1_code":"04",
    "gn:asciiname":"Estancia Finaya",
    "gn:country_code":"BO",
    "gn:dem":3965,
    "gn:feature_class":"P",
    "gn:feature_code":"PPL",
    "gn:name":"Estancia Finaya",
    "gn:population":0,
    "gn:timezone":"America/La_Paz",
    "iso:country":"BO",
    "wof:name":"Estancia Finaya",
    "wof:placetype":"locality"
},
  "geometry": {"coordinates":[-68.16667,-16.86667000000001],"type":"Point"}
}