{
  "type": "Feature",
  "properties": {
    "gn:admin1_code":"5.0",
    "gn:asciiname":"Tunavi",
    "gn:country_code":"BO",
    "gn:dem":3702,
    "gn:feature_class":"P",
    "gn:feature_code":"PPL",
    "gn:name":"Tunavi",
    "gn:population":0,
    "gn:timezone":"America/La_Paz",
    "iso:country":"BO",
    "wof:name":"Tunavi",
    "wof:placetype":"locality"
},
  "geometry": {"coordinates":[-67.47367,-19.32109],"type":"Point"}
}