{
  "type": "Feature",
  "properties": {
    "gn:admin1_code":"6.0",
    "gn:asciiname":"Melandros",
    "gn:cc2":"BO",
    "gn:country_code":"BO",
    "gn:dem":259,
    "gn:feature_class":"P",
    "gn:feature_code":"PPL",
    "gn:name":"Melandros",
    "gn:population":0,
    "gn:timezone":"America/La_Paz",
    "iso:country":"BO",
    "name:und_x_variant":[
        "Meiandros",
        "Melandros"
    ],
    "wof:name":"Melandros",
    "wof:placetype":"locality"
},
  "geometry": {"coordinates":[-68.36667,-11.15],"type":"Point"}
}