{
  "type": "Feature",
  "properties": {
    "gn:admin1_code":"8.0",
    "gn:asciiname":"Puerto Grether",
    "gn:cc2":"BO",
    "gn:country_code":"BO",
    "gn:dem":235,
    "gn:feature_class":"P",
    "gn:feature_code":"PPL",
    "gn:name":"Puerto Grether",
    "gn:population":0,
    "gn:timezone":"America/La_Paz",
    "iso:country":"BO",
    "name:und_x_variant":[
        "Puerto Gretner",
        "Puerto Grether"
    ],
    "wof:name":"Puerto Grether",
    "wof:placetype":"locality"
},
  "geometry": {"coordinates":[-64.34999999999999,-17.18333],"type":"Point"}
}