{
  "type": "Feature",
  "properties": {
    "gn:admin1_code":"8.0",
    "gn:asciiname":"Tembladeras",
    "gn:country_code":"BO",
    "gn:dem":1864,
    "gn:feature_class":"P",
    "gn:feature_code":"PPL",
    "gn:name":"Tembladeras",
    "gn:population":0,
    "gn:timezone":"America/La_Paz",
    "iso:country":"BO",
    "wof:name":"Tembladeras",
    "wof:placetype":"locality"
},
  "geometry": {"coordinates":[-64.01666999999999,-18.31667],"type":"Point"}
}