{
  "type": "Feature",
  "properties": {
    "gn:admin1_code":"3.0",
    "gn:asciiname":"Los Paquitos",
    "gn:country_code":"BO",
    "gn:dem":150,
    "gn:feature_class":"P",
    "gn:feature_code":"PPL",
    "gn:name":"Los Paquitos",
    "gn:population":0,
    "gn:timezone":"America/La_Paz",
    "iso:country":"BO",
    "wof:name":"Los Paquitos",
    "wof:placetype":"locality"
},
  "geometry": {"coordinates":[-65.75,-11.16667],"type":"Point"}
}