{
  "type": "Feature",
  "properties": {
    "gn:admin1_code":"8.0",
    "gn:asciiname":"Icuati",
    "gn:country_code":"BO",
    "gn:dem":803,
    "gn:feature_class":"P",
    "gn:feature_code":"PPL",
    "gn:name":"Icuati",
    "gn:population":0,
    "gn:timezone":"America/La_Paz",
    "iso:country":"BO",
    "wof:name":"Icuati",
    "wof:placetype":"locality"
},
  "geometry": {"coordinates":[-63.18333000000001,-19.65],"type":"Point"}
}