{
  "type": "Feature",
  "properties": {
    "gn:admin1_code":"08",
    "gn:asciiname":"Destierro",
    "gn:cc2":"BO",
    "gn:country_code":"BO",
    "gn:dem":222,
    "gn:feature_class":"P",
    "gn:feature_code":"PPL",
    "gn:name":"Destierro",
    "gn:population":0,
    "gn:timezone":"America/La_Paz",
    "iso:country":"BO",
    "name:und_x_variant":[
        "El Carmen",
        "Destierro"
    ],
    "wof:name":"Destierro",
    "wof:placetype":"locality"
},
  "geometry": {"coordinates":[-62.08333,-14.61667],"type":"Point"}
}