{
  "type": "Feature",
  "properties": {
    "gn:admin1_code":"2.0",
    "gn:asciiname":"Itiripampa",
    "gn:cc2":"BO",
    "gn:country_code":"BO",
    "gn:dem":1693,
    "gn:feature_class":"P",
    "gn:feature_code":"PPL",
    "gn:name":"Itiripampa",
    "gn:population":0,
    "gn:timezone":"America/La_Paz",
    "iso:country":"BO",
    "name:und_x_variant":[
        "Itirapampa",
        "Itimpampa",
        "Itiripampa"
    ],
    "wof:name":"Itiripampa",
    "wof:placetype":"locality"
},
  "geometry": {"coordinates":[-65.76666999999999,-17.11667000000001],"type":"Point"}
}