{
  "type": "Feature",
  "properties": {
    "gn:admin1_code":"7.0",
    "gn:asciiname":"Sillmaloma",
    "gn:country_code":"BO",
    "gn:dem":3782,
    "gn:feature_class":"P",
    "gn:feature_code":"PPL",
    "gn:name":"Sillmaloma",
    "gn:population":0,
    "gn:timezone":"America/La_Paz",
    "iso:country":"BO",
    "wof:name":"Sillmaloma",
    "wof:placetype":"locality"
},
  "geometry": {"coordinates":[-66.51666999999999,-20.56667],"type":"Point"}
}