{
  "type": "Feature",
  "properties": {
    "gn:admin1_code":"4.0",
    "gn:asciiname":"Santiago de Pacaguaras",
    "gn:country_code":"BO",
    "gn:dem":185,
    "gn:feature_class":"P",
    "gn:feature_code":"PPL",
    "gn:name":"Santiago de Pacaguaras",
    "gn:population":0,
    "gn:timezone":"America/La_Paz",
    "iso:country":"BO",
    "wof:name":"Santiago de Pacaguaras",
    "wof:placetype":"locality"
},
  "geometry": {"coordinates":[-68.01666999999999,-13.03333],"type":"Point"}
}