{
  "type": "Feature",
  "properties": {
    "gn:admin1_code":"04",
    "gn:asciiname":"Chuegara",
    "gn:cc2":"BO",
    "gn:country_code":"BO",
    "gn:dem":3920,
    "gn:feature_class":"P",
    "gn:feature_code":"PPL",
    "gn:name":"Chuegara",
    "gn:population":0,
    "gn:timezone":"America/La_Paz",
    "iso:country":"BO",
    "name:und_x_variant":[
        "Chungara",
        "Chuegara"
    ],
    "wof:name":"Chuegara",
    "wof:placetype":"locality"
},
  "geometry": {"coordinates":[-67.96666999999999,-17.15],"type":"Point"}
}