{
  "type": "Feature",
  "properties": {
    "gn:admin1_code":"04",
    "gn:asciiname":"Estancia Ajnuri",
    "gn:country_code":"BO",
    "gn:dem":3861,
    "gn:feature_class":"P",
    "gn:feature_code":"PPL",
    "gn:name":"Estancia Ajnuri",
    "gn:population":0,
    "gn:timezone":"America/La_Paz",
    "iso:country":"BO",
    "wof:name":"Estancia Ajnuri",
    "wof:placetype":"locality"
},
  "geometry": {"coordinates":[-68.71666999999999,-17.01667],"type":"Point"}
}