{
  "type": "Feature",
  "properties": {
    "gn:admin1_code":"04",
    "gn:asciiname":"Crucero",
    "gn:country_code":"BO",
    "gn:dem":1122,
    "gn:feature_class":"P",
    "gn:feature_code":"PPL",
    "gn:name":"Crucero",
    "gn:population":0,
    "gn:timezone":"America/La_Paz",
    "iso:country":"BO",
    "name:ceb_x_preferred":[
        "Crucero"
    ],
    "name:fas_x_preferred":[
        "\u06a9\u0631\u0648\u062b\u0631\u0648"
    ],
    "name:swe_x_preferred":[
        "Crucero"
    ],
    "wof:name":"Crucero",
    "wof:placetype":"locality"
},
  "geometry": {"coordinates":[-67.61667,-15.85],"type":"Point"}
}