{
  "type": "Feature",
  "properties": {
    "gn:admin1_code":"06",
    "gn:asciiname":"Puerto Sucre",
    "gn:country_code":"BO",
    "gn:dem":167,
    "gn:feature_class":"P",
    "gn:feature_code":"PPL",
    "gn:name":"Puerto Sucre",
    "gn:population":0,
    "gn:timezone":"America/La_Paz",
    "iso:country":"BO",
    "name:spa_x_preferred":[
        "Puerto Sucre"
    ],
    "wof:name":"Puerto Sucre",
    "wof:placetype":"locality"
},
  "geometry": {"coordinates":[-67.71666999999999,-11.27537],"type":"Point"}
}