{
  "type": "Feature",
  "properties": {
    "gn:admin1_code":"2.0",
    "gn:asciiname":"Siquipampa",
    "gn:country_code":"BO",
    "gn:dem":3853,
    "gn:feature_class":"P",
    "gn:feature_code":"PPL",
    "gn:name":"Siquipampa",
    "gn:population":0,
    "gn:timezone":"America/La_Paz",
    "iso:country":"BO",
    "wof:name":"Siquipampa",
    "wof:placetype":"locality"
},
  "geometry": {"coordinates":[-66.71666999999999,-17.76667],"type":"Point"}
}