{
  "type": "Feature",
  "properties": {
    "gn:admin1_code":"06",
    "gn:asciiname":"Planchon Dos",
    "gn:country_code":"BO",
    "gn:dem":297,
    "gn:feature_class":"P",
    "gn:feature_code":"PPL",
    "gn:name":"Planchon Dos",
    "gn:population":0,
    "gn:timezone":"America/La_Paz",
    "iso:country":"BO",
    "name:spa_x_preferred":[
        "Planchon Dos"
    ],
    "wof:name":"Planchon Dos",
    "wof:placetype":"locality"
},
  "geometry": {"coordinates":[-68.78003000000001,-11.4549],"type":"Point"}
}