{
  "type": "Feature",
  "properties": {
    "gn:admin1_code":"7.0",
    "gn:asciiname":"Sailoma",
    "gn:country_code":"BO",
    "gn:dem":3849,
    "gn:feature_class":"P",
    "gn:feature_code":"PPL",
    "gn:name":"Sailoma",
    "gn:population":0,
    "gn:timezone":"America/La_Paz",
    "iso:country":"BO",
    "wof:name":"Sailoma",
    "wof:placetype":"locality"
},
  "geometry": {"coordinates":[-65.84999999999999,-20.93333],"type":"Point"}
}