{
  "type": "Feature",
  "properties": {
    "gn:admin1_code":"8.0",
    "gn:asciiname":"Las Conchas",
    "gn:cc2":"BO",
    "gn:country_code":"BO",
    "gn:dem":263,
    "gn:feature_class":"P",
    "gn:feature_code":"PPL",
    "gn:name":"Las Conchas",
    "gn:population":0,
    "gn:timezone":"America/La_Paz",
    "iso:country":"BO",
    "name:und_x_variant":[
        "Las Canchas",
        "Las Conchas"
    ],
    "wof:name":"Las Conchas",
    "wof:placetype":"locality"
},
  "geometry": {"coordinates":[-62.88333000000001,-17.33333],"type":"Point"}
}