{
  "type": "Feature",
  "properties": {
    "gn:admin1_code":"4.0",
    "gn:asciiname":"Tahari",
    "gn:country_code":"BO",
    "gn:dem":3831,
    "gn:feature_class":"P",
    "gn:feature_code":"PPL",
    "gn:name":"Tahari",
    "gn:population":0,
    "gn:timezone":"America/La_Paz",
    "iso:country":"BO",
    "name:und_x_variant":[
        "Tavi",
        "Tari",
        "Tahari"
    ],
    "wof:name":"Tahari",
    "wof:placetype":"locality"
},
  "geometry": {"coordinates":[-68.68659,-15.95424],"type":"Point"}
}