{
  "type": "Feature",
  "properties": {
    "gn:admin1_code":"09",
    "gn:asciiname":"El Yuchan",
    "gn:country_code":"BO",
    "gn:dem":313,
    "gn:feature_class":"P",
    "gn:feature_code":"PPL",
    "gn:name":"El Yuchan",
    "gn:population":0,
    "gn:timezone":"America/La_Paz",
    "iso:country":"BO",
    "wof:name":"El Yuchan",
    "wof:placetype":"locality"
},
  "geometry": {"coordinates":[-63.01667,-21.85],"type":"Point"}
}