{
  "type": "Feature",
  "properties": {
    "gn:admin1_code":"4.0",
    "gn:asciiname":"Isca Casca",
    "gn:cc2":"BO",
    "gn:country_code":"BO",
    "gn:dem":3860,
    "gn:feature_class":"P",
    "gn:feature_code":"PPL",
    "gn:name":"Isca Casca",
    "gn:population":0,
    "gn:timezone":"America/La_Paz",
    "iso:country":"BO",
    "name:und_x_variant":[
        "Hisca Casca",
        "Isca Casca"
    ],
    "wof:name":"Isca Casca",
    "wof:placetype":"locality"
},
  "geometry": {"coordinates":[-68.51666999999999,-16.53333],"type":"Point"}
}