{
  "type": "Feature",
  "properties": {
    "iso:country":"BO",
    "name:ara_x_preferred":[
        "\u0633\u0627\u0646\u062a\u0627 \u0631\u064a\u062a\u0627"
    ],
    "name:ben_x_preferred":[
        "\u09b8\u09be\u09a8\u09cd\u09a4\u09be \u09b0\u09bf\u09a4\u09be"
    ],
    "name:ceb_x_preferred":[
        "Santa Rita"
    ],
    "name:deu_x_preferred":[
        "Santa Rita"
    ],
    "name:ell_x_preferred":[
        "\u03a3\u03ac\u03bd\u03c4\u03b1 \u03a1\u03af\u03c4\u03b1"
    ],
    "name:eng_x_preferred":[
        "Santa Rita"
    ],
    "name:fas_x_preferred":[
        "\u0633\u0627\u0646\u062a\u0627 \u0631\u06cc\u062a\u0627"
    ],
    "name:fra_x_preferred":[
        "Santa Rita"
    ],
    "name:heb_x_preferred":[
        "\u05e1\u05e0\u05d8\u05d4 \u05e8\u05d9\u05d8\u05d4"
    ],
    "name:hin_x_preferred":[
        "\u0938\u0948\u0902\u091f\u093e \u0930\u0940\u0924\u093e"
    ],
    "name:hun_x_preferred":[
        "Santa Rita"
    ],
    "name:ind_x_preferred":[
        "Santa Rita"
    ],
    "name:ita_x_preferred":[
        "Santa Rita"
    ],
    "name:jpn_x_preferred":[
        "\u30b5\u30f3\u30bf\u30ea\u30bf"
    ],
    "name:kor_x_preferred":[
        "\uc0b0\ud0c0 \ub9ac\ud0c0"
    ],
    "name:nld_x_preferred":[
        "Santa Rita"
    ],
    "name:rus_x_preferred":[
        "\u0421\u0430\u043d\u0442\u0430-\u0420\u0438\u0442\u0430"
    ],
    "name:swe_x_preferred":[
        "Santa Rita"
    ],
    "name:tur_x_preferred":[
        "Santa Rita"
    ],
    "name:ukr_x_preferred":[
        "\u0421\u0430\u043d\u0442\u0430-\u0420\u0456\u0442\u0430"
    ],
    "name:urd_x_preferred":[
        "\u0633\u06cc\u0646\u0679\u0627 \u0631\u06cc\u0679\u0627"
    ],
    "name:vie_x_preferred":[
        "Santa Rita"
    ],
    "name:zho_x_preferred":[
        "\u8056\u91cc\u5854"
    ],
    "qs:gn_country":"BO",
    "qs:gn_fcode":"PPL",
    "qs:gn_pop":2444,
    "qs:name":"Santa Rita",
    "qs:name_adm0":"Bolivia",
    "qs:name_adm1":"Santa Cruz",
    "qs:photos":0,
    "qs:photos_1k":0,
    "qs:photos_9k":0,
    "qs:photos_9r":0,
    "qs:photos_all":0,
    "qs:photos_sr":0,
    "qs:placetype":"Town",
    "qs:pop_sr":"4",
    "qs:woe_adm0":23424762,
    "wof:name":"Santa Rita",
    "wof:placetype":"locality",
    "wof:population":2444
},
  "geometry": {"coordinates":[-63.35,-17.96667],"type":"Point"}
}