{
  "type": "Feature",
  "properties": {
    "iso:country":"BO",
    "name:chi_x_preferred":[
        "\u8056\u91cc\u5854"
    ],
    "name:dut_x_preferred":[
        "Santa Rita"
    ],
    "name:eng_x_preferred":[
        "Santa Rita"
    ],
    "name:fre_x_preferred":[
        "Santa Rita"
    ],
    "name:ger_x_preferred":[
        "Santa Rita"
    ],
    "qs:gn_country":"BO",
    "qs:gn_fcode":"PPL",
    "qs:gn_pop":2444,
    "qs:name":"Santa Rita",
    "qs:name_adm0":"Bolivia",
    "qs:name_adm1":"Santa Cruz",
    "qs:photos":0,
    "qs:photos_1k":0,
    "qs:photos_9k":0,
    "qs:photos_9r":0,
    "qs:photos_all":0,
    "qs:photos_sr":0,
    "qs:placetype":"Town",
    "qs:pop_sr":"4",
    "qs:woe_adm0":23424762,
    "wof:name":"Santa Rita",
    "wof:placetype":"locality",
    "wof:population":2444
},
  "geometry": {"coordinates":[-63.35,-17.96667],"type":"Point"}
}