{
  "type": "Feature",
  "properties": {
    "gn:admin1_code":"06",
    "gn:asciiname":"Sabuche",
    "gn:country_code":"BO",
    "gn:dem":185,
    "gn:feature_class":"P",
    "gn:feature_code":"PPL",
    "gn:name":"Sabuche",
    "gn:population":0,
    "gn:timezone":"America/La_Paz",
    "iso:country":"BO",
    "name:spa_x_preferred":[
        "Sabuche"
    ],
    "wof:name":"Sabuche",
    "wof:placetype":"locality"
},
  "geometry": {"coordinates":[-67.61270999999999,-10.64022],"type":"Point"}
}