{
  "type": "Feature",
  "properties": {
    "gn:admin1_code":"4.0",
    "gn:asciiname":"Pucusani",
    "gn:cc2":"BO",
    "gn:country_code":"BO",
    "gn:dem":2737,
    "gn:feature_class":"P",
    "gn:feature_code":"PPL",
    "gn:name":"Pucusani",
    "gn:population":0,
    "gn:timezone":"America/La_Paz",
    "iso:country":"BO",
    "name:und_x_variant":[
        "Estancia Pocosani",
        "Pucusani"
    ],
    "wof:name":"Pucusani",
    "wof:placetype":"locality"
},
  "geometry": {"coordinates":[-66.90000000000001,-17.25],"type":"Point"}
}