{
  "type": "Feature",
  "properties": {
    "iso:country":"BO",
    "name:deu_x_preferred":[
        "Kanton Alota"
    ],
    "name:eng_x_preferred":[
        "Alota Canton"
    ],
    "name:fas_x_preferred":[
        "\u0627\u0644\u0627\u062a\u0627 \u06a9\u0627\u0646\u062a\u0648\u0646"
    ],
    "name:que_x_preferred":[
        "Aluta kantun"
    ],
    "name:unk_x_variant":[
        "Alota"
    ],
    "qs:gn_country":"BO",
    "qs:gn_fcode":"PPL",
    "qs:gn_pop":75,
    "qs:name":"Villa Alota",
    "qs:name_adm0":"Bolivia",
    "qs:name_adm1":"Potos\u00ed",
    "qs:photos":0,
    "qs:photos_1k":0,
    "qs:photos_9k":1,
    "qs:photos_9r":1,
    "qs:photos_all":2,
    "qs:photos_sr":0,
    "qs:placetype":"Town",
    "qs:pop_sr":"1",
    "qs:woe_adm0":23424762,
    "wof:name":"Villa Alota",
    "wof:placetype":"locality",
    "wof:population":75
},
  "geometry": {"coordinates":[-67.59622,-21.40409],"type":"Point"}
}