{
  "type": "Feature",
  "properties": {
    "gn:admin1_code":"05",
    "gn:asciiname":"Challacollo",
    "gn:country_code":"BO",
    "gn:dem":3717,
    "gn:feature_class":"P",
    "gn:feature_code":"PPL",
    "gn:name":"Challacollo",
    "gn:population":0,
    "gn:timezone":"America/La_Paz",
    "iso:country":"BO",
    "name:und_x_variant":[
        "Challacolla",
        "Challacollo"
    ],
    "wof:name":"Challacollo",
    "wof:placetype":"locality"
},
  "geometry": {"coordinates":[-67.24027,-18.0778],"type":"Point"}
}