{
  "type": "Feature",
  "properties": {
    "gn:admin1_code":"2.0",
    "gn:asciiname":"Yanamayo",
    "gn:country_code":"BO",
    "gn:dem":1366,
    "gn:feature_class":"P",
    "gn:feature_code":"PPL",
    "gn:name":"Yanamayo",
    "gn:population":0,
    "gn:timezone":"America/La_Paz",
    "iso:country":"BO",
    "name:spa_x_preferred":[
        "R\u00edo Yanamayo"
    ],
    "wof:name":"Yanamayo",
    "wof:placetype":"locality"
},
  "geometry": {"coordinates":[-65.78333000000001,-17.15],"type":"Point"}
}