{
  "type": "Feature",
  "properties": {
    "gn:admin1_code":"05",
    "gn:asciiname":"Ayparahui",
    "gn:country_code":"BO",
    "gn:dem":3674,
    "gn:feature_class":"P",
    "gn:feature_code":"PPL",
    "gn:name":"Ayparahui",
    "gn:population":0,
    "gn:timezone":"America/La_Paz",
    "iso:country":"BO",
    "name:und_x_variant":[
        "Ayparavi",
        "Ayparahul",
        "Ayparahui"
    ],
    "wof:name":"Ayparahui",
    "wof:placetype":"locality"
},
  "geometry": {"coordinates":[-67.90966999999999,-19.03963],"type":"Point"}
}