{
  "type": "Feature",
  "properties": {
    "gn:admin1_code":"06",
    "gn:asciiname":"Remanzo",
    "gn:country_code":"BO",
    "gn:dem":252,
    "gn:feature_class":"P",
    "gn:feature_code":"PPL",
    "gn:name":"Remanzo",
    "gn:population":0,
    "gn:timezone":"America/La_Paz",
    "iso:country":"BO",
    "wof:name":"Remanzo",
    "wof:placetype":"locality"
},
  "geometry": {"coordinates":[-69.03265,-11.44099],"type":"Point"}
}