{
  "type": "Feature",
  "properties": {
    "gn:admin1_code":"4.0",
    "gn:asciiname":"Franz Tamayo",
    "gn:country_code":"BO",
    "gn:dem":3935,
    "gn:feature_class":"P",
    "gn:feature_code":"PPL",
    "gn:name":"Franz Tamayo",
    "gn:population":0,
    "gn:timezone":"America/La_Paz",
    "iso:country":"BO",
    "wof:name":"Franz Tamayo",
    "wof:placetype":"locality"
},
  "geometry": {"coordinates":[-67.25,-17.18333],"type":"Point"}
}