{
  "type": "Feature",
  "properties": {
    "gn:admin1_code":"4.0",
    "gn:asciiname":"Nunumayuni",
    "gn:country_code":"BO",
    "gn:dem":3792,
    "gn:feature_class":"P",
    "gn:feature_code":"PPL",
    "gn:name":"Nu\u00f1umayuni",
    "gn:population":0,
    "gn:timezone":"America/La_Paz",
    "iso:country":"BO",
    "wof:name":"Nunumayuni",
    "wof:placetype":"locality"
},
  "geometry": {"coordinates":[-67.98333000000001,-16.65],"type":"Point"}
}