{
  "type": "Feature",
  "properties": {
    "gn:admin1_code":"4.0",
    "gn:asciiname":"Wila Kota",
    "gn:cc2":"BO",
    "gn:country_code":"BO",
    "gn:dem":4290,
    "gn:feature_class":"P",
    "gn:feature_code":"PPL",
    "gn:name":"Wila Kota",
    "gn:population":0,
    "gn:timezone":"America/La_Paz",
    "iso:country":"BO",
    "name:und_x_variant":[
        "Estancia Vila Kkota",
        "Wila Kota"
    ],
    "wof:name":"Wila Kota",
    "wof:placetype":"locality"
},
  "geometry": {"coordinates":[-69.18333,-17.33333],"type":"Point"}
}