{
  "type": "Feature",
  "properties": {
    "gn:admin1_code":"01",
    "gn:asciiname":"Baisondo",
    "gn:country_code":"BO",
    "gn:dem":732,
    "gn:feature_class":"P",
    "gn:feature_code":"PPL",
    "gn:name":"Baisondo",
    "gn:population":0,
    "gn:timezone":"America/La_Paz",
    "iso:country":"BO",
    "wof:name":"Baisondo",
    "wof:placetype":"locality"
},
  "geometry": {"coordinates":[-63.87909000000001,-20.87652000000001],"type":"Point"}
}