{
  "type": "Feature",
  "properties": {
    "gn:admin1_code":"06",
    "gn:asciiname":"Dina",
    "gn:country_code":"BO",
    "gn:dem":185,
    "gn:feature_class":"P",
    "gn:feature_code":"PPL",
    "gn:name":"Dina",
    "gn:population":0,
    "gn:timezone":"America/La_Paz",
    "iso:country":"BO",
    "name:als_x_preferred":[
        "Dina"
    ],
    "name:ces_x_preferred":[
        "Dina"
    ],
    "name:dan_x_preferred":[
        "Dina"
    ],
    "name:deu_x_preferred":[
        "Dina"
    ],
    "name:hun_x_preferred":[
        "Dina"
    ],
    "name:ita_x_preferred":[
        "Dina"
    ],
    "name:nno_x_preferred":[
        "Dina"
    ],
    "name:nor_x_preferred":[
        "Dina"
    ],
    "name:pol_x_preferred":[
        "Dina"
    ],
    "name:rus_x_preferred":[
        "\u0414\u0438\u043d\u0430"
    ],
    "name:spa_x_preferred":[
        "Dina"
    ],
    "name:swe_x_preferred":[
        "Dina"
    ],
    "wof:name":"Dina",
    "wof:placetype":"locality"
},
  "geometry": {"coordinates":[-67.7961,-11.14657],"type":"Point"}
}