{
  "type": "Feature",
  "properties": {
    "gn:admin1_code":"2.0",
    "gn:asciiname":"Villa Viscarra",
    "gn:cc2":"BO",
    "gn:country_code":"BO",
    "gn:dem":2636,
    "gn:feature_class":"P",
    "gn:feature_code":"PPL",
    "gn:name":"Villa Viscarra",
    "gn:population":0,
    "gn:timezone":"America/La_Paz",
    "iso:country":"BO",
    "name:ceb_x_preferred":[
        "Villa Viscarra"
    ],
    "name:deu_x_preferred":[
        "Vila Vila"
    ],
    "name:que_x_preferred":[
        "Wila Wila"
    ],
    "name:und_x_variant":[
        "Eufronia Viscarra",
        "Viscarra",
        "Villa Eufronio Vizcarra",
        "Villa Eufronio Viscarra",
        "Villa Vizcarra",
        "Vila Vila",
        "Villa Viscarra"
    ],
    "wof:name":"Villa Viscarra",
    "wof:placetype":"locality"
},
  "geometry": {"coordinates":[-65.59999999999999,-17.98333],"type":"Point"}
}