{
  "type": "Feature",
  "properties": {
    "gn:admin1_code":"4.0",
    "gn:asciiname":"Pallcosa Grana",
    "gn:country_code":"BO",
    "gn:dem":3863,
    "gn:feature_class":"P",
    "gn:feature_code":"PPL",
    "gn:name":"Pallcosa Grana",
    "gn:population":0,
    "gn:timezone":"America/La_Paz",
    "iso:country":"BO",
    "wof:name":"Pallcosa Grana",
    "wof:placetype":"locality"
},
  "geometry": {"coordinates":[-68.33333,-16.65],"type":"Point"}
}