{
  "type": "Feature",
  "properties": {
    "gn:admin1_code":"7.0",
    "gn:asciiname":"Jaco",
    "gn:country_code":"BO",
    "gn:dem":4128,
    "gn:feature_class":"P",
    "gn:feature_code":"PPL",
    "gn:name":"Jaco",
    "gn:population":0,
    "gn:timezone":"America/La_Paz",
    "iso:country":"BO",
    "name:ceb_x_preferred":[
        "Jaco"
    ],
    "name:deu_x_preferred":[
        "Jaco"
    ],
    "name:fra_x_preferred":[
        "Jaco"
    ],
    "name:ita_x_preferred":[
        "Jaco"
    ],
    "name:nld_x_preferred":[
        "Jaco"
    ],
    "name:nor_x_preferred":[
        "Jaco"
    ],
    "name:rus_x_preferred":[
        "\u0416\u0430\u043a\u043e"
    ],
    "name:swe_x_preferred":[
        "Jaco"
    ],
    "name:und_x_variant":[
        "Isco",
        "Jaco"
    ],
    "wof:name":"Jaco",
    "wof:placetype":"locality"
},
  "geometry": {"coordinates":[-66.63379999999999,-21.56681],"type":"Point"}
}