{
  "type": "Feature",
  "properties": {
    "gn:admin1_code":"07",
    "gn:asciiname":"Estancia El Palomar",
    "gn:country_code":"BO",
    "gn:dem":3050,
    "gn:feature_class":"P",
    "gn:feature_code":"PPL",
    "gn:name":"Estancia El Palomar",
    "gn:population":0,
    "gn:timezone":"America/La_Paz",
    "iso:country":"BO",
    "wof:name":"Estancia El Palomar",
    "wof:placetype":"locality"
},
  "geometry": {"coordinates":[-65.41405999999999,-19.65316],"type":"Point"}
}