{
  "type": "Feature",
  "properties": {
    "gn:admin1_code":"5.0",
    "gn:asciiname":"Tangani",
    "gn:country_code":"BO",
    "gn:dem":3718,
    "gn:feature_class":"P",
    "gn:feature_code":"PPL",
    "gn:name":"Tangani",
    "gn:population":0,
    "gn:timezone":"America/La_Paz",
    "iso:country":"BO",
    "wof:name":"Tangani",
    "wof:placetype":"locality"
},
  "geometry": {"coordinates":[-67.40534,-19.0422],"type":"Point"}
}