{
  "type": "Feature",
  "properties": {
    "gn:admin1_code":"06",
    "gn:asciiname":"Tres Barracas",
    "gn:country_code":"BO",
    "gn:dem":252,
    "gn:feature_class":"P",
    "gn:feature_code":"PPL",
    "gn:name":"Tres Barracas",
    "gn:population":0,
    "gn:timezone":"America/La_Paz",
    "iso:country":"BO",
    "name:spa_x_preferred":[
        "Tres Barracas"
    ],
    "name:und_x_variant":[
        "El Cedro"
    ],
    "wof:name":"Tres Barracas",
    "wof:placetype":"locality"
},
  "geometry": {"coordinates":[-68.60956999999999,-11.19271],"type":"Point"}
}