{
  "type": "Feature",
  "properties": {
    "gn:admin1_code":"2.0",
    "gn:asciiname":"Siches",
    "gn:country_code":"BO",
    "gn:dem":2875,
    "gn:feature_class":"P",
    "gn:feature_code":"PPL",
    "gn:name":"Siches",
    "gn:population":0,
    "gn:timezone":"America/La_Paz",
    "iso:country":"BO",
    "wof:name":"Siches",
    "wof:placetype":"locality"
},
  "geometry": {"coordinates":[-65.93333,-17.66667],"type":"Point"}
}