{
  "type": "Feature",
  "properties": {
    "gn:admin1_code":"8.0",
    "gn:asciiname":"Ocoroca",
    "gn:cc2":"BO",
    "gn:country_code":"BO",
    "gn:dem":320,
    "gn:feature_class":"P",
    "gn:feature_code":"PPL",
    "gn:name":"Ocoroca",
    "gn:population":0,
    "gn:timezone":"America/La_Paz",
    "iso:country":"BO",
    "name:und_x_variant":[
        "Ocoraca",
        "Ocaraca",
        "Ocoroca"
    ],
    "wof:name":"Ocoroca",
    "wof:placetype":"locality"
},
  "geometry": {"coordinates":[-60.85,-17.05],"type":"Point"}
}