{
  "type": "Feature",
  "properties": {
    "gn:admin1_code":"08",
    "gn:asciiname":"Estancia El Cerrito",
    "gn:country_code":"BO",
    "gn:dem":427,
    "gn:feature_class":"P",
    "gn:feature_code":"PPL",
    "gn:name":"Estancia El Cerrito",
    "gn:population":0,
    "gn:timezone":"America/La_Paz",
    "iso:country":"BO",
    "wof:name":"Estancia El Cerrito",
    "wof:placetype":"locality"
},
  "geometry": {"coordinates":[-60.75,-16.55],"type":"Point"}
}