{
  "type": "Feature",
  "properties": {
    "gn:admin1_code":"07",
    "gn:asciiname":"Apacheta",
    "gn:country_code":"BO",
    "gn:dem":3970,
    "gn:feature_class":"P",
    "gn:feature_code":"PPL",
    "gn:name":"Apacheta",
    "gn:population":0,
    "gn:timezone":"America/La_Paz",
    "iso:country":"BO",
    "wof:name":"Apacheta",
    "wof:placetype":"locality"
},
  "geometry": {"coordinates":[-66.27367,-19.8978],"type":"Point"}
}