{
  "type": "Feature",
  "properties": {
    "gn:admin1_code":"05",
    "gn:asciiname":"Caihuasi",
    "gn:country_code":"BO",
    "gn:dem":4016,
    "gn:feature_class":"P",
    "gn:feature_code":"PPL",
    "gn:name":"Caihuasi",
    "gn:population":0,
    "gn:timezone":"America/La_Paz",
    "iso:country":"BO",
    "wof:name":"Caihuasi",
    "wof:placetype":"locality"
},
  "geometry": {"coordinates":[-66.98333000000001,-17.71667],"type":"Point"}
}