{
  "type": "Feature",
  "properties": {
    "gn:admin1_code":"4.0",
    "gn:asciiname":"Rea Rea",
    "gn:country_code":"BO",
    "gn:dem":2672,
    "gn:feature_class":"P",
    "gn:feature_code":"PPL",
    "gn:name":"Rea Rea",
    "gn:population":0,
    "gn:timezone":"America/La_Paz",
    "iso:country":"BO",
    "wof:name":"Rea Rea",
    "wof:placetype":"locality"
},
  "geometry": {"coordinates":[-67.07198000000001,-17.11466],"type":"Point"}
}