{
  "type": "Feature",
  "properties": {
    "gn:admin1_code":"2.0",
    "gn:asciiname":"Rosarito",
    "gn:country_code":"BO",
    "gn:dem":1225,
    "gn:feature_class":"P",
    "gn:feature_code":"PPL",
    "gn:name":"Rosarito",
    "gn:population":0,
    "gn:timezone":"America/La_Paz",
    "iso:country":"BO",
    "wof:name":"Rosarito",
    "wof:placetype":"locality"
},
  "geometry": {"coordinates":[-64.78333000000001,-18.51667],"type":"Point"}
}