{
  "type": "Feature",
  "properties": {
    "gn:admin1_code":"04",
    "gn:asciiname":"Collocollo",
    "gn:cc2":"BO",
    "gn:country_code":"BO",
    "gn:dem":3862,
    "gn:feature_class":"P",
    "gn:feature_code":"PPL",
    "gn:name":"Collocollo",
    "gn:population":0,
    "gn:timezone":"America/La_Paz",
    "iso:country":"BO",
    "name:und_x_variant":[
        "Callacollo",
        "Collocollo"
    ],
    "wof:name":"Collocollo",
    "wof:placetype":"locality"
},
  "geometry": {"coordinates":[-68.58333,-16.58333],"type":"Point"}
}