{
  "type": "Feature",
  "properties": {
    "gn:admin1_code":"01",
    "gn:asciiname":"Estancia Cana Huayco Grande",
    "gn:country_code":"BO",
    "gn:dem":2988,
    "gn:feature_class":"P",
    "gn:feature_code":"PPL",
    "gn:name":"Estancia Ca\u00f1a Huayco Grande",
    "gn:population":0,
    "gn:timezone":"America/La_Paz",
    "iso:country":"BO",
    "wof:name":"Estancia Cana Huayco Grande",
    "wof:placetype":"locality"
},
  "geometry": {"coordinates":[-64.83731,-20.83891],"type":"Point"}
}