{
  "type": "Feature",
  "properties": {
    "gn:admin1_code":"8.0",
    "gn:asciiname":"Hungria",
    "gn:country_code":"BO",
    "gn:dem":242,
    "gn:feature_class":"P",
    "gn:feature_code":"PPL",
    "gn:name":"Hungr\u00eda",
    "gn:population":0,
    "gn:timezone":"America/La_Paz",
    "iso:country":"BO",
    "wof:name":"Hungria",
    "wof:placetype":"locality"
},
  "geometry": {"coordinates":[-61.98333,-13.93333],"type":"Point"}
}