{
  "type": "Feature",
  "properties": {
    "gn:admin1_code":"7.0",
    "gn:asciiname":"Otuyo",
    "gn:country_code":"BO",
    "gn:dem":2938,
    "gn:feature_class":"P",
    "gn:feature_code":"PPL",
    "gn:name":"Otuyo",
    "gn:population":0,
    "gn:timezone":"America/La_Paz",
    "iso:country":"BO",
    "wof:name":"Otuyo",
    "wof:placetype":"locality"
},
  "geometry": {"coordinates":[-65.23009999999999,-19.48625],"type":"Point"}
}