{
  "type": "Feature",
  "properties": {
    "gn:admin1_code":"04",
    "gn:asciiname":"Coque",
    "gn:cc2":"BO",
    "gn:country_code":"BO",
    "gn:dem":4234,
    "gn:feature_class":"P",
    "gn:feature_code":"PPL",
    "gn:name":"Coque",
    "gn:population":0,
    "gn:timezone":"America/La_Paz",
    "iso:country":"BO",
    "name:fra_x_preferred":[
        "Coque"
    ],
    "name:ita_x_preferred":[
        "Coque"
    ],
    "name:spa_x_preferred":[
        "Coque"
    ],
    "name:und_x_variant":[
        "Koque",
        "Coque"
    ],
    "wof:name":"Coque",
    "wof:placetype":"locality"
},
  "geometry": {"coordinates":[-67.38333,-17.11667000000001],"type":"Point"}
}