{
  "type": "Feature",
  "properties": {
    "gn:admin1_code":"7.0",
    "gn:asciiname":"Manzanal",
    "gn:country_code":"BO",
    "gn:dem":3150,
    "gn:feature_class":"P",
    "gn:feature_code":"PPL",
    "gn:name":"Manzanal",
    "gn:population":0,
    "gn:timezone":"America/La_Paz",
    "iso:country":"BO",
    "name:spa_x_preferred":[
        "Manzanal"
    ],
    "wof:name":"Manzanal",
    "wof:placetype":"locality"
},
  "geometry": {"coordinates":[-65.57075,-21.10242],"type":"Point"}
}