{
  "type": "Feature",
  "properties": {
    "gn:admin1_code":"09",
    "gn:asciiname":"Erquiz",
    "gn:country_code":"BO",
    "gn:dem":2085,
    "gn:feature_class":"P",
    "gn:feature_code":"PPL",
    "gn:name":"Erquiz",
    "gn:population":0,
    "gn:timezone":"America/La_Paz",
    "iso:country":"BO",
    "name:und_x_variant":[
        "Erquis",
        "Erquiz"
    ],
    "wof:name":"Erquiz",
    "wof:placetype":"locality"
},
  "geometry": {"coordinates":[-64.80274,-21.46775],"type":"Point"}
}