{
  "type": "Feature",
  "properties": {
    "gn:admin1_code":"06",
    "gn:asciiname":"Bolivar",
    "gn:country_code":"BO",
    "gn:dem":215,
    "gn:feature_class":"P",
    "gn:feature_code":"PPL",
    "gn:name":"Bol\u00edvar",
    "gn:population":0,
    "gn:timezone":"America/La_Paz",
    "iso:country":"BO",
    "wof:name":"Bolivar",
    "wof:placetype":"locality"
},
  "geometry": {"coordinates":[-68.09999999999999,-11.05],"type":"Point"}
}