{
  "type": "Feature",
  "properties": {
    "gn:admin1_code":"06",
    "gn:asciiname":"Venecia",
    "gn:country_code":"BO",
    "gn:dem":250,
    "gn:feature_class":"P",
    "gn:feature_code":"PPL",
    "gn:name":"Venecia",
    "gn:population":0,
    "gn:timezone":"America/La_Paz",
    "iso:country":"BO",
    "name:spa_x_preferred":[
        "Venecia"
    ],
    "wof:name":"Venecia",
    "wof:placetype":"locality"
},
  "geometry": {"coordinates":[-68.96151999999999,-11.05445],"type":"Point"}
}