{
  "type": "Feature",
  "properties": {
    "gn:admin1_code":"06",
    "gn:asciiname":"Venecia",
    "gn:country_code":"BO",
    "gn:dem":250,
    "gn:feature_class":"P",
    "gn:feature_code":"PPL",
    "gn:name":"Venecia",
    "gn:population":0,
    "gn:timezone":"America/La_Paz",
    "iso:country":"BO",
    "name:ceb_x_preferred":[
        "Venecia"
    ],
    "name:ita_x_preferred":[
        "Venecia"
    ],
    "name:msa_x_preferred":[
        "Venecia"
    ],
    "name:nld_x_preferred":[
        "Venecia"
    ],
    "name:spa_x_preferred":[
        "Venecia"
    ],
    "name:srp_x_preferred":[
        "\u0412\u0435\u043d\u0435\u0441\u0438\u0458\u0430"
    ],
    "name:swe_x_preferred":[
        "Venecia"
    ],
    "name:war_x_preferred":[
        "Venecia"
    ],
    "wof:name":"Venecia",
    "wof:placetype":"locality"
},
  "geometry": {"coordinates":[-68.96151999999999,-11.05445],"type":"Point"}
}