{
  "type": "Feature",
  "properties": {
    "gn:admin1_code":"4.0",
    "gn:asciiname":"Nichipaca",
    "gn:country_code":"BO",
    "gn:dem":3865,
    "gn:feature_class":"P",
    "gn:feature_code":"PPL",
    "gn:name":"Nichipaca",
    "gn:population":0,
    "gn:timezone":"America/La_Paz",
    "iso:country":"BO",
    "wof:name":"Nichipaca",
    "wof:placetype":"locality"
},
  "geometry": {"coordinates":[-68.65000000000001,-16.08333],"type":"Point"}
}