{
  "type": "Feature",
  "properties": {
    "gn:admin1_code":"06",
    "gn:asciiname":"Buraco",
    "gn:country_code":"BO",
    "gn:dem":274,
    "gn:feature_class":"P",
    "gn:feature_code":"PPL",
    "gn:name":"Buraco",
    "gn:population":0,
    "gn:timezone":"America/La_Paz",
    "iso:country":"BO",
    "name:deu_x_preferred":[
        "Buraco"
    ],
    "name:hrv_x_preferred":[
        "Burraco"
    ],
    "name:ita_x_preferred":[
        "Burraco"
    ],
    "name:spa_x_preferred":[
        "Buraco"
    ],
    "wof:name":"Buraco",
    "wof:placetype":"locality"
},
  "geometry": {"coordinates":[-68.73249,-11.14889],"type":"Point"}
}