{
  "type": "Feature",
  "properties": {
    "gn:admin1_code":"06",
    "gn:asciiname":"Nueva America",
    "gn:country_code":"BO",
    "gn:dem":207,
    "gn:feature_class":"P",
    "gn:feature_code":"PPL",
    "gn:name":"Nueva America",
    "gn:population":0,
    "gn:timezone":"America/La_Paz",
    "iso:country":"BO",
    "name:spa_x_preferred":[
        "Nueva America"
    ],
    "wof:name":"Nueva America",
    "wof:placetype":"locality"
},
  "geometry": {"coordinates":[-68.26306,-11.58915],"type":"Point"}
}