{
  "type": "Feature",
  "properties": {
    "gn:admin1_code":"4.0",
    "gn:asciiname":"Estancia Veloitera",
    "gn:country_code":"BO",
    "gn:dem":4446,
    "gn:feature_class":"P",
    "gn:feature_code":"PPL",
    "gn:name":"Estancia Veloitera",
    "gn:population":0,
    "gn:timezone":"America/La_Paz",
    "iso:country":"BO",
    "wof:name":"Estancia Veloitera",
    "wof:placetype":"locality"
},
  "geometry": {"coordinates":[-69.08333,-15.25],"type":"Point"}
}