{
  "type": "Feature",
  "properties": {
    "gn:admin1_code":"06",
    "gn:asciiname":"La Esperanza",
    "gn:country_code":"BO",
    "gn:dem":235,
    "gn:feature_class":"P",
    "gn:feature_code":"PPL",
    "gn:name":"La Esperanza",
    "gn:population":0,
    "gn:timezone":"America/La_Paz",
    "iso:country":"BO",
    "name:spa_x_preferred":[
        "La Esperanza"
    ],
    "wof:name":"La Esperanza",
    "wof:placetype":"locality"
},
  "geometry": {"coordinates":[-67.83009,-11.4578],"type":"Point"}
}