{
  "type": "Feature",
  "properties": {
    "gn:admin1_code":"7.0",
    "gn:asciiname":"Tapaquilcha",
    "gn:country_code":"BO",
    "gn:dem":4768,
    "gn:feature_class":"P",
    "gn:feature_code":"PPL",
    "gn:name":"Tapaquilcha",
    "gn:population":0,
    "gn:timezone":"America/La_Paz",
    "iso:country":"BO",
    "wof:name":"Tapaquilcha",
    "wof:placetype":"locality"
},
  "geometry": {"coordinates":[-67.90000000000001,-21.51667],"type":"Point"}
}