{
  "type": "Feature",
  "properties": {
    "gn:admin1_code":"1.0",
    "gn:asciiname":"Toca",
    "gn:cc2":"BO",
    "gn:country_code":"BO",
    "gn:dem":2848,
    "gn:feature_class":"P",
    "gn:feature_code":"PPL",
    "gn:name":"Toca",
    "gn:population":0,
    "gn:timezone":"America/La_Paz",
    "iso:country":"BO",
    "name:ceb_x_preferred":[
        "Toca"
    ],
    "name:fra_x_preferred":[
        "Toca"
    ],
    "name:por_x_preferred":[
        "Toca"
    ],
    "name:spa_x_preferred":[
        "Toca"
    ],
    "name:swe_x_preferred":[
        "Toca"
    ],
    "name:und_x_variant":[
        "Tora"
    ],
    "wof:name":"Toca",
    "wof:placetype":"locality"
},
  "geometry": {"coordinates":[-64.95,-18.98333],"type":"Point"}
}