{
  "type": "Feature",
  "properties": {
    "gn:admin1_code":"8.0",
    "gn:asciiname":"Potrero de Abril",
    "gn:country_code":"BO",
    "gn:dem":103,
    "gn:feature_class":"P",
    "gn:feature_code":"PPL",
    "gn:name":"Potrero de Abril",
    "gn:population":0,
    "gn:timezone":"America/La_Paz",
    "iso:country":"BO",
    "wof:name":"Potrero de Abril",
    "wof:placetype":"locality"
},
  "geometry": {"coordinates":[-58.21666999999999,-18.98333],"type":"Point"}
}