{
  "type": "Feature",
  "properties": {
    "gn:admin1_code":"06",
    "gn:asciiname":"Montecarlo",
    "gn:country_code":"BO",
    "gn:dem":203,
    "gn:feature_class":"P",
    "gn:feature_code":"PPL",
    "gn:name":"Montecarlo",
    "gn:population":0,
    "gn:timezone":"America/La_Paz",
    "iso:country":"BO",
    "name:spa_x_preferred":[
        "Montecarlo"
    ],
    "wof:name":"Montecarlo",
    "wof:placetype":"locality"
},
  "geometry": {"coordinates":[-68.36525999999999,-11.695],"type":"Point"}
}