{
  "type": "Feature",
  "properties": {
    "gn:admin1_code":"07",
    "gn:asciiname":"Banos",
    "gn:country_code":"BO",
    "gn:dem":3787,
    "gn:feature_class":"P",
    "gn:feature_code":"PPL",
    "gn:name":"Ba\u00f1os",
    "gn:population":0,
    "gn:timezone":"America/La_Paz",
    "iso:country":"BO",
    "name:ceb_x_preferred":[
        "Banos"
    ],
    "name:deu_x_preferred":[
        "Banos"
    ],
    "name:nld_x_preferred":[
        "Banos"
    ],
    "wof:name":"Banos",
    "wof:placetype":"locality"
},
  "geometry": {"coordinates":[-66.05,-21.76667],"type":"Point"}
}