{
  "type": "Feature",
  "properties": {
    "gn:admin1_code":"08",
    "gn:asciiname":"El Salitral",
    "gn:cc2":"BO",
    "gn:country_code":"BO",
    "gn:dem":304,
    "gn:feature_class":"P",
    "gn:feature_code":"PPL",
    "gn:name":"El Salitral",
    "gn:population":0,
    "gn:timezone":"America/La_Paz",
    "iso:country":"BO",
    "name:und_x_variant":[
        "Salitral",
        "El Salitral"
    ],
    "wof:name":"El Salitral",
    "wof:placetype":"locality"
},
  "geometry": {"coordinates":[-63.26667,-17.38332999999999],"type":"Point"}
}