{
  "type": "Feature",
  "properties": {
    "gn:admin1_code":"4.0",
    "gn:asciiname":"Rosa",
    "gn:cc2":"BO",
    "gn:country_code":"BO",
    "gn:dem":157,
    "gn:feature_class":"P",
    "gn:feature_code":"PPL",
    "gn:name":"Rosa",
    "gn:population":0,
    "gn:timezone":"America/La_Paz",
    "iso:country":"BO",
    "name:und_x_variant":[
        "Santa Rosa",
        "Rosa"
    ],
    "wof:name":"Rosa",
    "wof:placetype":"locality"
},
  "geometry": {"coordinates":[-66.95,-12.55],"type":"Point"}
}