{
  "type": "Feature",
  "properties": {
    "gn:admin1_code":"8.0",
    "gn:asciiname":"Ibabiyute",
    "gn:country_code":"BO",
    "gn:dem":896,
    "gn:feature_class":"P",
    "gn:feature_code":"PPL",
    "gn:name":"Ibabiyute",
    "gn:population":0,
    "gn:timezone":"America/La_Paz",
    "iso:country":"BO",
    "name:und_x_variant":[
        "Ibabiyuti",
        "Ibayiubi",
        "Ibabiyute"
    ],
    "wof:name":"Ibabiyute",
    "wof:placetype":"locality"
},
  "geometry": {"coordinates":[-63.27842,-19.89753],"type":"Point"}
}