{
  "type": "Feature",
  "properties": {
    "gn:admin1_code":"2.0",
    "gn:asciiname":"Vizcaino",
    "gn:cc2":"BO",
    "gn:country_code":"BO",
    "gn:dem":4526,
    "gn:feature_class":"P",
    "gn:feature_code":"PPL",
    "gn:name":"Vizca\u00edno",
    "gn:population":0,
    "gn:timezone":"America/La_Paz",
    "iso:country":"BO",
    "name:und_x_variant":[
        "Viscaino",
        "Vizeaino",
        "Vizca\u00edno"
    ],
    "wof:name":"Vizcaino",
    "wof:placetype":"locality"
},
  "geometry": {"coordinates":[-66.65000000000001,-16.93333],"type":"Point"}
}