{
  "type": "Feature",
  "properties": {
    "gn:admin1_code":"2.0",
    "gn:asciiname":"Icona",
    "gn:cc2":"BO",
    "gn:country_code":"BO",
    "gn:dem":1288,
    "gn:feature_class":"P",
    "gn:feature_code":"PPL",
    "gn:name":"Icona",
    "gn:population":0,
    "gn:timezone":"America/La_Paz",
    "iso:country":"BO",
    "name:und_x_variant":[
        "Icora",
        "Icona"
    ],
    "wof:name":"Icona",
    "wof:placetype":"locality"
},
  "geometry": {"coordinates":[-65.68333,-17.01667],"type":"Point"}
}