{
  "type": "Feature",
  "properties": {
    "gn:admin1_code":"7.0",
    "gn:asciiname":"Garita",
    "gn:country_code":"BO",
    "gn:dem":4194,
    "gn:feature_class":"P",
    "gn:feature_code":"PPL",
    "gn:name":"Garita",
    "gn:population":0,
    "gn:timezone":"America/La_Paz",
    "iso:country":"BO",
    "wof:name":"Garita",
    "wof:placetype":"locality"
},
  "geometry": {"coordinates":[-68.65716999999999,-20.27205],"type":"Point"}
}