{
  "type": "Feature",
  "properties": {
    "gn:admin1_code":"07",
    "gn:asciiname":"Escarqui",
    "gn:country_code":"BO",
    "gn:dem":2671,
    "gn:feature_class":"P",
    "gn:feature_code":"PPL",
    "gn:name":"Escarqui",
    "gn:population":0,
    "gn:timezone":"America/La_Paz",
    "iso:country":"BO",
    "name:und_x_variant":[
        "Rancho Escorque",
        "Escarqui"
    ],
    "wof:name":"Escarqui",
    "wof:placetype":"locality"
},
  "geometry": {"coordinates":[-65.69104,-20.82428],"type":"Point"}
}