{
  "type": "Feature",
  "properties": {
    "gn:admin1_code":"8.0",
    "gn:asciiname":"Santa Anita",
    "gn:country_code":"BO",
    "gn:dem":350,
    "gn:feature_class":"P",
    "gn:feature_code":"PPL",
    "gn:name":"Santa Anita",
    "gn:population":0,
    "gn:timezone":"America/La_Paz",
    "iso:country":"BO",
    "name:ceb_x_preferred":[
        "Santa Anita"
    ],
    "name:deu_x_preferred":[
        "Santa Anita"
    ],
    "name:spa_x_preferred":[
        "Santa Anita"
    ],
    "name:srp_x_preferred":[
        "\u0421\u0430\u043d\u0442\u0430 \u0410\u043d\u0438\u0442\u0430"
    ],
    "name:swe_x_preferred":[
        "Santa Anita"
    ],
    "wof:name":"Santa Anita",
    "wof:placetype":"locality"
},
  "geometry": {"coordinates":[-61.03333000000001,-16.16667],"type":"Point"}
}