{
  "type": "Feature",
  "properties": {
    "gn:admin1_code":"5.0",
    "gn:asciiname":"Quilcota",
    "gn:country_code":"BO",
    "gn:dem":3711,
    "gn:feature_class":"P",
    "gn:feature_code":"PPL",
    "gn:name":"Quilcota",
    "gn:population":0,
    "gn:timezone":"America/La_Paz",
    "iso:country":"BO",
    "wof:name":"Quilcota",
    "wof:placetype":"locality"
},
  "geometry": {"coordinates":[-67.43333,-18.36667000000001],"type":"Point"}
}