{
  "type": "Feature",
  "properties": {
    "gn:admin1_code":"02",
    "gn:asciiname":"Barraca General Roman",
    "gn:country_code":"BO",
    "gn:dem":239,
    "gn:feature_class":"P",
    "gn:feature_code":"PPL",
    "gn:name":"Barraca General Rom\u00e1n",
    "gn:population":0,
    "gn:timezone":"America/La_Paz",
    "iso:country":"BO",
    "wof:name":"Barraca General Roman",
    "wof:placetype":"locality"
},
  "geometry": {"coordinates":[-64.46666999999999,-17.15],"type":"Point"}
}