{
  "type": "Feature",
  "properties": {
    "gn:admin1_code":"06",
    "gn:asciiname":"Progreso",
    "gn:country_code":"BO",
    "gn:dem":191,
    "gn:feature_class":"P",
    "gn:feature_code":"PPL",
    "gn:name":"Progreso",
    "gn:population":0,
    "gn:timezone":"America/La_Paz",
    "iso:country":"BO",
    "name:spa_x_preferred":[
        "Progreso"
    ],
    "wof:name":"Progreso",
    "wof:placetype":"locality"
},
  "geometry": {"coordinates":[-67.22723000000001,-10.96479],"type":"Point"}
}