{
  "type": "Feature",
  "properties": {
    "gn:admin1_code":"06",
    "gn:asciiname":"Carmen",
    "gn:country_code":"BO",
    "gn:dem":174,
    "gn:feature_class":"P",
    "gn:feature_code":"PPL",
    "gn:name":"Carmen",
    "gn:population":0,
    "gn:timezone":"America/La_Paz",
    "iso:country":"BO",
    "wof:name":"Carmen",
    "wof:placetype":"locality"
},
  "geometry": {"coordinates":[-67.43888000000001,-11.20264],"type":"Point"}
}