{
  "type": "Feature",
  "properties": {
    "gn:admin1_code":"6.0",
    "gn:asciiname":"Comunidad Santa Rosa",
    "gn:country_code":"BO",
    "gn:dem":246,
    "gn:feature_class":"P",
    "gn:feature_code":"PPL",
    "gn:name":"Comunidad Santa Rosa",
    "gn:population":0,
    "gn:timezone":"America/La_Paz",
    "iso:country":"BO",
    "name:spa_x_preferred":[
        "Comunidad Santa Rosa"
    ],
    "name:und_x_variant":[
        "Santa Rosa"
    ],
    "wof:name":"Comunidad Santa Rosa",
    "wof:placetype":"locality"
},
  "geometry": {"coordinates":[-68.91754,-11.37203],"type":"Point"}
}