{
  "type": "Feature",
  "properties": {
    "gn:admin1_code":"7.0",
    "gn:asciiname":"Panacachi",
    "gn:country_code":"BO",
    "gn:dem":3802,
    "gn:feature_class":"P",
    "gn:feature_code":"PPL",
    "gn:name":"Panacachi",
    "gn:population":0,
    "gn:timezone":"America/La_Paz",
    "iso:country":"BO",
    "wof:name":"Panacachi",
    "wof:placetype":"locality"
},
  "geometry": {"coordinates":[-66.28506,-18.42501],"type":"Point"}
}