{
  "type": "Feature",
  "properties": {
    "gn:admin1_code":"07",
    "gn:asciiname":"Comunidad Huvilla",
    "gn:country_code":"BO",
    "gn:dem":3309,
    "gn:feature_class":"P",
    "gn:feature_code":"PPL",
    "gn:name":"Comunidad Huvilla",
    "gn:population":0,
    "gn:timezone":"America/La_Paz",
    "iso:country":"BO",
    "wof:name":"Comunidad Huvilla",
    "wof:placetype":"locality"
},
  "geometry": {"coordinates":[-65.36854,-19.87736],"type":"Point"}
}