{
  "type": "Feature",
  "properties": {
    "gn:admin1_code":"06",
    "gn:asciiname":"Pinalito",
    "gn:country_code":"BO",
    "gn:dem":211,
    "gn:feature_class":"P",
    "gn:feature_code":"PPL",
    "gn:name":"Pinalito",
    "gn:population":0,
    "gn:timezone":"America/La_Paz",
    "iso:country":"BO",
    "name:spa_x_preferred":[
        "Pinalito"
    ],
    "name:spa_x_variant":[
        "Pi\u00f1alito"
    ],
    "wof:name":"Pinalito",
    "wof:placetype":"locality"
},
  "geometry": {"coordinates":[-67.63020999999999,-11.46843],"type":"Point"}
}