{
  "type": "Feature",
  "properties": {
    "gn:admin1_code":"7.0",
    "gn:asciiname":"Tancani",
    "gn:country_code":"BO",
    "gn:dem":4108,
    "gn:feature_class":"P",
    "gn:feature_code":"PPL",
    "gn:name":"Tancani",
    "gn:population":0,
    "gn:timezone":"America/La_Paz",
    "iso:country":"BO",
    "wof:name":"Tancani",
    "wof:placetype":"locality"
},
  "geometry": {"coordinates":[-66.08333,-20.98333],"type":"Point"}
}