{
  "type": "Feature",
  "properties": {
    "gn:admin1_code":"6.0",
    "gn:admin2_code":"3915598.0",
    "gn:asciiname":"Jose Gomez",
    "gn:country_code":"BO",
    "gn:dem":111,
    "gn:feature_class":"P",
    "gn:feature_code":"PPL",
    "gn:name":"Jos\u00e9 G\u00f3mez",
    "gn:population":0,
    "gn:timezone":"America/La_Paz",
    "iso:country":"BO",
    "wof:name":"Jose Gomez",
    "wof:placetype":"locality"
},
  "geometry": {"coordinates":[-65.56829,-9.84752],"type":"Point"}
}