{
  "type": "Feature",
  "properties": {
    "gn:admin1_code":"4.0",
    "gn:asciiname":"Uyuni",
    "gn:country_code":"BO",
    "gn:dem":4061,
    "gn:feature_class":"P",
    "gn:feature_code":"PPL",
    "gn:name":"Uyuni",
    "gn:population":0,
    "gn:timezone":"America/La_Paz",
    "iso:country":"BO",
    "name:ara_x_preferred":[
        "\u0623\u0648\u064a\u0648\u0646\u064a"
    ],
    "name:aym_x_preferred":[
        "Uyuni"
    ],
    "name:ben_x_preferred":[
        "\u0989\u09df\u09be\u09a8\u09bf"
    ],
    "name:cat_x_preferred":[
        "Uyuni"
    ],
    "name:ceb_x_preferred":[
        "Uyuni"
    ],
    "name:ces_x_preferred":[
        "Uyuni"
    ],
    "name:deu_x_preferred":[
        "Uyuni"
    ],
    "name:ell_x_preferred":[
        "\u039f\u03c5\u03b3\u03b9\u03bf\u03cd\u03bd\u03b9"
    ],
    "name:fra_x_preferred":[
        "Uyuni"
    ],
    "name:guj_x_preferred":[
        "\u0a89\u0aaf\u0ac2\u0aa8\u0ac0"
    ],
    "name:hin_x_preferred":[
        "\u0909\u092f\u0942\u0928\u0940"
    ],
    "name:hun_x_preferred":[
        "Uyuni"
    ],
    "name:ind_x_preferred":[
        "Uyuni"
    ],
    "name:ita_x_preferred":[
        "Uyuni"
    ],
    "name:jpn_x_preferred":[
        "\u30a6\u30e6\u30cb"
    ],
    "name:kor_x_preferred":[
        "\uc6b0\uc720\ub2c8"
    ],
    "name:lit_x_preferred":[
        "Uj\u016bnis"
    ],
    "name:nld_x_preferred":[
        "Uyuni"
    ],
    "name:nor_x_preferred":[
        "Uyuni"
    ],
    "name:pol_x_preferred":[
        "Uyuni"
    ],
    "name:por_x_preferred":[
        "Uyuni"
    ],
    "name:que_x_preferred":[
        "Uyuni"
    ],
    "name:rus_x_preferred":[
        "\u0423\u044e\u043d\u0438"
    ],
    "name:slk_x_preferred":[
        "Uyuni"
    ],
    "name:spa_x_preferred":[
        "Uyuni"
    ],
    "name:swe_x_preferred":[
        "Uyuni"
    ],
    "name:tur_x_preferred":[
        "Uyuni"
    ],
    "name:ukr_x_preferred":[
        "\u0423\u044e\u043d\u0456"
    ],
    "name:urd_x_preferred":[
        "\u06cc\u0648\u0646\u06cc"
    ],
    "name:vie_x_preferred":[
        "Uyuni"
    ],
    "name:war_x_preferred":[
        "Uyuni"
    ],
    "name:zho_x_preferred":[
        "\u70cf\u5c24\u5c3c"
    ],
    "wof:name":"Uyuni",
    "wof:placetype":"locality"
},
  "geometry": {"coordinates":[-68.63333,-17.58333],"type":"Point"}
}