{
  "type": "Feature",
  "properties": {
    "gn:admin1_code":"06",
    "gn:asciiname":"Tatu",
    "gn:country_code":"BO",
    "gn:dem":222,
    "gn:feature_class":"P",
    "gn:feature_code":"PPL",
    "gn:name":"Tatu",
    "gn:population":0,
    "gn:timezone":"America/La_Paz",
    "iso:country":"BO",
    "name:spa_x_preferred":[
        "Tatu"
    ],
    "wof:name":"Tatu",
    "wof:placetype":"locality"
},
  "geometry": {"coordinates":[-68.23054999999999,-11.45639],"type":"Point"}
}