{
  "type": "Feature",
  "properties": {
    "gn:admin1_code":"9.0",
    "gn:asciiname":"Meriles",
    "gn:country_code":"BO",
    "gn:dem":801,
    "gn:feature_class":"P",
    "gn:feature_code":"PPL",
    "gn:name":"Meriles",
    "gn:population":0,
    "gn:timezone":"America/La_Paz",
    "iso:country":"BO",
    "wof:name":"Meriles",
    "wof:placetype":"locality"
},
  "geometry": {"coordinates":[-63.99373000000001,-21.34562],"type":"Point"}
}