{
  "type": "Feature",
  "properties": {
    "gn:admin1_code":"9.0",
    "gn:asciiname":"Yumbia",
    "gn:country_code":"BO",
    "gn:dem":561,
    "gn:feature_class":"P",
    "gn:feature_code":"PPL",
    "gn:name":"Yumbia",
    "gn:population":0,
    "gn:timezone":"America/La_Paz",
    "iso:country":"BO",
    "name:und_x_variant":[
        "Yambia",
        "Yumbia"
    ],
    "wof:name":"Yumbia",
    "wof:placetype":"locality"
},
  "geometry": {"coordinates":[-63.91638,-21.11611],"type":"Point"}
}