{
  "type": "Feature",
  "properties": {
    "gn:admin1_code":"2.0",
    "gn:asciiname":"Higuerani",
    "gn:cc2":"BO",
    "gn:country_code":"BO",
    "gn:dem":3177,
    "gn:feature_class":"P",
    "gn:feature_code":"PPL",
    "gn:name":"Higuerani",
    "gn:population":0,
    "gn:timezone":"America/La_Paz",
    "iso:country":"BO",
    "name:und_x_variant":[
        "Higuerani Nueva",
        "Higuerani"
    ],
    "wof:name":"Higuerani",
    "wof:placetype":"locality"
},
  "geometry": {"coordinates":[-66.36667,-17.78333],"type":"Point"}
}