{
  "type": "Feature",
  "properties": {
    "gn:admin1_code":"8.0",
    "gn:asciiname":"Moro Moro",
    "gn:country_code":"BO",
    "gn:dem":2365,
    "gn:feature_class":"P",
    "gn:feature_code":"PPL",
    "gn:name":"Moro Moro",
    "gn:population":0,
    "gn:timezone":"America/La_Paz",
    "iso:country":"BO",
    "wof:name":"Moro Moro",
    "wof:placetype":"locality"
},
  "geometry": {"coordinates":[-64.32311,-18.36652],"type":"Point"}
}