{
  "type": "Feature",
  "properties": {
    "gn:admin1_code":"04",
    "gn:asciiname":"Cuypa",
    "gn:cc2":"BO",
    "gn:country_code":"BO",
    "gn:dem":4084,
    "gn:feature_class":"P",
    "gn:feature_code":"PPL",
    "gn:name":"Cuypa",
    "gn:population":0,
    "gn:timezone":"America/La_Paz",
    "iso:country":"BO",
    "name:und_x_variant":[
        "Comunidad Cuypa",
        "Cuypa"
    ],
    "wof:name":"Cuypa",
    "wof:placetype":"locality"
},
  "geometry": {"coordinates":[-68.63333,-16.78333],"type":"Point"}
}