{
  "type": "Feature",
  "properties": {
    "gn:admin1_code":"8.0",
    "gn:asciiname":"Puerto Alvares",
    "gn:cc2":"BO",
    "gn:country_code":"BO",
    "gn:dem":184,
    "gn:feature_class":"P",
    "gn:feature_code":"PPL",
    "gn:name":"Puerto Alvares",
    "gn:population":0,
    "gn:timezone":"America/La_Paz",
    "iso:country":"BO",
    "name:und_x_variant":[
        "Puerto \u00c1lvarez",
        "Puerto Alvares"
    ],
    "wof:name":"Puerto Alvares",
    "wof:placetype":"locality"
},
  "geometry": {"coordinates":[-62.43333000000001,-14.15],"type":"Point"}
}