{
  "type": "Feature",
  "properties": {
    "gn:admin1_code":"7.0",
    "gn:asciiname":"Tomaquesa",
    "gn:country_code":"BO",
    "gn:dem":3779,
    "gn:feature_class":"P",
    "gn:feature_code":"PPL",
    "gn:name":"Tomaquesa",
    "gn:population":0,
    "gn:timezone":"America/La_Paz",
    "iso:country":"BO",
    "wof:name":"Tomaquesa",
    "wof:placetype":"locality"
},
  "geometry": {"coordinates":[-67.45415,-21.10013],"type":"Point"}
}