{
  "type": "Feature",
  "properties": {
    "gn:admin1_code":"07",
    "gn:asciiname":"Estancia Chiquira",
    "gn:country_code":"BO",
    "gn:dem":3386,
    "gn:feature_class":"P",
    "gn:feature_code":"PPL",
    "gn:name":"Estancia Chiquira",
    "gn:population":0,
    "gn:timezone":"America/La_Paz",
    "iso:country":"BO",
    "wof:name":"Estancia Chiquira",
    "wof:placetype":"locality"
},
  "geometry": {"coordinates":[-66.16034999999999,-20.12532],"type":"Point"}
}