{
  "type": "Feature",
  "properties": {
    "gn:admin1_code":"01",
    "gn:asciiname":"Arquillos",
    "gn:country_code":"BO",
    "gn:dem":2128,
    "gn:feature_class":"P",
    "gn:feature_code":"PPL",
    "gn:name":"Arquillos",
    "gn:population":0,
    "gn:timezone":"America/La_Paz",
    "iso:country":"BO",
    "name:ara_x_preferred":[
        "\u0623\u0631\u0643\u064a\u0648\u0633"
    ],
    "name:ast_x_preferred":[
        "Arquillos"
    ],
    "name:azb_x_preferred":[
        "\u0622\u0631\u06a9\u06cc\u06cc\u0633"
    ],
    "name:cat_x_preferred":[
        "Arquillos"
    ],
    "name:ceb_x_preferred":[
        "Arquillos"
    ],
    "name:epo_x_preferred":[
        "Arquillos"
    ],
    "name:eus_x_preferred":[
        "Arquillos"
    ],
    "name:fas_x_preferred":[
        "\u0622\u0631\u06a9\u06cc\u06cc\u0633"
    ],
    "name:fra_x_preferred":[
        "Arquillos"
    ],
    "name:hat_x_preferred":[
        "Arquillos"
    ],
    "name:hun_x_preferred":[
        "Arquillos"
    ],
    "name:hye_x_preferred":[
        "\u0531\u0580\u056f\u056b\u056c\u0575\u0578\u057d"
    ],
    "name:ita_x_preferred":[
        "Arquillos"
    ],
    "name:msa_x_preferred":[
        "Arquillos"
    ],
    "name:nld_x_preferred":[
        "Arquillos"
    ],
    "name:oci_x_preferred":[
        "Arquillos"
    ],
    "name:pol_x_preferred":[
        "Arquillos"
    ],
    "name:por_x_preferred":[
        "Arquillos"
    ],
    "name:ron_x_preferred":[
        "Arquillos"
    ],
    "name:rus_x_preferred":[
        "\u0410\u0440\u043a\u0438\u043b\u044c\u043e\u0441"
    ],
    "name:spa_x_preferred":[
        "Arquillos"
    ],
    "name:swe_x_preferred":[
        "Arquillos"
    ],
    "name:tur_x_preferred":[
        "Arquillos"
    ],
    "name:ukr_x_preferred":[
        "\u0410\u0440\u043a\u0456\u043b\u044c\u0439\u043e\u0441"
    ],
    "name:und_x_variant":[
        "Arquillas"
    ],
    "name:uzb_x_preferred":[
        "Arquillos"
    ],
    "name:vie_x_preferred":[
        "Arquillos"
    ],
    "name:war_x_preferred":[
        "Arquillos"
    ],
    "name:zho_x_preferred":[
        "\u963f\u5c14\u57fa\u7565\u65af"
    ],
    "wof:name":"Arquillos",
    "wof:placetype":"locality"
},
  "geometry": {"coordinates":[-64.45419,-19.25165],"type":"Point"}
}