{
  "type": "Feature",
  "properties": {
    "gn:admin1_code":"01",
    "gn:asciiname":"Arquillos",
    "gn:country_code":"BO",
    "gn:dem":2128,
    "gn:feature_class":"P",
    "gn:feature_code":"PPL",
    "gn:name":"Arquillos",
    "gn:population":0,
    "gn:timezone":"America/La_Paz",
    "iso:country":"BO",
    "name:und_x_variant":[
        "Arquillas",
        "Arquillos"
    ],
    "wof:name":"Arquillos",
    "wof:placetype":"locality"
},
  "geometry": {"coordinates":[-64.45419,-19.25165],"type":"Point"}
}