{
  "type": "Feature",
  "properties": {
    "gn:admin1_code":"5.0",
    "gn:asciiname":"Salinas de Garci Mendoza",
    "gn:country_code":"BO",
    "gn:dem":3735,
    "gn:feature_class":"P",
    "gn:feature_code":"PPL",
    "gn:name":"Salinas de Garci Mendoza",
    "gn:population":0,
    "gn:timezone":"America/La_Paz",
    "iso:country":"BO",
    "wof:name":"Salinas de Garci Mendoza",
    "wof:placetype":"locality"
},
  "geometry": {"coordinates":[-67.67518000000001,-19.63721],"type":"Point"}
}