{
  "type": "Feature",
  "properties": {
    "gn:admin1_code":"06",
    "gn:asciiname":"Los Guayabos",
    "gn:country_code":"BO",
    "gn:dem":145,
    "gn:feature_class":"P",
    "gn:feature_code":"PPL",
    "gn:name":"Los Guayabos",
    "gn:population":0,
    "gn:timezone":"America/La_Paz",
    "iso:country":"BO",
    "name:spa_x_preferred":[
        "Los Guayabos"
    ],
    "wof:name":"Los Guayabos",
    "wof:placetype":"locality"
},
  "geometry": {"coordinates":[-67.05509000000001,-10.37955],"type":"Point"}
}