{
  "type": "Feature",
  "properties": {
    "gn:admin1_code":"7.0",
    "gn:asciiname":"Isabel Cruz",
    "gn:country_code":"BO",
    "gn:dem":4037,
    "gn:feature_class":"P",
    "gn:feature_code":"PPL",
    "gn:name":"Isabel Cruz",
    "gn:population":0,
    "gn:timezone":"America/La_Paz",
    "iso:country":"BO",
    "wof:name":"Isabel Cruz",
    "wof:placetype":"locality"
},
  "geometry": {"coordinates":[-68.15000000000001,-21.01667],"type":"Point"}
}