{
  "type": "Feature",
  "properties": {
    "gn:admin1_code":"5.0",
    "gn:asciiname":"Jayucota",
    "gn:cc2":"BO",
    "gn:country_code":"BO",
    "gn:dem":3724,
    "gn:feature_class":"P",
    "gn:feature_code":"PPL",
    "gn:name":"Jayucota",
    "gn:population":0,
    "gn:timezone":"America/La_Paz",
    "iso:country":"BO",
    "name:und_x_variant":[
        "Jayucoto",
        "Jayucote",
        "Jayocota",
        "Jayucota"
    ],
    "wof:name":"Jayucota",
    "wof:placetype":"locality"
},
  "geometry": {"coordinates":[-68.18333,-18.71667],"type":"Point"}
}