{
  "type": "Feature",
  "properties": {
    "gn:admin1_code":"7.0",
    "gn:asciiname":"Trapiche",
    "gn:country_code":"BO",
    "gn:dem":3584,
    "gn:feature_class":"P",
    "gn:feature_code":"PPL",
    "gn:name":"Trapiche",
    "gn:population":0,
    "gn:timezone":"America/La_Paz",
    "iso:country":"BO",
    "name:und_x_variant":[
        "Comunidad Trapiche",
        "Trapiche"
    ],
    "wof:name":"Trapiche",
    "wof:placetype":"locality"
},
  "geometry": {"coordinates":[-65.52675000000001,-19.44518],"type":"Point"}
}