{
  "type": "Feature",
  "properties": {
    "gn:admin1_code":"01",
    "gn:asciiname":"Buararayapi",
    "gn:country_code":"BO",
    "gn:dem":1350,
    "gn:feature_class":"P",
    "gn:feature_code":"PPL",
    "gn:name":"Buararayapi",
    "gn:population":0,
    "gn:timezone":"America/La_Paz",
    "iso:country":"BO",
    "wof:name":"Buararayapi",
    "wof:placetype":"locality"
},
  "geometry": {"coordinates":[-63.63333000000001,-20.55],"type":"Point"}
}