{
  "type": "Feature",
  "properties": {
    "gn:admin1_code":"1.0",
    "gn:asciiname":"Rodeo Chico",
    "gn:country_code":"BO",
    "gn:dem":2489,
    "gn:feature_class":"P",
    "gn:feature_code":"PPL",
    "gn:name":"Rodeo Chico",
    "gn:population":0,
    "gn:timezone":"America/La_Paz",
    "iso:country":"BO",
    "name:und_x_variant":[
        "Estancia Rodeo Chico",
        "Rodeo Chico"
    ],
    "wof:name":"Rodeo Chico",
    "wof:placetype":"locality"
},
  "geometry": {"coordinates":[-64.53919999999999,-20.25241],"type":"Point"}
}