{
  "type": "Feature",
  "properties": {
    "gn:admin1_code":"02",
    "gn:asciiname":"Estancia Juchuy Chilka",
    "gn:country_code":"BO",
    "gn:dem":3379,
    "gn:feature_class":"P",
    "gn:feature_code":"PPL",
    "gn:name":"Estancia Juchuy Chilka",
    "gn:population":0,
    "gn:timezone":"America/La_Paz",
    "iso:country":"BO",
    "wof:name":"Estancia Juchuy Chilka",
    "wof:placetype":"locality"
},
  "geometry": {"coordinates":[-66.63333,-17.58333],"type":"Point"}
}