{
  "type": "Feature",
  "properties": {
    "gn:admin1_code":"07",
    "gn:asciiname":"Carasi",
    "gn:country_code":"BO",
    "gn:dem":2503,
    "gn:feature_class":"P",
    "gn:feature_code":"PPL",
    "gn:name":"Carasi",
    "gn:population":0,
    "gn:timezone":"America/La_Paz",
    "iso:country":"BO",
    "name:bcl_x_preferred":[
        "Carasi"
    ],
    "name:ceb_x_preferred":[
        "Carasi"
    ],
    "name:deu_x_preferred":[
        "Carasi"
    ],
    "name:fra_x_preferred":[
        "Carasi"
    ],
    "name:ilo_x_preferred":[
        "Carasi"
    ],
    "name:ind_x_preferred":[
        "Carasi"
    ],
    "name:ita_x_preferred":[
        "Carasi"
    ],
    "name:nld_x_preferred":[
        "Carasi"
    ],
    "name:pag_x_preferred":[
        "Carasi"
    ],
    "name:pam_x_preferred":[
        "Carasi"
    ],
    "name:spa_x_preferred":[
        "Carasi"
    ],
    "name:swe_x_preferred":[
        "Carasi"
    ],
    "name:tgl_x_preferred":[
        "Carasi"
    ],
    "name:vie_x_preferred":[
        "Carasi"
    ],
    "name:war_x_preferred":[
        "Carasi"
    ],
    "wof:name":"Carasi",
    "wof:placetype":"locality"
},
  "geometry": {"coordinates":[-65.68902,-18.31901],"type":"Point"}
}