{
  "type": "Feature",
  "properties": {
    "gn:country":"BO",
    "gn:fcode":"PPL",
    "gn:population":142,
    "iso:country":"BO",
    "qs:name":"Chakamayu",
    "qs:photos_9r":0,
    "qs:photos_sr":0,
    "qs:pop_sr":"1",
    "wof:name":"Chakamayu",
    "wof:placetype":"locality",
    "wof:population":142
},
  "geometry": {"coordinates":[-65.1688,-17.79534],"type":"Point"}
}