{
  "type": "Feature",
  "properties": {
    "gn:admin1_code":"04",
    "gn:asciiname":"Cotapalca",
    "gn:country_code":"BO",
    "gn:dem":4388,
    "gn:feature_class":"P",
    "gn:feature_code":"PPL",
    "gn:name":"Cotapalca",
    "gn:population":0,
    "gn:timezone":"America/La_Paz",
    "iso:country":"BO",
    "wof:name":"Cotapalca",
    "wof:placetype":"locality"
},
  "geometry": {"coordinates":[-69.01666999999999,-17.76667],"type":"Point"}
}