{
  "type": "Feature",
  "properties": {
    "gn:admin1_code":"06",
    "gn:asciiname":"El Centrito",
    "gn:country_code":"BO",
    "gn:dem":162,
    "gn:feature_class":"P",
    "gn:feature_code":"PPL",
    "gn:name":"El Centrito",
    "gn:population":0,
    "gn:timezone":"America/La_Paz",
    "iso:country":"BO",
    "name:spa_x_preferred":[
        "El Centrito"
    ],
    "wof:name":"El Centrito",
    "wof:placetype":"locality"
},
  "geometry": {"coordinates":[-67.24840999999999,-10.34541],"type":"Point"}
}