{
  "type": "Feature",
  "properties": {
    "gn:admin1_code":"03",
    "gn:asciiname":"Chocolatal",
    "gn:country_code":"BO",
    "gn:dem":159,
    "gn:feature_class":"P",
    "gn:feature_code":"PPL",
    "gn:name":"Chocolatal",
    "gn:population":0,
    "gn:timezone":"America/La_Paz",
    "iso:country":"BO",
    "wof:name":"Chocolatal",
    "wof:placetype":"locality"
},
  "geometry": {"coordinates":[-65.36667,-15.15],"type":"Point"}
}