{
  "type": "Feature",
  "properties": {
    "gn:admin1_code":"07",
    "gn:asciiname":"Cayaloria",
    "gn:country_code":"BO",
    "gn:dem":3930,
    "gn:feature_class":"P",
    "gn:feature_code":"PPL",
    "gn:name":"Cayaloria",
    "gn:population":0,
    "gn:timezone":"America/La_Paz",
    "iso:country":"BO",
    "wof:name":"Cayaloria",
    "wof:placetype":"locality"
},
  "geometry": {"coordinates":[-65.71666999999999,-21.18333],"type":"Point"}
}