{
  "type": "Feature",
  "properties": {
    "gn:admin1_code":"6.0",
    "gn:asciiname":"Severino",
    "gn:country_code":"BO",
    "gn:dem":196,
    "gn:feature_class":"P",
    "gn:feature_code":"PPL",
    "gn:name":"Severino",
    "gn:population":0,
    "gn:timezone":"America/La_Paz",
    "iso:country":"BO",
    "name:bre_x_preferred":[
        "Severino"
    ],
    "name:ita_x_preferred":[
        "Severino"
    ],
    "name:jpn_x_preferred":[
        "\u30bb\u30f4\u30a7\u30ea\u30fc\u30ce"
    ],
    "wof:name":"Severino",
    "wof:placetype":"locality"
},
  "geometry": {"coordinates":[-66.15000000000001,-10.43333],"type":"Point"}
}