{
  "type": "Feature",
  "properties": {
    "gn:admin1_code":"08",
    "gn:asciiname":"Comunidad Carmencita",
    "gn:country_code":"BO",
    "gn:dem":379,
    "gn:feature_class":"P",
    "gn:feature_code":"PPL",
    "gn:name":"Comunidad Carmencita",
    "gn:population":0,
    "gn:timezone":"America/La_Paz",
    "iso:country":"BO",
    "wof:name":"Comunidad Carmencita",
    "wof:placetype":"locality"
},
  "geometry": {"coordinates":[-61.01667,-16.28333],"type":"Point"}
}