{
  "type": "Feature",
  "properties": {
    "gn:admin1_code":"06",
    "gn:asciiname":"Apretada",
    "gn:country_code":"BO",
    "gn:dem":162,
    "gn:feature_class":"P",
    "gn:feature_code":"PPL",
    "gn:name":"Apretada",
    "gn:population":0,
    "gn:timezone":"America/La_Paz",
    "iso:country":"BO",
    "name:spa_x_preferred":[
        "Apretada"
    ],
    "wof:name":"Apretada",
    "wof:placetype":"locality"
},
  "geometry": {"coordinates":[-67.2724,-10.38933],"type":"Point"}
}