{
  "type": "Feature",
  "properties": {
    "iso:country":"BO",
    "qs:gn_country":"BO",
    "qs:gn_fcode":"ADM4",
    "qs:gn_pop":0,
    "qs:name":"Sucre",
    "qs:name_adm0":"Bolivia",
    "qs:name_adm1":"Chuquisaca",
    "qs:photos":1,
    "qs:photos_1k":1,
    "qs:photos_9k":14,
    "qs:photos_9r":11,
    "qs:photos_all":3265,
    "qs:photos_sr":1,
    "qs:placetype":"LocalAdmin",
    "qs:pop_sr":"0",
    "qs:woe_adm0":23424762,
    "wof:name":"Sucre",
    "wof:placetype":"localadmin"
},
  "geometry": {"coordinates":[-65.25767,-19.03694],"type":"Point"}
}