{
  "type": "Feature",
  "properties": {
    "gn:admin1_code":"02",
    "gn:asciiname":"Estancia Chiaraque",
    "gn:country_code":"BO",
    "gn:dem":3616,
    "gn:feature_class":"P",
    "gn:feature_code":"PPL",
    "gn:name":"Estancia Chiaraque",
    "gn:population":0,
    "gn:timezone":"America/La_Paz",
    "iso:country":"BO",
    "wof:name":"Estancia Chiaraque",
    "wof:placetype":"locality"
},
  "geometry": {"coordinates":[-66.63333,-17.46667],"type":"Point"}
}