{
  "type": "Feature",
  "properties": {
    "gn:admin1_code":"04",
    "gn:asciiname":"Comunidad Loko Lloko",
    "gn:country_code":"BO",
    "gn:dem":4135,
    "gn:feature_class":"P",
    "gn:feature_code":"PPL",
    "gn:name":"Comunidad Loko Lloko",
    "gn:population":0,
    "gn:timezone":"America/La_Paz",
    "iso:country":"BO",
    "wof:name":"Comunidad Loko Lloko",
    "wof:placetype":"locality"
},
  "geometry": {"coordinates":[-68.56667,-16.55],"type":"Point"}
}