{
  "type": "Feature",
  "properties": {
    "gn:admin1_code":"8.0",
    "gn:asciiname":"Pozo Salvacion",
    "gn:country_code":"BO",
    "gn:dem":382,
    "gn:feature_class":"P",
    "gn:feature_code":"PPL",
    "gn:name":"Pozo Salvaci\u00f3n",
    "gn:population":0,
    "gn:timezone":"America/La_Paz",
    "iso:country":"BO",
    "wof:name":"Pozo Salvacion",
    "wof:placetype":"locality"
},
  "geometry": {"coordinates":[-62.01667,-19.93333],"type":"Point"}
}