{
  "type": "Feature",
  "properties": {
    "gn:admin1_code":"05",
    "gn:asciiname":"Estancia Khara Huano",
    "gn:country_code":"BO",
    "gn:dem":4076,
    "gn:feature_class":"P",
    "gn:feature_code":"PPL",
    "gn:name":"Estancia Khara Huano",
    "gn:population":0,
    "gn:timezone":"America/La_Paz",
    "iso:country":"BO",
    "wof:name":"Estancia Khara Huano",
    "wof:placetype":"locality"
},
  "geometry": {"coordinates":[-68.72505,-18.80613],"type":"Point"}
}