{
  "type": "Feature",
  "properties": {
    "gn:admin1_code":"2.0",
    "gn:asciiname":"Estancia Tajlla",
    "gn:country_code":"BO",
    "gn:dem":3696,
    "gn:feature_class":"P",
    "gn:feature_code":"PPL",
    "gn:name":"Estancia Tajlla",
    "gn:population":0,
    "gn:timezone":"America/La_Paz",
    "iso:country":"BO",
    "wof:name":"Estancia Tajlla",
    "wof:placetype":"locality"
},
  "geometry": {"coordinates":[-66.83333,-17.53333],"type":"Point"}
}