{
  "type": "Feature",
  "properties": {
    "gn:admin1_code":"1.0",
    "gn:asciiname":"Estancia Sor Majchi",
    "gn:country_code":"BO",
    "gn:dem":3146,
    "gn:feature_class":"P",
    "gn:feature_code":"PPL",
    "gn:name":"Estancia Sor Majchi",
    "gn:population":0,
    "gn:timezone":"America/La_Paz",
    "iso:country":"BO",
    "wof:name":"Estancia Sor Majchi",
    "wof:placetype":"locality"
},
  "geometry": {"coordinates":[-65.33849000000001,-20.29197000000001],"type":"Point"}
}