{
  "type": "Feature",
  "properties": {
    "gn:admin1_code":"05",
    "gn:asciiname":"Estancia Jachcha Uta",
    "gn:country_code":"BO",
    "gn:dem":3814,
    "gn:feature_class":"P",
    "gn:feature_code":"PPL",
    "gn:name":"Estancia Jachcha Uta",
    "gn:population":0,
    "gn:timezone":"America/La_Paz",
    "iso:country":"BO",
    "wof:name":"Estancia Jachcha Uta",
    "wof:placetype":"locality"
},
  "geometry": {"coordinates":[-68.53917,-18.36966],"type":"Point"}
}