{
  "type": "Feature",
  "properties": {
    "gn:admin1_code":"8.0",
    "gn:asciiname":"Estancia Vista Hermosa",
    "gn:country_code":"BO",
    "gn:dem":130,
    "gn:feature_class":"P",
    "gn:feature_code":"PPL",
    "gn:name":"Estancia Vista Hermosa",
    "gn:population":0,
    "gn:timezone":"America/La_Paz",
    "iso:country":"BO",
    "wof:name":"Estancia Vista Hermosa",
    "wof:placetype":"locality"
},
  "geometry": {"coordinates":[-59.11666999999999,-16.41667],"type":"Point"}
}