{
  "type": "Feature",
  "properties": {
    "gn:admin1_code":"04",
    "gn:asciiname":"Chijipina Chico",
    "gn:country_code":"BO",
    "gn:dem":3826,
    "gn:feature_class":"P",
    "gn:feature_code":"PPL",
    "gn:name":"Chijipina Chico",
    "gn:population":0,
    "gn:timezone":"America/La_Paz",
    "iso:country":"BO",
    "name:spa_x_preferred":[
        "Chijipina Chico"
    ],
    "name:und_x_variant":[
        "Chijipina",
        "Chinchaya",
        "Chijpina"
    ],
    "wof:name":"Chijipina Chico",
    "wof:placetype":"locality"
},
  "geometry": {"coordinates":[-68.69431,-15.98374],"type":"Point"}
}