{
  "type": "Feature",
  "properties": {
    "gn:admin1_code":"4.0",
    "gn:asciiname":"Santo Diego de Machaca",
    "gn:country_code":"BO",
    "gn:dem":4143,
    "gn:feature_class":"P",
    "gn:feature_code":"PPL",
    "gn:name":"Santo Diego de Machaca",
    "gn:population":0,
    "gn:timezone":"America/La_Paz",
    "iso:country":"BO",
    "wof:name":"Santo Diego de Machaca",
    "wof:placetype":"locality"
},
  "geometry": {"coordinates":[-68.61667,-16.86667000000001],"type":"Point"}
}