{
  "type": "Feature",
  "properties": {
    "gn:admin1_code":"04",
    "gn:asciiname":"Cayapi",
    "gn:country_code":"BO",
    "gn:dem":2690,
    "gn:feature_class":"P",
    "gn:feature_code":"PPL",
    "gn:name":"Cayapi",
    "gn:population":0,
    "gn:timezone":"America/La_Paz",
    "iso:country":"BO",
    "wof:name":"Cayapi",
    "wof:placetype":"locality"
},
  "geometry": {"coordinates":[-67.75,-16.41667],"type":"Point"}
}