{
  "type": "Feature",
  "properties": {
    "gn:admin1_code":"6.0",
    "gn:asciiname":"Puerto Cardenas",
    "gn:country_code":"BO",
    "gn:dem":171,
    "gn:feature_class":"P",
    "gn:feature_code":"PPL",
    "gn:name":"Puerto C\u00e1rdenas",
    "gn:population":0,
    "gn:timezone":"America/La_Paz",
    "iso:country":"BO",
    "wof:name":"Puerto Cardenas",
    "wof:placetype":"locality"
},
  "geometry": {"coordinates":[-67.74375000000001,-11.33846],"type":"Point"}
}