{
  "type": "Feature",
  "properties": {
    "gn:admin1_code":"8.0",
    "gn:asciiname":"Tres Personas",
    "gn:country_code":"BO",
    "gn:dem":254,
    "gn:feature_class":"P",
    "gn:feature_code":"PPL",
    "gn:name":"Tres Personas",
    "gn:population":0,
    "gn:timezone":"America/La_Paz",
    "iso:country":"BO",
    "wof:name":"Tres Personas",
    "wof:placetype":"locality"
},
  "geometry": {"coordinates":[-61.81667,-14.15],"type":"Point"}
}