{
  "type": "Feature",
  "properties": {
    "gn:admin1_code":"06",
    "gn:asciiname":"Veintisiete de Noviembre",
    "gn:country_code":"BO",
    "gn:dem":156,
    "gn:feature_class":"P",
    "gn:feature_code":"PPL",
    "gn:name":"Veintisiete de Noviembre",
    "gn:population":0,
    "gn:timezone":"America/La_Paz",
    "iso:country":"BO",
    "name:spa_x_preferred":[
        "Veintisiete de Noviembre"
    ],
    "wof:name":"Veintisiete de Noviembre",
    "wof:placetype":"locality"
},
  "geometry": {"coordinates":[-67.15857,-10.41454],"type":"Point"}
}