{
  "type": "Feature",
  "properties": {
    "gn:admin1_code":"01",
    "gn:asciiname":"Cerro Colorado",
    "gn:country_code":"BO",
    "gn:dem":2958,
    "gn:feature_class":"P",
    "gn:feature_code":"PPL",
    "gn:name":"Cerro Colorado",
    "gn:population":0,
    "gn:timezone":"America/La_Paz",
    "iso:country":"BO",
    "name:ceb_x_preferred":[
        "Cerro Colorado"
    ],
    "name:deu_x_preferred":[
        "Cerro Colorado"
    ],
    "name:spa_x_preferred":[
        "Cerro Colorado"
    ],
    "name:swe_x_preferred":[
        "Cerro Colorado"
    ],
    "wof:name":"Cerro Colorado",
    "wof:placetype":"locality"
},
  "geometry": {"coordinates":[-65.41849000000001,-20.59517],"type":"Point"}
}