{
  "type": "Feature",
  "properties": {
    "gn:admin1_code":"1.0",
    "gn:asciiname":"Estancia Waca Cancha",
    "gn:country_code":"BO",
    "gn:dem":3117,
    "gn:feature_class":"P",
    "gn:feature_code":"PPL",
    "gn:name":"Estancia Waca Cancha",
    "gn:population":0,
    "gn:timezone":"America/La_Paz",
    "iso:country":"BO",
    "wof:name":"Estancia Waca Cancha",
    "wof:placetype":"locality"
},
  "geometry": {"coordinates":[-65.10072,-20.48581],"type":"Point"}
}