{
  "type": "Feature",
  "properties": {
    "gn:admin1_code":"5.0",
    "gn:asciiname":"Estancia Penablanca",
    "gn:country_code":"BO",
    "gn:dem":3679,
    "gn:feature_class":"P",
    "gn:feature_code":"PPL",
    "gn:name":"Estancia Pe\u00f1ablanca",
    "gn:population":0,
    "gn:timezone":"America/La_Paz",
    "iso:country":"BO",
    "wof:name":"Estancia Penablanca",
    "wof:placetype":"locality"
},
  "geometry": {"coordinates":[-67.78439,-19.7887],"type":"Point"}
}