{
  "type": "Feature",
  "properties": {
    "gn:admin1_code":"08",
    "gn:asciiname":"El Chape",
    "gn:cc2":"BO",
    "gn:country_code":"BO",
    "gn:dem":1603,
    "gn:feature_class":"P",
    "gn:feature_code":"PPL",
    "gn:name":"El Chape",
    "gn:population":0,
    "gn:timezone":"America/La_Paz",
    "iso:country":"BO",
    "name:und_x_variant":[
        "La Chape",
        "El Chape"
    ],
    "wof:name":"El Chape",
    "wof:placetype":"locality"
},
  "geometry": {"coordinates":[-64.03333000000001,-17.91667],"type":"Point"}
}