{
  "type": "Feature",
  "properties": {
    "gn:admin1_code":"07",
    "gn:asciiname":"Antora",
    "gn:country_code":"BO",
    "gn:dem":3679,
    "gn:feature_class":"P",
    "gn:feature_code":"PPL",
    "gn:name":"Antora",
    "gn:population":0,
    "gn:timezone":"America/La_Paz",
    "iso:country":"BO",
    "wof:name":"Antora",
    "wof:placetype":"locality"
},
  "geometry": {"coordinates":[-65.97152,-19.12466],"type":"Point"}
}