{
  "type": "Feature",
  "properties": {
    "gn:admin1_code":"6.0",
    "gn:asciiname":"Florestal",
    "gn:country_code":"BO",
    "gn:dem":251,
    "gn:feature_class":"P",
    "gn:feature_code":"PPL",
    "gn:name":"Florestal",
    "gn:population":0,
    "gn:timezone":"America/La_Paz",
    "iso:country":"BO",
    "name:bpy_x_preferred":[
        "\u09ab\u09cd\u09b2\u09cb\u09b0\u09c7\u09b8\u09cd\u099f\u09be\u09b2"
    ],
    "name:ceb_x_preferred":[
        "Florestal"
    ],
    "name:epo_x_preferred":[
        "Florestal"
    ],
    "name:eus_x_preferred":[
        "Florestal"
    ],
    "name:fra_x_preferred":[
        "Florestal"
    ],
    "name:ita_x_preferred":[
        "Florestal"
    ],
    "name:kat_x_preferred":[
        "\u10e4\u10da\u10dd\u10e0\u10d4\u10e1\u10e2\u10d0\u10da\u10d8"
    ],
    "name:kaz_x_preferred":[
        "\u0424\u043b\u043e\u0440\u0435\u0441\u0442\u0430\u043b"
    ],
    "name:mlg_x_preferred":[
        "Florestal"
    ],
    "name:nld_x_preferred":[
        "Florestal"
    ],
    "name:nor_x_preferred":[
        "Florestal"
    ],
    "name:pol_x_preferred":[
        "Florestal"
    ],
    "name:por_x_preferred":[
        "Florestal"
    ],
    "name:rus_x_preferred":[
        "\u0424\u043b\u043e\u0440\u0435\u0441\u0442\u0430\u043b"
    ],
    "name:sco_x_preferred":[
        "Florestal"
    ],
    "name:spa_x_preferred":[
        "Florestal"
    ],
    "name:swe_x_preferred":[
        "Florestal"
    ],
    "name:und_x_variant":[
        "Flores"
    ],
    "name:vie_x_preferred":[
        "Florestal"
    ],
    "name:vol_x_preferred":[
        "Florestal"
    ],
    "name:war_x_preferred":[
        "Florestal"
    ],
    "name:zho_x_preferred":[
        "\u5f17\u6d1b\u96f7\u65af\u5854\u5c14"
    ],
    "wof:name":"Florestal",
    "wof:placetype":"locality"
},
  "geometry": {"coordinates":[-68.95756999999999,-11.5249],"type":"Point"}
}