{
  "type": "Feature",
  "properties": {
    "gn:admin1_code":"6.0",
    "gn:asciiname":"Florestal",
    "gn:country_code":"BO",
    "gn:dem":251,
    "gn:feature_class":"P",
    "gn:feature_code":"PPL",
    "gn:name":"Florestal",
    "gn:population":0,
    "gn:timezone":"America/La_Paz",
    "iso:country":"BO",
    "name:und_x_variant":[
        "Flores"
    ],
    "wof:name":"Florestal",
    "wof:placetype":"locality"
},
  "geometry": {"coordinates":[-68.95756999999999,-11.5249],"type":"Point"}
}