{
  "type": "Feature",
  "properties": {
    "gn:admin1_code":"4.0",
    "gn:asciiname":"Estancia Pabellon",
    "gn:country_code":"BO",
    "gn:dem":3056,
    "gn:feature_class":"P",
    "gn:feature_code":"PPL",
    "gn:name":"Estancia Pabell\u00f3n",
    "gn:population":0,
    "gn:timezone":"America/La_Paz",
    "iso:country":"BO",
    "wof:name":"Estancia Pabellon",
    "wof:placetype":"locality"
},
  "geometry": {"coordinates":[-67.84999999999999,-16.95],"type":"Point"}
}