{
  "type": "Feature",
  "properties": {
    "gn:admin1_code":"7.0",
    "gn:asciiname":"Estancia Leche Pujio",
    "gn:country_code":"BO",
    "gn:dem":2586,
    "gn:feature_class":"P",
    "gn:feature_code":"PPL",
    "gn:name":"Estancia Leche Pujio",
    "gn:population":0,
    "gn:timezone":"America/La_Paz",
    "iso:country":"BO",
    "wof:name":"Estancia Leche Pujio",
    "wof:placetype":"locality"
},
  "geometry": {"coordinates":[-65.23770999999999,-19.51971],"type":"Point"}
}