{
  "type": "Feature",
  "properties": {
    "gn:admin1_code":"4.0",
    "gn:asciiname":"Estancia Mamaniri",
    "gn:country_code":"BO",
    "gn:dem":3940,
    "gn:feature_class":"P",
    "gn:feature_code":"PPL",
    "gn:name":"Estancia Mamaniri",
    "gn:population":0,
    "gn:timezone":"America/La_Paz",
    "iso:country":"BO",
    "wof:name":"Estancia Mamaniri",
    "wof:placetype":"locality"
},
  "geometry": {"coordinates":[-69.26666999999999,-16.93333],"type":"Point"}
}