{
  "type": "Feature",
  "properties": {
    "gn:admin1_code":"7.0",
    "gn:asciiname":"Pillanta",
    "gn:cc2":"BO",
    "gn:country_code":"BO",
    "gn:dem":3869,
    "gn:feature_class":"P",
    "gn:feature_code":"PPL",
    "gn:name":"Pillanta",
    "gn:population":0,
    "gn:timezone":"America/La_Paz",
    "iso:country":"BO",
    "name:und_x_variant":[
        "Pillana",
        "Pillanta"
    ],
    "wof:name":"Pillanta",
    "wof:placetype":"locality"
},
  "geometry": {"coordinates":[-68.59999999999999,-20.38333],"type":"Point"}
}