{
  "type": "Feature",
  "properties": {
    "gn:admin1_code":"07",
    "gn:asciiname":"Corregidores",
    "gn:cc2":"BO",
    "gn:country_code":"BO",
    "gn:dem":3727,
    "gn:feature_class":"P",
    "gn:feature_code":"PPL",
    "gn:name":"Corregidores",
    "gn:population":0,
    "gn:timezone":"America/La_Paz",
    "iso:country":"BO",
    "name:und_x_variant":[
        "Comunidad Corregidores",
        "Correjidores",
        "Corregidores"
    ],
    "wof:name":"Corregidores",
    "wof:placetype":"locality"
},
  "geometry": {"coordinates":[-67.05,-20.86667000000001],"type":"Point"}
}