{
  "type": "Feature",
  "properties": {
    "gn:admin1_code":"7.0",
    "gn:asciiname":"Molino",
    "gn:country_code":"BO",
    "gn:dem":3462,
    "gn:feature_class":"P",
    "gn:feature_code":"PPL",
    "gn:name":"Molino",
    "gn:population":0,
    "gn:timezone":"America/La_Paz",
    "iso:country":"BO",
    "name:und_x_variant":[
        "Molina",
        "Molino"
    ],
    "wof:name":"Molino",
    "wof:placetype":"locality"
},
  "geometry": {"coordinates":[-66.17653,-20.00619],"type":"Point"}
}