{
  "type": "Feature",
  "properties": {
    "gn:admin1_code":"7.0",
    "gn:asciiname":"Portugalete",
    "gn:country_code":"BO",
    "gn:dem":4194,
    "gn:feature_class":"P",
    "gn:feature_code":"PPL",
    "gn:name":"Portugalete",
    "gn:population":0,
    "gn:timezone":"America/La_Paz",
    "iso:country":"BO",
    "name:ara_x_preferred":[
        "\u0628\u0648\u0631\u062a\u063a\u0627\u0644\u064a\u062a\u064a"
    ],
    "name:arg_x_preferred":[
        "Portugalete"
    ],
    "name:azb_x_preferred":[
        "\u067e\u0648\u0631\u062a\u0648\u0642\u0627\u0644\u062a\u0647"
    ],
    "name:bre_x_preferred":[
        "Portugalete"
    ],
    "name:cat_x_preferred":[
        "Portugalete"
    ],
    "name:ceb_x_preferred":[
        "Portugalete"
    ],
    "name:ces_x_preferred":[
        "Portugalete"
    ],
    "name:cym_x_preferred":[
        "Portugalete"
    ],
    "name:deu_x_preferred":[
        "Portugalete"
    ],
    "name:ell_x_preferred":[
        "\u03a0\u03bf\u03c1\u03c4\u03bf\u03c5\u03b3\u03b1\u03bb\u03ad\u03c4\u03b5"
    ],
    "name:epo_x_preferred":[
        "Portugaleto"
    ],
    "name:eus_x_preferred":[
        "Portugalete"
    ],
    "name:fas_x_preferred":[
        "\u067e\u0648\u0631\u062a\u0648\u06af\u0627\u0644\u062a\u0647"
    ],
    "name:fra_x_preferred":[
        "Portugalete"
    ],
    "name:glg_x_preferred":[
        "Portugalete"
    ],
    "name:heb_x_preferred":[
        "\u05e4\u05d5\u05e8\u05d8\u05d5\u05d2\u05dc\u05d8\u05d4"
    ],
    "name:hun_x_preferred":[
        "Portugalete"
    ],
    "name:hye_x_preferred":[
        "\u054a\u0578\u0580\u057f\u0578\u0582\u0563\u0561\u056c\u0565\u057f\u0565"
    ],
    "name:ita_x_preferred":[
        "Portugalete"
    ],
    "name:jpn_x_preferred":[
        "\u30dd\u30eb\u30c8\u30a5\u30ac\u30ec\u30c6"
    ],
    "name:lat_x_preferred":[
        "Portus Gallorum"
    ],
    "name:mlg_x_preferred":[
        "Portugalete"
    ],
    "name:msa_x_preferred":[
        "Portugalete"
    ],
    "name:nld_x_preferred":[
        "Portugalete"
    ],
    "name:oci_x_preferred":[
        "Portugalete"
    ],
    "name:pol_x_preferred":[
        "Portugalete"
    ],
    "name:por_x_preferred":[
        "Portugalete"
    ],
    "name:rus_x_preferred":[
        "\u041f\u043e\u0440\u0442\u0443\u0433\u0430\u043b\u0435\u0442\u0435"
    ],
    "name:sco_x_preferred":[
        "Portugalete"
    ],
    "name:spa_x_preferred":[
        "Portugalete"
    ],
    "name:sqi_x_preferred":[
        "Portugalete"
    ],
    "name:srp_x_preferred":[
        "\u041f\u043e\u0440\u0442\u0443\u0433\u0430\u043b\u0435\u0442\u0435"
    ],
    "name:swe_x_preferred":[
        "Portugalete"
    ],
    "name:tur_x_preferred":[
        "Portugalete"
    ],
    "name:ukr_x_preferred":[
        "\u041f\u043e\u0440\u0442\u0443\u0433\u0430\u043b\u0435\u0442\u0435"
    ],
    "name:und_x_variant":[
        "Tortugalete Pacheco",
        "Portugaleti"
    ],
    "name:uzb_x_preferred":[
        "Portugalete"
    ],
    "name:war_x_preferred":[
        "Portugalete"
    ],
    "name:zho_x_preferred":[
        "\u6ce2\u5c14\u56fe\u52a0\u83b1\u7279"
    ],
    "wof:name":"Portugalete",
    "wof:placetype":"locality"
},
  "geometry": {"coordinates":[-66.16643000000001,-21.17317],"type":"Point"}
}