{
  "type": "Feature",
  "properties": {
    "gn:admin1_code":"7.0",
    "gn:asciiname":"Portugalete",
    "gn:country_code":"BO",
    "gn:dem":4194,
    "gn:feature_class":"P",
    "gn:feature_code":"PPL",
    "gn:name":"Portugalete",
    "gn:population":0,
    "gn:timezone":"America/La_Paz",
    "iso:country":"BO",
    "name:und_x_variant":[
        "Tortugalete Pacheco",
        "Portugaleti",
        "Portugalete"
    ],
    "wof:name":"Portugalete",
    "wof:placetype":"locality"
},
  "geometry": {"coordinates":[-66.16643000000001,-21.17317],"type":"Point"}
}