{
  "type": "Feature",
  "properties": {
    "gn:admin1_code":"07",
    "gn:asciiname":"Chinoli",
    "gn:country_code":"BO",
    "gn:dem":3332,
    "gn:feature_class":"P",
    "gn:feature_code":"PPL",
    "gn:name":"Chinoli",
    "gn:population":0,
    "gn:timezone":"America/La_Paz",
    "iso:country":"BO",
    "name:und_x_variant":[
        "Chimuli",
        "Chinoli"
    ],
    "wof:name":"Chinoli",
    "wof:placetype":"locality"
},
  "geometry": {"coordinates":[-65.28537,-19.70543],"type":"Point"}
}