{
  "type": "Feature",
  "properties": {
    "gn:admin1_code":"08",
    "gn:asciiname":"Brasilia",
    "gn:country_code":"BO",
    "gn:dem":266,
    "gn:feature_class":"P",
    "gn:feature_code":"PPL",
    "gn:name":"Brasilia",
    "gn:population":0,
    "gn:timezone":"America/La_Paz",
    "iso:country":"BO",
    "wof:name":"Brasilia",
    "wof:placetype":"locality"
},
  "geometry": {"coordinates":[-62.83333,-17.28333],"type":"Point"}
}