{
  "type": "Feature",
  "properties": {
    "gn:admin1_code":"5.0",
    "gn:asciiname":"La Joya",
    "gn:country_code":"BO",
    "gn:dem":3735,
    "gn:feature_class":"P",
    "gn:feature_code":"PPL",
    "gn:name":"La Joya",
    "gn:population":0,
    "gn:timezone":"America/La_Paz",
    "iso:country":"BO",
    "name:und_x_variant":[
        "Oruro",
        "La Joya"
    ],
    "wof:name":"La Joya",
    "wof:placetype":"locality"
},
  "geometry": {"coordinates":[-67.49597,-17.77228999999999],"type":"Point"}
}