{
  "type": "Feature",
  "properties": {
    "gn:admin1_code":"8.0",
    "gn:asciiname":"Veladero",
    "gn:country_code":"BO",
    "gn:dem":2044,
    "gn:feature_class":"P",
    "gn:feature_code":"PPL",
    "gn:name":"Veladero",
    "gn:population":0,
    "gn:timezone":"America/La_Paz",
    "iso:country":"BO",
    "name:ita_x_preferred":[
        "Veladero"
    ],
    "name:spa_x_preferred":[
        "Veladero"
    ],
    "name:zho_x_preferred":[
        "\u8d1d\u62c9\u5fb7\u7f57"
    ],
    "wof:name":"Veladero",
    "wof:placetype":"locality"
},
  "geometry": {"coordinates":[-64.26666999999999,-18.26667],"type":"Point"}
}