{
  "type": "Feature",
  "properties": {
    "gn:admin1_code":"05",
    "gn:asciiname":"Chillahua",
    "gn:cc2":"BO",
    "gn:country_code":"BO",
    "gn:dem":3754,
    "gn:feature_class":"P",
    "gn:feature_code":"PPL",
    "gn:name":"Chillahua",
    "gn:population":0,
    "gn:timezone":"America/La_Paz",
    "iso:country":"BO",
    "name:und_x_variant":[
        "Chillagua",
        "Chillahua"
    ],
    "wof:name":"Chillahua",
    "wof:placetype":"locality"
},
  "geometry": {"coordinates":[-68.21666999999999,-18.56667],"type":"Point"}
}