{
  "type": "Feature",
  "properties": {
    "gn:admin1_code":"4.0",
    "gn:asciiname":"Sallani",
    "gn:country_code":"BO",
    "gn:dem":2695,
    "gn:feature_class":"P",
    "gn:feature_code":"PPL",
    "gn:name":"Sallani",
    "gn:population":0,
    "gn:timezone":"America/La_Paz",
    "iso:country":"BO",
    "wof:name":"Sallani",
    "wof:placetype":"locality"
},
  "geometry": {"coordinates":[-67.83333,-16.96667],"type":"Point"}
}