{
  "type": "Feature",
  "properties": {
    "gn:admin1_code":"8.0",
    "gn:asciiname":"La Cautiva",
    "gn:country_code":"BO",
    "gn:dem":454,
    "gn:feature_class":"P",
    "gn:feature_code":"PPL",
    "gn:name":"La Cautiva",
    "gn:population":0,
    "gn:timezone":"America/La_Paz",
    "iso:country":"BO",
    "wof:name":"La Cautiva",
    "wof:placetype":"locality"
},
  "geometry": {"coordinates":[-61.95,-19.68333],"type":"Point"}
}