{
  "type": "Feature",
  "properties": {
    "gn:admin1_code":"7.0",
    "gn:asciiname":"Tambillos",
    "gn:country_code":"BO",
    "gn:dem":3021,
    "gn:feature_class":"P",
    "gn:feature_code":"PPL",
    "gn:name":"Tambillos",
    "gn:population":0,
    "gn:timezone":"America/La_Paz",
    "iso:country":"BO",
    "wof:name":"Tambillos",
    "wof:placetype":"locality"
},
  "geometry": {"coordinates":[-65.73329,-21.39875],"type":"Point"}
}