{
  "type": "Feature",
  "properties": {
    "gn:admin1_code":"07",
    "gn:asciiname":"Chajrahuaico",
    "gn:country_code":"BO",
    "gn:dem":3778,
    "gn:feature_class":"P",
    "gn:feature_code":"PPL",
    "gn:name":"Chajrahuaico",
    "gn:population":0,
    "gn:timezone":"America/La_Paz",
    "iso:country":"BO",
    "wof:name":"Chajrahuaico",
    "wof:placetype":"locality"
},
  "geometry": {"coordinates":[-66.43333,-22.13333],"type":"Point"}
}