{
  "type": "Feature",
  "properties": {
    "gn:admin1_code":"3.0",
    "gn:asciiname":"Papanto",
    "gn:country_code":"BO",
    "gn:dem":144,
    "gn:feature_class":"P",
    "gn:feature_code":"PPL",
    "gn:name":"Papanto",
    "gn:population":0,
    "gn:timezone":"America/La_Paz",
    "iso:country":"BO",
    "wof:name":"Papanto",
    "wof:placetype":"locality"
},
  "geometry": {"coordinates":[-65.38333,-13.96667],"type":"Point"}
}