{
  "type": "Feature",
  "properties": {
    "gn:admin1_code":"7.0",
    "gn:asciiname":"Llatilquima",
    "gn:cc2":"BO",
    "gn:country_code":"BO",
    "gn:dem":4072,
    "gn:feature_class":"P",
    "gn:feature_code":"PPL",
    "gn:name":"Llatilquima",
    "gn:population":0,
    "gn:timezone":"America/La_Paz",
    "iso:country":"BO",
    "name:und_x_variant":[
        "Llatiquima",
        "Llatilquima"
    ],
    "wof:name":"Llatilquima",
    "wof:placetype":"locality"
},
  "geometry": {"coordinates":[-68.33333,-19.98333],"type":"Point"}
}