{
  "type": "Feature",
  "properties": {
    "gn:admin1_code":"06",
    "gn:asciiname":"Borchi",
    "gn:country_code":"BO",
    "gn:dem":207,
    "gn:feature_class":"P",
    "gn:feature_code":"PPL",
    "gn:name":"Borchi",
    "gn:population":0,
    "gn:timezone":"America/La_Paz",
    "iso:country":"BO",
    "name:spa_x_preferred":[
        "Borchi"
    ],
    "wof:name":"Borchi",
    "wof:placetype":"locality"
},
  "geometry": {"coordinates":[-67.82403000000001,-10.95919],"type":"Point"}
}