{
  "type": "Feature",
  "properties": {
    "gn:admin1_code":"6.0",
    "gn:asciiname":"Santa Rosa del Abuna",
    "gn:cc2":"BO",
    "gn:country_code":"BO",
    "gn:dem":141,
    "gn:feature_class":"P",
    "gn:feature_code":"PPL",
    "gn:name":"Santa Rosa del Abun\u00e1",
    "gn:population":0,
    "gn:timezone":"America/La_Paz",
    "iso:country":"BO",
    "name:deu_x_preferred":[
        "Santa Rosa del Abun\u00e1"
    ],
    "name:que_x_preferred":[
        "Santa Rosa del Abun\u00e1"
    ],
    "name:spa_x_preferred":[
        "Santa Rosa del Abun\u00e1"
    ],
    "name:und_x_variant":[
        "Fort\u00edn Santa Rosa",
        "Santa Rosa",
        "Santa Rosa del Abun\u00e1"
    ],
    "wof:name":"Santa Rosa del Abuna",
    "wof:placetype":"locality"
},
  "geometry": {"coordinates":[-67.45246999999999,-10.60743],"type":"Point"}
}