{
  "type": "Feature",
  "properties": {
    "gn:admin1_code":"8.0",
    "gn:asciiname":"Tres Salitres",
    "gn:cc2":"BO",
    "gn:country_code":"BO",
    "gn:dem":215,
    "gn:feature_class":"P",
    "gn:feature_code":"PPL",
    "gn:name":"Tres Salitres",
    "gn:population":0,
    "gn:timezone":"America/La_Paz",
    "iso:country":"BO",
    "name:und_x_variant":[
        "Tres Sauces",
        "Tres Salitres"
    ],
    "wof:name":"Tres Salitres",
    "wof:placetype":"locality"
},
  "geometry": {"coordinates":[-63.55,-16.73333],"type":"Point"}
}