{
  "type": "Feature",
  "properties": {
    "gn:admin1_code":"2.0",
    "gn:asciiname":"Villa Carmen",
    "gn:country_code":"BO",
    "gn:dem":2710,
    "gn:feature_class":"P",
    "gn:feature_code":"PPL",
    "gn:name":"Villa Carmen",
    "gn:population":0,
    "gn:timezone":"America/La_Paz",
    "iso:country":"BO",
    "name:ita_x_preferred":[
        "Villa Carmen"
    ],
    "wof:name":"Villa Carmen",
    "wof:placetype":"locality"
},
  "geometry": {"coordinates":[-66.09813,-17.545],"type":"Point"}
}