{
  "type": "Feature",
  "properties": {
    "gn:admin1_code":"03",
    "gn:asciiname":"Carrito",
    "gn:country_code":"BO",
    "gn:dem":138,
    "gn:feature_class":"P",
    "gn:feature_code":"PPL",
    "gn:name":"Carrito",
    "gn:population":0,
    "gn:timezone":"America/La_Paz",
    "iso:country":"BO",
    "wof:name":"Carrito",
    "wof:placetype":"locality"
},
  "geometry": {"coordinates":[-65.41667,-13.21667],"type":"Point"}
}