{
  "type": "Feature",
  "properties": {
    "gn:admin1_code":"08",
    "gn:asciiname":"Embocada",
    "gn:country_code":"BO",
    "gn:dem":348,
    "gn:feature_class":"P",
    "gn:feature_code":"PPL",
    "gn:name":"Embocada",
    "gn:population":0,
    "gn:timezone":"America/La_Paz",
    "iso:country":"BO",
    "wof:name":"Embocada",
    "wof:placetype":"locality"
},
  "geometry": {"coordinates":[-60.33333,-16.73333],"type":"Point"}
}