{
  "type": "Feature",
  "properties": {
    "gn:admin1_code":"7.0",
    "gn:asciiname":"Estancia Tokho Chaca",
    "gn:country_code":"BO",
    "gn:dem":4056,
    "gn:feature_class":"P",
    "gn:feature_code":"PPL",
    "gn:name":"Estancia Tokho Chaca",
    "gn:population":0,
    "gn:timezone":"America/La_Paz",
    "iso:country":"BO",
    "wof:name":"Estancia Tokho Chaca",
    "wof:placetype":"locality"
},
  "geometry": {"coordinates":[-65.67255,-19.31211],"type":"Point"}
}