{
  "type": "Feature",
  "properties": {
    "gn:admin1_code":"02",
    "gn:asciiname":"Chillincasa",
    "gn:country_code":"BO",
    "gn:dem":3671,
    "gn:feature_class":"P",
    "gn:feature_code":"PPL",
    "gn:name":"Chillincasa",
    "gn:population":0,
    "gn:timezone":"America/La_Paz",
    "iso:country":"BO",
    "name:und_x_variant":[
        "Chilinkasa",
        "Chilincasa",
        "Chillincasa"
    ],
    "wof:name":"Chillincasa",
    "wof:placetype":"locality"
},
  "geometry": {"coordinates":[-65.63051,-17.71546],"type":"Point"}
}