{
  "type": "Feature",
  "properties": {
    "gn:admin1_code":"7.0",
    "gn:asciiname":"Estancia Quigina",
    "gn:country_code":"BO",
    "gn:dem":3995,
    "gn:feature_class":"P",
    "gn:feature_code":"PPL",
    "gn:name":"Estancia Quigina",
    "gn:population":0,
    "gn:timezone":"America/La_Paz",
    "iso:country":"BO",
    "wof:name":"Estancia Quigina",
    "wof:placetype":"locality"
},
  "geometry": {"coordinates":[-68.34496999999999,-19.86751],"type":"Point"}
}