{
  "type": "Feature",
  "properties": {
    "gn:admin1_code":"02",
    "gn:asciiname":"Estancia Caporuro",
    "gn:country_code":"BO",
    "gn:dem":3123,
    "gn:feature_class":"P",
    "gn:feature_code":"PPL",
    "gn:name":"Estancia Caporuro",
    "gn:population":0,
    "gn:timezone":"America/La_Paz",
    "iso:country":"BO",
    "wof:name":"Estancia Caporuro",
    "wof:placetype":"locality"
},
  "geometry": {"coordinates":[-66.75,-17.26667],"type":"Point"}
}