{
  "type": "Feature",
  "properties": {
    "gn:admin1_code":"06",
    "gn:asciiname":"Dionisio",
    "gn:cc2":"BO",
    "gn:country_code":"BO",
    "gn:dem":165,
    "gn:feature_class":"P",
    "gn:feature_code":"PPL",
    "gn:name":"Dionisio",
    "gn:population":0,
    "gn:timezone":"America/La_Paz",
    "iso:country":"BO",
    "name:und_x_variant":[
        "Dionicio",
        "Dionisio"
    ],
    "wof:name":"Dionisio",
    "wof:placetype":"locality"
},
  "geometry": {"coordinates":[-67.66667,-10.76667],"type":"Point"}
}