{
  "type": "Feature",
  "properties": {
    "gn:admin1_code":"08",
    "gn:asciiname":"Asunta",
    "gn:cc2":"BO",
    "gn:country_code":"BO",
    "gn:dem":341,
    "gn:feature_class":"P",
    "gn:feature_code":"PPL",
    "gn:name":"Asunta",
    "gn:population":0,
    "gn:timezone":"America/La_Paz",
    "iso:country":"BO",
    "name:und_x_variant":[
        "La Asunta",
        "Asunta"
    ],
    "wof:name":"Asunta",
    "wof:placetype":"locality"
},
  "geometry": {"coordinates":[-62.43333000000001,-15.56667],"type":"Point"}
}