{
  "type": "Feature",
  "properties": {
    "gn:admin1_code":"04",
    "gn:asciiname":"Collabamba",
    "gn:country_code":"BO",
    "gn:dem":2903,
    "gn:feature_class":"P",
    "gn:feature_code":"PPL",
    "gn:name":"Collabamba",
    "gn:population":0,
    "gn:timezone":"America/La_Paz",
    "iso:country":"BO",
    "name:spa_x_preferred":[
        "Collabamba"
    ],
    "name:spa_x_variant":[
        "Colabamba"
    ],
    "wof:name":"Collabamba",
    "wof:placetype":"locality"
},
  "geometry": {"coordinates":[-68.63298,-15.50461],"type":"Point"}
}