{
  "type": "Feature",
  "properties": {
    "gn:admin1_code":"04",
    "gn:asciiname":"Collpani",
    "gn:country_code":"BO",
    "gn:dem":3816,
    "gn:feature_class":"P",
    "gn:feature_code":"PPL",
    "gn:name":"Collpani",
    "gn:population":0,
    "gn:timezone":"America/La_Paz",
    "iso:country":"BO",
    "name:spa_x_preferred":[
        "Collpani"
    ],
    "wof:name":"Collpani",
    "wof:placetype":"locality"
},
  "geometry": {"coordinates":[-68.71980000000001,-15.84964],"type":"Point"}
}