{
  "type": "Feature",
  "properties": {
    "gn:admin1_code":"8.0",
    "gn:asciiname":"Estancia Tocoma",
    "gn:country_code":"BO",
    "gn:dem":416,
    "gn:feature_class":"P",
    "gn:feature_code":"PPL",
    "gn:name":"Estancia Tocoma",
    "gn:population":0,
    "gn:timezone":"America/La_Paz",
    "iso:country":"BO",
    "wof:name":"Estancia Tocoma",
    "wof:placetype":"locality"
},
  "geometry": {"coordinates":[-60.78333000000001,-16.85],"type":"Point"}
}