{
  "type": "Feature",
  "properties": {
    "gn:admin1_code":"06",
    "gn:asciiname":"La Rosa",
    "gn:country_code":"BO",
    "gn:dem":276,
    "gn:feature_class":"P",
    "gn:feature_code":"PPL",
    "gn:name":"La Rosa",
    "gn:population":0,
    "gn:timezone":"America/La_Paz",
    "iso:country":"BO",
    "wof:name":"La Rosa",
    "wof:placetype":"locality"
},
  "geometry": {"coordinates":[-69.01214,-11.33557],"type":"Point"}
}