{
  "type": "Feature",
  "properties": {
    "gn:admin1_code":"8.0",
    "gn:asciiname":"Yuarenda",
    "gn:cc2":"BO",
    "gn:country_code":"BO",
    "gn:dem":1081,
    "gn:feature_class":"P",
    "gn:feature_code":"PPL",
    "gn:name":"Yuarenda",
    "gn:population":0,
    "gn:timezone":"America/La_Paz",
    "iso:country":"BO",
    "name:und_x_variant":[
        "Yuairenda",
        "Yuarenda"
    ],
    "wof:name":"Yuarenda",
    "wof:placetype":"locality"
},
  "geometry": {"coordinates":[-63.48333,-19.81667],"type":"Point"}
}