{
  "type": "Feature",
  "properties": {
    "gn:admin1_code":"06",
    "gn:asciiname":"Palacios",
    "gn:country_code":"BO",
    "gn:dem":173,
    "gn:feature_class":"P",
    "gn:feature_code":"PPL",
    "gn:name":"Palacios",
    "gn:population":0,
    "gn:timezone":"America/La_Paz",
    "iso:country":"BO",
    "name:cat_x_preferred":[
        "Palacios"
    ],
    "name:ceb_x_preferred":[
        "Palacios"
    ],
    "name:ces_x_preferred":[
        "Palacios"
    ],
    "name:deu_x_preferred":[
        "Palacios"
    ],
    "name:fra_x_preferred":[
        "Palacios"
    ],
    "name:ita_x_preferred":[
        "Palacios"
    ],
    "name:jpn_x_preferred":[
        "\u30d1\u30e9\u30b7\u30aa\u30b9"
    ],
    "name:nds_x_preferred":[
        "Palacios"
    ],
    "name:rus_x_preferred":[
        "\u041f\u0430\u043b\u0430\u0441\u0438\u043e\u0441"
    ],
    "name:slv_x_preferred":[
        "Palacios"
    ],
    "name:spa_x_preferred":[
        "Palacios"
    ],
    "name:spa_x_variant":[
        "Rancho Palacio"
    ],
    "name:swe_x_preferred":[
        "Palacios"
    ],
    "name:ukr_x_preferred":[
        "\u041f\u0430\u043b\u0430\u0441\u0456\u043e\u0441"
    ],
    "wof:name":"Palacios",
    "wof:placetype":"locality"
},
  "geometry": {"coordinates":[-67.62906,-11.14024],"type":"Point"}
}