{
  "type": "Feature",
  "properties": {
    "gn:admin1_code":"06",
    "gn:asciiname":"Palacios",
    "gn:country_code":"BO",
    "gn:dem":173,
    "gn:feature_class":"P",
    "gn:feature_code":"PPL",
    "gn:name":"Palacios",
    "gn:population":0,
    "gn:timezone":"America/La_Paz",
    "iso:country":"BO",
    "name:spa_x_preferred":[
        "Palacios"
    ],
    "name:spa_x_variant":[
        "Rancho Palacio"
    ],
    "wof:name":"Palacios",
    "wof:placetype":"locality"
},
  "geometry": {"coordinates":[-67.62906,-11.14024],"type":"Point"}
}