{
  "type": "Feature",
  "properties": {
    "gn:admin1_code":"9.0",
    "gn:asciiname":"Junacas",
    "gn:country_code":"BO",
    "gn:dem":2348,
    "gn:feature_class":"P",
    "gn:feature_code":"PPL",
    "gn:name":"Junacas",
    "gn:population":0,
    "gn:timezone":"America/La_Paz",
    "iso:country":"BO",
    "wof:name":"Junacas",
    "wof:placetype":"locality"
},
  "geometry": {"coordinates":[-64.46056999999999,-21.43586],"type":"Point"}
}