{
  "type": "Feature",
  "properties": {
    "gn:admin1_code":"06",
    "gn:asciiname":"Avilio",
    "gn:country_code":"BO",
    "gn:dem":214,
    "gn:feature_class":"P",
    "gn:feature_code":"PPL",
    "gn:name":"Avilio",
    "gn:population":0,
    "gn:timezone":"America/La_Paz",
    "iso:country":"BO",
    "wof:name":"Avilio",
    "wof:placetype":"locality"
},
  "geometry": {"coordinates":[-67.51666999999999,-11.38333],"type":"Point"}
}