{
  "type": "Feature",
  "properties": {
    "gn:admin1_code":"7.0",
    "gn:asciiname":"Polulos",
    "gn:country_code":"BO",
    "gn:dem":4049,
    "gn:feature_class":"P",
    "gn:feature_code":"PPL",
    "gn:name":"Polulos",
    "gn:population":0,
    "gn:timezone":"America/La_Paz",
    "iso:country":"BO",
    "wof:name":"Polulos",
    "wof:placetype":"locality"
},
  "geometry": {"coordinates":[-66.67069000000001,-21.50508],"type":"Point"}
}