{
  "type": "Feature",
  "properties": {
    "gn:admin1_code":"5.0",
    "gn:asciiname":"Pasto Grande",
    "gn:country_code":"BO",
    "gn:dem":3749,
    "gn:feature_class":"P",
    "gn:feature_code":"PPL",
    "gn:name":"Pasto Grande",
    "gn:population":0,
    "gn:timezone":"America/La_Paz",
    "iso:country":"BO",
    "wof:name":"Pasto Grande",
    "wof:placetype":"locality"
},
  "geometry": {"coordinates":[-67.15000000000001,-17.71667],"type":"Point"}
}