{
  "type": "Feature",
  "properties": {
    "gn:admin1_code":"03",
    "gn:asciiname":"Sasasama",
    "gn:country_code":"BO",
    "gn:dem":258,
    "gn:feature_class":"P",
    "gn:feature_code":"PPL",
    "gn:name":"Sasasama",
    "gn:population":0,
    "gn:timezone":"America/La_Paz",
    "iso:country":"BO",
    "wof:name":"Sasasama",
    "wof:placetype":"locality"
},
  "geometry": {"coordinates":[-65.75,-16.61667000000001],"type":"Point"}
}