{
  "type": "Feature",
  "properties": {
    "gn:admin1_code":"04",
    "gn:asciiname":"Estancia Kasilla",
    "gn:country_code":"BO",
    "gn:dem":3880,
    "gn:feature_class":"P",
    "gn:feature_code":"PPL",
    "gn:name":"Estancia Kasilla",
    "gn:population":0,
    "gn:timezone":"America/La_Paz",
    "iso:country":"BO",
    "wof:name":"Estancia Kasilla",
    "wof:placetype":"locality"
},
  "geometry": {"coordinates":[-68.45,-17.81667000000001],"type":"Point"}
}