{
  "type": "Feature",
  "properties": {
    "gn:admin1_code":"8.0",
    "gn:asciiname":"Panacu",
    "gn:country_code":"BO",
    "gn:dem":442,
    "gn:feature_class":"P",
    "gn:feature_code":"PPL",
    "gn:name":"Panac\u00fa",
    "gn:population":0,
    "gn:timezone":"America/La_Paz",
    "iso:country":"BO",
    "wof:name":"Panacu",
    "wof:placetype":"locality"
},
  "geometry": {"coordinates":[-61.13333000000001,-16.78333],"type":"Point"}
}