{
  "type": "Feature",
  "properties": {
    "gn:admin1_code":"3.0",
    "gn:asciiname":"Puerto San Martin",
    "gn:cc2":"BO",
    "gn:country_code":"BO",
    "gn:dem":137,
    "gn:feature_class":"P",
    "gn:feature_code":"PPL",
    "gn:name":"Puerto San Mart\u00edn",
    "gn:population":0,
    "gn:timezone":"America/La_Paz",
    "iso:country":"BO",
    "name:und_x_variant":[
        "San Martin",
        "Puerto San Mart\u00edn"
    ],
    "wof:name":"Puerto San Martin",
    "wof:placetype":"locality"
},
  "geometry": {"coordinates":[-65.25,-13.23333],"type":"Point"}
}