{
  "type": "Feature",
  "properties": {
    "gn:admin1_code":"8.0",
    "gn:asciiname":"Pozos Negros",
    "gn:country_code":"BO",
    "gn:dem":516,
    "gn:feature_class":"P",
    "gn:feature_code":"PPL",
    "gn:name":"Pozos Negros",
    "gn:population":0,
    "gn:timezone":"America/La_Paz",
    "iso:country":"BO",
    "wof:name":"Pozos Negros",
    "wof:placetype":"locality"
},
  "geometry": {"coordinates":[-62.76667,-20.01667],"type":"Point"}
}