{
  "type": "Feature",
  "properties": {
    "gn:admin1_code":"05",
    "gn:asciiname":"Comunidad Colque Khaua",
    "gn:country_code":"BO",
    "gn:dem":4160,
    "gn:feature_class":"P",
    "gn:feature_code":"PPL",
    "gn:name":"Comunidad Colque Khaua",
    "gn:population":0,
    "gn:timezone":"America/La_Paz",
    "iso:country":"BO",
    "wof:name":"Comunidad Colque Khaua",
    "wof:placetype":"locality"
},
  "geometry": {"coordinates":[-67.83333,-17.95],"type":"Point"}
}