{
  "type": "Feature",
  "properties": {
    "gn:admin1_code":"4.0",
    "gn:asciiname":"Jarka",
    "gn:cc2":"BO",
    "gn:country_code":"BO",
    "gn:dem":3074,
    "gn:feature_class":"P",
    "gn:feature_code":"PPL",
    "gn:name":"Jarka",
    "gn:population":0,
    "gn:timezone":"America/La_Paz",
    "iso:country":"BO",
    "name:und_x_variant":[
        "Harka",
        "Jarka"
    ],
    "wof:name":"Jarka",
    "wof:placetype":"locality"
},
  "geometry": {"coordinates":[-67.98333000000001,-16.08333],"type":"Point"}
}