{
  "type": "Feature",
  "properties": {
    "gn:admin1_code":"7.0",
    "gn:asciiname":"Totorapampa",
    "gn:country_code":"BO",
    "gn:dem":3772,
    "gn:feature_class":"P",
    "gn:feature_code":"PPL",
    "gn:name":"Totorapampa",
    "gn:population":0,
    "gn:timezone":"America/La_Paz",
    "iso:country":"BO",
    "wof:name":"Totorapampa",
    "wof:placetype":"locality"
},
  "geometry": {"coordinates":[-66.45,-20.51667],"type":"Point"}
}