{
  "type": "Feature",
  "properties": {
    "gn:admin1_code":"06",
    "gn:asciiname":"Truin de Palo",
    "gn:country_code":"BO",
    "gn:dem":167,
    "gn:feature_class":"P",
    "gn:feature_code":"PPL",
    "gn:name":"Truin de Palo",
    "gn:population":0,
    "gn:timezone":"America/La_Paz",
    "iso:country":"BO",
    "name:spa_x_preferred":[
        "Truin de Palo"
    ],
    "wof:name":"Truin de Palo",
    "wof:placetype":"locality"
},
  "geometry": {"coordinates":[-67.29857,-10.52894],"type":"Point"}
}