{
  "type": "Feature",
  "properties": {
    "gn:admin1_code":"02",
    "gn:asciiname":"Chillcamallina",
    "gn:country_code":"BO",
    "gn:dem":3200,
    "gn:feature_class":"P",
    "gn:feature_code":"PPL",
    "gn:name":"Chillcamallina",
    "gn:population":0,
    "gn:timezone":"America/La_Paz",
    "iso:country":"BO",
    "wof:name":"Chillcamallina",
    "wof:placetype":"locality"
},
  "geometry": {"coordinates":[-66.61667,-17.55],"type":"Point"}
}