{
  "type": "Feature",
  "properties": {
    "gn:admin1_code":"05",
    "gn:asciiname":"Challahuani",
    "gn:country_code":"BO",
    "gn:dem":3845,
    "gn:feature_class":"P",
    "gn:feature_code":"PPL",
    "gn:name":"Challahuani",
    "gn:population":0,
    "gn:timezone":"America/La_Paz",
    "iso:country":"BO",
    "name:und_x_variant":[
        "Challhuani",
        "Challahuani"
    ],
    "wof:name":"Challahuani",
    "wof:placetype":"locality"
},
  "geometry": {"coordinates":[-67.90786999999999,-18.34509],"type":"Point"}
}