{
  "type": "Feature",
  "properties": {
    "gn:admin1_code":"08",
    "gn:asciiname":"Estancia El Gavilan",
    "gn:country_code":"BO",
    "gn:dem":303,
    "gn:feature_class":"P",
    "gn:feature_code":"PPL",
    "gn:name":"Estancia El Gavil\u00e1n",
    "gn:population":0,
    "gn:timezone":"America/La_Paz",
    "iso:country":"BO",
    "wof:name":"Estancia El Gavilan",
    "wof:placetype":"locality"
},
  "geometry": {"coordinates":[-63.28333000000001,-17.36667000000001],"type":"Point"}
}