{
  "type": "Feature",
  "properties": {
    "gn:admin1_code":"07",
    "gn:asciiname":"Cancha",
    "gn:country_code":"BO",
    "gn:dem":2696,
    "gn:feature_class":"P",
    "gn:feature_code":"PPL",
    "gn:name":"Cancha",
    "gn:population":0,
    "gn:timezone":"America/La_Paz",
    "iso:country":"BO",
    "name:und_x_variant":[
        "Tanta Cancha",
        "Cancha"
    ],
    "wof:name":"Cancha",
    "wof:placetype":"locality"
},
  "geometry": {"coordinates":[-65.22525,-19.68942],"type":"Point"}
}