{
  "type": "Feature",
  "properties": {
    "gn:admin1_code":"06",
    "gn:asciiname":"Alianza",
    "gn:country_code":"BO",
    "gn:dem":192,
    "gn:feature_class":"P",
    "gn:feature_code":"PPL",
    "gn:name":"Alianza",
    "gn:population":0,
    "gn:timezone":"America/La_Paz",
    "iso:country":"BO",
    "name:ceb_x_preferred":[
        "Alianza"
    ],
    "name:por_x_preferred":[
        "Alianza"
    ],
    "name:spa_x_preferred":[
        "Alianza"
    ],
    "name:swe_x_preferred":[
        "Alianza"
    ],
    "wof:name":"Alianza",
    "wof:placetype":"locality"
},
  "geometry": {"coordinates":[-67.977,-11.48932],"type":"Point"}
}