{
  "type": "Feature",
  "properties": {
    "gn:admin1_code":"5.0",
    "gn:asciiname":"Halenta",
    "gn:country_code":"BO",
    "gn:dem":4379,
    "gn:feature_class":"P",
    "gn:feature_code":"PPL",
    "gn:name":"Halenta",
    "gn:population":0,
    "gn:timezone":"America/La_Paz",
    "iso:country":"BO",
    "wof:name":"Halenta",
    "wof:placetype":"locality"
},
  "geometry": {"coordinates":[-68.53333000000001,-18.18333],"type":"Point"}
}