{
  "type": "Feature",
  "properties": {
    "gn:admin1_code":"02",
    "gn:asciiname":"Cabrera",
    "gn:country_code":"BO",
    "gn:dem":2196,
    "gn:feature_class":"P",
    "gn:feature_code":"PPL",
    "gn:name":"Cabrera",
    "gn:population":0,
    "gn:timezone":"America/La_Paz",
    "iso:country":"BO",
    "name:und_x_variant":[
        "Cabrera Rancho",
        "Cabrera"
    ],
    "wof:name":"Cabrera",
    "wof:placetype":"locality"
},
  "geometry": {"coordinates":[-64.57739000000001,-18.29663],"type":"Point"}
}