{
  "type": "Feature",
  "properties": {
    "gn:admin1_code":"04",
    "gn:asciiname":"Comunidad Wila Kkollu",
    "gn:country_code":"BO",
    "gn:dem":3779,
    "gn:feature_class":"P",
    "gn:feature_code":"PPL",
    "gn:name":"Comunidad Wila Kkollu",
    "gn:population":0,
    "gn:timezone":"America/La_Paz",
    "iso:country":"BO",
    "wof:name":"Comunidad Wila Kkollu",
    "wof:placetype":"locality"
},
  "geometry": {"coordinates":[-67.84999999999999,-17.83333],"type":"Point"}
}