{
  "type": "Feature",
  "properties": {
    "gn:admin1_code":"05",
    "gn:asciiname":"Canaikollu",
    "gn:country_code":"BO",
    "gn:dem":3720,
    "gn:feature_class":"P",
    "gn:feature_code":"PPL",
    "gn:name":"Ca\u00f1aikollu",
    "gn:population":0,
    "gn:timezone":"America/La_Paz",
    "iso:country":"BO",
    "wof:name":"Canaikollu",
    "wof:placetype":"locality"
},
  "geometry": {"coordinates":[-67.47745999999999,-18.80922],"type":"Point"}
}