{
  "type": "Feature",
  "properties": {
    "gn:admin1_code":"04",
    "gn:asciiname":"Estancia Jankho Jakke",
    "gn:country_code":"BO",
    "gn:dem":3931,
    "gn:feature_class":"P",
    "gn:feature_code":"PPL",
    "gn:name":"Estancia Jankho Jakke",
    "gn:population":0,
    "gn:timezone":"America/La_Paz",
    "iso:country":"BO",
    "wof:name":"Estancia Jankho Jakke",
    "wof:placetype":"locality"
},
  "geometry": {"coordinates":[-69.05,-17.21667],"type":"Point"}
}