{
  "type": "Feature",
  "properties": {
    "gn:admin1_code":"6.0",
    "gn:asciiname":"Monte Bello Viejo",
    "gn:country_code":"BO",
    "gn:dem":140,
    "gn:feature_class":"P",
    "gn:feature_code":"PPL",
    "gn:name":"Monte Bello Viejo",
    "gn:population":0,
    "gn:timezone":"America/La_Paz",
    "iso:country":"BO",
    "wof:name":"Monte Bello Viejo",
    "wof:placetype":"locality"
},
  "geometry": {"coordinates":[-66.76666999999999,-10.96667],"type":"Point"}
}