{
  "type": "Feature",
  "properties": {
    "gn:admin1_code":"04",
    "gn:asciiname":"Estancia Khala Uta",
    "gn:country_code":"BO",
    "gn:dem":4044,
    "gn:feature_class":"P",
    "gn:feature_code":"PPL",
    "gn:name":"Estancia Khala Uta",
    "gn:population":0,
    "gn:timezone":"America/La_Paz",
    "iso:country":"BO",
    "wof:name":"Estancia Khala Uta",
    "wof:placetype":"locality"
},
  "geometry": {"coordinates":[-69.34999999999999,-17.56667],"type":"Point"}
}