{
  "type": "Feature",
  "properties": {
    "gn:admin1_code":"06",
    "gn:asciiname":"Chaoa Barra",
    "gn:country_code":"BO",
    "gn:dem":217,
    "gn:feature_class":"P",
    "gn:feature_code":"PPL",
    "gn:name":"Chaoa Barra",
    "gn:population":0,
    "gn:timezone":"America/La_Paz",
    "iso:country":"BO",
    "name:und_x_variant":[
        "Chaca Barraca",
        "Chaca Barra",
        "Chaoa Barra"
    ],
    "wof:name":"Chaoa Barra",
    "wof:placetype":"locality"
},
  "geometry": {"coordinates":[-68.60630999999999,-11.87755],"type":"Point"}
}