{
  "type": "Feature",
  "properties": {
    "gn:admin1_code":"02",
    "gn:asciiname":"Charapaya",
    "gn:cc2":"BO",
    "gn:country_code":"BO",
    "gn:dem":3414,
    "gn:feature_class":"P",
    "gn:feature_code":"PPL",
    "gn:name":"Charapaya",
    "gn:population":0,
    "gn:timezone":"America/La_Paz",
    "iso:country":"BO",
    "name:und_x_variant":[
        "Charuplaya",
        "Charapaya"
    ],
    "wof:name":"Charapaya",
    "wof:placetype":"locality"
},
  "geometry": {"coordinates":[-66.75,-17.36667000000001],"type":"Point"}
}