{
  "type": "Feature",
  "properties": {
    "gn:admin1_code":"2.0",
    "gn:asciiname":"Palca",
    "gn:country_code":"BO",
    "gn:dem":247,
    "gn:feature_class":"P",
    "gn:feature_code":"PPL",
    "gn:name":"Palca",
    "gn:population":0,
    "gn:timezone":"America/La_Paz",
    "iso:country":"BO",
    "wof:name":"Palca",
    "wof:placetype":"locality"
},
  "geometry": {"coordinates":[-65.78333000000001,-16.41667],"type":"Point"}
}