{
  "type": "Feature",
  "properties": {
    "gn:admin1_code":"08",
    "gn:asciiname":"Cumbre",
    "gn:country_code":"BO",
    "gn:dem":528,
    "gn:feature_class":"P",
    "gn:feature_code":"PPL",
    "gn:name":"Cumbre",
    "gn:population":0,
    "gn:timezone":"America/La_Paz",
    "iso:country":"BO",
    "wof:name":"Cumbre",
    "wof:placetype":"locality"
},
  "geometry": {"coordinates":[-63.55,-18.93333],"type":"Point"}
}