{
  "type": "Feature",
  "properties": {
    "gn:admin1_code":"06",
    "gn:asciiname":"Esmirna",
    "gn:country_code":"BO",
    "gn:dem":179,
    "gn:feature_class":"P",
    "gn:feature_code":"PPL",
    "gn:name":"Esmirna",
    "gn:population":0,
    "gn:timezone":"America/La_Paz",
    "iso:country":"BO",
    "name:spa_x_preferred":[
        "Esmirna"
    ],
    "wof:name":"Esmirna",
    "wof:placetype":"locality"
},
  "geometry": {"coordinates":[-67.90501999999999,-11.40812],"type":"Point"}
}