{
  "type": "Feature",
  "properties": {
    "gn:admin1_code":"02",
    "gn:asciiname":"Sauce Pila Pata",
    "gn:country_code":"BO",
    "gn:dem":2317,
    "gn:feature_class":"P",
    "gn:feature_code":"PPL",
    "gn:name":"Sauce Pila Pata",
    "gn:population":0,
    "gn:timezone":"America/La_Paz",
    "iso:country":"BO",
    "wof:name":"Sauce Pila Pata",
    "wof:placetype":"locality"
},
  "geometry": {"coordinates":[-65.06274999999999,-17.82307],"type":"Point"}
}