{
  "type": "Feature",
  "properties": {
    "gn:admin1_code":"01",
    "gn:asciiname":"Estancia Kaipa",
    "gn:country_code":"BO",
    "gn:dem":3217,
    "gn:feature_class":"P",
    "gn:feature_code":"PPL",
    "gn:name":"Estancia Kaipa",
    "gn:population":0,
    "gn:timezone":"America/La_Paz",
    "iso:country":"BO",
    "wof:name":"Estancia Kaipa",
    "wof:placetype":"locality"
},
  "geometry": {"coordinates":[-65.30852,-20.81435],"type":"Point"}
}