{
  "type": "Feature",
  "properties": {
    "gn:admin1_code":"5.0",
    "gn:asciiname":"Quillacas",
    "gn:country_code":"BO",
    "gn:dem":3770,
    "gn:feature_class":"P",
    "gn:feature_code":"PPL",
    "gn:name":"Quillacas",
    "gn:population":0,
    "gn:timezone":"America/La_Paz",
    "iso:country":"BO",
    "name:aym_x_preferred":[
        "Killaka"
    ],
    "name:spa_x_preferred":[
        "Quillacas"
    ],
    "wof:name":"Quillacas",
    "wof:placetype":"locality"
},
  "geometry": {"coordinates":[-66.9419,-19.23278],"type":"Point"}
}