{
  "type": "Feature",
  "properties": {
    "gn:admin1_code":"7.0",
    "gn:asciiname":"Estancia Vila Ake",
    "gn:country_code":"BO",
    "gn:dem":3649,
    "gn:feature_class":"P",
    "gn:feature_code":"PPL",
    "gn:name":"Estancia Vila Ake",
    "gn:population":0,
    "gn:timezone":"America/La_Paz",
    "iso:country":"BO",
    "wof:name":"Estancia Vila Ake",
    "wof:placetype":"locality"
},
  "geometry": {"coordinates":[-66.19664,-20.36527],"type":"Point"}
}