{
  "type": "Feature",
  "properties": {
    "gn:admin1_code":"07",
    "gn:asciiname":"Estancia Khocha Pampa",
    "gn:country_code":"BO",
    "gn:dem":3658,
    "gn:feature_class":"P",
    "gn:feature_code":"PPL",
    "gn:name":"Estancia Khocha Pampa",
    "gn:population":0,
    "gn:timezone":"America/La_Paz",
    "iso:country":"BO",
    "wof:name":"Estancia Khocha Pampa",
    "wof:placetype":"locality"
},
  "geometry": {"coordinates":[-65.67586,-18.88029],"type":"Point"}
}