{
  "type": "Feature",
  "properties": {
    "iso:country":"BO",
    "qs:gn_pop":0,
    "qs:name":"Pucarani",
    "qs:name_adm0":"Bolivia",
    "qs:name_adm1":"La Paz",
    "qs:photos":1,
    "qs:photos_1k":1,
    "qs:photos_9k":1,
    "qs:photos_9r":1,
    "qs:photos_all":8,
    "qs:photos_sr":1,
    "qs:placetype":"LocalAdmin",
    "qs:pop_sr":"0",
    "qs:woe_adm0":23424762,
    "wof:name":"Pucarani",
    "wof:placetype":"localadmin"
},
  "geometry": {"coordinates":[-68.39572800000001,-16.360497],"type":"Point"}
}