{
  "type": "Feature",
  "properties": {
    "gn:admin1_code":"7.0",
    "gn:asciiname":"La Palca",
    "gn:country_code":"BO",
    "gn:dem":3617,
    "gn:feature_class":"P",
    "gn:feature_code":"PPL",
    "gn:name":"La Palca",
    "gn:population":0,
    "gn:timezone":"America/La_Paz",
    "iso:country":"BO",
    "name:und_x_variant":[
        "Palca",
        "La Palca"
    ],
    "wof:name":"La Palca",
    "wof:placetype":"locality"
},
  "geometry": {"coordinates":[-66.00964,-18.75858],"type":"Point"}
}