{
  "type": "Feature",
  "properties": {
    "gn:admin1_code":"05",
    "gn:asciiname":"Estancia Buena Vista Jalakheri",
    "gn:country_code":"BO",
    "gn:dem":3739,
    "gn:feature_class":"P",
    "gn:feature_code":"PPL",
    "gn:name":"Estancia Buena Vista Jalakheri",
    "gn:population":0,
    "gn:timezone":"America/La_Paz",
    "iso:country":"BO",
    "wof:name":"Estancia Buena Vista Jalakheri",
    "wof:placetype":"locality"
},
  "geometry": {"coordinates":[-67.52332,-18.6851],"type":"Point"}
}