{
  "type": "Feature",
  "properties": {
    "gn:admin1_code":"2.0",
    "gn:asciiname":"Miscamayu",
    "gn:country_code":"BO",
    "gn:dem":3595,
    "gn:feature_class":"P",
    "gn:feature_code":"PPL",
    "gn:name":"Miscamayu",
    "gn:population":0,
    "gn:timezone":"America/La_Paz",
    "iso:country":"BO",
    "name:und_x_variant":[
        "Miscamayo",
        "Miscamayu"
    ],
    "wof:name":"Miscamayu",
    "wof:placetype":"locality"
},
  "geometry": {"coordinates":[-65.51674,-17.47073],"type":"Point"}
}