{
  "type": "Feature",
  "properties": {
    "gn:admin1_code":"05",
    "gn:asciiname":"Estancia Jayokara",
    "gn:country_code":"BO",
    "gn:dem":3682,
    "gn:feature_class":"P",
    "gn:feature_code":"PPL",
    "gn:name":"Estancia Jayokara",
    "gn:population":0,
    "gn:timezone":"America/La_Paz",
    "iso:country":"BO",
    "wof:name":"Estancia Jayokara",
    "wof:placetype":"locality"
},
  "geometry": {"coordinates":[-67.85021,-19.0186],"type":"Point"}
}