{
  "type": "Feature",
  "properties": {
    "gn:admin1_code":"7.0",
    "gn:asciiname":"Sintuni",
    "gn:country_code":"BO",
    "gn:dem":4077,
    "gn:feature_class":"P",
    "gn:feature_code":"PPL",
    "gn:name":"Sintuni",
    "gn:population":0,
    "gn:timezone":"America/La_Paz",
    "iso:country":"BO",
    "wof:name":"Sintuni",
    "wof:placetype":"locality"
},
  "geometry": {"coordinates":[-66.03333000000001,-20.98333],"type":"Point"}
}