{
  "type": "Feature",
  "properties": {
    "gn:admin1_code":"07",
    "gn:asciiname":"Caliberno",
    "gn:country_code":"BO",
    "gn:dem":3962,
    "gn:feature_class":"P",
    "gn:feature_code":"PPL",
    "gn:name":"Caliberno",
    "gn:population":0,
    "gn:timezone":"America/La_Paz",
    "iso:country":"BO",
    "wof:name":"Caliberno",
    "wof:placetype":"locality"
},
  "geometry": {"coordinates":[-67.16667,-21.66667],"type":"Point"}
}