{
  "type": "Feature",
  "properties": {
    "gn:admin1_code":"05",
    "gn:asciiname":"Conchiri",
    "gn:cc2":"BO",
    "gn:country_code":"BO",
    "gn:dem":4060,
    "gn:feature_class":"P",
    "gn:feature_code":"PPL",
    "gn:name":"Conchiri",
    "gn:population":0,
    "gn:timezone":"America/La_Paz",
    "iso:country":"BO",
    "name:und_x_variant":[
        "Estancia Conchiri",
        "Conchiri"
    ],
    "wof:name":"Conchiri",
    "wof:placetype":"locality"
},
  "geometry": {"coordinates":[-66.96666999999999,-17.73333],"type":"Point"}
}