{
  "type": "Feature",
  "properties": {
    "gn:admin1_code":"4.0",
    "gn:asciiname":"Sehuecani",
    "gn:cc2":"BO",
    "gn:country_code":"BO",
    "gn:dem":3780,
    "gn:feature_class":"P",
    "gn:feature_code":"PPL",
    "gn:name":"Sehuecani",
    "gn:population":0,
    "gn:timezone":"America/La_Paz",
    "iso:country":"BO",
    "name:und_x_variant":[
        "Huacachi",
        "Sehuecani"
    ],
    "wof:name":"Sehuecani",
    "wof:placetype":"locality"
},
  "geometry": {"coordinates":[-67.96666999999999,-17.35],"type":"Point"}
}