{
  "type": "Feature",
  "properties": {
    "gn:admin1_code":"7.0",
    "gn:asciiname":"Incambo",
    "gn:country_code":"BO",
    "gn:dem":2807,
    "gn:feature_class":"P",
    "gn:feature_code":"PPL",
    "gn:name":"Incambo",
    "gn:population":0,
    "gn:timezone":"America/La_Paz",
    "iso:country":"BO",
    "wof:name":"Incambo",
    "wof:placetype":"locality"
},
  "geometry": {"coordinates":[-64.91667,-19.43333],"type":"Point"}
}