{
  "type": "Feature",
  "properties": {
    "gn:admin1_code":"8.0",
    "gn:asciiname":"Limon",
    "gn:country_code":"BO",
    "gn:dem":764,
    "gn:feature_class":"P",
    "gn:feature_code":"PPL",
    "gn:name":"Lim\u00f3n",
    "gn:population":0,
    "gn:timezone":"America/La_Paz",
    "iso:country":"BO",
    "name:bre_x_preferred":[
        "Limon"
    ],
    "name:bul_x_preferred":[
        "\u041b\u0438\u043c\u043e\u043d"
    ],
    "name:ceb_x_preferred":[
        "Limon"
    ],
    "name:fra_x_preferred":[
        "Limon"
    ],
    "name:heb_x_preferred":[
        "\u05dc\u05d9\u05de\u05d5\u05df"
    ],
    "name:ita_x_preferred":[
        "Limon"
    ],
    "name:lmo_x_preferred":[
        "Limon"
    ],
    "name:nld_x_preferred":[
        "Limon"
    ],
    "name:oci_x_preferred":[
        "Limon"
    ],
    "name:pms_x_preferred":[
        "Limon"
    ],
    "name:pol_x_preferred":[
        "Limon"
    ],
    "name:srp_x_preferred":[
        "\u041b\u0438\u043c\u043e\u043d"
    ],
    "name:swe_x_preferred":[
        "Limon"
    ],
    "name:tur_x_preferred":[
        "Limon"
    ],
    "wof:name":"Limon",
    "wof:placetype":"locality"
},
  "geometry": {"coordinates":[-63.47929,-19.06478],"type":"Point"}
}