{
  "type": "Feature",
  "properties": {
    "gn:admin1_code":"8.0",
    "gn:asciiname":"Limon",
    "gn:country_code":"BO",
    "gn:dem":764,
    "gn:feature_class":"P",
    "gn:feature_code":"PPL",
    "gn:name":"Lim\u00f3n",
    "gn:population":0,
    "gn:timezone":"America/La_Paz",
    "iso:country":"BO",
    "wof:name":"Limon",
    "wof:placetype":"locality"
},
  "geometry": {"coordinates":[-63.47929,-19.06478],"type":"Point"}
}