{
  "type": "Feature",
  "properties": {
    "gn:admin1_code":"7.0",
    "gn:asciiname":"Uli",
    "gn:country_code":"BO",
    "gn:dem":3670,
    "gn:feature_class":"P",
    "gn:feature_code":"PPL",
    "gn:name":"Uli",
    "gn:population":0,
    "gn:timezone":"America/La_Paz",
    "iso:country":"BO",
    "name:ceb_x_preferred":[
        "Uli"
    ],
    "name:ibo_x_preferred":[
        "Uli"
    ],
    "name:nld_x_preferred":[
        "Uli"
    ],
    "name:spa_x_preferred":[
        "Uli"
    ],
    "name:swe_x_preferred":[
        "Uli"
    ],
    "name:und_x_variant":[
        "Estancia Uli"
    ],
    "wof:name":"Uli",
    "wof:placetype":"locality"
},
  "geometry": {"coordinates":[-65.79940999999999,-19.27019],"type":"Point"}
}