{
  "type": "Feature",
  "properties": {
    "gn:admin1_code":"7.0",
    "gn:asciiname":"Pairumani",
    "gn:country_code":"BO",
    "gn:dem":3500,
    "gn:feature_class":"P",
    "gn:feature_code":"PPL",
    "gn:name":"Pairumani",
    "gn:population":0,
    "gn:timezone":"America/La_Paz",
    "iso:country":"BO",
    "wof:name":"Pairumani",
    "wof:placetype":"locality"
},
  "geometry": {"coordinates":[-65.47924,-19.42182],"type":"Point"}
}