{
  "type": "Feature",
  "properties": {
    "gn:admin1_code":"4.0",
    "gn:asciiname":"Nazacara",
    "gn:country_code":"BO",
    "gn:dem":3829,
    "gn:feature_class":"P",
    "gn:feature_code":"PPL",
    "gn:name":"Nazacara",
    "gn:population":0,
    "gn:timezone":"America/La_Paz",
    "iso:country":"BO",
    "wof:name":"Nazacara",
    "wof:placetype":"locality"
},
  "geometry": {"coordinates":[-68.76845,-16.93784],"type":"Point"}
}