{
  "type": "Feature",
  "properties": {
    "gn:admin1_code":"4.0",
    "gn:asciiname":"Laram Kota",
    "gn:cc2":"BO",
    "gn:country_code":"BO",
    "gn:dem":3873,
    "gn:feature_class":"P",
    "gn:feature_code":"PPL",
    "gn:name":"Laram Kota",
    "gn:population":0,
    "gn:timezone":"America/La_Paz",
    "iso:country":"BO",
    "name:und_x_variant":[
        "Estancia Laram Kkota",
        "Laram Kota"
    ],
    "wof:name":"Laram Kota",
    "wof:placetype":"locality"
},
  "geometry": {"coordinates":[-68.93333,-17.15],"type":"Point"}
}