{
  "type": "Feature",
  "properties": {
    "gn:admin1_code":"02",
    "gn:asciiname":"Estancia Chiutara",
    "gn:country_code":"BO",
    "gn:dem":2314,
    "gn:feature_class":"P",
    "gn:feature_code":"PPL",
    "gn:name":"Estancia Chiutara",
    "gn:population":0,
    "gn:timezone":"America/La_Paz",
    "iso:country":"BO",
    "wof:name":"Estancia Chiutara",
    "wof:placetype":"locality"
},
  "geometry": {"coordinates":[-65.08516999999999,-18.25408],"type":"Point"}
}