{
  "type": "Feature",
  "properties": {
    "gn:admin1_code":"7.0",
    "gn:asciiname":"Porkherani",
    "gn:country_code":"BO",
    "gn:dem":3751,
    "gn:feature_class":"P",
    "gn:feature_code":"PPL",
    "gn:name":"Porkherani",
    "gn:population":0,
    "gn:timezone":"America/La_Paz",
    "iso:country":"BO",
    "wof:name":"Porkherani",
    "wof:placetype":"locality"
},
  "geometry": {"coordinates":[-66.92258000000001,-21.16916],"type":"Point"}
}