{
  "type": "Feature",
  "properties": {
    "gn:admin1_code":"7.0",
    "gn:asciiname":"San Bartolome",
    "gn:cc2":"BO",
    "gn:country_code":"BO",
    "gn:dem":3717,
    "gn:feature_class":"P",
    "gn:feature_code":"PPL",
    "gn:name":"San Bartolom\u00e9",
    "gn:population":0,
    "gn:timezone":"America/La_Paz",
    "iso:country":"BO",
    "name:und_x_variant":[
        "San Bartolo",
        "San Bartolom\u00e9"
    ],
    "wof:name":"San Bartolome",
    "wof:placetype":"locality"
},
  "geometry": {"coordinates":[-65.83333,-19.58333],"type":"Point"}
}