{
  "type": "Feature",
  "properties": {
    "gn:admin1_code":"06",
    "gn:asciiname":"El Pinal",
    "gn:country_code":"BO",
    "gn:dem":262,
    "gn:feature_class":"P",
    "gn:feature_code":"PPL",
    "gn:name":"El Pinal",
    "gn:population":0,
    "gn:timezone":"America/La_Paz",
    "iso:country":"BO",
    "name:spa_x_preferred":[
        "El Pinal"
    ],
    "wof:name":"El Pinal",
    "wof:placetype":"locality"
},
  "geometry": {"coordinates":[-68.45891,-11.41318],"type":"Point"}
}