{
  "type": "Feature",
  "properties": {
    "gn:admin1_code":"03",
    "gn:asciiname":"El Toco",
    "gn:country_code":"BO",
    "gn:dem":171,
    "gn:feature_class":"P",
    "gn:feature_code":"PPL",
    "gn:name":"El Toco",
    "gn:population":0,
    "gn:timezone":"America/La_Paz",
    "iso:country":"BO",
    "wof:name":"El Toco",
    "wof:placetype":"locality"
},
  "geometry": {"coordinates":[-64.28333000000001,-15.55],"type":"Point"}
}