{
  "type": "Feature",
  "properties": {
    "gn:admin1_code":"04",
    "gn:asciiname":"Coriri",
    "gn:country_code":"BO",
    "gn:dem":3110,
    "gn:feature_class":"P",
    "gn:feature_code":"PPL",
    "gn:name":"Coriri",
    "gn:population":0,
    "gn:timezone":"America/La_Paz",
    "iso:country":"BO",
    "wof:name":"Coriri",
    "wof:placetype":"locality"
},
  "geometry": {"coordinates":[-66.86667,-17.38332999999999],"type":"Point"}
}