{
  "type": "Feature",
  "properties": {
    "gn:admin1_code":"7.0",
    "gn:asciiname":"Negro Tambo",
    "gn:country_code":"BO",
    "gn:dem":3532,
    "gn:feature_class":"P",
    "gn:feature_code":"PPL",
    "gn:name":"Negro Tambo",
    "gn:population":0,
    "gn:timezone":"America/La_Paz",
    "iso:country":"BO",
    "wof:name":"Negro Tambo",
    "wof:placetype":"locality"
},
  "geometry": {"coordinates":[-65.58202,-19.51003],"type":"Point"}
}