{
  "type": "Feature",
  "properties": {
    "gn:admin1_code":"9.0",
    "gn:asciiname":"Rancho Campanario",
    "gn:country_code":"BO",
    "gn:dem":1802,
    "gn:feature_class":"P",
    "gn:feature_code":"PPL",
    "gn:name":"Rancho Campanario",
    "gn:population":0,
    "gn:timezone":"America/La_Paz",
    "iso:country":"BO",
    "wof:name":"Rancho Campanario",
    "wof:placetype":"locality"
},
  "geometry": {"coordinates":[-64.6641,-22.0143],"type":"Point"}
}