{
  "type": "Feature",
  "properties": {
    "gn:admin1_code":"5.0",
    "gn:asciiname":"Humahuaracta",
    "gn:cc2":"BO",
    "gn:country_code":"BO",
    "gn:dem":3736,
    "gn:feature_class":"P",
    "gn:feature_code":"PPL",
    "gn:name":"Humahuaracta",
    "gn:population":0,
    "gn:timezone":"America/La_Paz",
    "iso:country":"BO",
    "name:und_x_variant":[
        "Humahuaracha",
        "Humahuaracta"
    ],
    "wof:name":"Humahuaracta",
    "wof:placetype":"locality"
},
  "geometry": {"coordinates":[-67.13333,-17.75],"type":"Point"}
}