{
  "type": "Feature",
  "properties": {
    "gn:admin1_code":"07",
    "gn:asciiname":"Arampampa",
    "gn:country_code":"BO",
    "gn:dem":3004,
    "gn:feature_class":"P",
    "gn:feature_code":"PPL",
    "gn:name":"Arampampa",
    "gn:population":0,
    "gn:timezone":"America/La_Paz",
    "iso:country":"BO",
    "name:ceb_x_preferred":[
        "Arampampa"
    ],
    "name:deu_x_preferred":[
        "Arampampa"
    ],
    "name:fra_x_preferred":[
        "Arampampa"
    ],
    "name:nld_x_preferred":[
        "Arampampa"
    ],
    "name:que_x_preferred":[
        "Arampampa"
    ],
    "name:sco_x_preferred":[
        "Arampampa"
    ],
    "name:war_x_preferred":[
        "Arampampa"
    ],
    "name:zho_x_preferred":[
        "\u963f\u862d\u6f58\u5e15"
    ],
    "wof:name":"Arampampa",
    "wof:placetype":"locality"
},
  "geometry": {"coordinates":[-66.09411,-17.95861],"type":"Point"}
}