{
  "type": "Feature",
  "properties": {
    "gn:admin1_code":"9.0",
    "gn:asciiname":"La Palca",
    "gn:country_code":"BO",
    "gn:dem":2623,
    "gn:feature_class":"P",
    "gn:feature_code":"PPL",
    "gn:name":"La Palca",
    "gn:population":0,
    "gn:timezone":"America/La_Paz",
    "iso:country":"BO",
    "wof:name":"La Palca",
    "wof:placetype":"locality"
},
  "geometry": {"coordinates":[-65.28333000000001,-21.35],"type":"Point"}
}