{
  "type": "Feature",
  "properties": {
    "gn:admin1_code":"02",
    "gn:asciiname":"Bolivar",
    "gn:cc2":"BO",
    "gn:country_code":"BO",
    "gn:dem":3740,
    "gn:feature_class":"P",
    "gn:feature_code":"PPL",
    "gn:name":"Bol\u00edvar",
    "gn:population":0,
    "gn:timezone":"America/La_Paz",
    "iso:country":"BO",
    "name:und_x_variant":[
        "Quirquiavi",
        "Bol\u00edvar"
    ],
    "wof:name":"Bolivar",
    "wof:placetype":"locality"
},
  "geometry": {"coordinates":[-66.53793,-17.96933],"type":"Point"}
}