{
  "type": "Feature",
  "properties": {
    "gn:admin1_code":"02",
    "gn:asciiname":"Bolivar",
    "gn:cc2":"BO",
    "gn:country_code":"BO",
    "gn:dem":3740,
    "gn:feature_class":"P",
    "gn:feature_code":"PPL",
    "gn:name":"Bol\u00edvar",
    "gn:population":0,
    "gn:timezone":"America/La_Paz",
    "iso:country":"BO",
    "name:deu_x_preferred":[
        "Bol\u00edvar"
    ],
    "name:fas_x_preferred":[
        "\u0628\u0648\u0644\u06cc\u0648\u0627\u0631"
    ],
    "name:fra_x_preferred":[
        "Bol\u00edvar"
    ],
    "name:heb_x_preferred":[
        "\u05d1\u05d5\u05dc\u05d9\u05d1\u05e8"
    ],
    "name:ita_x_preferred":[
        "Bol\u00edvar"
    ],
    "name:nor_x_preferred":[
        "Bol\u00edvar"
    ],
    "name:por_x_preferred":[
        "Bol\u00edvar"
    ],
    "name:que_x_preferred":[
        "Bol\u00edvar llaqta"
    ],
    "name:spa_x_preferred":[
        "Bol\u00edvar"
    ],
    "name:swe_x_preferred":[
        "Bol\u00edvar"
    ],
    "name:und_x_variant":[
        "Quirquiavi"
    ],
    "name:urd_x_preferred":[
        "\u0628\u0648\u0644\u06cc\u0648\u0631"
    ],
    "name:war_x_preferred":[
        "Bol\u00edvar"
    ],
    "name:zho_x_preferred":[
        "\u73bb\u5229\u74e6\u723e"
    ],
    "wof:name":"Bolivar",
    "wof:placetype":"locality"
},
  "geometry": {"coordinates":[-66.53793,-17.96933],"type":"Point"}
}