{
  "type": "Feature",
  "properties": {
    "gn:admin1_code":"1.0",
    "gn:asciiname":"Mariscal Braun",
    "gn:cc2":"BO",
    "gn:country_code":"BO",
    "gn:dem":1931,
    "gn:feature_class":"P",
    "gn:feature_code":"PPL",
    "gn:name":"Mariscal Braun",
    "gn:population":0,
    "gn:timezone":"America/La_Paz",
    "iso:country":"BO",
    "name:ita_x_preferred":[
        "Mariscal Braun"
    ],
    "name:nld_x_preferred":[
        "Club Mariscal Braun"
    ],
    "name:por_x_preferred":[
        "Mariscal Braun"
    ],
    "name:spa_x_preferred":[
        "Club Mariscal Braun"
    ],
    "name:und_x_variant":[
        "Rodeo",
        "Mariscal Brawn",
        "Mariscal Brown",
        "Mariscal Braun"
    ],
    "wof:name":"Mariscal Braun",
    "wof:placetype":"locality"
},
  "geometry": {"coordinates":[-64.56667,-20.06667],"type":"Point"}
}