{
  "type": "Feature",
  "properties": {
    "gn:admin1_code":"4.0",
    "gn:asciiname":"Hirpa Chico",
    "gn:country_code":"BO",
    "gn:dem":3949,
    "gn:feature_class":"P",
    "gn:feature_code":"PPL",
    "gn:name":"Hirpa Chico",
    "gn:population":0,
    "gn:timezone":"America/La_Paz",
    "iso:country":"BO",
    "wof:name":"Hirpa Chico",
    "wof:placetype":"locality"
},
  "geometry": {"coordinates":[-68.28333000000001,-16.78333],"type":"Point"}
}