{
  "type": "Feature",
  "properties": {
    "gn:admin1_code":"06",
    "gn:asciiname":"Curichon",
    "gn:country_code":"BO",
    "gn:dem":186,
    "gn:feature_class":"P",
    "gn:feature_code":"PPL",
    "gn:name":"Curich\u00f3n",
    "gn:population":0,
    "gn:timezone":"America/La_Paz",
    "iso:country":"BO",
    "name:spa_x_preferred":[
        "Curich\u00f3n"
    ],
    "wof:name":"Curichon",
    "wof:placetype":"locality"
},
  "geometry": {"coordinates":[-67.60095,-10.96474],"type":"Point"}
}