{
  "type": "Feature",
  "properties": {
    "gn:admin1_code":"01",
    "gn:asciiname":"Coochis",
    "gn:country_code":"BO",
    "gn:dem":2765,
    "gn:feature_class":"P",
    "gn:feature_code":"PPL",
    "gn:name":"Coochis",
    "gn:population":0,
    "gn:timezone":"America/La_Paz",
    "iso:country":"BO",
    "name:und_x_variant":[
        "Cochis",
        "Coochis"
    ],
    "wof:name":"Coochis",
    "wof:placetype":"locality"
},
  "geometry": {"coordinates":[-65.20532,-19.13135],"type":"Point"}
}