{
  "type": "Feature",
  "properties": {
    "gn:admin1_code":"06",
    "gn:asciiname":"Ancho \"B\"",
    "gn:country_code":"BO",
    "gn:dem":237,
    "gn:feature_class":"P",
    "gn:feature_code":"PPL",
    "gn:name":"Ancho \u201dB\u201d",
    "gn:population":0,
    "gn:timezone":"America/La_Paz",
    "iso:country":"BO",
    "name:spa_x_preferred":[
        "Ancho \u201dB\u201d"
    ],
    "wof:name":"Ancho \"B\"",
    "wof:placetype":"locality"
},
  "geometry": {"coordinates":[-68.83601999999999,-11.07248],"type":"Point"}
}