{
  "type": "Feature",
  "properties": {
    "gn:admin1_code":"9.0",
    "gn:asciiname":"Ipahuazu",
    "gn:country_code":"BO",
    "gn:dem":1419,
    "gn:feature_class":"P",
    "gn:feature_code":"PPL",
    "gn:name":"Ipahuazu",
    "gn:population":0,
    "gn:timezone":"America/La_Paz",
    "iso:country":"BO",
    "wof:name":"Ipahuazu",
    "wof:placetype":"locality"
},
  "geometry": {"coordinates":[-63.87331,-21.36702],"type":"Point"}
}