{
  "type": "Feature",
  "properties": {
    "gn:admin1_code":"07",
    "gn:asciiname":"Estancia Choquecala",
    "gn:country_code":"BO",
    "gn:dem":3446,
    "gn:feature_class":"P",
    "gn:feature_code":"PPL",
    "gn:name":"Estancia Choquecala",
    "gn:population":0,
    "gn:timezone":"America/La_Paz",
    "iso:country":"BO",
    "wof:name":"Estancia Choquecala",
    "wof:placetype":"locality"
},
  "geometry": {"coordinates":[-66.10735,-20.16491],"type":"Point"}
}