{
  "type": "Feature",
  "properties": {
    "gn:admin1_code":"7.0",
    "gn:asciiname":"Liri",
    "gn:country_code":"BO",
    "gn:dem":3139,
    "gn:feature_class":"P",
    "gn:feature_code":"PPL",
    "gn:name":"Liri",
    "gn:population":0,
    "gn:timezone":"America/La_Paz",
    "iso:country":"BO",
    "name:bul_x_preferred":[
        "\u041b\u0438\u0440\u0438"
    ],
    "name:cat_x_preferred":[
        "Liris"
    ],
    "name:epo_x_preferred":[
        "Liri"
    ],
    "name:eus_x_preferred":[
        "Liri"
    ],
    "name:fra_x_preferred":[
        "Liri"
    ],
    "name:glg_x_preferred":[
        "R\u00edo Liri"
    ],
    "name:heb_x_preferred":[
        "\u05dc\u05d9\u05e8\u05d9"
    ],
    "name:hun_x_preferred":[
        "Liri"
    ],
    "name:ita_x_preferred":[
        "Liri"
    ],
    "name:lat_x_preferred":[
        "Liris"
    ],
    "name:nno_x_preferred":[
        "Liri"
    ],
    "name:nor_x_preferred":[
        "Liri"
    ],
    "name:pol_x_preferred":[
        "Liri"
    ],
    "name:por_x_preferred":[
        "Liri"
    ],
    "name:rus_x_preferred":[
        "\u041b\u0438\u0440\u0438"
    ],
    "name:spa_x_preferred":[
        "R\u00edo Liri"
    ],
    "name:swe_x_preferred":[
        "Liris"
    ],
    "name:und_x_variant":[
        "Estancia Liriyuj"
    ],
    "name:zho_x_preferred":[
        "\u5229\u91cc\u6cb3"
    ],
    "wof:name":"Liri",
    "wof:placetype":"locality"
},
  "geometry": {"coordinates":[-65.39618,-20.47345],"type":"Point"}
}