{
  "type": "Feature",
  "properties": {
    "gn:admin1_code":"7.0",
    "gn:asciiname":"Liri",
    "gn:country_code":"BO",
    "gn:dem":3139,
    "gn:feature_class":"P",
    "gn:feature_code":"PPL",
    "gn:name":"Liri",
    "gn:population":0,
    "gn:timezone":"America/La_Paz",
    "iso:country":"BO",
    "name:und_x_variant":[
        "Estancia Liriyuj",
        "Liri"
    ],
    "wof:name":"Liri",
    "wof:placetype":"locality"
},
  "geometry": {"coordinates":[-65.39618,-20.47345],"type":"Point"}
}