{
  "type": "Feature",
  "properties": {
    "gn:admin1_code":"5.0",
    "gn:asciiname":"Estancia Sejruyo",
    "gn:country_code":"BO",
    "gn:dem":4076,
    "gn:feature_class":"P",
    "gn:feature_code":"PPL",
    "gn:name":"Estancia Sejruyo",
    "gn:population":0,
    "gn:timezone":"America/La_Paz",
    "iso:country":"BO",
    "wof:name":"Estancia Sejruyo",
    "wof:placetype":"locality"
},
  "geometry": {"coordinates":[-68.27771,-18.09009],"type":"Point"}
}