{
  "type": "Feature",
  "properties": {
    "gn:admin1_code":"04",
    "gn:asciiname":"Zona Chilchata",
    "gn:country_code":"BO",
    "gn:dem":4458,
    "gn:feature_class":"P",
    "gn:feature_code":"PPL",
    "gn:name":"Zona Chilchata",
    "gn:population":0,
    "gn:timezone":"America/La_Paz",
    "iso:country":"BO",
    "name:spa_x_preferred":[
        "Zona Chilchata"
    ],
    "name:spa_x_variant":[
        "Estancia Chillkhata",
        "Estancia Chillchata"
    ],
    "wof:name":"Zona Chilchata",
    "wof:placetype":"locality"
},
  "geometry": {"coordinates":[-69.11667,-15.13333],"type":"Point"}
}