{
  "type": "Feature",
  "properties": {
    "gn:admin1_code":"06",
    "gn:asciiname":"Dos de Mayo",
    "gn:country_code":"BO",
    "gn:dem":185,
    "gn:feature_class":"P",
    "gn:feature_code":"PPL",
    "gn:name":"Dos de Mayo",
    "gn:population":0,
    "gn:timezone":"America/La_Paz",
    "iso:country":"BO",
    "name:spa_x_preferred":[
        "Dos de Mayo"
    ],
    "wof:name":"Dos de Mayo",
    "wof:placetype":"locality"
},
  "geometry": {"coordinates":[-67.32154,-10.53458],"type":"Point"}
}