{
  "type": "Feature",
  "properties": {
    "gn:admin1_code":"4.0",
    "gn:asciiname":"Pucara",
    "gn:country_code":"BO",
    "gn:dem":3797,
    "gn:feature_class":"P",
    "gn:feature_code":"PPL",
    "gn:name":"Pucar\u00e1",
    "gn:population":0,
    "gn:timezone":"America/La_Paz",
    "iso:country":"BO",
    "wof:name":"Pucara",
    "wof:placetype":"locality"
},
  "geometry": {"coordinates":[-67.59999999999999,-16.95],"type":"Point"}
}