{
  "type": "Feature",
  "properties": {
    "gn:admin1_code":"4.0",
    "gn:asciiname":"Kiripujo",
    "gn:cc2":"BO",
    "gn:country_code":"BO",
    "gn:dem":3856,
    "gn:feature_class":"P",
    "gn:feature_code":"PPL",
    "gn:name":"Kiripujo",
    "gn:population":0,
    "gn:timezone":"America/La_Paz",
    "iso:country":"BO",
    "name:und_x_variant":[
        "Kiripuyo",
        "Kiripujo"
    ],
    "wof:name":"Kiripujo",
    "wof:placetype":"locality"
},
  "geometry": {"coordinates":[-68.65000000000001,-16.45],"type":"Point"}
}