{
  "type": "Feature",
  "properties": {
    "gn:admin1_code":"8.0",
    "gn:asciiname":"Izozog Bajo",
    "gn:country_code":"BO",
    "gn:dem":354,
    "gn:feature_class":"P",
    "gn:feature_code":"PPL",
    "gn:name":"Izozog Bajo",
    "gn:population":0,
    "gn:timezone":"America/La_Paz",
    "iso:country":"BO",
    "wof:name":"Izozog Bajo",
    "wof:placetype":"locality"
},
  "geometry": {"coordinates":[-62.43333000000001,-19.03333],"type":"Point"}
}