{
  "type": "Feature",
  "properties": {
    "gn:admin1_code":"8.0",
    "gn:asciiname":"Saipuru",
    "gn:country_code":"BO",
    "gn:dem":820,
    "gn:feature_class":"P",
    "gn:feature_code":"PPL",
    "gn:name":"Saipuru",
    "gn:population":0,
    "gn:timezone":"America/La_Paz",
    "iso:country":"BO",
    "wof:name":"Saipuru",
    "wof:placetype":"locality"
},
  "geometry": {"coordinates":[-63.23198000000001,-19.523],"type":"Point"}
}