{
  "type": "Feature",
  "properties": {
    "gn:admin1_code":"06",
    "gn:asciiname":"Maravilla",
    "gn:country_code":"BO",
    "gn:dem":278,
    "gn:feature_class":"P",
    "gn:feature_code":"PPL",
    "gn:name":"Maravilla",
    "gn:population":0,
    "gn:timezone":"America/La_Paz",
    "iso:country":"BO",
    "name:spa_x_preferred":[
        "Maravilla"
    ],
    "wof:name":"Maravilla",
    "wof:placetype":"locality"
},
  "geometry": {"coordinates":[-68.91382,-11.50055],"type":"Point"}
}