{
  "type": "Feature",
  "properties": {
    "gn:admin1_code":"01",
    "gn:asciiname":"Escana",
    "gn:country_code":"BO",
    "gn:dem":3076,
    "gn:feature_class":"P",
    "gn:feature_code":"PPL",
    "gn:name":"Escana",
    "gn:population":0,
    "gn:timezone":"America/La_Paz",
    "iso:country":"BO",
    "wof:name":"Escana",
    "wof:placetype":"locality"
},
  "geometry": {"coordinates":[-65.10254,-19.27294],"type":"Point"}
}