{
  "type": "Feature",
  "properties": {
    "gn:admin1_code":"4.0",
    "gn:asciiname":"San Fermin",
    "gn:country_code":"BO",
    "gn:dem":1198,
    "gn:feature_class":"P",
    "gn:feature_code":"PPL",
    "gn:name":"San Ferm\u00edn",
    "gn:population":0,
    "gn:timezone":"America/Lima",
    "iso:country":"BO",
    "name:spa_x_preferred":[
        "San Ferm\u00edn"
    ],
    "wof:name":"San Fermin",
    "wof:placetype":"locality"
},
  "geometry": {"coordinates":[-68.96511,-13.96945],"type":"Point"}
}