{
  "type": "Feature",
  "properties": {
    "gn:admin1_code":"4.0",
    "gn:asciiname":"Vilaque",
    "gn:country_code":"BO",
    "gn:dem":3774,
    "gn:feature_class":"P",
    "gn:feature_code":"PPL",
    "gn:name":"Vilaque",
    "gn:population":0,
    "gn:timezone":"America/La_Paz",
    "iso:country":"BO",
    "wof:name":"Vilaque",
    "wof:placetype":"locality"
},
  "geometry": {"coordinates":[-67.51666999999999,-17.45],"type":"Point"}
}