{
  "type": "Feature",
  "properties": {
    "gn:admin1_code":"3.0",
    "gn:asciiname":"Loreto",
    "gn:country_code":"BO",
    "gn:dem":161,
    "gn:feature_class":"P",
    "gn:feature_code":"PPL",
    "gn:name":"Loreto",
    "gn:population":0,
    "gn:timezone":"America/La_Paz",
    "iso:country":"BO",
    "name:ben_x_preferred":[
        "\u09b2\u09cb\u09b0\u09c7\u09a4\u09cb"
    ],
    "name:ceb_x_preferred":[
        "Loreto"
    ],
    "name:deu_x_preferred":[
        "Loreto"
    ],
    "name:ell_x_preferred":[
        "\u039b\u03bf\u03c1\u03ad\u03c4\u03bf"
    ],
    "name:fas_x_preferred":[
        "\u0644\u0648\u0631\u062a\u0648"
    ],
    "name:heb_x_preferred":[
        "\u05dc\u05d5\u05e8\u05d9"
    ],
    "name:hin_x_preferred":[
        "\u0932\u094b\u0930\u0947\u091f\u094b"
    ],
    "name:que_x_preferred":[
        "Luritu"
    ],
    "name:swe_x_preferred":[
        "Loreto"
    ],
    "name:ukr_x_preferred":[
        "\u041b\u043e\u0440\u0435\u0442\u043e"
    ],
    "name:urd_x_preferred":[
        "\u0644\u0648\u0631\u06cc\u0679\u0648"
    ],
    "name:war_x_preferred":[
        "Loreto"
    ],
    "name:zho_x_preferred":[
        "\u6d1b\u96f7\u6258"
    ],
    "wof:name":"Loreto",
    "wof:placetype":"locality"
},
  "geometry": {"coordinates":[-64.75887,-15.19275],"type":"Point"}
}