{
  "type": "Feature",
  "properties": {
    "gn:admin1_code":"6.0",
    "gn:asciiname":"Gironda",
    "gn:country_code":"BO",
    "gn:dem":197,
    "gn:feature_class":"P",
    "gn:feature_code":"PPL",
    "gn:name":"Gironda",
    "gn:population":0,
    "gn:timezone":"America/La_Paz",
    "iso:country":"BO",
    "name:spa_x_preferred":[
        "Gironda"
    ],
    "wof:name":"Gironda",
    "wof:placetype":"locality"
},
  "geometry": {"coordinates":[-67.82330999999999,-11.14324],"type":"Point"}
}