{
  "type": "Feature",
  "properties": {
    "gn:admin1_code":"4.0",
    "gn:asciiname":"Santa Emilia",
    "gn:country_code":"BO",
    "gn:dem":835,
    "gn:feature_class":"P",
    "gn:feature_code":"PPL",
    "gn:name":"Santa Emilia",
    "gn:population":0,
    "gn:timezone":"America/La_Paz",
    "iso:country":"BO",
    "wof:name":"Santa Emilia",
    "wof:placetype":"locality"
},
  "geometry": {"coordinates":[-67.83333,-15.45],"type":"Point"}
}