{
  "type": "Feature",
  "properties": {
    "gn:admin1_code":"1.0",
    "gn:asciiname":"Totacoa",
    "gn:country_code":"BO",
    "gn:dem":2520,
    "gn:feature_class":"P",
    "gn:feature_code":"PPL",
    "gn:name":"Totacoa",
    "gn:population":0,
    "gn:timezone":"America/La_Paz",
    "iso:country":"BO",
    "wof:name":"Totacoa",
    "wof:placetype":"locality"
},
  "geometry": {"coordinates":[-65.26666999999999,-19.15],"type":"Point"}
}