{
  "type": "Feature",
  "properties": {
    "gn:admin1_code":"08",
    "gn:asciiname":"Curiche",
    "gn:cc2":"BO",
    "gn:country_code":"BO",
    "gn:dem":311,
    "gn:feature_class":"P",
    "gn:feature_code":"PPL",
    "gn:name":"Curiche",
    "gn:population":0,
    "gn:timezone":"America/La_Paz",
    "iso:country":"BO",
    "name:und_x_variant":[
        "Curichi",
        "Curiches",
        "Curiche"
    ],
    "wof:name":"Curiche",
    "wof:placetype":"locality"
},
  "geometry": {"coordinates":[-60.98333,-19.43333],"type":"Point"}
}