{
  "type": "Feature",
  "properties": {
    "gn:admin1_code":"8.0",
    "gn:asciiname":"Versalles",
    "gn:country_code":"BO",
    "gn:dem":278,
    "gn:feature_class":"P",
    "gn:feature_code":"PPL",
    "gn:name":"Versalles",
    "gn:population":0,
    "gn:timezone":"America/La_Paz",
    "iso:country":"BO",
    "wof:name":"Versalles",
    "wof:placetype":"locality"
},
  "geometry": {"coordinates":[-62.75,-17.48333],"type":"Point"}
}