{
  "type": "Feature",
  "properties": {
    "gn:admin1_code":"4.0",
    "gn:asciiname":"Nogalani",
    "gn:cc2":"BO",
    "gn:country_code":"BO",
    "gn:dem":1994,
    "gn:feature_class":"P",
    "gn:feature_code":"PPL",
    "gn:name":"Nogalani",
    "gn:population":0,
    "gn:timezone":"America/La_Paz",
    "iso:country":"BO",
    "name:und_x_variant":[
        "Nogolani",
        "Nogalani"
    ],
    "wof:name":"Nogalani",
    "wof:placetype":"locality"
},
  "geometry": {"coordinates":[-67.71666999999999,-15.98333],"type":"Point"}
}