{
  "type": "Feature",
  "properties": {
    "gn:admin1_code":"1.0",
    "gn:asciiname":"Las Arenas",
    "gn:cc2":"BO",
    "gn:country_code":"BO",
    "gn:dem":1027,
    "gn:feature_class":"P",
    "gn:feature_code":"PPL",
    "gn:name":"Las Arenas",
    "gn:population":0,
    "gn:timezone":"America/La_Paz",
    "iso:country":"BO",
    "name:cat_x_preferred":[
        "Areeta"
    ],
    "name:eus_x_preferred":[
        "Areeta"
    ],
    "name:fra_x_preferred":[
        "Areeta"
    ],
    "name:glg_x_preferred":[
        "Areeta"
    ],
    "name:ita_x_preferred":[
        "Las Arenas"
    ],
    "name:spa_x_preferred":[
        "Las Arenas"
    ],
    "name:und_x_variant":[
        "Arenas",
        "Arena"
    ],
    "wof:name":"Las Arenas",
    "wof:placetype":"locality"
},
  "geometry": {"coordinates":[-63.88333000000001,-20.18333],"type":"Point"}
}