{
  "type": "Feature",
  "properties": {
    "gn:admin1_code":"03",
    "gn:asciiname":"El Prado",
    "gn:country_code":"BO",
    "gn:dem":201,
    "gn:feature_class":"P",
    "gn:feature_code":"PPL",
    "gn:name":"El Prado",
    "gn:population":0,
    "gn:timezone":"America/La_Paz",
    "iso:country":"BO",
    "wof:name":"El Prado",
    "wof:placetype":"locality"
},
  "geometry": {"coordinates":[-66.93333,-14.71667],"type":"Point"}
}