{
  "type": "Feature",
  "properties": {
    "gn:admin1_code":"4.0",
    "gn:asciiname":"Sipla",
    "gn:cc2":"BO",
    "gn:country_code":"BO",
    "gn:dem":745,
    "gn:feature_class":"P",
    "gn:feature_code":"PPL",
    "gn:name":"Sipla",
    "gn:population":0,
    "gn:timezone":"America/La_Paz",
    "iso:country":"BO",
    "name:und_x_variant":[
        "Sipia",
        "Sipla"
    ],
    "wof:name":"Sipla",
    "wof:placetype":"locality"
},
  "geometry": {"coordinates":[-68.54722,-14.40833],"type":"Point"}
}