{
  "type": "Feature",
  "properties": {
    "gn:admin1_code":"04",
    "gn:asciiname":"Karasirca",
    "gn:country_code":"BO",
    "gn:dem":2569,
    "gn:feature_class":"P",
    "gn:feature_code":"PPL",
    "gn:name":"Karasirca",
    "gn:population":0,
    "gn:timezone":"America/La_Paz",
    "iso:country":"BO",
    "name:und_x_variant":[
        "Cariasaca"
    ],
    "wof:name":"Karasirca",
    "wof:placetype":"locality"
},
  "geometry": {"coordinates":[-68.71784,-15.73892],"type":"Point"}
}