{
  "type": "Feature",
  "properties": {
    "gn:admin1_code":"3.0",
    "gn:asciiname":"Los Penocos",
    "gn:country_code":"BO",
    "gn:dem":138,
    "gn:feature_class":"P",
    "gn:feature_code":"PPL",
    "gn:name":"Los Penocos",
    "gn:population":0,
    "gn:timezone":"America/La_Paz",
    "iso:country":"BO",
    "wof:name":"Los Penocos",
    "wof:placetype":"locality"
},
  "geometry": {"coordinates":[-64.73333000000001,-13.33333],"type":"Point"}
}