{
  "type": "Feature",
  "properties": {
    "gn:admin1_code":"7.0",
    "gn:asciiname":"Rodeo",
    "gn:country_code":"BO",
    "gn:dem":3187,
    "gn:feature_class":"P",
    "gn:feature_code":"PPL",
    "gn:name":"Rodeo",
    "gn:population":0,
    "gn:timezone":"America/La_Paz",
    "iso:country":"BO",
    "wof:name":"Rodeo",
    "wof:placetype":"locality"
},
  "geometry": {"coordinates":[-65.58181999999999,-19.08489],"type":"Point"}
}