{
  "type": "Feature",
  "properties": {
    "gn:admin1_code":"7.0",
    "gn:asciiname":"Huari",
    "gn:country_code":"BO",
    "gn:dem":3832,
    "gn:feature_class":"P",
    "gn:feature_code":"PPL",
    "gn:name":"Huari",
    "gn:population":0,
    "gn:timezone":"America/La_Paz",
    "iso:country":"BO",
    "name:ceb_x_preferred":[
        "Huari"
    ],
    "name:deu_x_preferred":[
        "Huari"
    ],
    "name:lit_x_preferred":[
        "Varis"
    ],
    "name:nld_x_preferred":[
        "Huari"
    ],
    "name:pol_x_preferred":[
        "Huari"
    ],
    "name:por_x_preferred":[
        "Huari"
    ],
    "name:rus_x_preferred":[
        "\u0423\u0430\u0440\u0438"
    ],
    "name:spa_x_preferred":[
        "Huari"
    ],
    "name:und_x_variant":[
        "Comunidad Huari Pampa"
    ],
    "wof:name":"Huari",
    "wof:placetype":"locality"
},
  "geometry": {"coordinates":[-65.68333,-18.76667],"type":"Point"}
}