{
  "type": "Feature",
  "properties": {
    "gn:admin1_code":"05",
    "gn:asciiname":"Agua Dulce",
    "gn:country_code":"BO",
    "gn:dem":3733,
    "gn:feature_class":"P",
    "gn:feature_code":"PPL",
    "gn:name":"Agua Dulce",
    "gn:population":0,
    "gn:timezone":"America/La_Paz",
    "iso:country":"BO",
    "wof:name":"Agua Dulce",
    "wof:placetype":"locality"
},
  "geometry": {"coordinates":[-67.11667,-19.61667000000001],"type":"Point"}
}