{
  "type": "Feature",
  "properties": {
    "gn:admin1_code":"1.0",
    "gn:asciiname":"San Blas",
    "gn:country_code":"BO",
    "gn:dem":2029,
    "gn:feature_class":"P",
    "gn:feature_code":"PPL",
    "gn:name":"San Blas",
    "gn:population":0,
    "gn:timezone":"America/La_Paz",
    "iso:country":"BO",
    "wof:name":"San Blas",
    "wof:placetype":"locality"
},
  "geometry": {"coordinates":[-64.38946999999999,-19.63051],"type":"Point"}
}