{
  "type": "Feature",
  "properties": {
    "gn:admin1_code":"07",
    "gn:asciiname":"Comunidad La Cienega",
    "gn:country_code":"BO",
    "gn:dem":2626,
    "gn:feature_class":"P",
    "gn:feature_code":"PPL",
    "gn:name":"Comunidad La Cienega",
    "gn:population":0,
    "gn:timezone":"America/La_Paz",
    "iso:country":"BO",
    "name:und_x_variant":[
        "La Ci\u00e9naga"
    ],
    "wof:name":"Comunidad La Cienega",
    "wof:placetype":"locality"
},
  "geometry": {"coordinates":[-65.63518000000001,-20.8195],"type":"Point"}
}