{
  "type": "Feature",
  "properties": {
    "gn:admin1_code":"8.0",
    "gn:asciiname":"Santa Anita",
    "gn:country_code":"BO",
    "gn:dem":505,
    "gn:feature_class":"P",
    "gn:feature_code":"PPL",
    "gn:name":"Santa Anita",
    "gn:population":0,
    "gn:timezone":"America/La_Paz",
    "iso:country":"BO",
    "wof:name":"Santa Anita",
    "wof:placetype":"locality"
},
  "geometry": {"coordinates":[-62.10503000000001,-16.1567],"type":"Point"}
}