{
  "type": "Feature",
  "properties": {
    "gn:admin1_code":"8.0",
    "gn:asciiname":"Estancia Bahia San Juan",
    "gn:country_code":"BO",
    "gn:dem":177,
    "gn:feature_class":"P",
    "gn:feature_code":"PPL",
    "gn:name":"Estancia Bahia San Ju\u00e1n",
    "gn:population":0,
    "gn:timezone":"America/La_Paz",
    "iso:country":"BO",
    "wof:name":"Estancia Bahia San Juan",
    "wof:placetype":"locality"
},
  "geometry": {"coordinates":[-59.55,-16.65],"type":"Point"}
}