{
  "type": "Feature",
  "properties": {
    "gn:admin1_code":"06",
    "gn:asciiname":"Hacienda Costa Rica",
    "gn:country_code":"BO",
    "gn:dem":215,
    "gn:feature_class":"P",
    "gn:feature_code":"PPL",
    "gn:name":"Hacienda Costa Rica",
    "gn:population":0,
    "gn:timezone":"America/La_Paz",
    "iso:country":"BO",
    "name:und_x_variant":[
        "Costa Rica"
    ],
    "wof:name":"Hacienda Costa Rica",
    "wof:placetype":"locality"
},
  "geometry": {"coordinates":[-68.25541,-11.24268],"type":"Point"}
}