{
  "type": "Feature",
  "properties": {
    "gn:admin1_code":"07",
    "gn:asciiname":"Alpahuasi",
    "gn:country_code":"BO",
    "gn:dem":4075,
    "gn:feature_class":"P",
    "gn:feature_code":"PPL",
    "gn:name":"Alpahuasi",
    "gn:population":0,
    "gn:timezone":"America/La_Paz",
    "iso:country":"BO",
    "wof:name":"Alpahuasi",
    "wof:placetype":"locality"
},
  "geometry": {"coordinates":[-65.86667,-21.13333],"type":"Point"}
}