{
  "type": "Feature",
  "properties": {
    "gn:admin1_code":"7.0",
    "gn:asciiname":"Tambilio",
    "gn:country_code":"BO",
    "gn:dem":4198,
    "gn:feature_class":"P",
    "gn:feature_code":"PPL",
    "gn:name":"Tambilio",
    "gn:population":0,
    "gn:timezone":"America/La_Paz",
    "iso:country":"BO",
    "wof:name":"Tambilio",
    "wof:placetype":"locality"
},
  "geometry": {"coordinates":[-66.32009000000001,-21.06506],"type":"Point"}
}