{
  "type": "Feature",
  "properties": {
    "gn:admin1_code":"6.0",
    "gn:asciiname":"Monte Cristo",
    "gn:country_code":"BO",
    "gn:dem":154,
    "gn:feature_class":"P",
    "gn:feature_code":"PPL",
    "gn:name":"Monte Cristo",
    "gn:population":0,
    "gn:timezone":"America/La_Paz",
    "iso:country":"BO",
    "wof:name":"Monte Cristo",
    "wof:placetype":"locality"
},
  "geometry": {"coordinates":[-66.69507,-10.97819],"type":"Point"}
}