{
  "type": "Feature",
  "properties": {
    "gn:admin1_code":"6.0",
    "gn:asciiname":"Pascua",
    "gn:country_code":"BO",
    "gn:dem":181,
    "gn:feature_class":"P",
    "gn:feature_code":"PPL",
    "gn:name":"Pascua",
    "gn:population":0,
    "gn:timezone":"America/La_Paz",
    "iso:country":"BO",
    "name:ceb_x_preferred":[
        "Pascua"
    ],
    "name:hun_x_preferred":[
        "Pascua"
    ],
    "name:nld_x_preferred":[
        "Pascua"
    ],
    "name:swe_x_preferred":[
        "Pascua"
    ],
    "name:war_x_preferred":[
        "Pascua"
    ],
    "wof:name":"Pascua",
    "wof:placetype":"locality"
},
  "geometry": {"coordinates":[-67.36667,-11.11667],"type":"Point"}
}