{
  "type": "Feature",
  "properties": {
    "gn:admin1_code":"1.0",
    "gn:asciiname":"Orcote",
    "gn:country_code":"BO",
    "gn:dem":1109,
    "gn:feature_class":"P",
    "gn:feature_code":"PPL",
    "gn:name":"Orcote",
    "gn:population":0,
    "gn:timezone":"America/La_Paz",
    "iso:country":"BO",
    "wof:name":"Orcote",
    "wof:placetype":"locality"
},
  "geometry": {"coordinates":[-64.29561,-20.79763],"type":"Point"}
}