{
  "type": "Feature",
  "properties": {
    "gn:admin1_code":"7.0",
    "gn:asciiname":"Punahuasi",
    "gn:country_code":"BO",
    "gn:dem":4155,
    "gn:feature_class":"P",
    "gn:feature_code":"PPL",
    "gn:name":"Punahuasi",
    "gn:population":0,
    "gn:timezone":"America/La_Paz",
    "iso:country":"BO",
    "wof:name":"Punahuasi",
    "wof:placetype":"locality"
},
  "geometry": {"coordinates":[-66.41667,-21.45],"type":"Point"}
}