{
  "type": "Feature",
  "properties": {
    "gn:admin1_code":"04",
    "gn:asciiname":"Estancia Cala Cruz",
    "gn:country_code":"BO",
    "gn:dem":3964,
    "gn:feature_class":"P",
    "gn:feature_code":"PPL",
    "gn:name":"Estancia Cala Cruz",
    "gn:population":0,
    "gn:timezone":"America/La_Paz",
    "iso:country":"BO",
    "wof:name":"Estancia Cala Cruz",
    "wof:placetype":"locality"
},
  "geometry": {"coordinates":[-67.26666999999999,-17.45],"type":"Point"}
}