{
  "type": "Feature",
  "properties": {
    "gn:admin1_code":"4.0",
    "gn:asciiname":"Mariado",
    "gn:cc2":"BO",
    "gn:country_code":"BO",
    "gn:dem":339,
    "gn:feature_class":"P",
    "gn:feature_code":"PPL",
    "gn:name":"Mariado",
    "gn:population":0,
    "gn:timezone":"America/La_Paz",
    "iso:country":"BO",
    "name:und_x_variant":[
        "Miriado",
        "Mariado"
    ],
    "wof:name":"Mariado",
    "wof:placetype":"locality"
},
  "geometry": {"coordinates":[-67.66667,-15.21667],"type":"Point"}
}