{
  "type": "Feature",
  "properties": {
    "gn:admin1_code":"08",
    "gn:asciiname":"Delta",
    "gn:country_code":"BO",
    "gn:dem":203,
    "gn:feature_class":"P",
    "gn:feature_code":"PPL",
    "gn:name":"Delta",
    "gn:population":0,
    "gn:timezone":"America/La_Paz",
    "iso:country":"BO",
    "name:ara_x_preferred":[
        "\u062f\u0644\u062a\u0627"
    ],
    "name:arg_x_preferred":[
        "Delta"
    ],
    "name:azb_x_preferred":[
        "\u062f\u0644\u062a\u0627"
    ],
    "name:aze_x_preferred":[
        "Delta"
    ],
    "name:bos_x_preferred":[
        "Delta"
    ],
    "name:bre_x_preferred":[
        "Delta"
    ],
    "name:bul_x_preferred":[
        "\u0414\u0435\u043b\u0442\u0430"
    ],
    "name:cat_x_preferred":[
        "Delta"
    ],
    "name:ceb_x_preferred":[
        "Delta"
    ],
    "name:ces_x_preferred":[
        "Delta"
    ],
    "name:cym_x_preferred":[
        "Delta"
    ],
    "name:dan_x_preferred":[
        "Delta"
    ],
    "name:deu_x_preferred":[
        "Delta"
    ],
    "name:ell_x_preferred":[
        "\u0394\u03ad\u03bb\u03c4\u03b1"
    ],
    "name:epo_x_preferred":[
        "Delta"
    ],
    "name:est_x_preferred":[
        "Delta"
    ],
    "name:eus_x_preferred":[
        "Delta"
    ],
    "name:ext_x_preferred":[
        "Delta"
    ],
    "name:fas_x_preferred":[
        "\u062f\u0644\u062a\u0627"
    ],
    "name:fin_x_preferred":[
        "Delta"
    ],
    "name:fra_x_preferred":[
        "Delta"
    ],
    "name:frr_x_preferred":[
        "Delta"
    ],
    "name:fry_x_preferred":[
        "Delta"
    ],
    "name:glg_x_preferred":[
        "Delta"
    ],
    "name:heb_x_preferred":[
        "\u05d3\u05dc\u05ea\u05d0"
    ],
    "name:hrv_x_preferred":[
        "Delta"
    ],
    "name:hun_x_preferred":[
        "Delta"
    ],
    "name:hye_x_preferred":[
        "\u0534\u0565\u056c\u057f\u0561"
    ],
    "name:ind_x_preferred":[
        "Delta"
    ],
    "name:ita_x_preferred":[
        "Delta"
    ],
    "name:jpn_x_preferred":[
        "\u30c7\u30eb\u30bf"
    ],
    "name:kat_x_preferred":[
        "\u10d3\u10d4\u10da\u10e2\u10d0"
    ],
    "name:kur_x_preferred":[
        "Delta"
    ],
    "name:lav_x_preferred":[
        "Delta"
    ],
    "name:lit_x_preferred":[
        "Delta"
    ],
    "name:nds_x_preferred":[
        "Delta"
    ],
    "name:nld_x_preferred":[
        "Delta"
    ],
    "name:nor_x_preferred":[
        "Delta"
    ],
    "name:oci_x_preferred":[
        "D\u00e8lta"
    ],
    "name:pol_x_preferred":[
        "Delta"
    ],
    "name:por_x_preferred":[
        "Delta"
    ],
    "name:ron_x_preferred":[
        "Delta"
    ],
    "name:rus_x_preferred":[
        "\u0414\u0435\u043b\u044c\u0442\u0430"
    ],
    "name:scn_x_preferred":[
        "Delta"
    ],
    "name:sco_x_preferred":[
        "Delta"
    ],
    "name:slk_x_preferred":[
        "Delta"
    ],
    "name:slv_x_preferred":[
        "Delta"
    ],
    "name:spa_x_preferred":[
        "Delta"
    ],
    "name:srp_x_preferred":[
        "\u0414\u0435\u043b\u0442\u0430"
    ],
    "name:swe_x_preferred":[
        "Delta"
    ],
    "name:tur_x_preferred":[
        "Delta"
    ],
    "name:ukr_x_preferred":[
        "\u0414\u0435\u043b\u044c\u0442\u0430"
    ],
    "name:vol_x_preferred":[
        "Delta"
    ],
    "name:yid_x_preferred":[
        "\u05d3\u05e2\u05dc\u05d8\u05e2"
    ],
    "name:zho_x_preferred":[
        "\u5fb7\u723e\u5854"
    ],
    "wof:name":"Delta",
    "wof:placetype":"locality"
},
  "geometry": {"coordinates":[-62.03333000000001,-13.98333],"type":"Point"}
}