{
  "type": "Feature",
  "properties": {
    "gn:admin1_code":"08",
    "gn:asciiname":"Delta",
    "gn:country_code":"BO",
    "gn:dem":203,
    "gn:feature_class":"P",
    "gn:feature_code":"PPL",
    "gn:name":"Delta",
    "gn:population":0,
    "gn:timezone":"America/La_Paz",
    "iso:country":"BO",
    "wof:name":"Delta",
    "wof:placetype":"locality"
},
  "geometry": {"coordinates":[-62.03333000000001,-13.98333],"type":"Point"}
}