{
  "type": "Feature",
  "properties": {
    "gn:admin1_code":"2.0",
    "gn:asciiname":"Virquemayo",
    "gn:country_code":"BO",
    "gn:dem":2722,
    "gn:feature_class":"P",
    "gn:feature_code":"PPL",
    "gn:name":"Virquemayo",
    "gn:population":0,
    "gn:timezone":"America/La_Paz",
    "iso:country":"BO",
    "wof:name":"Virquemayo",
    "wof:placetype":"locality"
},
  "geometry": {"coordinates":[-65.34999999999999,-18.11667000000001],"type":"Point"}
}