{
  "type": "Feature",
  "properties": {
    "gn:admin1_code":"04",
    "gn:asciiname":"Estancia Jiskha Marca",
    "gn:country_code":"BO",
    "gn:dem":4401,
    "gn:feature_class":"P",
    "gn:feature_code":"PPL",
    "gn:name":"Estancia Jiskha Marca",
    "gn:population":0,
    "gn:timezone":"America/La_Paz",
    "iso:country":"BO",
    "wof:name":"Estancia Jiskha Marca",
    "wof:placetype":"locality"
},
  "geometry": {"coordinates":[-67.26666999999999,-17.23333],"type":"Point"}
}