{
  "type": "Feature",
  "properties": {
    "gn:admin1_code":"9.0",
    "gn:asciiname":"Isla del Criston",
    "gn:cc2":"BO",
    "gn:country_code":"BO",
    "gn:dem":901,
    "gn:feature_class":"P",
    "gn:feature_code":"PPL",
    "gn:name":"Isla del Crist\u00f3n",
    "gn:population":0,
    "gn:timezone":"America/La_Paz",
    "iso:country":"BO",
    "name:und_x_variant":[
        "Isla de Crest\u00f3n",
        "Isla del Crist\u00f3n"
    ],
    "wof:name":"Isla del Criston",
    "wof:placetype":"locality"
},
  "geometry": {"coordinates":[-64.59999999999999,-22.35],"type":"Point"}
}