{
  "type": "Feature",
  "properties": {
    "gn:admin1_code":"7.0",
    "gn:asciiname":"Estancia Tojchiki",
    "gn:country_code":"BO",
    "gn:dem":4020,
    "gn:feature_class":"P",
    "gn:feature_code":"PPL",
    "gn:name":"Estancia Tojchiki",
    "gn:population":0,
    "gn:timezone":"America/La_Paz",
    "iso:country":"BO",
    "wof:name":"Estancia Tojchiki",
    "wof:placetype":"locality"
},
  "geometry": {"coordinates":[-66.36126,-20.03627],"type":"Point"}
}