{
  "type": "Feature",
  "properties": {
    "gn:admin1_code":"9.0",
    "gn:asciiname":"Serere",
    "gn:country_code":"BO",
    "gn:dem":1024,
    "gn:feature_class":"P",
    "gn:feature_code":"PPL",
    "gn:name":"Serer\u00e9",
    "gn:population":0,
    "gn:timezone":"America/La_Paz",
    "iso:country":"BO",
    "name:ceb_x_preferred":[
        "Serere"
    ],
    "name:fra_x_preferred":[
        "Serere"
    ],
    "name:heb_x_preferred":[
        "\u05e1\u05e8\u05b6\u05e8\u05b6\u05d4"
    ],
    "name:hun_x_preferred":[
        "Serere"
    ],
    "name:lug_x_preferred":[
        "Serere"
    ],
    "name:und_x_variant":[
        "Sarere",
        "Serer\u00e9"
    ],
    "name:urd_x_preferred":[
        "\u0633\u06cc\u0631\u06cc\u0631\u06d2"
    ],
    "wof:name":"Serere",
    "wof:placetype":"locality"
},
  "geometry": {"coordinates":[-64.10337,-21.46911],"type":"Point"}
}