{
  "type": "Feature",
  "properties": {
    "gn:admin1_code":"3.0",
    "gn:asciiname":"Guarayos",
    "gn:country_code":"BO",
    "gn:dem":161,
    "gn:feature_class":"P",
    "gn:feature_code":"PPL",
    "gn:name":"Guarayos",
    "gn:population":0,
    "gn:timezone":"America/La_Paz",
    "iso:country":"BO",
    "name:deu_x_preferred":[
        "Guarayos"
    ],
    "name:hrv_x_preferred":[
        "Guarayu"
    ],
    "name:lit_x_preferred":[
        "Gvarajai"
    ],
    "name:por_x_preferred":[
        "Guaraios"
    ],
    "name:que_x_preferred":[
        "Warayu runa"
    ],
    "name:spa_x_preferred":[
        "Guarayos"
    ],
    "name:und_x_variant":[
        "Guanay"
    ],
    "wof:name":"Guarayos",
    "wof:placetype":"locality"
},
  "geometry": {"coordinates":[-66.9521,-12.72002],"type":"Point"}
}