{
  "type": "Feature",
  "properties": {
    "gn:admin1_code":"4.0",
    "gn:asciiname":"Pablo Amaya",
    "gn:cc2":"BO",
    "gn:country_code":"BO",
    "gn:dem":3600,
    "gn:feature_class":"P",
    "gn:feature_code":"PPL",
    "gn:name":"Pablo Amaya",
    "gn:population":0,
    "gn:timezone":"America/La_Paz",
    "iso:country":"BO",
    "name:und_x_variant":[
        "Publo Amaya",
        "Pablo Amaya"
    ],
    "wof:name":"Pablo Amaya",
    "wof:placetype":"locality"
},
  "geometry": {"coordinates":[-68.25,-15.93333],"type":"Point"}
}