{
  "type": "Feature",
  "properties": {
    "gn:admin1_code":"02",
    "gn:asciiname":"Chillcani",
    "gn:country_code":"BO",
    "gn:dem":2898,
    "gn:feature_class":"P",
    "gn:feature_code":"PPL",
    "gn:name":"Chillcani",
    "gn:population":0,
    "gn:timezone":"America/La_Paz",
    "iso:country":"BO",
    "wof:name":"Chillcani",
    "wof:placetype":"locality"
},
  "geometry": {"coordinates":[-66.01666999999999,-17.81667000000001],"type":"Point"}
}