{
  "type": "Feature",
  "properties": {
    "gn:admin1_code":"04",
    "gn:asciiname":"Challa",
    "gn:cc2":"BO",
    "gn:country_code":"BO",
    "gn:dem":4304,
    "gn:feature_class":"P",
    "gn:feature_code":"PPL",
    "gn:name":"Challa",
    "gn:population":0,
    "gn:timezone":"America/La_Paz",
    "iso:country":"BO",
    "name:und_x_variant":[
        "Estancia Challa",
        "Challa"
    ],
    "wof:name":"Challa",
    "wof:placetype":"locality"
},
  "geometry": {"coordinates":[-67.16667,-17.23333],"type":"Point"}
}