{
  "type": "Feature",
  "properties": {
    "gn:admin1_code":"7.0",
    "gn:asciiname":"Puquios",
    "gn:country_code":"BO",
    "gn:dem":3733,
    "gn:feature_class":"P",
    "gn:feature_code":"PPL",
    "gn:name":"Puquios",
    "gn:population":0,
    "gn:timezone":"America/La_Paz",
    "iso:country":"BO",
    "name:ben_x_preferred":[
        "\u09aa\u09c1\u0995\u09c1\u0987\u09af\u09bc\u09cb"
    ],
    "name:fra_x_preferred":[
        "Puquios"
    ],
    "name:kat_x_preferred":[
        "\u10de\u10e3\u10d9\u10d8\u10dd\u10e1\u10d8"
    ],
    "name:mal_x_preferred":[
        "\u0d2a\u0d41\u0d15\u0d4d\u0d15\u0d3f\u0d2f\u0d4b\u0d15\u0d7e"
    ],
    "name:nld_x_preferred":[
        "Puquios"
    ],
    "name:pol_x_preferred":[
        "Puquios"
    ],
    "name:rus_x_preferred":[
        "\u041f\u0443\u043a\u0438\u043e\u0441"
    ],
    "name:spa_x_preferred":[
        "Puquio"
    ],
    "wof:name":"Puquios",
    "wof:placetype":"locality"
},
  "geometry": {"coordinates":[-65.93333,-21.61667000000001],"type":"Point"}
}