{
  "type": "Feature",
  "properties": {
    "gn:admin1_code":"7.0",
    "gn:asciiname":"Puquios",
    "gn:country_code":"BO",
    "gn:dem":3733,
    "gn:feature_class":"P",
    "gn:feature_code":"PPL",
    "gn:name":"Puquios",
    "gn:population":0,
    "gn:timezone":"America/La_Paz",
    "iso:country":"BO",
    "wof:name":"Puquios",
    "wof:placetype":"locality"
},
  "geometry": {"coordinates":[-65.93333,-21.61667000000001],"type":"Point"}
}