{
  "type": "Feature",
  "properties": {
    "gn:admin1_code":"9.0",
    "gn:asciiname":"Tentahuaso",
    "gn:country_code":"BO",
    "gn:dem":556,
    "gn:feature_class":"P",
    "gn:feature_code":"PPL",
    "gn:name":"Tentahuaso",
    "gn:population":0,
    "gn:timezone":"America/La_Paz",
    "iso:country":"BO",
    "wof:name":"Tentahuaso",
    "wof:placetype":"locality"
},
  "geometry": {"coordinates":[-63.96351,-21.11415],"type":"Point"}
}