{
  "type": "Feature",
  "properties": {
    "gn:admin1_code":"04",
    "gn:asciiname":"Anquioma Bajo",
    "gn:country_code":"BO",
    "gn:dem":2742,
    "gn:feature_class":"P",
    "gn:feature_code":"PPL",
    "gn:name":"Anquioma Bajo",
    "gn:population":0,
    "gn:timezone":"America/La_Paz",
    "iso:country":"BO",
    "wof:name":"Anquioma Bajo",
    "wof:placetype":"locality"
},
  "geometry": {"coordinates":[-67.66667,-16.96667],"type":"Point"}
}