{
  "type": "Feature",
  "properties": {
    "gn:admin1_code":"1.0",
    "gn:asciiname":"I. Ibarra",
    "gn:country_code":"BO",
    "gn:dem":666,
    "gn:feature_class":"P",
    "gn:feature_code":"PPL",
    "gn:name":"I. Ibarra",
    "gn:population":0,
    "gn:timezone":"America/La_Paz",
    "iso:country":"BO",
    "wof:name":"I. Ibarra",
    "wof:placetype":"locality"
},
  "geometry": {"coordinates":[-63.08333,-20.95],"type":"Point"}
}