{
  "type": "Feature",
  "properties": {
    "gn:admin1_code":"5.0",
    "gn:asciiname":"Laguna",
    "gn:cc2":"BO",
    "gn:country_code":"BO",
    "gn:dem":4149,
    "gn:feature_class":"P",
    "gn:feature_code":"PPL",
    "gn:name":"Laguna",
    "gn:population":0,
    "gn:timezone":"America/La_Paz",
    "iso:country":"BO",
    "name:cat_x_preferred":[
        "Laguna"
    ],
    "name:ceb_x_preferred":[
        "Laguna"
    ],
    "name:ces_x_preferred":[
        "Laguna"
    ],
    "name:deu_x_preferred":[
        "Laguna"
    ],
    "name:fra_x_preferred":[
        "Laguna"
    ],
    "name:ind_x_preferred":[
        "Laguna"
    ],
    "name:ita_x_preferred":[
        "Laguna"
    ],
    "name:jpn_x_preferred":[
        "\u30e9\u30b0\u30ca"
    ],
    "name:kat_x_preferred":[
        "\u10da\u10d0\u10d2\u10e3\u10dc\u10d0"
    ],
    "name:kor_x_preferred":[
        "\ub77c\uad6c\ub098"
    ],
    "name:nds_x_preferred":[
        "Laguna"
    ],
    "name:nld_x_preferred":[
        "Laguna"
    ],
    "name:nor_x_preferred":[
        "Laguna"
    ],
    "name:pol_x_preferred":[
        "Laguna"
    ],
    "name:por_x_preferred":[
        "Laguna"
    ],
    "name:ron_x_preferred":[
        "Laguna"
    ],
    "name:rus_x_preferred":[
        "\u041b\u0430\u0433\u0443\u043d\u0430"
    ],
    "name:sco_x_preferred":[
        "Laguna"
    ],
    "name:slk_x_preferred":[
        "Lag\u00fana"
    ],
    "name:slv_x_preferred":[
        "Laguna"
    ],
    "name:spa_x_preferred":[
        "Laguna"
    ],
    "name:swe_x_preferred":[
        "Laguna"
    ],
    "name:tgl_x_preferred":[
        "Laguna"
    ],
    "name:und_x_variant":[
        "Comisario",
        "Estancia Laguna",
        "Lagunas",
        "Laguna"
    ],
    "name:vol_x_preferred":[
        "Laguna"
    ],
    "wof:name":"Laguna",
    "wof:placetype":"locality"
},
  "geometry": {"coordinates":[-68.96666999999999,-18.21667],"type":"Point"}
}