{
  "type": "Feature",
  "properties": {
    "gn:admin1_code":"5.0",
    "gn:asciiname":"Laguna",
    "gn:cc2":"BO",
    "gn:country_code":"BO",
    "gn:dem":4149,
    "gn:feature_class":"P",
    "gn:feature_code":"PPL",
    "gn:name":"Laguna",
    "gn:population":0,
    "gn:timezone":"America/La_Paz",
    "iso:country":"BO",
    "name:und_x_variant":[
        "Comisario",
        "Estancia Laguna",
        "Lagunas",
        "Laguna"
    ],
    "wof:name":"Laguna",
    "wof:placetype":"locality"
},
  "geometry": {"coordinates":[-68.96666999999999,-18.21667],"type":"Point"}
}