{
  "type": "Feature",
  "properties": {
    "gn:admin1_code":"04",
    "gn:asciiname":"Achica Arriba",
    "gn:country_code":"BO",
    "gn:dem":3890,
    "gn:feature_class":"P",
    "gn:feature_code":"PPL",
    "gn:name":"Achica Arriba",
    "gn:population":0,
    "gn:timezone":"America/La_Paz",
    "iso:country":"BO",
    "wof:name":"Achica Arriba",
    "wof:placetype":"locality"
},
  "geometry": {"coordinates":[-68.21666999999999,-16.71667],"type":"Point"}
}