{
  "type": "Feature",
  "properties": {
    "gn:admin1_code":"04",
    "gn:asciiname":"Chinalaya",
    "gn:country_code":"BO",
    "gn:dem":1267,
    "gn:feature_class":"P",
    "gn:feature_code":"PPL",
    "gn:name":"Chinalaya",
    "gn:population":0,
    "gn:timezone":"America/La_Paz",
    "iso:country":"BO",
    "wof:name":"Chinalaya",
    "wof:placetype":"locality"
},
  "geometry": {"coordinates":[-68.03333000000001,-15.78333],"type":"Point"}
}