{
  "type": "Feature",
  "properties": {
    "gn:admin1_code":"7.0",
    "gn:asciiname":"Estancia Mayu Palca",
    "gn:country_code":"BO",
    "gn:dem":2970,
    "gn:feature_class":"P",
    "gn:feature_code":"PPL",
    "gn:name":"Estancia Mayu Palca",
    "gn:population":0,
    "gn:timezone":"America/La_Paz",
    "iso:country":"BO",
    "wof:name":"Estancia Mayu Palca",
    "wof:placetype":"locality"
},
  "geometry": {"coordinates":[-65.38110999999999,-20.26138],"type":"Point"}
}