{
  "type": "Feature",
  "properties": {
    "gn:admin1_code":"4.0",
    "gn:asciiname":"Santo Domingo",
    "gn:country_code":"BO",
    "gn:dem":1809,
    "gn:feature_class":"P",
    "gn:feature_code":"PPL",
    "gn:name":"Santo Domingo",
    "gn:population":0,
    "gn:timezone":"America/La_Paz",
    "iso:country":"BO",
    "wof:name":"Santo Domingo",
    "wof:placetype":"locality"
},
  "geometry": {"coordinates":[-67.75,-16.16667],"type":"Point"}
}