{
  "type": "Feature",
  "properties": {
    "gn:admin1_code":"07",
    "gn:asciiname":"Chaquilla",
    "gn:country_code":"BO",
    "gn:dem":4163,
    "gn:feature_class":"P",
    "gn:feature_code":"PPL",
    "gn:name":"Chaquilla",
    "gn:population":0,
    "gn:timezone":"America/La_Paz",
    "iso:country":"BO",
    "name:und_x_variant":[
        "Estancia Chaquilla",
        "Chaquilla"
    ],
    "wof:name":"Chaquilla",
    "wof:placetype":"locality"
},
  "geometry": {"coordinates":[-65.74088,-19.7857],"type":"Point"}
}