{
  "type": "Feature",
  "properties": {
    "gn:admin1_code":"7.0",
    "gn:asciiname":"Ista",
    "gn:country_code":"BO",
    "gn:dem":3358,
    "gn:feature_class":"P",
    "gn:feature_code":"PPL",
    "gn:name":"Ista",
    "gn:population":0,
    "gn:timezone":"America/La_Paz",
    "iso:country":"BO",
    "name:ceb_x_preferred":[
        "Ista"
    ],
    "wof:name":"Ista",
    "wof:placetype":"locality"
},
  "geometry": {"coordinates":[-65.84999999999999,-19.35],"type":"Point"}
}