{
  "type": "Feature",
  "properties": {
    "gn:admin1_code":"8.0",
    "gn:asciiname":"Estancia La Enconada",
    "gn:country_code":"BO",
    "gn:dem":260,
    "gn:feature_class":"P",
    "gn:feature_code":"PPL",
    "gn:name":"Estancia La Enconada",
    "gn:population":0,
    "gn:timezone":"America/La_Paz",
    "iso:country":"BO",
    "wof:name":"Estancia La Enconada",
    "wof:placetype":"locality"
},
  "geometry": {"coordinates":[-63.88333000000001,-17.05],"type":"Point"}
}