{
  "type": "Feature",
  "properties": {
    "gn:admin1_code":"07",
    "gn:asciiname":"Estancia Esquela",
    "gn:country_code":"BO",
    "gn:dem":4267,
    "gn:feature_class":"P",
    "gn:feature_code":"PPL",
    "gn:name":"Estancia Esquela",
    "gn:population":0,
    "gn:timezone":"America/La_Paz",
    "iso:country":"BO",
    "wof:name":"Estancia Esquela",
    "wof:placetype":"locality"
},
  "geometry": {"coordinates":[-66.73333000000001,-20.23333],"type":"Point"}
}