{
  "type": "Feature",
  "properties": {
    "gn:admin1_code":"07",
    "gn:asciiname":"Cuchihuasi",
    "gn:country_code":"BO",
    "gn:dem":3226,
    "gn:feature_class":"P",
    "gn:feature_code":"PPL",
    "gn:name":"Cuchihuasi",
    "gn:population":0,
    "gn:timezone":"America/La_Paz",
    "iso:country":"BO",
    "name:und_x_variant":[
        "Cuchihuasa",
        "Cuchihuasi"
    ],
    "wof:name":"Cuchihuasi",
    "wof:placetype":"locality"
},
  "geometry": {"coordinates":[-65.34605999999999,-19.39588],"type":"Point"}
}