{
  "type": "Feature",
  "properties": {
    "gn:admin1_code":"1.0",
    "gn:asciiname":"Matico",
    "gn:country_code":"BO",
    "gn:dem":1223,
    "gn:feature_class":"P",
    "gn:feature_code":"PPL",
    "gn:name":"Matico",
    "gn:population":0,
    "gn:timezone":"America/La_Paz",
    "iso:country":"BO",
    "name:spa_x_preferred":[
        "Matico"
    ],
    "wof:name":"Matico",
    "wof:placetype":"locality"
},
  "geometry": {"coordinates":[-63.86666999999999,-19.51667],"type":"Point"}
}