{
  "type": "Feature",
  "properties": {
    "gn:admin1_code":"1.0",
    "gn:asciiname":"La Torre",
    "gn:country_code":"BO",
    "gn:dem":2549,
    "gn:feature_class":"P",
    "gn:feature_code":"PPL",
    "gn:name":"La Torre",
    "gn:population":0,
    "gn:timezone":"America/La_Paz",
    "iso:country":"BO",
    "wof:name":"La Torre",
    "wof:placetype":"locality"
},
  "geometry": {"coordinates":[-64.58698000000001,-19.28574],"type":"Point"}
}