{
  "type": "Feature",
  "properties": {
    "gn:admin1_code":"03",
    "gn:asciiname":"Colon",
    "gn:country_code":"BO",
    "gn:dem":121,
    "gn:feature_class":"P",
    "gn:feature_code":"PPL",
    "gn:name":"Col\u00f3n",
    "gn:population":0,
    "gn:timezone":"America/La_Paz",
    "iso:country":"BO",
    "wof:name":"Colon",
    "wof:placetype":"locality"
},
  "geometry": {"coordinates":[-65.26666999999999,-10.96667],"type":"Point"}
}