{
  "type": "Feature",
  "properties": {
    "gn:admin1_code":"08",
    "gn:asciiname":"Banegas",
    "gn:cc2":"BO",
    "gn:country_code":"BO",
    "gn:dem":261,
    "gn:feature_class":"P",
    "gn:feature_code":"PPL",
    "gn:name":"Banegas",
    "gn:population":0,
    "gn:timezone":"America/La_Paz",
    "iso:country":"BO",
    "name:und_x_variant":[
        "Puerto Banegas",
        "Banegas"
    ],
    "wof:name":"Banegas",
    "wof:placetype":"locality"
},
  "geometry": {"coordinates":[-62.83333,-17.15],"type":"Point"}
}