{
  "type": "Feature",
  "properties": {
    "gn:admin1_code":"4.0",
    "gn:asciiname":"Uma-Acsi",
    "gn:cc2":"BO",
    "gn:country_code":"BO",
    "gn:dem":3994,
    "gn:feature_class":"P",
    "gn:feature_code":"PPL",
    "gn:name":"Uma-Acsi",
    "gn:population":0,
    "gn:timezone":"America/La_Paz",
    "iso:country":"BO",
    "name:und_x_variant":[
        "Humajacsi",
        "Uma-Acsi"
    ],
    "wof:name":"Uma-Acsi",
    "wof:placetype":"locality"
},
  "geometry": {"coordinates":[-69.05,-17.43333],"type":"Point"}
}