{
  "type": "Feature",
  "properties": {
    "gn:admin1_code":"7.0",
    "gn:asciiname":"San Pablopampa",
    "gn:cc2":"BO",
    "gn:country_code":"BO",
    "gn:dem":4206,
    "gn:feature_class":"P",
    "gn:feature_code":"PPL",
    "gn:name":"San Pablopampa",
    "gn:population":0,
    "gn:timezone":"America/La_Paz",
    "iso:country":"BO",
    "name:und_x_variant":[
        "Pablopampa",
        "San Pablopampa"
    ],
    "wof:name":"San Pablopampa",
    "wof:placetype":"locality"
},
  "geometry": {"coordinates":[-66.68333,-21.71667],"type":"Point"}
}