{
  "type": "Feature",
  "properties": {
    "gn:admin1_code":"7.0",
    "gn:asciiname":"Poroma",
    "gn:country_code":"BO",
    "gn:dem":2826,
    "gn:feature_class":"P",
    "gn:feature_code":"PPL",
    "gn:name":"Poroma",
    "gn:population":0,
    "gn:timezone":"America/La_Paz",
    "iso:country":"BO",
    "name:ara_x_preferred":[
        "\u0634\u0632\u0646"
    ],
    "name:und_x_variant":[
        "Estancia Poroma",
        "Poroma"
    ],
    "wof:name":"Poroma",
    "wof:placetype":"locality"
},
  "geometry": {"coordinates":[-65.42214,-20.61247],"type":"Point"}
}