{
  "type": "Feature",
  "properties": {
    "gn:admin1_code":"6.0",
    "gn:asciiname":"Rio Negro",
    "gn:cc2":"BO",
    "gn:country_code":"BO",
    "gn:dem":131,
    "gn:feature_class":"P",
    "gn:feature_code":"PPL",
    "gn:name":"R\u00edo Negro",
    "gn:population":0,
    "gn:timezone":"America/La_Paz",
    "iso:country":"BO",
    "name:und_x_variant":[
        "Fort\u00edn R\u00edo Negro",
        "R\u00edo Negro"
    ],
    "wof:name":"Rio Negro",
    "wof:placetype":"locality"
},
  "geometry": {"coordinates":[-65.68333,-9.81667],"type":"Point"}
}