{
  "type": "Feature",
  "properties": {
    "gn:admin1_code":"05",
    "gn:asciiname":"Estancia Chulucuma",
    "gn:country_code":"BO",
    "gn:dem":3700,
    "gn:feature_class":"P",
    "gn:feature_code":"PPL",
    "gn:name":"Estancia Chulucuma",
    "gn:population":0,
    "gn:timezone":"America/La_Paz",
    "iso:country":"BO",
    "wof:name":"Estancia Chulucuma",
    "wof:placetype":"locality"
},
  "geometry": {"coordinates":[-67.62059000000001,-19.20675],"type":"Point"}
}