{
  "type": "Feature",
  "properties": {
    "gn:admin1_code":"01",
    "gn:asciiname":"Chanchajllo",
    "gn:country_code":"BO",
    "gn:dem":3382,
    "gn:feature_class":"P",
    "gn:feature_code":"PPL",
    "gn:name":"Chanchajllo",
    "gn:population":0,
    "gn:timezone":"America/La_Paz",
    "iso:country":"BO",
    "name:und_x_variant":[
        "Estancia Chanchajli",
        "Chanchajlla",
        "Chanchajllo"
    ],
    "wof:name":"Chanchajllo",
    "wof:placetype":"locality"
},
  "geometry": {"coordinates":[-65.21720999999999,-20.20812],"type":"Point"}
}