{
  "type": "Feature",
  "properties": {
    "gn:admin1_code":"7.0",
    "gn:asciiname":"Florespunta",
    "gn:country_code":"BO",
    "gn:dem":3731,
    "gn:feature_class":"P",
    "gn:feature_code":"PPL",
    "gn:name":"Florespunta",
    "gn:population":0,
    "gn:timezone":"America/La_Paz",
    "iso:country":"BO",
    "wof:name":"Florespunta",
    "wof:placetype":"locality"
},
  "geometry": {"coordinates":[-65.96666999999999,-21.38333],"type":"Point"}
}