{
  "type": "Feature",
  "properties": {
    "gn:admin1_code":"01",
    "gn:asciiname":"Chorro",
    "gn:cc2":"BO",
    "gn:country_code":"BO",
    "gn:dem":1881,
    "gn:feature_class":"P",
    "gn:feature_code":"PPL",
    "gn:name":"Chorro",
    "gn:population":0,
    "gn:timezone":"America/La_Paz",
    "iso:country":"BO",
    "name:bre_x_preferred":[
        "Chorro"
    ],
    "name:spa_x_preferred":[
        "Chorro"
    ],
    "name:und_x_variant":[
        "Chorra"
    ],
    "wof:name":"Chorro",
    "wof:placetype":"locality"
},
  "geometry": {"coordinates":[-64.21666999999999,-19.45],"type":"Point"}
}