{
  "type": "Feature",
  "properties": {
    "gn:admin1_code":"05",
    "gn:asciiname":"Collpa",
    "gn:cc2":"BO",
    "gn:country_code":"BO",
    "gn:dem":4843,
    "gn:feature_class":"P",
    "gn:feature_code":"PPL",
    "gn:name":"Collpa",
    "gn:population":0,
    "gn:timezone":"America/La_Paz",
    "iso:country":"BO",
    "name:und_x_variant":[
        "Colpa",
        "Collpa"
    ],
    "wof:name":"Collpa",
    "wof:placetype":"locality"
},
  "geometry": {"coordinates":[-66.71666999999999,-18.96667],"type":"Point"}
}