{
  "type": "Feature",
  "properties": {
    "gn:admin1_code":"3.0",
    "gn:asciiname":"La Paz",
    "gn:country_code":"BO",
    "gn:dem":160,
    "gn:feature_class":"P",
    "gn:feature_code":"PPL",
    "gn:name":"La Paz",
    "gn:population":0,
    "gn:timezone":"America/La_Paz",
    "iso:country":"BO",
    "wof:name":"La Paz",
    "wof:placetype":"locality"
},
  "geometry": {"coordinates":[-66.20028000000001,-13.96667],"type":"Point"}
}