{
  "type": "Feature",
  "properties": {
    "gn:admin1_code":"07",
    "gn:asciiname":"Estancia Isla Takakaya",
    "gn:country_code":"BO",
    "gn:dem":3513,
    "gn:feature_class":"P",
    "gn:feature_code":"PPL",
    "gn:name":"Estancia Isla Takakaya",
    "gn:population":0,
    "gn:timezone":"America/La_Paz",
    "iso:country":"BO",
    "wof:name":"Estancia Isla Takakaya",
    "wof:placetype":"locality"
},
  "geometry": {"coordinates":[-65.83615999999999,-19.36862],"type":"Point"}
}