{
  "type": "Feature",
  "properties": {
    "gn:admin1_code":"06",
    "gn:asciiname":"Puerto Carmen",
    "gn:country_code":"BO",
    "gn:dem":241,
    "gn:feature_class":"P",
    "gn:feature_code":"PPL",
    "gn:name":"Puerto Carmen",
    "gn:population":0,
    "gn:timezone":"America/La_Paz",
    "iso:country":"BO",
    "name:spa_x_preferred":[
        "Puerto Carmen"
    ],
    "wof:name":"Puerto Carmen",
    "wof:placetype":"locality"
},
  "geometry": {"coordinates":[-68.91673,-11.29931],"type":"Point"}
}