{
  "type": "Feature",
  "properties": {
    "gn:admin1_code":"04",
    "gn:asciiname":"Calle",
    "gn:country_code":"BO",
    "gn:dem":1959,
    "gn:feature_class":"P",
    "gn:feature_code":"PPL",
    "gn:name":"Calle",
    "gn:population":0,
    "gn:timezone":"America/La_Paz",
    "iso:country":"BO",
    "name:deu_x_preferred":[
        "Calle"
    ],
    "name:fra_x_preferred":[
        "Calle"
    ],
    "name:glg_x_preferred":[
        "Calle"
    ],
    "name:ita_x_preferred":[
        "Calle"
    ],
    "name:spa_x_preferred":[
        "Calle"
    ],
    "name:srp_x_preferred":[
        "Calle"
    ],
    "wof:name":"Calle",
    "wof:placetype":"locality"
},
  "geometry": {"coordinates":[-68.93333,-14.61667],"type":"Point"}
}