{
  "type": "Feature",
  "properties": {
    "gn:admin1_code":"06",
    "gn:asciiname":"Aguilera",
    "gn:cc2":"BO",
    "gn:country_code":"BO",
    "gn:dem":219,
    "gn:feature_class":"P",
    "gn:feature_code":"PPL",
    "gn:name":"Aguilera",
    "gn:population":0,
    "gn:timezone":"America/La_Paz",
    "iso:country":"BO",
    "name:cat_x_preferred":[
        "Aguilera"
    ],
    "name:ceb_x_preferred":[
        "Aguilera"
    ],
    "name:deu_x_preferred":[
        "Aguilera"
    ],
    "name:fin_x_preferred":[
        "Aguilera"
    ],
    "name:fra_x_preferred":[
        "Aguilera"
    ],
    "name:hsb_x_preferred":[
        "Aguilera"
    ],
    "name:ita_x_preferred":[
        "Aguilera"
    ],
    "name:jpn_x_preferred":[
        "\u30a2\u30ae\u30ec\u30e9"
    ],
    "name:kor_x_preferred":[
        "\uc544\uae38\ub808\ub77c"
    ],
    "name:pol_x_preferred":[
        "Aguilera"
    ],
    "name:rus_x_preferred":[
        "\u0410\u0433\u0438\u043b\u0435\u0440\u0430"
    ],
    "name:slk_x_preferred":[
        "Aguilera"
    ],
    "name:spa_x_preferred":[
        "Aguilera"
    ],
    "name:srp_x_preferred":[
        "\u0410\u0433\u0438\u043b\u0435\u0440\u0430"
    ],
    "name:swe_x_preferred":[
        "Aguilera"
    ],
    "name:ukr_x_preferred":[
        "\u0410\u0433\u0456\u043b\u0435\u0440\u0430"
    ],
    "name:und_x_variant":[
        "Centro Aguilera",
        "Aguilera"
    ],
    "wof:name":"Aguilera",
    "wof:placetype":"locality"
},
  "geometry": {"coordinates":[-68.01666999999999,-11.51667],"type":"Point"}
}