{
  "type": "Feature",
  "properties": {
    "gn:admin1_code":"06",
    "gn:asciiname":"Aguilera",
    "gn:cc2":"BO",
    "gn:country_code":"BO",
    "gn:dem":219,
    "gn:feature_class":"P",
    "gn:feature_code":"PPL",
    "gn:name":"Aguilera",
    "gn:population":0,
    "gn:timezone":"America/La_Paz",
    "iso:country":"BO",
    "name:und_x_variant":[
        "Centro Aguilera",
        "Aguilera"
    ],
    "wof:name":"Aguilera",
    "wof:placetype":"locality"
},
  "geometry": {"coordinates":[-68.01666999999999,-11.51667],"type":"Point"}
}