{
  "type": "Feature",
  "properties": {
    "gn:admin1_code":"04",
    "gn:asciiname":"Cocos Lanza",
    "gn:country_code":"BO",
    "gn:dem":1478,
    "gn:feature_class":"P",
    "gn:feature_code":"PPL",
    "gn:name":"Cocos Lanza",
    "gn:population":0,
    "gn:timezone":"America/La_Paz",
    "iso:country":"BO",
    "wof:name":"Cocos Lanza",
    "wof:placetype":"locality"
},
  "geometry": {"coordinates":[-68.43156,-14.72255],"type":"Point"}
}