{
  "type": "Feature",
  "properties": {
    "gn:admin1_code":"01",
    "gn:asciiname":"Estancia Japu",
    "gn:country_code":"BO",
    "gn:dem":3919,
    "gn:feature_class":"P",
    "gn:feature_code":"PPL",
    "gn:name":"Estancia Japu",
    "gn:population":0,
    "gn:timezone":"America/La_Paz",
    "iso:country":"BO",
    "wof:name":"Estancia Japu",
    "wof:placetype":"locality"
},
  "geometry": {"coordinates":[-64.77580999999999,-20.08076],"type":"Point"}
}