{
  "type": "Feature",
  "properties": {
    "gn:admin1_code":"7.0",
    "gn:asciiname":"Parco",
    "gn:cc2":"BO",
    "gn:country_code":"BO",
    "gn:dem":4327,
    "gn:feature_class":"P",
    "gn:feature_code":"PPL",
    "gn:name":"Parco",
    "gn:population":0,
    "gn:timezone":"America/La_Paz",
    "iso:country":"BO",
    "name:und_x_variant":[
        "Estancia Parco",
        "Parco"
    ],
    "wof:name":"Parco",
    "wof:placetype":"locality"
},
  "geometry": {"coordinates":[-66.71666999999999,-20.28333],"type":"Point"}
}