{
  "type": "Feature",
  "properties": {
    "gn:admin1_code":"4.0",
    "gn:asciiname":"Huancane",
    "gn:country_code":"BO",
    "gn:dem":3815,
    "gn:feature_class":"P",
    "gn:feature_code":"PPL",
    "gn:name":"Huancan\u00e9",
    "gn:population":0,
    "gn:timezone":"America/La_Paz",
    "iso:country":"BO",
    "wof:name":"Huancane",
    "wof:placetype":"locality"
},
  "geometry": {"coordinates":[-68.63333,-16.23333],"type":"Point"}
}