{
  "type": "Feature",
  "properties": {
    "gn:admin1_code":"02",
    "gn:asciiname":"Estancia Cuatro Esquinas",
    "gn:cc2":"BO",
    "gn:country_code":"BO",
    "gn:dem":2614,
    "gn:feature_class":"P",
    "gn:feature_code":"PPL",
    "gn:name":"Estancia Cuatro Esquinas",
    "gn:population":0,
    "gn:timezone":"America/La_Paz",
    "iso:country":"BO",
    "name:und_x_variant":[
        "Estancia Quatro Esquinas",
        "Estancia Cuatro Esquinas"
    ],
    "wof:name":"Estancia Cuatro Esquinas",
    "wof:placetype":"locality"
},
  "geometry": {"coordinates":[-66.21666999999999,-17.35],"type":"Point"}
}