{
  "type": "Feature",
  "properties": {
    "iso:country":"BO",
    "name:ara_x_preferred":[
        "\u0643\u0627\u0645\u064a\u0631\u064a"
    ],
    "name:chi_x_preferred":[
        "\u5361\u7c73\u91cc"
    ],
    "name:dut_x_preferred":[
        "Camiri"
    ],
    "name:eng_x_preferred":[
        "Camiri"
    ],
    "name:fre_x_preferred":[
        "Camiri"
    ],
    "name:geo_x_preferred":[
        "\u10d9\u10d0\u10db\u10d8\u10e0\u10d8"
    ],
    "name:ger_x_preferred":[
        "Camiri"
    ],
    "name:jpn_x_preferred":[
        "\u30ab\u30df\u30ea"
    ],
    "name:nob_x_preferred":[
        "Camiri"
    ],
    "name:per_x_preferred":[
        "\u06a9\u0627\u0645\u06cc\u0631\u06cc"
    ],
    "name:pol_x_preferred":[
        "Camiri"
    ],
    "name:por_x_preferred":[
        "Camiri"
    ],
    "name:que_x_preferred":[
        "Kamiri"
    ],
    "name:rum_x_preferred":[
        "Camiri"
    ],
    "name:spa_x_preferred":[
        "Camiri"
    ],
    "name:swe_x_preferred":[
        "Camiri"
    ],
    "ne:ADM0CAP":0.0,
    "ne:ADM0NAME":"Bolivia",
    "ne:ADM0_A3":"BOL",
    "ne:ADM1NAME":"Santa Cruz",
    "ne:ADMIN1_COD":8,
    "ne:CAPALT":0,
    "ne:CHANGED":1,
    "ne:CHECKME":0,
    "ne:COMPARE":0,
    "ne:DIFFASCII":0,
    "ne:DIFFNOTE":"Changed scale rank.",
    "ne:ELEVATION":0.0,
    "ne:FEATURECLA":"Populated place",
    "ne:FEATURE_CL":"P",
    "ne:FEATURE_CO":"PPL",
    "ne:GEONAMEID":3922414,
    "ne:GEONAMESNO":"GeoNames match with ascii name + lat + long whole numbers.",
    "ne:GN_ASCII":"Camiri",
    "ne:GN_POP":27961,
    "ne:GTOPO30":740.0,
    "ne:ISO_A2":"BO",
    "ne:LABELRANK":6,
    "ne:LATITUDE":-20.050005,
    "ne:LONGITUDE":-63.519984,
    "ne:LS_MATCH":1,
    "ne:LS_NAME":"Camiri",
    "ne:MAX_AREAKM":6.0,
    "ne:MAX_AREAMI":2.0,
    "ne:MAX_BBXMAX":-63.508333,
    "ne:MAX_BBXMIN":-63.533333,
    "ne:MAX_BBYMAX":-20.025,
    "ne:MAX_BBYMIN":-20.05,
    "ne:MAX_NATSCA":10.0,
    "ne:MAX_PERKM":11.0,
    "ne:MAX_PERMI":7.0,
    "ne:MAX_POP10":10464,
    "ne:MAX_POP20":0,
    "ne:MAX_POP300":0,
    "ne:MAX_POP310":0,
    "ne:MAX_POP50":0,
    "ne:MEAN_BBXC":-63.521875,
    "ne:MEAN_BBYC":-20.038542,
    "ne:MEGACITY":0,
    "ne:MIN_AREAKM":6.0,
    "ne:MIN_AREAMI":2.0,
    "ne:MIN_BBXMAX":-63.508333,
    "ne:MIN_BBXMIN":-63.533333,
    "ne:MIN_BBYMAX":-20.025,
    "ne:MIN_BBYMIN":-20.05,
    "ne:MIN_PERKM":11.0,
    "ne:MIN_PERMI":7.0,
    "ne:NAME":"Camiri",
    "ne:NAMEASCII":"Camiri",
    "ne:NAMEDIFF":0,
    "ne:NATSCALE":30,
    "ne:POP1950":0,
    "ne:POP1955":0,
    "ne:POP1960":0,
    "ne:POP1965":0,
    "ne:POP1970":0,
    "ne:POP1975":0,
    "ne:POP1980":0,
    "ne:POP1985":0,
    "ne:POP1990":0,
    "ne:POP1995":0,
    "ne:POP2000":0,
    "ne:POP2005":0,
    "ne:POP2010":0,
    "ne:POP2015":0,
    "ne:POP2020":0,
    "ne:POP2025":0,
    "ne:POP2050":0,
    "ne:POP_MAX":27961,
    "ne:POP_MIN":10464,
    "ne:POP_OTHER":10464,
    "ne:RANK_MAX":7,
    "ne:RANK_MIN":6,
    "ne:SCALERANK":6,
    "ne:SOV0NAME":"Bolivia",
    "ne:SOV_A3":"BOL",
    "ne:TIMEZONE":"America/La_Paz",
    "ne:UN_FID":0,
    "ne:UN_LAT":0.0,
    "ne:UN_LONG":0.0,
    "ne:WORLDCITY":0,
    "ne:min_zoom":6.0,
    "wof:name":"Camiri",
    "wof:placetype":"locality"
},
  "geometry": {"coordinates":[-63.51998356286668,-20.05000486367061],"type":"Point"}
}