{
  "type": "Feature",
  "properties": {
    "gn:admin1_code":"6.0",
    "gn:asciiname":"Verdun",
    "gn:cc2":"BO",
    "gn:country_code":"BO",
    "gn:dem":167,
    "gn:feature_class":"P",
    "gn:feature_code":"PPL",
    "gn:name":"Verd\u00fan",
    "gn:population":0,
    "gn:timezone":"America/La_Paz",
    "iso:country":"BO",
    "name:und_x_variant":[
        "Verdum",
        "Verd\u00fan"
    ],
    "wof:name":"Verdun",
    "wof:placetype":"locality"
},
  "geometry": {"coordinates":[-66.56667,-10.66667],"type":"Point"}
}