{
  "type": "Feature",
  "properties": {
    "gn:admin1_code":"4.0",
    "gn:asciiname":"Hellu-Uta",
    "gn:country_code":"BO",
    "gn:dem":4075,
    "gn:feature_class":"P",
    "gn:feature_code":"PPL",
    "gn:name":"Hellu-Uta",
    "gn:population":0,
    "gn:timezone":"America/La_Paz",
    "iso:country":"BO",
    "wof:name":"Hellu-Uta",
    "wof:placetype":"locality"
},
  "geometry": {"coordinates":[-69.40000000000001,-17.51667],"type":"Point"}
}