{
  "type": "Feature",
  "properties": {
    "gn:admin1_code":"5.0",
    "gn:asciiname":"Lamar Pata",
    "gn:country_code":"BO",
    "gn:dem":3723,
    "gn:feature_class":"P",
    "gn:feature_code":"PPL",
    "gn:name":"Lamar Pata",
    "gn:population":0,
    "gn:timezone":"America/La_Paz",
    "iso:country":"BO",
    "wof:name":"Lamar Pata",
    "wof:placetype":"locality"
},
  "geometry": {"coordinates":[-67.22718,-19.17315],"type":"Point"}
}