{
  "type": "Feature",
  "properties": {
    "gn:admin1_code":"5.0",
    "gn:asciiname":"Tolataca",
    "gn:cc2":"BO",
    "gn:country_code":"BO",
    "gn:dem":4108,
    "gn:feature_class":"P",
    "gn:feature_code":"PPL",
    "gn:name":"Tolataca",
    "gn:population":0,
    "gn:timezone":"America/La_Paz",
    "iso:country":"BO",
    "name:und_x_variant":[
        "Tolalaca",
        "Tolataca"
    ],
    "wof:name":"Tolataca",
    "wof:placetype":"locality"
},
  "geometry": {"coordinates":[-68.76666999999999,-17.93332999999999],"type":"Point"}
}