{
  "type": "Feature",
  "properties": {
    "gn:admin1_code":"06",
    "gn:asciiname":"Pinal",
    "gn:country_code":"BO",
    "gn:dem":222,
    "gn:feature_class":"P",
    "gn:feature_code":"PPL",
    "gn:name":"Pi\u00f1al",
    "gn:population":0,
    "gn:timezone":"America/La_Paz",
    "iso:country":"BO",
    "name:spa_x_preferred":[
        "Pi\u00f1al"
    ],
    "wof:name":"Pinal",
    "wof:placetype":"locality"
},
  "geometry": {"coordinates":[-68.0193,-11.37084],"type":"Point"}
}