{
  "type": "Feature",
  "properties": {
    "gn:admin1_code":"4.0",
    "gn:asciiname":"Toreni",
    "gn:country_code":"BO",
    "gn:dem":4591,
    "gn:feature_class":"P",
    "gn:feature_code":"PPL",
    "gn:name":"Toreni",
    "gn:population":0,
    "gn:timezone":"America/La_Paz",
    "iso:country":"BO",
    "wof:name":"Toreni",
    "wof:placetype":"locality"
},
  "geometry": {"coordinates":[-68.23333000000001,-16.03333],"type":"Point"}
}