{
  "type": "Feature",
  "properties": {
    "gn:admin1_code":"6.0",
    "gn:asciiname":"Puerto Chico",
    "gn:country_code":"BO",
    "gn:dem":174,
    "gn:feature_class":"P",
    "gn:feature_code":"PPL",
    "gn:name":"Puerto Chico",
    "gn:population":0,
    "gn:timezone":"America/La_Paz",
    "iso:country":"BO",
    "wof:name":"Puerto Chico",
    "wof:placetype":"locality"
},
  "geometry": {"coordinates":[-67.58333,-11.05],"type":"Point"}
}