{
  "type": "Feature",
  "properties": {
    "gn:admin1_code":"5.0",
    "gn:asciiname":"Quijina",
    "gn:country_code":"BO",
    "gn:dem":3753,
    "gn:feature_class":"P",
    "gn:feature_code":"PPL",
    "gn:name":"Quijina",
    "gn:population":0,
    "gn:timezone":"America/La_Paz",
    "iso:country":"BO",
    "name:und_x_variant":[
        "Estancia Quijina",
        "Quijina"
    ],
    "wof:name":"Quijina",
    "wof:placetype":"locality"
},
  "geometry": {"coordinates":[-67.673,-19.50076],"type":"Point"}
}