{
  "type": "Feature",
  "properties": {
    "gn:admin1_code":"8.0",
    "gn:asciiname":"Puesto",
    "gn:country_code":"BO",
    "gn:dem":393,
    "gn:feature_class":"P",
    "gn:feature_code":"PPL",
    "gn:name":"Puesto",
    "gn:population":0,
    "gn:timezone":"America/La_Paz",
    "iso:country":"BO",
    "wof:name":"Puesto",
    "wof:placetype":"locality"
},
  "geometry": {"coordinates":[-62.13333000000001,-20.13333],"type":"Point"}
}