{
  "type": "Feature",
  "properties": {
    "gn:admin1_code":"05",
    "gn:asciiname":"Caripaya",
    "gn:country_code":"BO",
    "gn:dem":3822,
    "gn:feature_class":"P",
    "gn:feature_code":"PPL",
    "gn:name":"Caripaya",
    "gn:population":0,
    "gn:timezone":"America/La_Paz",
    "iso:country":"BO",
    "name:und_x_variant":[
        "Estancia Caripaya",
        "Carlpaya",
        "Caripaya"
    ],
    "wof:name":"Caripaya",
    "wof:placetype":"locality"
},
  "geometry": {"coordinates":[-67.82646,-18.47689],"type":"Point"}
}