{
  "type": "Feature",
  "properties": {
    "gn:admin1_code":"6.0",
    "gn:asciiname":"Ultimatum",
    "gn:cc2":"BO",
    "gn:country_code":"BO",
    "gn:dem":136,
    "gn:feature_class":"P",
    "gn:feature_code":"PPL",
    "gn:name":"Ultim\u00e1tum",
    "gn:population":0,
    "gn:timezone":"America/La_Paz",
    "iso:country":"BO",
    "name:und_x_variant":[
        "Ultimatun",
        "Ultim\u00e1tum"
    ],
    "wof:name":"Ultimatum",
    "wof:placetype":"locality"
},
  "geometry": {"coordinates":[-66.93333,-10.16667],"type":"Point"}
}