{
  "type": "Feature",
  "properties": {
    "gn:admin1_code":"6.0",
    "gn:asciiname":"Ultimatum",
    "gn:cc2":"BO",
    "gn:country_code":"BO",
    "gn:dem":136,
    "gn:feature_class":"P",
    "gn:feature_code":"PPL",
    "gn:name":"Ultim\u00e1tum",
    "gn:population":0,
    "gn:timezone":"America/La_Paz",
    "iso:country":"BO",
    "name:ara_x_preferred":[
        "\u0628\u0644\u0627\u063a \u0646\u0647\u0627\u0626\u064a"
    ],
    "name:bel_x_preferred":[
        "\u0423\u043b\u044c\u0442\u044b\u043c\u0430\u0442\u0443\u043c"
    ],
    "name:bos_x_preferred":[
        "Ultimatum"
    ],
    "name:bul_x_preferred":[
        "\u0423\u043b\u0442\u0438\u043c\u0430\u0442\u0443\u043c"
    ],
    "name:cat_x_preferred":[
        "Ultim\u00e0tum"
    ],
    "name:ces_x_preferred":[
        "Ultim\u00e1tum"
    ],
    "name:dan_x_preferred":[
        "Ultimatum"
    ],
    "name:deu_x_preferred":[
        "Ultimatum"
    ],
    "name:ell_x_preferred":[
        "\u03a4\u03b5\u03bb\u03b5\u03c3\u03af\u03b3\u03c1\u03b1\u03c6\u03bf"
    ],
    "name:epo_x_preferred":[
        "Ultimato"
    ],
    "name:est_x_preferred":[
        "Ultimaatum"
    ],
    "name:eus_x_preferred":[
        "Ultimatum"
    ],
    "name:fas_x_preferred":[
        "\u0627\u0648\u0644\u062a\u06cc\u0645\u0627\u062a\u0648\u0645"
    ],
    "name:fin_x_preferred":[
        "Ultimaatumi"
    ],
    "name:fra_x_preferred":[
        "Ultimatum"
    ],
    "name:glg_x_preferred":[
        "Ultimato"
    ],
    "name:heb_x_preferred":[
        "\u05d0\u05d5\u05dc\u05d8\u05d9\u05de\u05d8\u05d5\u05dd"
    ],
    "name:hrv_x_preferred":[
        "Ultimatum"
    ],
    "name:hun_x_preferred":[
        "Ultim\u00e1tum"
    ],
    "name:hye_x_preferred":[
        "\u054e\u0565\u0580\u057b\u0576\u0561\u0563\u056b\u0580"
    ],
    "name:ido_x_preferred":[
        "Ultimato"
    ],
    "name:ind_x_preferred":[
        "Ultimatum"
    ],
    "name:ita_x_preferred":[
        "Ultimatum"
    ],
    "name:jpn_x_preferred":[
        "\u6700\u5f8c\u901a\u7252"
    ],
    "name:kaz_x_preferred":[
        "\u0423\u043b\u044c\u0442\u0438\u043c\u0430\u0442\u0443\u043c"
    ],
    "name:kor_x_preferred":[
        "\ucd5c\ud6c4\ud1b5\ucca9"
    ],
    "name:lav_x_preferred":[
        "Ultim\u0101ts"
    ],
    "name:lit_x_preferred":[
        "Ultimatumas"
    ],
    "name:ltz_x_preferred":[
        "Ultimatum"
    ],
    "name:msa_x_preferred":[
        "Kata dua"
    ],
    "name:nld_x_preferred":[
        "Ultimatum"
    ],
    "name:nno_x_preferred":[
        "Ultimatum"
    ],
    "name:nor_x_preferred":[
        "Ultimatum"
    ],
    "name:pol_x_preferred":[
        "Ultimatum"
    ],
    "name:por_x_preferred":[
        "Ultimato"
    ],
    "name:ron_x_preferred":[
        "Ultimatum"
    ],
    "name:rus_x_preferred":[
        "\u0423\u043b\u044c\u0442\u0438\u043c\u0430\u0442\u0443\u043c"
    ],
    "name:spa_x_preferred":[
        "Ultim\u00e1tum"
    ],
    "name:srp_x_preferred":[
        "\u0423\u043b\u0442\u0438\u043c\u0430\u0442\u0443\u043c"
    ],
    "name:swe_x_preferred":[
        "Ultimatum"
    ],
    "name:tur_x_preferred":[
        "\u00dcltimatom"
    ],
    "name:ukr_x_preferred":[
        "\u0423\u043b\u044c\u0442\u0438\u043c\u0430\u0442\u0443\u043c"
    ],
    "name:und_x_variant":[
        "Ultimatun"
    ],
    "name:uzb_x_preferred":[
        "Ultimatum"
    ],
    "name:zho_x_preferred":[
        "\u6700\u5f8c\u901a\u7252"
    ],
    "wof:name":"Ultimatum",
    "wof:placetype":"locality"
},
  "geometry": {"coordinates":[-66.93333,-10.16667],"type":"Point"}
}