{
  "type": "Feature",
  "properties": {
    "gn:admin1_code":"5.0",
    "gn:asciiname":"Estancia Tulu Tulluni",
    "gn:country_code":"BO",
    "gn:dem":3888,
    "gn:feature_class":"P",
    "gn:feature_code":"PPL",
    "gn:name":"Estancia Tulu Tulluni",
    "gn:population":0,
    "gn:timezone":"America/La_Paz",
    "iso:country":"BO",
    "wof:name":"Estancia Tulu Tulluni",
    "wof:placetype":"locality"
},
  "geometry": {"coordinates":[-67.69141999999999,-18.18302000000001],"type":"Point"}
}