{
  "type": "Feature",
  "properties": {
    "gn:admin1_code":"04",
    "gn:asciiname":"Estancia Catavi",
    "gn:country_code":"BO",
    "gn:dem":4031,
    "gn:feature_class":"P",
    "gn:feature_code":"PPL",
    "gn:name":"Estancia Catavi",
    "gn:population":0,
    "gn:timezone":"America/La_Paz",
    "iso:country":"BO",
    "wof:name":"Estancia Catavi",
    "wof:placetype":"locality"
},
  "geometry": {"coordinates":[-69.33333,-17.63332999999999],"type":"Point"}
}