{
  "type": "Feature",
  "properties": {
    "gn:admin1_code":"03",
    "gn:asciiname":"Luis Flores",
    "gn:cc2":"BR",
    "gn:country_code":"BO",
    "gn:dem":132,
    "gn:feature_class":"P",
    "gn:feature_code":"PPL",
    "gn:name":"Lu\u00eds Flores",
    "gn:population":0,
    "gn:timezone":"America/Porto_Velho",
    "iso:country":"BO",
    "name:und_x_variant":[
        "Manoel",
        "Manuel",
        "Luiz Fl\u00f5res",
        "Lu\u00eds Flores"
    ],
    "wof:name":"Luis Flores",
    "wof:placetype":"locality"
},
  "geometry": {"coordinates":[-65.36667,-11.28333],"type":"Point"}
}