{
  "type": "Feature",
  "properties": {
    "gn:admin1_code":"03",
    "gn:asciiname":"Luis Flores",
    "gn:cc2":"BR",
    "gn:country_code":"BO",
    "gn:dem":132,
    "gn:feature_class":"P",
    "gn:feature_code":"PPL",
    "gn:name":"Lu\u00eds Flores",
    "gn:population":0,
    "gn:timezone":"America/Porto_Velho",
    "iso:country":"BO",
    "name:deu_x_preferred":[
        "Luis Flores"
    ],
    "name:fra_x_preferred":[
        "Luis Flores"
    ],
    "name:ita_x_preferred":[
        "Luis Flores"
    ],
    "name:jpn_x_preferred":[
        "\u30eb\u30a4\u30b9\u30fb\u30d5\u30ed\u30fc\u30ec\u30b9"
    ],
    "name:por_x_preferred":[
        "Luis Flores"
    ],
    "name:spa_x_preferred":[
        "Luis Flores"
    ],
    "name:und_x_variant":[
        "Manoel",
        "Manuel",
        "Luiz Fl\u00f5res",
        "Lu\u00eds Flores"
    ],
    "wof:name":"Luis Flores",
    "wof:placetype":"locality"
},
  "geometry": {"coordinates":[-65.36667,-11.28333],"type":"Point"}
}