{
  "type": "Feature",
  "properties": {
    "gn:admin1_code":"01",
    "gn:asciiname":"Colpamayu",
    "gn:country_code":"BO",
    "gn:dem":1604,
    "gn:feature_class":"P",
    "gn:feature_code":"PPL",
    "gn:name":"Colpamayu",
    "gn:population":0,
    "gn:timezone":"America/La_Paz",
    "iso:country":"BO",
    "wof:name":"Colpamayu",
    "wof:placetype":"locality"
},
  "geometry": {"coordinates":[-64.59999999999999,-20.05],"type":"Point"}
}