{
  "type": "Feature",
  "properties": {
    "gn:admin1_code":"1.0",
    "gn:asciiname":"Rum",
    "gn:country_code":"BO",
    "gn:dem":2932,
    "gn:feature_class":"P",
    "gn:feature_code":"PPL",
    "gn:name":"Rum",
    "gn:population":0,
    "gn:timezone":"America/La_Paz",
    "iso:country":"BO",
    "wof:name":"Rum",
    "wof:placetype":"locality"
},
  "geometry": {"coordinates":[-64.98333000000001,-20.83333],"type":"Point"}
}