{
  "type": "Feature",
  "properties": {
    "gn:admin1_code":"4.0",
    "gn:asciiname":"Laurani",
    "gn:country_code":"BO",
    "gn:dem":4239,
    "gn:feature_class":"P",
    "gn:feature_code":"PPL",
    "gn:name":"Laurani",
    "gn:population":0,
    "gn:timezone":"America/La_Paz",
    "iso:country":"BO",
    "wof:name":"Laurani",
    "wof:placetype":"locality"
},
  "geometry": {"coordinates":[-67.33333,-17.21667],"type":"Point"}
}