{
  "type": "Feature",
  "properties": {
    "gn:admin1_code":"4.0",
    "gn:asciiname":"Tuni",
    "gn:country_code":"BO",
    "gn:dem":4090,
    "gn:feature_class":"P",
    "gn:feature_code":"PPL",
    "gn:name":"Tuni",
    "gn:population":0,
    "gn:timezone":"America/La_Paz",
    "iso:country":"BO",
    "wof:name":"Tuni",
    "wof:placetype":"locality"
},
  "geometry": {"coordinates":[-68.13333,-16.66667],"type":"Point"}
}