{
  "type": "Feature",
  "properties": {
    "gn:admin1_code":"4.0",
    "gn:asciiname":"Tuni",
    "gn:country_code":"BO",
    "gn:dem":4090,
    "gn:feature_class":"P",
    "gn:feature_code":"PPL",
    "gn:name":"Tuni",
    "gn:population":0,
    "gn:timezone":"America/La_Paz",
    "iso:country":"BO",
    "name:bpy_x_preferred":[
        "\u09a4\u09c1\u09a8\u09bf"
    ],
    "name:ceb_x_preferred":[
        "Tuni"
    ],
    "name:ita_x_preferred":[
        "Tuni"
    ],
    "name:msa_x_preferred":[
        "Tuni"
    ],
    "name:new_x_preferred":[
        "\u0924\u0941\u0928\u093f \u092e\u0923\u094d\u0921\u0932"
    ],
    "name:por_x_preferred":[
        "Tuni"
    ],
    "name:swe_x_preferred":[
        "Tuni"
    ],
    "name:tel_x_preferred":[
        "\u0c24\u0c41\u0c28\u0c3f"
    ],
    "name:tgl_x_preferred":[
        "Tuni"
    ],
    "name:urd_x_preferred":[
        "\u062a\u0648\u0646\u06cc"
    ],
    "name:vie_x_preferred":[
        "Tuni"
    ],
    "wof:name":"Tuni",
    "wof:placetype":"locality"
},
  "geometry": {"coordinates":[-68.13333,-16.66667],"type":"Point"}
}