{
  "type": "Feature",
  "properties": {
    "gn:admin1_code":"06",
    "gn:asciiname":"Caramani",
    "gn:country_code":"BO",
    "gn:dem":213,
    "gn:feature_class":"P",
    "gn:feature_code":"PPL",
    "gn:name":"Caramani",
    "gn:population":0,
    "gn:timezone":"America/La_Paz",
    "iso:country":"BO",
    "name:spa_x_preferred":[
        "Caramani"
    ],
    "name:und_x_variant":[
        "Karamanito",
        "Caramanito"
    ],
    "wof:name":"Caramani",
    "wof:placetype":"locality"
},
  "geometry": {"coordinates":[-68.1613,-11.12642],"type":"Point"}
}