{
  "type": "Feature",
  "properties": {
    "gn:admin1_code":"5.0",
    "gn:asciiname":"Tuntola",
    "gn:country_code":"BO",
    "gn:dem":4477,
    "gn:feature_class":"P",
    "gn:feature_code":"PPL",
    "gn:name":"Tuntola",
    "gn:population":0,
    "gn:timezone":"America/La_Paz",
    "iso:country":"BO",
    "wof:name":"Tuntola",
    "wof:placetype":"locality"
},
  "geometry": {"coordinates":[-66.59999999999999,-18.83333],"type":"Point"}
}