{
  "type": "Feature",
  "properties": {
    "gn:admin1_code":"5.0",
    "gn:asciiname":"Tambo Quemado",
    "gn:country_code":"BO",
    "gn:dem":4679,
    "gn:feature_class":"P",
    "gn:feature_code":"PPL",
    "gn:name":"Tambo Quemado",
    "gn:population":0,
    "gn:timezone":"America/La_Paz",
    "iso:country":"BO",
    "wof:name":"Tambo Quemado",
    "wof:placetype":"locality"
},
  "geometry": {"coordinates":[-69.03333000000001,-18.26667],"type":"Point"}
}