{
  "type": "Feature",
  "properties": {
    "gn:admin1_code":"4.0",
    "gn:asciiname":"Tolacica",
    "gn:cc2":"BO",
    "gn:country_code":"BO",
    "gn:dem":3752,
    "gn:feature_class":"P",
    "gn:feature_code":"PPL",
    "gn:name":"Tolacica",
    "gn:population":0,
    "gn:timezone":"America/La_Paz",
    "iso:country":"BO",
    "name:und_x_variant":[
        "Tolacirco",
        "Tolacica"
    ],
    "wof:name":"Tolacica",
    "wof:placetype":"locality"
},
  "geometry": {"coordinates":[-67.88333,-17.33333],"type":"Point"}
}