{
  "type": "Feature",
  "properties": {
    "gn:admin1_code":"1.0",
    "gn:asciiname":"Torcotarca",
    "gn:cc2":"BO",
    "gn:country_code":"BO",
    "gn:dem":1818,
    "gn:feature_class":"P",
    "gn:feature_code":"PPL",
    "gn:name":"Torcotarca",
    "gn:population":0,
    "gn:timezone":"America/La_Paz",
    "iso:country":"BO",
    "name:und_x_variant":[
        "Torcotorca",
        "Torco-torcoa",
        "Torcotarca"
    ],
    "wof:name":"Torcotarca",
    "wof:placetype":"locality"
},
  "geometry": {"coordinates":[-64.75,-18.81667],"type":"Point"}
}