{
  "type": "Feature",
  "properties": {
    "gn:admin1_code":"7.0",
    "gn:asciiname":"Estancia Vargas",
    "gn:country_code":"BO",
    "gn:dem":3036,
    "gn:feature_class":"P",
    "gn:feature_code":"PPL",
    "gn:name":"Estancia Vargas",
    "gn:population":0,
    "gn:timezone":"America/La_Paz",
    "iso:country":"BO",
    "wof:name":"Estancia Vargas",
    "wof:placetype":"locality"
},
  "geometry": {"coordinates":[-65.37921999999999,-20.22404],"type":"Point"}
}