{
  "type": "Feature",
  "properties": {
    "gn:admin1_code":"7.0",
    "gn:asciiname":"Estancia Waca",
    "gn:country_code":"BO",
    "gn:dem":3652,
    "gn:feature_class":"P",
    "gn:feature_code":"PPL",
    "gn:name":"Estancia Waca",
    "gn:population":0,
    "gn:timezone":"America/La_Paz",
    "iso:country":"BO",
    "wof:name":"Estancia Waca",
    "wof:placetype":"locality"
},
  "geometry": {"coordinates":[-66.3291,-20.12528],"type":"Point"}
}