{
  "type": "Feature",
  "properties": {
    "gn:admin1_code":"6.0",
    "gn:asciiname":"Belmonte",
    "gn:country_code":"BO",
    "gn:dem":136,
    "gn:feature_class":"P",
    "gn:feature_code":"PPL",
    "gn:name":"Belmonte",
    "gn:population":0,
    "gn:timezone":"America/La_Paz",
    "iso:country":"BO",
    "wof:name":"Belmonte",
    "wof:placetype":"locality"
},
  "geometry": {"coordinates":[-66.26666999999999,-9.85],"type":"Point"}
}