{
  "type": "Feature",
  "properties": {
    "gn:admin1_code":"05",
    "gn:asciiname":"Chiar Kollu",
    "gn:country_code":"BO",
    "gn:dem":3685,
    "gn:feature_class":"P",
    "gn:feature_code":"PPL",
    "gn:name":"Chiar Kollu",
    "gn:population":0,
    "gn:timezone":"America/La_Paz",
    "iso:country":"BO",
    "name:und_x_variant":[
        "Estancia Chiarcollo",
        "Chiar Kollu"
    ],
    "wof:name":"Chiar Kollu",
    "wof:placetype":"locality"
},
  "geometry": {"coordinates":[-68.02454,-19.71838],"type":"Point"}
}