{
  "type": "Feature",
  "properties": {
    "gn:admin1_code":"4.0",
    "gn:asciiname":"Pococata",
    "gn:country_code":"BO",
    "gn:dem":3835,
    "gn:feature_class":"P",
    "gn:feature_code":"PPL",
    "gn:name":"Pococata",
    "gn:population":0,
    "gn:timezone":"America/La_Paz",
    "iso:country":"BO",
    "name:und_x_variant":[
        "Estancia Pococata",
        "Pococata"
    ],
    "wof:name":"Pococata",
    "wof:placetype":"locality"
},
  "geometry": {"coordinates":[-69.23888000000001,-15.57564],"type":"Point"}
}