{
  "type": "Feature",
  "properties": {
    "gn:admin1_code":"07",
    "gn:asciiname":"Ajtara",
    "gn:country_code":"BO",
    "gn:dem":3474,
    "gn:feature_class":"P",
    "gn:feature_code":"PPL",
    "gn:name":"Ajtara",
    "gn:population":0,
    "gn:timezone":"America/La_Paz",
    "iso:country":"BO",
    "wof:name":"Ajtara",
    "wof:placetype":"locality"
},
  "geometry": {"coordinates":[-65.96176,-19.07315],"type":"Point"}
}