{
  "type": "Feature",
  "properties": {
    "gn:admin1_code":"8.0",
    "gn:asciiname":"Santa Rosita",
    "gn:country_code":"BO",
    "gn:dem":395,
    "gn:feature_class":"P",
    "gn:feature_code":"PPL",
    "gn:name":"Santa Rosita",
    "gn:population":0,
    "gn:timezone":"America/La_Paz",
    "iso:country":"BO",
    "name:ceb_x_preferred":[
        "Santa Rosita"
    ],
    "name:srp_x_preferred":[
        "\u0421\u0430\u043d\u0442\u0430 \u0420\u043e\u0441\u0438\u0442\u0430"
    ],
    "name:swe_x_preferred":[
        "Santa Rosita"
    ],
    "wof:name":"Santa Rosita",
    "wof:placetype":"locality"
},
  "geometry": {"coordinates":[-61.58333,-16.91667],"type":"Point"}
}