{
  "type": "Feature",
  "properties": {
    "gn:admin1_code":"4.0",
    "gn:asciiname":"Sivincani",
    "gn:cc2":"BO",
    "gn:country_code":"BO",
    "gn:dem":4005,
    "gn:feature_class":"P",
    "gn:feature_code":"PPL",
    "gn:name":"Sivincani",
    "gn:population":0,
    "gn:timezone":"America/La_Paz",
    "iso:country":"BO",
    "name:und_x_variant":[
        "Comunidad Sihuicani",
        "Sivincani"
    ],
    "wof:name":"Sivincani",
    "wof:placetype":"locality"
},
  "geometry": {"coordinates":[-68.18333,-16.98333],"type":"Point"}
}