{
  "type": "Feature",
  "properties": {
    "gn:admin1_code":"05",
    "gn:asciiname":"Catuyo",
    "gn:country_code":"BO",
    "gn:dem":3749,
    "gn:feature_class":"P",
    "gn:feature_code":"PPL",
    "gn:name":"Catuyo",
    "gn:population":0,
    "gn:timezone":"America/La_Paz",
    "iso:country":"BO",
    "name:und_x_variant":[
        "Estancia Catuyo",
        "Catuyo"
    ],
    "wof:name":"Catuyo",
    "wof:placetype":"locality"
},
  "geometry": {"coordinates":[-67.50329000000001,-18.48852],"type":"Point"}
}