{
  "type": "Feature",
  "properties": {
    "gn:admin1_code":"08",
    "gn:asciiname":"Canada Honda",
    "gn:country_code":"BO",
    "gn:dem":282,
    "gn:feature_class":"P",
    "gn:feature_code":"PPL",
    "gn:name":"Ca\u00f1ada Honda",
    "gn:population":0,
    "gn:timezone":"America/La_Paz",
    "iso:country":"BO",
    "wof:name":"Canada Honda",
    "wof:placetype":"locality"
},
  "geometry": {"coordinates":[-62.55,-17.55],"type":"Point"}
}