{
  "type": "Feature",
  "properties": {
    "gn:admin1_code":"01",
    "gn:asciiname":"Estancia Ucu Lacani",
    "gn:country_code":"BO",
    "gn:dem":3174,
    "gn:feature_class":"P",
    "gn:feature_code":"PPL",
    "gn:name":"Estancia Ucu Lacani",
    "gn:population":0,
    "gn:timezone":"America/La_Paz",
    "iso:country":"BO",
    "wof:name":"Estancia Ucu Lacani",
    "wof:placetype":"locality"
},
  "geometry": {"coordinates":[-65.37210999999999,-19.19149],"type":"Point"}
}