{
  "type": "Feature",
  "properties": {
    "gn:admin1_code":"06",
    "gn:asciiname":"Cafesal",
    "gn:country_code":"BO",
    "gn:dem":195,
    "gn:feature_class":"P",
    "gn:feature_code":"PPL",
    "gn:name":"Cafesal",
    "gn:population":0,
    "gn:timezone":"America/La_Paz",
    "iso:country":"BO",
    "name:spa_x_preferred":[
        "Cafesal"
    ],
    "wof:name":"Cafesal",
    "wof:placetype":"locality"
},
  "geometry": {"coordinates":[-67.97757,-10.83805],"type":"Point"}
}