{
  "type": "Feature",
  "properties": {
    "gn:admin1_code":"1.0",
    "gn:asciiname":"Molle Pata",
    "gn:country_code":"BO",
    "gn:dem":2391,
    "gn:feature_class":"P",
    "gn:feature_code":"PPL",
    "gn:name":"Molle Pata",
    "gn:population":0,
    "gn:timezone":"America/La_Paz",
    "iso:country":"BO",
    "wof:name":"Molle Pata",
    "wof:placetype":"locality"
},
  "geometry": {"coordinates":[-64.61667,-20.38333],"type":"Point"}
}