{
  "type": "Feature",
  "properties": {
    "gn:admin1_code":"8.0",
    "gn:asciiname":"El Puquio",
    "gn:cc2":"BO",
    "gn:country_code":"BO",
    "gn:dem":83,
    "gn:feature_class":"P",
    "gn:feature_code":"PPL",
    "gn:name":"El Puquio",
    "gn:population":0,
    "gn:timezone":"America/La_Paz",
    "iso:country":"BO",
    "name:und_x_variant":[
        "Puquio",
        "El Puquio"
    ],
    "wof:name":"El Puquio",
    "wof:placetype":"locality"
},
  "geometry": {"coordinates":[-57.93333000000001,-19.26667],"type":"Point"}
}