{
  "type": "Feature",
  "properties": {
    "gn:admin1_code":"01",
    "gn:asciiname":"Estancia Kehuina Mayu",
    "gn:country_code":"BO",
    "gn:dem":2551,
    "gn:feature_class":"P",
    "gn:feature_code":"PPL",
    "gn:name":"Estancia Kehui\u00f1a Mayu",
    "gn:population":0,
    "gn:timezone":"America/La_Paz",
    "iso:country":"BO",
    "wof:name":"Estancia Kehuina Mayu",
    "wof:placetype":"locality"
},
  "geometry": {"coordinates":[-64.79007,-20.25334],"type":"Point"}
}