{
  "type": "Feature",
  "properties": {
    "gn:admin1_code":"06",
    "gn:asciiname":"Centro Obrero",
    "gn:country_code":"BO",
    "gn:dem":279,
    "gn:feature_class":"P",
    "gn:feature_code":"PPL",
    "gn:name":"Centro Obrero",
    "gn:population":0,
    "gn:timezone":"America/La_Paz",
    "iso:country":"BO",
    "wof:name":"Centro Obrero",
    "wof:placetype":"locality"
},
  "geometry": {"coordinates":[-69.01158000000001,-11.35833],"type":"Point"}
}