{
  "type": "Feature",
  "properties": {
    "gn:admin1_code":"2.0",
    "gn:asciiname":"Salsuri",
    "gn:cc2":"BO",
    "gn:country_code":"BO",
    "gn:dem":4110,
    "gn:feature_class":"P",
    "gn:feature_code":"PPL",
    "gn:name":"Salsuri",
    "gn:population":0,
    "gn:timezone":"America/La_Paz",
    "iso:country":"BO",
    "name:und_x_variant":[
        "Salcuri",
        "Salsuri"
    ],
    "wof:name":"Salsuri",
    "wof:placetype":"locality"
},
  "geometry": {"coordinates":[-65.45,-17.46667],"type":"Point"}
}