{
  "type": "Feature",
  "properties": {
    "gn:admin1_code":"4.0",
    "gn:asciiname":"Karawilque",
    "gn:cc2":"BO",
    "gn:country_code":"BO",
    "gn:dem":3974,
    "gn:feature_class":"P",
    "gn:feature_code":"PPL",
    "gn:name":"Karawilque",
    "gn:population":0,
    "gn:timezone":"America/La_Paz",
    "iso:country":"BO",
    "name:und_x_variant":[
        "Karavilque",
        "Karawilque"
    ],
    "wof:name":"Karawilque",
    "wof:placetype":"locality"
},
  "geometry": {"coordinates":[-69.03333000000001,-17.18333],"type":"Point"}
}