{
  "type": "Feature",
  "properties": {
    "gn:admin1_code":"4.0",
    "gn:asciiname":"Pisirapina",
    "gn:cc2":"BO",
    "gn:country_code":"BO",
    "gn:dem":4012,
    "gn:feature_class":"P",
    "gn:feature_code":"PPL",
    "gn:name":"Pisirapi\u00f1a",
    "gn:population":0,
    "gn:timezone":"America/La_Paz",
    "iso:country":"BO",
    "name:und_x_variant":[
        "Pisacapi\u00f1a",
        "Pisamapi\u00f1a",
        "Pisirapi\u00f1a"
    ],
    "wof:name":"Pisirapina",
    "wof:placetype":"locality"
},
  "geometry": {"coordinates":[-68.18333,-17.01667],"type":"Point"}
}