{
  "type": "Feature",
  "properties": {
    "gn:admin1_code":"1.0",
    "gn:admin2_code":"101.0",
    "gn:admin3_code":"1.0",
    "gn:admin4_code":"11.0",
    "gn:asciiname":"Maragua",
    "gn:country_code":"BO",
    "gn:dem":3104,
    "gn:feature_class":"P",
    "gn:feature_code":"PPLA4",
    "gn:name":"Maragua",
    "gn:population":0,
    "gn:timezone":"America/La_Paz",
    "iso:country":"BO",
    "name:ceb_x_preferred":[
        "Maragua"
    ],
    "name:deu_x_preferred":[
        "Maragua"
    ],
    "name:fas_x_preferred":[
        "\u0645\u0627\u0631\u0627\u06af\u0648\u0626\u0627"
    ],
    "name:ita_x_preferred":[
        "Maragua"
    ],
    "name:nld_x_preferred":[
        "Maragua"
    ],
    "name:nor_x_preferred":[
        "Maragua"
    ],
    "name:pol_x_preferred":[
        "Maragua"
    ],
    "name:por_x_preferred":[
        "Maragua"
    ],
    "name:spa_x_preferred":[
        "Maragua"
    ],
    "name:swa_x_preferred":[
        "Maragua"
    ],
    "name:swe_x_preferred":[
        "Maragua"
    ],
    "name:zho_x_preferred":[
        "\u99ac\u62c9\u74dc"
    ],
    "wof:name":"Maragua",
    "wof:placetype":"locality"
},
  "geometry": {"coordinates":[-65.42860999999999,-19.04611],"type":"Point"}
}