{
  "type": "Feature",
  "properties": {
    "gn:admin1_code":"1.0",
    "gn:admin2_code":"101.0",
    "gn:admin3_code":"1.0",
    "gn:admin4_code":"11.0",
    "gn:asciiname":"Maragua",
    "gn:country_code":"BO",
    "gn:dem":3104,
    "gn:feature_class":"P",
    "gn:feature_code":"PPLA4",
    "gn:name":"Maragua",
    "gn:population":0,
    "gn:timezone":"America/La_Paz",
    "iso:country":"BO",
    "wof:name":"Maragua",
    "wof:placetype":"locality"
},
  "geometry": {"coordinates":[-65.42860999999999,-19.04611],"type":"Point"}
}