{
  "type": "Feature",
  "properties": {
    "gn:admin1_code":"4.0",
    "gn:asciiname":"Estancia Taypi Kkollu",
    "gn:country_code":"BO",
    "gn:dem":3819,
    "gn:feature_class":"P",
    "gn:feature_code":"PPL",
    "gn:name":"Estancia Taypi Kkollu",
    "gn:population":0,
    "gn:timezone":"America/La_Paz",
    "iso:country":"BO",
    "wof:name":"Estancia Taypi Kkollu",
    "wof:placetype":"locality"
},
  "geometry": {"coordinates":[-68.21666999999999,-17.45],"type":"Point"}
}