{
  "type": "Feature",
  "properties": {
    "gn:admin1_code":"9.0",
    "gn:asciiname":"Simon",
    "gn:country_code":"BO",
    "gn:dem":431,
    "gn:feature_class":"P",
    "gn:feature_code":"PPL",
    "gn:name":"Sim\u00f3n",
    "gn:population":0,
    "gn:timezone":"America/La_Paz",
    "iso:country":"BO",
    "name:ara_x_preferred":[
        "\u0633\u064a\u0645\u0648\u0646"
    ],
    "name:ceb_x_preferred":[
        "Simon"
    ],
    "name:ces_x_preferred":[
        "Simon"
    ],
    "name:deu_x_preferred":[
        "Simon"
    ],
    "name:eus_x_preferred":[
        "Simon"
    ],
    "name:fas_x_preferred":[
        "\u0633\u06cc\u0645\u0648\u0646"
    ],
    "name:fin_x_preferred":[
        "Simon"
    ],
    "name:fra_x_preferred":[
        "Simon"
    ],
    "name:heb_x_preferred":[
        "\u05e1\u05d9\u05d9\u05de\u05d5\u05df"
    ],
    "name:ind_x_preferred":[
        "Simon"
    ],
    "name:ita_x_preferred":[
        "Simon"
    ],
    "name:jpn_x_preferred":[
        "\u30b5\u30a4\u30e2\u30f3"
    ],
    "name:lav_x_preferred":[
        "Simon"
    ],
    "name:mkd_x_preferred":[
        "\u0428\u0438\u043c\u043e\u043d"
    ],
    "name:nld_x_preferred":[
        "Simon"
    ],
    "name:rus_x_preferred":[
        "Simon"
    ],
    "name:slk_x_preferred":[
        "Simon"
    ],
    "name:spa_x_preferred":[
        "Simon"
    ],
    "name:srp_x_preferred":[
        "\u0428\u0438\u043c\u043e\u043d"
    ],
    "name:swe_x_preferred":[
        "Simon"
    ],
    "wof:name":"Simon",
    "wof:placetype":"locality"
},
  "geometry": {"coordinates":[-63.48333,-21.28333],"type":"Point"}
}