{
  "type": "Feature",
  "properties": {
    "gn:admin1_code":"9.0",
    "gn:asciiname":"Simon",
    "gn:country_code":"BO",
    "gn:dem":431,
    "gn:feature_class":"P",
    "gn:feature_code":"PPL",
    "gn:name":"Sim\u00f3n",
    "gn:population":0,
    "gn:timezone":"America/La_Paz",
    "iso:country":"BO",
    "wof:name":"Simon",
    "wof:placetype":"locality"
},
  "geometry": {"coordinates":[-63.48333,-21.28333],"type":"Point"}
}