{
  "type": "Feature",
  "properties": {
    "gn:admin1_code":"6.0",
    "gn:asciiname":"Versalles",
    "gn:country_code":"BO",
    "gn:dem":184,
    "gn:feature_class":"P",
    "gn:feature_code":"PPL",
    "gn:name":"Versalles",
    "gn:population":0,
    "gn:timezone":"America/La_Paz",
    "iso:country":"BO",
    "wof:name":"Versalles",
    "wof:placetype":"locality"
},
  "geometry": {"coordinates":[-68.13994,-11.50256],"type":"Point"}
}