{
  "type": "Feature",
  "properties": {
    "gn:admin1_code":"7.0",
    "gn:asciiname":"Iruni",
    "gn:country_code":"BO",
    "gn:dem":3335,
    "gn:feature_class":"P",
    "gn:feature_code":"PPL",
    "gn:name":"Iruni",
    "gn:population":0,
    "gn:timezone":"America/La_Paz",
    "iso:country":"BO",
    "wof:name":"Iruni",
    "wof:placetype":"locality"
},
  "geometry": {"coordinates":[-66.07771,-20.04182],"type":"Point"}
}