{
  "type": "Feature",
  "properties": {
    "gn:admin1_code":"9.0",
    "gn:asciiname":"La Trampa del Tigre",
    "gn:country_code":"BO",
    "gn:dem":407,
    "gn:feature_class":"P",
    "gn:feature_code":"PPL",
    "gn:name":"La Trampa del Tigre",
    "gn:population":0,
    "gn:timezone":"America/La_Paz",
    "iso:country":"BO",
    "name:und_x_variant":[
        "Trampa del Tigre",
        "El Tigre",
        "La Trampa del Tigre"
    ],
    "wof:name":"La Trampa del Tigre",
    "wof:placetype":"locality"
},
  "geometry": {"coordinates":[-63.38048000000001,-21.2512],"type":"Point"}
}