{
  "type": "Feature",
  "properties": {
    "gn:admin1_code":"7.0",
    "gn:asciiname":"Huylayaqui",
    "gn:country_code":"BO",
    "gn:dem":3934,
    "gn:feature_class":"P",
    "gn:feature_code":"PPL",
    "gn:name":"Huylayaqui",
    "gn:population":0,
    "gn:timezone":"America/La_Paz",
    "iso:country":"BO",
    "wof:name":"Huylayaqui",
    "wof:placetype":"locality"
},
  "geometry": {"coordinates":[-66.71418,-21.21746],"type":"Point"}
}