{
  "type": "Feature",
  "properties": {
    "gn:admin1_code":"01",
    "gn:asciiname":"Estancia Alizar",
    "gn:country_code":"BO",
    "gn:dem":2350,
    "gn:feature_class":"P",
    "gn:feature_code":"PPL",
    "gn:name":"Estancia Alizar",
    "gn:population":0,
    "gn:timezone":"America/La_Paz",
    "iso:country":"BO",
    "wof:name":"Estancia Alizar",
    "wof:placetype":"locality"
},
  "geometry": {"coordinates":[-64.53851,-20.83112],"type":"Point"}
}