{
  "type": "Feature",
  "properties": {
    "gn:admin1_code":"9.0",
    "gn:asciiname":"Lago Seco",
    "gn:country_code":"BO",
    "gn:dem":1569,
    "gn:feature_class":"P",
    "gn:feature_code":"PPL",
    "gn:name":"Lago Seco",
    "gn:population":0,
    "gn:timezone":"America/La_Paz",
    "iso:country":"BO",
    "wof:name":"Lago Seco",
    "wof:placetype":"locality"
},
  "geometry": {"coordinates":[-63.91667,-21.36667000000001],"type":"Point"}
}