{
  "type": "Feature",
  "properties": {
    "gn:admin1_code":"4.0",
    "gn:asciiname":"Paturani",
    "gn:cc2":"BO",
    "gn:country_code":"BO",
    "gn:dem":3864,
    "gn:feature_class":"P",
    "gn:feature_code":"PPL",
    "gn:name":"Paturani",
    "gn:population":0,
    "gn:timezone":"America/La_Paz",
    "iso:country":"BO",
    "name:und_x_variant":[
        "Comunidad Patarani",
        "Patarani",
        "Paturani"
    ],
    "wof:name":"Paturani",
    "wof:placetype":"locality"
},
  "geometry": {"coordinates":[-68.01666999999999,-17.23333],"type":"Point"}
}