{
  "type": "Feature",
  "properties": {
    "gn:admin1_code":"06",
    "gn:asciiname":"Paraguay",
    "gn:country_code":"BO",
    "gn:dem":272,
    "gn:feature_class":"P",
    "gn:feature_code":"PPL",
    "gn:name":"Paraguay",
    "gn:population":0,
    "gn:timezone":"America/La_Paz",
    "iso:country":"BO",
    "wof:name":"Paraguay",
    "wof:placetype":"locality"
},
  "geometry": {"coordinates":[-69.44271999999999,-10.97648],"type":"Point"}
}