{
  "type": "Feature",
  "properties": {
    "gn:admin1_code":"7.0",
    "gn:asciiname":"Korisaya",
    "gn:country_code":"BO",
    "gn:dem":3792,
    "gn:feature_class":"P",
    "gn:feature_code":"PPL",
    "gn:name":"Korisaya",
    "gn:population":0,
    "gn:timezone":"America/La_Paz",
    "iso:country":"BO",
    "wof:name":"Korisaya",
    "wof:placetype":"locality"
},
  "geometry": {"coordinates":[-65.95222,-20.01862],"type":"Point"}
}