{
  "type": "Feature",
  "properties": {
    "gn:admin1_code":"7.0",
    "gn:asciiname":"Yanacasa",
    "gn:country_code":"BO",
    "gn:dem":3760,
    "gn:feature_class":"P",
    "gn:feature_code":"PPL",
    "gn:name":"Yanacasa",
    "gn:population":0,
    "gn:timezone":"America/La_Paz",
    "iso:country":"BO",
    "wof:name":"Yanacasa",
    "wof:placetype":"locality"
},
  "geometry": {"coordinates":[-66.25,-20.56667],"type":"Point"}
}