{
  "type": "Feature",
  "properties": {
    "gn:admin1_code":"03",
    "gn:asciiname":"Copaiba",
    "gn:country_code":"BO",
    "gn:dem":177,
    "gn:feature_class":"P",
    "gn:feature_code":"PPL",
    "gn:name":"Copaiba",
    "gn:population":0,
    "gn:timezone":"America/La_Paz",
    "iso:country":"BO",
    "wof:name":"Copaiba",
    "wof:placetype":"locality"
},
  "geometry": {"coordinates":[-67.23333000000001,-14.35],"type":"Point"}
}