{
  "type": "Feature",
  "properties": {
    "gn:admin1_code":"3.0",
    "gn:asciiname":"Toney",
    "gn:country_code":"BO",
    "gn:dem":792,
    "gn:feature_class":"P",
    "gn:feature_code":"PPL",
    "gn:name":"Toney",
    "gn:population":0,
    "gn:timezone":"America/La_Paz",
    "iso:country":"BO",
    "wof:name":"Toney",
    "wof:placetype":"locality"
},
  "geometry": {"coordinates":[-67.05,-15.45],"type":"Point"}
}