{
  "type": "Feature",
  "properties": {
    "gn:admin1_code":"4.0",
    "gn:asciiname":"Guayguasi",
    "gn:cc2":"BO",
    "gn:country_code":"BO",
    "gn:dem":3509,
    "gn:feature_class":"P",
    "gn:feature_code":"PPL",
    "gn:name":"Guayguasi",
    "gn:population":0,
    "gn:timezone":"America/La_Paz",
    "iso:country":"BO",
    "name:und_x_variant":[
        "Huayhuasi",
        "Guayguasi"
    ],
    "wof:name":"Guayguasi",
    "wof:placetype":"locality"
},
  "geometry": {"coordinates":[-68.01666999999999,-16.71667],"type":"Point"}
}