{
  "type": "Feature",
  "properties": {
    "gn:admin1_code":"04",
    "gn:asciiname":"Chua",
    "gn:country_code":"BO",
    "gn:dem":3815,
    "gn:feature_class":"P",
    "gn:feature_code":"PPL",
    "gn:name":"Ch\u00faa",
    "gn:population":0,
    "gn:timezone":"America/La_Paz",
    "iso:country":"BO",
    "name:ceb_x_preferred":[
        "Chua"
    ],
    "name:deu_x_preferred":[
        "Chua"
    ],
    "name:swe_x_preferred":[
        "Chua"
    ],
    "wof:name":"Chua",
    "wof:placetype":"locality"
},
  "geometry": {"coordinates":[-68.78333000000001,-16.18333],"type":"Point"}
}