{
  "type": "Feature",
  "properties": {
    "gn:admin1_code":"04",
    "gn:asciiname":"Estancia Cabana Liphichi",
    "gn:country_code":"BO",
    "gn:dem":4217,
    "gn:feature_class":"P",
    "gn:feature_code":"PPL",
    "gn:name":"Estancia Caba\u00f1a Liphichi",
    "gn:population":0,
    "gn:timezone":"America/La_Paz",
    "iso:country":"BO",
    "wof:name":"Estancia Cabana Liphichi",
    "wof:placetype":"locality"
},
  "geometry": {"coordinates":[-69.56667,-17.21667],"type":"Point"}
}