{
  "type": "Feature",
  "properties": {
    "gn:admin1_code":"4.0",
    "gn:asciiname":"Estancia Puitucani",
    "gn:country_code":"BO",
    "gn:dem":4350,
    "gn:feature_class":"P",
    "gn:feature_code":"PPL",
    "gn:name":"Estancia Puitucani",
    "gn:population":0,
    "gn:timezone":"America/La_Paz",
    "iso:country":"BO",
    "wof:name":"Estancia Puitucani",
    "wof:placetype":"locality"
},
  "geometry": {"coordinates":[-67.26666999999999,-17.25],"type":"Point"}
}