{
  "type": "Feature",
  "properties": {
    "gn:admin1_code":"07",
    "gn:asciiname":"Cienegpunta",
    "gn:country_code":"BO",
    "gn:dem":4401,
    "gn:feature_class":"P",
    "gn:feature_code":"PPL",
    "gn:name":"Cienegpunta",
    "gn:population":0,
    "gn:timezone":"America/La_Paz",
    "iso:country":"BO",
    "wof:name":"Cienegpunta",
    "wof:placetype":"locality"
},
  "geometry": {"coordinates":[-66.31667,-21.18333],"type":"Point"}
}