{
  "type": "Feature",
  "properties": {
    "gn:admin1_code":"5.0",
    "gn:asciiname":"Kota Saya",
    "gn:country_code":"BO",
    "gn:dem":4228,
    "gn:feature_class":"P",
    "gn:feature_code":"PPL",
    "gn:name":"Kota Saya",
    "gn:population":0,
    "gn:timezone":"America/La_Paz",
    "iso:country":"BO",
    "wof:name":"Kota Saya",
    "wof:placetype":"locality"
},
  "geometry": {"coordinates":[-68.81667,-17.98333],"type":"Point"}
}