{
  "type": "Feature",
  "properties": {
    "gn:admin1_code":"2.0",
    "gn:asciiname":"Higo Pampa",
    "gn:country_code":"BO",
    "gn:dem":2217,
    "gn:feature_class":"P",
    "gn:feature_code":"PPL",
    "gn:name":"Higo Pampa",
    "gn:population":0,
    "gn:timezone":"America/La_Paz",
    "iso:country":"BO",
    "name:und_x_variant":[
        "Estancia Higo Pampa",
        "Higo Pampa"
    ],
    "wof:name":"Higo Pampa",
    "wof:placetype":"locality"
},
  "geometry": {"coordinates":[-65.00716,-18.26814],"type":"Point"}
}