{
  "type": "Feature",
  "properties": {
    "gn:admin1_code":"7.0",
    "gn:asciiname":"Evangelista",
    "gn:country_code":"BO",
    "gn:dem":4425,
    "gn:feature_class":"P",
    "gn:feature_code":"PPL",
    "gn:name":"Evangelista",
    "gn:population":0,
    "gn:timezone":"America/La_Paz",
    "iso:country":"BO",
    "name:cat_x_preferred":[
        "Evangelista"
    ],
    "name:ceb_x_preferred":[
        "Evangelista"
    ],
    "name:deu_x_preferred":[
        "Evangelista"
    ],
    "name:fra_x_preferred":[
        "Evangelista"
    ],
    "name:ita_x_preferred":[
        "Evangelista"
    ],
    "name:jpn_x_preferred":[
        "\u30a8\u30f4\u30a1\u30f3\u30b8\u30a7\u30ea\u30b9\u30bf"
    ],
    "name:por_x_preferred":[
        "Evangelista"
    ],
    "name:rus_x_preferred":[
        "\u0415\u0432\u0430\u043d\u0433\u0435\u043b\u0438\u0441\u0442\u0430"
    ],
    "name:spa_x_preferred":[
        "Evangelista"
    ],
    "name:swe_x_preferred":[
        "Evangelista"
    ],
    "wof:name":"Evangelista",
    "wof:placetype":"locality"
},
  "geometry": {"coordinates":[-66.36667,-21.33333],"type":"Point"}
}