{
  "type": "Feature",
  "properties": {
    "gn:admin1_code":"7.0",
    "gn:asciiname":"Evangelista",
    "gn:country_code":"BO",
    "gn:dem":4425,
    "gn:feature_class":"P",
    "gn:feature_code":"PPL",
    "gn:name":"Evangelista",
    "gn:population":0,
    "gn:timezone":"America/La_Paz",
    "iso:country":"BO",
    "wof:name":"Evangelista",
    "wof:placetype":"locality"
},
  "geometry": {"coordinates":[-66.36667,-21.33333],"type":"Point"}
}