{
  "type": "Feature",
  "properties": {
    "iso:country":"BO",
    "name:aym_x_preferred":[
        "Chulumani"
    ],
    "name:aze_x_preferred":[
        "\u00c7ulumani"
    ],
    "name:bul_x_preferred":[
        "\u0427\u0443\u043b\u0443\u043c\u0430\u043d\u0438"
    ],
    "name:ceb_x_preferred":[
        "Chulumani"
    ],
    "name:deu_x_preferred":[
        "Chulumani"
    ],
    "name:eng_x_preferred":[
        "Chulumani"
    ],
    "name:fra_x_preferred":[
        "Chulumani"
    ],
    "name:jpn_x_preferred":[
        "\u30c1\u30e3\u30eb\u30de\u30cb"
    ],
    "name:nld_x_preferred":[
        "Chulumani"
    ],
    "name:nob_x_preferred":[
        "Chulumani"
    ],
    "name:nor_x_preferred":[
        "Chulumani"
    ],
    "name:pol_x_preferred":[
        "Chulumani"
    ],
    "name:que_x_preferred":[
        "Chulumani"
    ],
    "name:rus_x_preferred":[
        "\u0427\u0443\u043b\u0443\u043c\u0430\u043d\u0438"
    ],
    "name:spa_x_preferred":[
        "Chulumani"
    ],
    "name:swe_x_preferred":[
        "Chulumani"
    ],
    "name:war_x_preferred":[
        "Chulumani"
    ],
    "name:zho_x_preferred":[
        "\u4e18\u76e7\u99ac\u5c3c"
    ],
    "qs:gn_country":"BO",
    "qs:gn_fcode":"PPL",
    "qs:gn_pop":2952,
    "qs:name":"Chulumani",
    "qs:name_adm0":"Bolivia",
    "qs:name_adm1":"La Paz",
    "qs:photos":0,
    "qs:photos_1k":0,
    "qs:photos_9k":1,
    "qs:photos_9r":1,
    "qs:photos_all":4,
    "qs:photos_sr":0,
    "qs:placetype":"Town",
    "qs:pop_sr":"4",
    "qs:woe_adm0":23424762,
    "wd:wordcount":153,
    "wof:name":"Chulumani",
    "wof:placetype":"locality",
    "wof:population":2952
},
  "geometry": {"coordinates":[-67.52625999999999,-16.40962],"type":"Point"}
}