{
  "type": "Feature",
  "properties": {
    "gn:admin1_code":"04",
    "gn:asciiname":"Agana",
    "gn:cc2":"BO",
    "gn:country_code":"BO",
    "gn:dem":1927,
    "gn:feature_class":"P",
    "gn:feature_code":"PPL",
    "gn:name":"Agana",
    "gn:population":0,
    "gn:timezone":"America/La_Paz",
    "iso:country":"BO",
    "name:und_x_variant":[
        "Arana",
        "Agana"
    ],
    "wof:name":"Agana",
    "wof:placetype":"locality"
},
  "geometry": {"coordinates":[-67.81667,-15.88333],"type":"Point"}
}