{
  "type": "Feature",
  "properties": {
    "gn:admin1_code":"5.0",
    "gn:asciiname":"Livis Khota",
    "gn:country_code":"BO",
    "gn:dem":3694,
    "gn:feature_class":"P",
    "gn:feature_code":"PPL",
    "gn:name":"Livis Khota",
    "gn:population":0,
    "gn:timezone":"America/La_Paz",
    "iso:country":"BO",
    "name:und_x_variant":[
        "Estancia Livis-Kkota",
        "Libiscota",
        "Livis Khota"
    ],
    "wof:name":"Livis Khota",
    "wof:placetype":"locality"
},
  "geometry": {"coordinates":[-68.39917,-19.59152000000001],"type":"Point"}
}