{
  "type": "Feature",
  "properties": {
    "gn:admin1_code":"06",
    "gn:asciiname":"Copacabana",
    "gn:country_code":"BO",
    "gn:dem":161,
    "gn:feature_class":"P",
    "gn:feature_code":"PPL",
    "gn:name":"Copacabana",
    "gn:population":0,
    "gn:timezone":"America/La_Paz",
    "iso:country":"BO",
    "name:spa_x_preferred":[
        "Copacabana"
    ],
    "wof:name":"Copacabana",
    "wof:placetype":"locality"
},
  "geometry": {"coordinates":[-67.81438,-10.66456],"type":"Point"}
}