{
  "type": "Feature",
  "properties": {
    "gn:admin1_code":"06",
    "gn:asciiname":"Belmonte",
    "gn:country_code":"BO",
    "gn:dem":274,
    "gn:feature_class":"P",
    "gn:feature_code":"PPL",
    "gn:name":"Belmonte",
    "gn:population":0,
    "gn:timezone":"America/La_Paz",
    "iso:country":"BO",
    "name:spa_x_preferred":[
        "Belmonte"
    ],
    "wof:name":"Belmonte",
    "wof:placetype":"locality"
},
  "geometry": {"coordinates":[-68.90333000000001,-11.11275],"type":"Point"}
}