{
  "type": "Feature",
  "properties": {
    "gn:admin1_code":"04",
    "gn:asciiname":"Comunidad Putuni",
    "gn:country_code":"BO",
    "gn:dem":4284,
    "gn:feature_class":"P",
    "gn:feature_code":"PPL",
    "gn:name":"Comunidad Putuni",
    "gn:population":0,
    "gn:timezone":"America/La_Paz",
    "iso:country":"BO",
    "wof:name":"Comunidad Putuni",
    "wof:placetype":"locality"
},
  "geometry": {"coordinates":[-68.31667,-17.16667],"type":"Point"}
}