{
  "type": "Feature",
  "properties": {
    "gn:admin1_code":"08",
    "gn:asciiname":"El Barrial",
    "gn:country_code":"BO",
    "gn:dem":320,
    "gn:feature_class":"P",
    "gn:feature_code":"PPL",
    "gn:name":"El Barrial",
    "gn:population":0,
    "gn:timezone":"America/La_Paz",
    "iso:country":"BO",
    "name:spa_x_preferred":[
        "El Barrial"
    ],
    "wof:name":"El Barrial",
    "wof:placetype":"locality"
},
  "geometry": {"coordinates":[-63.05,-17.48333],"type":"Point"}
}