{
  "type": "Feature",
  "properties": {
    "gn:admin1_code":"1.0",
    "gn:asciiname":"Otoronco",
    "gn:cc2":"BO",
    "gn:country_code":"BO",
    "gn:dem":2399,
    "gn:feature_class":"P",
    "gn:feature_code":"PPL",
    "gn:name":"Otoronco",
    "gn:population":0,
    "gn:timezone":"America/La_Paz",
    "iso:country":"BO",
    "name:und_x_variant":[
        "Uturungo",
        "Otorongo",
        "Uturunku",
        "Otoronco"
    ],
    "wof:name":"Otoronco",
    "wof:placetype":"locality"
},
  "geometry": {"coordinates":[-64.58333,-19.15],"type":"Point"}
}