{
  "type": "Feature",
  "properties": {
    "gn:admin1_code":"06",
    "gn:asciiname":"Alto Bahia Dos",
    "gn:country_code":"BO",
    "gn:dem":198,
    "gn:feature_class":"P",
    "gn:feature_code":"PPL",
    "gn:name":"Alto Bahia Dos",
    "gn:population":0,
    "gn:timezone":"America/La_Paz",
    "iso:country":"BO",
    "name:spa_x_preferred":[
        "Alto Bahia Dos"
    ],
    "wof:name":"Alto Bahia Dos",
    "wof:placetype":"locality"
},
  "geometry": {"coordinates":[-67.38278000000001,-10.90551],"type":"Point"}
}