{
  "type": "Feature",
  "properties": {
    "gn:admin1_code":"04",
    "gn:asciiname":"Altamarani",
    "gn:country_code":"BO",
    "gn:dem":217,
    "gn:feature_class":"P",
    "gn:feature_code":"PPL",
    "gn:name":"Altamarani",
    "gn:population":0,
    "gn:timezone":"America/La_Paz",
    "iso:country":"BO",
    "wof:name":"Altamarani",
    "wof:placetype":"locality"
},
  "geometry": {"coordinates":[-67.56667,-14.35],"type":"Point"}
}