{
  "type": "Feature",
  "properties": {
    "gn:admin1_code":"7.0",
    "gn:asciiname":"Yuracpabello",
    "gn:cc2":"BO",
    "gn:country_code":"BO",
    "gn:dem":4274,
    "gn:feature_class":"P",
    "gn:feature_code":"PPL",
    "gn:name":"Yuracpabello",
    "gn:population":0,
    "gn:timezone":"America/La_Paz",
    "iso:country":"BO",
    "name:und_x_variant":[
        "Yuracpabellon",
        "Yuracpabello"
    ],
    "wof:name":"Yuracpabello",
    "wof:placetype":"locality"
},
  "geometry": {"coordinates":[-66.76666999999999,-21.73333],"type":"Point"}
}