{
  "type": "Feature",
  "properties": {
    "gn:admin1_code":"6.0",
    "gn:asciiname":"Ruiz",
    "gn:country_code":"BO",
    "gn:dem":229,
    "gn:feature_class":"P",
    "gn:feature_code":"PPL",
    "gn:name":"Ruiz",
    "gn:population":0,
    "gn:timezone":"America/La_Paz",
    "iso:country":"BO",
    "name:deu_x_preferred":[
        "Ruiz"
    ],
    "name:ita_x_preferred":[
        "Ruiz"
    ],
    "name:spa_x_preferred":[
        "Ruiz"
    ],
    "wof:name":"Ruiz",
    "wof:placetype":"locality"
},
  "geometry": {"coordinates":[-68.97105999999999,-11.90812],"type":"Point"}
}