{
  "type": "Feature",
  "properties": {
    "gn:admin1_code":"05",
    "gn:asciiname":"Bella Vista",
    "gn:country_code":"BO",
    "gn:dem":4099,
    "gn:feature_class":"P",
    "gn:feature_code":"PPL",
    "gn:name":"Bella Vista",
    "gn:population":0,
    "gn:timezone":"America/La_Paz",
    "iso:country":"BO",
    "name:ara_x_preferred":[
        "\u0628\u064a\u0644\u0627 \u0641\u064a\u0633\u062a\u0627"
    ],
    "name:ben_x_preferred":[
        "\u09ac\u09c7\u09b2\u09cd\u09b2\u09be \u09ad\u09bf\u09b8\u09cd\u09a4\u09be"
    ],
    "name:cat_x_preferred":[
        "Bella Vista"
    ],
    "name:ceb_x_preferred":[
        "Bella Vista"
    ],
    "name:deu_x_preferred":[
        "Bella Vista"
    ],
    "name:ell_x_preferred":[
        "\u039c\u03c0\u03ad\u03bb\u03b1 \u0392\u03af\u03c3\u03c4\u03b1"
    ],
    "name:fas_x_preferred":[
        "\u0628\u0644\u0627 \u0648\u06cc\u0633\u062a\u0627"
    ],
    "name:heb_x_preferred":[
        "\u05d1\u05dc\u05d4 \u05d5\u05d5\u05d9\u05e1\u05d8\u05d4"
    ],
    "name:hin_x_preferred":[
        "\u092c\u0947\u0932\u093e \u0935\u093f\u0938\u094d\u091f\u093e"
    ],
    "name:hun_x_preferred":[
        "Bella Vista"
    ],
    "name:ind_x_preferred":[
        "Bella Vista"
    ],
    "name:ita_x_preferred":[
        "Bella Vista"
    ],
    "name:jpn_x_preferred":[
        "\u30d9\u30e9\u30d3\u30b9\u30bf"
    ],
    "name:kor_x_preferred":[
        "\ubca8\ub77c \ube44\uc2a4\ud0c0"
    ],
    "name:lit_x_preferred":[
        "Belja Vista"
    ],
    "name:nds_x_preferred":[
        "Bella Vista"
    ],
    "name:nld_x_preferred":[
        "Bella Vista"
    ],
    "name:pol_x_preferred":[
        "Bella Vista"
    ],
    "name:por_x_preferred":[
        "Bella Vista"
    ],
    "name:rus_x_preferred":[
        "\u0411\u0435\u043b\u044c\u044f-\u0412\u0438\u0441\u0442\u0430"
    ],
    "name:sco_x_preferred":[
        "Bella Vista"
    ],
    "name:slk_x_preferred":[
        "Bella Vista"
    ],
    "name:spa_x_preferred":[
        "Bella Vista"
    ],
    "name:srp_x_preferred":[
        "\u0411\u0435\u043b\u0430 \u0412\u0438\u0441\u0442\u0430"
    ],
    "name:swe_x_preferred":[
        "Bella Vista"
    ],
    "name:tur_x_preferred":[
        "Bella Vista"
    ],
    "name:ukr_x_preferred":[
        "\u0411\u0435\u043b\u043b\u0430-\u0412\u0456\u0441\u0442\u0430"
    ],
    "name:urd_x_preferred":[
        "\u0628\u06cc\u0644\u0627 \u0648\u0633\u0679\u0627"
    ],
    "name:vie_x_preferred":[
        "Bella Vista"
    ],
    "name:vol_x_preferred":[
        "Bella Vista"
    ],
    "wof:name":"Bella Vista",
    "wof:placetype":"locality"
},
  "geometry": {"coordinates":[-67.96666999999999,-17.91667],"type":"Point"}
}