{
  "type": "Feature",
  "properties": {
    "gn:admin1_code":"1.0",
    "gn:asciiname":"Jucumari",
    "gn:country_code":"BO",
    "gn:dem":1212,
    "gn:feature_class":"P",
    "gn:feature_code":"PPL",
    "gn:name":"Jucumari",
    "gn:population":0,
    "gn:timezone":"America/La_Paz",
    "iso:country":"BO",
    "name:und_x_variant":[
        "Jucumar",
        "Jucumor",
        "Jucumari"
    ],
    "wof:name":"Jucumari",
    "wof:placetype":"locality"
},
  "geometry": {"coordinates":[-63.77593,-19.83299],"type":"Point"}
}