{
  "type": "Feature",
  "properties": {
    "gn:admin1_code":"8.0",
    "gn:asciiname":"Almendros",
    "gn:cc2":"BO",
    "gn:country_code":"BO",
    "gn:dem":231,
    "gn:feature_class":"P",
    "gn:feature_code":"PPL",
    "gn:name":"Almendros",
    "gn:population":0,
    "gn:timezone":"America/La_Paz",
    "iso:country":"BO",
    "name:ara_x_preferred":[
        "\u0627\u0644\u0645\u064a\u0646\u062f\u0631\u0648\u0633"
    ],
    "name:arg_x_preferred":[
        "Almendros"
    ],
    "name:ast_x_preferred":[
        "Almendros"
    ],
    "name:cat_x_preferred":[
        "Almendros"
    ],
    "name:ceb_x_preferred":[
        "Almendros"
    ],
    "name:epo_x_preferred":[
        "Almendros"
    ],
    "name:eus_x_preferred":[
        "Almendros"
    ],
    "name:fra_x_preferred":[
        "Almendros"
    ],
    "name:hun_x_preferred":[
        "Almendros"
    ],
    "name:ita_x_preferred":[
        "Almendros"
    ],
    "name:kaz_x_preferred":[
        "\u0410\u043b\u044c\u043c\u0435\u043d\u0434\u0440\u043e\u0441"
    ],
    "name:msa_x_preferred":[
        "Almendros"
    ],
    "name:nld_x_preferred":[
        "Almendros"
    ],
    "name:oci_x_preferred":[
        "Almendros"
    ],
    "name:pol_x_preferred":[
        "Almendros"
    ],
    "name:por_x_preferred":[
        "Almendros"
    ],
    "name:rus_x_preferred":[
        "\u0410\u043b\u044c\u043c\u0435\u043d\u0434\u0440\u043e\u0441"
    ],
    "name:spa_x_preferred":[
        "Almendros"
    ],
    "name:swe_x_preferred":[
        "Almendros"
    ],
    "name:ukr_x_preferred":[
        "\u0410\u043b\u044c\u043c\u0435\u043d\u0434\u0440\u043e\u0441"
    ],
    "name:und_x_variant":[
        "Almendro",
        "Almendros"
    ],
    "name:vie_x_preferred":[
        "Almendros"
    ],
    "name:war_x_preferred":[
        "Almendros"
    ],
    "name:zho_x_preferred":[
        "\u963f\u5c14\u95e8\u5fb7\u7f57\u65af"
    ],
    "wof:name":"Almendros",
    "wof:placetype":"locality"
},
  "geometry": {"coordinates":[-59.05,-18.56667],"type":"Point"}
}