{
  "type": "Feature",
  "properties": {
    "gn:admin1_code":"8.0",
    "gn:asciiname":"Puerto Cespedes",
    "gn:cc2":"BO",
    "gn:country_code":"BO",
    "gn:dem":276,
    "gn:feature_class":"P",
    "gn:feature_code":"PPL",
    "gn:name":"Puerto Cespedes",
    "gn:population":0,
    "gn:timezone":"America/La_Paz",
    "iso:country":"BO",
    "name:und_x_variant":[
        "Hacienda La Cubanita",
        "Puerto Cespedes"
    ],
    "wof:name":"Puerto Cespedes",
    "wof:placetype":"locality"
},
  "geometry": {"coordinates":[-62.73333,-17.41667],"type":"Point"}
}