{
  "type": "Feature",
  "properties": {
    "gn:admin1_code":"4.0",
    "gn:asciiname":"Palca",
    "gn:country_code":"BO",
    "gn:dem":3460,
    "gn:feature_class":"P",
    "gn:feature_code":"PPL",
    "gn:name":"Palca",
    "gn:population":0,
    "gn:timezone":"America/La_Paz",
    "iso:country":"BO",
    "name:ceb_x_preferred":[
        "Palca"
    ],
    "name:deu_x_preferred":[
        "Palca"
    ],
    "name:fra_x_preferred":[
        "Palca"
    ],
    "name:que_x_preferred":[
        "Pallqa"
    ],
    "name:spa_x_preferred":[
        "Palca"
    ],
    "name:swe_x_preferred":[
        "Palca"
    ],
    "name:war_x_preferred":[
        "Palca"
    ],
    "name:zho_x_preferred":[
        "\u5e15\u723e\u5361"
    ],
    "wof:name":"Palca",
    "wof:placetype":"locality"
},
  "geometry": {"coordinates":[-67.9528,-16.56162],"type":"Point"}
}