{
  "type": "Feature",
  "properties": {
    "gn:admin1_code":"8.0",
    "gn:asciiname":"San Blas",
    "gn:country_code":"BO",
    "gn:dem":260,
    "gn:feature_class":"P",
    "gn:feature_code":"PPL",
    "gn:name":"San Blas",
    "gn:population":0,
    "gn:timezone":"America/La_Paz",
    "iso:country":"BO",
    "wof:name":"San Blas",
    "wof:placetype":"locality"
},
  "geometry": {"coordinates":[-60.85,-17.71667],"type":"Point"}
}