{
  "type": "Feature",
  "properties": {
    "gn:admin1_code":"2.0",
    "gn:asciiname":"Pujyuni",
    "gn:country_code":"BO",
    "gn:dem":2817,
    "gn:feature_class":"P",
    "gn:feature_code":"PPL",
    "gn:name":"Pujyuni",
    "gn:population":0,
    "gn:timezone":"America/La_Paz",
    "iso:country":"BO",
    "wof:name":"Pujyuni",
    "wof:placetype":"locality"
},
  "geometry": {"coordinates":[-65.98333000000001,-17.65],"type":"Point"}
}