{
  "type": "Feature",
  "properties": {
    "gn:admin1_code":"1.0",
    "gn:asciiname":"Muralla",
    "gn:country_code":"BO",
    "gn:dem":2502,
    "gn:feature_class":"P",
    "gn:feature_code":"PPL",
    "gn:name":"Muralla",
    "gn:population":0,
    "gn:timezone":"America/La_Paz",
    "iso:country":"BO",
    "name:und_x_variant":[
        "Estancia Muralla",
        "Muralla"
    ],
    "wof:name":"Muralla",
    "wof:placetype":"locality"
},
  "geometry": {"coordinates":[-64.53095999999999,-19.69086],"type":"Point"}
}