{
  "type": "Feature",
  "properties": {
    "gn:admin1_code":"4.0",
    "gn:asciiname":"Vinto Amaya",
    "gn:country_code":"BO",
    "gn:dem":3902,
    "gn:feature_class":"P",
    "gn:feature_code":"PPL",
    "gn:name":"Vinto Amaya",
    "gn:population":0,
    "gn:timezone":"America/La_Paz",
    "iso:country":"BO",
    "wof:name":"Vinto Amaya",
    "wof:placetype":"locality"
},
  "geometry": {"coordinates":[-69.23333000000001,-17.11667000000001],"type":"Point"}
}