{
  "type": "Feature",
  "properties": {
    "gn:admin1_code":"4.0",
    "gn:asciiname":"Santa Clara",
    "gn:country_code":"BO",
    "gn:dem":947,
    "gn:feature_class":"P",
    "gn:feature_code":"PPL",
    "gn:name":"Santa Clara",
    "gn:population":0,
    "gn:timezone":"America/La_Paz",
    "iso:country":"BO",
    "wof:name":"Santa Clara",
    "wof:placetype":"locality"
},
  "geometry": {"coordinates":[-68.18333,-15.33333],"type":"Point"}
}