{
  "type": "Feature",
  "properties": {
    "gn:admin1_code":"4.0",
    "gn:asciiname":"Pampa Uta",
    "gn:cc2":"BO",
    "gn:country_code":"BO",
    "gn:dem":3861,
    "gn:feature_class":"P",
    "gn:feature_code":"PPL",
    "gn:name":"Pampa Uta",
    "gn:population":0,
    "gn:timezone":"America/La_Paz",
    "iso:country":"BO",
    "name:und_x_variant":[
        "Estancia Pampa Uta",
        "Pampa Uta"
    ],
    "wof:name":"Pampa Uta",
    "wof:placetype":"locality"
},
  "geometry": {"coordinates":[-69.05,-17.03333],"type":"Point"}
}