{
  "type": "Feature",
  "properties": {
    "gn:admin1_code":"03",
    "gn:asciiname":"Armenia",
    "gn:cc2":"BO",
    "gn:country_code":"BO",
    "gn:dem":185,
    "gn:feature_class":"P",
    "gn:feature_code":"PPL",
    "gn:name":"Armenia",
    "gn:population":0,
    "gn:timezone":"America/La_Paz",
    "iso:country":"BO",
    "name:und_x_variant":[
        "Armenta",
        "Armenia"
    ],
    "wof:name":"Armenia",
    "wof:placetype":"locality"
},
  "geometry": {"coordinates":[-67.06667,-14.41667],"type":"Point"}
}