{
  "type": "Feature",
  "properties": {
    "gn:admin1_code":"7.0",
    "gn:asciiname":"Pueblito",
    "gn:cc2":"BO",
    "gn:country_code":"BO",
    "gn:dem":3705,
    "gn:feature_class":"P",
    "gn:feature_code":"PPL",
    "gn:name":"Pueblito",
    "gn:population":0,
    "gn:timezone":"America/La_Paz",
    "iso:country":"BO",
    "name:und_x_variant":[
        "Ticanoma Palsa",
        "Pueblito"
    ],
    "wof:name":"Pueblito",
    "wof:placetype":"locality"
},
  "geometry": {"coordinates":[-66.36667,-18.06667],"type":"Point"}
}