{
  "type": "Feature",
  "properties": {
    "gn:admin1_code":"5.0",
    "gn:asciiname":"Estancia Uncalliri",
    "gn:country_code":"BO",
    "gn:dem":3768,
    "gn:feature_class":"P",
    "gn:feature_code":"PPL",
    "gn:name":"Estancia Uncalliri",
    "gn:population":0,
    "gn:timezone":"America/La_Paz",
    "iso:country":"BO",
    "wof:name":"Estancia Uncalliri",
    "wof:placetype":"locality"
},
  "geometry": {"coordinates":[-68.53089,-18.78844],"type":"Point"}
}