{
  "type": "Feature",
  "properties": {
    "gn:admin1_code":"9.0",
    "gn:asciiname":"Tres Pilares",
    "gn:country_code":"BO",
    "gn:dem":561,
    "gn:feature_class":"P",
    "gn:feature_code":"PPL",
    "gn:name":"Tres Pilares",
    "gn:population":0,
    "gn:timezone":"America/La_Paz",
    "iso:country":"BO",
    "name:und_x_variant":[
        "Tres Puares",
        "Tres Pilares"
    ],
    "wof:name":"Tres Pilares",
    "wof:placetype":"locality"
},
  "geometry": {"coordinates":[-63.61763000000001,-21.31386],"type":"Point"}
}