{
  "type": "Feature",
  "properties": {
    "gn:admin1_code":"4.0",
    "gn:asciiname":"Khalasuni",
    "gn:cc2":"BO",
    "gn:country_code":"BO",
    "gn:dem":3942,
    "gn:feature_class":"P",
    "gn:feature_code":"PPL",
    "gn:name":"Khalasuni",
    "gn:population":0,
    "gn:timezone":"America/La_Paz",
    "iso:country":"BO",
    "name:und_x_variant":[
        "Estancia Calazuni",
        "Khalasuni"
    ],
    "wof:name":"Khalasuni",
    "wof:placetype":"locality"
},
  "geometry": {"coordinates":[-68.75,-17.48333],"type":"Point"}
}