{
  "type": "Feature",
  "properties": {
    "gn:admin1_code":"1.0",
    "gn:asciiname":"Estancia Piedras Blancas",
    "gn:country_code":"BO",
    "gn:dem":2986,
    "gn:feature_class":"P",
    "gn:feature_code":"PPL",
    "gn:name":"Estancia Piedras Blancas",
    "gn:population":0,
    "gn:timezone":"America/La_Paz",
    "iso:country":"BO",
    "wof:name":"Estancia Piedras Blancas",
    "wof:placetype":"locality"
},
  "geometry": {"coordinates":[-65.3635,-20.64112],"type":"Point"}
}