{
  "type": "Feature",
  "properties": {
    "gn:admin1_code":"01",
    "gn:asciiname":"Estancia Casa Sola",
    "gn:country_code":"BO",
    "gn:dem":3439,
    "gn:feature_class":"P",
    "gn:feature_code":"PPL",
    "gn:name":"Estancia Casa Sola",
    "gn:population":0,
    "gn:timezone":"America/La_Paz",
    "iso:country":"BO",
    "wof:name":"Estancia Casa Sola",
    "wof:placetype":"locality"
},
  "geometry": {"coordinates":[-65.06667,-20.26667],"type":"Point"}
}