{
  "type": "Feature",
  "properties": {
    "gn:admin1_code":"7.0",
    "gn:asciiname":"Totoroma",
    "gn:country_code":"BO",
    "gn:dem":3124,
    "gn:feature_class":"P",
    "gn:feature_code":"PPL",
    "gn:name":"Totoroma",
    "gn:population":0,
    "gn:timezone":"America/La_Paz",
    "iso:country":"BO",
    "wof:name":"Totoroma",
    "wof:placetype":"locality"
},
  "geometry": {"coordinates":[-66.12663000000001,-18.04651],"type":"Point"}
}