{
  "type": "Feature",
  "properties": {
    "gn:admin1_code":"8.0",
    "gn:asciiname":"Huacarati",
    "gn:country_code":"BO",
    "gn:dem":931,
    "gn:feature_class":"P",
    "gn:feature_code":"PPL",
    "gn:name":"Huacarat\u00ed",
    "gn:population":0,
    "gn:timezone":"America/La_Paz",
    "iso:country":"BO",
    "name:und_x_variant":[
        "Huacareti",
        "Huacareta",
        "Huacarat\u00ed"
    ],
    "wof:name":"Huacarati",
    "wof:placetype":"locality"
},
  "geometry": {"coordinates":[-63.28799,-20.19683],"type":"Point"}
}