{
  "type": "Feature",
  "properties": {
    "gn:admin1_code":"8.0",
    "gn:asciiname":"Quiriquirigua",
    "gn:country_code":"BO",
    "gn:dem":1029,
    "gn:feature_class":"P",
    "gn:feature_code":"PPL",
    "gn:name":"Quiriquirigua",
    "gn:population":0,
    "gn:timezone":"America/La_Paz",
    "iso:country":"BO",
    "name:und_x_variant":[
        "Quiriquimba",
        "Quiriquirhua",
        "Quiriquirigua"
    ],
    "wof:name":"Quiriquirigua",
    "wof:placetype":"locality"
},
  "geometry": {"coordinates":[-63.5568,-19.79271],"type":"Point"}
}