{
  "type": "Feature",
  "properties": {
    "gn:admin1_code":"9.0",
    "gn:asciiname":"Pampa Redonda",
    "gn:country_code":"BO",
    "gn:dem":1974,
    "gn:feature_class":"P",
    "gn:feature_code":"PPL",
    "gn:name":"Pampa Redonda",
    "gn:population":0,
    "gn:timezone":"America/La_Paz",
    "iso:country":"BO",
    "wof:name":"Pampa Redonda",
    "wof:placetype":"locality"
},
  "geometry": {"coordinates":[-64.82162,-21.68662],"type":"Point"}
}