{
  "type": "Feature",
  "properties": {
    "gn:admin1_code":"9.0",
    "gn:asciiname":"Santiago",
    "gn:country_code":"BO",
    "gn:dem":1085,
    "gn:feature_class":"P",
    "gn:feature_code":"PPL",
    "gn:name":"Santiago",
    "gn:population":0,
    "gn:timezone":"America/La_Paz",
    "iso:country":"BO",
    "wof:name":"Santiago",
    "wof:placetype":"locality"
},
  "geometry": {"coordinates":[-64.21666999999999,-21.71667],"type":"Point"}
}