{
  "type": "Feature",
  "properties": {
    "gn:admin1_code":"07",
    "gn:asciiname":"Chayala",
    "gn:country_code":"BO",
    "gn:dem":2711,
    "gn:feature_class":"P",
    "gn:feature_code":"PPL",
    "gn:name":"Chayala",
    "gn:population":0,
    "gn:timezone":"America/La_Paz",
    "iso:country":"BO",
    "wof:name":"Chayala",
    "wof:placetype":"locality"
},
  "geometry": {"coordinates":[-65.99608000000001,-18.54677],"type":"Point"}
}