{
  "type": "Feature",
  "properties": {
    "gn:admin1_code":"7.0",
    "gn:asciiname":"Telucayo",
    "gn:cc2":"BO",
    "gn:country_code":"BO",
    "gn:dem":4127,
    "gn:feature_class":"P",
    "gn:feature_code":"PPL",
    "gn:name":"Telucayo",
    "gn:population":0,
    "gn:timezone":"America/La_Paz",
    "iso:country":"BO",
    "name:und_x_variant":[
        "Telucayoc",
        "Telucayo"
    ],
    "wof:name":"Telucayo",
    "wof:placetype":"locality"
},
  "geometry": {"coordinates":[-65.95,-21.06667],"type":"Point"}
}