{
  "type": "Feature",
  "properties": {
    "gn:admin1_code":"2.0",
    "gn:asciiname":"Kalani",
    "gn:cc2":"BO",
    "gn:country_code":"BO",
    "gn:dem":3383,
    "gn:feature_class":"P",
    "gn:feature_code":"PPL",
    "gn:name":"Kalani",
    "gn:population":0,
    "gn:timezone":"America/La_Paz",
    "iso:country":"BO",
    "name:fas_x_preferred":[
        "\u06a9\u0644\u0627\u0646\u06cc"
    ],
    "name:und_x_variant":[
        "Estancia Chaco Villque",
        "Kalani"
    ],
    "wof:name":"Kalani",
    "wof:placetype":"locality"
},
  "geometry": {"coordinates":[-66.78333000000001,-17.16667],"type":"Point"}
}