{
  "type": "Feature",
  "properties": {
    "gn:admin1_code":"9.0",
    "gn:asciiname":"Ibitibi",
    "gn:country_code":"BO",
    "gn:dem":980,
    "gn:feature_class":"P",
    "gn:feature_code":"PPL",
    "gn:name":"Ibitibi",
    "gn:population":0,
    "gn:timezone":"America/La_Paz",
    "iso:country":"BO",
    "wof:name":"Ibitibi",
    "wof:placetype":"locality"
},
  "geometry": {"coordinates":[-63.82467,-21.60741],"type":"Point"}
}