{
  "type": "Feature",
  "properties": {
    "gn:admin1_code":"4.0",
    "gn:asciiname":"Saira",
    "gn:country_code":"BO",
    "gn:dem":3200,
    "gn:feature_class":"P",
    "gn:feature_code":"PPL",
    "gn:name":"Saira",
    "gn:population":0,
    "gn:timezone":"America/La_Paz",
    "iso:country":"BO",
    "wof:name":"Saira",
    "wof:placetype":"locality"
},
  "geometry": {"coordinates":[-68.67421,-15.81213],"type":"Point"}
}