{
  "type": "Feature",
  "properties": {
    "gn:admin1_code":"4.0",
    "gn:admin2_code":"206.0",
    "gn:asciiname":"Guanay",
    "gn:country_code":"BO",
    "gn:dem":477,
    "gn:feature_class":"P",
    "gn:feature_code":"PPLA3",
    "gn:name":"Guanay",
    "gn:population":0,
    "gn:timezone":"America/La_Paz",
    "iso:country":"BO",
    "name:ceb_x_preferred":[
        "Guanay"
    ],
    "name:deu_x_preferred":[
        "Guanay"
    ],
    "name:fra_x_preferred":[
        "Guanay"
    ],
    "name:ita_x_preferred":[
        "Guanay"
    ],
    "name:que_x_preferred":[
        "Wanay llaqta"
    ],
    "name:swe_x_preferred":[
        "Guanay"
    ],
    "name:und_x_variant":[
        "Huanay"
    ],
    "wof:name":"Guanay",
    "wof:placetype":"locality"
},
  "geometry": {"coordinates":[-67.88332,-15.49756],"type":"Point"}
}