{
  "type": "Feature",
  "properties": {
    "gn:admin1_code":"05",
    "gn:asciiname":"Estancia Ticana",
    "gn:country_code":"BO",
    "gn:dem":3789,
    "gn:feature_class":"P",
    "gn:feature_code":"PPL",
    "gn:name":"Estancia Tica\u00f1a",
    "gn:population":0,
    "gn:timezone":"America/La_Paz",
    "iso:country":"BO",
    "wof:name":"Estancia Ticana",
    "wof:placetype":"locality"
},
  "geometry": {"coordinates":[-68.56746,-18.58718],"type":"Point"}
}