{
  "type": "Feature",
  "properties": {
    "gn:admin1_code":"7.0",
    "gn:asciiname":"Ingenio",
    "gn:country_code":"BO",
    "gn:dem":3524,
    "gn:feature_class":"P",
    "gn:feature_code":"PPL",
    "gn:name":"Ingenio",
    "gn:population":0,
    "gn:timezone":"America/La_Paz",
    "iso:country":"BO",
    "name:ceb_x_preferred":[
        "Ingenio"
    ],
    "name:ita_x_preferred":[
        "Ingenio"
    ],
    "name:nld_x_preferred":[
        "Ingenio"
    ],
    "name:por_x_preferred":[
        "Ingenio"
    ],
    "name:spa_x_preferred":[
        "Ingenio"
    ],
    "name:swe_x_preferred":[
        "Ingenio"
    ],
    "wof:name":"Ingenio",
    "wof:placetype":"locality"
},
  "geometry": {"coordinates":[-65.81667,-19.48333],"type":"Point"}
}