{
  "type": "Feature",
  "properties": {
    "gn:admin1_code":"4.0",
    "gn:asciiname":"Estancia Thola Nusata",
    "gn:country_code":"BO",
    "gn:dem":3802,
    "gn:feature_class":"P",
    "gn:feature_code":"PPL",
    "gn:name":"Estancia Thola \u00d1usata",
    "gn:population":0,
    "gn:timezone":"America/La_Paz",
    "iso:country":"BO",
    "wof:name":"Estancia Thola Nusata",
    "wof:placetype":"locality"
},
  "geometry": {"coordinates":[-68.09999999999999,-17.53333],"type":"Point"}
}