{
  "type": "Feature",
  "properties": {
    "gn:admin1_code":"3.0",
    "gn:asciiname":"La Garganta",
    "gn:country_code":"BO",
    "gn:dem":182,
    "gn:feature_class":"P",
    "gn:feature_code":"PPL",
    "gn:name":"La Garganta",
    "gn:population":0,
    "gn:timezone":"America/La_Paz",
    "iso:country":"BO",
    "name:ara_x_preferred":[
        "\u0644\u0627 \u062c\u0627\u0631\u062c\u0627\u0646\u062a\u0627"
    ],
    "name:ast_x_preferred":[
        "La Garganta"
    ],
    "name:cat_x_preferred":[
        "La Garganta"
    ],
    "name:ceb_x_preferred":[
        "La Garganta"
    ],
    "name:deu_x_preferred":[
        "La Garganta"
    ],
    "name:epo_x_preferred":[
        "La Garganta"
    ],
    "name:eus_x_preferred":[
        "La Garganta"
    ],
    "name:fra_x_preferred":[
        "La Garganta"
    ],
    "name:hun_x_preferred":[
        "La Garganta"
    ],
    "name:ina_x_preferred":[
        "La Garganta"
    ],
    "name:ita_x_preferred":[
        "La Garganta"
    ],
    "name:msa_x_preferred":[
        "La Garganta"
    ],
    "name:nld_x_preferred":[
        "La Garganta"
    ],
    "name:oci_x_preferred":[
        "La Garganta"
    ],
    "name:pol_x_preferred":[
        "La Garganta"
    ],
    "name:por_x_preferred":[
        "La Garganta"
    ],
    "name:ron_x_preferred":[
        "La Garganta"
    ],
    "name:rus_x_preferred":[
        "\u041b\u0430-\u0413\u0430\u0440\u0433\u0430\u043d\u0442\u0430"
    ],
    "name:spa_x_preferred":[
        "La Garganta"
    ],
    "name:swe_x_preferred":[
        "La Garganta"
    ],
    "name:ukr_x_preferred":[
        "\u041b\u0430-\u0413\u0430\u0440\u0433\u0430\u043d\u0442\u0430"
    ],
    "name:uzb_x_preferred":[
        "La Garganta"
    ],
    "name:vie_x_preferred":[
        "La Garganta"
    ],
    "name:war_x_preferred":[
        "La Garganta"
    ],
    "name:zho_x_preferred":[
        "\u62c9\u52a0\u5c14\u7518\u5854"
    ],
    "wof:name":"La Garganta",
    "wof:placetype":"locality"
},
  "geometry": {"coordinates":[-65.13333,-15.56667],"type":"Point"}
}