{
  "type": "Feature",
  "properties": {
    "gn:admin1_code":"3.0",
    "gn:asciiname":"La Garganta",
    "gn:country_code":"BO",
    "gn:dem":182,
    "gn:feature_class":"P",
    "gn:feature_code":"PPL",
    "gn:name":"La Garganta",
    "gn:population":0,
    "gn:timezone":"America/La_Paz",
    "iso:country":"BO",
    "wof:name":"La Garganta",
    "wof:placetype":"locality"
},
  "geometry": {"coordinates":[-65.13333,-15.56667],"type":"Point"}
}