{
  "type": "Feature",
  "properties": {
    "gn:admin1_code":"2.0",
    "gn:asciiname":"Humamarca",
    "gn:country_code":"BO",
    "gn:dem":4012,
    "gn:feature_class":"P",
    "gn:feature_code":"PPL",
    "gn:name":"Humamarca",
    "gn:population":0,
    "gn:timezone":"America/La_Paz",
    "iso:country":"BO",
    "wof:name":"Humamarca",
    "wof:placetype":"locality"
},
  "geometry": {"coordinates":[-66.51666999999999,-17.13332999999999],"type":"Point"}
}