{
  "type": "Feature",
  "properties": {
    "gn:admin1_code":"04",
    "gn:asciiname":"Estancia Chapi Pampa",
    "gn:country_code":"BO",
    "gn:dem":3538,
    "gn:feature_class":"P",
    "gn:feature_code":"PPL",
    "gn:name":"Estancia Chapi Pampa",
    "gn:population":0,
    "gn:timezone":"America/La_Paz",
    "iso:country":"BO",
    "wof:name":"Estancia Chapi Pampa",
    "wof:placetype":"locality"
},
  "geometry": {"coordinates":[-67.09999999999999,-17.13332999999999],"type":"Point"}
}