{
  "type": "Feature",
  "properties": {
    "gn:admin1_code":"8.0",
    "gn:asciiname":"Saladillo",
    "gn:country_code":"BO",
    "gn:dem":1525,
    "gn:feature_class":"P",
    "gn:feature_code":"PPL",
    "gn:name":"Saladillo",
    "gn:population":0,
    "gn:timezone":"America/La_Paz",
    "iso:country":"BO",
    "name:ceb_x_preferred":[
        "Saladillo"
    ],
    "name:deu_x_preferred":[
        "Saladillo"
    ],
    "name:nld_x_preferred":[
        "Saladillo"
    ],
    "name:por_x_preferred":[
        "Saladillo"
    ],
    "name:spa_x_preferred":[
        "Saladillo"
    ],
    "name:swe_x_preferred":[
        "Saladillo"
    ],
    "wof:name":"Saladillo",
    "wof:placetype":"locality"
},
  "geometry": {"coordinates":[-64.06667,-17.93332999999999],"type":"Point"}
}