{
  "type": "Feature",
  "properties": {
    "gn:admin1_code":"05",
    "gn:asciiname":"Estancia Khaymani Grande",
    "gn:country_code":"BO",
    "gn:dem":4064,
    "gn:feature_class":"P",
    "gn:feature_code":"PPL",
    "gn:name":"Estancia Khaymani Grande",
    "gn:population":0,
    "gn:timezone":"America/La_Paz",
    "iso:country":"BO",
    "wof:name":"Estancia Khaymani Grande",
    "wof:placetype":"locality"
},
  "geometry": {"coordinates":[-66.71666999999999,-17.85],"type":"Point"}
}