{
  "type": "Feature",
  "properties": {
    "gn:admin1_code":"7.0",
    "gn:asciiname":"Estancia Paspocori",
    "gn:country_code":"BO",
    "gn:dem":3488,
    "gn:feature_class":"P",
    "gn:feature_code":"PPL",
    "gn:name":"Estancia Paspocori",
    "gn:population":0,
    "gn:timezone":"America/La_Paz",
    "iso:country":"BO",
    "wof:name":"Estancia Paspocori",
    "wof:placetype":"locality"
},
  "geometry": {"coordinates":[-66.20959999999999,-20.16555],"type":"Point"}
}