{
  "type": "Feature",
  "properties": {
    "gn:admin1_code":"4.0",
    "gn:asciiname":"Millucato",
    "gn:cc2":"BO",
    "gn:country_code":"BO",
    "gn:dem":2469,
    "gn:feature_class":"P",
    "gn:feature_code":"PPL",
    "gn:name":"Millucato",
    "gn:population":0,
    "gn:timezone":"America/La_Paz",
    "iso:country":"BO",
    "name:und_x_variant":[
        "Millocatu",
        "Millocato",
        "Millucato"
    ],
    "wof:name":"Millucato",
    "wof:placetype":"locality"
},
  "geometry": {"coordinates":[-67.90000000000001,-16.73333],"type":"Point"}
}