{
  "type": "Feature",
  "properties": {
    "gn:admin1_code":"02",
    "gn:asciiname":"Estancia Indio Huaychuma",
    "gn:country_code":"BO",
    "gn:dem":3045,
    "gn:feature_class":"P",
    "gn:feature_code":"PPL",
    "gn:name":"Estancia Indio Huaychuma",
    "gn:population":0,
    "gn:timezone":"America/La_Paz",
    "iso:country":"BO",
    "wof:name":"Estancia Indio Huaychuma",
    "wof:placetype":"locality"
},
  "geometry": {"coordinates":[-66.21666999999999,-17.86667000000001],"type":"Point"}
}