{
  "type": "Feature",
  "properties": {
    "gn:admin1_code":"04",
    "gn:asciiname":"Charia",
    "gn:country_code":"BO",
    "gn:dem":957,
    "gn:feature_class":"P",
    "gn:feature_code":"PPL",
    "gn:name":"Charia",
    "gn:population":0,
    "gn:timezone":"America/La_Paz",
    "iso:country":"BO",
    "wof:name":"Charia",
    "wof:placetype":"locality"
},
  "geometry": {"coordinates":[-67.16667,-15.96667],"type":"Point"}
}