{
  "type": "Feature",
  "properties": {
    "gn:admin1_code":"05",
    "gn:asciiname":"Estancia Chuchulaya",
    "gn:country_code":"BO",
    "gn:dem":3760,
    "gn:feature_class":"P",
    "gn:feature_code":"PPL",
    "gn:name":"Estancia Chuchulaya",
    "gn:population":0,
    "gn:timezone":"America/La_Paz",
    "iso:country":"BO",
    "wof:name":"Estancia Chuchulaya",
    "wof:placetype":"locality"
},
  "geometry": {"coordinates":[-67.50407,-18.82867],"type":"Point"}
}