{
  "type": "Feature",
  "properties": {
    "gn:admin1_code":"1.0",
    "gn:asciiname":"Hacienda Molle Pata",
    "gn:country_code":"BO",
    "gn:dem":2369,
    "gn:feature_class":"P",
    "gn:feature_code":"PPL",
    "gn:name":"Hacienda Molle Pata",
    "gn:population":0,
    "gn:timezone":"America/La_Paz",
    "iso:country":"BO",
    "wof:name":"Hacienda Molle Pata",
    "wof:placetype":"locality"
},
  "geometry": {"coordinates":[-64.63946,-20.41272],"type":"Point"}
}