{
  "type": "Feature",
  "properties": {
    "gn:admin1_code":"4.0",
    "gn:asciiname":"Kellcata",
    "gn:cc2":"BO",
    "gn:country_code":"BO",
    "gn:dem":4017,
    "gn:feature_class":"P",
    "gn:feature_code":"PPL",
    "gn:name":"Kellcata",
    "gn:population":0,
    "gn:timezone":"America/La_Paz",
    "iso:country":"BO",
    "name:und_x_variant":[
        "Estancia Kellkhata",
        "Kellcata"
    ],
    "wof:name":"Kellcata",
    "wof:placetype":"locality"
},
  "geometry": {"coordinates":[-68.53333000000001,-17.85],"type":"Point"}
}