{
  "type": "Feature",
  "properties": {
    "gn:admin1_code":"4.0",
    "gn:asciiname":"Llave",
    "gn:country_code":"BO",
    "gn:dem":3958,
    "gn:feature_class":"P",
    "gn:feature_code":"PPL",
    "gn:name":"Llave",
    "gn:population":0,
    "gn:timezone":"America/La_Paz",
    "iso:country":"BO",
    "name:ita_x_preferred":[
        "Llave"
    ],
    "name:spa_x_preferred":[
        "Llave"
    ],
    "wof:name":"Llave",
    "wof:placetype":"locality"
},
  "geometry": {"coordinates":[-67.98333000000001,-16.83333],"type":"Point"}
}