{
  "type": "Feature",
  "properties": {
    "gn:admin1_code":"4.0",
    "gn:asciiname":"Tutirihuara",
    "gn:country_code":"BO",
    "gn:dem":1406,
    "gn:feature_class":"P",
    "gn:feature_code":"PPL",
    "gn:name":"Tutirihuara",
    "gn:population":0,
    "gn:timezone":"America/La_Paz",
    "iso:country":"BO",
    "wof:name":"Tutirihuara",
    "wof:placetype":"locality"
},
  "geometry": {"coordinates":[-67.65000000000001,-15.71667],"type":"Point"}
}