{
  "type": "Feature",
  "properties": {
    "gn:admin1_code":"1.0",
    "gn:asciiname":"Yanallpa",
    "gn:cc2":"BO",
    "gn:country_code":"BO",
    "gn:dem":1460,
    "gn:feature_class":"P",
    "gn:feature_code":"PPL",
    "gn:name":"Yanallpa",
    "gn:population":0,
    "gn:timezone":"America/La_Paz",
    "iso:country":"BO",
    "name:und_x_variant":[
        "Yanal pa",
        "Yanallpa"
    ],
    "wof:name":"Yanallpa",
    "wof:placetype":"locality"
},
  "geometry": {"coordinates":[-64.51666999999999,-18.85],"type":"Point"}
}