{
  "type": "Feature",
  "properties": {
    "gn:admin1_code":"7.0",
    "gn:asciiname":"Posta",
    "gn:cc2":"BO",
    "gn:country_code":"BO",
    "gn:dem":3743,
    "gn:feature_class":"P",
    "gn:feature_code":"PPL",
    "gn:name":"Posta",
    "gn:population":0,
    "gn:timezone":"America/La_Paz",
    "iso:country":"BO",
    "name:und_x_variant":[
        "Poste",
        "Posta"
    ],
    "wof:name":"Posta",
    "wof:placetype":"locality"
},
  "geometry": {"coordinates":[-67.09999999999999,-21.25],"type":"Point"}
}