{
  "type": "Feature",
  "properties": {
    "gn:admin1_code":"8.0",
    "gn:asciiname":"Santo Belisario",
    "gn:country_code":"BO",
    "gn:dem":526,
    "gn:feature_class":"P",
    "gn:feature_code":"PPL",
    "gn:name":"Santo Belisario",
    "gn:population":0,
    "gn:timezone":"America/La_Paz",
    "iso:country":"BO",
    "wof:name":"Santo Belisario",
    "wof:placetype":"locality"
},
  "geometry": {"coordinates":[-62.15,-16.65],"type":"Point"}
}