{
  "type": "Feature",
  "properties": {
    "gn:admin1_code":"9.0",
    "gn:asciiname":"Fortin D'Orbigny",
    "gn:country_code":"BO",
    "gn:dem":287,
    "gn:feature_class":"P",
    "gn:feature_code":"PPL",
    "gn:name":"Fort\u00edn D\u2019Orbigny",
    "gn:population":0,
    "gn:timezone":"America/La_Paz",
    "iso:country":"BO",
    "name:und_x_variant":[
        "D\u2019Orbigny",
        "Fort\u00edn Dorbigni",
        "D\u2019Orbigni",
        "Fort\u00edn D\u2019Orbigny"
    ],
    "wof:name":"Fortin D'Orbigny",
    "wof:placetype":"locality"
},
  "geometry": {"coordinates":[-62.82475,-21.99795],"type":"Point"}
}