{
  "type": "Feature",
  "properties": {
    "gn:admin1_code":"09",
    "gn:asciiname":"Anarenda",
    "gn:country_code":"BO",
    "gn:dem":972,
    "gn:feature_class":"P",
    "gn:feature_code":"PPL",
    "gn:name":"A\u00f1arenda",
    "gn:population":0,
    "gn:timezone":"America/La_Paz",
    "iso:country":"BO",
    "wof:name":"Anarenda",
    "wof:placetype":"locality"
},
  "geometry": {"coordinates":[-64.09999999999999,-21.06667],"type":"Point"}
}