{
  "type": "Feature",
  "properties": {
    "gn:admin1_code":"06",
    "gn:asciiname":"Callao",
    "gn:country_code":"BO",
    "gn:dem":146,
    "gn:feature_class":"P",
    "gn:feature_code":"PPL",
    "gn:name":"Callao",
    "gn:population":0,
    "gn:timezone":"America/La_Paz",
    "iso:country":"BO",
    "wof:name":"Callao",
    "wof:placetype":"locality"
},
  "geometry": {"coordinates":[-66.51666999999999,-10.85],"type":"Point"}
}