{
  "type": "Feature",
  "properties": {
    "gn:admin1_code":"7.0",
    "gn:asciiname":"Farellon",
    "gn:country_code":"BO",
    "gn:dem":4030,
    "gn:feature_class":"P",
    "gn:feature_code":"PPL",
    "gn:name":"Farell\u00f3n",
    "gn:population":0,
    "gn:timezone":"America/La_Paz",
    "iso:country":"BO",
    "wof:name":"Farellon",
    "wof:placetype":"locality"
},
  "geometry": {"coordinates":[-66.2054,-21.4063],"type":"Point"}
}