{
  "type": "Feature",
  "properties": {
    "gn:admin1_code":"04",
    "gn:asciiname":"Comunidad Chuni Chununi",
    "gn:country_code":"BO",
    "gn:dem":3909,
    "gn:feature_class":"P",
    "gn:feature_code":"PPL",
    "gn:name":"Comunidad Chu\u00f1i Chu\u00f1uni",
    "gn:population":0,
    "gn:timezone":"America/La_Paz",
    "iso:country":"BO",
    "wof:name":"Comunidad Chuni Chununi",
    "wof:placetype":"locality"
},
  "geometry": {"coordinates":[-68.58333,-16.61667000000001],"type":"Point"}
}