{
  "type": "Feature",
  "properties": {
    "gn:admin1_code":"1.0",
    "gn:asciiname":"Pirasillo",
    "gn:country_code":"BO",
    "gn:dem":1063,
    "gn:feature_class":"P",
    "gn:feature_code":"PPL",
    "gn:name":"Pirasillo",
    "gn:population":0,
    "gn:timezone":"America/La_Paz",
    "iso:country":"BO",
    "name:und_x_variant":[
        "Pirisilo",
        "Pirisito",
        "Pirasillo"
    ],
    "wof:name":"Pirasillo",
    "wof:placetype":"locality"
},
  "geometry": {"coordinates":[-63.96823000000001,-20.15248],"type":"Point"}
}