{
  "type": "Feature",
  "properties": {
    "gn:admin1_code":"5.0",
    "gn:asciiname":"Estancia Parcoya",
    "gn:country_code":"BO",
    "gn:dem":3680,
    "gn:feature_class":"P",
    "gn:feature_code":"PPL",
    "gn:name":"Estancia Parcoya",
    "gn:population":0,
    "gn:timezone":"America/La_Paz",
    "iso:country":"BO",
    "wof:name":"Estancia Parcoya",
    "wof:placetype":"locality"
},
  "geometry": {"coordinates":[-67.76461999999999,-19.10793],"type":"Point"}
}