{
  "type": "Feature",
  "properties": {
    "gn:admin1_code":"04",
    "gn:asciiname":"Estancia Chitcata",
    "gn:country_code":"BO",
    "gn:dem":3960,
    "gn:feature_class":"P",
    "gn:feature_code":"PPL",
    "gn:name":"Estancia Chitcata",
    "gn:population":0,
    "gn:timezone":"America/La_Paz",
    "iso:country":"BO",
    "wof:name":"Estancia Chitcata",
    "wof:placetype":"locality"
},
  "geometry": {"coordinates":[-69.01666999999999,-17.28333],"type":"Point"}
}