{
  "type": "Feature",
  "properties": {
    "gn:admin1_code":"4.0",
    "gn:asciiname":"Estancia Tuniri",
    "gn:country_code":"BO",
    "gn:dem":4093,
    "gn:feature_class":"P",
    "gn:feature_code":"PPL",
    "gn:name":"Estancia Tuniri",
    "gn:population":0,
    "gn:timezone":"America/La_Paz",
    "iso:country":"BO",
    "wof:name":"Estancia Tuniri",
    "wof:placetype":"locality"
},
  "geometry": {"coordinates":[-69.25,-17.28333],"type":"Point"}
}