{
  "type": "Feature",
  "properties": {
    "gn:admin1_code":"07",
    "gn:asciiname":"Estancia Kkollu Misi",
    "gn:country_code":"BO",
    "gn:dem":3755,
    "gn:feature_class":"P",
    "gn:feature_code":"PPL",
    "gn:name":"Estancia Kkollu Misi",
    "gn:population":0,
    "gn:timezone":"America/La_Paz",
    "iso:country":"BO",
    "wof:name":"Estancia Kkollu Misi",
    "wof:placetype":"locality"
},
  "geometry": {"coordinates":[-67.89668,-21.21289],"type":"Point"}
}