{
  "type": "Feature",
  "properties": {
    "gn:admin1_code":"4.0",
    "gn:asciiname":"Kasaamaya",
    "gn:cc2":"BO",
    "gn:country_code":"BO",
    "gn:dem":3904,
    "gn:feature_class":"P",
    "gn:feature_code":"PPL",
    "gn:name":"Kasaamaya",
    "gn:population":0,
    "gn:timezone":"America/La_Paz",
    "iso:country":"BO",
    "name:und_x_variant":[
        "Casamaya",
        "Kasaamaya"
    ],
    "wof:name":"Kasaamaya",
    "wof:placetype":"locality"
},
  "geometry": {"coordinates":[-68.61667,-16.05],"type":"Point"}
}