{
  "type": "Feature",
  "properties": {
    "gn:admin1_code":"01",
    "gn:asciiname":"Estancia Abajo",
    "gn:country_code":"BO",
    "gn:dem":2270,
    "gn:feature_class":"P",
    "gn:feature_code":"PPL",
    "gn:name":"Estancia Abajo",
    "gn:population":0,
    "gn:timezone":"America/La_Paz",
    "iso:country":"BO",
    "wof:name":"Estancia Abajo",
    "wof:placetype":"locality"
},
  "geometry": {"coordinates":[-64.9932,-20.99298],"type":"Point"}
}