{
  "type": "Feature",
  "properties": {
    "gn:admin1_code":"08",
    "gn:asciiname":"Boca Chapare",
    "gn:country_code":"BO",
    "gn:dem":190,
    "gn:feature_class":"P",
    "gn:feature_code":"PPL",
    "gn:name":"Boca Chapar\u00e9",
    "gn:population":0,
    "gn:timezone":"America/La_Paz",
    "iso:country":"BO",
    "wof:name":"Boca Chapare",
    "wof:placetype":"locality"
},
  "geometry": {"coordinates":[-64.68333,-15.93333],"type":"Point"}
}