{
  "type": "Feature",
  "properties": {
    "gn:admin1_code":"8.0",
    "gn:asciiname":"Lucero",
    "gn:country_code":"BO",
    "gn:dem":245,
    "gn:feature_class":"P",
    "gn:feature_code":"PPL",
    "gn:name":"Lucero",
    "gn:population":0,
    "gn:timezone":"America/La_Paz",
    "iso:country":"BO",
    "name:bre_x_preferred":[
        "Lucero"
    ],
    "name:ceb_x_preferred":[
        "Lucero"
    ],
    "name:deu_x_preferred":[
        "Lucero"
    ],
    "name:ita_x_preferred":[
        "Lucero"
    ],
    "name:por_x_preferred":[
        "Lucero"
    ],
    "name:sco_x_preferred":[
        "Lucero"
    ],
    "name:spa_x_preferred":[
        "Lucero"
    ],
    "name:swe_x_preferred":[
        "Lucero"
    ],
    "wof:name":"Lucero",
    "wof:placetype":"locality"
},
  "geometry": {"coordinates":[-61.66667,-14.38333],"type":"Point"}
}