{
  "type": "Feature",
  "properties": {
    "gn:admin1_code":"02",
    "gn:asciiname":"Alalay",
    "gn:country_code":"BO",
    "gn:dem":3993,
    "gn:feature_class":"P",
    "gn:feature_code":"PPL",
    "gn:name":"Alalay",
    "gn:population":0,
    "gn:timezone":"America/La_Paz",
    "iso:country":"BO",
    "wof:name":"Alalay",
    "wof:placetype":"locality"
},
  "geometry": {"coordinates":[-65.68333,-17.68332999999999],"type":"Point"}
}