{
  "type": "Feature",
  "properties": {
    "gn:admin1_code":"4.0",
    "gn:asciiname":"Hallancacho",
    "gn:country_code":"BO",
    "gn:dem":3784,
    "gn:feature_class":"P",
    "gn:feature_code":"PPL",
    "gn:name":"Hallancacho",
    "gn:population":0,
    "gn:timezone":"America/La_Paz",
    "iso:country":"BO",
    "wof:name":"Hallancacho",
    "wof:placetype":"locality"
},
  "geometry": {"coordinates":[-68.16667,-16.58333],"type":"Point"}
}