{
  "type": "Feature",
  "properties": {
    "gn:admin1_code":"7.0",
    "gn:asciiname":"Hura Chatena",
    "gn:country_code":"BO",
    "gn:dem":4024,
    "gn:feature_class":"P",
    "gn:feature_code":"PPL",
    "gn:name":"Hura Chatena",
    "gn:population":0,
    "gn:timezone":"America/La_Paz",
    "iso:country":"BO",
    "wof:name":"Hura Chatena",
    "wof:placetype":"locality"
},
  "geometry": {"coordinates":[-67.42256999999999,-21.8501],"type":"Point"}
}