{
  "type": "Feature",
  "properties": {
    "gn:admin1_code":"04",
    "gn:asciiname":"Achumani",
    "gn:country_code":"BO",
    "gn:dem":3468,
    "gn:feature_class":"P",
    "gn:feature_code":"PPL",
    "gn:name":"Achumani",
    "gn:population":0,
    "gn:timezone":"America/La_Paz",
    "iso:country":"BO",
    "wof:name":"Achumani",
    "wof:placetype":"locality"
},
  "geometry": {"coordinates":[-68.06667,-16.53333],"type":"Point"}
}