{
  "type": "Feature",
  "properties": {
    "gn:admin1_code":"09",
    "gn:asciiname":"Capirenda",
    "gn:country_code":"BO",
    "gn:dem":553,
    "gn:feature_class":"P",
    "gn:feature_code":"PPL",
    "gn:name":"Capirenda",
    "gn:population":0,
    "gn:timezone":"America/La_Paz",
    "iso:country":"BO",
    "wof:name":"Capirenda",
    "wof:placetype":"locality"
},
  "geometry": {"coordinates":[-63.01686,-21.10579],"type":"Point"}
}