{
  "type": "Feature",
  "properties": {
    "gn:admin1_code":"02",
    "gn:asciiname":"Comunidad Vilaque",
    "gn:country_code":"BO",
    "gn:dem":2896,
    "gn:feature_class":"P",
    "gn:feature_code":"PPL",
    "gn:name":"Comunidad Vilaque",
    "gn:population":0,
    "gn:timezone":"America/La_Paz",
    "iso:country":"BO",
    "wof:name":"Comunidad Vilaque",
    "wof:placetype":"locality"
},
  "geometry": {"coordinates":[-66.01666999999999,-17.66667],"type":"Point"}
}