{
  "type": "Feature",
  "properties": {
    "gn:admin1_code":"04",
    "gn:asciiname":"Cagua",
    "gn:country_code":"BO",
    "gn:dem":2129,
    "gn:feature_class":"P",
    "gn:feature_code":"PPL",
    "gn:name":"Cagua",
    "gn:population":0,
    "gn:timezone":"America/La_Paz",
    "iso:country":"BO",
    "wof:name":"Cagua",
    "wof:placetype":"locality"
},
  "geometry": {"coordinates":[-68.09999999999999,-15.86667],"type":"Point"}
}