{
  "type": "Feature",
  "properties": {
    "gn:admin1_code":"07",
    "gn:asciiname":"Chaquicancha",
    "gn:country_code":"BO",
    "gn:dem":3751,
    "gn:feature_class":"P",
    "gn:feature_code":"PPL",
    "gn:name":"Chaquicancha",
    "gn:population":0,
    "gn:timezone":"America/La_Paz",
    "iso:country":"BO",
    "wof:name":"Chaquicancha",
    "wof:placetype":"locality"
},
  "geometry": {"coordinates":[-65.89461,-21.80665],"type":"Point"}
}