{
  "type": "Feature",
  "properties": {
    "gn:admin1_code":"3.0",
    "gn:asciiname":"Los Marqueces",
    "gn:cc2":"BO",
    "gn:country_code":"BO",
    "gn:dem":177,
    "gn:feature_class":"P",
    "gn:feature_code":"PPL",
    "gn:name":"Los Marqueces",
    "gn:population":0,
    "gn:timezone":"America/La_Paz",
    "iso:country":"BO",
    "name:und_x_variant":[
        "Los Magueses",
        "Los Marqueces"
    ],
    "wof:name":"Los Marqueces",
    "wof:placetype":"locality"
},
  "geometry": {"coordinates":[-64.38333,-15.46667],"type":"Point"}
}