{
  "type": "Feature",
  "properties": {
    "gn:admin1_code":"7.0",
    "gn:asciiname":"Livichuco",
    "gn:country_code":"BO",
    "gn:dem":4181,
    "gn:feature_class":"P",
    "gn:feature_code":"PPL",
    "gn:name":"Livichuco",
    "gn:population":0,
    "gn:timezone":"America/La_Paz",
    "iso:country":"BO",
    "wof:name":"Livichuco",
    "wof:placetype":"locality"
},
  "geometry": {"coordinates":[-66.42978000000001,-18.88974],"type":"Point"}
}