{
  "type": "Feature",
  "properties": {
    "gn:admin1_code":"4.0",
    "gn:asciiname":"Quilihuyo",
    "gn:country_code":"BO",
    "gn:dem":3958,
    "gn:feature_class":"P",
    "gn:feature_code":"PPL",
    "gn:name":"Quilihuyo",
    "gn:population":0,
    "gn:timezone":"America/La_Paz",
    "iso:country":"BO",
    "name:spa_x_preferred":[
        "Quilihuyo"
    ],
    "name:spa_x_variant":[
        "Comunidad Quillihuy"
    ],
    "name:und_x_variant":[
        "Comunidad Quilli Huyo",
        "Quili Huyo"
    ],
    "wof:name":"Quilihuyo",
    "wof:placetype":"locality"
},
  "geometry": {"coordinates":[-69.10256,-15.42568],"type":"Point"}
}