{
  "type": "Feature",
  "properties": {
    "gn:admin1_code":"5.0",
    "gn:asciiname":"Quillita",
    "gn:country_code":"BO",
    "gn:dem":3819,
    "gn:feature_class":"P",
    "gn:feature_code":"PPL",
    "gn:name":"Quillita",
    "gn:population":0,
    "gn:timezone":"America/La_Paz",
    "iso:country":"BO",
    "wof:name":"Quillita",
    "wof:placetype":"locality"
},
  "geometry": {"coordinates":[-68.68333,-18.43333],"type":"Point"}
}