{
  "type": "Feature",
  "properties": {
    "gn:admin1_code":"7.0",
    "gn:asciiname":"Estancia Wila Ananoko",
    "gn:country_code":"BO",
    "gn:dem":4135,
    "gn:feature_class":"P",
    "gn:feature_code":"PPL",
    "gn:name":"Estancia Wila Ananoko",
    "gn:population":0,
    "gn:timezone":"America/La_Paz",
    "iso:country":"BO",
    "wof:name":"Estancia Wila Ananoko",
    "wof:placetype":"locality"
},
  "geometry": {"coordinates":[-66.59999999999999,-20.06667],"type":"Point"}
}