{
  "type": "Feature",
  "properties": {
    "gn:admin1_code":"07",
    "gn:asciiname":"Estancia Jatun Jara",
    "gn:country_code":"BO",
    "gn:dem":2966,
    "gn:feature_class":"P",
    "gn:feature_code":"PPL",
    "gn:name":"Estancia Jatun Jara",
    "gn:population":0,
    "gn:timezone":"America/La_Paz",
    "iso:country":"BO",
    "wof:name":"Estancia Jatun Jara",
    "wof:placetype":"locality"
},
  "geometry": {"coordinates":[-65.61133000000001,-20.28431],"type":"Point"}
}