{
  "type": "Feature",
  "properties": {
    "gn:admin1_code":"1.0",
    "gn:asciiname":"Molinos",
    "gn:country_code":"BO",
    "gn:dem":3257,
    "gn:feature_class":"P",
    "gn:feature_code":"PPL",
    "gn:name":"Molinos",
    "gn:population":0,
    "gn:timezone":"America/La_Paz",
    "iso:country":"BO",
    "name:arg_x_preferred":[
        "Molinos"
    ],
    "name:cat_x_preferred":[
        "Molinos"
    ],
    "name:ceb_x_preferred":[
        "Molinos"
    ],
    "name:deu_x_preferred":[
        "Molinos"
    ],
    "name:fra_x_preferred":[
        "Molinos"
    ],
    "name:hun_x_preferred":[
        "Molinos"
    ],
    "name:hye_x_preferred":[
        "\u0544\u0578\u056c\u056b\u0576\u0578\u057d"
    ],
    "name:ita_x_preferred":[
        "Molinos"
    ],
    "name:nld_x_preferred":[
        "Molinos"
    ],
    "name:por_x_preferred":[
        "Molinos"
    ],
    "name:rus_x_preferred":[
        "\u041c\u043e\u043b\u0438\u043d\u043e\u0441"
    ],
    "name:spa_x_preferred":[
        "Molinos"
    ],
    "name:srp_x_preferred":[
        "\u041c\u043e\u043b\u0438\u043d\u043e\u0441"
    ],
    "name:swe_x_preferred":[
        "Molinos"
    ],
    "wof:name":"Molinos",
    "wof:placetype":"locality"
},
  "geometry": {"coordinates":[-65.11667,-20.13333],"type":"Point"}
}