{
  "type": "Feature",
  "properties": {
    "gn:admin1_code":"2.0",
    "gn:asciiname":"Ituchi",
    "gn:country_code":"BO",
    "gn:dem":1946,
    "gn:feature_class":"P",
    "gn:feature_code":"PPL",
    "gn:name":"Ituchi",
    "gn:population":0,
    "gn:timezone":"America/La_Paz",
    "iso:country":"BO",
    "wof:name":"Ituchi",
    "wof:placetype":"locality"
},
  "geometry": {"coordinates":[-65.26666999999999,-17.91667],"type":"Point"}
}