{
  "type": "Feature",
  "properties": {
    "gn:admin1_code":"7.0",
    "gn:asciiname":"Selvayoc",
    "gn:country_code":"BO",
    "gn:dem":4049,
    "gn:feature_class":"P",
    "gn:feature_code":"PPL",
    "gn:name":"Selvayoc",
    "gn:population":0,
    "gn:timezone":"America/La_Paz",
    "iso:country":"BO",
    "wof:name":"Selvayoc",
    "wof:placetype":"locality"
},
  "geometry": {"coordinates":[-65.88333,-21.08333],"type":"Point"}
}