{
  "type": "Feature",
  "properties": {
    "gn:admin1_code":"4.0",
    "gn:asciiname":"Guelequelera",
    "gn:cc2":"BO",
    "gn:country_code":"BO",
    "gn:dem":1012,
    "gn:feature_class":"P",
    "gn:feature_code":"PPL",
    "gn:name":"Guelequelera",
    "gn:population":0,
    "gn:timezone":"America/La_Paz",
    "iso:country":"BO",
    "name:und_x_variant":[
        "Gualequera",
        "Guelequelera"
    ],
    "wof:name":"Guelequelera",
    "wof:placetype":"locality"
},
  "geometry": {"coordinates":[-67.88333,-15.45],"type":"Point"}
}