{
  "type": "Feature",
  "properties": {
    "gn:admin1_code":"1.0",
    "gn:asciiname":"Puerto Central",
    "gn:country_code":"BO",
    "gn:dem":669,
    "gn:feature_class":"P",
    "gn:feature_code":"PPL",
    "gn:name":"Puerto Central",
    "gn:population":0,
    "gn:timezone":"America/La_Paz",
    "iso:country":"BO",
    "wof:name":"Puerto Central",
    "wof:placetype":"locality"
},
  "geometry": {"coordinates":[-63.08333,-20.83333],"type":"Point"}
}