{
  "type": "Feature",
  "properties": {
    "gn:admin1_code":"1.0",
    "gn:asciiname":"Las Abras",
    "gn:country_code":"BO",
    "gn:dem":2428,
    "gn:feature_class":"P",
    "gn:feature_code":"PPL",
    "gn:name":"Las Abras",
    "gn:population":0,
    "gn:timezone":"America/La_Paz",
    "iso:country":"BO",
    "wof:name":"Las Abras",
    "wof:placetype":"locality"
},
  "geometry": {"coordinates":[-64.36667,-20.13333],"type":"Point"}
}