{
  "type": "Feature",
  "properties": {
    "gn:admin1_code":"09",
    "gn:asciiname":"Chirimayu",
    "gn:country_code":"BO",
    "gn:dem":3769,
    "gn:feature_class":"P",
    "gn:feature_code":"PPL",
    "gn:name":"Chirimayu",
    "gn:population":0,
    "gn:timezone":"America/La_Paz",
    "iso:country":"BO",
    "wof:name":"Chirimayu",
    "wof:placetype":"locality"
},
  "geometry": {"coordinates":[-65.09950000000001,-21.94706],"type":"Point"}
}