{
  "type": "Feature",
  "properties": {
    "gn:admin1_code":"5.0",
    "gn:asciiname":"Huallchapi",
    "gn:cc2":"BO",
    "gn:country_code":"BO",
    "gn:dem":3725,
    "gn:feature_class":"P",
    "gn:feature_code":"PPL",
    "gn:name":"Huallchapi",
    "gn:population":0,
    "gn:timezone":"America/La_Paz",
    "iso:country":"BO",
    "name:und_x_variant":[
        "Estancia Huallchapi",
        "Huallchapi"
    ],
    "wof:name":"Huallchapi",
    "wof:placetype":"locality"
},
  "geometry": {"coordinates":[-67.34999999999999,-17.86667000000001],"type":"Point"}
}