{
  "type": "Feature",
  "properties": {
    "gn:admin1_code":"06",
    "gn:asciiname":"Copacabana",
    "gn:country_code":"BO",
    "gn:dem":202,
    "gn:feature_class":"P",
    "gn:feature_code":"PPL",
    "gn:name":"Copacabana",
    "gn:population":0,
    "gn:timezone":"America/La_Paz",
    "iso:country":"BO",
    "wof:name":"Copacabana",
    "wof:placetype":"locality"
},
  "geometry": {"coordinates":[-67.96666999999999,-11.25],"type":"Point"}
}