{
  "type": "Feature",
  "properties": {
    "gn:admin1_code":"06",
    "gn:asciiname":"Copacabana",
    "gn:country_code":"BO",
    "gn:dem":202,
    "gn:feature_class":"P",
    "gn:feature_code":"PPL",
    "gn:name":"Copacabana",
    "gn:population":0,
    "gn:timezone":"America/La_Paz",
    "iso:country":"BO",
    "name:cat_x_preferred":[
        "Copacabana"
    ],
    "name:ceb_x_preferred":[
        "Copacabana"
    ],
    "name:deu_x_preferred":[
        "Copacabana"
    ],
    "name:fra_x_preferred":[
        "Copacabana"
    ],
    "name:ita_x_preferred":[
        "Copacabana"
    ],
    "name:jpn_x_preferred":[
        "\u30b3\u30d1\u30ab\u30d0\u30fc\u30ca"
    ],
    "name:kor_x_preferred":[
        "\ucf54\ud30c\uce74\ubc14\ub098"
    ],
    "name:mlg_x_preferred":[
        "Copacabana"
    ],
    "name:nld_x_preferred":[
        "Copacabana"
    ],
    "name:nor_x_preferred":[
        "Copacabana"
    ],
    "name:pol_x_preferred":[
        "Copacabana"
    ],
    "name:por_x_preferred":[
        "Copacabana"
    ],
    "name:que_x_preferred":[
        "Copacabana"
    ],
    "name:ron_x_preferred":[
        "Copacabana"
    ],
    "name:rus_x_preferred":[
        "\u041a\u043e\u043f\u0430\u043a\u0430\u0431\u0430\u043d\u0430"
    ],
    "name:sco_x_preferred":[
        "Copacabana"
    ],
    "name:spa_x_preferred":[
        "Copacabana"
    ],
    "name:swe_x_preferred":[
        "Copacabana"
    ],
    "wof:name":"Copacabana",
    "wof:placetype":"locality"
},
  "geometry": {"coordinates":[-67.96666999999999,-11.25],"type":"Point"}
}