{
  "type": "Feature",
  "properties": {
    "gn:admin1_code":"06",
    "gn:asciiname":"Remanso",
    "gn:country_code":"BO",
    "gn:dem":189,
    "gn:feature_class":"P",
    "gn:feature_code":"PPL",
    "gn:name":"Remanso",
    "gn:population":0,
    "gn:timezone":"America/La_Paz",
    "iso:country":"BO",
    "name:ara_x_preferred":[
        "\u0631\u064a\u0645\u0627\u0646\u0633\u0648"
    ],
    "name:ben_x_preferred":[
        "\u09b0\u09c7\u09ae\u09be\u09a8\u09cd\u09b8\u09cb"
    ],
    "name:bpy_x_preferred":[
        "\u09b0\u09c7\u09ae\u09be\u09a8\u09cd\u09b8\u09cb"
    ],
    "name:bul_x_preferred":[
        "\u0420\u0435\u043c\u0430\u043d\u0441\u043e"
    ],
    "name:ceb_x_preferred":[
        "Remanso"
    ],
    "name:ell_x_preferred":[
        "\u03a1\u03b5\u03bc\u03ac\u03bd\u03c3\u03bf"
    ],
    "name:epo_x_preferred":[
        "Remanso"
    ],
    "name:eus_x_preferred":[
        "Remanso"
    ],
    "name:fas_x_preferred":[
        "\u0631\u0645\u0627\u0646\u0633\u0648"
    ],
    "name:fra_x_preferred":[
        "Remanso"
    ],
    "name:heb_x_preferred":[
        "\u05e8\u05de\u05e0\u05e1\u05d5"
    ],
    "name:hin_x_preferred":[
        "\u0930\u0947\u092e\u093e\u0902\u0938\u094b"
    ],
    "name:hye_x_preferred":[
        "\u054c\u0565\u0574\u0561\u0576\u057d\u0578\u0582"
    ],
    "name:ind_x_preferred":[
        "Remanso"
    ],
    "name:ita_x_preferred":[
        "Remanso"
    ],
    "name:jpn_x_preferred":[
        "\u30ec\u30de\u30f3\u30bd"
    ],
    "name:kat_x_preferred":[
        "\u10e0\u10d4\u10db\u10d0\u10dc\u10e1\u10e3"
    ],
    "name:kaz_x_preferred":[
        "\u0420\u0435\u043c\u0430\u043d\u0441\u0443"
    ],
    "name:kor_x_preferred":[
        "\ub808\ub9cc\uc18c"
    ],
    "name:mlg_x_preferred":[
        "Remanso"
    ],
    "name:nld_x_preferred":[
        "Remanso"
    ],
    "name:nor_x_preferred":[
        "Remanso"
    ],
    "name:pol_x_preferred":[
        "Remanso"
    ],
    "name:por_x_preferred":[
        "Remanso"
    ],
    "name:ron_x_preferred":[
        "Remanso"
    ],
    "name:rus_x_preferred":[
        "\u0420\u0435\u043c\u0430\u043d\u0441\u0443"
    ],
    "name:spa_x_preferred":[
        "Remanso"
    ],
    "name:swe_x_preferred":[
        "Remanso"
    ],
    "name:tur_x_preferred":[
        "Remanso"
    ],
    "name:ukr_x_preferred":[
        "\u0420\u0435\u043c\u0430\u043d\u0441\u0443"
    ],
    "name:urd_x_preferred":[
        "\u0631\u06cc\u0645\u0627\u0646\u0633\u0648"
    ],
    "name:vie_x_preferred":[
        "Remanso"
    ],
    "name:vol_x_preferred":[
        "Remanso"
    ],
    "name:war_x_preferred":[
        "Remanso"
    ],
    "name:zho_x_preferred":[
        "\u96f7\u66fc\u82cf"
    ],
    "wof:name":"Remanso",
    "wof:placetype":"locality"
},
  "geometry": {"coordinates":[-68.06019000000001,-11.78399],"type":"Point"}
}