{
  "type": "Feature",
  "properties": {
    "gn:admin1_code":"06",
    "gn:asciiname":"Remanso",
    "gn:country_code":"BO",
    "gn:dem":189,
    "gn:feature_class":"P",
    "gn:feature_code":"PPL",
    "gn:name":"Remanso",
    "gn:population":0,
    "gn:timezone":"America/La_Paz",
    "iso:country":"BO",
    "name:spa_x_preferred":[
        "Remanso"
    ],
    "wof:name":"Remanso",
    "wof:placetype":"locality"
},
  "geometry": {"coordinates":[-68.06019000000001,-11.78399],"type":"Point"}
}