{
  "type": "Feature",
  "properties": {
    "gn:admin1_code":"05",
    "gn:asciiname":"Khara Huamo",
    "gn:country_code":"BO",
    "gn:dem":3777,
    "gn:feature_class":"P",
    "gn:feature_code":"PPL",
    "gn:name":"Khara Huamo",
    "gn:population":0,
    "gn:timezone":"America/La_Paz",
    "iso:country":"BO",
    "wof:name":"Khara Huamo",
    "wof:placetype":"locality"
},
  "geometry": {"coordinates":[-68.51456,-18.65292],"type":"Point"}
}