{
  "type": "Feature",
  "properties": {
    "gn:admin1_code":"1.0",
    "gn:asciiname":"Huache",
    "gn:country_code":"BO",
    "gn:dem":1288,
    "gn:feature_class":"P",
    "gn:feature_code":"PPL",
    "gn:name":"Huache",
    "gn:population":0,
    "gn:timezone":"America/La_Paz",
    "iso:country":"BO",
    "wof:name":"Huache",
    "wof:placetype":"locality"
},
  "geometry": {"coordinates":[-64.19465,-20.3512],"type":"Point"}
}