{
  "type": "Feature",
  "properties": {
    "gn:admin1_code":"05",
    "gn:asciiname":"Estancia Crusani",
    "gn:country_code":"BO",
    "gn:dem":4177,
    "gn:feature_class":"P",
    "gn:feature_code":"PPL",
    "gn:name":"Estancia Crusani",
    "gn:population":0,
    "gn:timezone":"America/La_Paz",
    "iso:country":"BO",
    "wof:name":"Estancia Crusani",
    "wof:placetype":"locality"
},
  "geometry": {"coordinates":[-68.83968,-19.05447],"type":"Point"}
}