{
  "type": "Feature",
  "properties": {
    "gn:admin1_code":"02",
    "gn:asciiname":"Coyaviri",
    "gn:cc2":"BO",
    "gn:country_code":"BO",
    "gn:dem":3054,
    "gn:feature_class":"P",
    "gn:feature_code":"PPL",
    "gn:name":"Coyaviri",
    "gn:population":0,
    "gn:timezone":"America/La_Paz",
    "iso:country":"BO",
    "name:und_x_variant":[
        "Ovejario",
        "Coyaviri"
    ],
    "wof:name":"Coyaviri",
    "wof:placetype":"locality"
},
  "geometry": {"coordinates":[-66.23333000000001,-17.83333],"type":"Point"}
}