{
  "type": "Feature",
  "properties": {
    "gn:admin1_code":"01",
    "gn:admin2_code":"109.0",
    "gn:admin3_code":"2.0",
    "gn:admin4_code":"1.0",
    "gn:asciiname":"Culpina",
    "gn:country_code":"BO",
    "gn:dem":2972,
    "gn:feature_class":"P",
    "gn:feature_code":"PPLA4",
    "gn:name":"Culpina",
    "gn:population":0,
    "gn:timezone":"America/La_Paz",
    "iso:country":"BO",
    "name:deu_x_preferred":[
        "Culpina"
    ],
    "name:nor_x_preferred":[
        "Culpina"
    ],
    "name:que_x_preferred":[
        "K'ullpina"
    ],
    "name:zho_x_preferred":[
        "\u5eab\u723e\u76ae\u7d0d"
    ],
    "wof:name":"Culpina",
    "wof:placetype":"locality"
},
  "geometry": {"coordinates":[-64.94492,-20.82358],"type":"Point"}
}