{
  "type": "Feature",
  "properties": {
    "gn:admin1_code":"6.0",
    "gn:asciiname":"Magdalena",
    "gn:country_code":"BO",
    "gn:dem":108,
    "gn:feature_class":"P",
    "gn:feature_code":"PPL",
    "gn:name":"Magdalena",
    "gn:population":0,
    "gn:timezone":"America/La_Paz",
    "iso:country":"BO",
    "wof:name":"Magdalena",
    "wof:placetype":"locality"
},
  "geometry": {"coordinates":[-65.78333000000001,-9.78333],"type":"Point"}
}