{
  "type": "Feature",
  "properties": {
    "gn:admin1_code":"7.0",
    "gn:asciiname":"Llanacienega",
    "gn:country_code":"BO",
    "gn:dem":4312,
    "gn:feature_class":"P",
    "gn:feature_code":"PPL",
    "gn:name":"Llanaci\u00e9nega",
    "gn:population":0,
    "gn:timezone":"America/La_Paz",
    "iso:country":"BO",
    "wof:name":"Llanacienega",
    "wof:placetype":"locality"
},
  "geometry": {"coordinates":[-66.53333000000001,-21.53333],"type":"Point"}
}