{
  "type": "Feature",
  "properties": {
    "iso:country":"BO",
    "name:ceb_x_preferred":[
        "Buena Vista"
    ],
    "name:deu_x_preferred":[
        "Buena Vista"
    ],
    "name:eng_x_preferred":[
        "Buena Vista"
    ],
    "name:fra_x_preferred":[
        "Buena Vista"
    ],
    "name:nld_x_preferred":[
        "Buena Vista"
    ],
    "name:que_x_preferred":[
        "Buena Vista"
    ],
    "name:spa_x_preferred":[
        "Buena Vista"
    ],
    "name:swe_x_preferred":[
        "Buena Vista"
    ],
    "name:urd_x_preferred":[
        "\u0628\u06cc\u0644\u0627 \u0648\u0633\u0679\u0627"
    ],
    "name:urd_x_variant":[
        "\u0628\u06cc\u0648\u06cc\u0646\u0627 \u0648\u0633\u0679\u0627",
        "\u0628\u06cc\u0648\u06cc\u0646\u0627 \u0648\u0633\u0679\u0627\u060c \u0627\u0686\u06cc\u0644\u0648"
    ],
    "name:vie_x_preferred":[
        "Bella Vista"
    ],
    "name:war_x_preferred":[
        "Buena Vista"
    ],
    "name:zho_x_preferred":[
        "\u5e03\u57c3\u7d0d\u7dad\u65af\u5854"
    ],
    "qs:gn_country":"BO",
    "qs:gn_fcode":"PPL",
    "qs:gn_pop":4282,
    "qs:name":"Bella Vista",
    "qs:name_adm0":"Bolivia",
    "qs:name_adm1":"Santa Cruz",
    "qs:photos":0,
    "qs:photos_1k":0,
    "qs:photos_9k":0,
    "qs:photos_9r":0,
    "qs:photos_all":0,
    "qs:photos_sr":0,
    "qs:placetype":"Town",
    "qs:pop_sr":"4",
    "qs:woe_adm0":23424762,
    "wof:name":"Bella Vista",
    "wof:placetype":"locality",
    "wof:population":4282
},
  "geometry": {"coordinates":[-63.66667,-17.45],"type":"Point"}
}