{
  "type": "Feature",
  "properties": {
    "gn:country":"BO",
    "gn:fcode":"PPL",
    "gn:pop":4944,
    "iso:country":"BO",
    "name:deu_x_preferred":[
        "Municipio Okinawa Uno"
    ],
    "name:eng_x_preferred":[
        "Okinawa Uno"
    ],
    "name:ita_x_preferred":[
        "Okinawa Uno"
    ],
    "name:jpn_x_preferred":[
        "\u30aa\u30ad\u30ca\u30ef\u30fb\u30a6\u30ce"
    ],
    "name:que_x_preferred":[
        "Ukinawa munisipyu"
    ],
    "name:spa_x_preferred":[
        "Municipio de Okinawa Uno"
    ],
    "name:swe_x_preferred":[
        "Okinawa N\u00famero Uno"
    ],
    "qs:name":"Okinawa N\u00famero Uno",
    "qs:photos_9r":0,
    "qs:photos_sr":0,
    "qs:pop_sr":"4",
    "wof:name":"Okinawa N\u00famero Uno",
    "wof:placetype":"locality",
    "wof:population":4944
},
  "geometry": {"coordinates":[-62.81667,-17.23333],"type":"Point"}
}