{
  "type": "Feature",
  "properties": {
    "gn:admin1_code":"07",
    "gn:asciiname":"El Turqui",
    "gn:country_code":"BO",
    "gn:dem":3933,
    "gn:feature_class":"P",
    "gn:feature_code":"PPL",
    "gn:name":"El Turqui",
    "gn:population":0,
    "gn:timezone":"America/La_Paz",
    "iso:country":"BO",
    "name:und_x_variant":[
        "Mina El Turqui",
        "El Turqui"
    ],
    "wof:name":"El Turqui",
    "wof:placetype":"locality"
},
  "geometry": {"coordinates":[-65.97951999999999,-19.4419],"type":"Point"}
}