{
  "type": "Feature",
  "properties": {
    "gn:admin1_code":"07",
    "gn:asciiname":"Cenotcha",
    "gn:cc2":"BO",
    "gn:country_code":"BO",
    "gn:dem":4360,
    "gn:feature_class":"P",
    "gn:feature_code":"PPL",
    "gn:name":"Cenotcha",
    "gn:population":0,
    "gn:timezone":"America/La_Paz",
    "iso:country":"BO",
    "name:und_x_variant":[
        "Cenoicha",
        "Cercicha",
        "Cenotcha"
    ],
    "wof:name":"Cenotcha",
    "wof:placetype":"locality"
},
  "geometry": {"coordinates":[-68.38333,-20.98333],"type":"Point"}
}