{
  "type": "Feature",
  "properties": {
    "gn:admin1_code":"04",
    "gn:asciiname":"Comunidad Sicuani",
    "gn:country_code":"BO",
    "gn:dem":4026,
    "gn:feature_class":"P",
    "gn:feature_code":"PPL",
    "gn:name":"Comunidad Sicuani",
    "gn:population":0,
    "gn:timezone":"America/La_Paz",
    "iso:country":"BO",
    "wof:name":"Comunidad Sicuani",
    "wof:placetype":"locality"
},
  "geometry": {"coordinates":[-69.09999999999999,-16.08333],"type":"Point"}
}