{
  "type": "Feature",
  "properties": {
    "gn:admin1_code":"07",
    "gn:asciiname":"Chuquiuta",
    "gn:country_code":"BO",
    "gn:dem":3594,
    "gn:feature_class":"P",
    "gn:feature_code":"PPL",
    "gn:name":"Chuquiuta",
    "gn:population":0,
    "gn:timezone":"America/La_Paz",
    "iso:country":"BO",
    "wof:name":"Chuquiuta",
    "wof:placetype":"locality"
},
  "geometry": {"coordinates":[-66.36069999999999,-18.59241],"type":"Point"}
}