{
  "type": "Feature",
  "properties": {
    "gn:admin1_code":"8.0",
    "gn:asciiname":"Junin",
    "gn:country_code":"BO",
    "gn:dem":245,
    "gn:feature_class":"P",
    "gn:feature_code":"PPL",
    "gn:name":"Jun\u00edn",
    "gn:population":0,
    "gn:timezone":"America/La_Paz",
    "iso:country":"BO",
    "wof:name":"Junin",
    "wof:placetype":"locality"
},
  "geometry": {"coordinates":[-61.39381,-14.86894],"type":"Point"}
}