{
  "type": "Feature",
  "properties": {
    "gn:admin1_code":"07",
    "gn:asciiname":"Agua Chica",
    "gn:country_code":"BO",
    "gn:dem":3842,
    "gn:feature_class":"P",
    "gn:feature_code":"PPL",
    "gn:name":"Agua Chica",
    "gn:population":0,
    "gn:timezone":"America/La_Paz",
    "iso:country":"BO",
    "wof:name":"Agua Chica",
    "wof:placetype":"locality"
},
  "geometry": {"coordinates":[-66.05,-21.71667],"type":"Point"}
}