{
  "type": "Feature",
  "properties": {
    "gn:admin1_code":"1.0",
    "gn:asciiname":"La Cueva Chica",
    "gn:cc2":"BO",
    "gn:country_code":"BO",
    "gn:dem":3247,
    "gn:feature_class":"P",
    "gn:feature_code":"PPL",
    "gn:name":"La Cueva Chica",
    "gn:population":0,
    "gn:timezone":"America/La_Paz",
    "iso:country":"BO",
    "name:und_x_variant":[
        "Cueva Chica",
        "La Cueva Chica"
    ],
    "wof:name":"La Cueva Chica",
    "wof:placetype":"locality"
},
  "geometry": {"coordinates":[-65.34999999999999,-20.98333],"type":"Point"}
}