{
  "type": "Feature",
  "properties": {
    "gn:admin1_code":"06",
    "gn:asciiname":"Arayal",
    "gn:country_code":"BO",
    "gn:dem":270,
    "gn:feature_class":"P",
    "gn:feature_code":"PPL",
    "gn:name":"Arayal",
    "gn:population":0,
    "gn:timezone":"America/La_Paz",
    "iso:country":"BO",
    "wof:name":"Arayal",
    "wof:placetype":"locality"
},
  "geometry": {"coordinates":[-69.06274000000001,-11.58156],"type":"Point"}
}