{
  "type": "Feature",
  "properties": {
    "gn:admin1_code":"5.0",
    "gn:asciiname":"Japo",
    "gn:country_code":"BO",
    "gn:dem":4088,
    "gn:feature_class":"P",
    "gn:feature_code":"PPL",
    "gn:name":"Japo",
    "gn:population":0,
    "gn:timezone":"America/La_Paz",
    "iso:country":"BO",
    "wof:name":"Japo",
    "wof:placetype":"locality"
},
  "geometry": {"coordinates":[-66.4901,-18.90798],"type":"Point"}
}