{
  "type": "Feature",
  "properties": {
    "gn:admin1_code":"8.0",
    "gn:asciiname":"Nueva Esperanza",
    "gn:cc2":"BO",
    "gn:country_code":"BO",
    "gn:dem":272,
    "gn:feature_class":"P",
    "gn:feature_code":"PPL",
    "gn:name":"Nueva Esperanza",
    "gn:population":0,
    "gn:timezone":"America/La_Paz",
    "iso:country":"BO",
    "name:und_x_variant":[
        "Estancia Nueva Esperanza",
        "Nueva Esperanza"
    ],
    "wof:name":"Nueva Esperanza",
    "wof:placetype":"locality"
},
  "geometry": {"coordinates":[-62.76667,-17.23333],"type":"Point"}
}