{
  "type": "Feature",
  "properties": {
    "gn:admin1_code":"06",
    "gn:asciiname":"Trailal",
    "gn:country_code":"BO",
    "gn:dem":230,
    "gn:feature_class":"P",
    "gn:feature_code":"PPL",
    "gn:name":"Trailal",
    "gn:population":0,
    "gn:timezone":"America/La_Paz",
    "iso:country":"BO",
    "name:spa_x_preferred":[
        "Trailal"
    ],
    "wof:name":"Trailal",
    "wof:placetype":"locality"
},
  "geometry": {"coordinates":[-68.47508000000001,-11.21324],"type":"Point"}
}