{
  "type": "Feature",
  "properties": {
    "gn:admin1_code":"01",
    "gn:asciiname":"Comunidad Khakha",
    "gn:country_code":"BO",
    "gn:dem":2303,
    "gn:feature_class":"P",
    "gn:feature_code":"PPL",
    "gn:name":"Comunidad Khakha",
    "gn:population":0,
    "gn:timezone":"America/La_Paz",
    "iso:country":"BO",
    "wof:name":"Comunidad Khakha",
    "wof:placetype":"locality"
},
  "geometry": {"coordinates":[-65.00416,-19.28796],"type":"Point"}
}