{
  "type": "Feature",
  "properties": {
    "gn:admin1_code":"5.0",
    "gn:asciiname":"Huayllatiri",
    "gn:cc2":"BO",
    "gn:country_code":"BO",
    "gn:dem":3996,
    "gn:feature_class":"P",
    "gn:feature_code":"PPL",
    "gn:name":"Huayllatiri",
    "gn:population":0,
    "gn:timezone":"America/La_Paz",
    "iso:country":"BO",
    "name:und_x_variant":[
        "Estancia Huayllatira",
        "Huayllatiri"
    ],
    "wof:name":"Huayllatiri",
    "wof:placetype":"locality"
},
  "geometry": {"coordinates":[-66.86667,-17.88332999999999],"type":"Point"}
}