{
  "type": "Feature",
  "properties": {
    "gn:admin1_code":"2.0",
    "gn:asciiname":"San Miguel de Aquerana",
    "gn:country_code":"BO",
    "gn:dem":3768,
    "gn:feature_class":"P",
    "gn:feature_code":"PPL",
    "gn:name":"San Miguel de Aquerana",
    "gn:population":0,
    "gn:timezone":"America/La_Paz",
    "iso:country":"BO",
    "wof:name":"San Miguel de Aquerana",
    "wof:placetype":"locality"
},
  "geometry": {"coordinates":[-66.58333,-17.76667],"type":"Point"}
}