{
  "type": "Feature",
  "properties": {
    "gn:admin1_code":"04",
    "gn:asciiname":"Coniri",
    "gn:country_code":"BO",
    "gn:dem":3890,
    "gn:feature_class":"P",
    "gn:feature_code":"PPL",
    "gn:name":"Coniri",
    "gn:population":0,
    "gn:timezone":"America/La_Paz",
    "iso:country":"BO",
    "wof:name":"Coniri",
    "wof:placetype":"locality"
},
  "geometry": {"coordinates":[-68.28333000000001,-16.86667000000001],"type":"Point"}
}