{
  "type": "Feature",
  "properties": {
    "gn:admin1_code":"2.0",
    "gn:asciiname":"Pascollo",
    "gn:country_code":"BO",
    "gn:dem":2252,
    "gn:feature_class":"P",
    "gn:feature_code":"PPL",
    "gn:name":"Pascollo",
    "gn:population":0,
    "gn:timezone":"America/La_Paz",
    "iso:country":"BO",
    "wof:name":"Pascollo",
    "wof:placetype":"locality"
},
  "geometry": {"coordinates":[-64.78333000000001,-17.71667],"type":"Point"}
}