{
  "type": "Feature",
  "properties": {
    "gn:admin1_code":"05",
    "gn:asciiname":"Caico",
    "gn:country_code":"BO",
    "gn:dem":3794,
    "gn:feature_class":"P",
    "gn:feature_code":"PPL",
    "gn:name":"Caico",
    "gn:population":0,
    "gn:timezone":"America/La_Paz",
    "iso:country":"BO",
    "wof:name":"Caico",
    "wof:placetype":"locality"
},
  "geometry": {"coordinates":[-67.71666999999999,-19.83333],"type":"Point"}
}