{
  "type": "Feature",
  "properties": {
    "gn:admin1_code":"07",
    "gn:asciiname":"Estancia Irpa Yapo",
    "gn:country_code":"BO",
    "gn:dem":4013,
    "gn:feature_class":"P",
    "gn:feature_code":"PPL",
    "gn:name":"Estancia Irpa Yapo",
    "gn:population":0,
    "gn:timezone":"America/La_Paz",
    "iso:country":"BO",
    "wof:name":"Estancia Irpa Yapo",
    "wof:placetype":"locality"
},
  "geometry": {"coordinates":[-65.92437,-20.29171],"type":"Point"}
}