{
  "type": "Feature",
  "properties": {
    "gn:admin1_code":"08",
    "gn:asciiname":"Enconadita",
    "gn:cc2":"BO",
    "gn:country_code":"BO",
    "gn:dem":332,
    "gn:feature_class":"P",
    "gn:feature_code":"PPL",
    "gn:name":"Enconadita",
    "gn:population":0,
    "gn:timezone":"America/La_Paz",
    "iso:country":"BO",
    "name:und_x_variant":[
        "Comunidad Enconada",
        "Enconadita"
    ],
    "wof:name":"Enconadita",
    "wof:placetype":"locality"
},
  "geometry": {"coordinates":[-62.91667,-17.71667],"type":"Point"}
}