{
  "type": "Feature",
  "properties": {
    "gn:admin1_code":"7.0",
    "gn:asciiname":"Tambillopampa",
    "gn:country_code":"BO",
    "gn:dem":3719,
    "gn:feature_class":"P",
    "gn:feature_code":"PPL",
    "gn:name":"Tambillopampa",
    "gn:population":0,
    "gn:timezone":"America/La_Paz",
    "iso:country":"BO",
    "wof:name":"Tambillopampa",
    "wof:placetype":"locality"
},
  "geometry": {"coordinates":[-67.26666999999999,-20.91667],"type":"Point"}
}