{
  "type": "Feature",
  "properties": {
    "gn:admin1_code":"9.0",
    "gn:asciiname":"San Luis de Palqui",
    "gn:country_code":"BO",
    "gn:dem":3295,
    "gn:feature_class":"P",
    "gn:feature_code":"PPL",
    "gn:name":"San Luis de Palqui",
    "gn:population":0,
    "gn:timezone":"America/La_Paz",
    "iso:country":"BO",
    "wof:name":"San Luis de Palqui",
    "wof:placetype":"locality"
},
  "geometry": {"coordinates":[-65.13509999999999,-21.55687],"type":"Point"}
}