{
  "type": "Feature",
  "properties": {
    "iso:country":"BO",
    "name:ben_x_preferred":[
        "\u09a4\u09be\u09b0\u09be\u09ac\u09c1\u0995\u09cb"
    ],
    "name:ceb_x_preferred":[
        "Tarabuco"
    ],
    "name:deu_x_preferred":[
        "Tarabuco"
    ],
    "name:ell_x_preferred":[
        "\u03a4\u03b1\u03c1\u03b1\u03bc\u03c0\u03bf\u03cd\u03ba\u03bf"
    ],
    "name:fas_x_preferred":[
        "\u062a\u0627\u0631\u0627\u0628\u0648\u06a9\u0648"
    ],
    "name:fra_x_preferred":[
        "Tarabuco"
    ],
    "name:heb_x_preferred":[
        "\u05d8\u05d0\u05e8\u05d1\u05d5\u05e7\u05d5"
    ],
    "name:hin_x_preferred":[
        "\u0924\u093e\u0930\u093e\u092c\u0942\u0915\u094b"
    ],
    "name:hun_x_preferred":[
        "Tarabuco"
    ],
    "name:ind_x_preferred":[
        "Tarabuco"
    ],
    "name:ita_x_preferred":[
        "Tarabuco"
    ],
    "name:jpn_x_preferred":[
        "\u30bf\u30e9\u30d6\u30b3"
    ],
    "name:kor_x_preferred":[
        "\ud0c0\ub77c\ubd80\ucf54"
    ],
    "name:nld_x_preferred":[
        "Tarabuco"
    ],
    "name:nor_x_preferred":[
        "Tarabuco"
    ],
    "name:pol_x_preferred":[
        "Tarabuco"
    ],
    "name:que_x_preferred":[
        "Tarapuku"
    ],
    "name:rus_x_preferred":[
        "\u0422\u0430\u0440\u0430\u0431\u0443\u043a\u043e"
    ],
    "name:spa_x_preferred":[
        "Tarabuco"
    ],
    "name:swe_x_preferred":[
        "Tarabuco"
    ],
    "name:tur_x_preferred":[
        "Tarabuco"
    ],
    "name:ukr_x_preferred":[
        "\u0422\u0430\u0440\u0430\u0431\u0443\u043a\u043e"
    ],
    "name:urd_x_preferred":[
        "\u0679\u0627\u0631\u0627\u0628\u0648\u06a9\u0648"
    ],
    "name:vie_x_preferred":[
        "Tarabuco"
    ],
    "name:war_x_preferred":[
        "Tarabuco"
    ],
    "name:zho_x_preferred":[
        "\u5854\u62c9\u5e03\u79d1"
    ],
    "qs:gn_country":"BO",
    "qs:gn_fcode":"ADM4",
    "qs:gn_pop":0,
    "qs:name":"Tarabuco",
    "qs:name_adm0":"Bolivia",
    "qs:name_adm1":"Chuquisaca",
    "qs:photos":1,
    "qs:photos_1k":1,
    "qs:photos_9k":1,
    "qs:photos_9r":4,
    "qs:photos_all":287,
    "qs:photos_sr":1,
    "qs:placetype":"LocalAdmin",
    "qs:pop_sr":"0",
    "qs:woe_adm0":23424762,
    "wof:name":"Tarabuco",
    "wof:placetype":"localadmin"
},
  "geometry": {"coordinates":[-64.89042000000001,-19.16676],"type":"Point"}
}