{
  "type": "Feature",
  "properties": {
    "iso:country":"BO",
    "name:ceb_x_preferred":[
        "Tarabuco"
    ],
    "name:deu_x_preferred":[
        "Tarabuco"
    ],
    "name:fra_x_preferred":[
        "Tarabuco"
    ],
    "name:ita_x_preferred":[
        "Tarabuco"
    ],
    "name:jpn_x_preferred":[
        "\u30bf\u30e9\u30d6\u30b3"
    ],
    "name:kor_x_preferred":[
        "\ud0c0\ub77c\ubd80\ucf54"
    ],
    "name:nld_x_preferred":[
        "Tarabuco"
    ],
    "name:nor_x_preferred":[
        "Tarabuco"
    ],
    "name:pol_x_preferred":[
        "Tarabuco"
    ],
    "name:que_x_preferred":[
        "Tarapuku"
    ],
    "name:swe_x_preferred":[
        "Tarabuco"
    ],
    "name:war_x_preferred":[
        "Tarabuco"
    ],
    "name:zho_x_preferred":[
        "\u5854\u62c9\u5e03\u79d1"
    ],
    "qs:gn_country":"BO",
    "qs:gn_fcode":"ADM4",
    "qs:gn_pop":0,
    "qs:name":"Tarabuco",
    "qs:name_adm0":"Bolivia",
    "qs:name_adm1":"Chuquisaca",
    "qs:photos":1,
    "qs:photos_1k":1,
    "qs:photos_9k":1,
    "qs:photos_9r":4,
    "qs:photos_all":287,
    "qs:photos_sr":1,
    "qs:placetype":"LocalAdmin",
    "qs:pop_sr":"0",
    "qs:woe_adm0":23424762,
    "wof:name":"Tarabuco",
    "wof:placetype":"localadmin"
},
  "geometry": {"coordinates":[-64.89042000000001,-19.16676],"type":"Point"}
}