{
  "type": "Feature",
  "properties": {
    "iso:country":"BO",
    "qs:gn_country":"BO",
    "qs:gn_fcode":"ADM4",
    "qs:gn_pop":0,
    "qs:name":"Tarabuco",
    "qs:name_adm0":"Bolivia",
    "qs:name_adm1":"Chuquisaca",
    "qs:photos":1,
    "qs:photos_1k":1,
    "qs:photos_9k":1,
    "qs:photos_9r":4,
    "qs:photos_all":287,
    "qs:photos_sr":1,
    "qs:placetype":"LocalAdmin",
    "qs:pop_sr":"0",
    "qs:woe_adm0":23424762,
    "wof:name":"Tarabuco",
    "wof:placetype":"localadmin"
},
  "geometry": {"coordinates":[-64.89042000000001,-19.16676],"type":"Point"}
}