{
  "type": "Feature",
  "properties": {
    "gn:admin1_code":"02",
    "gn:asciiname":"Acevedo",
    "gn:country_code":"BO",
    "gn:dem":1432,
    "gn:feature_class":"P",
    "gn:feature_code":"PPL",
    "gn:name":"Acevedo",
    "gn:population":0,
    "gn:timezone":"America/La_Paz",
    "iso:country":"BO",
    "name:cat_x_preferred":[
        "Acevedo"
    ],
    "name:ceb_x_preferred":[
        "Acevedo"
    ],
    "name:deu_x_preferred":[
        "Acevedo"
    ],
    "name:glg_x_preferred":[
        "Acevedo"
    ],
    "name:ita_x_preferred":[
        "Acevedo"
    ],
    "name:nld_x_preferred":[
        "Acevedo"
    ],
    "name:rus_x_preferred":[
        "\u0410\u0441\u0435\u0432\u0435\u0434\u043e"
    ],
    "name:slv_x_preferred":[
        "Acevedo"
    ],
    "name:spa_x_preferred":[
        "Acevedo"
    ],
    "name:swe_x_preferred":[
        "Acevedo"
    ],
    "name:ukr_x_preferred":[
        "\u0410\u0441\u0435\u0432\u0435\u0434\u043e"
    ],
    "name:und_x_variant":[
        "Estancia Acevedo"
    ],
    "name:zho_x_preferred":[
        "\u963f\u585e\u7ef4\u591a"
    ],
    "wof:name":"Acevedo",
    "wof:placetype":"locality"
},
  "geometry": {"coordinates":[-64.97412,-18.50536],"type":"Point"}
}