{
  "type": "Feature",
  "properties": {
    "gn:admin1_code":"02",
    "gn:asciiname":"Acevedo",
    "gn:country_code":"BO",
    "gn:dem":1432,
    "gn:feature_class":"P",
    "gn:feature_code":"PPL",
    "gn:name":"Acevedo",
    "gn:population":0,
    "gn:timezone":"America/La_Paz",
    "iso:country":"BO",
    "name:und_x_variant":[
        "Estancia Acevedo",
        "Acevedo"
    ],
    "wof:name":"Acevedo",
    "wof:placetype":"locality"
},
  "geometry": {"coordinates":[-64.97412,-18.50536],"type":"Point"}
}