{
  "type": "Feature",
  "properties": {
    "gn:admin1_code":"2.0",
    "gn:asciiname":"Rodeo",
    "gn:country_code":"BO",
    "gn:dem":3511,
    "gn:feature_class":"P",
    "gn:feature_code":"PPL",
    "gn:name":"Rodeo",
    "gn:population":0,
    "gn:timezone":"America/La_Paz",
    "iso:country":"BO",
    "wof:name":"Rodeo",
    "wof:placetype":"locality"
},
  "geometry": {"coordinates":[-65.63333,-17.61667000000001],"type":"Point"}
}