{
  "type": "Feature",
  "properties": {
    "gn:admin1_code":"5.0",
    "gn:asciiname":"Quevillan",
    "gn:cc2":"BO",
    "gn:country_code":"BO",
    "gn:dem":3729,
    "gn:feature_class":"P",
    "gn:feature_code":"PPL",
    "gn:name":"Quevillan",
    "gn:population":0,
    "gn:timezone":"America/La_Paz",
    "iso:country":"BO",
    "name:und_x_variant":[
        "Quevillani",
        "Quevillan"
    ],
    "wof:name":"Quevillan",
    "wof:placetype":"locality"
},
  "geometry": {"coordinates":[-67.01666999999999,-19.31667],"type":"Point"}
}