{
  "type": "Feature",
  "properties": {
    "gn:admin1_code":"4.0",
    "gn:asciiname":"Putiri",
    "gn:cc2":"BO",
    "gn:country_code":"BO",
    "gn:dem":4042,
    "gn:feature_class":"P",
    "gn:feature_code":"PPL",
    "gn:name":"Putiri",
    "gn:population":0,
    "gn:timezone":"America/La_Paz",
    "iso:country":"BO",
    "name:und_x_variant":[
        "Estancia Putiri",
        "Putiri"
    ],
    "wof:name":"Putiri",
    "wof:placetype":"locality"
},
  "geometry": {"coordinates":[-68.95,-17.51667],"type":"Point"}
}