{
  "type": "Feature",
  "properties": {
    "gn:admin1_code":"7.0",
    "gn:asciiname":"Yana Orko",
    "gn:country_code":"BO",
    "gn:dem":4252,
    "gn:feature_class":"P",
    "gn:feature_code":"PPL",
    "gn:name":"Yana Orko",
    "gn:population":0,
    "gn:timezone":"America/La_Paz",
    "iso:country":"BO",
    "wof:name":"Yana Orko",
    "wof:placetype":"locality"
},
  "geometry": {"coordinates":[-66.40043,-21.59639],"type":"Point"}
}