{
  "type": "Feature",
  "properties": {
    "gn:admin1_code":"01",
    "gn:asciiname":"El Tejar",
    "gn:country_code":"BO",
    "gn:dem":2705,
    "gn:feature_class":"P",
    "gn:feature_code":"PPL",
    "gn:name":"El Tejar",
    "gn:population":0,
    "gn:timezone":"America/La_Paz",
    "iso:country":"BO",
    "name:ceb_x_preferred":[
        "El Tejar"
    ],
    "name:fra_x_preferred":[
        "El Tejar"
    ],
    "name:ita_x_preferred":[
        "El Tejar"
    ],
    "name:spa_x_preferred":[
        "El Tejar"
    ],
    "name:swe_x_preferred":[
        "El Tejar"
    ],
    "name:und_x_variant":[
        "Tejar",
        "El Tejar"
    ],
    "wof:name":"El Tejar",
    "wof:placetype":"locality"
},
  "geometry": {"coordinates":[-65.27339000000001,-19.0589],"type":"Point"}
}