{
  "type": "Feature",
  "properties": {
    "gn:admin1_code":"6.0",
    "gn:asciiname":"Illampu",
    "gn:country_code":"BO",
    "gn:dem":231,
    "gn:feature_class":"P",
    "gn:feature_code":"PPL",
    "gn:name":"Illampu",
    "gn:population":0,
    "gn:timezone":"America/La_Paz",
    "iso:country":"BO",
    "name:aym_x_preferred":[
        "Illampu"
    ],
    "name:ben_x_preferred":[
        "\u0987\u09b2\u09bf\u09af\u09bc\u09be\u09ae\u09cd\u09aa\u09c1"
    ],
    "name:ceb_x_preferred":[
        "Nevado Illampu"
    ],
    "name:ces_x_preferred":[
        "Illampu"
    ],
    "name:deu_x_preferred":[
        "Illamp\u00fa"
    ],
    "name:epo_x_preferred":[
        "Illampu"
    ],
    "name:eus_x_preferred":[
        "Illampu"
    ],
    "name:fin_x_preferred":[
        "Illamp\u00fa"
    ],
    "name:fra_x_preferred":[
        "Illampu"
    ],
    "name:ita_x_preferred":[
        "Illampu"
    ],
    "name:kat_x_preferred":[
        "\u10d8\u10da\u10d8\u10d0\u10db\u10de\u10e3"
    ],
    "name:lit_x_preferred":[
        "Iljampu"
    ],
    "name:nld_x_preferred":[
        "Illampu"
    ],
    "name:oss_x_preferred":[
        "\u0418\u043b\u044c\u044f\u043c\u043f\u0443"
    ],
    "name:pol_x_preferred":[
        "Illampu"
    ],
    "name:por_x_preferred":[
        "Illampu"
    ],
    "name:que_x_preferred":[
        "Illampu"
    ],
    "name:rus_x_preferred":[
        "\u0418\u043b\u044c\u044f\u043c\u043f\u0443"
    ],
    "name:spa_x_preferred":[
        "Illampu"
    ],
    "name:swa_x_preferred":[
        "Illamp\u00fa"
    ],
    "name:swe_x_preferred":[
        "Illampu"
    ],
    "name:ukr_x_preferred":[
        "\u0406\u044f\u043c\u043f\u0443"
    ],
    "name:zho_x_preferred":[
        "\u4f0a\u826f\u666e\u5c71"
    ],
    "wof:name":"Illampu",
    "wof:placetype":"locality"
},
  "geometry": {"coordinates":[-68.83333,-11.93333],"type":"Point"}
}