{
  "type": "Feature",
  "properties": {
    "gn:admin1_code":"6.0",
    "gn:asciiname":"Illampu",
    "gn:country_code":"BO",
    "gn:dem":231,
    "gn:feature_class":"P",
    "gn:feature_code":"PPL",
    "gn:name":"Illampu",
    "gn:population":0,
    "gn:timezone":"America/La_Paz",
    "iso:country":"BO",
    "wof:name":"Illampu",
    "wof:placetype":"locality"
},
  "geometry": {"coordinates":[-68.83333,-11.93333],"type":"Point"}
}