{
  "type": "Feature",
  "properties": {
    "iso:country":"BO",
    "name:ara_x_preferred":[
        "\u0633\u0627\u0646\u062a\u0627 \u0643\u0631\u0648\u0632 \u062f\u064a \u0644\u0627 \u0633\u064a\u064a\u0631\u0627"
    ],
    "name:bul_x_preferred":[
        "\u0421\u0430\u043d\u0442\u0430 \u041a\u0440\u0443\u0441 \u0434\u0435 \u043b\u0430 \u0421\u0438\u0435\u0440\u0430"
    ],
    "name:ell_x_preferred":[
        "\u03a3\u03ac\u03bd\u03c4\u03b1 \u039a\u03c1\u03bf\u03c5\u03c2 \u03bd\u03c4\u03b5 \u03bb\u03b1 \u03a3\u03b9\u03ad\u03c1\u03c1\u03b1"
    ],
    "name:fas_x_preferred":[
        "\u0633\u0627\u0646\u062a\u0627 \u06a9\u0631\u0648\u0633 \u062f \u0644\u0627 \u0633\u06cc\u0631\u0627"
    ],
    "name:heb_x_preferred":[
        "\u05e1\u05e0\u05d8\u05d4 \u05e7\u05e8\u05d5\u05e1 \u05d3\u05d4 \u05dc\u05d4 \u05e1\u05d9\u05d9\u05e8\u05d4"
    ],
    "name:hye_x_preferred":[
        "\u054d\u0561\u0576\u057f\u0561 \u053f\u0580\u0578\u0582\u057d \u0564\u0565 \u056c\u0561 \u054d\u056b\u0565\u0580\u0580\u0561"
    ],
    "name:mkd_x_preferred":[
        "\u0421\u0430\u043d\u0442\u0430 \u041a\u0440\u0443\u0437 \u0434\u0435 \u043b\u0430 \u0421\u0438\u0435\u0440\u0430"
    ],
    "name:que_x_preferred":[
        "Santa Krus llaqta"
    ],
    "name:srp_x_preferred":[
        "\u0421\u0430\u043d\u0442\u0430 \u041a\u0440\u0443\u0437 \u0434\u0435 \u043b\u0430 \u0421\u0438\u0458\u0435\u0440\u0430"
    ],
    "name:tam_x_preferred":[
        "\u0b9a\u0bbe\u0ba9\u0bcd\u0b9f\u0bcd\u0b9f\u0bbe \u0b95\u0bc1\u0bb0\u0bc2\u0b9a\u0bc1 \u0b9f\u0bc6 \u0bb2\u0bbe \u0b9a\u0bbf\u0baf\u0bc7\u0bb1\u0bbe"
    ],
    "name:urd_x_preferred":[
        "\u0633\u0627\u0646\u062a\u0627 \u06a9\u0631\u0648\u0632 \u062f\u06d2 \u0644\u0627 \u0633\u06cc\u0626\u0631\u0627"
    ],
    "qs:gn_pop":0,
    "qs:name":"Santa Cruz de la Sierra",
    "qs:name_adm0":"Bolivia",
    "qs:name_adm1":"Santa Cruz",
    "qs:photos":2,
    "qs:photos_1k":1,
    "qs:photos_9k":12,
    "qs:photos_9r":10,
    "qs:photos_all":2715,
    "qs:photos_sr":1,
    "qs:placetype":"LocalAdmin",
    "qs:pop_sr":"0",
    "qs:woe_adm0":23424762,
    "wof:name":"Santa Cruz de la Sierra",
    "wof:placetype":"localadmin"
},
  "geometry": {"coordinates":[-63.186492,-17.788573],"type":"Point"}
}