{
  "type": "Feature",
  "properties": {
    "iso:country":"BO",
    "qs:gn_pop":0,
    "qs:name":"Santa Cruz de la Sierra",
    "qs:name_adm0":"Bolivia",
    "qs:name_adm1":"Santa Cruz",
    "qs:photos":2,
    "qs:photos_1k":1,
    "qs:photos_9k":12,
    "qs:photos_9r":10,
    "qs:photos_all":2715,
    "qs:photos_sr":1,
    "qs:placetype":"LocalAdmin",
    "qs:pop_sr":"0",
    "qs:woe_adm0":23424762,
    "wof:name":"Santa Cruz de la Sierra",
    "wof:placetype":"localadmin"
},
  "geometry": {"coordinates":[-63.186492,-17.788573],"type":"Point"}
}