{
  "type": "Feature",
  "properties": {
    "gn:admin1_code":"8.0",
    "gn:asciiname":"Pasiviqui",
    "gn:cc2":"BO",
    "gn:country_code":"BO",
    "gn:dem":467,
    "gn:feature_class":"P",
    "gn:feature_code":"PPL",
    "gn:name":"Pasiviqui",
    "gn:population":0,
    "gn:timezone":"America/La_Paz",
    "iso:country":"BO",
    "name:und_x_variant":[
        "Comunidad Pasiviqui",
        "Pacivique",
        "Pasiviqui"
    ],
    "wof:name":"Pasiviqui",
    "wof:placetype":"locality"
},
  "geometry": {"coordinates":[-60.98333,-16.48333],"type":"Point"}
}