{
  "type": "Feature",
  "properties": {
    "gn:admin1_code":"05",
    "gn:asciiname":"Estancia Uma Phusa",
    "gn:country_code":"BO",
    "gn:dem":4011,
    "gn:feature_class":"P",
    "gn:feature_code":"PPL",
    "gn:name":"Estancia Uma Phusa",
    "gn:population":0,
    "gn:timezone":"America/La_Paz",
    "iso:country":"BO",
    "wof:name":"Estancia Uma Phusa",
    "wof:placetype":"locality"
},
  "geometry": {"coordinates":[-68.60826999999999,-18.02367000000001],"type":"Point"}
}