{
  "type": "Feature",
  "properties": {
    "gn:admin1_code":"1.0",
    "gn:asciiname":"Siccha",
    "gn:country_code":"BO",
    "gn:dem":2823,
    "gn:feature_class":"P",
    "gn:feature_code":"PPL",
    "gn:name":"Siccha",
    "gn:population":0,
    "gn:timezone":"America/La_Paz",
    "iso:country":"BO",
    "wof:name":"Siccha",
    "wof:placetype":"locality"
},
  "geometry": {"coordinates":[-65.32637,-18.90178],"type":"Point"}
}