{
  "type": "Feature",
  "properties": {
    "gn:admin1_code":"6.0",
    "gn:asciiname":"Granja",
    "gn:country_code":"BO",
    "gn:dem":147,
    "gn:feature_class":"P",
    "gn:feature_code":"PPL",
    "gn:name":"Granja",
    "gn:population":0,
    "gn:timezone":"America/La_Paz",
    "iso:country":"BO",
    "name:cat_x_preferred":[
        "Granja"
    ],
    "name:ceb_x_preferred":[
        "Granja"
    ],
    "name:deu_x_preferred":[
        "Granja"
    ],
    "name:fra_x_preferred":[
        "Granja"
    ],
    "name:ita_x_preferred":[
        "Granja"
    ],
    "name:mlg_x_preferred":[
        "Granja"
    ],
    "name:nld_x_preferred":[
        "Granja"
    ],
    "name:por_x_preferred":[
        "Granja"
    ],
    "name:rus_x_preferred":[
        "\u0413\u0440\u0430\u043d\u0436\u0430"
    ],
    "name:spa_x_preferred":[
        "Granja"
    ],
    "name:swe_x_preferred":[
        "Granja"
    ],
    "name:tur_x_preferred":[
        "Granja"
    ],
    "name:und_x_variant":[
        "La Granga"
    ],
    "name:vie_x_preferred":[
        "Granja"
    ],
    "wof:name":"Granja",
    "wof:placetype":"locality"
},
  "geometry": {"coordinates":[-66.1191,-10.77713],"type":"Point"}
}