{
  "type": "Feature",
  "properties": {
    "gn:admin1_code":"6.0",
    "gn:asciiname":"Granja",
    "gn:country_code":"BO",
    "gn:dem":147,
    "gn:feature_class":"P",
    "gn:feature_code":"PPL",
    "gn:name":"Granja",
    "gn:population":0,
    "gn:timezone":"America/La_Paz",
    "iso:country":"BO",
    "name:und_x_variant":[
        "La Granga",
        "Granja"
    ],
    "wof:name":"Granja",
    "wof:placetype":"locality"
},
  "geometry": {"coordinates":[-66.1191,-10.77713],"type":"Point"}
}