{
  "type": "Feature",
  "properties": {
    "gn:admin1_code":"4.0",
    "gn:asciiname":"Lluto",
    "gn:country_code":"BO",
    "gn:dem":3410,
    "gn:feature_class":"P",
    "gn:feature_code":"PPL",
    "gn:name":"Lluto",
    "gn:population":0,
    "gn:timezone":"America/La_Paz",
    "iso:country":"BO",
    "wof:name":"Lluto",
    "wof:placetype":"locality"
},
  "geometry": {"coordinates":[-68.01666999999999,-16.61667000000001],"type":"Point"}
}