{
  "type": "Feature",
  "properties": {
    "gn:admin1_code":"07",
    "gn:asciiname":"Agua Castilla",
    "gn:country_code":"BO",
    "gn:dem":4396,
    "gn:feature_class":"P",
    "gn:feature_code":"PPL",
    "gn:name":"Agua Castilla",
    "gn:population":0,
    "gn:timezone":"America/La_Paz",
    "iso:country":"BO",
    "wof:name":"Agua Castilla",
    "wof:placetype":"locality"
},
  "geometry": {"coordinates":[-66.15000000000001,-21.15],"type":"Point"}
}