{
  "type": "Feature",
  "properties": {
    "gn:admin1_code":"8.0",
    "gn:asciiname":"Villa Valdez",
    "gn:country_code":"BO",
    "gn:dem":456,
    "gn:feature_class":"P",
    "gn:feature_code":"PPL",
    "gn:name":"Villa Valdez",
    "gn:population":0,
    "gn:timezone":"America/La_Paz",
    "iso:country":"BO",
    "wof:name":"Villa Valdez",
    "wof:placetype":"locality"
},
  "geometry": {"coordinates":[-62.61666999999999,-19.68333],"type":"Point"}
}