{
  "type": "Feature",
  "properties": {
    "gn:admin1_code":"1.0",
    "gn:asciiname":"Uruguay",
    "gn:country_code":"BO",
    "gn:dem":1035,
    "gn:feature_class":"P",
    "gn:feature_code":"PPL",
    "gn:name":"Uruguay",
    "gn:population":0,
    "gn:timezone":"America/La_Paz",
    "iso:country":"BO",
    "name:und_x_variant":[
        "Urquia",
        "Uruguay"
    ],
    "wof:name":"Uruguay",
    "wof:placetype":"locality"
},
  "geometry": {"coordinates":[-64.15125999999999,-20.52031],"type":"Point"}
}