{
  "type": "Feature",
  "properties": {
    "gn:admin1_code":"04",
    "gn:asciiname":"Chinijo",
    "gn:country_code":"BO",
    "gn:dem":1775,
    "gn:feature_class":"P",
    "gn:feature_code":"PPL",
    "gn:name":"Chi\u00f1ijo",
    "gn:population":0,
    "gn:timezone":"America/La_Paz",
    "iso:country":"BO",
    "wof:name":"Chinijo",
    "wof:placetype":"locality"
},
  "geometry": {"coordinates":[-68.41667,-15.43333],"type":"Point"}
}