{
  "type": "Feature",
  "properties": {
    "gn:admin1_code":"4.0",
    "gn:asciiname":"Rodeo",
    "gn:country_code":"BO",
    "gn:dem":4310,
    "gn:feature_class":"P",
    "gn:feature_code":"PPL",
    "gn:name":"Rodeo",
    "gn:population":0,
    "gn:timezone":"America/La_Paz",
    "iso:country":"BO",
    "wof:name":"Rodeo",
    "wof:placetype":"locality"
},
  "geometry": {"coordinates":[-67.36135999999999,-17.04397],"type":"Point"}
}