{
  "type": "Feature",
  "properties": {
    "gn:admin1_code":"7.0",
    "gn:asciiname":"Tambillo",
    "gn:country_code":"BO",
    "gn:dem":3722,
    "gn:feature_class":"P",
    "gn:feature_code":"PPL",
    "gn:name":"Tambillo",
    "gn:population":0,
    "gn:timezone":"America/La_Paz",
    "iso:country":"BO",
    "wof:name":"Tambillo",
    "wof:placetype":"locality"
},
  "geometry": {"coordinates":[-65.90000000000001,-21.01667],"type":"Point"}
}