{
  "type": "Feature",
  "properties": {
    "gn:admin1_code":"9.0",
    "gn:asciiname":"Saladito Sud",
    "gn:country_code":"BO",
    "gn:dem":852,
    "gn:feature_class":"P",
    "gn:feature_code":"PPL",
    "gn:name":"Saladito Sud",
    "gn:population":0,
    "gn:timezone":"America/La_Paz",
    "iso:country":"BO",
    "wof:name":"Saladito Sud",
    "wof:placetype":"locality"
},
  "geometry": {"coordinates":[-64.127,-21.32093],"type":"Point"}
}