{
  "type": "Feature",
  "properties": {
    "gn:admin1_code":"5.0",
    "gn:asciiname":"Jayucota",
    "gn:country_code":"BO",
    "gn:dem":3711,
    "gn:feature_class":"P",
    "gn:feature_code":"PPL",
    "gn:name":"Jayucota",
    "gn:population":0,
    "gn:timezone":"America/La_Paz",
    "iso:country":"BO",
    "name:und_x_variant":[
        "Cayacoto",
        "Jayucuta",
        "Jayucota"
    ],
    "wof:name":"Jayucota",
    "wof:placetype":"locality"
},
  "geometry": {"coordinates":[-67.42484,-19.46124],"type":"Point"}
}