{
  "type": "Feature",
  "properties": {
    "gn:admin1_code":"05",
    "gn:asciiname":"Estancia Bella Vista",
    "gn:country_code":"BO",
    "gn:dem":3759,
    "gn:feature_class":"P",
    "gn:feature_code":"PPL",
    "gn:name":"Estancia Bella Vista",
    "gn:population":0,
    "gn:timezone":"America/La_Paz",
    "iso:country":"BO",
    "wof:name":"Estancia Bella Vista",
    "wof:placetype":"locality"
},
  "geometry": {"coordinates":[-67.63762,-18.05492000000001],"type":"Point"}
}