{
  "type": "Feature",
  "properties": {
    "gn:admin1_code":"08",
    "gn:asciiname":"Curibo",
    "gn:country_code":"BO",
    "gn:dem":417,
    "gn:feature_class":"P",
    "gn:feature_code":"PPL",
    "gn:name":"Curibo",
    "gn:population":0,
    "gn:timezone":"America/La_Paz",
    "iso:country":"BO",
    "wof:name":"Curibo",
    "wof:placetype":"locality"
},
  "geometry": {"coordinates":[-63.23333,-17.73333],"type":"Point"}
}