{
  "type": "Feature",
  "properties": {
    "gn:admin1_code":"07",
    "gn:asciiname":"Collpa",
    "gn:country_code":"BO",
    "gn:dem":4268,
    "gn:feature_class":"P",
    "gn:feature_code":"PPL",
    "gn:name":"Collpa",
    "gn:population":0,
    "gn:timezone":"America/La_Paz",
    "iso:country":"BO",
    "wof:name":"Collpa",
    "wof:placetype":"locality"
},
  "geometry": {"coordinates":[-66.26666999999999,-21.11667000000001],"type":"Point"}
}