{
  "type": "Feature",
  "properties": {
    "gn:admin1_code":"08",
    "gn:asciiname":"Alto Almacen",
    "gn:country_code":"BO",
    "gn:dem":201,
    "gn:feature_class":"P",
    "gn:feature_code":"PPL",
    "gn:name":"Alto Almac\u00e9n",
    "gn:population":0,
    "gn:timezone":"America/La_Paz",
    "iso:country":"BO",
    "wof:name":"Alto Almacen",
    "wof:placetype":"locality"
},
  "geometry": {"coordinates":[-62.16667,-14.33333],"type":"Point"}
}