{
  "type": "Feature",
  "properties": {
    "gn:admin1_code":"4.0",
    "gn:asciiname":"Tora",
    "gn:country_code":"BO",
    "gn:dem":1419,
    "gn:feature_class":"P",
    "gn:feature_code":"PPL",
    "gn:name":"Tora",
    "gn:population":0,
    "gn:timezone":"America/La_Paz",
    "iso:country":"BO",
    "wof:name":"Tora",
    "wof:placetype":"locality"
},
  "geometry": {"coordinates":[-68.15000000000001,-15.58333],"type":"Point"}
}