{
  "type": "Feature",
  "properties": {
    "gn:admin1_code":"4.0",
    "gn:asciiname":"Quillcoma",
    "gn:country_code":"BO",
    "gn:dem":4160,
    "gn:feature_class":"P",
    "gn:feature_code":"PPL",
    "gn:name":"Quillcoma",
    "gn:population":0,
    "gn:timezone":"America/La_Paz",
    "iso:country":"BO",
    "wof:name":"Quillcoma",
    "wof:placetype":"locality"
},
  "geometry": {"coordinates":[-68.01666999999999,-16.96667],"type":"Point"}
}