{
  "type": "Feature",
  "properties": {
    "gn:admin1_code":"4.0",
    "gn:asciiname":"Puerto Pando Carmen",
    "gn:country_code":"BO",
    "gn:dem":699,
    "gn:feature_class":"P",
    "gn:feature_code":"PPL",
    "gn:name":"Puerto Pando Carmen",
    "gn:population":0,
    "gn:timezone":"America/La_Paz",
    "iso:country":"BO",
    "wof:name":"Puerto Pando Carmen",
    "wof:placetype":"locality"
},
  "geometry": {"coordinates":[-67.75,-15.11667],"type":"Point"}
}