{
  "type": "Feature",
  "properties": {
    "gn:admin1_code":"4.0",
    "gn:asciiname":"Estancia Paroco",
    "gn:country_code":"BO",
    "gn:dem":4295,
    "gn:feature_class":"P",
    "gn:feature_code":"PPL",
    "gn:name":"Estancia Paroco",
    "gn:population":0,
    "gn:timezone":"America/La_Paz",
    "iso:country":"BO",
    "wof:name":"Estancia Paroco",
    "wof:placetype":"locality"
},
  "geometry": {"coordinates":[-69.33333,-17.28333],"type":"Point"}
}