{
  "type": "Feature",
  "properties": {
    "gn:admin1_code":"8.0",
    "gn:asciiname":"Rincon del Urucu",
    "gn:cc2":"BO",
    "gn:country_code":"BO",
    "gn:dem":268,
    "gn:feature_class":"P",
    "gn:feature_code":"PPL",
    "gn:name":"Rinc\u00f3n del Uruc\u00fa",
    "gn:population":0,
    "gn:timezone":"America/La_Paz",
    "iso:country":"BO",
    "name:und_x_variant":[
        "Estancia Rinc\u00f3n del Uruc\u00fa",
        "Rinc\u00f3n del Uruc\u00fa"
    ],
    "wof:name":"Rincon del Urucu",
    "wof:placetype":"locality"
},
  "geometry": {"coordinates":[-63.48333,-17.25],"type":"Point"}
}