{
  "type": "Feature",
  "properties": {
    "gn:admin1_code":"1.0",
    "gn:asciiname":"Pasopaya",
    "gn:country_code":"BO",
    "gn:dem":2475,
    "gn:feature_class":"P",
    "gn:feature_code":"PPL",
    "gn:name":"Pasopaya",
    "gn:population":0,
    "gn:timezone":"America/La_Paz",
    "iso:country":"BO",
    "name:und_x_variant":[
        "Pesopaya",
        "Pasopaya"
    ],
    "wof:name":"Pasopaya",
    "wof:placetype":"locality"
},
  "geometry": {"coordinates":[-64.94109,-18.7723],"type":"Point"}
}