{
  "type": "Feature",
  "properties": {
    "gn:admin1_code":"04",
    "gn:asciiname":"Condor Amaya",
    "gn:cc2":"BO",
    "gn:country_code":"BO",
    "gn:dem":3872,
    "gn:feature_class":"P",
    "gn:feature_code":"PPL",
    "gn:name":"Condor Amaya",
    "gn:population":0,
    "gn:timezone":"America/La_Paz",
    "iso:country":"BO",
    "name:und_x_variant":[
        "Estancia Condor Amaya",
        "Condor Amaya"
    ],
    "wof:name":"Condor Amaya",
    "wof:placetype":"locality"
},
  "geometry": {"coordinates":[-69.18333,-17.01667],"type":"Point"}
}