{
  "type": "Feature",
  "properties": {
    "gn:admin1_code":"7.0",
    "gn:asciiname":"Mamahola",
    "gn:cc2":"BO",
    "gn:country_code":"BO",
    "gn:dem":3535,
    "gn:feature_class":"P",
    "gn:feature_code":"PPL",
    "gn:name":"Mamahola",
    "gn:population":0,
    "gn:timezone":"America/La_Paz",
    "iso:country":"BO",
    "name:und_x_variant":[
        "Mamahota",
        "Mamahola"
    ],
    "wof:name":"Mamahola",
    "wof:placetype":"locality"
},
  "geometry": {"coordinates":[-65.48333000000001,-19.48333],"type":"Point"}
}