{
  "type": "Feature",
  "properties": {
    "gn:admin1_code":"4.0",
    "gn:asciiname":"Tahuapalca",
    "gn:cc2":"BO",
    "gn:country_code":"BO",
    "gn:dem":3345,
    "gn:feature_class":"P",
    "gn:feature_code":"PPL",
    "gn:name":"Tahuapalca",
    "gn:population":0,
    "gn:timezone":"America/La_Paz",
    "iso:country":"BO",
    "name:und_x_variant":[
        "Estancia Tahuapalca",
        "Taguapalca",
        "Tagupaca",
        "Tahuapalca"
    ],
    "wof:name":"Tahuapalca",
    "wof:placetype":"locality"
},
  "geometry": {"coordinates":[-67.88333,-16.75],"type":"Point"}
}