{
  "type": "Feature",
  "properties": {
    "gn:admin1_code":"4.0",
    "gn:asciiname":"Taypi Belen",
    "gn:cc2":"BO",
    "gn:country_code":"BO",
    "gn:dem":4015,
    "gn:feature_class":"P",
    "gn:feature_code":"PPL",
    "gn:name":"Taypi Bel\u00e9n",
    "gn:population":0,
    "gn:timezone":"America/La_Paz",
    "iso:country":"BO",
    "name:und_x_variant":[
        "Estancia Taypi Bel\u00e9n",
        "Taypi Bel\u00e9n"
    ],
    "wof:name":"Taypi Belen",
    "wof:placetype":"locality"
},
  "geometry": {"coordinates":[-69.16667,-17.18333],"type":"Point"}
}