{
  "type": "Feature",
  "properties": {
    "gn:admin1_code":"5.0",
    "gn:asciiname":"Villa Tunari",
    "gn:country_code":"BO",
    "gn:dem":3857,
    "gn:feature_class":"P",
    "gn:feature_code":"PPL",
    "gn:name":"Villa Tunari",
    "gn:population":0,
    "gn:timezone":"America/La_Paz",
    "iso:country":"BO",
    "name:ceb_x_preferred":[
        "Villa Tunari"
    ],
    "name:dan_x_preferred":[
        "Villa Tunari"
    ],
    "name:deu_x_preferred":[
        "Villa Tunari"
    ],
    "name:fra_x_preferred":[
        "Villa Tunari"
    ],
    "name:nld_x_preferred":[
        "Villa Tunari"
    ],
    "name:nor_x_preferred":[
        "Villa Tunari"
    ],
    "name:pol_x_preferred":[
        "Villa Tunari"
    ],
    "name:que_x_preferred":[
        "Tunari llaqta"
    ],
    "name:sco_x_preferred":[
        "Villa Tunari"
    ],
    "name:spa_x_preferred":[
        "Villa Tunari"
    ],
    "name:swe_x_preferred":[
        "Villa Tunari"
    ],
    "name:und_x_variant":[
        "Estancia Villa Tunari"
    ],
    "name:zho_x_preferred":[
        "\u5716\u7d0d\u91cc\u93ae"
    ],
    "wof:name":"Villa Tunari",
    "wof:placetype":"locality"
},
  "geometry": {"coordinates":[-68.61084,-18.79068],"type":"Point"}
}