{
  "type": "Feature",
  "properties": {
    "gn:admin1_code":"5.0",
    "gn:asciiname":"Villa Tunari",
    "gn:country_code":"BO",
    "gn:dem":3857,
    "gn:feature_class":"P",
    "gn:feature_code":"PPL",
    "gn:name":"Villa Tunari",
    "gn:population":0,
    "gn:timezone":"America/La_Paz",
    "iso:country":"BO",
    "name:und_x_variant":[
        "Estancia Villa Tunari",
        "Villa Tunari"
    ],
    "wof:name":"Villa Tunari",
    "wof:placetype":"locality"
},
  "geometry": {"coordinates":[-68.61084,-18.79068],"type":"Point"}
}