{
  "type": "Feature",
  "properties": {
    "gn:admin1_code":"06",
    "gn:asciiname":"Lampion",
    "gn:country_code":"BO",
    "gn:dem":276,
    "gn:feature_class":"P",
    "gn:feature_code":"PPL",
    "gn:name":"Lampi\u00f3n",
    "gn:population":0,
    "gn:timezone":"America/La_Paz",
    "iso:country":"BO",
    "name:spa_x_preferred":[
        "Lampi\u00f3n"
    ],
    "wof:name":"Lampion",
    "wof:placetype":"locality"
},
  "geometry": {"coordinates":[-68.71178,-11.41473],"type":"Point"}
}