{
  "type": "Feature",
  "properties": {
    "gn:admin1_code":"4.0",
    "gn:asciiname":"Limpia",
    "gn:country_code":"BO",
    "gn:dem":3932,
    "gn:feature_class":"P",
    "gn:feature_code":"PPL",
    "gn:name":"Limpia",
    "gn:population":0,
    "gn:timezone":"America/La_Paz",
    "iso:country":"BO",
    "wof:name":"Limpia",
    "wof:placetype":"locality"
},
  "geometry": {"coordinates":[-68.55,-17.08333],"type":"Point"}
}