{
  "type": "Feature",
  "properties": {
    "iso:country":"BO",
    "name:dut_x_preferred":[
        "Patamanta"
    ],
    "name:eng_x_preferred":[
        "Patamanta"
    ],
    "name:ger_x_preferred":[
        "Patamanta"
    ],
    "name:unk_x_variant":[
        "Palamanta"
    ],
    "qs:gn_country":"BO",
    "qs:gn_fcode":"PPL",
    "qs:gn_pop":0,
    "qs:name":"Pata Manta",
    "qs:name_adm0":"Bolivia",
    "qs:name_adm1":"La Paz",
    "qs:photos":7,
    "qs:photos_1k":1,
    "qs:photos_9k":1,
    "qs:photos_9r":1,
    "qs:photos_all":7,
    "qs:photos_sr":1,
    "qs:placetype":"Town",
    "qs:pop_sr":"0",
    "qs:woe_adm0":23424762,
    "wof:name":"Pata Manta",
    "wof:placetype":"locality"
},
  "geometry": {"coordinates":[-68.40000000000001,-16.36667],"type":"Point"}
}