{
  "type": "Feature",
  "properties": {
    "gn:admin1_code":"9.0",
    "gn:asciiname":"Puerto Sucre",
    "gn:country_code":"BO",
    "gn:dem":295,
    "gn:feature_class":"P",
    "gn:feature_code":"PPL",
    "gn:name":"Puerto Sucre",
    "gn:population":0,
    "gn:timezone":"America/La_Paz",
    "iso:country":"BO",
    "wof:name":"Puerto Sucre",
    "wof:placetype":"locality"
},
  "geometry": {"coordinates":[-62.61666999999999,-21.63333],"type":"Point"}
}