{
  "type": "Feature",
  "properties": {
    "gn:admin1_code":"04",
    "gn:asciiname":"Anupucara",
    "gn:cc2":"BO",
    "gn:country_code":"BO",
    "gn:dem":3969,
    "gn:feature_class":"P",
    "gn:feature_code":"PPL",
    "gn:name":"Anupucara",
    "gn:population":0,
    "gn:timezone":"America/La_Paz",
    "iso:country":"BO",
    "name:und_x_variant":[
        "Estancia Anu Pucara",
        "Anupuraca",
        "Anupucara"
    ],
    "wof:name":"Anupucara",
    "wof:placetype":"locality"
},
  "geometry": {"coordinates":[-67.41667,-17.41667],"type":"Point"}
}