{
  "type": "Feature",
  "properties": {
    "gn:admin1_code":"07",
    "gn:asciiname":"Cruz Pata",
    "gn:country_code":"BO",
    "gn:dem":2941,
    "gn:feature_class":"P",
    "gn:feature_code":"PPL",
    "gn:name":"Cruz Pata",
    "gn:population":0,
    "gn:timezone":"America/La_Paz",
    "iso:country":"BO",
    "wof:name":"Cruz Pata",
    "wof:placetype":"locality"
},
  "geometry": {"coordinates":[-65.33914,-19.74522],"type":"Point"}
}