{
  "type": "Feature",
  "properties": {
    "gn:admin1_code":"08",
    "gn:asciiname":"Breme",
    "gn:country_code":"BO",
    "gn:dem":255,
    "gn:feature_class":"P",
    "gn:feature_code":"PPL",
    "gn:name":"Breme",
    "gn:population":0,
    "gn:timezone":"America/La_Paz",
    "iso:country":"BO",
    "name:ara_x_preferred":[
        "\u0628\u0631\u064a\u0645\u064a"
    ],
    "name:azb_x_preferred":[
        "\u0628\u0631\u0645\u0647"
    ],
    "name:bul_x_preferred":[
        "\u0411\u0440\u0435\u043c\u0435"
    ],
    "name:ceb_x_preferred":[
        "Breme"
    ],
    "name:ces_x_preferred":[
        "Breme"
    ],
    "name:deu_x_preferred":[
        "Breme"
    ],
    "name:eml_x_preferred":[
        "Breme"
    ],
    "name:epo_x_preferred":[
        "Breme"
    ],
    "name:eus_x_preferred":[
        "Breme"
    ],
    "name:fas_x_preferred":[
        "\u0628\u0631\u0645\u0647"
    ],
    "name:fra_x_preferred":[
        "Breme"
    ],
    "name:hun_x_preferred":[
        "Breme"
    ],
    "name:hye_x_preferred":[
        "\u0532\u0580\u0565\u0574\u0565"
    ],
    "name:ind_x_preferred":[
        "Breme"
    ],
    "name:ita_x_preferred":[
        "Breme"
    ],
    "name:jpn_x_preferred":[
        "\u30d6\u30ec\u30fc\u30e1"
    ],
    "name:lat_x_preferred":[
        "Bremma"
    ],
    "name:lmo_x_preferred":[
        "Br\u00e4m"
    ],
    "name:msa_x_preferred":[
        "Breme"
    ],
    "name:nap_x_preferred":[
        "Breme"
    ],
    "name:nld_x_preferred":[
        "Breme"
    ],
    "name:pms_x_preferred":[
        "Breme"
    ],
    "name:pol_x_preferred":[
        "Breme"
    ],
    "name:por_x_preferred":[
        "Breme"
    ],
    "name:ron_x_preferred":[
        "Breme"
    ],
    "name:rus_x_preferred":[
        "\u0411\u0440\u0435\u043c\u0435"
    ],
    "name:scn_x_preferred":[
        "Breme"
    ],
    "name:spa_x_preferred":[
        "Breme"
    ],
    "name:srp_x_preferred":[
        "\u0411\u0440\u0435\u043c\u0435"
    ],
    "name:tgl_x_preferred":[
        "Breme"
    ],
    "name:ukr_x_preferred":[
        "\u0411\u0440\u0435\u043c\u0435"
    ],
    "name:vie_x_preferred":[
        "Breme"
    ],
    "name:vol_x_preferred":[
        "Breme"
    ],
    "name:war_x_preferred":[
        "Breme"
    ],
    "name:zho_x_preferred":[
        "\u5e03\u96f7\u6885"
    ],
    "wof:name":"Breme",
    "wof:placetype":"locality"
},
  "geometry": {"coordinates":[-63.08333,-17.15],"type":"Point"}
}