{
  "type": "Feature",
  "properties": {
    "gn:admin1_code":"08",
    "gn:asciiname":"Breme",
    "gn:country_code":"BO",
    "gn:dem":255,
    "gn:feature_class":"P",
    "gn:feature_code":"PPL",
    "gn:name":"Breme",
    "gn:population":0,
    "gn:timezone":"America/La_Paz",
    "iso:country":"BO",
    "wof:name":"Breme",
    "wof:placetype":"locality"
},
  "geometry": {"coordinates":[-63.08333,-17.15],"type":"Point"}
}