{
  "type": "Feature",
  "properties": {
    "gn:admin1_code":"05",
    "gn:asciiname":"Estancia Huacuyo",
    "gn:country_code":"BO",
    "gn:dem":4063,
    "gn:feature_class":"P",
    "gn:feature_code":"PPL",
    "gn:name":"Estancia Huacuyo",
    "gn:population":0,
    "gn:timezone":"America/La_Paz",
    "iso:country":"BO",
    "wof:name":"Estancia Huacuyo",
    "wof:placetype":"locality"
},
  "geometry": {"coordinates":[-67.6931,-18.12548],"type":"Point"}
}