{
  "type": "Feature",
  "properties": {
    "gn:admin1_code":"1.0",
    "gn:asciiname":"Pata Pampa",
    "gn:country_code":"BO",
    "gn:dem":2462,
    "gn:feature_class":"P",
    "gn:feature_code":"PPL",
    "gn:name":"Pata Pampa",
    "gn:population":0,
    "gn:timezone":"America/La_Paz",
    "iso:country":"BO",
    "name:und_x_variant":[
        "Estancia Pata Pampa",
        "Pata Pampa"
    ],
    "wof:name":"Pata Pampa",
    "wof:placetype":"locality"
},
  "geometry": {"coordinates":[-65.18859999999999,-20.61464],"type":"Point"}
}