{
  "type": "Feature",
  "properties": {
    "gn:admin1_code":"7.0",
    "gn:asciiname":"Pachincha Grande",
    "gn:country_code":"BO",
    "gn:dem":4023,
    "gn:feature_class":"P",
    "gn:feature_code":"PPL",
    "gn:name":"Pachincha Grande",
    "gn:population":0,
    "gn:timezone":"America/La_Paz",
    "iso:country":"BO",
    "wof:name":"Pachincha Grande",
    "wof:placetype":"locality"
},
  "geometry": {"coordinates":[-67.78333000000001,-20.85],"type":"Point"}
}