{
  "type": "Feature",
  "properties": {
    "gn:admin1_code":"6.0",
    "gn:asciiname":"Napoleon",
    "gn:country_code":"BO",
    "gn:dem":252,
    "gn:feature_class":"P",
    "gn:feature_code":"PPL",
    "gn:name":"Napole\u00f3n",
    "gn:population":0,
    "gn:timezone":"America/La_Paz",
    "iso:country":"BO",
    "wof:name":"Napoleon",
    "wof:placetype":"locality"
},
  "geometry": {"coordinates":[-69.34999999999999,-10.95],"type":"Point"}
}