{
  "type": "Feature",
  "properties": {
    "gn:admin1_code":"04",
    "gn:asciiname":"Chojasivi",
    "gn:country_code":"BO",
    "gn:dem":3830,
    "gn:feature_class":"P",
    "gn:feature_code":"PPL",
    "gn:name":"Chojasivi",
    "gn:population":0,
    "gn:timezone":"America/La_Paz",
    "iso:country":"BO",
    "wof:name":"Chojasivi",
    "wof:placetype":"locality"
},
  "geometry": {"coordinates":[-68.69423,-16.43941],"type":"Point"}
}