{
  "type": "Feature",
  "properties": {
    "gn:admin1_code":"9.0",
    "gn:asciiname":"Piedra Pintada",
    "gn:country_code":"BO",
    "gn:dem":1815,
    "gn:feature_class":"P",
    "gn:feature_code":"PPL",
    "gn:name":"Piedra Pintada",
    "gn:population":0,
    "gn:timezone":"America/La_Paz",
    "iso:country":"BO",
    "name:spa_x_preferred":[
        "Piedra Pintada"
    ],
    "wof:name":"Piedra Pintada",
    "wof:placetype":"locality"
},
  "geometry": {"coordinates":[-64.62035,-21.60405],"type":"Point"}
}