{
  "type": "Feature",
  "properties": {
    "gn:admin1_code":"06",
    "gn:asciiname":"Bolpebra",
    "gn:cc2":"BO",
    "gn:country_code":"BO",
    "gn:dem":234,
    "gn:feature_class":"P",
    "gn:feature_code":"PPL",
    "gn:name":"Bolpebra",
    "gn:population":0,
    "gn:timezone":"America/La_Paz",
    "iso:country":"BO",
    "name:por_x_preferred":[
        "Bolpebra"
    ],
    "name:spa_x_preferred":[
        "Bolpebra"
    ],
    "name:und_x_variant":[
        "Guarnicion Bolpebra",
        "Bolpabra",
        "Fort\u00edn Bolpebra",
        "Bolpebra"
    ],
    "wof:name":"Bolpebra",
    "wof:placetype":"locality"
},
  "geometry": {"coordinates":[-69.56369000000001,-10.94894],"type":"Point"}
}