{
  "type": "Feature",
  "properties": {
    "gn:admin1_code":"1.0",
    "gn:asciiname":"San Jacinto",
    "gn:country_code":"BO",
    "gn:dem":3117,
    "gn:feature_class":"P",
    "gn:feature_code":"PPL",
    "gn:name":"San Jacinto",
    "gn:population":0,
    "gn:timezone":"America/La_Paz",
    "iso:country":"BO",
    "name:und_x_variant":[
        "Estancia San Jacinto",
        "San Jacinto"
    ],
    "wof:name":"San Jacinto",
    "wof:placetype":"locality"
},
  "geometry": {"coordinates":[-64.74791,-19.32067],"type":"Point"}
}