{
  "type": "Feature",
  "properties": {
    "gn:admin1_code":"06",
    "gn:asciiname":"Libertad",
    "gn:country_code":"BO",
    "gn:dem":202,
    "gn:feature_class":"P",
    "gn:feature_code":"PPL",
    "gn:name":"Libertad",
    "gn:population":0,
    "gn:timezone":"America/La_Paz",
    "iso:country":"BO",
    "name:spa_x_preferred":[
        "Libertad"
    ],
    "wof:name":"Libertad",
    "wof:placetype":"locality"
},
  "geometry": {"coordinates":[-68.09645999999999,-11.57127],"type":"Point"}
}