{
  "type": "Feature",
  "properties": {
    "gn:admin1_code":"5.0",
    "gn:asciiname":"Estancia Sullavi",
    "gn:country_code":"BO",
    "gn:dem":3804,
    "gn:feature_class":"P",
    "gn:feature_code":"PPL",
    "gn:name":"Estancia Sullavi",
    "gn:population":0,
    "gn:timezone":"America/La_Paz",
    "iso:country":"BO",
    "wof:name":"Estancia Sullavi",
    "wof:placetype":"locality"
},
  "geometry": {"coordinates":[-68.57432,-19.00737],"type":"Point"}
}