{
  "type": "Feature",
  "properties": {
    "gn:admin1_code":"2.0",
    "gn:asciiname":"Estancia Llallagua",
    "gn:country_code":"BO",
    "gn:dem":3930,
    "gn:feature_class":"P",
    "gn:feature_code":"PPL",
    "gn:name":"Estancia Llallagua",
    "gn:population":0,
    "gn:timezone":"America/La_Paz",
    "iso:country":"BO",
    "wof:name":"Estancia Llallagua",
    "wof:placetype":"locality"
},
  "geometry": {"coordinates":[-66.46666999999999,-17.68332999999999],"type":"Point"}
}