{
  "type": "Feature",
  "properties": {
    "gn:admin1_code":"02",
    "gn:asciiname":"Estancia Khuchu Rancho",
    "gn:country_code":"BO",
    "gn:dem":2212,
    "gn:feature_class":"P",
    "gn:feature_code":"PPL",
    "gn:name":"Estancia Khuchu Rancho",
    "gn:population":0,
    "gn:timezone":"America/La_Paz",
    "iso:country":"BO",
    "wof:name":"Estancia Khuchu Rancho",
    "wof:placetype":"locality"
},
  "geometry": {"coordinates":[-65.14416999999999,-18.13215],"type":"Point"}
}