{
  "type": "Feature",
  "properties": {
    "gn:admin1_code":"02",
    "gn:asciiname":"Estancia Aramani",
    "gn:country_code":"BO",
    "gn:dem":2981,
    "gn:feature_class":"P",
    "gn:feature_code":"PPL",
    "gn:name":"Estancia Aramani",
    "gn:population":0,
    "gn:timezone":"America/La_Paz",
    "iso:country":"BO",
    "wof:name":"Estancia Aramani",
    "wof:placetype":"locality"
},
  "geometry": {"coordinates":[-66.86667,-17.26667],"type":"Point"}
}