{
  "type": "Feature",
  "properties": {
    "gn:admin1_code":"5.0",
    "gn:asciiname":"Estancia Machaj Huano",
    "gn:country_code":"BO",
    "gn:dem":3709,
    "gn:feature_class":"P",
    "gn:feature_code":"PPL",
    "gn:name":"Estancia Machaj Huano",
    "gn:population":0,
    "gn:timezone":"America/La_Paz",
    "iso:country":"BO",
    "wof:name":"Estancia Machaj Huano",
    "wof:placetype":"locality"
},
  "geometry": {"coordinates":[-68.06451,-18.76904],"type":"Point"}
}