{
  "type": "Feature",
  "properties": {
    "gn:admin1_code":"4.0",
    "gn:asciiname":"Jicha Pata",
    "gn:cc2":"BO",
    "gn:country_code":"BO",
    "gn:dem":4383,
    "gn:feature_class":"P",
    "gn:feature_code":"PPL",
    "gn:name":"Jicha Pata",
    "gn:population":0,
    "gn:timezone":"America/La_Paz",
    "iso:country":"BO",
    "name:und_x_variant":[
        "Estancia Jichapata",
        "Jicha Pata"
    ],
    "wof:name":"Jicha Pata",
    "wof:placetype":"locality"
},
  "geometry": {"coordinates":[-69.23333000000001,-15.06667],"type":"Point"}
}