{
  "type": "Feature",
  "properties": {
    "gn:admin1_code":"7.0",
    "gn:asciiname":"Pajancha",
    "gn:country_code":"BO",
    "gn:dem":3816,
    "gn:feature_class":"P",
    "gn:feature_code":"PPL",
    "gn:name":"Pajancha",
    "gn:population":0,
    "gn:timezone":"America/La_Paz",
    "iso:country":"BO",
    "wof:name":"Pajancha",
    "wof:placetype":"locality"
},
  "geometry": {"coordinates":[-68.35259000000001,-21.00912000000001],"type":"Point"}
}