{
  "type": "Feature",
  "properties": {
    "gn:admin1_code":"4.0",
    "gn:asciiname":"Umala",
    "gn:country_code":"BO",
    "gn:dem":3836,
    "gn:feature_class":"P",
    "gn:feature_code":"PPL",
    "gn:name":"Umala",
    "gn:population":0,
    "gn:timezone":"America/La_Paz",
    "iso:country":"BO",
    "name:ceb_x_preferred":[
        "Umala"
    ],
    "name:deu_x_preferred":[
        "Umala"
    ],
    "name:ita_x_preferred":[
        "Umala"
    ],
    "name:kat_x_preferred":[
        "\u10e3\u10db\u10d0\u10da\u10d8\u10e1 \u10db\u10e3\u10dc\u10d8\u10ea\u10d8\u10de\u10d0\u10da\u10d8\u10e2\u10d4\u10e2\u10d8"
    ],
    "name:nld_x_preferred":[
        "Umala"
    ],
    "name:que_x_preferred":[
        "Umala munisipyu"
    ],
    "name:sco_x_preferred":[
        "Umala"
    ],
    "name:spa_x_preferred":[
        "Umala"
    ],
    "name:swe_x_preferred":[
        "Umala"
    ],
    "name:xmf_x_preferred":[
        "\u10e3\u10db\u10d0\u10da\u10d0\u10e8 \u10db\u10e3\u10dc\u10d8\u10ea\u10d8\u10de\u10d0\u10da\u10d8\u10e2\u10d4\u10e2\u10d8"
    ],
    "wof:name":"Umala",
    "wof:placetype":"locality"
},
  "geometry": {"coordinates":[-68.02177,-17.37561],"type":"Point"}
}