{
  "type": "Feature",
  "properties": {
    "gn:admin1_code":"07",
    "gn:asciiname":"Chahuiri",
    "gn:country_code":"BO",
    "gn:dem":4386,
    "gn:feature_class":"P",
    "gn:feature_code":"PPL",
    "gn:name":"Chahuiri",
    "gn:population":0,
    "gn:timezone":"America/La_Paz",
    "iso:country":"BO",
    "wof:name":"Chahuiri",
    "wof:placetype":"locality"
},
  "geometry": {"coordinates":[-66.61667,-21.65],"type":"Point"}
}