{
  "type": "Feature",
  "properties": {
    "gn:admin1_code":"8.0",
    "gn:asciiname":"Santa Cruz y Surutu",
    "gn:cc2":"BO",
    "gn:country_code":"BO",
    "gn:dem":874,
    "gn:feature_class":"P",
    "gn:feature_code":"PPL",
    "gn:name":"Santa Cruz y Surut\u00fa",
    "gn:population":0,
    "gn:timezone":"America/La_Paz",
    "iso:country":"BO",
    "name:und_x_variant":[
        "Santa Cruz Surut\u00fa",
        "Santa Cruz y Surut\u00fa"
    ],
    "wof:name":"Santa Cruz y Surutu",
    "wof:placetype":"locality"
},
  "geometry": {"coordinates":[-63.63333000000001,-17.78333],"type":"Point"}
}