{
  "type": "Feature",
  "properties": {
    "gn:admin1_code":"08",
    "gn:asciiname":"Alegre",
    "gn:country_code":"BO",
    "gn:dem":263,
    "gn:feature_class":"P",
    "gn:feature_code":"PPL",
    "gn:name":"Alegre",
    "gn:population":0,
    "gn:timezone":"America/La_Paz",
    "iso:country":"BO",
    "name:cat_x_preferred":[
        "Alegre"
    ],
    "name:ceb_x_preferred":[
        "Alegre"
    ],
    "name:deu_x_preferred":[
        "Alegre"
    ],
    "name:fra_x_preferred":[
        "Alegre"
    ],
    "name:nld_x_preferred":[
        "Alegre"
    ],
    "name:srp_x_preferred":[
        "\u0410\u043b\u0435\u0433\u0440\u0435"
    ],
    "name:swe_x_preferred":[
        "Alegre"
    ],
    "wof:name":"Alegre",
    "wof:placetype":"locality"
},
  "geometry": {"coordinates":[-61.16667,-17.31667],"type":"Point"}
}