{
  "type": "Feature",
  "properties": {
    "gn:admin1_code":"08",
    "gn:asciiname":"Comunidad La Encrucijada",
    "gn:country_code":"BO",
    "gn:dem":512,
    "gn:feature_class":"P",
    "gn:feature_code":"PPL",
    "gn:name":"Comunidad La Encrucijada",
    "gn:population":0,
    "gn:timezone":"America/La_Paz",
    "iso:country":"BO",
    "wof:name":"Comunidad La Encrucijada",
    "wof:placetype":"locality"
},
  "geometry": {"coordinates":[-60.76667,-16.61667000000001],"type":"Point"}
}