{
  "type": "Feature",
  "properties": {
    "gn:admin1_code":"7.0",
    "gn:asciiname":"Toroca",
    "gn:country_code":"BO",
    "gn:dem":2632,
    "gn:feature_class":"P",
    "gn:feature_code":"PPL",
    "gn:name":"Toroca",
    "gn:population":0,
    "gn:timezone":"America/La_Paz",
    "iso:country":"BO",
    "wof:name":"Toroca",
    "wof:placetype":"locality"
},
  "geometry": {"coordinates":[-65.44015,-18.69929],"type":"Point"}
}