{
  "type": "Feature",
  "properties": {
    "gn:admin1_code":"06",
    "gn:asciiname":"Barraca Puerto Romero",
    "gn:country_code":"BO",
    "gn:dem":151,
    "gn:feature_class":"P",
    "gn:feature_code":"PPL",
    "gn:name":"Barraca Puerto Romero",
    "gn:population":0,
    "gn:timezone":"America/La_Paz",
    "iso:country":"BO",
    "name:spa_x_preferred":[
        "Barraca Puerto Romero"
    ],
    "wof:name":"Barraca Puerto Romero",
    "wof:placetype":"locality"
},
  "geometry": {"coordinates":[-67.14820999999999,-10.48338],"type":"Point"}
}