{
  "type": "Feature",
  "properties": {
    "gn:admin1_code":"5.0",
    "gn:asciiname":"Soracachi",
    "gn:country_code":"BO",
    "gn:dem":3784,
    "gn:feature_class":"P",
    "gn:feature_code":"PPL",
    "gn:name":"Soracachi",
    "gn:population":0,
    "gn:timezone":"America/La_Paz",
    "iso:country":"BO",
    "wof:name":"Soracachi",
    "wof:placetype":"locality"
},
  "geometry": {"coordinates":[-67.03333000000001,-17.76667],"type":"Point"}
}