{
  "type": "Feature",
  "properties": {
    "gn:admin1_code":"01",
    "gn:asciiname":"Capira",
    "gn:country_code":"BO",
    "gn:dem":2405,
    "gn:feature_class":"P",
    "gn:feature_code":"PPL",
    "gn:name":"Capira",
    "gn:population":0,
    "gn:timezone":"America/La_Paz",
    "iso:country":"BO",
    "name:ita_x_preferred":[
        "Capira"
    ],
    "name:nld_x_preferred":[
        "Capira"
    ],
    "name:spa_x_preferred":[
        "Capira"
    ],
    "name:zho_x_preferred":[
        "\u5361\u76ae\u62c9"
    ],
    "wof:name":"Capira",
    "wof:placetype":"locality"
},
  "geometry": {"coordinates":[-64.61667,-20.36667000000001],"type":"Point"}
}