{
  "type": "Feature",
  "properties": {
    "gn:admin1_code":"04",
    "gn:asciiname":"Culta",
    "gn:cc2":"BO",
    "gn:country_code":"BO",
    "gn:dem":3789,
    "gn:feature_class":"P",
    "gn:feature_code":"PPL",
    "gn:name":"Culta",
    "gn:population":0,
    "gn:timezone":"America/La_Paz",
    "iso:country":"BO",
    "name:und_x_variant":[
        "Collta",
        "Culta"
    ],
    "wof:name":"Culta",
    "wof:placetype":"locality"
},
  "geometry": {"coordinates":[-67.90000000000001,-17.26667],"type":"Point"}
}