{
  "type": "Feature",
  "properties": {
    "gn:admin1_code":"01",
    "gn:asciiname":"Cidral",
    "gn:country_code":"BO",
    "gn:dem":1059,
    "gn:feature_class":"P",
    "gn:feature_code":"PPL",
    "gn:name":"Cidral",
    "gn:population":0,
    "gn:timezone":"America/La_Paz",
    "iso:country":"BO",
    "name:spa_x_preferred":[
        "Cidral"
    ],
    "name:und_x_variant":[
        "El Cidral"
    ],
    "wof:name":"Cidral",
    "wof:placetype":"locality"
},
  "geometry": {"coordinates":[-64.10025,-19.6355],"type":"Point"}
}