{
  "type": "Feature",
  "properties": {
    "gn:admin1_code":"06",
    "gn:asciiname":"Centro",
    "gn:country_code":"BO",
    "gn:dem":209,
    "gn:feature_class":"P",
    "gn:feature_code":"PPL",
    "gn:name":"Centro",
    "gn:population":0,
    "gn:timezone":"America/La_Paz",
    "iso:country":"BO",
    "wof:name":"Centro",
    "wof:placetype":"locality"
},
  "geometry": {"coordinates":[-67.28333000000001,-10.68333],"type":"Point"}
}