{
  "type": "Feature",
  "properties": {
    "gn:admin1_code":"7.0",
    "gn:asciiname":"Lupi Gera",
    "gn:country_code":"BO",
    "gn:dem":4229,
    "gn:feature_class":"P",
    "gn:feature_code":"PPL",
    "gn:name":"Lupi Gera",
    "gn:population":0,
    "gn:timezone":"America/La_Paz",
    "iso:country":"BO",
    "wof:name":"Lupi Gera",
    "wof:placetype":"locality"
},
  "geometry": {"coordinates":[-67.34913,-22.04641],"type":"Point"}
}