{
  "type": "Feature",
  "properties": {
    "gn:admin1_code":"7.0",
    "gn:asciiname":"Quenayani",
    "gn:country_code":"BO",
    "gn:dem":3775,
    "gn:feature_class":"P",
    "gn:feature_code":"PPL",
    "gn:name":"Quenayani",
    "gn:population":0,
    "gn:timezone":"America/La_Paz",
    "iso:country":"BO",
    "wof:name":"Quenayani",
    "wof:placetype":"locality"
},
  "geometry": {"coordinates":[-67.13602,-21.13175],"type":"Point"}
}