{
  "type": "Feature",
  "properties": {
    "gn:admin1_code":"4.0",
    "gn:asciiname":"Ixiamas",
    "gn:country_code":"BO",
    "gn:dem":258,
    "gn:feature_class":"P",
    "gn:feature_code":"PPL",
    "gn:name":"Ixiamas",
    "gn:population":0,
    "gn:timezone":"America/La_Paz",
    "iso:country":"BO",
    "name:ceb_x_preferred":[
        "Ixiamas"
    ],
    "name:deu_x_preferred":[
        "Ixiamas"
    ],
    "name:fra_x_preferred":[
        "Ixiamas"
    ],
    "name:pol_x_preferred":[
        "Ixiamas"
    ],
    "name:que_x_preferred":[
        "Ixiamas"
    ],
    "name:spa_x_preferred":[
        "Ixiamas"
    ],
    "name:war_x_preferred":[
        "Ixiamas"
    ],
    "name:zho_x_preferred":[
        "\u4f0a\u897f\u4e9e\u99ac\u65af"
    ],
    "wof:name":"Ixiamas",
    "wof:placetype":"locality"
},
  "geometry": {"coordinates":[-68.15000000000001,-13.75],"type":"Point"}
}