{
  "type": "Feature",
  "properties": {
    "gn:admin1_code":"4.0",
    "gn:asciiname":"Wichuraya",
    "gn:cc2":"BO",
    "gn:country_code":"BO",
    "gn:dem":3899,
    "gn:feature_class":"P",
    "gn:feature_code":"PPL",
    "gn:name":"Wichuraya",
    "gn:population":0,
    "gn:timezone":"America/La_Paz",
    "iso:country":"BO",
    "name:und_x_variant":[
        "Estancia Wichuraya Chico",
        "Wichuraya"
    ],
    "wof:name":"Wichuraya",
    "wof:placetype":"locality"
},
  "geometry": {"coordinates":[-68.23333000000001,-16.83333],"type":"Point"}
}