{
  "type": "Feature",
  "properties": {
    "gn:admin1_code":"6.0",
    "gn:asciiname":"Hamburgo",
    "gn:country_code":"BO",
    "gn:dem":243,
    "gn:feature_class":"P",
    "gn:feature_code":"PPL",
    "gn:name":"Hamburgo",
    "gn:population":0,
    "gn:timezone":"America/La_Paz",
    "iso:country":"BO",
    "wof:name":"Hamburgo",
    "wof:placetype":"locality"
},
  "geometry": {"coordinates":[-67.88333,-10.98333],"type":"Point"}
}