{
  "type": "Feature",
  "properties": {
    "gn:admin1_code":"7.0",
    "gn:asciiname":"Hornos",
    "gn:country_code":"BO",
    "gn:dem":3364,
    "gn:feature_class":"P",
    "gn:feature_code":"PPL",
    "gn:name":"Hornos",
    "gn:population":0,
    "gn:timezone":"America/La_Paz",
    "iso:country":"BO",
    "name:ara_x_preferred":[
        "\u0623\u0648\u0631\u0646\u0648\u0633"
    ],
    "name:ast_x_preferred":[
        "Hornos"
    ],
    "name:azb_x_preferred":[
        "\u0647\u0631\u0646\u0633"
    ],
    "name:cat_x_preferred":[
        "Hornos"
    ],
    "name:deu_x_preferred":[
        "Hornos"
    ],
    "name:eus_x_preferred":[
        "Hornos"
    ],
    "name:fas_x_preferred":[
        "\u0647\u0631\u0646\u0633"
    ],
    "name:fra_x_preferred":[
        "Hornos"
    ],
    "name:hat_x_preferred":[
        "Hornos"
    ],
    "name:hun_x_preferred":[
        "Hornos"
    ],
    "name:hye_x_preferred":[
        "\u0555\u057c\u0576\u0578\u057d"
    ],
    "name:ita_x_preferred":[
        "Hornos"
    ],
    "name:msa_x_preferred":[
        "Hornos"
    ],
    "name:nld_x_preferred":[
        "Hornos"
    ],
    "name:oci_x_preferred":[
        "Hornos"
    ],
    "name:pol_x_preferred":[
        "Hornos"
    ],
    "name:por_x_preferred":[
        "Hornos"
    ],
    "name:ron_x_preferred":[
        "Hornos"
    ],
    "name:rus_x_preferred":[
        "\u041e\u0440\u043d\u043e\u0441"
    ],
    "name:spa_x_preferred":[
        "Hornos"
    ],
    "name:tur_x_preferred":[
        "Hornos"
    ],
    "name:ukr_x_preferred":[
        "\u041e\u0440\u043d\u043e\u0441"
    ],
    "name:uzb_x_preferred":[
        "Hornos"
    ],
    "name:vie_x_preferred":[
        "Hornos"
    ],
    "name:war_x_preferred":[
        "Hornos"
    ],
    "name:zho_x_preferred":[
        "\u5965\u5c14\u8bfa\u65af"
    ],
    "wof:name":"Hornos",
    "wof:placetype":"locality"
},
  "geometry": {"coordinates":[-65.43736,-22.00243],"type":"Point"}
}