{
  "type": "Feature",
  "properties": {
    "gn:admin1_code":"7.0",
    "gn:asciiname":"Hornos",
    "gn:country_code":"BO",
    "gn:dem":3364,
    "gn:feature_class":"P",
    "gn:feature_code":"PPL",
    "gn:name":"Hornos",
    "gn:population":0,
    "gn:timezone":"America/La_Paz",
    "iso:country":"BO",
    "wof:name":"Hornos",
    "wof:placetype":"locality"
},
  "geometry": {"coordinates":[-65.43736,-22.00243],"type":"Point"}
}