{
  "type": "Feature",
  "properties": {
    "gn:admin1_code":"2.0",
    "gn:asciiname":"Estancia Monte Waykho",
    "gn:country_code":"BO",
    "gn:dem":4087,
    "gn:feature_class":"P",
    "gn:feature_code":"PPL",
    "gn:name":"Estancia Monte Waykho",
    "gn:population":0,
    "gn:timezone":"America/La_Paz",
    "iso:country":"BO",
    "wof:name":"Estancia Monte Waykho",
    "wof:placetype":"locality"
},
  "geometry": {"coordinates":[-66.25,-17.16667],"type":"Point"}
}