{
  "type": "Feature",
  "properties": {
    "gn:admin1_code":"4.0",
    "gn:asciiname":"Huancarani",
    "gn:country_code":"BO",
    "gn:dem":4339,
    "gn:feature_class":"P",
    "gn:feature_code":"PPL",
    "gn:name":"Huancarani",
    "gn:population":0,
    "gn:timezone":"America/La_Paz",
    "iso:country":"BO",
    "name:und_x_variant":[
        "Estancia Huancarani",
        "Huancarani"
    ],
    "wof:name":"Huancarani",
    "wof:placetype":"locality"
},
  "geometry": {"coordinates":[-69.02059,-15.30679],"type":"Point"}
}