{
  "type": "Feature",
  "properties": {
    "gn:admin1_code":"04",
    "gn:asciiname":"Boca Toma",
    "gn:cc2":"BO",
    "gn:country_code":"BO",
    "gn:dem":2689,
    "gn:feature_class":"P",
    "gn:feature_code":"PPL",
    "gn:name":"Boca Toma",
    "gn:population":0,
    "gn:timezone":"America/La_Paz",
    "iso:country":"BO",
    "name:und_x_variant":[
        "Estancia Bocatoma",
        "Boca Toma"
    ],
    "wof:name":"Boca Toma",
    "wof:placetype":"locality"
},
  "geometry": {"coordinates":[-67.09999999999999,-17.11667000000001],"type":"Point"}
}