{
  "type": "Feature",
  "properties": {
    "gn:admin1_code":"4.0",
    "gn:asciiname":"Estancia Sirarani",
    "gn:country_code":"BO",
    "gn:dem":3889,
    "gn:feature_class":"P",
    "gn:feature_code":"PPL",
    "gn:name":"Estancia Sirarani",
    "gn:population":0,
    "gn:timezone":"America/La_Paz",
    "iso:country":"BO",
    "wof:name":"Estancia Sirarani",
    "wof:placetype":"locality"
},
  "geometry": {"coordinates":[-67.08333,-17.15],"type":"Point"}
}