{
  "type": "Feature",
  "properties": {
    "gn:admin1_code":"4.0",
    "gn:asciiname":"Huaychuayo",
    "gn:country_code":"BO",
    "gn:dem":3157,
    "gn:feature_class":"P",
    "gn:feature_code":"PPL",
    "gn:name":"Huaychuayo",
    "gn:population":0,
    "gn:timezone":"America/La_Paz",
    "iso:country":"BO",
    "wof:name":"Huaychuayo",
    "wof:placetype":"locality"
},
  "geometry": {"coordinates":[-68.75,-15.73333],"type":"Point"}
}