{
  "type": "Feature",
  "properties": {
    "gn:admin1_code":"06",
    "gn:asciiname":"Deposito de Almendras",
    "gn:country_code":"BO",
    "gn:dem":181,
    "gn:feature_class":"P",
    "gn:feature_code":"PPL",
    "gn:name":"Deposito de Almendras",
    "gn:population":0,
    "gn:timezone":"America/La_Paz",
    "iso:country":"BO",
    "name:spa_x_preferred":[
        "Deposito de Almendras"
    ],
    "wof:name":"Deposito de Almendras",
    "wof:placetype":"locality"
},
  "geometry": {"coordinates":[-67.08773000000001,-10.42375],"type":"Point"}
}