{
  "type": "Feature",
  "properties": {
    "gn:admin1_code":"4.0",
    "gn:asciiname":"Ulla Ulla",
    "gn:country_code":"BO",
    "gn:dem":4339,
    "gn:feature_class":"P",
    "gn:feature_code":"PPL",
    "gn:name":"Ulla Ulla",
    "gn:population":0,
    "gn:timezone":"America/La_Paz",
    "iso:country":"BO",
    "wof:name":"Ulla Ulla",
    "wof:placetype":"locality"
},
  "geometry": {"coordinates":[-69.26666999999999,-15.05],"type":"Point"}
}