{
  "type": "Feature",
  "properties": {
    "gn:admin1_code":"7.0",
    "gn:asciiname":"Jorinoca",
    "gn:country_code":"BO",
    "gn:dem":3825,
    "gn:feature_class":"P",
    "gn:feature_code":"PPL",
    "gn:name":"Jorinoca",
    "gn:population":0,
    "gn:timezone":"America/La_Paz",
    "iso:country":"BO",
    "wof:name":"Jorinoca",
    "wof:placetype":"locality"
},
  "geometry": {"coordinates":[-66.95748,-19.68128],"type":"Point"}
}