{
  "type": "Feature",
  "properties": {
    "gn:admin1_code":"01",
    "gn:asciiname":"Estancia Jarca Loma",
    "gn:country_code":"BO",
    "gn:dem":2341,
    "gn:feature_class":"P",
    "gn:feature_code":"PPL",
    "gn:name":"Estancia Jarca Loma",
    "gn:population":0,
    "gn:timezone":"America/La_Paz",
    "iso:country":"BO",
    "wof:name":"Estancia Jarca Loma",
    "wof:placetype":"locality"
},
  "geometry": {"coordinates":[-64.61369000000001,-20.87294],"type":"Point"}
}