{
  "type": "Feature",
  "properties": {
    "gn:admin1_code":"04",
    "gn:asciiname":"Comunidad Cotacota",
    "gn:country_code":"BO",
    "gn:dem":3833,
    "gn:feature_class":"P",
    "gn:feature_code":"PPL",
    "gn:name":"Comunidad Cotacota",
    "gn:population":0,
    "gn:timezone":"America/La_Paz",
    "iso:country":"BO",
    "wof:name":"Comunidad Cotacota",
    "wof:placetype":"locality"
},
  "geometry": {"coordinates":[-68.51666999999999,-16.41667],"type":"Point"}
}