{
  "type": "Feature",
  "properties": {
    "gn:admin1_code":"5.0",
    "gn:asciiname":"Estancia Rosa Pata",
    "gn:country_code":"BO",
    "gn:dem":3735,
    "gn:feature_class":"P",
    "gn:feature_code":"PPL",
    "gn:name":"Estancia Rosa Pata",
    "gn:population":0,
    "gn:timezone":"America/La_Paz",
    "iso:country":"BO",
    "wof:name":"Estancia Rosa Pata",
    "wof:placetype":"locality"
},
  "geometry": {"coordinates":[-67.5492,-18.66565],"type":"Point"}
}