{
  "type": "Feature",
  "properties": {
    "gn:admin1_code":"7.0",
    "gn:asciiname":"La Cienaga",
    "gn:country_code":"BO",
    "gn:dem":2662,
    "gn:feature_class":"P",
    "gn:feature_code":"PPL",
    "gn:name":"La Ci\u00e9naga",
    "gn:population":0,
    "gn:timezone":"America/La_Paz",
    "iso:country":"BO",
    "wof:name":"La Cienaga",
    "wof:placetype":"locality"
},
  "geometry": {"coordinates":[-65.61667,-20.81667],"type":"Point"}
}