{
  "type": "Feature",
  "properties": {
    "gn:admin1_code":"4.0",
    "gn:asciiname":"Llojeta",
    "gn:cc2":"BO",
    "gn:country_code":"BO",
    "gn:dem":3698,
    "gn:feature_class":"P",
    "gn:feature_code":"PPL",
    "gn:name":"Llojeta",
    "gn:population":0,
    "gn:timezone":"America/La_Paz",
    "iso:country":"BO",
    "name:und_x_variant":[
        "Comunidad Llojeta",
        "Llojeta"
    ],
    "wof:name":"Llojeta",
    "wof:placetype":"locality"
},
  "geometry": {"coordinates":[-68.13333,-16.53333],"type":"Point"}
}