{
  "type": "Feature",
  "properties": {
    "gn:admin1_code":"08",
    "gn:asciiname":"El Mocho",
    "gn:cc2":"BO",
    "gn:country_code":"BO",
    "gn:dem":279,
    "gn:feature_class":"P",
    "gn:feature_code":"PPL",
    "gn:name":"El Mocho",
    "gn:population":0,
    "gn:timezone":"America/La_Paz",
    "iso:country":"BO",
    "name:und_x_variant":[
        "El Macho",
        "El Mocho"
    ],
    "wof:name":"El Mocho",
    "wof:placetype":"locality"
},
  "geometry": {"coordinates":[-62.55,-15.15],"type":"Point"}
}