{
  "type": "Feature",
  "properties": {
    "gn:admin1_code":"5.0",
    "gn:asciiname":"Tomaquipa",
    "gn:country_code":"BO",
    "gn:dem":3716,
    "gn:feature_class":"P",
    "gn:feature_code":"PPL",
    "gn:name":"Tomaquipa",
    "gn:population":0,
    "gn:timezone":"America/La_Paz",
    "iso:country":"BO",
    "wof:name":"Tomaquipa",
    "wof:placetype":"locality"
},
  "geometry": {"coordinates":[-67.45735000000001,-19.04629],"type":"Point"}
}