{
  "type": "Feature",
  "properties": {
    "gn:admin1_code":"4.0",
    "gn:asciiname":"Macata",
    "gn:cc2":"BO",
    "gn:country_code":"BO",
    "gn:dem":4051,
    "gn:feature_class":"P",
    "gn:feature_code":"PPL",
    "gn:name":"Macata",
    "gn:population":0,
    "gn:timezone":"America/La_Paz",
    "iso:country":"BO",
    "name:und_x_variant":[
        "Estancia Jachcha Macata",
        "Macata"
    ],
    "wof:name":"Macata",
    "wof:placetype":"locality"
},
  "geometry": {"coordinates":[-69.28333000000001,-16.95],"type":"Point"}
}