{
  "type": "Feature",
  "properties": {
    "gn:admin1_code":"04",
    "gn:asciiname":"Cangallo",
    "gn:cc2":"BO",
    "gn:country_code":"BO",
    "gn:dem":777,
    "gn:feature_class":"P",
    "gn:feature_code":"PPL",
    "gn:name":"Cangallo",
    "gn:population":0,
    "gn:timezone":"America/La_Paz",
    "iso:country":"BO",
    "name:und_x_variant":[
        "Sangal",
        "Cangalli",
        "Cangallo"
    ],
    "wof:name":"Cangallo",
    "wof:placetype":"locality"
},
  "geometry": {"coordinates":[-67.95,-15.51667],"type":"Point"}
}