{
  "type": "Feature",
  "properties": {
    "gn:admin1_code":"04",
    "gn:asciiname":"Ancosuni",
    "gn:country_code":"BO",
    "gn:dem":3100,
    "gn:feature_class":"P",
    "gn:feature_code":"PPL",
    "gn:name":"Ancosuni",
    "gn:population":0,
    "gn:timezone":"America/La_Paz",
    "iso:country":"BO",
    "wof:name":"Ancosuni",
    "wof:placetype":"locality"
},
  "geometry": {"coordinates":[-67.96666999999999,-16.78333],"type":"Point"}
}