{
  "type": "Feature",
  "properties": {
    "gn:admin1_code":"09",
    "gn:asciiname":"Capilla de Bermejo",
    "gn:country_code":"BO",
    "gn:dem":1195,
    "gn:feature_class":"P",
    "gn:feature_code":"PPL",
    "gn:name":"Capilla de Bermejo",
    "gn:population":0,
    "gn:timezone":"America/La_Paz",
    "iso:country":"BO",
    "name:und_x_variant":[
        "Bermejo",
        "La Capilla de Bermejo",
        "Capilla de Bermejo"
    ],
    "wof:name":"Capilla de Bermejo",
    "wof:placetype":"locality"
},
  "geometry": {"coordinates":[-64.67227,-22.1803],"type":"Point"}
}