{
  "type": "Feature",
  "properties": {
    "gn:admin1_code":"02",
    "gn:asciiname":"Estancia Huayra Pata",
    "gn:country_code":"BO",
    "gn:dem":2934,
    "gn:feature_class":"P",
    "gn:feature_code":"PPL",
    "gn:name":"Estancia Huayra Pata",
    "gn:population":0,
    "gn:timezone":"America/La_Paz",
    "iso:country":"BO",
    "wof:name":"Estancia Huayra Pata",
    "wof:placetype":"locality"
},
  "geometry": {"coordinates":[-65.41689000000001,-18.2108],"type":"Point"}
}