{
  "type": "Feature",
  "properties": {
    "gn:admin1_code":"3.0",
    "gn:asciiname":"Libertad",
    "gn:country_code":"BO",
    "gn:dem":158,
    "gn:feature_class":"P",
    "gn:feature_code":"PPL",
    "gn:name":"Libertad",
    "gn:population":0,
    "gn:timezone":"America/La_Paz",
    "iso:country":"BO",
    "wof:name":"Libertad",
    "wof:placetype":"locality"
},
  "geometry": {"coordinates":[-64.90000000000001,-15.08333],"type":"Point"}
}