{
  "type": "Feature",
  "properties": {
    "gn:admin1_code":"1.0",
    "gn:asciiname":"Pueblo Alto",
    "gn:country_code":"BO",
    "gn:dem":3021,
    "gn:feature_class":"P",
    "gn:feature_code":"PPL",
    "gn:name":"Pueblo Alto",
    "gn:population":0,
    "gn:timezone":"America/La_Paz",
    "iso:country":"BO",
    "wof:name":"Pueblo Alto",
    "wof:placetype":"locality"
},
  "geometry": {"coordinates":[-64.85935000000001,-20.75799],"type":"Point"}
}