{
  "type": "Feature",
  "properties": {
    "gn:admin1_code":"2.0",
    "gn:asciiname":"Puna Cachi",
    "gn:country_code":"BO",
    "gn:dem":2921,
    "gn:feature_class":"P",
    "gn:feature_code":"PPL",
    "gn:name":"Puna Cachi",
    "gn:population":0,
    "gn:timezone":"America/La_Paz",
    "iso:country":"BO",
    "wof:name":"Puna Cachi",
    "wof:placetype":"locality"
},
  "geometry": {"coordinates":[-66.59999999999999,-17.25],"type":"Point"}
}