{
  "type": "Feature",
  "properties": {
    "gn:admin1_code":"08",
    "gn:asciiname":"Casa Alta",
    "gn:country_code":"BO",
    "gn:dem":606,
    "gn:feature_class":"P",
    "gn:feature_code":"PPL",
    "gn:name":"Casa Alta",
    "gn:population":0,
    "gn:timezone":"America/La_Paz",
    "iso:country":"BO",
    "name:und_x_variant":[
        "Casalta",
        "Casa Alta"
    ],
    "wof:name":"Casa Alta",
    "wof:placetype":"locality"
},
  "geometry": {"coordinates":[-63.13551,-20.02311],"type":"Point"}
}