{
  "type": "Feature",
  "properties": {
    "gn:admin1_code":"1.0",
    "gn:asciiname":"Estancia Nequeta Baja",
    "gn:country_code":"BO",
    "gn:dem":3088,
    "gn:feature_class":"P",
    "gn:feature_code":"PPL",
    "gn:name":"Estancia \u00d1equeta Baja",
    "gn:population":0,
    "gn:timezone":"America/La_Paz",
    "iso:country":"BO",
    "wof:name":"Estancia Nequeta Baja",
    "wof:placetype":"locality"
},
  "geometry": {"coordinates":[-65.20478,-20.53257],"type":"Point"}
}