{
  "type": "Feature",
  "properties": {
    "gn:admin1_code":"7.0",
    "gn:asciiname":"Ticaticaniloma",
    "gn:country_code":"BO",
    "gn:dem":4093,
    "gn:feature_class":"P",
    "gn:feature_code":"PPL",
    "gn:name":"Ticaticaniloma",
    "gn:population":0,
    "gn:timezone":"America/La_Paz",
    "iso:country":"BO",
    "wof:name":"Ticaticaniloma",
    "wof:placetype":"locality"
},
  "geometry": {"coordinates":[-66.43333,-21.13333],"type":"Point"}
}