{
  "type": "Feature",
  "properties": {
    "gn:admin1_code":"07",
    "gn:asciiname":"Actapalla",
    "gn:country_code":"BO",
    "gn:dem":3126,
    "gn:feature_class":"P",
    "gn:feature_code":"PPL",
    "gn:name":"Actapalla",
    "gn:population":0,
    "gn:timezone":"America/La_Paz",
    "iso:country":"BO",
    "wof:name":"Actapalla",
    "wof:placetype":"locality"
},
  "geometry": {"coordinates":[-65.73333000000001,-20.81667],"type":"Point"}
}