{
  "type": "Feature",
  "properties": {
    "gn:admin1_code":"8.0",
    "gn:asciiname":"Mataral",
    "gn:country_code":"BO",
    "gn:dem":1390,
    "gn:feature_class":"P",
    "gn:feature_code":"PPL",
    "gn:name":"Mataral",
    "gn:population":0,
    "gn:timezone":"America/La_Paz",
    "iso:country":"BO",
    "wof:name":"Mataral",
    "wof:placetype":"locality"
},
  "geometry": {"coordinates":[-64.21464,-18.11614],"type":"Point"}
}