{
  "type": "Feature",
  "properties": {
    "gn:admin1_code":"06",
    "gn:asciiname":"Benton",
    "gn:country_code":"BO",
    "gn:dem":182,
    "gn:feature_class":"P",
    "gn:feature_code":"PPL",
    "gn:name":"Benton",
    "gn:population":0,
    "gn:timezone":"America/La_Paz",
    "iso:country":"BO",
    "name:spa_x_preferred":[
        "Benton"
    ],
    "wof:name":"Benton",
    "wof:placetype":"locality"
},
  "geometry": {"coordinates":[-67.76403000000001,-11.14253],"type":"Point"}
}