{
  "type": "Feature",
  "properties": {
    "gn:admin1_code":"06",
    "gn:asciiname":"Benton",
    "gn:country_code":"BO",
    "gn:dem":182,
    "gn:feature_class":"P",
    "gn:feature_code":"PPL",
    "gn:name":"Benton",
    "gn:population":0,
    "gn:timezone":"America/La_Paz",
    "iso:country":"BO",
    "name:bul_x_preferred":[
        "\u0411\u0435\u043d\u0442\u044a\u043d"
    ],
    "name:cat_x_preferred":[
        "Benton"
    ],
    "name:ceb_x_preferred":[
        "Benton"
    ],
    "name:ces_x_preferred":[
        "Benton"
    ],
    "name:deu_x_preferred":[
        "Benton"
    ],
    "name:fra_x_preferred":[
        "Benton"
    ],
    "name:glg_x_preferred":[
        "Benton"
    ],
    "name:hun_x_preferred":[
        "Benton"
    ],
    "name:ido_x_preferred":[
        "Benton"
    ],
    "name:ita_x_preferred":[
        "Benton"
    ],
    "name:jpn_x_preferred":[
        "\u30d9\u30f3\u30c8\u30f3"
    ],
    "name:nld_x_preferred":[
        "Benton"
    ],
    "name:pol_x_preferred":[
        "Benton"
    ],
    "name:por_x_preferred":[
        "Benton"
    ],
    "name:rus_x_preferred":[
        "\u0411\u0435\u043d\u0442\u043e\u043d"
    ],
    "name:spa_x_preferred":[
        "Benton"
    ],
    "name:srp_x_preferred":[
        "\u0411\u0435\u043d\u0442\u043e\u043d"
    ],
    "name:swe_x_preferred":[
        "Benton"
    ],
    "name:ukr_x_preferred":[
        "\u0411\u0435\u043d\u0442\u043e\u043d"
    ],
    "name:urd_x_preferred":[
        "\u0628\u06cc\u0646\u0679\u0646"
    ],
    "name:vol_x_preferred":[
        "Benton"
    ],
    "wof:name":"Benton",
    "wof:placetype":"locality"
},
  "geometry": {"coordinates":[-67.76403000000001,-11.14253],"type":"Point"}
}