{
  "type": "Feature",
  "properties": {
    "gn:admin1_code":"6.0",
    "gn:asciiname":"Nuevo Destino",
    "gn:country_code":"BO",
    "gn:dem":143,
    "gn:feature_class":"P",
    "gn:feature_code":"PPL",
    "gn:name":"Nuevo Destino",
    "gn:population":0,
    "gn:timezone":"America/La_Paz",
    "iso:country":"BO",
    "wof:name":"Nuevo Destino",
    "wof:placetype":"locality"
},
  "geometry": {"coordinates":[-66.82379,-10.47449],"type":"Point"}
}