{
  "type": "Feature",
  "properties": {
    "gn:admin1_code":"04",
    "gn:asciiname":"Chiaraque",
    "gn:country_code":"BO",
    "gn:dem":3389,
    "gn:feature_class":"P",
    "gn:feature_code":"PPL",
    "gn:name":"Chiaraque",
    "gn:population":0,
    "gn:timezone":"America/La_Paz",
    "iso:country":"BO",
    "wof:name":"Chiaraque",
    "wof:placetype":"locality"
},
  "geometry": {"coordinates":[-67.45,-17.18333],"type":"Point"}
}