{
  "type": "Feature",
  "properties": {
    "gn:admin1_code":"06",
    "gn:asciiname":"Colonia",
    "gn:country_code":"BO",
    "gn:dem":183,
    "gn:feature_class":"P",
    "gn:feature_code":"PPL",
    "gn:name":"Colonia",
    "gn:population":0,
    "gn:timezone":"America/La_Paz",
    "iso:country":"BO",
    "wof:name":"Colonia",
    "wof:placetype":"locality"
},
  "geometry": {"coordinates":[-66.13333,-10.36667],"type":"Point"}
}