{
  "type": "Feature",
  "properties": {
    "gn:admin1_code":"06",
    "gn:asciiname":"Colonia",
    "gn:country_code":"BO",
    "gn:dem":183,
    "gn:feature_class":"P",
    "gn:feature_code":"PPL",
    "gn:name":"Colonia",
    "gn:population":0,
    "gn:timezone":"America/La_Paz",
    "iso:country":"BO",
    "name:ast_x_preferred":[
        "Colonia"
    ],
    "name:bel_x_preferred":[
        "\u041a\u0430\u043b\u043e\u043d\u0456\u044f"
    ],
    "name:bre_x_preferred":[
        "Colonia"
    ],
    "name:bul_x_preferred":[
        "\u041a\u043e\u043b\u043e\u043d\u0438\u044f"
    ],
    "name:cat_x_preferred":[
        "Col\u00f2nia"
    ],
    "name:ceb_x_preferred":[
        "Colonia"
    ],
    "name:deu_x_preferred":[
        "Colonia"
    ],
    "name:epo_x_preferred":[
        "Colonia"
    ],
    "name:est_x_preferred":[
        "Koloonia"
    ],
    "name:fin_x_preferred":[
        "Colonia"
    ],
    "name:fra_x_preferred":[
        "Colonia"
    ],
    "name:glg_x_preferred":[
        "Colonia"
    ],
    "name:ita_x_preferred":[
        "Colonia"
    ],
    "name:jpn_x_preferred":[
        "\u30b3\u30ed\u30cb\u30a2"
    ],
    "name:kat_x_preferred":[
        "\u10d9\u10dd\u10da\u10dd\u10dc\u10d8\u10d0"
    ],
    "name:kir_x_preferred":[
        "\u041a\u043e\u043b\u043e\u043d\u0438\u044f"
    ],
    "name:kor_x_preferred":[
        "\ucf5c\ub85c\ub2c8\uc544"
    ],
    "name:lat_x_preferred":[
        "Colonia"
    ],
    "name:nld_x_preferred":[
        "Colonia"
    ],
    "name:pol_x_preferred":[
        "Colonia"
    ],
    "name:por_x_preferred":[
        "Col\u00f3nia"
    ],
    "name:que_x_preferred":[
        "Colonia"
    ],
    "name:ron_x_preferred":[
        "Colonia"
    ],
    "name:rus_x_preferred":[
        "\u041a\u043e\u043b\u043e\u043d\u0438\u044f"
    ],
    "name:spa_x_preferred":[
        "Colonia"
    ],
    "name:swe_x_preferred":[
        "Colonia"
    ],
    "name:ukr_x_preferred":[
        "\u041a\u043e\u043b\u043e\u043d\u0456\u044f"
    ],
    "name:vec_x_preferred":[
        "Co\u0142onia"
    ],
    "name:zho_x_preferred":[
        "\u79d1\u6d1b\u5c3c\u4e9a"
    ],
    "wof:name":"Colonia",
    "wof:placetype":"locality"
},
  "geometry": {"coordinates":[-66.13333,-10.36667],"type":"Point"}
}