{
  "type": "Feature",
  "properties": {
    "gn:admin1_code":"7.0",
    "gn:asciiname":"Isla Grande",
    "gn:country_code":"BO",
    "gn:dem":3480,
    "gn:feature_class":"P",
    "gn:feature_code":"PPL",
    "gn:name":"Isla Grande",
    "gn:population":0,
    "gn:timezone":"America/La_Paz",
    "iso:country":"BO",
    "wof:name":"Isla Grande",
    "wof:placetype":"locality"
},
  "geometry": {"coordinates":[-65.80048000000001,-19.34945],"type":"Point"}
}