{
  "type": "Feature",
  "properties": {
    "gn:admin1_code":"01",
    "gn:asciiname":"El Cerro",
    "gn:country_code":"BO",
    "gn:dem":1968,
    "gn:feature_class":"P",
    "gn:feature_code":"PPL",
    "gn:name":"El Cerro",
    "gn:population":0,
    "gn:timezone":"America/La_Paz",
    "iso:country":"BO",
    "name:arg_x_preferred":[
        "El Cerro"
    ],
    "name:cat_x_preferred":[
        "El Cerro"
    ],
    "name:ceb_x_preferred":[
        "El Cerro"
    ],
    "name:eus_x_preferred":[
        "El Cerro"
    ],
    "name:fra_x_preferred":[
        "El Cerro"
    ],
    "name:haw_x_preferred":[
        "El Cerro"
    ],
    "name:hun_x_preferred":[
        "El Cerro"
    ],
    "name:ina_x_preferred":[
        "El Cerro"
    ],
    "name:ita_x_preferred":[
        "El Cerro"
    ],
    "name:kaz_x_preferred":[
        "\u042d\u043b\u044c-\u0421\u0435\u0440\u0440\u043e"
    ],
    "name:msa_x_preferred":[
        "El Cerro"
    ],
    "name:nld_x_preferred":[
        "El Cerro"
    ],
    "name:oci_x_preferred":[
        "El Cerro"
    ],
    "name:pol_x_preferred":[
        "El Cerro"
    ],
    "name:por_x_preferred":[
        "El Cerro"
    ],
    "name:rus_x_preferred":[
        "\u042d\u043b\u044c-\u0421\u0435\u0440\u0440\u043e"
    ],
    "name:spa_x_preferred":[
        "El Cerro"
    ],
    "name:ukr_x_preferred":[
        "\u0415\u043b\u044c-\u0421\u0435\u0440\u0440\u043e"
    ],
    "name:und_x_variant":[
        "Cerro",
        "El Cerro"
    ],
    "name:vie_x_preferred":[
        "El Cerro"
    ],
    "name:war_x_preferred":[
        "El Cerro"
    ],
    "name:zho_x_preferred":[
        "\u57c3\u5c14\u585e\u7f57"
    ],
    "wof:name":"El Cerro",
    "wof:placetype":"locality"
},
  "geometry": {"coordinates":[-64.21185,-19.51647],"type":"Point"}
}