{
  "type": "Feature",
  "properties": {
    "gn:admin1_code":"06",
    "gn:asciiname":"Vertiente",
    "gn:country_code":"BO",
    "gn:dem":201,
    "gn:feature_class":"P",
    "gn:feature_code":"PPL",
    "gn:name":"Vertiente",
    "gn:population":0,
    "gn:timezone":"America/La_Paz",
    "iso:country":"BO",
    "name:spa_x_preferred":[
        "Vertiente"
    ],
    "wof:name":"Vertiente",
    "wof:placetype":"locality"
},
  "geometry": {"coordinates":[-67.52613000000001,-10.5218],"type":"Point"}
}