{
  "type": "Feature",
  "properties": {
    "gn:admin1_code":"4.0",
    "gn:asciiname":"San Andres de Machaca",
    "gn:cc2":"BO",
    "gn:country_code":"BO",
    "gn:dem":3893,
    "gn:feature_class":"P",
    "gn:feature_code":"PPL",
    "gn:name":"San Andr\u00e9s de Machaca",
    "gn:population":0,
    "gn:timezone":"America/La_Paz",
    "iso:country":"BO",
    "name:und_x_variant":[
        "San Andr\u00e9s",
        "San Andr\u00e9s de Machaca"
    ],
    "wof:name":"San Andres de Machaca",
    "wof:placetype":"locality"
},
  "geometry": {"coordinates":[-68.96666999999999,-16.95],"type":"Point"}
}