{
  "type": "Feature",
  "properties": {
    "gn:admin1_code":"06",
    "gn:asciiname":"Buen Destino",
    "gn:country_code":"BO",
    "gn:dem":265,
    "gn:feature_class":"P",
    "gn:feature_code":"PPL",
    "gn:name":"Buen Destino",
    "gn:population":0,
    "gn:timezone":"America/La_Paz",
    "iso:country":"BO",
    "wof:name":"Buen Destino",
    "wof:placetype":"locality"
},
  "geometry": {"coordinates":[-69.09595,-11.28786],"type":"Point"}
}