{
  "type": "Feature",
  "properties": {
    "gn:admin1_code":"06",
    "gn:asciiname":"San Jose Nuevo",
    "gn:country_code":"BO",
    "gn:dem":162,
    "gn:feature_class":"P",
    "gn:feature_code":"PPL",
    "gn:name":"San Jose Nuevo",
    "gn:population":0,
    "gn:timezone":"America/Rio_Branco",
    "iso:country":"BO",
    "name:spa_x_preferred":[
        "San Jose Nuevo"
    ],
    "wof:name":"San Jose Nuevo",
    "wof:placetype":"locality"
},
  "geometry": {"coordinates":[-68.03621,-10.6693],"type":"Point"}
}