{
  "type": "Feature",
  "properties": {
    "gn:admin1_code":"06",
    "gn:asciiname":"Rimber Ecuari",
    "gn:country_code":"BO",
    "gn:dem":242,
    "gn:feature_class":"P",
    "gn:feature_code":"PPL",
    "gn:name":"Rimber Ecuari",
    "gn:population":0,
    "gn:timezone":"America/La_Paz",
    "iso:country":"BO",
    "name:spa_x_preferred":[
        "Rimber Ecuari"
    ],
    "wof:name":"Rimber Ecuari",
    "wof:placetype":"locality"
},
  "geometry": {"coordinates":[-68.57840999999999,-11.35286],"type":"Point"}
}