{
  "type": "Feature",
  "properties": {
    "gn:admin1_code":"04",
    "gn:asciiname":"Colquepata",
    "gn:cc2":"BO",
    "gn:country_code":"BO",
    "gn:dem":3945,
    "gn:feature_class":"P",
    "gn:feature_code":"PPL",
    "gn:name":"Colquepata",
    "gn:population":0,
    "gn:timezone":"America/La_Paz",
    "iso:country":"BO",
    "name:und_x_variant":[
        "Comunidad Colquepata",
        "Colquepata"
    ],
    "wof:name":"Colquepata",
    "wof:placetype":"locality"
},
  "geometry": {"coordinates":[-68.65000000000001,-16.95],"type":"Point"}
}