{
  "type": "Feature",
  "properties": {
    "gn:admin1_code":"1.0",
    "gn:asciiname":"Tabacal",
    "gn:country_code":"BO",
    "gn:dem":1496,
    "gn:feature_class":"P",
    "gn:feature_code":"PPL",
    "gn:name":"Tabacal",
    "gn:population":0,
    "gn:timezone":"America/La_Paz",
    "iso:country":"BO",
    "wof:name":"Tabacal",
    "wof:placetype":"locality"
},
  "geometry": {"coordinates":[-64.14211,-19.33249],"type":"Point"}
}