{
  "type": "Feature",
  "properties": {
    "gn:admin1_code":"2.0",
    "gn:asciiname":"Jatun Llusta",
    "gn:cc2":"BO",
    "gn:country_code":"BO",
    "gn:dem":2617,
    "gn:feature_class":"P",
    "gn:feature_code":"PPL",
    "gn:name":"Jatun Llusta",
    "gn:population":0,
    "gn:timezone":"America/La_Paz",
    "iso:country":"BO",
    "name:und_x_variant":[
        "Llusta",
        "Jatun Llusta"
    ],
    "wof:name":"Jatun Llusta",
    "wof:placetype":"locality"
},
  "geometry": {"coordinates":[-65.59999999999999,-17.95],"type":"Point"}
}