{
  "type": "Feature",
  "properties": {
    "gn:admin1_code":"2.0",
    "gn:asciiname":"Ventilla",
    "gn:country_code":"BO",
    "gn:dem":3898,
    "gn:feature_class":"P",
    "gn:feature_code":"PPL",
    "gn:name":"Ventilla",
    "gn:population":0,
    "gn:timezone":"America/La_Paz",
    "iso:country":"BO",
    "wof:name":"Ventilla",
    "wof:placetype":"locality"
},
  "geometry": {"coordinates":[-66.66667,-17.78333],"type":"Point"}
}