{
  "type": "Feature",
  "properties": {
    "gn:admin1_code":"1.0",
    "gn:asciiname":"Sanerenda",
    "gn:country_code":"BO",
    "gn:dem":909,
    "gn:feature_class":"P",
    "gn:feature_code":"PPL",
    "gn:name":"Sa\u00f1erenda",
    "gn:population":0,
    "gn:timezone":"America/La_Paz",
    "iso:country":"BO",
    "wof:name":"Sanerenda",
    "wof:placetype":"locality"
},
  "geometry": {"coordinates":[-63.77734,-20.73865],"type":"Point"}
}