{
  "type": "Feature",
  "properties": {
    "gn:admin1_code":"08",
    "gn:asciiname":"Buena Esperanza",
    "gn:country_code":"BO",
    "gn:dem":273,
    "gn:feature_class":"P",
    "gn:feature_code":"PPL",
    "gn:name":"Buena Esperanza",
    "gn:population":0,
    "gn:timezone":"America/La_Paz",
    "iso:country":"BO",
    "name:und_x_variant":[
        "Esperanza",
        "Buena Esperanza"
    ],
    "wof:name":"Buena Esperanza",
    "wof:placetype":"locality"
},
  "geometry": {"coordinates":[-62.31548000000001,-14.88796],"type":"Point"}
}