{
  "type": "Feature",
  "properties": {
    "gn:admin1_code":"7.0",
    "gn:asciiname":"Estancia Tijra",
    "gn:country_code":"BO",
    "gn:dem":4300,
    "gn:feature_class":"P",
    "gn:feature_code":"PPL",
    "gn:name":"Estancia Tijra",
    "gn:population":0,
    "gn:timezone":"America/La_Paz",
    "iso:country":"BO",
    "wof:name":"Estancia Tijra",
    "wof:placetype":"locality"
},
  "geometry": {"coordinates":[-65.73550999999999,-19.68111],"type":"Point"}
}