{
  "type": "Feature",
  "properties": {
    "gn:admin1_code":"8.0",
    "gn:asciiname":"Pascana",
    "gn:country_code":"BO",
    "gn:dem":306,
    "gn:feature_class":"P",
    "gn:feature_code":"PPL",
    "gn:name":"Pascana",
    "gn:population":0,
    "gn:timezone":"America/La_Paz",
    "iso:country":"BO",
    "wof:name":"Pascana",
    "wof:placetype":"locality"
},
  "geometry": {"coordinates":[-60.86666999999999,-17.81667000000001],"type":"Point"}
}