{
  "type": "Feature",
  "properties": {
    "gn:admin1_code":"8.0",
    "gn:asciiname":"Los Huesos",
    "gn:country_code":"BO",
    "gn:dem":926,
    "gn:feature_class":"P",
    "gn:feature_code":"PPL",
    "gn:name":"Los Huesos",
    "gn:population":0,
    "gn:timezone":"America/La_Paz",
    "iso:country":"BO",
    "wof:name":"Los Huesos",
    "wof:placetype":"locality"
},
  "geometry": {"coordinates":[-63.55749,-19.58888],"type":"Point"}
}