{
  "type": "Feature",
  "properties": {
    "gn:admin1_code":"7.0",
    "gn:asciiname":"Estancia Visijsi",
    "gn:country_code":"BO",
    "gn:dem":2869,
    "gn:feature_class":"P",
    "gn:feature_code":"PPL",
    "gn:name":"Estancia Visijsi",
    "gn:population":0,
    "gn:timezone":"America/La_Paz",
    "iso:country":"BO",
    "wof:name":"Estancia Visijsi",
    "wof:placetype":"locality"
},
  "geometry": {"coordinates":[-65.63753,-20.26357],"type":"Point"}
}