{
  "type": "Feature",
  "properties": {
    "gn:admin1_code":"7.0",
    "gn:asciiname":"Wichu Mokho",
    "gn:country_code":"BO",
    "gn:dem":3186,
    "gn:feature_class":"P",
    "gn:feature_code":"PPL",
    "gn:name":"Wichu Mokho",
    "gn:population":0,
    "gn:timezone":"America/La_Paz",
    "iso:country":"BO",
    "name:und_x_variant":[
        "Estancia Wichu Mokho",
        "Wichu Mokho"
    ],
    "wof:name":"Wichu Mokho",
    "wof:placetype":"locality"
},
  "geometry": {"coordinates":[-65.71881999999999,-18.65859],"type":"Point"}
}