{
  "type": "Feature",
  "properties": {
    "gn:admin1_code":"1.0",
    "gn:asciiname":"Estancia Morruda",
    "gn:country_code":"BO",
    "gn:dem":2756,
    "gn:feature_class":"P",
    "gn:feature_code":"PPL",
    "gn:name":"Estancia Morruda",
    "gn:population":0,
    "gn:timezone":"America/La_Paz",
    "iso:country":"BO",
    "wof:name":"Estancia Morruda",
    "wof:placetype":"locality"
},
  "geometry": {"coordinates":[-64.81740000000001,-20.79832],"type":"Point"}
}