{
  "type": "Feature",
  "properties": {
    "gn:admin1_code":"01",
    "gn:asciiname":"Estancia Khatiquilla",
    "gn:country_code":"BO",
    "gn:dem":2996,
    "gn:feature_class":"P",
    "gn:feature_code":"PPL",
    "gn:name":"Estancia Khatiquilla",
    "gn:population":0,
    "gn:timezone":"America/La_Paz",
    "iso:country":"BO",
    "wof:name":"Estancia Khatiquilla",
    "wof:placetype":"locality"
},
  "geometry": {"coordinates":[-65.04524000000001,-19.15938],"type":"Point"}
}