{
  "type": "Feature",
  "properties": {
    "gn:admin1_code":"8.0",
    "gn:asciiname":"Estancia San Andres",
    "gn:country_code":"BO",
    "gn:dem":128,
    "gn:feature_class":"P",
    "gn:feature_code":"PPL",
    "gn:name":"Estancia San Andres",
    "gn:population":0,
    "gn:timezone":"America/La_Paz",
    "iso:country":"BO",
    "wof:name":"Estancia San Andres",
    "wof:placetype":"locality"
},
  "geometry": {"coordinates":[-59.18333000000001,-16.63332999999999],"type":"Point"}
}