{
  "type": "Feature",
  "properties": {
    "gn:admin1_code":"09",
    "gn:asciiname":"Asioca",
    "gn:country_code":"BO",
    "gn:dem":2799,
    "gn:feature_class":"P",
    "gn:feature_code":"PPL",
    "gn:name":"Asioca",
    "gn:population":0,
    "gn:timezone":"America/La_Paz",
    "iso:country":"BO",
    "wof:name":"Asioca",
    "wof:placetype":"locality"
},
  "geometry": {"coordinates":[-65.33333,-21.75],"type":"Point"}
}