{
  "type": "Feature",
  "properties": {
    "gn:admin1_code":"06",
    "gn:asciiname":"Bella Flor",
    "gn:country_code":"BO",
    "gn:dem":188,
    "gn:feature_class":"P",
    "gn:feature_code":"PPL",
    "gn:name":"Bella Flor",
    "gn:population":0,
    "gn:timezone":"America/La_Paz",
    "iso:country":"BO",
    "wof:name":"Bella Flor",
    "wof:placetype":"locality"
},
  "geometry": {"coordinates":[-67.8205,-11.14209],"type":"Point"}
}