{
  "type": "Feature",
  "properties": {
    "gn:admin1_code":"04",
    "gn:asciiname":"Estancia Jankhosuni",
    "gn:country_code":"BO",
    "gn:dem":3397,
    "gn:feature_class":"P",
    "gn:feature_code":"PPL",
    "gn:name":"Estancia Jankhosuni",
    "gn:population":0,
    "gn:timezone":"America/La_Paz",
    "iso:country":"BO",
    "wof:name":"Estancia Jankhosuni",
    "wof:placetype":"locality"
},
  "geometry": {"coordinates":[-67.86667,-16.78333],"type":"Point"}
}