{
  "type": "Feature",
  "properties": {
    "gn:admin1_code":"7.0",
    "gn:asciiname":"Yani Grande",
    "gn:country_code":"BO",
    "gn:dem":3664,
    "gn:feature_class":"P",
    "gn:feature_code":"PPL",
    "gn:name":"Yani Grande",
    "gn:population":0,
    "gn:timezone":"America/La_Paz",
    "iso:country":"BO",
    "name:und_x_variant":[
        "Estancia Yani Grande",
        "Yani Grande"
    ],
    "wof:name":"Yani Grande",
    "wof:placetype":"locality"
},
  "geometry": {"coordinates":[-68.23985999999999,-20.20863],"type":"Point"}
}