{
  "type": "Feature",
  "properties": {
    "gn:admin1_code":"06",
    "gn:asciiname":"Estancia El Centrico",
    "gn:country_code":"BO",
    "gn:dem":267,
    "gn:feature_class":"P",
    "gn:feature_code":"PPL",
    "gn:name":"Estancia El Centrico",
    "gn:population":0,
    "gn:timezone":"America/La_Paz",
    "iso:country":"BO",
    "name:spa_x_preferred":[
        "Estancia El Centrico"
    ],
    "wof:name":"Estancia El Centrico",
    "wof:placetype":"locality"
},
  "geometry": {"coordinates":[-68.47309,-11.17352],"type":"Point"}
}