{
  "type": "Feature",
  "properties": {
    "iso:country":"BO",
    "qs:gn_pop":0,
    "qs:name":"Achacachi",
    "qs:name_adm0":"Bolivia",
    "qs:name_adm1":"La Paz",
    "qs:photos":2,
    "qs:photos_1k":1,
    "qs:photos_9k":2,
    "qs:photos_9r":5,
    "qs:photos_all":418,
    "qs:photos_sr":1,
    "qs:placetype":"LocalAdmin",
    "qs:pop_sr":"0",
    "qs:woe_adm0":23424762,
    "wof:name":"Achacachi",
    "wof:placetype":"localadmin"
},
  "geometry": {"coordinates":[-68.8459105,-16.214842],"type":"Point"}
}