{
  "type": "Feature",
  "properties": {
    "iso:country":"BO",
    "name:aym_x_preferred":[
        "Jach'ak'achi"
    ],
    "name:cat_x_preferred":[
        "Achacachi"
    ],
    "name:ceb_x_preferred":[
        "Achacachi"
    ],
    "name:deu_x_preferred":[
        "Achacachi"
    ],
    "name:eus_x_preferred":[
        "Achacachi"
    ],
    "name:fas_x_preferred":[
        "\u0627\u06a9\u0627\u0633\u0627\u0686\u06cc"
    ],
    "name:fra_x_preferred":[
        "Achacachi"
    ],
    "name:ita_x_preferred":[
        "Achacachi"
    ],
    "name:kor_x_preferred":[
        "\uc544\ucc28\uce74\uce58"
    ],
    "name:lit_x_preferred":[
        "A\u010daka\u010dis"
    ],
    "name:nor_x_preferred":[
        "Achacachi"
    ],
    "name:pol_x_preferred":[
        "Achacachi"
    ],
    "name:que_x_preferred":[
        "Jach'ak'achi"
    ],
    "name:sco_x_preferred":[
        "Achacachi"
    ],
    "name:spa_x_preferred":[
        "Achacachi"
    ],
    "name:swe_x_preferred":[
        "Achacachi"
    ],
    "name:war_x_preferred":[
        "Achacachi"
    ],
    "name:yid_x_preferred":[
        "\u05d0\u05d8\u05e9\u05d0\u05e7\u05d0\u05d8\u05e9\u05d9"
    ],
    "name:zho_x_preferred":[
        "\u963f\u67e5\u5361\u5947"
    ],
    "qs:gn_pop":0,
    "qs:name":"Achacachi",
    "qs:name_adm0":"Bolivia",
    "qs:name_adm1":"La Paz",
    "qs:photos":2,
    "qs:photos_1k":1,
    "qs:photos_9k":2,
    "qs:photos_9r":5,
    "qs:photos_all":418,
    "qs:photos_sr":1,
    "qs:placetype":"LocalAdmin",
    "qs:pop_sr":"0",
    "qs:woe_adm0":23424762,
    "wof:name":"Achacachi",
    "wof:placetype":"localadmin"
},
  "geometry": {"coordinates":[-68.8459105,-16.214842],"type":"Point"}
}