{
  "type": "Feature",
  "properties": {
    "gn:admin1_code":"04",
    "gn:asciiname":"Chojna Kala",
    "gn:country_code":"BO",
    "gn:dem":3943,
    "gn:feature_class":"P",
    "gn:feature_code":"PPL",
    "gn:name":"Choj\u00f1a Kala",
    "gn:population":0,
    "gn:timezone":"America/La_Paz",
    "iso:country":"BO",
    "name:spa_x_preferred":[
        "Choj\u00f1a Kala"
    ],
    "name:und_x_variant":[
        "Chojneacollo",
        "Choj\u00f1acollo"
    ],
    "wof:name":"Chojna Kala",
    "wof:placetype":"locality"
},
  "geometry": {"coordinates":[-68.63795,-15.95349],"type":"Point"}
}