{
  "type": "Feature",
  "properties": {
    "gn:admin1_code":"2.0",
    "gn:asciiname":"Pasorapa",
    "gn:country_code":"BO",
    "gn:dem":2108,
    "gn:feature_class":"P",
    "gn:feature_code":"PPL",
    "gn:name":"Pasorapa",
    "gn:population":0,
    "gn:timezone":"America/La_Paz",
    "iso:country":"BO",
    "name:ceb_x_preferred":[
        "Pasorapa"
    ],
    "name:deu_x_preferred":[
        "Pasorapa"
    ],
    "name:nor_x_preferred":[
        "Pasorapa"
    ],
    "name:que_x_preferred":[
        "Pasurapa"
    ],
    "name:spa_x_preferred":[
        "Pasorapa"
    ],
    "name:swe_x_preferred":[
        "Pasorapa"
    ],
    "wof:name":"Pasorapa",
    "wof:placetype":"locality"
},
  "geometry": {"coordinates":[-64.67664000000001,-18.32114],"type":"Point"}
}