{
  "type": "Feature",
  "properties": {
    "gn:admin1_code":"05",
    "gn:asciiname":"Chilaco",
    "gn:country_code":"BO",
    "gn:dem":3817,
    "gn:feature_class":"P",
    "gn:feature_code":"PPL",
    "gn:name":"Chilaco",
    "gn:population":0,
    "gn:timezone":"America/La_Paz",
    "iso:country":"BO",
    "name:und_x_variant":[
        "Estancia Chilalo",
        "Chilaco"
    ],
    "wof:name":"Chilaco",
    "wof:placetype":"locality"
},
  "geometry": {"coordinates":[-67.81496,-19.80481],"type":"Point"}
}