{
  "type": "Feature",
  "properties": {
    "gn:admin1_code":"08",
    "gn:asciiname":"Despedido",
    "gn:country_code":"BO",
    "gn:dem":215,
    "gn:feature_class":"P",
    "gn:feature_code":"PPL",
    "gn:name":"Despedido",
    "gn:population":0,
    "gn:timezone":"America/La_Paz",
    "iso:country":"BO",
    "wof:name":"Despedido",
    "wof:placetype":"locality"
},
  "geometry": {"coordinates":[-61.98333,-13.98333],"type":"Point"}
}