{
  "type": "Feature",
  "properties": {
    "gn:admin1_code":"8.0",
    "gn:asciiname":"Itacua",
    "gn:country_code":"BO",
    "gn:dem":896,
    "gn:feature_class":"P",
    "gn:feature_code":"PPL",
    "gn:name":"Itacua",
    "gn:population":0,
    "gn:timezone":"America/La_Paz",
    "iso:country":"BO",
    "wof:name":"Itacua",
    "wof:placetype":"locality"
},
  "geometry": {"coordinates":[-63.53373000000001,-19.91106],"type":"Point"}
}