{
  "type": "Feature",
  "properties": {
    "gn:admin1_code":"05",
    "gn:asciiname":"Condor",
    "gn:country_code":"BO",
    "gn:dem":4223,
    "gn:feature_class":"P",
    "gn:feature_code":"PPL",
    "gn:name":"Condor",
    "gn:population":0,
    "gn:timezone":"America/La_Paz",
    "iso:country":"BO",
    "name:ara_x_preferred":[
        "\u0643\u0646\u062f\u0648\u0631"
    ],
    "name:bpy_x_preferred":[
        "\u0995\u09cb\u09a8\u09a1\u09cb\u09b0\u09cd"
    ],
    "name:bre_x_preferred":[
        "Kondor"
    ],
    "name:deu_x_preferred":[
        "Kondor"
    ],
    "name:ell_x_preferred":[
        "\u039a\u03cc\u03bd\u03b4\u03bf\u03c1\u03b1\u03c2"
    ],
    "name:epo_x_preferred":[
        "Kondoroj"
    ],
    "name:fra_x_preferred":[
        "Condor"
    ],
    "name:fur_x_preferred":[
        "Cond\u00f4r"
    ],
    "name:gle_x_preferred":[
        "Condar"
    ],
    "name:ido_x_preferred":[
        "Kondoro"
    ],
    "name:ind_x_preferred":[
        "Kondor"
    ],
    "name:isl_x_preferred":[
        "Kond\u00f3r"
    ],
    "name:ita_x_preferred":[
        "Condor"
    ],
    "name:kor_x_preferred":[
        "\ucf58\ub3c4\ub974"
    ],
    "name:lit_x_preferred":[
        "Kondoras"
    ],
    "name:mkd_x_preferred":[
        "\u041a\u043e\u043d\u0434\u043e\u0440"
    ],
    "name:mrj_x_preferred":[
        "\u041a\u043e\u043d\u0434\u043e\u0440"
    ],
    "name:msa_x_preferred":[
        "Kondor"
    ],
    "name:mya_x_preferred":[
        "\u1000\u103d\u1014\u103a\u1038\u1012\u1031\u102b\u101c\u1004\u103a\u1038\u1010"
    ],
    "name:nor_x_preferred":[
        "Kondorer"
    ],
    "name:por_x_preferred":[
        "Condor"
    ],
    "name:ron_x_preferred":[
        "Condor"
    ],
    "name:sco_x_preferred":[
        "Condor"
    ],
    "name:srp_x_preferred":[
        "\u041a\u043e\u043d\u0434\u043e\u0440"
    ],
    "name:ukr_x_preferred":[
        "\u041a\u043e\u043d\u0434\u043e\u0440"
    ],
    "name:vie_x_preferred":[
        "Chim \u0111i\u00eau"
    ],
    "wof:name":"Condor",
    "wof:placetype":"locality"
},
  "geometry": {"coordinates":[-66.79793000000001,-18.46958],"type":"Point"}
}