{
  "type": "Feature",
  "properties": {
    "gn:admin1_code":"05",
    "gn:asciiname":"Condor",
    "gn:country_code":"BO",
    "gn:dem":4223,
    "gn:feature_class":"P",
    "gn:feature_code":"PPL",
    "gn:name":"Condor",
    "gn:population":0,
    "gn:timezone":"America/La_Paz",
    "iso:country":"BO",
    "wof:name":"Condor",
    "wof:placetype":"locality"
},
  "geometry": {"coordinates":[-66.79793000000001,-18.46958],"type":"Point"}
}