{
  "type": "Feature",
  "properties": {
    "gn:admin1_code":"07",
    "gn:asciiname":"Estancia Jayaquilla",
    "gn:country_code":"BO",
    "gn:dem":4502,
    "gn:feature_class":"P",
    "gn:feature_code":"PPL",
    "gn:name":"Estancia Jayaquilla",
    "gn:population":0,
    "gn:timezone":"America/La_Paz",
    "iso:country":"BO",
    "wof:name":"Estancia Jayaquilla",
    "wof:placetype":"locality"
},
  "geometry": {"coordinates":[-65.70491,-19.75195],"type":"Point"}
}