{
  "type": "Feature",
  "properties": {
    "gn:admin1_code":"8.0",
    "gn:asciiname":"Montu",
    "gn:cc2":"BO",
    "gn:country_code":"BO",
    "gn:dem":170,
    "gn:feature_class":"P",
    "gn:feature_code":"PPL",
    "gn:name":"Mont\u00fa",
    "gn:population":0,
    "gn:timezone":"America/La_Paz",
    "iso:country":"BO",
    "name:afr_x_preferred":[
        "Montoe"
    ],
    "name:ara_x_preferred":[
        "\u0645\u0646\u062a\u0648"
    ],
    "name:arz_x_preferred":[
        "\u0645\u0646\u062a\u0648"
    ],
    "name:aze_x_preferred":[
        "Montu"
    ],
    "name:cat_x_preferred":[
        "Menthu"
    ],
    "name:deu_x_preferred":[
        "Month"
    ],
    "name:ell_x_preferred":[
        "\u039c\u03bf\u03bd\u03c4\u03bf\u03cd"
    ],
    "name:epo_x_preferred":[
        "Montu"
    ],
    "name:est_x_preferred":[
        "Month"
    ],
    "name:eus_x_preferred":[
        "Montu"
    ],
    "name:fas_x_preferred":[
        "\u0645\u0648\u0646\u062a"
    ],
    "name:fin_x_preferred":[
        "Montu"
    ],
    "name:fra_x_preferred":[
        "Montou"
    ],
    "name:hrv_x_preferred":[
        "Menthu"
    ],
    "name:ind_x_preferred":[
        "Montu"
    ],
    "name:isl_x_preferred":[
        "Montj\u00fa"
    ],
    "name:ita_x_preferred":[
        "Montu"
    ],
    "name:jpn_x_preferred":[
        "\u30e2\u30f3\u30c1\u30e5"
    ],
    "name:lit_x_preferred":[
        "Montas"
    ],
    "name:mal_x_preferred":[
        "\u0d2e\u0d4b\u0d7a\u0d1f\u0d41"
    ],
    "name:nld_x_preferred":[
        "Mentoe"
    ],
    "name:nor_x_preferred":[
        "Montu"
    ],
    "name:oci_x_preferred":[
        "Monto"
    ],
    "name:pol_x_preferred":[
        "Montu"
    ],
    "name:por_x_preferred":[
        "Montu"
    ],
    "name:rus_x_preferred":[
        "\u041c\u043e\u043d\u0442\u0443"
    ],
    "name:slk_x_preferred":[
        "Moncu"
    ],
    "name:slv_x_preferred":[
        "Montu"
    ],
    "name:spa_x_preferred":[
        "Montu"
    ],
    "name:swe_x_preferred":[
        "Montu"
    ],
    "name:ukr_x_preferred":[
        "\u041c\u043e\u043d\u0442\u0443"
    ],
    "name:und_x_variant":[
        "Monc\u00fa",
        "Mont\u00fa"
    ],
    "name:urd_x_preferred":[
        "\u0645\u0648\u0646\u062a"
    ],
    "name:vie_x_preferred":[
        "Montu"
    ],
    "name:xmf_x_preferred":[
        "\u10db\u10dd\u10dc\u10e2\u10e3"
    ],
    "wof:name":"Montu",
    "wof:placetype":"locality"
},
  "geometry": {"coordinates":[-58.75,-17.76667],"type":"Point"}
}