{
  "type": "Feature",
  "properties": {
    "gn:admin1_code":"8.0",
    "gn:asciiname":"Montu",
    "gn:cc2":"BO",
    "gn:country_code":"BO",
    "gn:dem":170,
    "gn:feature_class":"P",
    "gn:feature_code":"PPL",
    "gn:name":"Mont\u00fa",
    "gn:population":0,
    "gn:timezone":"America/La_Paz",
    "iso:country":"BO",
    "name:und_x_variant":[
        "Monc\u00fa",
        "Mont\u00fa"
    ],
    "wof:name":"Montu",
    "wof:placetype":"locality"
},
  "geometry": {"coordinates":[-58.75,-17.76667],"type":"Point"}
}