{
  "type": "Feature",
  "properties": {
    "gn:admin1_code":"1.0",
    "gn:asciiname":"Terrado",
    "gn:country_code":"BO",
    "gn:dem":3370,
    "gn:feature_class":"P",
    "gn:feature_code":"PPL",
    "gn:name":"Terrado",
    "gn:population":0,
    "gn:timezone":"America/La_Paz",
    "iso:country":"BO",
    "wof:name":"Terrado",
    "wof:placetype":"locality"
},
  "geometry": {"coordinates":[-64.96666999999999,-20.36667000000001],"type":"Point"}
}