{
  "type": "Feature",
  "properties": {
    "gn:admin1_code":"1.0",
    "gn:asciiname":"Estancia Missca Pampa",
    "gn:country_code":"BO",
    "gn:dem":3270,
    "gn:feature_class":"P",
    "gn:feature_code":"PPL",
    "gn:name":"Estancia Missca Pampa",
    "gn:population":0,
    "gn:timezone":"America/La_Paz",
    "iso:country":"BO",
    "wof:name":"Estancia Missca Pampa",
    "wof:placetype":"locality"
},
  "geometry": {"coordinates":[-64.91996999999999,-20.95099],"type":"Point"}
}