{
  "type": "Feature",
  "properties": {
    "gn:admin1_code":"9.0",
    "gn:asciiname":"Porcelana",
    "gn:country_code":"BO",
    "gn:dem":395,
    "gn:feature_class":"P",
    "gn:feature_code":"PPL",
    "gn:name":"Porcelana",
    "gn:population":0,
    "gn:timezone":"America/La_Paz",
    "iso:country":"BO",
    "wof:name":"Porcelana",
    "wof:placetype":"locality"
},
  "geometry": {"coordinates":[-64.31667,-22.75],"type":"Point"}
}