{
  "type": "Feature",
  "properties": {
    "gn:admin1_code":"1.0",
    "gn:asciiname":"Tacuacua",
    "gn:cc2":"BO",
    "gn:country_code":"BO",
    "gn:dem":1191,
    "gn:feature_class":"P",
    "gn:feature_code":"PPL",
    "gn:name":"Tacuacua",
    "gn:population":0,
    "gn:timezone":"America/La_Paz",
    "iso:country":"BO",
    "name:und_x_variant":[
        "Tacacua",
        "Tacuacua"
    ],
    "wof:name":"Tacuacua",
    "wof:placetype":"locality"
},
  "geometry": {"coordinates":[-63.81667,-20.31667],"type":"Point"}
}