{
  "type": "Feature",
  "properties": {
    "gn:admin1_code":"2.0",
    "gn:asciiname":"Retamani",
    "gn:cc2":"BO",
    "gn:country_code":"BO",
    "gn:dem":3170,
    "gn:feature_class":"P",
    "gn:feature_code":"PPL",
    "gn:name":"Retamani",
    "gn:population":0,
    "gn:timezone":"America/La_Paz",
    "iso:country":"BO",
    "name:und_x_variant":[
        "Petamani",
        "Retamani"
    ],
    "wof:name":"Retamani",
    "wof:placetype":"locality"
},
  "geometry": {"coordinates":[-66.63333,-17.48333],"type":"Point"}
}