{
  "type": "Feature",
  "properties": {
    "gn:admin1_code":"2.0",
    "gn:asciiname":"Remanso",
    "gn:cc2":"BO",
    "gn:country_code":"BO",
    "gn:dem":205,
    "gn:feature_class":"P",
    "gn:feature_code":"PPL",
    "gn:name":"Remanso",
    "gn:population":0,
    "gn:timezone":"America/La_Paz",
    "iso:country":"BO",
    "name:und_x_variant":[
        "Remanzo",
        "Remanso"
    ],
    "wof:name":"Remanso",
    "wof:placetype":"locality"
},
  "geometry": {"coordinates":[-64.98333000000001,-16.55],"type":"Point"}
}