{
  "type": "Feature",
  "properties": {
    "gn:admin1_code":"1.0",
    "gn:asciiname":"Estancia Yuraj Cancha",
    "gn:country_code":"BO",
    "gn:dem":3106,
    "gn:feature_class":"P",
    "gn:feature_code":"PPL",
    "gn:name":"Estancia Yuraj Cancha",
    "gn:population":0,
    "gn:timezone":"America/La_Paz",
    "iso:country":"BO",
    "wof:name":"Estancia Yuraj Cancha",
    "wof:placetype":"locality"
},
  "geometry": {"coordinates":[-65.36863000000001,-20.39161],"type":"Point"}
}