{
  "type": "Feature",
  "properties": {
    "gn:admin1_code":"9.0",
    "gn:asciiname":"Estancia La Viguera",
    "gn:country_code":"BO",
    "gn:dem":2225,
    "gn:feature_class":"P",
    "gn:feature_code":"PPL",
    "gn:name":"Estancia La Viguera",
    "gn:population":0,
    "gn:timezone":"America/La_Paz",
    "iso:country":"BO",
    "wof:name":"Estancia La Viguera",
    "wof:placetype":"locality"
},
  "geometry": {"coordinates":[-65.1901,-20.97985],"type":"Point"}
}