{
  "type": "Feature",
  "properties": {
    "gn:admin1_code":"04",
    "gn:asciiname":"Cahuina",
    "gn:cc2":"BO",
    "gn:country_code":"BO",
    "gn:dem":4098,
    "gn:feature_class":"P",
    "gn:feature_code":"PPL",
    "gn:name":"Cahui\u00f1a",
    "gn:population":0,
    "gn:timezone":"America/La_Paz",
    "iso:country":"BO",
    "name:und_x_variant":[
        "Cohui\u00f1a",
        "Cahuma",
        "Cahui\u00f1a"
    ],
    "wof:name":"Cahuina",
    "wof:placetype":"locality"
},
  "geometry": {"coordinates":[-68.55,-16.38332999999999],"type":"Point"}
}