{
  "type": "Feature",
  "properties": {
    "gn:admin1_code":"4.0",
    "gn:asciiname":"Sacramento Bajo",
    "gn:cc2":"BO",
    "gn:country_code":"BO",
    "gn:dem":2132,
    "gn:feature_class":"P",
    "gn:feature_code":"PPL",
    "gn:name":"Sacramento Bajo",
    "gn:population":0,
    "gn:timezone":"America/La_Paz",
    "iso:country":"BO",
    "name:und_x_variant":[
        "Sacramento Chico",
        "Sacramento Bajo"
    ],
    "wof:name":"Sacramento Bajo",
    "wof:placetype":"locality"
},
  "geometry": {"coordinates":[-67.78333000000001,-16.23333],"type":"Point"}
}