{
  "type": "Feature",
  "properties": {
    "gn:admin1_code":"01",
    "gn:asciiname":"Estancia Agua Buena",
    "gn:country_code":"BO",
    "gn:dem":2931,
    "gn:feature_class":"P",
    "gn:feature_code":"PPL",
    "gn:name":"Estancia Agua Buena",
    "gn:population":0,
    "gn:timezone":"America/La_Paz",
    "iso:country":"BO",
    "wof:name":"Estancia Agua Buena",
    "wof:placetype":"locality"
},
  "geometry": {"coordinates":[-65.01402,-20.84923],"type":"Point"}
}