{
  "type": "Feature",
  "properties": {
    "gn:admin1_code":"4.0",
    "gn:asciiname":"Puerto Brais",
    "gn:cc2":"BO",
    "gn:country_code":"BO",
    "gn:dem":236,
    "gn:feature_class":"P",
    "gn:feature_code":"PPL",
    "gn:name":"Puerto Brais",
    "gn:population":0,
    "gn:timezone":"America/La_Paz",
    "iso:country":"BO",
    "name:und_x_variant":[
        "Puerto Braiso",
        "Puerto Brais"
    ],
    "wof:name":"Puerto Brais",
    "wof:placetype":"locality"
},
  "geometry": {"coordinates":[-67.59999999999999,-14.35],"type":"Point"}
}