{
  "type": "Feature",
  "properties": {
    "gn:admin1_code":"08",
    "gn:asciiname":"Comunidad Las Anguilas",
    "gn:country_code":"BO",
    "gn:dem":286,
    "gn:feature_class":"P",
    "gn:feature_code":"PPL",
    "gn:name":"Comunidad Las Anguilas",
    "gn:population":0,
    "gn:timezone":"America/La_Paz",
    "iso:country":"BO",
    "wof:name":"Comunidad Las Anguilas",
    "wof:placetype":"locality"
},
  "geometry": {"coordinates":[-62.65,-17.65],"type":"Point"}
}