{
  "type": "Feature",
  "properties": {
    "gn:admin1_code":"4.0",
    "gn:asciiname":"Estancia Wara Warani",
    "gn:country_code":"BO",
    "gn:dem":4105,
    "gn:feature_class":"P",
    "gn:feature_code":"PPL",
    "gn:name":"Estancia Wara Warani",
    "gn:population":0,
    "gn:timezone":"America/La_Paz",
    "iso:country":"BO",
    "wof:name":"Estancia Wara Warani",
    "wof:placetype":"locality"
},
  "geometry": {"coordinates":[-68.46666999999999,-17.11667000000001],"type":"Point"}
}