{
  "type": "Feature",
  "properties": {
    "iso:country":"BO",
    "name:ceb_x_preferred":[
        "Villa Tunari"
    ],
    "name:dan_x_preferred":[
        "Villa Tunari"
    ],
    "name:deu_x_preferred":[
        "Villa Tunari"
    ],
    "name:fra_x_preferred":[
        "Villa Tunari"
    ],
    "name:nld_x_preferred":[
        "Villa Tunari"
    ],
    "name:nor_x_preferred":[
        "Villa Tunari"
    ],
    "name:pol_x_preferred":[
        "Villa Tunari"
    ],
    "name:que_x_preferred":[
        "Tunari llaqta"
    ],
    "name:sco_x_preferred":[
        "Villa Tunari"
    ],
    "name:spa_x_preferred":[
        "Villa Tunari"
    ],
    "name:swe_x_preferred":[
        "Villa Tunari"
    ],
    "name:zho_x_preferred":[
        "\u5716\u7d0d\u91cc\u93ae"
    ],
    "qs:gn_country":"BO",
    "qs:gn_fcode":"PPL",
    "qs:gn_pop":0,
    "qs:name":"Villa Tunari",
    "qs:name_adm0":"Bolivia",
    "qs:name_adm1":"Cochabamba",
    "qs:photos":92,
    "qs:photos_1k":19,
    "qs:photos_9k":1,
    "qs:photos_9r":3,
    "qs:photos_all":92,
    "qs:photos_sr":3,
    "qs:placetype":"Town",
    "qs:pop_sr":"0",
    "qs:woe_adm0":23424762,
    "wd:wordcount":219,
    "wof:name":"Villa Tunari",
    "wof:placetype":"locality"
},
  "geometry": {"coordinates":[-65.42015000000001,-16.97307],"type":"Point"}
}