{
  "type": "Feature",
  "properties": {
    "gn:admin1_code":"06",
    "gn:asciiname":"Comunidad Avemanu",
    "gn:country_code":"BO",
    "gn:dem":259,
    "gn:feature_class":"P",
    "gn:feature_code":"PPL",
    "gn:name":"Comunidad Avemanu",
    "gn:population":0,
    "gn:timezone":"America/La_Paz",
    "iso:country":"BO",
    "name:spa_x_preferred":[
        "Comunidad Avemanu"
    ],
    "wof:name":"Comunidad Avemanu",
    "wof:placetype":"locality"
},
  "geometry": {"coordinates":[-68.81310000000001,-11.15589],"type":"Point"}
}