{
  "type": "Feature",
  "properties": {
    "gn:admin1_code":"4.0",
    "gn:asciiname":"Querarani",
    "gn:country_code":"BO",
    "gn:dem":3854,
    "gn:feature_class":"P",
    "gn:feature_code":"PPL",
    "gn:name":"Querarani",
    "gn:population":0,
    "gn:timezone":"America/La_Paz",
    "iso:country":"BO",
    "wof:name":"Querarani",
    "wof:placetype":"locality"
},
  "geometry": {"coordinates":[-69.06667,-16.98333],"type":"Point"}
}