{
  "type": "Feature",
  "properties": {
    "gn:admin1_code":"1.0",
    "gn:asciiname":"Meson",
    "gn:country_code":"BO",
    "gn:dem":1077,
    "gn:feature_class":"P",
    "gn:feature_code":"PPL",
    "gn:name":"Meson",
    "gn:population":0,
    "gn:timezone":"America/La_Paz",
    "iso:country":"BO",
    "wof:name":"Meson",
    "wof:placetype":"locality"
},
  "geometry": {"coordinates":[-63.97788000000001,-20.31178],"type":"Point"}
}