{
  "type": "Feature",
  "properties": {
    "gn:admin1_code":"3.0",
    "gn:asciiname":"Monte Cristo",
    "gn:country_code":"BO",
    "gn:dem":159,
    "gn:feature_class":"P",
    "gn:feature_code":"PPL",
    "gn:name":"Monte Cristo",
    "gn:population":0,
    "gn:timezone":"America/La_Paz",
    "iso:country":"BO",
    "name:ceb_x_preferred":[
        "Monte Cristo"
    ],
    "name:ces_x_preferred":[
        "Monte Cristo"
    ],
    "name:ita_x_preferred":[
        "Monte Cristo"
    ],
    "name:mkd_x_preferred":[
        "\u041c\u043e\u043d\u0442\u0435 \u041a\u0440\u0438\u0441\u0442\u043e"
    ],
    "name:nld_x_preferred":[
        "Monte Cristo"
    ],
    "name:nor_x_preferred":[
        "Monte Cristo"
    ],
    "name:pol_x_preferred":[
        "Monte Cristo"
    ],
    "name:rus_x_preferred":[
        "\u041c\u043e\u043d\u0442\u0435-\u041a\u0440\u0438\u0441\u0442\u043e"
    ],
    "name:swe_x_preferred":[
        "Monte Cristo"
    ],
    "name:vie_x_preferred":[
        "Monte Cristo"
    ],
    "wof:name":"Monte Cristo",
    "wof:placetype":"locality"
},
  "geometry": {"coordinates":[-66.48833,-13.97778],"type":"Point"}
}