{
  "type": "Feature",
  "properties": {
    "gn:admin1_code":"3.0",
    "gn:asciiname":"Monte Cristo",
    "gn:country_code":"BO",
    "gn:dem":159,
    "gn:feature_class":"P",
    "gn:feature_code":"PPL",
    "gn:name":"Monte Cristo",
    "gn:population":0,
    "gn:timezone":"America/La_Paz",
    "iso:country":"BO",
    "wof:name":"Monte Cristo",
    "wof:placetype":"locality"
},
  "geometry": {"coordinates":[-66.48833,-13.97778],"type":"Point"}
}