{
  "type": "Feature",
  "properties": {
    "gn:admin1_code":"9.0",
    "gn:asciiname":"Senoritas",
    "gn:country_code":"BO",
    "gn:dem":303,
    "gn:feature_class":"P",
    "gn:feature_code":"PPL",
    "gn:name":"Se\u00f1oritas",
    "gn:population":0,
    "gn:timezone":"America/La_Paz",
    "iso:country":"BO",
    "wof:name":"Senoritas",
    "wof:placetype":"locality"
},
  "geometry": {"coordinates":[-62.98333,-21.85],"type":"Point"}
}