{
  "type": "Feature",
  "properties": {
    "gn:admin1_code":"7.0",
    "gn:asciiname":"Pajcha",
    "gn:country_code":"BO",
    "gn:dem":3651,
    "gn:feature_class":"P",
    "gn:feature_code":"PPL",
    "gn:name":"Pajcha",
    "gn:population":0,
    "gn:timezone":"America/La_Paz",
    "iso:country":"BO",
    "name:und_x_variant":[
        "Estancia Pajcha Cullcu",
        "Pajcha"
    ],
    "wof:name":"Pajcha",
    "wof:placetype":"locality"
},
  "geometry": {"coordinates":[-66.21353000000001,-20.2421],"type":"Point"}
}