{
  "type": "Feature",
  "properties": {
    "gn:admin1_code":"7.0",
    "gn:asciiname":"Malcocotu",
    "gn:cc2":"BO",
    "gn:country_code":"BO",
    "gn:dem":4227,
    "gn:feature_class":"P",
    "gn:feature_code":"PPL",
    "gn:name":"Malcocotu",
    "gn:population":0,
    "gn:timezone":"America/La_Paz",
    "iso:country":"BO",
    "name:und_x_variant":[
        "Malcocota",
        "Malcocotu"
    ],
    "wof:name":"Malcocotu",
    "wof:placetype":"locality"
},
  "geometry": {"coordinates":[-66.21666999999999,-18.15],"type":"Point"}
}