{
  "type": "Feature",
  "properties": {
    "gn:admin1_code":"08",
    "gn:asciiname":"Campamento de los Pozos",
    "gn:cc2":"BO",
    "gn:country_code":"BO",
    "gn:dem":304,
    "gn:feature_class":"P",
    "gn:feature_code":"PPL",
    "gn:name":"Campamento de los Pozos",
    "gn:population":0,
    "gn:timezone":"America/La_Paz",
    "iso:country":"BO",
    "name:und_x_variant":[
        "Cerro de los Pozos",
        "Campamento de los Pozos"
    ],
    "wof:name":"Campamento de los Pozos",
    "wof:placetype":"locality"
},
  "geometry": {"coordinates":[-61.23333,-19.26667],"type":"Point"}
}