{
  "type": "Feature",
  "properties": {
    "gn:admin1_code":"9.0",
    "gn:asciiname":"Vayas",
    "gn:country_code":"BO",
    "gn:dem":282,
    "gn:feature_class":"P",
    "gn:feature_code":"PPL",
    "gn:name":"Vayas",
    "gn:population":0,
    "gn:timezone":"America/La_Paz",
    "iso:country":"BO",
    "name:spa_x_preferred":[
        "Vayas"
    ],
    "wof:name":"Vayas",
    "wof:placetype":"locality"
},
  "geometry": {"coordinates":[-62.67053000000001,-21.92717],"type":"Point"}
}