{
  "type": "Feature",
  "properties": {
    "gn:admin1_code":"7.0",
    "gn:asciiname":"Panari",
    "gn:country_code":"BO",
    "gn:dem":2935,
    "gn:feature_class":"P",
    "gn:feature_code":"PPL",
    "gn:name":"Panari",
    "gn:population":0,
    "gn:timezone":"America/La_Paz",
    "iso:country":"BO",
    "wof:name":"Panari",
    "wof:placetype":"locality"
},
  "geometry": {"coordinates":[-65.59999999999999,-20.85],"type":"Point"}
}