{
  "type": "Feature",
  "properties": {
    "gn:admin1_code":"7.0",
    "gn:asciiname":"Huantapita",
    "gn:country_code":"BO",
    "gn:dem":3225,
    "gn:feature_class":"P",
    "gn:feature_code":"PPL",
    "gn:name":"Huantapita",
    "gn:population":0,
    "gn:timezone":"America/La_Paz",
    "iso:country":"BO",
    "name:und_x_variant":[
        "Estancia Huantapita",
        "Huantapite",
        "Huantapila",
        "Huantapita"
    ],
    "wof:name":"Huantapita",
    "wof:placetype":"locality"
},
  "geometry": {"coordinates":[-65.38464999999999,-19.39668],"type":"Point"}
}