{
  "type": "Feature",
  "properties": {
    "gn:admin1_code":"07",
    "gn:asciiname":"Castillohuma",
    "gn:country_code":"BO",
    "gn:dem":3510,
    "gn:feature_class":"P",
    "gn:feature_code":"PPL",
    "gn:name":"Castillohuma",
    "gn:population":0,
    "gn:timezone":"America/La_Paz",
    "iso:country":"BO",
    "name:und_x_variant":[
        "Castillo Uma",
        "Castillohuma"
    ],
    "wof:name":"Castillohuma",
    "wof:placetype":"locality"
},
  "geometry": {"coordinates":[-66.11813000000001,-18.88677],"type":"Point"}
}