{
  "type": "Feature",
  "properties": {
    "gn:admin1_code":"7.0",
    "gn:asciiname":"Morocohorco",
    "gn:country_code":"BO",
    "gn:dem":4283,
    "gn:feature_class":"P",
    "gn:feature_code":"PPL",
    "gn:name":"Morocohorco",
    "gn:population":0,
    "gn:timezone":"America/La_Paz",
    "iso:country":"BO",
    "wof:name":"Morocohorco",
    "wof:placetype":"locality"
},
  "geometry": {"coordinates":[-66.27675000000001,-21.43586],"type":"Point"}
}