{
  "type": "Feature",
  "properties": {
    "gn:admin1_code":"1.0",
    "gn:asciiname":"Pampa Grande",
    "gn:country_code":"BO",
    "gn:dem":1817,
    "gn:feature_class":"P",
    "gn:feature_code":"PPL",
    "gn:name":"Pampa Grande",
    "gn:population":0,
    "gn:timezone":"America/La_Paz",
    "iso:country":"BO",
    "name:spa_x_preferred":[
        "Pampa Grande"
    ],
    "wof:name":"Pampa Grande",
    "wof:placetype":"locality"
},
  "geometry": {"coordinates":[-64.21162,-19.66311],"type":"Point"}
}