{
  "type": "Feature",
  "properties": {
    "gn:admin1_code":"05",
    "gn:asciiname":"Colcha",
    "gn:country_code":"BO",
    "gn:dem":3710,
    "gn:feature_class":"P",
    "gn:feature_code":"PPL",
    "gn:name":"Colcha",
    "gn:population":0,
    "gn:timezone":"America/La_Paz",
    "iso:country":"BO",
    "wof:name":"Colcha",
    "wof:placetype":"locality"
},
  "geometry": {"coordinates":[-67.53205,-19.19762],"type":"Point"}
}