{
  "type": "Feature",
  "properties": {
    "gn:admin1_code":"2.0",
    "gn:asciiname":"Mendoza",
    "gn:country_code":"BO",
    "gn:dem":1799,
    "gn:feature_class":"P",
    "gn:feature_code":"PPL",
    "gn:name":"Mendoza",
    "gn:population":0,
    "gn:timezone":"America/La_Paz",
    "iso:country":"BO",
    "wof:name":"Mendoza",
    "wof:placetype":"locality"
},
  "geometry": {"coordinates":[-65.86667,-16.95],"type":"Point"}
}