{
  "type": "Feature",
  "properties": {
    "gn:admin1_code":"9.0",
    "gn:asciiname":"Vertientes Sulfhidricas",
    "gn:cc2":"BO",
    "gn:country_code":"BO",
    "gn:dem":683,
    "gn:feature_class":"P",
    "gn:feature_code":"PPL",
    "gn:name":"Vertientes Sulfh\u00eddricas",
    "gn:population":0,
    "gn:timezone":"America/La_Paz",
    "iso:country":"BO",
    "name:und_x_variant":[
        "Vertientes Sulfidricas",
        "Vertientes Sulfh\u00eddricas"
    ],
    "wof:name":"Vertientes Sulfhidricas",
    "wof:placetype":"locality"
},
  "geometry": {"coordinates":[-64.51666999999999,-22.43333],"type":"Point"}
}