{
  "type": "Feature",
  "properties": {
    "gn:admin1_code":"1.0",
    "gn:asciiname":"Mazo Cruz",
    "gn:country_code":"BO",
    "gn:dem":2599,
    "gn:feature_class":"P",
    "gn:feature_code":"PPL",
    "gn:name":"Mazo Cruz",
    "gn:population":0,
    "gn:timezone":"America/La_Paz",
    "iso:country":"BO",
    "wof:name":"Mazo Cruz",
    "wof:placetype":"locality"
},
  "geometry": {"coordinates":[-65.21666999999999,-18.81667],"type":"Point"}
}