{
  "type": "Feature",
  "properties": {
    "gn:admin1_code":"7.0",
    "gn:asciiname":"Moraya",
    "gn:country_code":"BO",
    "gn:dem":3389,
    "gn:feature_class":"P",
    "gn:feature_code":"PPL",
    "gn:name":"Moraya",
    "gn:population":0,
    "gn:timezone":"America/La_Paz",
    "iso:country":"BO",
    "wof:name":"Moraya",
    "wof:placetype":"locality"
},
  "geometry": {"coordinates":[-65.54999000000001,-21.7503],"type":"Point"}
}