{
  "type": "Feature",
  "properties": {
    "gn:admin1_code":"01",
    "gn:asciiname":"Carapari",
    "gn:country_code":"BO",
    "gn:dem":1198,
    "gn:feature_class":"P",
    "gn:feature_code":"PPL",
    "gn:name":"Carapar\u00ed",
    "gn:population":0,
    "gn:timezone":"America/La_Paz",
    "iso:country":"BO",
    "wof:name":"Carapari",
    "wof:placetype":"locality"
},
  "geometry": {"coordinates":[-63.88333000000001,-19.43333],"type":"Point"}
}