{
  "type": "Feature",
  "properties": {
    "gn:admin1_code":"05",
    "gn:asciiname":"Estancia Nekheta",
    "gn:country_code":"BO",
    "gn:dem":3980,
    "gn:feature_class":"P",
    "gn:feature_code":"PPL",
    "gn:name":"Estancia Nekheta",
    "gn:population":0,
    "gn:timezone":"America/La_Paz",
    "iso:country":"BO",
    "wof:name":"Estancia Nekheta",
    "wof:placetype":"locality"
},
  "geometry": {"coordinates":[-68.62224999999999,-18.06769],"type":"Point"}
}