{
  "type": "Feature",
  "properties": {
    "gn:admin1_code":"3.0",
    "gn:asciiname":"La Estacion",
    "gn:country_code":"BO",
    "gn:dem":238,
    "gn:feature_class":"P",
    "gn:feature_code":"PPL",
    "gn:name":"La Estaci\u00f3n",
    "gn:population":0,
    "gn:timezone":"America/La_Paz",
    "iso:country":"BO",
    "wof:name":"La Estacion",
    "wof:placetype":"locality"
},
  "geometry": {"coordinates":[-66.95,-15.03333],"type":"Point"}
}