{
  "type": "Feature",
  "properties": {
    "gn:admin1_code":"5.0",
    "gn:asciiname":"Mallcu",
    "gn:country_code":"BO",
    "gn:dem":3719,
    "gn:feature_class":"P",
    "gn:feature_code":"PPL",
    "gn:name":"Mallcu",
    "gn:population":0,
    "gn:timezone":"America/La_Paz",
    "iso:country":"BO",
    "wof:name":"Mallcu",
    "wof:placetype":"locality"
},
  "geometry": {"coordinates":[-67.15000000000001,-19.28333],"type":"Point"}
}