{
  "type": "Feature",
  "properties": {
    "gn:admin1_code":"2.0",
    "gn:asciiname":"Guanuma",
    "gn:country_code":"BO",
    "gn:dem":3121,
    "gn:feature_class":"P",
    "gn:feature_code":"PPL",
    "gn:name":"Gua\u00f1uma",
    "gn:population":0,
    "gn:timezone":"America/La_Paz",
    "iso:country":"BO",
    "wof:name":"Guanuma",
    "wof:placetype":"locality"
},
  "geometry": {"coordinates":[-65.58333,-17.91667],"type":"Point"}
}