{
  "type": "Feature",
  "properties": {
    "gn:admin1_code":"03",
    "gn:asciiname":"Correnteza",
    "gn:cc2":"BO",
    "gn:country_code":"BO",
    "gn:dem":133,
    "gn:feature_class":"P",
    "gn:feature_code":"PPL",
    "gn:name":"Correnteza",
    "gn:population":0,
    "gn:timezone":"America/La_Paz",
    "iso:country":"BO",
    "name:und_x_variant":[
        "Correntezo",
        "Correnteza"
    ],
    "wof:name":"Correnteza",
    "wof:placetype":"locality"
},
  "geometry": {"coordinates":[-65.63333,-10.53333],"type":"Point"}
}