{
  "type": "Feature",
  "properties": {
    "gn:admin1_code":"4.0",
    "gn:asciiname":"Maimasi",
    "gn:country_code":"BO",
    "gn:dem":3888,
    "gn:feature_class":"P",
    "gn:feature_code":"PPL",
    "gn:name":"Maimasi",
    "gn:population":0,
    "gn:timezone":"America/La_Paz",
    "iso:country":"BO",
    "wof:name":"Maimasi",
    "wof:placetype":"locality"
},
  "geometry": {"coordinates":[-68.81667,-17.33333],"type":"Point"}
}