{
  "type": "Feature",
  "properties": {
    "gn:admin1_code":"04",
    "gn:asciiname":"Chichiaque",
    "gn:country_code":"BO",
    "gn:dem":2644,
    "gn:feature_class":"P",
    "gn:feature_code":"PPL",
    "gn:name":"Chichiaque",
    "gn:population":0,
    "gn:timezone":"America/La_Paz",
    "iso:country":"BO",
    "name:spa_x_preferred":[
        "Chichiaque"
    ],
    "wof:name":"Chichiaque",
    "wof:placetype":"locality"
},
  "geometry": {"coordinates":[-68.7289,-15.76909],"type":"Point"}
}