{
  "type": "Feature",
  "properties": {
    "gn:admin1_code":"5.0",
    "gn:asciiname":"Layaca",
    "gn:country_code":"BO",
    "gn:dem":3685,
    "gn:feature_class":"P",
    "gn:feature_code":"PPL",
    "gn:name":"Layaca",
    "gn:population":0,
    "gn:timezone":"America/La_Paz",
    "iso:country":"BO",
    "name:und_x_variant":[
        "Laguacsa",
        "Lavaxa",
        "Laguaosa",
        "Layaca"
    ],
    "wof:name":"Layaca",
    "wof:placetype":"locality"
},
  "geometry": {"coordinates":[-68.24925999999999,-19.71626],"type":"Point"}
}