{
  "type": "Feature",
  "properties": {
    "gn:admin1_code":"01",
    "gn:asciiname":"Chacarilla",
    "gn:country_code":"BO",
    "gn:dem":2496,
    "gn:feature_class":"P",
    "gn:feature_code":"PPL",
    "gn:name":"Chacarilla",
    "gn:population":0,
    "gn:timezone":"America/La_Paz",
    "iso:country":"BO",
    "wof:name":"Chacarilla",
    "wof:placetype":"locality"
},
  "geometry": {"coordinates":[-65.08333,-18.88333],"type":"Point"}
}