{
  "type": "Feature",
  "properties": {
    "gn:admin1_code":"2.0",
    "gn:asciiname":"Tucsapujio",
    "gn:cc2":"BO",
    "gn:country_code":"BO",
    "gn:dem":2743,
    "gn:feature_class":"P",
    "gn:feature_code":"PPL",
    "gn:name":"Tucsapujio",
    "gn:population":0,
    "gn:timezone":"America/La_Paz",
    "iso:country":"BO",
    "name:und_x_variant":[
        "Tuscapuito",
        "Tuscapuilo",
        "Tucsapujio"
    ],
    "wof:name":"Tucsapujio",
    "wof:placetype":"locality"
},
  "geometry": {"coordinates":[-66.03333000000001,-17.41667],"type":"Point"}
}