{
  "type": "Feature",
  "properties": {
    "gn:admin1_code":"8.0",
    "gn:asciiname":"Tacuma",
    "gn:cc2":"BO",
    "gn:country_code":"BO",
    "gn:dem":209,
    "gn:feature_class":"P",
    "gn:feature_code":"PPL",
    "gn:name":"Tacuma",
    "gn:population":0,
    "gn:timezone":"America/La_Paz",
    "iso:country":"BO",
    "name:und_x_variant":[
        "Tarum\u00e1",
        "Tacuma"
    ],
    "wof:name":"Tacuma",
    "wof:placetype":"locality"
},
  "geometry": {"coordinates":[-61.76667,-14.76667],"type":"Point"}
}