{
  "type": "Feature",
  "properties": {
    "gn:admin1_code":"05",
    "gn:asciiname":"Cerrillo",
    "gn:country_code":"BO",
    "gn:dem":3866,
    "gn:feature_class":"P",
    "gn:feature_code":"PPL",
    "gn:name":"Cerrillo",
    "gn:population":0,
    "gn:timezone":"America/La_Paz",
    "iso:country":"BO",
    "wof:name":"Cerrillo",
    "wof:placetype":"locality"
},
  "geometry": {"coordinates":[-67.26666999999999,-17.61667000000001],"type":"Point"}
}