{
  "type": "Feature",
  "properties": {
    "gn:admin1_code":"4.0",
    "gn:asciiname":"Guallatiri",
    "gn:cc2":"BO",
    "gn:country_code":"BO",
    "gn:dem":4096,
    "gn:feature_class":"P",
    "gn:feature_code":"PPL",
    "gn:name":"Guallatiri",
    "gn:population":0,
    "gn:timezone":"America/La_Paz",
    "iso:country":"BO",
    "name:und_x_variant":[
        "Estancia Huallatiri",
        "Guallatiri"
    ],
    "wof:name":"Guallatiri",
    "wof:placetype":"locality"
},
  "geometry": {"coordinates":[-68.84999999999999,-17.75],"type":"Point"}
}