{
  "type": "Feature",
  "properties": {
    "gn:admin1_code":"4.0",
    "gn:asciiname":"Guallatiri",
    "gn:cc2":"BO",
    "gn:country_code":"BO",
    "gn:dem":4096,
    "gn:feature_class":"P",
    "gn:feature_code":"PPL",
    "gn:name":"Guallatiri",
    "gn:population":0,
    "gn:timezone":"America/La_Paz",
    "iso:country":"BO",
    "name:ceb_x_preferred":[
        "Volc\u00e1n Guallatiri"
    ],
    "name:ces_x_preferred":[
        "Guallatiri"
    ],
    "name:dan_x_preferred":[
        "Guallatiri"
    ],
    "name:deu_x_preferred":[
        "Guallatiri"
    ],
    "name:fra_x_preferred":[
        "Guallatiri"
    ],
    "name:ita_x_preferred":[
        "Monte Guallatiri"
    ],
    "name:kat_x_preferred":[
        "\u10d2\u10e3\u10d0\u10da\u10d8\u10d0\u10e2\u10d8\u10e0\u10d8"
    ],
    "name:nld_x_preferred":[
        "Gualatiro"
    ],
    "name:nno_x_preferred":[
        "Guallatiri"
    ],
    "name:por_x_preferred":[
        "Guallatiri"
    ],
    "name:que_x_preferred":[
        "Wallatiri"
    ],
    "name:rus_x_preferred":[
        "\u0413\u0443\u0430\u043b\u044c\u044f\u0442\u0438\u0440\u0438"
    ],
    "name:slk_x_preferred":[
        "Guallatiri"
    ],
    "name:spa_x_preferred":[
        "Volc\u00e1n Guallatiri"
    ],
    "name:swe_x_preferred":[
        "Guallatiri"
    ],
    "name:ukr_x_preferred":[
        "\u0490\u0443\u0430\u044f\u0442\u0456\u0440\u0456"
    ],
    "name:und_x_variant":[
        "Estancia Huallatiri"
    ],
    "name:vie_x_preferred":[
        "Guallatiri"
    ],
    "name:zho_x_preferred":[
        "\u74dc\u4e9e\u8482\u91cc\u706b\u5c71"
    ],
    "wof:name":"Guallatiri",
    "wof:placetype":"locality"
},
  "geometry": {"coordinates":[-68.84999999999999,-17.75],"type":"Point"}
}