{
  "type": "Feature",
  "properties": {
    "gn:admin1_code":"01",
    "gn:asciiname":"Estancia Pila Pata",
    "gn:country_code":"BO",
    "gn:dem":3144,
    "gn:feature_class":"P",
    "gn:feature_code":"PPL",
    "gn:name":"Estancia Pila Pata",
    "gn:population":0,
    "gn:timezone":"America/La_Paz",
    "iso:country":"BO",
    "wof:name":"Estancia Pila Pata",
    "wof:placetype":"locality"
},
  "geometry": {"coordinates":[-65.12743,-19.23097000000001],"type":"Point"}
}