{
  "type": "Feature",
  "properties": {
    "gn:admin1_code":"5.0",
    "gn:asciiname":"Marcamarca",
    "gn:country_code":"BO",
    "gn:dem":4043,
    "gn:feature_class":"P",
    "gn:feature_code":"PPL",
    "gn:name":"Marcamarca",
    "gn:population":0,
    "gn:timezone":"America/La_Paz",
    "iso:country":"BO",
    "wof:name":"Marcamarca",
    "wof:placetype":"locality"
},
  "geometry": {"coordinates":[-68.26666999999999,-18.08333],"type":"Point"}
}