{
  "type": "Feature",
  "properties": {
    "gn:admin1_code":"6.0",
    "gn:asciiname":"Montevideo",
    "gn:country_code":"BO",
    "gn:dem":153,
    "gn:feature_class":"P",
    "gn:feature_code":"PPL",
    "gn:name":"Montevideo",
    "gn:population":0,
    "gn:timezone":"America/La_Paz",
    "iso:country":"BO",
    "wof:name":"Montevideo",
    "wof:placetype":"locality"
},
  "geometry": {"coordinates":[-65.95,-10.25],"type":"Point"}
}