{
  "type": "Feature",
  "properties": {
    "gn:admin1_code":"07",
    "gn:asciiname":"Cerro Negro",
    "gn:country_code":"BO",
    "gn:dem":3949,
    "gn:feature_class":"P",
    "gn:feature_code":"PPL",
    "gn:name":"Cerro Negro",
    "gn:population":0,
    "gn:timezone":"America/La_Paz",
    "iso:country":"BO",
    "name:ceb_x_preferred":[
        "Volc\u00e1n Cerro Negro"
    ],
    "name:deu_x_preferred":[
        "Cerro Negro"
    ],
    "name:fas_x_preferred":[
        "\u0633\u0631\u0648 \u0646\u06af\u0631\u0648"
    ],
    "name:fra_x_preferred":[
        "Cerro Negro"
    ],
    "name:heb_x_preferred":[
        "\u05e1\u05e8\u05d5 \u05e0\u05d2\u05e8\u05d5"
    ],
    "name:hrv_x_preferred":[
        "Cerro Negro"
    ],
    "name:kor_x_preferred":[
        "\uc138\ub85c\ub124\uadf8\ub85c\uc0b0"
    ],
    "name:lit_x_preferred":[
        "Sero Negras"
    ],
    "name:nld_x_preferred":[
        "Cerro Negro"
    ],
    "name:nor_x_preferred":[
        "Cerro Negro"
    ],
    "name:pms_x_preferred":[
        "Cerro Negro"
    ],
    "name:rus_x_preferred":[
        "\u0421\u0435\u0440\u0440\u043e-\u041d\u0435\u0433\u0440\u043e"
    ],
    "name:slk_x_preferred":[
        "Cerro Negro"
    ],
    "name:spa_x_preferred":[
        "Cerro Negro"
    ],
    "name:swe_x_preferred":[
        "Cerro Negro"
    ],
    "name:ukr_x_preferred":[
        "\u0421\u0435\u0440\u0440\u043e-\u041d\u0435\u0433\u0440\u043e"
    ],
    "name:zho_x_preferred":[
        "\u585e\u7f57\u5185\u683c\u7f57\u706b\u5c71"
    ],
    "wof:name":"Cerro Negro",
    "wof:placetype":"locality"
},
  "geometry": {"coordinates":[-65.91667,-21.06667],"type":"Point"}
}