{
  "type": "Feature",
  "properties": {
    "gn:admin1_code":"07",
    "gn:asciiname":"Ciamala",
    "gn:cc2":"BO",
    "gn:country_code":"BO",
    "gn:dem":4359,
    "gn:feature_class":"P",
    "gn:feature_code":"PPL",
    "gn:name":"Ciamala",
    "gn:population":0,
    "gn:timezone":"America/La_Paz",
    "iso:country":"BO",
    "name:und_x_variant":[
        "Ciamalla",
        "Ciamala"
    ],
    "wof:name":"Ciamala",
    "wof:placetype":"locality"
},
  "geometry": {"coordinates":[-68.41667,-19.96667],"type":"Point"}
}