{
  "type": "Feature",
  "properties": {
    "gn:admin1_code":"4.0",
    "gn:asciiname":"Hullabarranco",
    "gn:cc2":"BO",
    "gn:country_code":"BO",
    "gn:dem":2882,
    "gn:feature_class":"P",
    "gn:feature_code":"PPL",
    "gn:name":"Hullabarranco",
    "gn:population":0,
    "gn:timezone":"America/La_Paz",
    "iso:country":"BO",
    "name:und_x_variant":[
        "Barranco",
        "Hullabarranco"
    ],
    "wof:name":"Hullabarranco",
    "wof:placetype":"locality"
},
  "geometry": {"coordinates":[-67.38333,-16.76667],"type":"Point"}
}