{
  "type": "Feature",
  "properties": {
    "gn:admin1_code":"8.0",
    "gn:asciiname":"Uruguayito",
    "gn:cc2":"BO",
    "gn:country_code":"BO",
    "gn:dem":543,
    "gn:feature_class":"P",
    "gn:feature_code":"PPL",
    "gn:name":"Uruguayito",
    "gn:population":0,
    "gn:timezone":"America/La_Paz",
    "iso:country":"BO",
    "name:und_x_variant":[
        "Aruguayito",
        "Uruguaito",
        "Urugayto",
        "Uruguayito"
    ],
    "wof:name":"Uruguayito",
    "wof:placetype":"locality"
},
  "geometry": {"coordinates":[-62.05,-16.38332999999999],"type":"Point"}
}