{
  "type": "Feature",
  "properties": {
    "gn:admin1_code":"3.0",
    "gn:asciiname":"Trompillo",
    "gn:country_code":"BO",
    "gn:dem":159,
    "gn:feature_class":"P",
    "gn:feature_code":"PPL",
    "gn:name":"Trompillo",
    "gn:population":0,
    "gn:timezone":"America/La_Paz",
    "iso:country":"BO",
    "wof:name":"Trompillo",
    "wof:placetype":"locality"
},
  "geometry": {"coordinates":[-64.73333000000001,-14.81667],"type":"Point"}
}