{
  "type": "Feature",
  "properties": {
    "gn:country":"BO",
    "gn:fcode":"PPL",
    "gn:population":7,
    "iso:country":"BO",
    "qs_pg:aaroncc":"BO",
    "qs_pg:gn_country":"BO",
    "qs_pg:gn_fcode":"PPL",
    "qs_pg:gn_pop":7,
    "qs_pg:name":"Tarko Pampa",
    "qs_pg:photos_9r":0,
    "qs_pg:photos_sr":0,
    "qs_pg:pop_sr":1,
    "qs_pg:qs_pg_placetype":"locality",
    "wof:name":"Tarko Pampa",
    "wof:placetype":"locality",
    "wof:population":7
},
  "geometry": {"coordinates":[-65.05668,-17.80981],"type":"Point"}
}