{
  "type": "Feature",
  "properties": {
    "gn:admin1_code":"1.0",
    "gn:asciiname":"Estancia Puca Pampa",
    "gn:country_code":"BO",
    "gn:dem":2980,
    "gn:feature_class":"P",
    "gn:feature_code":"PPL",
    "gn:name":"Estancia Puca Pampa",
    "gn:population":0,
    "gn:timezone":"America/La_Paz",
    "iso:country":"BO",
    "wof:name":"Estancia Puca Pampa",
    "wof:placetype":"locality"
},
  "geometry": {"coordinates":[-65.01694999999999,-20.06276],"type":"Point"}
}