{
  "type": "Feature",
  "properties": {
    "gn:admin1_code":"4.0",
    "gn:asciiname":"Lacatia",
    "gn:country_code":"BO",
    "gn:dem":3944,
    "gn:feature_class":"P",
    "gn:feature_code":"PPL",
    "gn:name":"Lacatia",
    "gn:population":0,
    "gn:timezone":"America/La_Paz",
    "iso:country":"BO",
    "name:und_x_variant":[
        "Lacatea"
    ],
    "wof:name":"Lacatia",
    "wof:placetype":"locality"
},
  "geometry": {"coordinates":[-68.58913000000001,-15.76745],"type":"Point"}
}