{
  "type": "Feature",
  "properties": {
    "gn:admin1_code":"1.0",
    "gn:asciiname":"Estancia Vinto",
    "gn:country_code":"BO",
    "gn:dem":3676,
    "gn:feature_class":"P",
    "gn:feature_code":"PPL",
    "gn:name":"Estancia Vinto",
    "gn:population":0,
    "gn:timezone":"America/La_Paz",
    "iso:country":"BO",
    "wof:name":"Estancia Vinto",
    "wof:placetype":"locality"
},
  "geometry": {"coordinates":[-65.22274,-20.12505],"type":"Point"}
}