{
  "type": "Feature",
  "properties": {
    "gn:admin1_code":"06",
    "gn:asciiname":"Calaya",
    "gn:country_code":"BO",
    "gn:dem":185,
    "gn:feature_class":"P",
    "gn:feature_code":"PPL",
    "gn:name":"Calaya",
    "gn:population":0,
    "gn:timezone":"America/La_Paz",
    "iso:country":"BO",
    "name:spa_x_preferred":[
        "Calaya"
    ],
    "wof:name":"Calaya",
    "wof:placetype":"locality"
},
  "geometry": {"coordinates":[-67.62948,-10.83077],"type":"Point"}
}