{
  "type": "Feature",
  "properties": {
    "gn:admin1_code":"8.0",
    "gn:asciiname":"Yotau",
    "gn:country_code":"BO",
    "gn:dem":257,
    "gn:feature_class":"P",
    "gn:feature_code":"PPL",
    "gn:name":"Yota\u00fa",
    "gn:population":0,
    "gn:timezone":"America/La_Paz",
    "iso:country":"BO",
    "name:deu_x_preferred":[
        "Yota\u00fa"
    ],
    "name:und_x_variant":[
        "Yota\u00fa"
    ],
    "name:urd_x_preferred":[
        "\u06cc\u0648\u0679\u0648"
    ],
    "wof:name":"Yotau",
    "wof:placetype":"locality"
},
  "geometry": {"coordinates":[-63.05369,-16.09287999999999],"type":"Point"}
}