{
  "type": "Feature",
  "properties": {
    "gn:admin1_code":"8.0",
    "gn:asciiname":"Paunania",
    "gn:country_code":"BO",
    "gn:dem":397,
    "gn:feature_class":"P",
    "gn:feature_code":"PPL",
    "gn:name":"Paunania",
    "gn:population":0,
    "gn:timezone":"America/La_Paz",
    "iso:country":"BO",
    "wof:name":"Paunania",
    "wof:placetype":"locality"
},
  "geometry": {"coordinates":[-59.93333000000001,-18.65],"type":"Point"}
}