{
  "type": "Feature",
  "properties": {
    "gn:admin1_code":"7.0",
    "gn:asciiname":"Hornopunta",
    "gn:country_code":"BO",
    "gn:dem":4280,
    "gn:feature_class":"P",
    "gn:feature_code":"PPL",
    "gn:name":"Hornopunta",
    "gn:population":0,
    "gn:timezone":"America/La_Paz",
    "iso:country":"BO",
    "wof:name":"Hornopunta",
    "wof:placetype":"locality"
},
  "geometry": {"coordinates":[-66.31667,-21.11667000000001],"type":"Point"}
}