{
  "type": "Feature",
  "properties": {
    "gn:admin1_code":"06",
    "gn:asciiname":"Esperanza",
    "gn:country_code":"BO",
    "gn:dem":227,
    "gn:feature_class":"P",
    "gn:feature_code":"PPL",
    "gn:name":"Esperanza",
    "gn:population":0,
    "gn:timezone":"America/La_Paz",
    "iso:country":"BO",
    "name:spa_x_preferred":[
        "Esperanza"
    ],
    "wof:name":"Esperanza",
    "wof:placetype":"locality"
},
  "geometry": {"coordinates":[-68.16379999999999,-11.43013],"type":"Point"}
}