{
  "type": "Feature",
  "properties": {
    "gn:admin1_code":"03",
    "gn:asciiname":"Colonia Sebastiao",
    "gn:country_code":"BO",
    "gn:dem":153,
    "gn:feature_class":"P",
    "gn:feature_code":"PPL",
    "gn:name":"Col\u00f4nia Sebasti\u00e3o",
    "gn:population":0,
    "gn:timezone":"America/Porto_Velho",
    "iso:country":"BO",
    "wof:name":"Colonia Sebastiao",
    "wof:placetype":"locality"
},
  "geometry": {"coordinates":[-65.33333,-11.05],"type":"Point"}
}