{
  "type": "Feature",
  "properties": {
    "gn:admin1_code":"7.0",
    "gn:asciiname":"Iguembe",
    "gn:country_code":"BO",
    "gn:dem":3710,
    "gn:feature_class":"P",
    "gn:feature_code":"PPL",
    "gn:name":"Ig\u00fcembe",
    "gn:population":0,
    "gn:timezone":"America/La_Paz",
    "iso:country":"BO",
    "wof:name":"Iguembe",
    "wof:placetype":"locality"
},
  "geometry": {"coordinates":[-66.76666999999999,-20.56667],"type":"Point"}
}