{
  "type": "Feature",
  "properties": {
    "gn:admin1_code":"4.0",
    "gn:asciiname":"Pongo",
    "gn:country_code":"BO",
    "gn:dem":4652,
    "gn:feature_class":"P",
    "gn:feature_code":"PPL",
    "gn:name":"Pongo",
    "gn:population":0,
    "gn:timezone":"America/La_Paz",
    "iso:country":"BO",
    "name:ceb_x_preferred":[
        "Pongo"
    ],
    "name:deu_x_preferred":[
        "Pongo"
    ],
    "name:fra_x_preferred":[
        "Pongo"
    ],
    "name:ita_x_preferred":[
        "Pongo"
    ],
    "name:swe_x_preferred":[
        "Pongo"
    ],
    "wof:name":"Pongo",
    "wof:placetype":"locality"
},
  "geometry": {"coordinates":[-67.28333000000001,-17.05],"type":"Point"}
}