{
  "type": "Feature",
  "properties": {
    "gn:admin1_code":"4.0",
    "gn:asciiname":"Santa Cruz del Valle Ameno",
    "gn:cc2":"BO",
    "gn:country_code":"BO",
    "gn:dem":1965,
    "gn:feature_class":"P",
    "gn:feature_code":"PPL",
    "gn:name":"Santa Cruz del Valle Ameno",
    "gn:population":0,
    "gn:timezone":"America/La_Paz",
    "iso:country":"BO",
    "name:und_x_variant":[
        "Santa Cruz",
        "Santa Cruz del Valle Ameno"
    ],
    "wof:name":"Santa Cruz del Valle Ameno",
    "wof:placetype":"locality"
},
  "geometry": {"coordinates":[-68.59201999999999,-14.65181],"type":"Point"}
}