{
  "type": "Feature",
  "properties": {
    "gn:admin1_code":"7.0",
    "gn:asciiname":"Kumullani",
    "gn:cc2":"BO",
    "gn:country_code":"BO",
    "gn:dem":3768,
    "gn:feature_class":"P",
    "gn:feature_code":"PPL",
    "gn:name":"Kumullani",
    "gn:population":0,
    "gn:timezone":"America/La_Paz",
    "iso:country":"BO",
    "name:und_x_variant":[
        "Rancho Kumullani",
        "Kumullani"
    ],
    "wof:name":"Kumullani",
    "wof:placetype":"locality"
},
  "geometry": {"coordinates":[-66.56667,-20.41667],"type":"Point"}
}