{
  "type": "Feature",
  "properties": {
    "gn:admin1_code":"4.0",
    "gn:asciiname":"Laza",
    "gn:country_code":"BO",
    "gn:dem":1397,
    "gn:feature_class":"P",
    "gn:feature_code":"PPL",
    "gn:name":"Laza",
    "gn:population":0,
    "gn:timezone":"America/La_Paz",
    "iso:country":"BO",
    "name:aze_x_preferred":[
        "Laza"
    ],
    "name:ceb_x_preferred":[
        "Laza"
    ],
    "name:glg_x_preferred":[
        "Laza"
    ],
    "name:ita_x_preferred":[
        "Laza"
    ],
    "name:kat_x_preferred":[
        "\u10da\u10d0\u10d6\u10d0"
    ],
    "name:msa_x_preferred":[
        "Laza"
    ],
    "name:sco_x_preferred":[
        "Laza"
    ],
    "name:spa_x_preferred":[
        "Laza"
    ],
    "name:swe_x_preferred":[
        "Laza"
    ],
    "wof:name":"Laza",
    "wof:placetype":"locality"
},
  "geometry": {"coordinates":[-67.43333,-16.41667],"type":"Point"}
}