{
  "type": "Feature",
  "properties": {
    "gn:admin1_code":"1.0",
    "gn:asciiname":"Pacay",
    "gn:country_code":"BO",
    "gn:dem":1034,
    "gn:feature_class":"P",
    "gn:feature_code":"PPL",
    "gn:name":"Pacay",
    "gn:population":0,
    "gn:timezone":"America/La_Paz",
    "iso:country":"BO",
    "name:und_x_variant":[
        "Pacaya",
        "Pacay"
    ],
    "wof:name":"Pacay",
    "wof:placetype":"locality"
},
  "geometry": {"coordinates":[-64.4473,-20.4609],"type":"Point"}
}