{
  "type": "Feature",
  "properties": {
    "gn:admin1_code":"7.0",
    "gn:asciiname":"Pirhua Cienega",
    "gn:country_code":"BO",
    "gn:dem":4209,
    "gn:feature_class":"P",
    "gn:feature_code":"PPL",
    "gn:name":"Pirhua Cienega",
    "gn:population":0,
    "gn:timezone":"America/La_Paz",
    "iso:country":"BO",
    "wof:name":"Pirhua Cienega",
    "wof:placetype":"locality"
},
  "geometry": {"coordinates":[-67.3002,-21.93088],"type":"Point"}
}