{
  "type": "Feature",
  "properties": {
    "gn:admin1_code":"7.0",
    "gn:asciiname":"Lacha Cancha",
    "gn:country_code":"BO",
    "gn:dem":3005,
    "gn:feature_class":"P",
    "gn:feature_code":"PPL",
    "gn:name":"Lacha Cancha",
    "gn:population":0,
    "gn:timezone":"America/La_Paz",
    "iso:country":"BO",
    "wof:name":"Lacha Cancha",
    "wof:placetype":"locality"
},
  "geometry": {"coordinates":[-65.63333,-21.61667000000001],"type":"Point"}
}