{
  "type": "Feature",
  "properties": {
    "gn:admin1_code":"4.0",
    "gn:asciiname":"Huishuinchuni",
    "gn:country_code":"BO",
    "gn:dem":825,
    "gn:feature_class":"P",
    "gn:feature_code":"PPL",
    "gn:name":"Huishuinchuni",
    "gn:population":0,
    "gn:timezone":"America/La_Paz",
    "iso:country":"BO",
    "wof:name":"Huishuinchuni",
    "wof:placetype":"locality"
},
  "geometry": {"coordinates":[-68.03333000000001,-15.56667],"type":"Point"}
}