{
  "type": "Feature",
  "properties": {
    "gn:admin1_code":"3.0",
    "gn:asciiname":"Manchuria",
    "gn:cc2":"BO",
    "gn:country_code":"BO",
    "gn:dem":201,
    "gn:feature_class":"P",
    "gn:feature_code":"PPL",
    "gn:name":"Manchuria",
    "gn:population":0,
    "gn:timezone":"America/La_Paz",
    "iso:country":"BO",
    "name:und_x_variant":[
        "Machuria",
        "Manchuria"
    ],
    "wof:name":"Manchuria",
    "wof:placetype":"locality"
},
  "geometry": {"coordinates":[-62.23333,-13.71667],"type":"Point"}
}