{
  "type": "Feature",
  "properties": {
    "gn:admin1_code":"07",
    "gn:asciiname":"Cornaca",
    "gn:country_code":"BO",
    "gn:dem":3072,
    "gn:feature_class":"P",
    "gn:feature_code":"PPL",
    "gn:name":"Cornaca",
    "gn:population":0,
    "gn:timezone":"America/La_Paz",
    "iso:country":"BO",
    "wof:name":"Cornaca",
    "wof:placetype":"locality"
},
  "geometry": {"coordinates":[-65.57274,-21.0593],"type":"Point"}
}