{
  "type": "Feature",
  "properties": {
    "gn:admin1_code":"4.0",
    "gn:asciiname":"Julia",
    "gn:country_code":"BO",
    "gn:dem":3120,
    "gn:feature_class":"P",
    "gn:feature_code":"PPL",
    "gn:name":"Julia",
    "gn:population":0,
    "gn:timezone":"America/La_Paz",
    "iso:country":"BO",
    "name:deu_x_preferred":[
        "Julia"
    ],
    "name:est_x_preferred":[
        "Julia"
    ],
    "name:fin_x_preferred":[
        "Julia"
    ],
    "name:lat_x_preferred":[
        "Julia"
    ],
    "name:nld_x_preferred":[
        "Julia"
    ],
    "name:nor_x_preferred":[
        "Julia"
    ],
    "name:pol_x_preferred":[
        "Julia"
    ],
    "name:slv_x_preferred":[
        "Julia"
    ],
    "name:spa_x_preferred":[
        "Julia"
    ],
    "name:swe_x_preferred":[
        "Julia"
    ],
    "wof:name":"Julia",
    "wof:placetype":"locality"
},
  "geometry": {"coordinates":[-68.65000000000001,-15.56667],"type":"Point"}
}