{
  "type": "Feature",
  "properties": {
    "gn:admin1_code":"5.0",
    "gn:asciiname":"Mocsahuma",
    "gn:cc2":"BO",
    "gn:country_code":"BO",
    "gn:dem":3951,
    "gn:feature_class":"P",
    "gn:feature_code":"PPL",
    "gn:name":"Mocsahuma",
    "gn:population":0,
    "gn:timezone":"America/La_Paz",
    "iso:country":"BO",
    "name:und_x_variant":[
        "Mojsahuma",
        "Mocsahuma"
    ],
    "wof:name":"Mocsahuma",
    "wof:placetype":"locality"
},
  "geometry": {"coordinates":[-67.93333,-17.95],"type":"Point"}
}