{
  "type": "Feature",
  "properties": {
    "gn:admin1_code":"7.0",
    "gn:asciiname":"Lolopotrero",
    "gn:country_code":"BO",
    "gn:dem":3790,
    "gn:feature_class":"P",
    "gn:feature_code":"PPL",
    "gn:name":"Lolopotrero",
    "gn:population":0,
    "gn:timezone":"America/La_Paz",
    "iso:country":"BO",
    "wof:name":"Lolopotrero",
    "wof:placetype":"locality"
},
  "geometry": {"coordinates":[-66.03333000000001,-21.46667],"type":"Point"}
}