{
  "type": "Feature",
  "properties": {
    "iso:country":"BO",
    "qs:gn_pop":0,
    "qs:name":"Toro Toro",
    "qs:name_adm0":"Bolivia",
    "qs:name_adm1":"Potos\u00ed",
    "qs:photos":2,
    "qs:photos_1k":1,
    "qs:photos_9k":1,
    "qs:photos_9r":2,
    "qs:photos_all":40,
    "qs:photos_sr":1,
    "qs:placetype":"LocalAdmin",
    "qs:pop_sr":"0",
    "qs:woe_adm0":23424762,
    "wof:name":"Toro Toro",
    "wof:placetype":"localadmin"
},
  "geometry": {"coordinates":[-65.75866600000001,-18.137532],"type":"Point"}
}