{
  "type": "Feature",
  "properties": {
    "gn:admin1_code":"09",
    "gn:asciiname":"El Rancho",
    "gn:country_code":"BO",
    "gn:dem":1957,
    "gn:feature_class":"P",
    "gn:feature_code":"PPL",
    "gn:name":"El Rancho",
    "gn:population":0,
    "gn:timezone":"America/La_Paz",
    "iso:country":"BO",
    "wof:name":"El Rancho",
    "wof:placetype":"locality"
},
  "geometry": {"coordinates":[-64.75479,-21.4646],"type":"Point"}
}