{
  "type": "Feature",
  "properties": {
    "gn:admin1_code":"3.0",
    "gn:asciiname":"Juncal Alegre",
    "gn:country_code":"BO",
    "gn:dem":145,
    "gn:feature_class":"P",
    "gn:feature_code":"PPL",
    "gn:name":"Juncal Alegre",
    "gn:population":0,
    "gn:timezone":"America/La_Paz",
    "iso:country":"BO",
    "wof:name":"Juncal Alegre",
    "wof:placetype":"locality"
},
  "geometry": {"coordinates":[-65.65000000000001,-13.13333],"type":"Point"}
}