{
  "type": "Feature",
  "properties": {
    "gn:admin1_code":"06",
    "gn:asciiname":"Blanca Flor",
    "gn:country_code":"BO",
    "gn:dem":177,
    "gn:feature_class":"P",
    "gn:feature_code":"PPL",
    "gn:name":"Blanca Flor",
    "gn:population":0,
    "gn:timezone":"America/La_Paz",
    "iso:country":"BO",
    "wof:name":"Blanca Flor",
    "wof:placetype":"locality"
},
  "geometry": {"coordinates":[-66.93344999999999,-11.72409],"type":"Point"}
}