{
  "type": "Feature",
  "properties": {
    "gn:admin1_code":"05",
    "gn:asciiname":"Canguana",
    "gn:country_code":"BO",
    "gn:dem":3762,
    "gn:feature_class":"P",
    "gn:feature_code":"PPL",
    "gn:name":"Canguana",
    "gn:population":0,
    "gn:timezone":"America/La_Paz",
    "iso:country":"BO",
    "name:und_x_variant":[
        "Ganguana",
        "Cahuana",
        "Caguana",
        "Canguana",
        "Estancia Cahuana"
    ],
    "wof:name":"Canguana",
    "wof:placetype":"locality"
},
  "geometry": {"coordinates":[-68.50121,-19.0626],"type":"Point"}
}