{
  "type": "Feature",
  "properties": {
    "gn:admin1_code":"7.0",
    "gn:asciiname":"Huano Pujro",
    "gn:country_code":"BO",
    "gn:dem":4287,
    "gn:feature_class":"P",
    "gn:feature_code":"PPL",
    "gn:name":"Huano Pujro",
    "gn:population":0,
    "gn:timezone":"America/La_Paz",
    "iso:country":"BO",
    "wof:name":"Huano Pujro",
    "wof:placetype":"locality"
},
  "geometry": {"coordinates":[-66.37529000000001,-21.20297],"type":"Point"}
}