{
  "type": "Feature",
  "properties": {
    "gn:admin1_code":"8.0",
    "gn:asciiname":"Siringal",
    "gn:cc2":"BO",
    "gn:country_code":"BO",
    "gn:dem":1548,
    "gn:feature_class":"P",
    "gn:feature_code":"PPL",
    "gn:name":"Siringal",
    "gn:population":0,
    "gn:timezone":"America/La_Paz",
    "iso:country":"BO",
    "name:und_x_variant":[
        "Siringa",
        "Siringal"
    ],
    "wof:name":"Siringal",
    "wof:placetype":"locality"
},
  "geometry": {"coordinates":[-63.81667,-18.33333],"type":"Point"}
}