{
  "type": "Feature",
  "properties": {
    "gn:admin1_code":"04",
    "gn:asciiname":"Cojata",
    "gn:country_code":"BO",
    "gn:dem":3865,
    "gn:feature_class":"P",
    "gn:feature_code":"PPL",
    "gn:name":"Cojata",
    "gn:population":0,
    "gn:timezone":"America/La_Paz",
    "iso:country":"BO",
    "wof:name":"Cojata",
    "wof:placetype":"locality"
},
  "geometry": {"coordinates":[-68.81667,-15.93333],"type":"Point"}
}