{
  "type": "Feature",
  "properties": {
    "gn:admin1_code":"8.0",
    "gn:asciiname":"Tundy",
    "gn:country_code":"BO",
    "gn:dem":365,
    "gn:feature_class":"P",
    "gn:feature_code":"PPL",
    "gn:name":"Tundy",
    "gn:population":0,
    "gn:timezone":"America/La_Paz",
    "iso:country":"BO",
    "wof:name":"Tundy",
    "wof:placetype":"locality"
},
  "geometry": {"coordinates":[-62.98333,-17.88332999999999],"type":"Point"}
}