{
  "type": "Feature",
  "properties": {
    "gn:admin1_code":"07",
    "gn:asciiname":"Estancia Khara Llanta",
    "gn:country_code":"BO",
    "gn:dem":3300,
    "gn:feature_class":"P",
    "gn:feature_code":"PPL",
    "gn:name":"Estancia Khara Llanta",
    "gn:population":0,
    "gn:timezone":"America/La_Paz",
    "iso:country":"BO",
    "wof:name":"Estancia Khara Llanta",
    "wof:placetype":"locality"
},
  "geometry": {"coordinates":[-65.01174,-19.55389],"type":"Point"}
}