{
  "type": "Feature",
  "properties": {
    "gn:admin1_code":"04",
    "gn:asciiname":"Cancahuani",
    "gn:cc2":"BO",
    "gn:country_code":"BO",
    "gn:dem":4277,
    "gn:feature_class":"P",
    "gn:feature_code":"PPL",
    "gn:name":"Cancahuani",
    "gn:population":0,
    "gn:timezone":"America/La_Paz",
    "iso:country":"BO",
    "name:und_x_variant":[
        "Estancia Cancahuani",
        "Cancahuani"
    ],
    "wof:name":"Cancahuani",
    "wof:placetype":"locality"
},
  "geometry": {"coordinates":[-68.53333000000001,-16.78333],"type":"Point"}
}