{
  "type": "Feature",
  "properties": {
    "gn:admin1_code":"07",
    "gn:asciiname":"Cienegafalda",
    "gn:country_code":"BO",
    "gn:dem":4230,
    "gn:feature_class":"P",
    "gn:feature_code":"PPL",
    "gn:name":"Cienegafalda",
    "gn:population":0,
    "gn:timezone":"America/La_Paz",
    "iso:country":"BO",
    "wof:name":"Cienegafalda",
    "wof:placetype":"locality"
},
  "geometry": {"coordinates":[-66.33333,-21.15],"type":"Point"}
}