{
  "type": "Feature",
  "properties": {
    "gn:admin1_code":"2.0",
    "gn:asciiname":"Itirapampa",
    "gn:country_code":"BO",
    "gn:dem":555,
    "gn:feature_class":"P",
    "gn:feature_code":"PPL",
    "gn:name":"Itirapampa",
    "gn:population":0,
    "gn:timezone":"America/La_Paz",
    "iso:country":"BO",
    "wof:name":"Itirapampa",
    "wof:placetype":"locality"
},
  "geometry": {"coordinates":[-65.48333000000001,-17.05],"type":"Point"}
}