{
  "type": "Feature",
  "properties": {
    "gn:admin1_code":"6.0",
    "gn:asciiname":"Comunidad San Luis",
    "gn:country_code":"BO",
    "gn:dem":231,
    "gn:feature_class":"P",
    "gn:feature_code":"PPL",
    "gn:name":"Comunidad San Luis",
    "gn:population":0,
    "gn:timezone":"America/La_Paz",
    "iso:country":"BO",
    "name:spa_x_preferred":[
        "Comunidad San Luis"
    ],
    "name:und_x_variant":[
        "San Luis"
    ],
    "wof:name":"Comunidad San Luis",
    "wof:placetype":"locality"
},
  "geometry": {"coordinates":[-68.53364000000001,-11.18542],"type":"Point"}
}