{
  "type": "Feature",
  "properties": {
    "gn:admin1_code":"06",
    "gn:asciiname":"Agua Rica",
    "gn:country_code":"BO",
    "gn:dem":268,
    "gn:feature_class":"P",
    "gn:feature_code":"PPL",
    "gn:name":"Agua Rica",
    "gn:population":0,
    "gn:timezone":"America/La_Paz",
    "iso:country":"BO",
    "name:spa_x_preferred":[
        "Agua Rica"
    ],
    "wof:name":"Agua Rica",
    "wof:placetype":"locality"
},
  "geometry": {"coordinates":[-68.87059000000001,-11.05907],"type":"Point"}
}