{
  "type": "Feature",
  "properties": {
    "gn:admin1_code":"6.0",
    "gn:asciiname":"Inapari",
    "gn:country_code":"BO",
    "gn:dem":182,
    "gn:feature_class":"P",
    "gn:feature_code":"PPL",
    "gn:name":"I\u00f1apari",
    "gn:population":0,
    "gn:timezone":"America/La_Paz",
    "iso:country":"BO",
    "wof:name":"Inapari",
    "wof:placetype":"locality"
},
  "geometry": {"coordinates":[-67.83333,-10.68333],"type":"Point"}
}