{
  "type": "Feature",
  "properties": {
    "gn:admin1_code":"9.0",
    "gn:asciiname":"Rio Negro",
    "gn:country_code":"BO",
    "gn:dem":1396,
    "gn:feature_class":"P",
    "gn:feature_code":"PPL",
    "gn:name":"R\u00edo Negro",
    "gn:population":0,
    "gn:timezone":"America/La_Paz",
    "iso:country":"BO",
    "wof:name":"Rio Negro",
    "wof:placetype":"locality"
},
  "geometry": {"coordinates":[-64.67395999999999,-22.10261],"type":"Point"}
}