{
  "type": "Feature",
  "properties": {
    "gn:admin1_code":"3.0",
    "gn:asciiname":"Puquio",
    "gn:country_code":"BO",
    "gn:dem":158,
    "gn:feature_class":"P",
    "gn:feature_code":"PPL",
    "gn:name":"Puquio",
    "gn:population":0,
    "gn:timezone":"America/La_Paz",
    "iso:country":"BO",
    "wof:name":"Puquio",
    "wof:placetype":"locality"
},
  "geometry": {"coordinates":[-66.23333000000001,-13.98333],"type":"Point"}
}