{
  "type": "Feature",
  "properties": {
    "gn:admin1_code":"2.0",
    "gn:asciiname":"Puca Pita",
    "gn:cc2":"BO",
    "gn:country_code":"BO",
    "gn:dem":2321,
    "gn:feature_class":"P",
    "gn:feature_code":"PPL",
    "gn:name":"Puca Pita",
    "gn:population":0,
    "gn:timezone":"America/La_Paz",
    "iso:country":"BO",
    "name:und_x_variant":[
        "Estancia Pucapilla",
        "Pucapuca",
        "Puca Pita"
    ],
    "wof:name":"Puca Pita",
    "wof:placetype":"locality"
},
  "geometry": {"coordinates":[-65.25,-18.05],"type":"Point"}
}