{
  "type": "Feature",
  "properties": {
    "gn:admin1_code":"1.0",
    "gn:asciiname":"Tayasihua",
    "gn:country_code":"BO",
    "gn:dem":1161,
    "gn:feature_class":"P",
    "gn:feature_code":"PPL",
    "gn:name":"Tayasihua",
    "gn:population":0,
    "gn:timezone":"America/La_Paz",
    "iso:country":"BO",
    "wof:name":"Tayasihua",
    "wof:placetype":"locality"
},
  "geometry": {"coordinates":[-63.80396,-20.02362],"type":"Point"}
}