{
  "type": "Feature",
  "properties": {
    "gn:admin1_code":"06",
    "gn:asciiname":"San Jesus",
    "gn:country_code":"BO",
    "gn:dem":191,
    "gn:feature_class":"P",
    "gn:feature_code":"PPL",
    "gn:name":"San Jesus",
    "gn:population":0,
    "gn:timezone":"America/La_Paz",
    "iso:country":"BO",
    "name:spa_x_preferred":[
        "San Jesus"
    ],
    "wof:name":"San Jesus",
    "wof:placetype":"locality"
},
  "geometry": {"coordinates":[-67.83866,-11.12548],"type":"Point"}
}