{
  "type": "Feature",
  "properties": {
    "gn:admin1_code":"8.0",
    "gn:asciiname":"San Nicolas",
    "gn:country_code":"BO",
    "gn:dem":187,
    "gn:feature_class":"P",
    "gn:feature_code":"PPL",
    "gn:name":"San Nicol\u00e1s",
    "gn:population":0,
    "gn:timezone":"America/La_Paz",
    "iso:country":"BO",
    "wof:name":"San Nicolas",
    "wof:placetype":"locality"
},
  "geometry": {"coordinates":[-62.66667,-14.21667],"type":"Point"}
}