{
  "type": "Feature",
  "properties": {
    "gn:admin1_code":"7.0",
    "gn:asciiname":"Vizcachillas",
    "gn:cc2":"BO",
    "gn:country_code":"BO",
    "gn:dem":4701,
    "gn:feature_class":"P",
    "gn:feature_code":"PPL",
    "gn:name":"Vizcachillas",
    "gn:population":0,
    "gn:timezone":"America/La_Paz",
    "iso:country":"BO",
    "name:und_x_variant":[
        "Viscachillas",
        "Vizcachillas"
    ],
    "wof:name":"Vizcachillas",
    "wof:placetype":"locality"
},
  "geometry": {"coordinates":[-67.71666999999999,-21.48333],"type":"Point"}
}