{
  "type": "Feature",
  "properties": {
    "gn:admin1_code":"4.0",
    "gn:asciiname":"Unponte",
    "gn:cc2":"BO",
    "gn:country_code":"BO",
    "gn:dem":1204,
    "gn:feature_class":"P",
    "gn:feature_code":"PPL",
    "gn:name":"Unponte",
    "gn:population":0,
    "gn:timezone":"America/La_Paz",
    "iso:country":"BO",
    "name:und_x_variant":[
        "Uponte",
        "Unponte"
    ],
    "wof:name":"Unponte",
    "wof:placetype":"locality"
},
  "geometry": {"coordinates":[-67.76666999999999,-15.51667],"type":"Point"}
}