{
  "type": "Feature",
  "properties": {
    "gn:admin1_code":"1.0",
    "gn:asciiname":"Pentirenda",
    "gn:country_code":"BO",
    "gn:dem":1004,
    "gn:feature_class":"P",
    "gn:feature_code":"PPL",
    "gn:name":"Pentirenda",
    "gn:population":0,
    "gn:timezone":"America/La_Paz",
    "iso:country":"BO",
    "wof:name":"Pentirenda",
    "wof:placetype":"locality"
},
  "geometry": {"coordinates":[-63.75584,-20.63249],"type":"Point"}
}