{
  "type": "Feature",
  "properties": {
    "gn:admin1_code":"7.0",
    "gn:asciiname":"Isca Isca",
    "gn:country_code":"BO",
    "gn:dem":3930,
    "gn:feature_class":"P",
    "gn:feature_code":"PPL",
    "gn:name":"Isca Isca",
    "gn:population":0,
    "gn:timezone":"America/La_Paz",
    "iso:country":"BO",
    "wof:name":"Isca Isca",
    "wof:placetype":"locality"
},
  "geometry": {"coordinates":[-65.85384999999999,-21.18156],"type":"Point"}
}