{
  "type": "Feature",
  "properties": {
    "gn:admin1_code":"06",
    "gn:asciiname":"America",
    "gn:country_code":"BO",
    "gn:dem":170,
    "gn:feature_class":"P",
    "gn:feature_code":"PPL",
    "gn:name":"Am\u00e9rica",
    "gn:population":0,
    "gn:timezone":"America/La_Paz",
    "iso:country":"BO",
    "wof:name":"America",
    "wof:placetype":"locality"
},
  "geometry": {"coordinates":[-66.68333,-10.76667],"type":"Point"}
}