{
  "type": "Feature",
  "properties": {
    "gn:admin1_code":"6.0",
    "gn:asciiname":"Tabuary",
    "gn:cc2":"BO",
    "gn:country_code":"BO",
    "gn:dem":155,
    "gn:feature_class":"P",
    "gn:feature_code":"PPL",
    "gn:name":"Tabuary",
    "gn:population":0,
    "gn:timezone":"America/La_Paz",
    "iso:country":"BO",
    "name:und_x_variant":[
        "Tabuari",
        "Tahuary",
        "Tabuary"
    ],
    "wof:name":"Tabuary",
    "wof:placetype":"locality"
},
  "geometry": {"coordinates":[-66.15000000000001,-10.18333],"type":"Point"}
}