{
  "type": "Feature",
  "properties": {
    "gn:admin1_code":"8.0",
    "gn:asciiname":"Tacetimi",
    "gn:cc2":"BO",
    "gn:country_code":"BO",
    "gn:dem":958,
    "gn:feature_class":"P",
    "gn:feature_code":"PPL",
    "gn:name":"Tacetimi",
    "gn:population":0,
    "gn:timezone":"America/La_Paz",
    "iso:country":"BO",
    "name:und_x_variant":[
        "Taceti",
        "Tacetimi"
    ],
    "wof:name":"Tacetimi",
    "wof:placetype":"locality"
},
  "geometry": {"coordinates":[-63.66667,-20.03333],"type":"Point"}
}