{
  "type": "Feature",
  "properties": {
    "gn:gn_country":"BO",
    "gn:gn_fcode":"PPLX",
    "gn:gn_pop":0,
    "iso:country":"BO",
    "name:deu_x_preferred":[
        "Challapampa"
    ],
    "name:spa_x_preferred":[
        "Challapampa"
    ],
    "name:unk_x_variant":[
        "Challapampa"
    ],
    "qs_pg:aaroncc":"BO",
    "qs_pg:gn_country":"BO",
    "qs_pg:gn_fcode":"PPLX",
    "qs_pg:gn_pop":0,
    "qs_pg:name":"Challapampa",
    "qs_pg:name_adm0":"Bolivia",
    "qs_pg:name_adm1":"La Paz",
    "qs_pg:photos":1802,
    "qs_pg:photos_1k":365,
    "qs_pg:photos_9k":8,
    "qs_pg:photos_9r":9,
    "qs_pg:photos_all":1802,
    "qs_pg:photos_sr":14,
    "qs_pg:pop_sr":0,
    "qs_pg:qs_pg_placetype":"neighbourhood",
    "qs_pg:qs_pg_placetype_gp":"Suburb",
    "qs_pg:woe_adm0":23424762,
    "woe:adm0_id":23424762,
    "woe:name_adm0":"Bolivia",
    "woe:name_adm1":"La Paz",
    "woe:placetype":"Suburb",
    "wof:name":"Challapampa",
    "wof:placetype":"neighbourhood"
},
  "geometry": {"coordinates":[-68.15000000000001,-16.48333],"type":"Point"}
}