{
  "type": "Feature",
  "properties": {
    "gn:admin1_code":"4.0",
    "gn:asciiname":"Murumaya",
    "gn:cc2":"BO",
    "gn:country_code":"BO",
    "gn:dem":3886,
    "gn:feature_class":"P",
    "gn:feature_code":"PPL",
    "gn:name":"Murumaya",
    "gn:population":0,
    "gn:timezone":"America/La_Paz",
    "iso:country":"BO",
    "name:und_x_variant":[
        "Estancia Muru Amaya",
        "Murumaya"
    ],
    "wof:name":"Murumaya",
    "wof:placetype":"locality"
},
  "geometry": {"coordinates":[-68.88333,-17.51667],"type":"Point"}
}