{
  "type": "Feature",
  "properties": {
    "gn:admin1_code":"04",
    "gn:asciiname":"Chari",
    "gn:country_code":"BO",
    "gn:dem":4086,
    "gn:feature_class":"P",
    "gn:feature_code":"PPL",
    "gn:name":"Chari",
    "gn:population":0,
    "gn:timezone":"America/La_Paz",
    "iso:country":"BO",
    "name:ceb_x_preferred":[
        "Chari"
    ],
    "name:fin_x_preferred":[
        "Chari"
    ],
    "name:hin_x_preferred":[
        "\u091a\u0930\u0940"
    ],
    "name:ita_x_preferred":[
        "Chari"
    ],
    "name:spa_x_preferred":[
        "Chari"
    ],
    "name:spa_x_variant":[
        "Estancia Chari",
        "Comunidad Chari"
    ],
    "wof:name":"Chari",
    "wof:placetype":"locality"
},
  "geometry": {"coordinates":[-69.04299,-15.1719],"type":"Point"}
}