{
  "type": "Feature",
  "properties": {
    "gn:admin1_code":"06",
    "gn:asciiname":"El Seis",
    "gn:country_code":"BO",
    "gn:dem":234,
    "gn:feature_class":"P",
    "gn:feature_code":"PPL",
    "gn:name":"El Seis",
    "gn:population":0,
    "gn:timezone":"America/La_Paz",
    "iso:country":"BO",
    "name:spa_x_preferred":[
        "El Seis"
    ],
    "wof:name":"El Seis",
    "wof:placetype":"locality"
},
  "geometry": {"coordinates":[-68.30319,-11.72223],"type":"Point"}
}