{
  "type": "Feature",
  "properties": {
    "gn:admin1_code":"7.0",
    "gn:asciiname":"Mondragon",
    "gn:country_code":"BO",
    "gn:dem":3289,
    "gn:feature_class":"P",
    "gn:feature_code":"PPL",
    "gn:name":"Mondrag\u00f3n",
    "gn:population":0,
    "gn:timezone":"America/La_Paz",
    "iso:country":"BO",
    "name:und_x_variant":[
        "Modragon",
        "Mondrag\u00f3n"
    ],
    "wof:name":"Mondragon",
    "wof:placetype":"locality"
},
  "geometry": {"coordinates":[-65.78955999999999,-19.42664],"type":"Point"}
}