{
  "type": "Feature",
  "properties": {
    "gn:admin1_code":"01",
    "gn:asciiname":"Chaco",
    "gn:country_code":"BO",
    "gn:dem":3184,
    "gn:feature_class":"P",
    "gn:feature_code":"PPL",
    "gn:name":"Chaco",
    "gn:population":0,
    "gn:timezone":"America/La_Paz",
    "iso:country":"BO",
    "name:bre_x_preferred":[
        "Chaco"
    ],
    "name:cat_x_preferred":[
        "Chaco"
    ],
    "name:ceb_x_preferred":[
        "Chaco"
    ],
    "name:ces_x_preferred":[
        "Chaco"
    ],
    "name:cym_x_preferred":[
        "Chaco"
    ],
    "name:deu_x_preferred":[
        "Chaco"
    ],
    "name:epo_x_preferred":[
        "\u0108ako"
    ],
    "name:eus_x_preferred":[
        "Chaco"
    ],
    "name:fra_x_preferred":[
        "Chaco"
    ],
    "name:glg_x_preferred":[
        "Chaco"
    ],
    "name:heb_x_preferred":[
        "\u05e6'\u05d0\u05e7\u05d5"
    ],
    "name:ita_x_preferred":[
        "Chaco"
    ],
    "name:jpn_x_preferred":[
        "\u30c1\u30e3\u30b3"
    ],
    "name:lit_x_preferred":[
        "\u010cakas"
    ],
    "name:nld_x_preferred":[
        "Chaco"
    ],
    "name:por_x_preferred":[
        "Chaco"
    ],
    "name:rus_x_preferred":[
        "\u0427\u0430\u043a\u043e"
    ],
    "name:slk_x_preferred":[
        "Chaco"
    ],
    "name:spa_x_preferred":[
        "Chaco"
    ],
    "name:swe_x_preferred":[
        "Chaco"
    ],
    "name:ukr_x_preferred":[
        "\u0427\u0430\u043a\u043e"
    ],
    "wof:name":"Chaco",
    "wof:placetype":"locality"
},
  "geometry": {"coordinates":[-65.13333,-20.58333],"type":"Point"}
}