{
  "type": "Feature",
  "properties": {
    "gn:admin1_code":"01",
    "gn:asciiname":"Chaco",
    "gn:country_code":"BO",
    "gn:dem":3184,
    "gn:feature_class":"P",
    "gn:feature_code":"PPL",
    "gn:name":"Chaco",
    "gn:population":0,
    "gn:timezone":"America/La_Paz",
    "iso:country":"BO",
    "wof:name":"Chaco",
    "wof:placetype":"locality"
},
  "geometry": {"coordinates":[-65.13333,-20.58333],"type":"Point"}
}