{
  "type": "Feature",
  "properties": {
    "gn:admin1_code":"7.0",
    "gn:asciiname":"San Joaquin",
    "gn:country_code":"BO",
    "gn:dem":3211,
    "gn:feature_class":"P",
    "gn:feature_code":"PPL",
    "gn:name":"San Joaqu\u00edn",
    "gn:population":0,
    "gn:timezone":"America/La_Paz",
    "iso:country":"BO",
    "wof:name":"San Joaquin",
    "wof:placetype":"locality"
},
  "geometry": {"coordinates":[-65.85068000000001,-21.32104],"type":"Point"}
}