{
  "type": "Feature",
  "properties": {
    "gn:admin1_code":"8.0",
    "gn:asciiname":"Guarayitos",
    "gn:cc2":"BO",
    "gn:country_code":"BO",
    "gn:dem":272,
    "gn:feature_class":"P",
    "gn:feature_code":"PPL",
    "gn:name":"Guarayitos",
    "gn:population":0,
    "gn:timezone":"America/La_Paz",
    "iso:country":"BO",
    "name:und_x_variant":[
        "Guaraytos",
        "Guayaros",
        "Guarayitos"
    ],
    "wof:name":"Guarayitos",
    "wof:placetype":"locality"
},
  "geometry": {"coordinates":[-61.76667,-17.58333],"type":"Point"}
}