{
  "type": "Feature",
  "properties": {
    "gn:admin1_code":"4.0",
    "gn:asciiname":"Gritado",
    "gn:country_code":"BO",
    "gn:dem":1178,
    "gn:feature_class":"P",
    "gn:feature_code":"PPL",
    "gn:name":"Gritado",
    "gn:population":0,
    "gn:timezone":"America/La_Paz",
    "iso:country":"BO",
    "wof:name":"Gritado",
    "wof:placetype":"locality"
},
  "geometry": {"coordinates":[-68.09999999999999,-15.55],"type":"Point"}
}