{
  "type": "Feature",
  "properties": {
    "gn:admin1_code":"5.0",
    "gn:asciiname":"Jumuyo",
    "gn:country_code":"BO",
    "gn:dem":4071,
    "gn:feature_class":"P",
    "gn:feature_code":"PPL",
    "gn:name":"Jumuyo",
    "gn:population":0,
    "gn:timezone":"America/La_Paz",
    "iso:country":"BO",
    "wof:name":"Jumuyo",
    "wof:placetype":"locality"
},
  "geometry": {"coordinates":[-66.55803,-18.67887],"type":"Point"}
}