{
  "type": "Feature",
  "properties": {
    "gn:admin1_code":"06",
    "gn:asciiname":"Isla Independencia",
    "gn:country_code":"BO",
    "gn:dem":166,
    "gn:feature_class":"P",
    "gn:feature_code":"PPL",
    "gn:name":"Isla Independencia",
    "gn:population":0,
    "gn:timezone":"America/La_Paz",
    "iso:country":"BO",
    "name:spa_x_preferred":[
        "Isla Independencia"
    ],
    "wof:name":"Isla Independencia",
    "wof:placetype":"locality"
},
  "geometry": {"coordinates":[-67.56296999999999,-11.46671],"type":"Point"}
}