{
  "type": "Feature",
  "properties": {
    "gn:admin1_code":"07",
    "gn:asciiname":"Carayoc",
    "gn:country_code":"BO",
    "gn:dem":4043,
    "gn:feature_class":"P",
    "gn:feature_code":"PPL",
    "gn:name":"Carayoc",
    "gn:population":0,
    "gn:timezone":"America/La_Paz",
    "iso:country":"BO",
    "wof:name":"Carayoc",
    "wof:placetype":"locality"
},
  "geometry": {"coordinates":[-66.18333,-21.23333],"type":"Point"}
}