{
  "type": "Feature",
  "properties": {
    "gn:admin1_code":"08",
    "gn:asciiname":"El Pocito",
    "gn:cc2":"BO",
    "gn:country_code":"BO",
    "gn:dem":263,
    "gn:feature_class":"P",
    "gn:feature_code":"PPL",
    "gn:name":"El Pocito",
    "gn:population":0,
    "gn:timezone":"America/La_Paz",
    "iso:country":"BO",
    "name:und_x_variant":[
        "El Posito",
        "El Pocito"
    ],
    "wof:name":"El Pocito",
    "wof:placetype":"locality"
},
  "geometry": {"coordinates":[-62.53333000000001,-15.26667],"type":"Point"}
}