{
  "type": "Feature",
  "properties": {
    "gn:admin1_code":"4.0",
    "gn:asciiname":"Huincuri",
    "gn:country_code":"BO",
    "gn:dem":3866,
    "gn:feature_class":"P",
    "gn:feature_code":"PPL",
    "gn:name":"Huincuri",
    "gn:population":0,
    "gn:timezone":"America/La_Paz",
    "iso:country":"BO",
    "wof:name":"Huincuri",
    "wof:placetype":"locality"
},
  "geometry": {"coordinates":[-68.68333,-17.13332999999999],"type":"Point"}
}