{
  "type": "Feature",
  "properties": {
    "gn:admin1_code":"8.0",
    "gn:asciiname":"Guaracas",
    "gn:country_code":"BO",
    "gn:dem":879,
    "gn:feature_class":"P",
    "gn:feature_code":"PPL",
    "gn:name":"Guaracas",
    "gn:population":0,
    "gn:timezone":"America/La_Paz",
    "iso:country":"BO",
    "name:und_x_variant":[
        "Guaraca",
        "Guaracas"
    ],
    "wof:name":"Guaracas",
    "wof:placetype":"locality"
},
  "geometry": {"coordinates":[-63.67648000000001,-20.13971],"type":"Point"}
}