{
  "type": "Feature",
  "properties": {
    "gn:admin1_code":"9.0",
    "gn:asciiname":"Madrejon",
    "gn:country_code":"BO",
    "gn:dem":329,
    "gn:feature_class":"P",
    "gn:feature_code":"PPL",
    "gn:name":"Madrej\u00f3n",
    "gn:population":0,
    "gn:timezone":"America/La_Paz",
    "iso:country":"BO",
    "wof:name":"Madrejon",
    "wof:placetype":"locality"
},
  "geometry": {"coordinates":[-63.01667,-21.65],"type":"Point"}
}