{
  "type": "Feature",
  "properties": {
    "gn:admin1_code":"05",
    "gn:asciiname":"Estancia Conchamarca",
    "gn:country_code":"BO",
    "gn:dem":3675,
    "gn:feature_class":"P",
    "gn:feature_code":"PPL",
    "gn:name":"Estancia Conchamarca",
    "gn:population":0,
    "gn:timezone":"America/La_Paz",
    "iso:country":"BO",
    "wof:name":"Estancia Conchamarca",
    "wof:placetype":"locality"
},
  "geometry": {"coordinates":[-67.85906999999999,-19.04961],"type":"Point"}
}