{
  "type": "Feature",
  "properties": {
    "gn:admin1_code":"8.0",
    "gn:asciiname":"La Villa",
    "gn:country_code":"BO",
    "gn:dem":422,
    "gn:feature_class":"P",
    "gn:feature_code":"PPL",
    "gn:name":"La Villa",
    "gn:population":0,
    "gn:timezone":"America/La_Paz",
    "iso:country":"BO",
    "name:ceb_x_preferred":[
        "La Villa"
    ],
    "name:fra_x_preferred":[
        "La Villa"
    ],
    "name:ita_x_preferred":[
        "La Villa"
    ],
    "name:nld_x_preferred":[
        "La Villa"
    ],
    "name:srp_x_preferred":[
        "La Villa"
    ],
    "name:swe_x_preferred":[
        "La Villa"
    ],
    "wof:name":"La Villa",
    "wof:placetype":"locality"
},
  "geometry": {"coordinates":[-63.15,-17.83333],"type":"Point"}
}