{
  "type": "Feature",
  "properties": {
    "gn:admin1_code":"4.0",
    "gn:asciiname":"Quiabaya",
    "gn:cc2":"BO",
    "gn:country_code":"BO",
    "gn:dem":1843,
    "gn:feature_class":"P",
    "gn:feature_code":"PPL",
    "gn:name":"Quiabaya",
    "gn:population":0,
    "gn:timezone":"America/La_Paz",
    "iso:country":"BO",
    "name:und_x_variant":[
        "Quibaya",
        "Quiabaya"
    ],
    "wof:name":"Quiabaya",
    "wof:placetype":"locality"
},
  "geometry": {"coordinates":[-68.76666999999999,-15.61667],"type":"Point"}
}