{
  "type": "Feature",
  "properties": {
    "gn:admin1_code":"07",
    "gn:asciiname":"Charahuaico",
    "gn:cc2":"BO",
    "gn:country_code":"BO",
    "gn:dem":2906,
    "gn:feature_class":"P",
    "gn:feature_code":"PPL",
    "gn:name":"Charahuaico",
    "gn:population":0,
    "gn:timezone":"America/La_Paz",
    "iso:country":"BO",
    "name:und_x_variant":[
        "Charahuayto",
        "Charahuaico"
    ],
    "wof:name":"Charahuaico",
    "wof:placetype":"locality"
},
  "geometry": {"coordinates":[-66.06667,-18.16667],"type":"Point"}
}