{
  "type": "Feature",
  "properties": {
    "gn:admin1_code":"08",
    "gn:asciiname":"Alta Gracia",
    "gn:country_code":"BO",
    "gn:dem":673,
    "gn:feature_class":"P",
    "gn:feature_code":"PPL",
    "gn:name":"Alta Gracia",
    "gn:population":0,
    "gn:timezone":"America/La_Paz",
    "iso:country":"BO",
    "wof:name":"Alta Gracia",
    "wof:placetype":"locality"
},
  "geometry": {"coordinates":[-62.15,-16.16667],"type":"Point"}
}