{
  "type": "Feature",
  "properties": {
    "gn:admin1_code":"08",
    "gn:asciiname":"Alta Gracia",
    "gn:country_code":"BO",
    "gn:dem":673,
    "gn:feature_class":"P",
    "gn:feature_code":"PPL",
    "gn:name":"Alta Gracia",
    "gn:population":0,
    "gn:timezone":"America/La_Paz",
    "iso:country":"BO",
    "name:ara_x_preferred":[
        "\u0623\u0644\u062a\u0627 \u063a\u0631\u0627\u0633\u064a\u0627"
    ],
    "name:azb_x_preferred":[
        "\u0622\u0644\u062a\u0627 \u0642\u0631\u0627\u0633\u06cc\u0627"
    ],
    "name:bul_x_preferred":[
        "\u0410\u043b\u0442\u0430 \u0413\u0440\u0430\u0441\u0438\u044f"
    ],
    "name:cat_x_preferred":[
        "Alta Gracia"
    ],
    "name:ceb_x_preferred":[
        "Alta Gracia"
    ],
    "name:deu_x_preferred":[
        "Alta Gracia"
    ],
    "name:epo_x_preferred":[
        "Alta Gracia"
    ],
    "name:fas_x_preferred":[
        "\u0622\u0644\u062a\u0627 \u06af\u0631\u0627\u0633\u06cc\u0627"
    ],
    "name:fra_x_preferred":[
        "Alta Gracia"
    ],
    "name:ita_x_preferred":[
        "Alta Gracia"
    ],
    "name:lit_x_preferred":[
        "Alta Grasija"
    ],
    "name:msa_x_preferred":[
        "Alta Gracia"
    ],
    "name:nld_x_preferred":[
        "Alta Gracia"
    ],
    "name:pol_x_preferred":[
        "Alta Gracia"
    ],
    "name:por_x_preferred":[
        "Alta Gracia"
    ],
    "name:rus_x_preferred":[
        "\u0410\u043b\u044c\u0442\u0430-\u0413\u0440\u0430\u0441\u0438\u044f"
    ],
    "name:spa_x_preferred":[
        "Alta Gracia"
    ],
    "name:tur_x_preferred":[
        "Alta Gracia"
    ],
    "name:zho_x_preferred":[
        "\u4e0a\u683c\u62c9\u897f\u4e9e"
    ],
    "wof:name":"Alta Gracia",
    "wof:placetype":"locality"
},
  "geometry": {"coordinates":[-62.15,-16.16667],"type":"Point"}
}