{
  "type": "Feature",
  "properties": {
    "gn:admin1_code":"07",
    "gn:asciiname":"Chitacasa",
    "gn:country_code":"BO",
    "gn:dem":3076,
    "gn:feature_class":"P",
    "gn:feature_code":"PPL",
    "gn:name":"Chitacasa",
    "gn:population":0,
    "gn:timezone":"America/La_Paz",
    "iso:country":"BO",
    "wof:name":"Chitacasa",
    "wof:placetype":"locality"
},
  "geometry": {"coordinates":[-65.65000000000001,-20.98333],"type":"Point"}
}