{
  "type": "Feature",
  "properties": {
    "gn:admin1_code":"02",
    "gn:asciiname":"Caporaya",
    "gn:cc2":"BO",
    "gn:country_code":"BO",
    "gn:dem":2901,
    "gn:feature_class":"P",
    "gn:feature_code":"PPL",
    "gn:name":"Caporaya",
    "gn:population":0,
    "gn:timezone":"America/La_Paz",
    "iso:country":"BO",
    "name:und_x_variant":[
        "Coparaya",
        "Caporaya"
    ],
    "wof:name":"Caporaya",
    "wof:placetype":"locality"
},
  "geometry": {"coordinates":[-66.26666999999999,-17.51667],"type":"Point"}
}