{
  "type": "Feature",
  "properties": {
    "gn:admin1_code":"7.0",
    "gn:asciiname":"Estancia Mesa Mesa",
    "gn:country_code":"BO",
    "gn:dem":3209,
    "gn:feature_class":"P",
    "gn:feature_code":"PPL",
    "gn:name":"Estancia Mesa Mesa",
    "gn:population":0,
    "gn:timezone":"America/La_Paz",
    "iso:country":"BO",
    "wof:name":"Estancia Mesa Mesa",
    "wof:placetype":"locality"
},
  "geometry": {"coordinates":[-65.81294,-20.31953],"type":"Point"}
}