{
  "type": "Feature",
  "properties": {
    "gn:admin1_code":"01",
    "gn:asciiname":"Estancia Khasa",
    "gn:country_code":"BO",
    "gn:dem":3273,
    "gn:feature_class":"P",
    "gn:feature_code":"PPL",
    "gn:name":"Estancia Khasa",
    "gn:population":0,
    "gn:timezone":"America/La_Paz",
    "iso:country":"BO",
    "wof:name":"Estancia Khasa",
    "wof:placetype":"locality"
},
  "geometry": {"coordinates":[-65.14856999999999,-20.17322],"type":"Point"}
}