{
  "type": "Feature",
  "properties": {
    "gn:admin1_code":"02",
    "gn:asciiname":"Calaya",
    "gn:country_code":"BO",
    "gn:dem":3394,
    "gn:feature_class":"P",
    "gn:feature_code":"PPL",
    "gn:name":"Calaya",
    "gn:population":0,
    "gn:timezone":"America/La_Paz",
    "iso:country":"BO",
    "wof:name":"Calaya",
    "wof:placetype":"locality"
},
  "geometry": {"coordinates":[-66.78333000000001,-17.31667],"type":"Point"}
}