{
  "type": "Feature",
  "properties": {
    "gn:admin1_code":"5.0",
    "gn:asciiname":"Uro-Vinto",
    "gn:cc2":"BO",
    "gn:country_code":"BO",
    "gn:dem":3745,
    "gn:feature_class":"P",
    "gn:feature_code":"PPL",
    "gn:name":"Uro-Vinto",
    "gn:population":0,
    "gn:timezone":"America/La_Paz",
    "iso:country":"BO",
    "name:und_x_variant":[
        "Uru-Vinto",
        "Uro-Vinto"
    ],
    "wof:name":"Uro-Vinto",
    "wof:placetype":"locality"
},
  "geometry": {"coordinates":[-66.75,-18.76667],"type":"Point"}
}