{
  "type": "Feature",
  "properties": {
    "gn:admin1_code":"06",
    "gn:asciiname":"Limera",
    "gn:country_code":"BO",
    "gn:dem":161,
    "gn:feature_class":"P",
    "gn:feature_code":"PPL",
    "gn:name":"Limera",
    "gn:population":0,
    "gn:timezone":"America/La_Paz",
    "iso:country":"BO",
    "name:spa_x_preferred":[
        "Limera"
    ],
    "wof:name":"Limera",
    "wof:placetype":"locality"
},
  "geometry": {"coordinates":[-67.78981999999999,-10.74166],"type":"Point"}
}