{
  "type": "Feature",
  "properties": {
    "gn:admin1_code":"7.0",
    "gn:asciiname":"Jacha Cruz",
    "gn:country_code":"BO",
    "gn:dem":2490,
    "gn:feature_class":"P",
    "gn:feature_code":"PPL",
    "gn:name":"Jacha Cruz",
    "gn:population":0,
    "gn:timezone":"America/La_Paz",
    "iso:country":"BO",
    "name:und_x_variant":[
        "Hacha Cruz",
        "Jacha Cruz"
    ],
    "wof:name":"Jacha Cruz",
    "wof:placetype":"locality"
},
  "geometry": {"coordinates":[-65.26365,-21.63167],"type":"Point"}
}