{
  "type": "Feature",
  "properties": {
    "gn:admin1_code":"04",
    "gn:asciiname":"Estancia Espiritu Willkhi",
    "gn:country_code":"BO",
    "gn:dem":3753,
    "gn:feature_class":"P",
    "gn:feature_code":"PPL",
    "gn:name":"Estancia Espiritu Willkhi",
    "gn:population":0,
    "gn:timezone":"America/La_Paz",
    "iso:country":"BO",
    "wof:name":"Estancia Espiritu Willkhi",
    "wof:placetype":"locality"
},
  "geometry": {"coordinates":[-67.91667,-17.41667],"type":"Point"}
}