{
  "type": "Feature",
  "properties": {
    "gn:admin1_code":"07",
    "gn:asciiname":"Bella Vista",
    "gn:country_code":"BO",
    "gn:dem":3830,
    "gn:feature_class":"P",
    "gn:feature_code":"PPL",
    "gn:name":"Bella Vista",
    "gn:population":0,
    "gn:timezone":"America/La_Paz",
    "iso:country":"BO",
    "name:cat_x_preferred":[
        "Bella Vista"
    ],
    "name:ceb_x_preferred":[
        "Bella Vista"
    ],
    "name:deu_x_preferred":[
        "Bella Vista"
    ],
    "name:ita_x_preferred":[
        "Bella Vista"
    ],
    "name:lit_x_preferred":[
        "Belja Vista"
    ],
    "name:nds_x_preferred":[
        "Bella Vista"
    ],
    "name:nld_x_preferred":[
        "Bella Vista"
    ],
    "name:pol_x_preferred":[
        "Bella Vista"
    ],
    "name:por_x_preferred":[
        "Bella Vista"
    ],
    "name:rus_x_preferred":[
        "\u0411\u0435\u043b\u044c\u044f-\u0412\u0438\u0441\u0442\u0430"
    ],
    "name:sco_x_preferred":[
        "Bella Vista"
    ],
    "name:slk_x_preferred":[
        "Bella Vista"
    ],
    "name:spa_x_preferred":[
        "Bella Vista"
    ],
    "name:srp_x_preferred":[
        "\u0411\u0435\u043b\u0430 \u0412\u0438\u0441\u0442\u0430"
    ],
    "name:swe_x_preferred":[
        "Bella Vista"
    ],
    "name:ukr_x_preferred":[
        "\u0411\u0435\u043b\u043b\u0430-\u0412\u0456\u0441\u0442\u0430"
    ],
    "name:und_x_variant":[
        "Buena Vista"
    ],
    "name:vol_x_preferred":[
        "Bella Vista"
    ],
    "wof:name":"Bella Vista",
    "wof:placetype":"locality"
},
  "geometry": {"coordinates":[-68.55031,-19.79884],"type":"Point"}
}