{
  "type": "Feature",
  "properties": {
    "gn:admin1_code":"5.0",
    "gn:asciiname":"Huacalli",
    "gn:country_code":"BO",
    "gn:dem":3742,
    "gn:feature_class":"P",
    "gn:feature_code":"PPL",
    "gn:name":"Huacalli",
    "gn:population":0,
    "gn:timezone":"America/La_Paz",
    "iso:country":"BO",
    "name:und_x_variant":[
        "Hucalli",
        "Huacalli"
    ],
    "wof:name":"Huacalli",
    "wof:placetype":"locality"
},
  "geometry": {"coordinates":[-67.64111,-18.44044],"type":"Point"}
}