{
  "type": "Feature",
  "properties": {
    "gn:admin1_code":"06",
    "gn:asciiname":"Bella Vista",
    "gn:country_code":"BO",
    "gn:dem":209,
    "gn:feature_class":"P",
    "gn:feature_code":"PPL",
    "gn:name":"Bella Vista",
    "gn:population":0,
    "gn:timezone":"America/La_Paz",
    "iso:country":"BO",
    "name:spa_x_preferred":[
        "Puesto Bella Vista"
    ],
    "wof:name":"Bella Vista",
    "wof:placetype":"locality"
},
  "geometry": {"coordinates":[-68.30093000000001,-11.23407],"type":"Point"}
}