{
  "type": "Feature",
  "properties": {
    "gn:admin1_code":"08",
    "gn:asciiname":"El Bicito",
    "gn:country_code":"BO",
    "gn:dem":374,
    "gn:feature_class":"P",
    "gn:feature_code":"PPL",
    "gn:name":"El Bicito",
    "gn:population":0,
    "gn:timezone":"America/La_Paz",
    "iso:country":"BO",
    "wof:name":"El Bicito",
    "wof:placetype":"locality"
},
  "geometry": {"coordinates":[-63.01667,-17.78333],"type":"Point"}
}