{
  "type": "Feature",
  "properties": {
    "gn:admin1_code":"06",
    "gn:asciiname":"Floresta",
    "gn:country_code":"BO",
    "gn:dem":141,
    "gn:feature_class":"P",
    "gn:feature_code":"PPL",
    "gn:name":"Floresta",
    "gn:population":0,
    "gn:timezone":"America/La_Paz",
    "iso:country":"BO",
    "name:spa_x_preferred":[
        "Floresta"
    ],
    "wof:name":"Floresta",
    "wof:placetype":"locality"
},
  "geometry": {"coordinates":[-67.65087,-10.70453],"type":"Point"}
}