{
  "type": "Feature",
  "properties": {
    "gn:admin1_code":"7.0",
    "gn:asciiname":"Estancia Towe",
    "gn:country_code":"BO",
    "gn:dem":3809,
    "gn:feature_class":"P",
    "gn:feature_code":"PPL",
    "gn:name":"Estancia Towe",
    "gn:population":0,
    "gn:timezone":"America/La_Paz",
    "iso:country":"BO",
    "wof:name":"Estancia Towe",
    "wof:placetype":"locality"
},
  "geometry": {"coordinates":[-68.43289,-20.50865],"type":"Point"}
}