{
  "type": "Feature",
  "properties": {
    "gn:admin1_code":"08",
    "gn:asciiname":"Asuncion",
    "gn:country_code":"BO",
    "gn:dem":419,
    "gn:feature_class":"P",
    "gn:feature_code":"PPL",
    "gn:name":"Asunci\u00f3n",
    "gn:population":0,
    "gn:timezone":"America/La_Paz",
    "iso:country":"BO",
    "wof:name":"Asuncion",
    "wof:placetype":"locality"
},
  "geometry": {"coordinates":[-60.16667,-17.85],"type":"Point"}
}