{
  "type": "Feature",
  "properties": {
    "gn:admin1_code":"4.0",
    "gn:asciiname":"Sorojaya",
    "gn:country_code":"BO",
    "gn:dem":4084,
    "gn:feature_class":"P",
    "gn:feature_code":"PPL",
    "gn:name":"Sorojaya",
    "gn:population":0,
    "gn:timezone":"America/La_Paz",
    "iso:country":"BO",
    "wof:name":"Sorojaya",
    "wof:placetype":"locality"
},
  "geometry": {"coordinates":[-68.76666999999999,-15.85],"type":"Point"}
}