{
  "type": "Feature",
  "properties": {
    "gn:admin1_code":"4.0",
    "gn:asciiname":"Kalachaca",
    "gn:cc2":"BO",
    "gn:country_code":"BO",
    "gn:dem":3834,
    "gn:feature_class":"P",
    "gn:feature_code":"PPL",
    "gn:name":"Kalachaca",
    "gn:population":0,
    "gn:timezone":"America/La_Paz",
    "iso:country":"BO",
    "name:und_x_variant":[
        "Calachaca",
        "Kalachaca"
    ],
    "wof:name":"Kalachaca",
    "wof:placetype":"locality"
},
  "geometry": {"coordinates":[-68.55,-16.41667],"type":"Point"}
}