{
  "type": "Feature",
  "properties": {
    "gn:admin1_code":"2.0",
    "gn:asciiname":"Tuigal",
    "gn:cc2":"BO",
    "gn:country_code":"BO",
    "gn:dem":2053,
    "gn:feature_class":"P",
    "gn:feature_code":"PPL",
    "gn:name":"Tuigal",
    "gn:population":0,
    "gn:timezone":"America/La_Paz",
    "iso:country":"BO",
    "name:und_x_variant":[
        "Trigal",
        "Tuigal"
    ],
    "wof:name":"Tuigal",
    "wof:placetype":"locality"
},
  "geometry": {"coordinates":[-64.84999999999999,-17.95],"type":"Point"}
}