{
  "type": "Feature",
  "properties": {
    "gn:admin1_code":"4.0",
    "gn:asciiname":"Pallacollo",
    "gn:country_code":"BO",
    "gn:dem":4258,
    "gn:feature_class":"P",
    "gn:feature_code":"PPL",
    "gn:name":"Pallacollo",
    "gn:population":0,
    "gn:timezone":"America/La_Paz",
    "iso:country":"BO",
    "wof:name":"Pallacollo",
    "wof:placetype":"locality"
},
  "geometry": {"coordinates":[-69.31667,-17.11667000000001],"type":"Point"}
}