{
  "type": "Feature",
  "properties": {
    "gn:admin1_code":"07",
    "gn:asciiname":"Chantani",
    "gn:country_code":"BO",
    "gn:dem":3678,
    "gn:feature_class":"P",
    "gn:feature_code":"PPL",
    "gn:name":"Chantani",
    "gn:population":0,
    "gn:timezone":"America/La_Paz",
    "iso:country":"BO",
    "name:und_x_variant":[
        "Estancia Chantani",
        "Chantani"
    ],
    "wof:name":"Chantani",
    "wof:placetype":"locality"
},
  "geometry": {"coordinates":[-67.65836999999999,-19.90219],"type":"Point"}
}