{
  "type": "Feature",
  "properties": {
    "gn:admin1_code":"04",
    "gn:asciiname":"Chacoma",
    "gn:country_code":"BO",
    "gn:dem":4188,
    "gn:feature_class":"P",
    "gn:feature_code":"PPL",
    "gn:name":"Chacoma",
    "gn:population":0,
    "gn:timezone":"America/La_Paz",
    "iso:country":"BO",
    "wof:name":"Chacoma",
    "wof:placetype":"locality"
},
  "geometry": {"coordinates":[-67.03333000000001,-17.38332999999999],"type":"Point"}
}