{
  "type": "Feature",
  "properties": {
    "gn:admin1_code":"2.0",
    "gn:asciiname":"Estancia Torreni",
    "gn:country_code":"BO",
    "gn:dem":3439,
    "gn:feature_class":"P",
    "gn:feature_code":"PPL",
    "gn:name":"Estancia Torreni",
    "gn:population":0,
    "gn:timezone":"America/La_Paz",
    "iso:country":"BO",
    "wof:name":"Estancia Torreni",
    "wof:placetype":"locality"
},
  "geometry": {"coordinates":[-66.11667,-17.01667],"type":"Point"}
}