{
  "type": "Feature",
  "properties": {
    "gn:admin1_code":"7.0",
    "gn:asciiname":"Sauta",
    "gn:country_code":"BO",
    "gn:dem":3722,
    "gn:feature_class":"P",
    "gn:feature_code":"PPL",
    "gn:name":"Sauta",
    "gn:population":0,
    "gn:timezone":"America/La_Paz",
    "iso:country":"BO",
    "name:und_x_variant":[
        "Santo",
        "Sauta"
    ],
    "wof:name":"Sauta",
    "wof:placetype":"locality"
},
  "geometry": {"coordinates":[-66.55937,-18.38257],"type":"Point"}
}