{
  "type": "Feature",
  "properties": {
    "gn:admin1_code":"1.0",
    "gn:asciiname":"Estancia Sani Mayu",
    "gn:country_code":"BO",
    "gn:dem":3358,
    "gn:feature_class":"P",
    "gn:feature_code":"PPL",
    "gn:name":"Estancia Sani Mayu",
    "gn:population":0,
    "gn:timezone":"America/La_Paz",
    "iso:country":"BO",
    "wof:name":"Estancia Sani Mayu",
    "wof:placetype":"locality"
},
  "geometry": {"coordinates":[-64.90982,-20.27081],"type":"Point"}
}