{
  "type": "Feature",
  "properties": {
    "gn:admin1_code":"05",
    "gn:asciiname":"Chuchilaya",
    "gn:cc2":"BO",
    "gn:country_code":"BO",
    "gn:dem":3832,
    "gn:feature_class":"P",
    "gn:feature_code":"PPL",
    "gn:name":"Chuchilaya",
    "gn:population":0,
    "gn:timezone":"America/La_Paz",
    "iso:country":"BO",
    "name:und_x_variant":[
        "Estancia Chuchulaya",
        "Chuchilaya"
    ],
    "wof:name":"Chuchilaya",
    "wof:placetype":"locality"
},
  "geometry": {"coordinates":[-67.51666999999999,-18.86667000000001],"type":"Point"}
}