{
  "type": "Feature",
  "properties": {
    "gn:admin1_code":"05",
    "gn:asciiname":"Challavito",
    "gn:country_code":"BO",
    "gn:dem":3723,
    "gn:feature_class":"P",
    "gn:feature_code":"PPL",
    "gn:name":"Challavito",
    "gn:population":0,
    "gn:timezone":"America/La_Paz",
    "iso:country":"BO",
    "wof:name":"Challavito",
    "wof:placetype":"locality"
},
  "geometry": {"coordinates":[-67.59768000000001,-18.02924],"type":"Point"}
}