{
  "type": "Feature",
  "properties": {
    "gn:admin1_code":"06",
    "gn:asciiname":"Estancia Villa Hermosa",
    "gn:country_code":"BO",
    "gn:dem":240,
    "gn:feature_class":"P",
    "gn:feature_code":"PPL",
    "gn:name":"Estancia Villa Hermosa",
    "gn:population":0,
    "gn:timezone":"America/La_Paz",
    "iso:country":"BO",
    "name:spa_x_preferred":[
        "Estancia Villa Hermosa"
    ],
    "wof:name":"Estancia Villa Hermosa",
    "wof:placetype":"locality"
},
  "geometry": {"coordinates":[-68.54345000000001,-11.15741],"type":"Point"}
}