{
  "type": "Feature",
  "properties": {
    "gn:admin1_code":"7.0",
    "gn:asciiname":"Paco Chico",
    "gn:country_code":"BO",
    "gn:dem":3908,
    "gn:feature_class":"P",
    "gn:feature_code":"PPL",
    "gn:name":"Paco Chico",
    "gn:population":0,
    "gn:timezone":"America/La_Paz",
    "iso:country":"BO",
    "name:und_x_variant":[
        "Estancia Paco Chico",
        "Paco Chico"
    ],
    "wof:name":"Paco Chico",
    "wof:placetype":"locality"
},
  "geometry": {"coordinates":[-65.89837,-19.51762],"type":"Point"}
}