{
  "type": "Feature",
  "properties": {
    "gn:admin1_code":"05",
    "gn:asciiname":"Coa Coani",
    "gn:country_code":"BO",
    "gn:dem":4303,
    "gn:feature_class":"P",
    "gn:feature_code":"PPL",
    "gn:name":"Coa Coani",
    "gn:population":0,
    "gn:timezone":"America/La_Paz",
    "iso:country":"BO",
    "wof:name":"Coa Coani",
    "wof:placetype":"locality"
},
  "geometry": {"coordinates":[-66.71666999999999,-18.68333],"type":"Point"}
}