{
  "type": "Feature",
  "properties": {
    "gn:admin1_code":"4.0",
    "gn:asciiname":"Uyapi",
    "gn:country_code":"BO",
    "gn:dem":1156,
    "gn:feature_class":"P",
    "gn:feature_code":"PPL",
    "gn:name":"Uyapi",
    "gn:population":0,
    "gn:timezone":"America/La_Paz",
    "iso:country":"BO",
    "wof:name":"Uyapi",
    "wof:placetype":"locality"
},
  "geometry": {"coordinates":[-67.76666999999999,-15.41667],"type":"Point"}
}