{
  "type": "Feature",
  "properties": {
    "gn:admin1_code":"06",
    "gn:asciiname":"Buen Jardin",
    "gn:country_code":"BO",
    "gn:dem":125,
    "gn:feature_class":"P",
    "gn:feature_code":"PPL",
    "gn:name":"Buen Jard\u00edn",
    "gn:population":0,
    "gn:timezone":"America/La_Paz",
    "iso:country":"BO",
    "wof:name":"Buen Jardin",
    "wof:placetype":"locality"
},
  "geometry": {"coordinates":[-66.21666999999999,-11.13333],"type":"Point"}
}