{
  "type": "Feature",
  "properties": {
    "gn:admin1_code":"5.0",
    "gn:asciiname":"Pinani",
    "gn:country_code":"BO",
    "gn:dem":3719,
    "gn:feature_class":"P",
    "gn:feature_code":"PPL",
    "gn:name":"Pi\u00f1ani",
    "gn:population":0,
    "gn:timezone":"America/La_Paz",
    "iso:country":"BO",
    "name:und_x_variant":[
        "Estancia Corpa Pi\u00f1ani",
        "Pi\u00f1ani"
    ],
    "wof:name":"Pinani",
    "wof:placetype":"locality"
},
  "geometry": {"coordinates":[-67.6173,-18.07428],"type":"Point"}
}