{
  "type": "Feature",
  "properties": {
    "gn:admin1_code":"03",
    "gn:asciiname":"Estambul West",
    "gn:country_code":"BO",
    "gn:dem":182,
    "gn:feature_class":"P",
    "gn:feature_code":"PPL",
    "gn:name":"Estambul West",
    "gn:population":0,
    "gn:timezone":"America/La_Paz",
    "iso:country":"BO",
    "wof:name":"Estambul West",
    "wof:placetype":"locality"
},
  "geometry": {"coordinates":[-66.68333,-14.66667],"type":"Point"}
}