{
  "type": "Feature",
  "properties": {
    "gn:admin1_code":"1.0",
    "gn:asciiname":"Tacapampa",
    "gn:country_code":"BO",
    "gn:dem":1939,
    "gn:feature_class":"P",
    "gn:feature_code":"PPL",
    "gn:name":"Tacapampa",
    "gn:population":0,
    "gn:timezone":"America/La_Paz",
    "iso:country":"BO",
    "wof:name":"Tacapampa",
    "wof:placetype":"locality"
},
  "geometry": {"coordinates":[-64.51666999999999,-18.95],"type":"Point"}
}