{
  "type": "Feature",
  "properties": {
    "gn:admin1_code":"07",
    "gn:asciiname":"Cerrillospampa",
    "gn:country_code":"BO",
    "gn:dem":4123,
    "gn:feature_class":"P",
    "gn:feature_code":"PPL",
    "gn:name":"Cerrillospampa",
    "gn:population":0,
    "gn:timezone":"America/La_Paz",
    "iso:country":"BO",
    "wof:name":"Cerrillospampa",
    "wof:placetype":"locality"
},
  "geometry": {"coordinates":[-66.40000000000001,-21.38333],"type":"Point"}
}