{
  "type": "Feature",
  "properties": {
    "gn:admin1_code":"06",
    "gn:asciiname":"Comunidad Tres Cruces",
    "gn:country_code":"BO",
    "gn:dem":300,
    "gn:feature_class":"P",
    "gn:feature_code":"PPL",
    "gn:name":"Comunidad Tres Cruces",
    "gn:population":0,
    "gn:timezone":"America/La_Paz",
    "iso:country":"BO",
    "wof:name":"Comunidad Tres Cruces",
    "wof:placetype":"locality"
},
  "geometry": {"coordinates":[-69.2632,-11.32149],"type":"Point"}
}