{
  "type": "Feature",
  "properties": {
    "gn:admin1_code":"02",
    "gn:asciiname":"Comunidad Toldo Mago",
    "gn:country_code":"BO",
    "gn:dem":3025,
    "gn:feature_class":"P",
    "gn:feature_code":"PPL",
    "gn:name":"Comunidad Toldo Mago",
    "gn:population":0,
    "gn:timezone":"America/La_Paz",
    "iso:country":"BO",
    "wof:name":"Comunidad Toldo Mago",
    "wof:placetype":"locality"
},
  "geometry": {"coordinates":[-66.51666999999999,-17.21667],"type":"Point"}
}