{
  "type": "Feature",
  "properties": {
    "gn:admin1_code":"05",
    "gn:asciiname":"Capuyo",
    "gn:country_code":"BO",
    "gn:dem":3753,
    "gn:feature_class":"P",
    "gn:feature_code":"PPL",
    "gn:name":"Capuyo",
    "gn:population":0,
    "gn:timezone":"America/La_Paz",
    "iso:country":"BO",
    "wof:name":"Capuyo",
    "wof:placetype":"locality"
},
  "geometry": {"coordinates":[-67.39816,-19.17592],"type":"Point"}
}