{
  "type": "Feature",
  "properties": {
    "gn:admin1_code":"9.0",
    "gn:asciiname":"La Petrolera",
    "gn:cc2":"BO",
    "gn:country_code":"BO",
    "gn:dem":456,
    "gn:feature_class":"P",
    "gn:feature_code":"PPL",
    "gn:name":"La Petrolera",
    "gn:population":0,
    "gn:timezone":"America/La_Paz",
    "iso:country":"BO",
    "name:und_x_variant":[
        "Petrolera",
        "La Petrolera"
    ],
    "wof:name":"La Petrolera",
    "wof:placetype":"locality"
},
  "geometry": {"coordinates":[-63.43333000000001,-21.95],"type":"Point"}
}