{
  "type": "Feature",
  "properties": {
    "gn:admin1_code":"7.0",
    "gn:asciiname":"Morijon",
    "gn:cc2":"BO",
    "gn:country_code":"BO",
    "gn:dem":4757,
    "gn:feature_class":"P",
    "gn:feature_code":"PPL",
    "gn:name":"Morij\u00f3n",
    "gn:population":0,
    "gn:timezone":"America/La_Paz",
    "iso:country":"BO",
    "name:und_x_variant":[
        "Mocijon",
        "Morij\u00f3n"
    ],
    "wof:name":"Morijon",
    "wof:placetype":"locality"
},
  "geometry": {"coordinates":[-67.11667,-22.05],"type":"Point"}
}