{
  "type": "Feature",
  "properties": {
    "gn:admin1_code":"5.0",
    "gn:asciiname":"Huancalli",
    "gn:country_code":"BO",
    "gn:dem":3721,
    "gn:feature_class":"P",
    "gn:feature_code":"PPL",
    "gn:name":"Huancalli",
    "gn:population":0,
    "gn:timezone":"America/La_Paz",
    "iso:country":"BO",
    "name:und_x_variant":[
        "Estancia Huancalle",
        "Huanalla",
        "Huancalli"
    ],
    "wof:name":"Huancalli",
    "wof:placetype":"locality"
},
  "geometry": {"coordinates":[-68.38880999999999,-19.03286],"type":"Point"}
}