{
  "type": "Feature",
  "properties": {
    "gn:admin1_code":"05",
    "gn:asciiname":"Estancia Caparchi",
    "gn:country_code":"BO",
    "gn:dem":3668,
    "gn:feature_class":"P",
    "gn:feature_code":"PPL",
    "gn:name":"Estancia Caparchi",
    "gn:population":0,
    "gn:timezone":"America/La_Paz",
    "iso:country":"BO",
    "wof:name":"Estancia Caparchi",
    "wof:placetype":"locality"
},
  "geometry": {"coordinates":[-68.08179,-19.11991],"type":"Point"}
}