{
  "type": "Feature",
  "properties": {
    "gn:admin1_code":"06",
    "gn:asciiname":"Cachari",
    "gn:country_code":"BO",
    "gn:dem":144,
    "gn:feature_class":"P",
    "gn:feature_code":"PPL",
    "gn:name":"Cachari",
    "gn:population":0,
    "gn:timezone":"America/La_Paz",
    "iso:country":"BO",
    "wof:name":"Cachari",
    "wof:placetype":"locality"
},
  "geometry": {"coordinates":[-66.15000000000001,-10.63333],"type":"Point"}
}