{
  "type": "Feature",
  "properties": {
    "gn:admin1_code":"04",
    "gn:asciiname":"Apama",
    "gn:cc2":"BO",
    "gn:country_code":"BO",
    "gn:dem":1367,
    "gn:feature_class":"P",
    "gn:feature_code":"PPL",
    "gn:name":"Apama",
    "gn:population":0,
    "gn:timezone":"America/La_Paz",
    "iso:country":"BO",
    "name:azb_x_preferred":[
        "\u0622\u067e\u0627\u0645\u0627"
    ],
    "name:bul_x_preferred":[
        "\u0410\u043f\u0430\u043c\u0430"
    ],
    "name:cat_x_preferred":[
        "Apama"
    ],
    "name:deu_x_preferred":[
        "Apame"
    ],
    "name:ell_x_preferred":[
        "\u0391\u03c0\u03ac\u03bc\u03b1"
    ],
    "name:fas_x_preferred":[
        "\u0622\u067e\u0627\u0645\u0627"
    ],
    "name:fin_x_preferred":[
        "Apama"
    ],
    "name:ind_x_preferred":[
        "Apama"
    ],
    "name:ita_x_preferred":[
        "Apama"
    ],
    "name:jpn_x_preferred":[
        "\u30a2\u30d1\u30e1\u30fc"
    ],
    "name:nld_x_preferred":[
        "Apame"
    ],
    "name:nor_x_preferred":[
        "Apama"
    ],
    "name:pol_x_preferred":[
        "Apame"
    ],
    "name:rus_x_preferred":[
        "\u0410\u043f\u0430\u043c\u0430"
    ],
    "name:spa_x_preferred":[
        "Apama"
    ],
    "name:tur_x_preferred":[
        "Epeme"
    ],
    "name:ukr_x_preferred":[
        "\u0410\u043f\u0430\u043c\u0430"
    ],
    "name:und_x_variant":[
        "Apana",
        "Agana"
    ],
    "name:zho_x_preferred":[
        "\u963f\u5e15\u746a"
    ],
    "wof:name":"Apama",
    "wof:placetype":"locality"
},
  "geometry": {"coordinates":[-67.91667,-15.93333],"type":"Point"}
}