{
  "type": "Feature",
  "properties": {
    "gn:admin1_code":"04",
    "gn:asciiname":"Apama",
    "gn:cc2":"BO",
    "gn:country_code":"BO",
    "gn:dem":1367,
    "gn:feature_class":"P",
    "gn:feature_code":"PPL",
    "gn:name":"Apama",
    "gn:population":0,
    "gn:timezone":"America/La_Paz",
    "iso:country":"BO",
    "name:und_x_variant":[
        "Apana",
        "Agana",
        "Apama"
    ],
    "wof:name":"Apama",
    "wof:placetype":"locality"
},
  "geometry": {"coordinates":[-67.91667,-15.93333],"type":"Point"}
}