{
  "type": "Feature",
  "properties": {
    "gn:admin1_code":"6.0",
    "gn:asciiname":"Nazaret",
    "gn:cc2":"BO",
    "gn:country_code":"BO",
    "gn:dem":152,
    "gn:feature_class":"P",
    "gn:feature_code":"PPL",
    "gn:name":"Nazaret",
    "gn:population":0,
    "gn:timezone":"America/La_Paz",
    "iso:country":"BO",
    "name:und_x_variant":[
        "Nazareth",
        "Nazareht",
        "Nazaret"
    ],
    "wof:name":"Nazaret",
    "wof:placetype":"locality"
},
  "geometry": {"coordinates":[-65.91667,-10.41667],"type":"Point"}
}