{
  "type": "Feature",
  "properties": {
    "gn:admin1_code":"04",
    "gn:asciiname":"Cutusuma",
    "gn:cc2":"BO",
    "gn:country_code":"BO",
    "gn:dem":3815,
    "gn:feature_class":"P",
    "gn:feature_code":"PPL",
    "gn:name":"Cutusuma",
    "gn:population":0,
    "gn:timezone":"America/La_Paz",
    "iso:country":"BO",
    "name:ceb_x_preferred":[
        "Cutusuma"
    ],
    "name:deu_x_preferred":[
        "Cutusuma"
    ],
    "name:swe_x_preferred":[
        "Cutusuma"
    ],
    "name:und_x_variant":[
        "Cutusani"
    ],
    "wof:name":"Cutusuma",
    "wof:placetype":"locality"
},
  "geometry": {"coordinates":[-68.61667,-16.28333],"type":"Point"}
}