{
  "type": "Feature",
  "properties": {
    "gn:admin1_code":"9.0",
    "gn:asciiname":"Teyu",
    "gn:cc2":"BO",
    "gn:country_code":"BO",
    "gn:dem":302,
    "gn:feature_class":"P",
    "gn:feature_code":"PPL",
    "gn:name":"Teyu",
    "gn:population":0,
    "gn:timezone":"America/La_Paz",
    "iso:country":"BO",
    "name:und_x_variant":[
        "El Teyu",
        "Teyo",
        "Teyu"
    ],
    "wof:name":"Teyu",
    "wof:placetype":"locality"
},
  "geometry": {"coordinates":[-62.88333000000001,-21.81667],"type":"Point"}
}