{
  "type": "Feature",
  "properties": {
    "gn:admin1_code":"08",
    "gn:asciiname":"Empedrado",
    "gn:country_code":"BO",
    "gn:dem":243,
    "gn:feature_class":"P",
    "gn:feature_code":"PPL",
    "gn:name":"Empedrado",
    "gn:population":0,
    "gn:timezone":"America/La_Paz",
    "iso:country":"BO",
    "wof:name":"Empedrado",
    "wof:placetype":"locality"
},
  "geometry": {"coordinates":[-61.81667,-14.31667],"type":"Point"}
}