{
  "type": "Feature",
  "properties": {
    "gn:admin1_code":"8.0",
    "gn:asciiname":"Chalot",
    "gn:cc2":"BO",
    "gn:country_code":"BO",
    "gn:dem":95,
    "gn:feature_class":"P",
    "gn:feature_code":"PPL",
    "gn:name":"Chalot",
    "gn:population":0,
    "gn:timezone":"America/La_Paz",
    "iso:country":"BO",
    "name:und_x_variant":[
        "Chalota",
        "Chalot"
    ],
    "wof:name":"Chalot",
    "wof:placetype":"locality"
},
  "geometry": {"coordinates":[-58.05,-18.95],"type":"Point"}
}