{
  "type": "Feature",
  "properties": {
    "gn:admin1_code":"7.0",
    "gn:asciiname":"Ventilla",
    "gn:cc2":"BO",
    "gn:country_code":"BO",
    "gn:dem":3677,
    "gn:feature_class":"P",
    "gn:feature_code":"PPL",
    "gn:name":"Ventilla",
    "gn:population":0,
    "gn:timezone":"America/La_Paz",
    "iso:country":"BO",
    "name:und_x_variant":[
        "Casas",
        "Ventilla"
    ],
    "wof:name":"Ventilla",
    "wof:placetype":"locality"
},
  "geometry": {"coordinates":[-66.36667,-18.08333],"type":"Point"}
}