{
  "type": "Feature",
  "properties": {
    "gn:admin1_code":"7.0",
    "gn:asciiname":"Khonas",
    "gn:country_code":"BO",
    "gn:dem":3891,
    "gn:feature_class":"P",
    "gn:feature_code":"PPL",
    "gn:name":"Khonas",
    "gn:population":0,
    "gn:timezone":"America/La_Paz",
    "iso:country":"BO",
    "wof:name":"Khonas",
    "wof:placetype":"locality"
},
  "geometry": {"coordinates":[-67.36825,-21.48388],"type":"Point"}
}