{
  "type": "Feature",
  "properties": {
    "gn:admin1_code":"08",
    "gn:asciiname":"Carmen Viejo",
    "gn:country_code":"BO",
    "gn:dem":229,
    "gn:feature_class":"P",
    "gn:feature_code":"PPL",
    "gn:name":"Carmen Viejo",
    "gn:population":0,
    "gn:timezone":"America/La_Paz",
    "iso:country":"BO",
    "wof:name":"Carmen Viejo",
    "wof:placetype":"locality"
},
  "geometry": {"coordinates":[-63.48333,-14.66667],"type":"Point"}
}