{
  "type": "Feature",
  "properties": {
    "gn:admin1_code":"4.0",
    "gn:asciiname":"Futuro",
    "gn:cc2":"BO",
    "gn:country_code":"BO",
    "gn:dem":937,
    "gn:feature_class":"P",
    "gn:feature_code":"PPL",
    "gn:name":"Futuro",
    "gn:population":0,
    "gn:timezone":"America/La_Paz",
    "iso:country":"BO",
    "name:und_x_variant":[
        "Buturo",
        "Buturu",
        "Futuro"
    ],
    "wof:name":"Futuro",
    "wof:placetype":"locality"
},
  "geometry": {"coordinates":[-68.56667,-14.28333],"type":"Point"}
}