{
  "type": "Feature",
  "properties": {
    "gn:admin1_code":"4.0",
    "gn:asciiname":"Futuro",
    "gn:cc2":"BO",
    "gn:country_code":"BO",
    "gn:dem":937,
    "gn:feature_class":"P",
    "gn:feature_code":"PPL",
    "gn:name":"Futuro",
    "gn:population":0,
    "gn:timezone":"America/La_Paz",
    "iso:country":"BO",
    "name:ara_x_preferred":[
        "\u0645\u0646\u0632\u0644 \u0627\u0644\u0645\u0633\u062a\u0642\u0628\u0644"
    ],
    "name:deu_x_preferred":[
        "Futuro"
    ],
    "name:fin_x_preferred":[
        "Futuro"
    ],
    "name:fra_x_preferred":[
        "Futuro"
    ],
    "name:nld_x_preferred":[
        "Futuro"
    ],
    "name:swe_x_preferred":[
        "Futuro"
    ],
    "name:und_x_variant":[
        "Buturo",
        "Buturu"
    ],
    "name:vie_x_preferred":[
        "Futuro"
    ],
    "wof:name":"Futuro",
    "wof:placetype":"locality"
},
  "geometry": {"coordinates":[-68.56667,-14.28333],"type":"Point"}
}