{
  "type": "Feature",
  "properties": {
    "gn:admin1_code":"1.0",
    "gn:asciiname":"Estancia Quilchavoj",
    "gn:country_code":"BO",
    "gn:dem":3774,
    "gn:feature_class":"P",
    "gn:feature_code":"PPL",
    "gn:name":"Estancia Quilchavoj",
    "gn:population":0,
    "gn:timezone":"America/La_Paz",
    "iso:country":"BO",
    "wof:name":"Estancia Quilchavoj",
    "wof:placetype":"locality"
},
  "geometry": {"coordinates":[-64.76994000000001,-19.99664],"type":"Point"}
}