{
  "type": "Feature",
  "properties": {
    "gn:admin1_code":"02",
    "gn:asciiname":"Castellon",
    "gn:country_code":"BO",
    "gn:dem":208,
    "gn:feature_class":"P",
    "gn:feature_code":"PPL",
    "gn:name":"Castell\u00f3n",
    "gn:population":0,
    "gn:timezone":"America/La_Paz",
    "iso:country":"BO",
    "wof:name":"Castellon",
    "wof:placetype":"locality"
},
  "geometry": {"coordinates":[-65.28333000000001,-16.55],"type":"Point"}
}