{
  "type": "Feature",
  "properties": {
    "gn:admin1_code":"04",
    "gn:asciiname":"Castilloma",
    "gn:country_code":"BO",
    "gn:dem":4095,
    "gn:feature_class":"P",
    "gn:feature_code":"PPL",
    "gn:name":"Castilloma",
    "gn:population":0,
    "gn:timezone":"America/La_Paz",
    "iso:country":"BO",
    "wof:name":"Castilloma",
    "wof:placetype":"locality"
},
  "geometry": {"coordinates":[-68.01666999999999,-16.81667],"type":"Point"}
}