{
  "type": "Feature",
  "properties": {
    "gn:admin1_code":"06",
    "gn:asciiname":"Manuripal",
    "gn:country_code":"BO",
    "gn:dem":181,
    "gn:feature_class":"P",
    "gn:feature_code":"PPL",
    "gn:name":"Manuripal",
    "gn:population":0,
    "gn:timezone":"America/La_Paz",
    "iso:country":"BO",
    "name:spa_x_preferred":[
        "Manuripal"
    ],
    "name:spa_x_variant":[
        "Manuripi"
    ],
    "wof:name":"Manuripal",
    "wof:placetype":"locality"
},
  "geometry": {"coordinates":[-67.52304000000001,-11.16054],"type":"Point"}
}