{
  "type": "Feature",
  "properties": {
    "gn:admin1_code":"1.0",
    "gn:admin2_code":"104.0",
    "gn:admin3_code":"2.0",
    "gn:admin4_code":"1.0",
    "gn:asciiname":"Tomina",
    "gn:country_code":"BO",
    "gn:dem":2663,
    "gn:feature_class":"P",
    "gn:feature_code":"PPLA4",
    "gn:name":"Tomina",
    "gn:population":0,
    "gn:timezone":"America/La_Paz",
    "iso:country":"BO",
    "name:ceb_x_preferred":[
        "Tomina"
    ],
    "name:deu_x_preferred":[
        "Tomina"
    ],
    "wof:name":"Tomina",
    "wof:placetype":"locality"
},
  "geometry": {"coordinates":[-64.53333000000001,-19.18333],"type":"Point"}
}