{
  "type": "Feature",
  "properties": {
    "gn:admin1_code":"7.0",
    "gn:asciiname":"Taruta",
    "gn:country_code":"BO",
    "gn:dem":3591,
    "gn:feature_class":"P",
    "gn:feature_code":"PPL",
    "gn:name":"Taruta",
    "gn:population":0,
    "gn:timezone":"America/La_Paz",
    "iso:country":"BO",
    "wof:name":"Taruta",
    "wof:placetype":"locality"
},
  "geometry": {"coordinates":[-66.18333,-20.03333],"type":"Point"}
}