{
  "type": "Feature",
  "properties": {
    "gn:admin1_code":"4.0",
    "gn:asciiname":"Mariara",
    "gn:cc2":"BO",
    "gn:country_code":"BO",
    "gn:dem":399,
    "gn:feature_class":"P",
    "gn:feature_code":"PPL",
    "gn:name":"Mariara",
    "gn:population":0,
    "gn:timezone":"America/La_Paz",
    "iso:country":"BO",
    "name:ceb_x_preferred":[
        "Mariara"
    ],
    "name:deu_x_preferred":[
        "Mariara"
    ],
    "name:epo_x_preferred":[
        "Mariara"
    ],
    "name:fra_x_preferred":[
        "Mariara"
    ],
    "name:ita_x_preferred":[
        "Mariara"
    ],
    "name:kat_x_preferred":[
        "\u10db\u10d0\u10e0\u10d8\u10d0\u10e0\u10d0"
    ],
    "name:pol_x_preferred":[
        "Mariara"
    ],
    "name:por_x_preferred":[
        "Mariara"
    ],
    "name:spa_x_preferred":[
        "Mariara"
    ],
    "name:swe_x_preferred":[
        "Mariara"
    ],
    "name:und_x_variant":[
        "Meriapu",
        "Mariapo",
        "Maraiaro",
        "Mariara"
    ],
    "name:vol_x_preferred":[
        "Mariara"
    ],
    "name:zho_x_preferred":[
        "\u99ac\u91cc\u4e9e\u62c9"
    ],
    "wof:name":"Mariara",
    "wof:placetype":"locality"
},
  "geometry": {"coordinates":[-67.73333000000001,-15.23333],"type":"Point"}
}