{
  "type": "Feature",
  "properties": {
    "gn:admin1_code":"4.0",
    "gn:asciiname":"Mariara",
    "gn:cc2":"BO",
    "gn:country_code":"BO",
    "gn:dem":399,
    "gn:feature_class":"P",
    "gn:feature_code":"PPL",
    "gn:name":"Mariara",
    "gn:population":0,
    "gn:timezone":"America/La_Paz",
    "iso:country":"BO",
    "name:und_x_variant":[
        "Meriapu",
        "Mariapo",
        "Maraiaro",
        "Mariara"
    ],
    "wof:name":"Mariara",
    "wof:placetype":"locality"
},
  "geometry": {"coordinates":[-67.73333000000001,-15.23333],"type":"Point"}
}