{
  "type": "Feature",
  "properties": {
    "gn:admin1_code":"01",
    "gn:asciiname":"Barbechos",
    "gn:country_code":"BO",
    "gn:dem":2637,
    "gn:feature_class":"P",
    "gn:feature_code":"PPL",
    "gn:name":"Barbechos",
    "gn:population":0,
    "gn:timezone":"America/La_Paz",
    "iso:country":"BO",
    "wof:name":"Barbechos",
    "wof:placetype":"locality"
},
  "geometry": {"coordinates":[-64.61667,-19.91667],"type":"Point"}
}