{
  "type": "Feature",
  "properties": {
    "gn:admin1_code":"05",
    "gn:asciiname":"Estancia Khalasaya",
    "gn:country_code":"BO",
    "gn:dem":3760,
    "gn:feature_class":"P",
    "gn:feature_code":"PPL",
    "gn:name":"Estancia Khalasaya",
    "gn:population":0,
    "gn:timezone":"America/La_Paz",
    "iso:country":"BO",
    "wof:name":"Estancia Khalasaya",
    "wof:placetype":"locality"
},
  "geometry": {"coordinates":[-68.38894999999999,-18.60382],"type":"Point"}
}