{
  "type": "Feature",
  "properties": {
    "gn:admin1_code":"4.0",
    "gn:asciiname":"Jaque",
    "gn:country_code":"BO",
    "gn:dem":3944,
    "gn:feature_class":"P",
    "gn:feature_code":"PPL",
    "gn:name":"Jaque",
    "gn:population":0,
    "gn:timezone":"America/La_Paz",
    "iso:country":"BO",
    "name:bre_x_preferred":[
        "Jaque"
    ],
    "name:cat_x_preferred":[
        "Jaque"
    ],
    "name:spa_x_preferred":[
        "Jaque"
    ],
    "wof:name":"Jaque",
    "wof:placetype":"locality"
},
  "geometry": {"coordinates":[-68.18333,-16.86667000000001],"type":"Point"}
}