{
  "type": "Feature",
  "properties": {
    "gn:admin1_code":"2.0",
    "gn:asciiname":"Lopez Mendoza",
    "gn:country_code":"BO",
    "gn:dem":3201,
    "gn:feature_class":"P",
    "gn:feature_code":"PPL",
    "gn:name":"Lopez Mendoza",
    "gn:population":0,
    "gn:timezone":"America/La_Paz",
    "iso:country":"BO",
    "wof:name":"Lopez Mendoza",
    "wof:placetype":"locality"
},
  "geometry": {"coordinates":[-65.36667,-17.55],"type":"Point"}
}