{
  "type": "Feature",
  "properties": {
    "gn:admin1_code":"09",
    "gn:asciiname":"Canadas",
    "gn:country_code":"BO",
    "gn:dem":945,
    "gn:feature_class":"P",
    "gn:feature_code":"PPL",
    "gn:name":"Ca\u00f1adas",
    "gn:population":0,
    "gn:timezone":"America/La_Paz",
    "iso:country":"BO",
    "wof:name":"Canadas",
    "wof:placetype":"locality"
},
  "geometry": {"coordinates":[-63.97252,-21.42151],"type":"Point"}
}