{
  "type": "Feature",
  "properties": {
    "gn:admin1_code":"08",
    "gn:asciiname":"San Antonio del Parapeti",
    "gn:country_code":"BO",
    "gn:dem":634,
    "gn:feature_class":"P",
    "gn:feature_code":"PPL",
    "gn:name":"San Antonio del Parapet\u00ed",
    "gn:population":0,
    "gn:timezone":"America/La_Paz",
    "iso:country":"BO",
    "wof:name":"San Antonio del Parapeti",
    "wof:placetype":"locality"
},
  "geometry": {"coordinates":[-63.17565,-19.99623],"type":"Point"}
}